Workbook

Sheet Overblik_32441483
A1: Hatting A/S (CVR 32441483) — Regnskabsanalyse – Resultatopgørelse & Balance (t.kr.) · Klasse C-mellem · Revision
H2: Indekstal (2021=100)
A3: Resultatopgørelse t.kr. | B3: 2021 | C3: 2022 | D3: 2023 | E3: 2024 | F3: 2025 | H3: 2021 | I3: 2022 | J3: 2023 | K3: 2024 | L3: 2025
A4: Nettoomsætning | B4: ='res_raw_32441483'!$B$2 | C4: ='res_raw_32441483'!$C$2 | D4: ='res_raw_32441483'!$D$2 | E4: ='res_raw_32441483'!$E$2 | F4: ='res_raw_32441483'!$F$2 | H4: =IFERROR(B4/$B$4*100,"") | I4: =IFERROR(C4/$B$4*100,"") | J4: =IFERROR(D4/$B$4*100,"") | K4: =IFERROR(E4/$B$4*100,"") | L4: =IFERROR(F4/$B$4*100,"")
A5: Produktionsomkostninger | B5: ='res_raw_32441483'!$B$3 | C5: ='res_raw_32441483'!$C$3 | D5: ='res_raw_32441483'!$D$3 | E5: ='res_raw_32441483'!$E$3 | F5: ='res_raw_32441483'!$F$3 | H5: =IFERROR(B5/$B$5*100,"") | I5: =IFERROR(C5/$B$5*100,"") | J5: =IFERROR(D5/$B$5*100,"") | K5: =IFERROR(E5/$B$5*100,"") | L5: =IFERROR(F5/$B$5*100,"")
A6: Bruttoresultat | B6: ='res_raw_32441483'!$B$4 | C6: ='res_raw_32441483'!$C$4 | D6: ='res_raw_32441483'!$D$4 | E6: ='res_raw_32441483'!$E$4 | F6: ='res_raw_32441483'!$F$4 | H6: =IFERROR(B6/$B$6*100,"") | I6: =IFERROR(C6/$B$6*100,"") | J6: =IFERROR(D6/$B$6*100,"") | K6: =IFERROR(E6/$B$6*100,"") | L6: =IFERROR(F6/$B$6*100,"")
A7: Salgs- og distributionsomkostninger | B7: ='res_raw_32441483'!$B$5 | C7: ='res_raw_32441483'!$C$5 | D7: ='res_raw_32441483'!$D$5 | E7: ='res_raw_32441483'!$E$5 | F7: ='res_raw_32441483'!$F$5 | H7: =IFERROR(B7/$B$7*100,"") | I7: =IFERROR(C7/$B$7*100,"") | J7: =IFERROR(D7/$B$7*100,"") | K7: =IFERROR(E7/$B$7*100,"") | L7: =IFERROR(F7/$B$7*100,"")
A8: Administrationsomkostninger | B8: ='res_raw_32441483'!$B$6 | C8: ='res_raw_32441483'!$C$6 | D8: ='res_raw_32441483'!$D$6 | E8: ='res_raw_32441483'!$E$6 | F8: ='res_raw_32441483'!$F$6 | H8: =IFERROR(B8/$B$8*100,"") | I8: =IFERROR(C8/$B$8*100,"") | J8: =IFERROR(D8/$B$8*100,"") | K8: =IFERROR(E8/$B$8*100,"") | L8: =IFERROR(F8/$B$8*100,"")
A9: Andre driftsindtægter | B9: ='res_raw_32441483'!$B$7 | C9: ='res_raw_32441483'!$C$7 | D9: ='res_raw_32441483'!$D$7 | E9: ='res_raw_32441483'!$E$7 | F9: ='res_raw_32441483'!$F$7 | H9: =IFERROR(B9/$B$9*100,"") | I9: =IFERROR(C9/$B$9*100,"") | J9: =IFERROR(D9/$B$9*100,"") | K9: =IFERROR(E9/$B$9*100,"") | L9: =IFERROR(F9/$B$9*100,"")
A10: Andre driftsomkostninger | B10: ='res_raw_32441483'!$B$8 | C10: ='res_raw_32441483'!$C$8 | D10: ='res_raw_32441483'!$D$8 | E10: ='res_raw_32441483'!$E$8 | F10: ='res_raw_32441483'!$F$8 | H10: =IFERROR(B10/$B$10*100,"") | I10: =IFERROR(C10/$B$10*100,"") | J10: =IFERROR(D10/$B$10*100,"") | K10: =IFERROR(E10/$B$10*100,"") | L10: =IFERROR(F10/$B$10*100,"")
A11: Resultat af primær drift | B11: ='res_raw_32441483'!$B$9 | C11: ='res_raw_32441483'!$C$9 | D11: ='res_raw_32441483'!$D$9 | E11: ='res_raw_32441483'!$E$9 | F11: ='res_raw_32441483'!$F$9 | H11: =IFERROR(B11/$B$11*100,"") | I11: =IFERROR(C11/$B$11*100,"") | J11: =IFERROR(D11/$B$11*100,"") | K11: =IFERROR(E11/$B$11*100,"") | L11: =IFERROR(F11/$B$11*100,"")
A12: Indtægter af kapitalandele, dattervirksomheder | B12: ='res_raw_32441483'!$B$10 | C12: ='res_raw_32441483'!$C$10 | D12: ='res_raw_32441483'!$D$10 | E12: ='res_raw_32441483'!$E$10 | F12: ='res_raw_32441483'!$F$10 | H12: =IFERROR(B12/$B$12*100,"") | I12: =IFERROR(C12/$B$12*100,"") | J12: =IFERROR(D12/$B$12*100,"") | K12: =IFERROR(E12/$B$12*100,"") | L12: =IFERROR(F12/$B$12*100,"")
A13: Finansielle indtægter | B13: ='res_raw_32441483'!$B$11 | C13: ='res_raw_32441483'!$C$11 | D13: ='res_raw_32441483'!$D$11 | E13: ='res_raw_32441483'!$E$11 | F13: ='res_raw_32441483'!$F$11 | H13: =IFERROR(B13/$B$13*100,"") | I13: =IFERROR(C13/$B$13*100,"") | J13: =IFERROR(D13/$B$13*100,"") | K13: =IFERROR(E13/$B$13*100,"") | L13: =IFERROR(F13/$B$13*100,"")
A14: Finansielle omkostninger | B14: ='res_raw_32441483'!$B$12 | C14: ='res_raw_32441483'!$C$12 | D14: ='res_raw_32441483'!$D$12 | E14: ='res_raw_32441483'!$E$12 | F14: ='res_raw_32441483'!$F$12 | H14: =IFERROR(B14/$B$14*100,"") | I14: =IFERROR(C14/$B$14*100,"") | J14: =IFERROR(D14/$B$14*100,"") | K14: =IFERROR(E14/$B$14*100,"") | L14: =IFERROR(F14/$B$14*100,"")
A15: Finansielle poster, netto | B15: ='res_raw_32441483'!$B$13 | C15: ='res_raw_32441483'!$C$13 | D15: ='res_raw_32441483'!$D$13 | E15: ='res_raw_32441483'!$E$13 | F15: ='res_raw_32441483'!$F$13 | H15: =IFERROR(B15/$B$15*100,"") | I15: =IFERROR(C15/$B$15*100,"") | J15: =IFERROR(D15/$B$15*100,"") | K15: =IFERROR(E15/$B$15*100,"") | L15: =IFERROR(F15/$B$15*100,"")
A16: Resultat før skat | B16: ='res_raw_32441483'!$B$14 | C16: ='res_raw_32441483'!$C$14 | D16: ='res_raw_32441483'!$D$14 | E16: ='res_raw_32441483'!$E$14 | F16: ='res_raw_32441483'!$F$14 | H16: =IFERROR(B16/$B$16*100,"") | I16: =IFERROR(C16/$B$16*100,"") | J16: =IFERROR(D16/$B$16*100,"") | K16: =IFERROR(E16/$B$16*100,"") | L16: =IFERROR(F16/$B$16*100,"")
A17: Skat af årets resultat | B17: ='res_raw_32441483'!$B$15 | C17: ='res_raw_32441483'!$C$15 | D17: ='res_raw_32441483'!$D$15 | E17: ='res_raw_32441483'!$E$15 | F17: ='res_raw_32441483'!$F$15 | H17: =IFERROR(B17/$B$17*100,"") | I17: =IFERROR(C17/$B$17*100,"") | J17: =IFERROR(D17/$B$17*100,"") | K17: =IFERROR(E17/$B$17*100,"") | L17: =IFERROR(F17/$B$17*100,"")
A18: Årets resultat | B18: ='res_raw_32441483'!$B$16 | C18: ='res_raw_32441483'!$C$16 | D18: ='res_raw_32441483'!$D$16 | E18: ='res_raw_32441483'!$E$16 | F18: ='res_raw_32441483'!$F$16 | H18: =IFERROR(B18/$B$18*100,"") | I18: =IFERROR(C18/$B$18*100,"") | J18: =IFERROR(D18/$B$18*100,"") | K18: =IFERROR(E18/$B$18*100,"") | L18: =IFERROR(F18/$B$18*100,"")
A20: AKTIVER t.kr. | B20: 2021 | C20: 2022 | D20: 2023 | E20: 2024 | F20: 2025 | H20: 2021 | I20: 2022 | J20: 2023 | K20: 2024 | L20: 2025
A21: Udviklingsprojekter | B21: ='balance_raw_32441483'!$B$2 | C21: ='balance_raw_32441483'!$C$2 | D21: ='balance_raw_32441483'!$D$2 | E21: ='balance_raw_32441483'!$E$2 | F21: ='balance_raw_32441483'!$F$2 | H21: =IFERROR(B21/$B$21*100,"") | I21: =IFERROR(C21/$B$21*100,"") | J21: =IFERROR(D21/$B$21*100,"") | K21: =IFERROR(E21/$B$21*100,"") | L21: =IFERROR(F21/$B$21*100,"")
A22: Patenter, varemærker mv. | B22: ='balance_raw_32441483'!$B$3 | C22: ='balance_raw_32441483'!$C$3 | D22: ='balance_raw_32441483'!$D$3 | E22: ='balance_raw_32441483'!$E$3 | F22: ='balance_raw_32441483'!$F$3 | H22: =IFERROR(B22/$B$22*100,"") | I22: =IFERROR(C22/$B$22*100,"") | J22: =IFERROR(D22/$B$22*100,"") | K22: =IFERROR(E22/$B$22*100,"") | L22: =IFERROR(F22/$B$22*100,"")
A23: Goodwill | B23: ='balance_raw_32441483'!$B$4 | C23: ='balance_raw_32441483'!$C$4 | D23: ='balance_raw_32441483'!$D$4 | E23: ='balance_raw_32441483'!$E$4 | F23: ='balance_raw_32441483'!$F$4 | H23: =IFERROR(B23/$B$23*100,"") | I23: =IFERROR(C23/$B$23*100,"") | J23: =IFERROR(D23/$B$23*100,"") | K23: =IFERROR(E23/$B$23*100,"") | L23: =IFERROR(F23/$B$23*100,"")
A24: Immaterielle anlægsaktiver | B24: ='balance_raw_32441483'!$B$5 | C24: ='balance_raw_32441483'!$C$5 | D24: ='balance_raw_32441483'!$D$5 | E24: ='balance_raw_32441483'!$E$5 | F24: ='balance_raw_32441483'!$F$5 | H24: =IFERROR(B24/$B$24*100,"") | I24: =IFERROR(C24/$B$24*100,"") | J24: =IFERROR(D24/$B$24*100,"") | K24: =IFERROR(E24/$B$24*100,"") | L24: =IFERROR(F24/$B$24*100,"")
A25: Grunde og bygninger | B25: ='balance_raw_32441483'!$B$6 | C25: ='balance_raw_32441483'!$C$6 | D25: ='balance_raw_32441483'!$D$6 | E25: ='balance_raw_32441483'!$E$6 | F25: ='balance_raw_32441483'!$F$6 | H25: =IFERROR(B25/$B$25*100,"") | I25: =IFERROR(C25/$B$25*100,"") | J25: =IFERROR(D25/$B$25*100,"") | K25: =IFERROR(E25/$B$25*100,"") | L25: =IFERROR(F25/$B$25*100,"")
A26: Produktionsanlæg og maskiner | B26: ='balance_raw_32441483'!$B$7 | C26: ='balance_raw_32441483'!$C$7 | D26: ='balance_raw_32441483'!$D$7 | E26: ='balance_raw_32441483'!$E$7 | F26: ='balance_raw_32441483'!$F$7 | H26: =IFERROR(B26/$B$26*100,"") | I26: =IFERROR(C26/$B$26*100,"") | J26: =IFERROR(D26/$B$26*100,"") | K26: =IFERROR(E26/$B$26*100,"") | L26: =IFERROR(F26/$B$26*100,"")
A27: Driftsmateriel og inventar | B27: ='balance_raw_32441483'!$B$8 | C27: ='balance_raw_32441483'!$C$8 | D27: ='balance_raw_32441483'!$D$8 | E27: ='balance_raw_32441483'!$E$8 | F27: ='balance_raw_32441483'!$F$8 | H27: =IFERROR(B27/$B$27*100,"") | I27: =IFERROR(C27/$B$27*100,"") | J27: =IFERROR(D27/$B$27*100,"") | K27: =IFERROR(E27/$B$27*100,"") | L27: =IFERROR(F27/$B$27*100,"")
A28: Indretning af lejede lokaler | B28: ='balance_raw_32441483'!$B$9 | C28: ='balance_raw_32441483'!$C$9 | D28: ='balance_raw_32441483'!$D$9 | E28: ='balance_raw_32441483'!$E$9 | F28: ='balance_raw_32441483'!$F$9 | H28: =IFERROR(B28/$B$28*100,"") | I28: =IFERROR(C28/$B$28*100,"") | J28: =IFERROR(D28/$B$28*100,"") | K28: =IFERROR(E28/$B$28*100,"") | L28: =IFERROR(F28/$B$28*100,"")
A29: Forudbetaling og anlægsaktiver under opførelse | B29: ='balance_raw_32441483'!$B$10 | C29: ='balance_raw_32441483'!$C$10 | D29: ='balance_raw_32441483'!$D$10 | E29: ='balance_raw_32441483'!$E$10 | F29: ='balance_raw_32441483'!$F$10 | H29: =IFERROR(B29/$B$29*100,"") | I29: =IFERROR(C29/$B$29*100,"") | J29: =IFERROR(D29/$B$29*100,"") | K29: =IFERROR(E29/$B$29*100,"") | L29: =IFERROR(F29/$B$29*100,"")
A30: Materielle anlægsaktiver | B30: ='balance_raw_32441483'!$B$11 | C30: ='balance_raw_32441483'!$C$11 | D30: ='balance_raw_32441483'!$D$11 | E30: ='balance_raw_32441483'!$E$11 | F30: ='balance_raw_32441483'!$F$11 | H30: =IFERROR(B30/$B$30*100,"") | I30: =IFERROR(C30/$B$30*100,"") | J30: =IFERROR(D30/$B$30*100,"") | K30: =IFERROR(E30/$B$30*100,"") | L30: =IFERROR(F30/$B$30*100,"")
A31: Kapitalandele, dattervirksomheder | B31: ='balance_raw_32441483'!$B$12 | C31: ='balance_raw_32441483'!$C$12 | D31: ='balance_raw_32441483'!$D$12 | E31: ='balance_raw_32441483'!$E$12 | F31: ='balance_raw_32441483'!$F$12 | H31: =IFERROR(B31/$B$31*100,"") | I31: =IFERROR(C31/$B$31*100,"") | J31: =IFERROR(D31/$B$31*100,"") | K31: =IFERROR(E31/$B$31*100,"") | L31: =IFERROR(F31/$B$31*100,"")
A32: Deposita | B32: ='balance_raw_32441483'!$B$13 | C32: ='balance_raw_32441483'!$C$13 | D32: ='balance_raw_32441483'!$D$13 | E32: ='balance_raw_32441483'!$E$13 | F32: ='balance_raw_32441483'!$F$13 | H32: =IFERROR(B32/$B$32*100,"") | I32: =IFERROR(C32/$B$32*100,"") | J32: =IFERROR(D32/$B$32*100,"") | K32: =IFERROR(E32/$B$32*100,"") | L32: =IFERROR(F32/$B$32*100,"")
A33: Finansielle anlægsaktiver | B33: ='balance_raw_32441483'!$B$14 | C33: ='balance_raw_32441483'!$C$14 | D33: ='balance_raw_32441483'!$D$14 | E33: ='balance_raw_32441483'!$E$14 | F33: ='balance_raw_32441483'!$F$14 | H33: =IFERROR(B33/$B$33*100,"") | I33: =IFERROR(C33/$B$33*100,"") | J33: =IFERROR(D33/$B$33*100,"") | K33: =IFERROR(E33/$B$33*100,"") | L33: =IFERROR(F33/$B$33*100,"")
A34: Anlægsaktiver | B34: ='balance_raw_32441483'!$B$15 | C34: ='balance_raw_32441483'!$C$15 | D34: ='balance_raw_32441483'!$D$15 | E34: ='balance_raw_32441483'!$E$15 | F34: ='balance_raw_32441483'!$F$15 | H34: =IFERROR(B34/$B$34*100,"") | I34: =IFERROR(C34/$B$34*100,"") | J34: =IFERROR(D34/$B$34*100,"") | K34: =IFERROR(E34/$B$34*100,"") | L34: =IFERROR(F34/$B$34*100,"")
A35: Råvarer og hjælpematerialer | B35: ='balance_raw_32441483'!$B$16 | C35: ='balance_raw_32441483'!$C$16 | D35: ='balance_raw_32441483'!$D$16 | E35: ='balance_raw_32441483'!$E$16 | F35: ='balance_raw_32441483'!$F$16 | H35: =IFERROR(B35/$B$35*100,"") | I35: =IFERROR(C35/$B$35*100,"") | J35: =IFERROR(D35/$B$35*100,"") | K35: =IFERROR(E35/$B$35*100,"") | L35: =IFERROR(F35/$B$35*100,"")
A36: Varer under fremstilling | B36: ='balance_raw_32441483'!$B$17 | C36: ='balance_raw_32441483'!$C$17 | D36: ='balance_raw_32441483'!$D$17 | E36: ='balance_raw_32441483'!$E$17 | F36: ='balance_raw_32441483'!$F$17 | H36: =IFERROR(B36/$B$36*100,"") | I36: =IFERROR(C36/$B$36*100,"") | J36: =IFERROR(D36/$B$36*100,"") | K36: =IFERROR(E36/$B$36*100,"") | L36: =IFERROR(F36/$B$36*100,"")
A37: Færdigvarer og handelsvarer | B37: ='balance_raw_32441483'!$B$18 | C37: ='balance_raw_32441483'!$C$18 | D37: ='balance_raw_32441483'!$D$18 | E37: ='balance_raw_32441483'!$E$18 | F37: ='balance_raw_32441483'!$F$18 | H37: =IFERROR(B37/$B$37*100,"") | I37: =IFERROR(C37/$B$37*100,"") | J37: =IFERROR(D37/$B$37*100,"") | K37: =IFERROR(E37/$B$37*100,"") | L37: =IFERROR(F37/$B$37*100,"")
A38: Varebeholdninger | B38: ='balance_raw_32441483'!$B$19 | C38: ='balance_raw_32441483'!$C$19 | D38: ='balance_raw_32441483'!$D$19 | E38: ='balance_raw_32441483'!$E$19 | F38: ='balance_raw_32441483'!$F$19 | H38: =IFERROR(B38/$B$38*100,"") | I38: =IFERROR(C38/$B$38*100,"") | J38: =IFERROR(D38/$B$38*100,"") | K38: =IFERROR(E38/$B$38*100,"") | L38: =IFERROR(F38/$B$38*100,"")
A39: Tilgodehavender fra salg og tjenesteydelser | B39: ='balance_raw_32441483'!$B$20 | C39: ='balance_raw_32441483'!$C$20 | D39: ='balance_raw_32441483'!$D$20 | E39: ='balance_raw_32441483'!$E$20 | F39: ='balance_raw_32441483'!$F$20 | H39: =IFERROR(B39/$B$39*100,"") | I39: =IFERROR(C39/$B$39*100,"") | J39: =IFERROR(D39/$B$39*100,"") | K39: =IFERROR(E39/$B$39*100,"") | L39: =IFERROR(F39/$B$39*100,"")
A40: Tilgodehavender hos tilknyttede virksomheder | B40: ='balance_raw_32441483'!$B$21 | C40: ='balance_raw_32441483'!$C$21 | D40: ='balance_raw_32441483'!$D$21 | E40: ='balance_raw_32441483'!$E$21 | F40: ='balance_raw_32441483'!$F$21 | H40: =IFERROR(B40/$B$40*100,"") | I40: =IFERROR(C40/$B$40*100,"") | J40: =IFERROR(D40/$B$40*100,"") | K40: =IFERROR(E40/$B$40*100,"") | L40: =IFERROR(F40/$B$40*100,"")
A41: Andre tilgodehavender | B41: ='balance_raw_32441483'!$B$22 | C41: ='balance_raw_32441483'!$C$22 | D41: ='balance_raw_32441483'!$D$22 | E41: ='balance_raw_32441483'!$E$22 | F41: ='balance_raw_32441483'!$F$22 | H41: =IFERROR(B41/$B$41*100,"") | I41: =IFERROR(C41/$B$41*100,"") | J41: =IFERROR(D41/$B$41*100,"") | K41: =IFERROR(E41/$B$41*100,"") | L41: =IFERROR(F41/$B$41*100,"")
A42: Periodeafgrænsningsposter (aktiver) | B42: ='balance_raw_32441483'!$B$23 | C42: ='balance_raw_32441483'!$C$23 | D42: ='balance_raw_32441483'!$D$23 | E42: ='balance_raw_32441483'!$E$23 | F42: ='balance_raw_32441483'!$F$23 | H42: =IFERROR(B42/$B$42*100,"") | I42: =IFERROR(C42/$B$42*100,"") | J42: =IFERROR(D42/$B$42*100,"") | K42: =IFERROR(E42/$B$42*100,"") | L42: =IFERROR(F42/$B$42*100,"")
A43: Udskudt skatteaktiv | B43: ='balance_raw_32441483'!$B$24 | C43: ='balance_raw_32441483'!$C$24 | D43: ='balance_raw_32441483'!$D$24 | E43: ='balance_raw_32441483'!$E$24 | F43: ='balance_raw_32441483'!$F$24 | H43: =IFERROR(B43/$B$43*100,"") | I43: =IFERROR(C43/$B$43*100,"") | J43: =IFERROR(D43/$B$43*100,"") | K43: =IFERROR(E43/$B$43*100,"") | L43: =IFERROR(F43/$B$43*100,"")
A44: Tilgodehavende skat hos tilknyttede virksomheder | B44: ='balance_raw_32441483'!$B$25 | C44: ='balance_raw_32441483'!$C$25 | D44: ='balance_raw_32441483'!$D$25 | E44: ='balance_raw_32441483'!$E$25 | F44: ='balance_raw_32441483'!$F$25 | H44: =IFERROR(B44/$B$44*100,"") | I44: =IFERROR(C44/$B$44*100,"") | J44: =IFERROR(D44/$B$44*100,"") | K44: =IFERROR(E44/$B$44*100,"") | L44: =IFERROR(F44/$B$44*100,"")
A45: Kortfristede skattetilgodehavender | B45: ='balance_raw_32441483'!$B$26 | C45: ='balance_raw_32441483'!$C$26 | D45: ='balance_raw_32441483'!$D$26 | E45: ='balance_raw_32441483'!$E$26 | F45: ='balance_raw_32441483'!$F$26 | H45: =IFERROR(B45/$B$45*100,"") | I45: =IFERROR(C45/$B$45*100,"") | J45: =IFERROR(D45/$B$45*100,"") | K45: =IFERROR(E45/$B$45*100,"") | L45: =IFERROR(F45/$B$45*100,"")
A46: Tilgodehavender | B46: ='balance_raw_32441483'!$B$27 | C46: ='balance_raw_32441483'!$C$27 | D46: ='balance_raw_32441483'!$D$27 | E46: ='balance_raw_32441483'!$E$27 | F46: ='balance_raw_32441483'!$F$27 | H46: =IFERROR(B46/$B$46*100,"") | I46: =IFERROR(C46/$B$46*100,"") | J46: =IFERROR(D46/$B$46*100,"") | K46: =IFERROR(E46/$B$46*100,"") | L46: =IFERROR(F46/$B$46*100,"")
A47: Værdipapirer | B47: ='balance_raw_32441483'!$B$28 | C47: ='balance_raw_32441483'!$C$28 | D47: ='balance_raw_32441483'!$D$28 | E47: ='balance_raw_32441483'!$E$28 | F47: ='balance_raw_32441483'!$F$28 | H47: =IFERROR(B47/$B$47*100,"") | I47: =IFERROR(C47/$B$47*100,"") | J47: =IFERROR(D47/$B$47*100,"") | K47: =IFERROR(E47/$B$47*100,"") | L47: =IFERROR(F47/$B$47*100,"")
A48: Likvide beholdninger | B48: ='balance_raw_32441483'!$B$29 | C48: ='balance_raw_32441483'!$C$29 | D48: ='balance_raw_32441483'!$D$29 | E48: ='balance_raw_32441483'!$E$29 | F48: ='balance_raw_32441483'!$F$29 | H48: =IFERROR(B48/$B$48*100,"") | I48: =IFERROR(C48/$B$48*100,"") | J48: =IFERROR(D48/$B$48*100,"") | K48: =IFERROR(E48/$B$48*100,"") | L48: =IFERROR(F48/$B$48*100,"")
A49: Omsætningsaktiver | B49: ='balance_raw_32441483'!$B$30 | C49: ='balance_raw_32441483'!$C$30 | D49: ='balance_raw_32441483'!$D$30 | E49: ='balance_raw_32441483'!$E$30 | F49: ='balance_raw_32441483'!$F$30 | H49: =IFERROR(B49/$B$49*100,"") | I49: =IFERROR(C49/$B$49*100,"") | J49: =IFERROR(D49/$B$49*100,"") | K49: =IFERROR(E49/$B$49*100,"") | L49: =IFERROR(F49/$B$49*100,"")
A50: Aktiver | B50: ='balance_raw_32441483'!$B$31 | C50: ='balance_raw_32441483'!$C$31 | D50: ='balance_raw_32441483'!$D$31 | E50: ='balance_raw_32441483'!$E$31 | F50: ='balance_raw_32441483'!$F$31 | H50: =IFERROR(B50/$B$50*100,"") | I50: =IFERROR(C50/$B$50*100,"") | J50: =IFERROR(D50/$B$50*100,"") | K50: =IFERROR(E50/$B$50*100,"") | L50: =IFERROR(F50/$B$50*100,"")
A52: PASSIVER t.kr. | B52: 2021 | C52: 2022 | D52: 2023 | E52: 2024 | F52: 2025 | H52: 2021 | I52: 2022 | J52: 2023 | K52: 2024 | L52: 2025
A53: Selskabskapital | B53: ='balance_raw_32441483'!$B$32 | C53: ='balance_raw_32441483'!$C$32 | D53: ='balance_raw_32441483'!$D$32 | E53: ='balance_raw_32441483'!$E$32 | F53: ='balance_raw_32441483'!$F$32 | H53: =IFERROR(B53/$B$53*100,"") | I53: =IFERROR(C53/$B$53*100,"") | J53: =IFERROR(D53/$B$53*100,"") | K53: =IFERROR(E53/$B$53*100,"") | L53: =IFERROR(F53/$B$53*100,"")
A54: Reserve for nettoopskrivning (indre værdis metode) | B54: ='balance_raw_32441483'!$B$33 | C54: ='balance_raw_32441483'!$C$33 | D54: ='balance_raw_32441483'!$D$33 | E54: ='balance_raw_32441483'!$E$33 | F54: ='balance_raw_32441483'!$F$33 | H54: =IFERROR(B54/$B$54*100,"") | I54: =IFERROR(C54/$B$54*100,"") | J54: =IFERROR(D54/$B$54*100,"") | K54: =IFERROR(E54/$B$54*100,"") | L54: =IFERROR(F54/$B$54*100,"")
A55: Reserve for udviklingsomkostninger | B55: ='balance_raw_32441483'!$B$34 | C55: ='balance_raw_32441483'!$C$34 | D55: ='balance_raw_32441483'!$D$34 | E55: ='balance_raw_32441483'!$E$34 | F55: ='balance_raw_32441483'!$F$34 | H55: =IFERROR(B55/$B$55*100,"") | I55: =IFERROR(C55/$B$55*100,"") | J55: =IFERROR(D55/$B$55*100,"") | K55: =IFERROR(E55/$B$55*100,"") | L55: =IFERROR(F55/$B$55*100,"")
A56: Reserve for sikringstransaktioner | B56: ='balance_raw_32441483'!$B$35 | C56: ='balance_raw_32441483'!$C$35 | D56: ='balance_raw_32441483'!$D$35 | E56: ='balance_raw_32441483'!$E$35 | F56: ='balance_raw_32441483'!$F$35 | H56: =IFERROR(B56/$B$56*100,"") | I56: =IFERROR(C56/$B$56*100,"") | J56: =IFERROR(D56/$B$56*100,"") | K56: =IFERROR(E56/$B$56*100,"") | L56: =IFERROR(F56/$B$56*100,"")
A57: Andre reserver | B57: ='balance_raw_32441483'!$B$36 | C57: ='balance_raw_32441483'!$C$36 | D57: ='balance_raw_32441483'!$D$36 | E57: ='balance_raw_32441483'!$E$36 | F57: ='balance_raw_32441483'!$F$36 | H57: =IFERROR(B57/$B$57*100,"") | I57: =IFERROR(C57/$B$57*100,"") | J57: =IFERROR(D57/$B$57*100,"") | K57: =IFERROR(E57/$B$57*100,"") | L57: =IFERROR(F57/$B$57*100,"")
A58: Overført resultat | B58: ='balance_raw_32441483'!$B$37 | C58: ='balance_raw_32441483'!$C$37 | D58: ='balance_raw_32441483'!$D$37 | E58: ='balance_raw_32441483'!$E$37 | F58: ='balance_raw_32441483'!$F$37 | H58: =IFERROR(B58/$B$58*100,"") | I58: =IFERROR(C58/$B$58*100,"") | J58: =IFERROR(D58/$B$58*100,"") | K58: =IFERROR(E58/$B$58*100,"") | L58: =IFERROR(F58/$B$58*100,"")
A59: Egenkapital i alt | B59: ='balance_raw_32441483'!$B$38 | C59: ='balance_raw_32441483'!$C$38 | D59: ='balance_raw_32441483'!$D$38 | E59: ='balance_raw_32441483'!$E$38 | F59: ='balance_raw_32441483'!$F$38 | H59: =IFERROR(B59/$B$59*100,"") | I59: =IFERROR(C59/$B$59*100,"") | J59: =IFERROR(D59/$B$59*100,"") | K59: =IFERROR(E59/$B$59*100,"") | L59: =IFERROR(F59/$B$59*100,"")
A60: Hensatte forpligtelser | B60: ='balance_raw_32441483'!$B$39 | C60: ='balance_raw_32441483'!$C$39 | D60: ='balance_raw_32441483'!$D$39 | E60: ='balance_raw_32441483'!$E$39 | F60: ='balance_raw_32441483'!$F$39 | H60: =IFERROR(B60/$B$60*100,"") | I60: =IFERROR(C60/$B$60*100,"") | J60: =IFERROR(D60/$B$60*100,"") | K60: =IFERROR(E60/$B$60*100,"") | L60: =IFERROR(F60/$B$60*100,"")
A61: Ansvarlig lånekapital (langfristet) | B61: ='balance_raw_32441483'!$B$40 | C61: ='balance_raw_32441483'!$C$40 | D61: ='balance_raw_32441483'!$D$40 | E61: ='balance_raw_32441483'!$E$40 | F61: ='balance_raw_32441483'!$F$40 | H61: =IFERROR(B61/$B$61*100,"") | I61: =IFERROR(C61/$B$61*100,"") | J61: =IFERROR(D61/$B$61*100,"") | K61: =IFERROR(E61/$B$61*100,"") | L61: =IFERROR(F61/$B$61*100,"")
A62: Langfristede lån | B62: ='balance_raw_32441483'!$B$41 | C62: ='balance_raw_32441483'!$C$41 | D62: ='balance_raw_32441483'!$D$41 | E62: ='balance_raw_32441483'!$E$41 | F62: ='balance_raw_32441483'!$F$41 | H62: =IFERROR(B62/$B$62*100,"") | I62: =IFERROR(C62/$B$62*100,"") | J62: =IFERROR(D62/$B$62*100,"") | K62: =IFERROR(E62/$B$62*100,"") | L62: =IFERROR(F62/$B$62*100,"")
A63: Leasingforpligtelser (langfristet) | B63: ='balance_raw_32441483'!$B$42 | C63: ='balance_raw_32441483'!$C$42 | D63: ='balance_raw_32441483'!$D$42 | E63: ='balance_raw_32441483'!$E$42 | F63: ='balance_raw_32441483'!$F$42 | H63: =IFERROR(B63/$B$63*100,"") | I63: =IFERROR(C63/$B$63*100,"") | J63: =IFERROR(D63/$B$63*100,"") | K63: =IFERROR(E63/$B$63*100,"") | L63: =IFERROR(F63/$B$63*100,"")
A64: Anden gæld (langfristet) | B64: ='balance_raw_32441483'!$B$43 | C64: ='balance_raw_32441483'!$C$43 | D64: ='balance_raw_32441483'!$D$43 | E64: ='balance_raw_32441483'!$E$43 | F64: ='balance_raw_32441483'!$F$43 | H64: =IFERROR(B64/$B$64*100,"") | I64: =IFERROR(C64/$B$64*100,"") | J64: =IFERROR(D64/$B$64*100,"") | K64: =IFERROR(E64/$B$64*100,"") | L64: =IFERROR(F64/$B$64*100,"")
A65: Langfristede gældsforpligtelser | B65: ='balance_raw_32441483'!$B$44 | C65: ='balance_raw_32441483'!$C$44 | D65: ='balance_raw_32441483'!$D$44 | E65: ='balance_raw_32441483'!$E$44 | F65: ='balance_raw_32441483'!$F$44 | H65: =IFERROR(B65/$B$65*100,"") | I65: =IFERROR(C65/$B$65*100,"") | J65: =IFERROR(D65/$B$65*100,"") | K65: =IFERROR(E65/$B$65*100,"") | L65: =IFERROR(F65/$B$65*100,"")
A66: Ansvarlig lånekapital (kortfristet) | B66: ='balance_raw_32441483'!$B$45 | C66: ='balance_raw_32441483'!$C$45 | D66: ='balance_raw_32441483'!$D$45 | E66: ='balance_raw_32441483'!$E$45 | F66: ='balance_raw_32441483'!$F$45 | H66: =IFERROR(B66/$B$66*100,"") | I66: =IFERROR(C66/$B$66*100,"") | J66: =IFERROR(D66/$B$66*100,"") | K66: =IFERROR(E66/$B$66*100,"") | L66: =IFERROR(F66/$B$66*100,"")
A67: Kortfristet del af langfristede gældsforpligtelser | B67: ='balance_raw_32441483'!$B$46 | C67: ='balance_raw_32441483'!$C$46 | D67: ='balance_raw_32441483'!$D$46 | E67: ='balance_raw_32441483'!$E$46 | F67: ='balance_raw_32441483'!$F$46 | H67: =IFERROR(B67/$B$67*100,"") | I67: =IFERROR(C67/$B$67*100,"") | J67: =IFERROR(D67/$B$67*100,"") | K67: =IFERROR(E67/$B$67*100,"") | L67: =IFERROR(F67/$B$67*100,"")
A68: Kreditinstitutter | B68: ='balance_raw_32441483'!$B$47 | C68: ='balance_raw_32441483'!$C$47 | D68: ='balance_raw_32441483'!$D$47 | E68: ='balance_raw_32441483'!$E$47 | F68: ='balance_raw_32441483'!$F$47 | H68: =IFERROR(B68/$B$68*100,"") | I68: =IFERROR(C68/$B$68*100,"") | J68: =IFERROR(D68/$B$68*100,"") | K68: =IFERROR(E68/$B$68*100,"") | L68: =IFERROR(F68/$B$68*100,"")
A69: Leasingforpligtelser (kortfristet) | B69: ='balance_raw_32441483'!$B$48 | C69: ='balance_raw_32441483'!$C$48 | D69: ='balance_raw_32441483'!$D$48 | E69: ='balance_raw_32441483'!$E$48 | F69: ='balance_raw_32441483'!$F$48 | H69: =IFERROR(B69/$B$69*100,"") | I69: =IFERROR(C69/$B$69*100,"") | J69: =IFERROR(D69/$B$69*100,"") | K69: =IFERROR(E69/$B$69*100,"") | L69: =IFERROR(F69/$B$69*100,"")
A70: Leverandører af varer og tjenesteydelser | B70: ='balance_raw_32441483'!$B$49 | C70: ='balance_raw_32441483'!$C$49 | D70: ='balance_raw_32441483'!$D$49 | E70: ='balance_raw_32441483'!$E$49 | F70: ='balance_raw_32441483'!$F$49 | H70: =IFERROR(B70/$B$70*100,"") | I70: =IFERROR(C70/$B$70*100,"") | J70: =IFERROR(D70/$B$70*100,"") | K70: =IFERROR(E70/$B$70*100,"") | L70: =IFERROR(F70/$B$70*100,"")
A71: Gæld til tilknyttede virksomheder | B71: ='balance_raw_32441483'!$B$50 | C71: ='balance_raw_32441483'!$C$50 | D71: ='balance_raw_32441483'!$D$50 | E71: ='balance_raw_32441483'!$E$50 | F71: ='balance_raw_32441483'!$F$50 | H71: =IFERROR(B71/$B$71*100,"") | I71: =IFERROR(C71/$B$71*100,"") | J71: =IFERROR(D71/$B$71*100,"") | K71: =IFERROR(E71/$B$71*100,"") | L71: =IFERROR(F71/$B$71*100,"")
A72: Gæld til selskabsdeltagere og ledelse | B72: ='balance_raw_32441483'!$B$51 | C72: ='balance_raw_32441483'!$C$51 | D72: ='balance_raw_32441483'!$D$51 | E72: ='balance_raw_32441483'!$E$51 | F72: ='balance_raw_32441483'!$F$51 | H72: =IFERROR(B72/$B$72*100,"") | I72: =IFERROR(C72/$B$72*100,"") | J72: =IFERROR(D72/$B$72*100,"") | K72: =IFERROR(E72/$B$72*100,"") | L72: =IFERROR(F72/$B$72*100,"")
A73: Selskabsskat | B73: ='balance_raw_32441483'!$B$52 | C73: ='balance_raw_32441483'!$C$52 | D73: ='balance_raw_32441483'!$D$52 | E73: ='balance_raw_32441483'!$E$52 | F73: ='balance_raw_32441483'!$F$52 | H73: =IFERROR(B73/$B$73*100,"") | I73: =IFERROR(C73/$B$73*100,"") | J73: =IFERROR(D73/$B$73*100,"") | K73: =IFERROR(E73/$B$73*100,"") | L73: =IFERROR(F73/$B$73*100,"")
A74: Gæld til tilknyttede virksomheder vedr. selskabsskat | B74: ='balance_raw_32441483'!$B$53 | C74: ='balance_raw_32441483'!$C$53 | D74: ='balance_raw_32441483'!$D$53 | E74: ='balance_raw_32441483'!$E$53 | F74: ='balance_raw_32441483'!$F$53 | H74: =IFERROR(B74/$B$74*100,"") | I74: =IFERROR(C74/$B$74*100,"") | J74: =IFERROR(D74/$B$74*100,"") | K74: =IFERROR(E74/$B$74*100,"") | L74: =IFERROR(F74/$B$74*100,"")
A75: Anden gæld (kortfristet) | B75: ='balance_raw_32441483'!$B$54 | C75: ='balance_raw_32441483'!$C$54 | D75: ='balance_raw_32441483'!$D$54 | E75: ='balance_raw_32441483'!$E$54 | F75: ='balance_raw_32441483'!$F$54 | H75: =IFERROR(B75/$B$75*100,"") | I75: =IFERROR(C75/$B$75*100,"") | J75: =IFERROR(D75/$B$75*100,"") | K75: =IFERROR(E75/$B$75*100,"") | L75: =IFERROR(F75/$B$75*100,"")
A76: Periodeafgrænsningsposter (passiver) | B76: ='balance_raw_32441483'!$B$55 | C76: ='balance_raw_32441483'!$C$55 | D76: ='balance_raw_32441483'!$D$55 | E76: ='balance_raw_32441483'!$E$55 | F76: ='balance_raw_32441483'!$F$55 | H76: =IFERROR(B76/$B$76*100,"") | I76: =IFERROR(C76/$B$76*100,"") | J76: =IFERROR(D76/$B$76*100,"") | K76: =IFERROR(E76/$B$76*100,"") | L76: =IFERROR(F76/$B$76*100,"")
A77: Kortfristede gældsforpligtelser | B77: ='balance_raw_32441483'!$B$56 | C77: ='balance_raw_32441483'!$C$56 | D77: ='balance_raw_32441483'!$D$56 | E77: ='balance_raw_32441483'!$E$56 | F77: ='balance_raw_32441483'!$F$56 | H77: =IFERROR(B77/$B$77*100,"") | I77: =IFERROR(C77/$B$77*100,"") | J77: =IFERROR(D77/$B$77*100,"") | K77: =IFERROR(E77/$B$77*100,"") | L77: =IFERROR(F77/$B$77*100,"")
A78: Gældsforpligtelser | B78: ='balance_raw_32441483'!$B$57 | C78: ='balance_raw_32441483'!$C$57 | D78: ='balance_raw_32441483'!$D$57 | E78: ='balance_raw_32441483'!$E$57 | F78: ='balance_raw_32441483'!$F$57 | H78: =IFERROR(B78/$B$78*100,"") | I78: =IFERROR(C78/$B$78*100,"") | J78: =IFERROR(D78/$B$78*100,"") | K78: =IFERROR(E78/$B$78*100,"") | L78: =IFERROR(F78/$B$78*100,"")
A79: Passiver | B79: ='balance_raw_32441483'!$B$58 | C79: ='balance_raw_32441483'!$C$58 | D79: ='balance_raw_32441483'!$D$58 | E79: ='balance_raw_32441483'!$E$58 | F79: ='balance_raw_32441483'!$F$58 | H79: =IFERROR(B79/$B$79*100,"") | I79: =IFERROR(C79/$B$79*100,"") | J79: =IFERROR(D79/$B$79*100,"") | K79: =IFERROR(E79/$B$79*100,"") | L79: =IFERROR(F79/$B$79*100,"")
A81: NØGLEOPLYSNINGER | B81: 2021 | C81: 2022 | D81: 2023 | E81: 2024 | F81: 2025
A82: Gns. antal medarbejdere | B82: ='res_raw_32441483'!$B$17 | C82: ='res_raw_32441483'!$C$17 | D82: ='res_raw_32441483'!$D$17 | E82: ='res_raw_32441483'!$E$17 | F82: ='res_raw_32441483'!$F$17 | H82: =IFERROR(B82/$B$82*100,"") | I82: =IFERROR(C82/$B$82*100,"") | J82: =IFERROR(D82/$B$82*100,"") | K82: =IFERROR(E82/$B$82*100,"") | L82: =IFERROR(F82/$B$82*100,"")
A83: Investering i materielle anlægsaktiver | B83: ='res_raw_32441483'!$B$18 | C83: ='res_raw_32441483'!$C$18 | D83: ='res_raw_32441483'!$D$18 | E83: ='res_raw_32441483'!$E$18 | F83: ='res_raw_32441483'!$F$18 | H83: =IFERROR(B83/$B$83*100,"") | I83: =IFERROR(C83/$B$83*100,"") | J83: =IFERROR(D83/$B$83*100,"") | K83: =IFERROR(E83/$B$83*100,"") | L83: =IFERROR(F83/$B$83*100,"")
A85: NØGLETAL | B85: 2021 | C85: 2022 | D85: 2023 | E85: 2024 | F85: 2025
A86: Afkastningsgrad, % | B86: =IFERROR(($B$11+$B$13+$B$12)/$B$50*100,"") | C86: =IFERROR(($C$11+$C$13+$C$12)/$C$50*100,"") | D86: =IFERROR(($D$11+$D$13+$D$12)/$D$50*100,"") | E86: =IFERROR(($E$11+$E$13+$E$12)/$E$50*100,"") | F86: =IFERROR(($F$11+$F$13+$F$12)/$F$50*100,"")
A87: Overskudsgrad (af bruttofortjeneste), % | B87: =IFERROR(($B$11+$B$13+$B$12)/$B$6*100,"") | C87: =IFERROR(($C$11+$C$13+$C$12)/$C$6*100,"") | D87: =IFERROR(($D$11+$D$13+$D$12)/$D$6*100,"") | E87: =IFERROR(($E$11+$E$13+$E$12)/$E$6*100,"") | F87: =IFERROR(($F$11+$F$13+$F$12)/$F$6*100,"")
A88: Aktivernes omsætningshastighed (af bruttofortjeneste), gange | B88: =IFERROR($B$6/$B$50,"") | C88: =IFERROR($C$6/$C$50,"") | D88: =IFERROR($D$6/$D$50,"") | E88: =IFERROR($E$6/$E$50,"") | F88: =IFERROR($F$6/$F$50,"")
A89: Egenkapitalens forrentning, % | B89: =IFERROR($B$16/$B$59*100,"") | C89: =IFERROR($C$16/$C$59*100,"") | D89: =IFERROR($D$16/$D$59*100,"") | E89: =IFERROR($E$16/$E$59*100,"") | F89: =IFERROR($F$16/$F$59*100,"")
A90: Gældsrente, % | B90: =IFERROR($B$14/($B$79-$B$59)*100,"") | C90: =IFERROR($C$14/($C$79-$C$59)*100,"") | D90: =IFERROR($D$14/($D$79-$D$59)*100,"") | E90: =IFERROR($E$14/($E$79-$E$59)*100,"") | F90: =IFERROR($F$14/($F$79-$F$59)*100,"")
A91: Soliditetsgrad, % | B91: =IFERROR($B$59/$B$50*100,"") | C91: =IFERROR($C$59/$C$50*100,"") | D91: =IFERROR($D$59/$D$50*100,"") | E91: =IFERROR($E$59/$E$50*100,"") | F91: =IFERROR($F$59/$F$50*100,"")
A92: Gearing | B92: =IFERROR(($B$79-$B$59)/$B$59,"") | C92: =IFERROR(($C$79-$C$59)/$C$59,"") | D92: =IFERROR(($D$79-$D$59)/$D$59,"") | E92: =IFERROR(($E$79-$E$59)/$E$59,"") | F92: =IFERROR(($F$79-$F$59)/$F$59,"")
A93: Likviditetsgrad, % | B93: =IFERROR($B$49/$B$77*100,"") | C93: =IFERROR($C$49/$C$77*100,"") | D93: =IFERROR($D$49/$D$77*100,"") | E93: =IFERROR($E$49/$E$77*100,"") | F93: =IFERROR($F$49/$F$77*100,"")
A94: Rentemarginal, % | B94: =IFERROR(B86-B90,"") | C94: =IFERROR(C86-C90,"") | D94: =IFERROR(D86-D90,"") | E94: =IFERROR(E86-E90,"") | F94: =IFERROR(F86-F90,"")
A95: Gældsandel, % | B95: =IFERROR(($B$79-$B$59)/$B$50*100,"") | C95: =IFERROR(($C$79-$C$59)/$C$50*100,"") | D95: =IFERROR(($D$79-$D$59)/$D$50*100,"") | E95: =IFERROR(($E$79-$E$59)/$E$50*100,"") | F95: =IFERROR(($F$79-$F$59)/$F$50*100,"")
A96: Kapitalbindingsgrad, % | B96: =IFERROR($B$34/($B$59+$B$65)*100,"") | C96: =IFERROR($C$34/($C$59+$C$65)*100,"") | D96: =IFERROR($D$34/($D$59+$D$65)*100,"") | E96: =IFERROR($E$34/($E$59+$E$65)*100,"") | F96: =IFERROR($F$34/($F$59+$F$65)*100,"")
A98: PENGESTRØMSOPGØRELSE t.kr.
A99: Pengestrømme fra driftsaktivitet | B99: ='pengestrom_raw_32441483'!$B$2 | C99: ='pengestrom_raw_32441483'!$C$2 | D99: ='pengestrom_raw_32441483'!$D$2 | E99: ='pengestrom_raw_32441483'!$E$2 | F99: ='pengestrom_raw_32441483'!$F$2
A100: Pengestrømme fra investeringsaktivitet | B100: ='pengestrom_raw_32441483'!$B$3 | C100: ='pengestrom_raw_32441483'!$C$3 | D100: ='pengestrom_raw_32441483'!$D$3 | E100: ='pengestrom_raw_32441483'!$E$3 | F100: ='pengestrom_raw_32441483'!$F$3
A101: Pengestrømme fra finansieringsaktivitet | B101: ='pengestrom_raw_32441483'!$B$4 | C101: ='pengestrom_raw_32441483'!$C$4 | D101: ='pengestrom_raw_32441483'!$D$4 | E101: ='pengestrom_raw_32441483'!$E$4 | F101: ='pengestrom_raw_32441483'!$F$4
A102: Årets pengestrøm (rapporteret) | B102: ='pengestrom_raw_32441483'!$B$5 | C102: ='pengestrom_raw_32441483'!$C$5 | D102: ='pengestrom_raw_32441483'!$D$5 | E102: ='pengestrom_raw_32441483'!$E$5 | F102: ='pengestrom_raw_32441483'!$F$5
A103: Krydstjek: drift + inv. + fin. = årets pengestrøm | B103: =IF(ABS(('pengestrom_raw_32441483'!$B$2+'pengestrom_raw_32441483'!$B$3+'pengestrom_raw_32441483'!$B$4)-'pengestrom_raw_32441483'!$B$5)<=2,"✓","⚠ "&TEXT(('pengestrom_raw_32441483'!$B$2+'pengestrom_raw_32441483'!$B$3+'pengestrom_raw_32441483'!$B$4)-'pengestrom_raw_32441483'!$B$5,"+#,##0;-#,##0")) | C103: =IF(ABS(('pengestrom_raw_32441483'!$C$2+'pengestrom_raw_32441483'!$C$3+'pengestrom_raw_32441483'!$C$4)-'pengestrom_raw_32441483'!$C$5)<=2,"✓","⚠ "&TEXT(('pengestrom_raw_32441483'!$C$2+'pengestrom_raw_32441483'!$C$3+'pengestrom_raw_32441483'!$C$4)-'pengestrom_raw_32441483'!$C$5,"+#,##0;-#,##0")) | D103: =IF(ABS(('pengestrom_raw_32441483'!$D$2+'pengestrom_raw_32441483'!$D$3+'pengestrom_raw_32441483'!$D$4)-'pengestrom_raw_32441483'!$D$5)<=2,"✓","⚠ "&TEXT(('pengestrom_raw_32441483'!$D$2+'pengestrom_raw_32441483'!$D$3+'pengestrom_raw_32441483'!$D$4)-'pengestrom_raw_32441483'!$D$5,"+#,##0;-#,##0")) | E103: =IF(ABS(('pengestrom_raw_32441483'!$E$2+'pengestrom_raw_32441483'!$E$3+'pengestrom_raw_32441483'!$E$4)-'pengestrom_raw_32441483'!$E$5)<=2,"✓","⚠ "&TEXT(('pengestrom_raw_32441483'!$E$2+'pengestrom_raw_32441483'!$E$3+'pengestrom_raw_32441483'!$E$4)-'pengestrom_raw_32441483'!$E$5,"+#,##0;-#,##0")) | F103: =IF(ABS(('pengestrom_raw_32441483'!$F$2+'pengestrom_raw_32441483'!$F$3+'pengestrom_raw_32441483'!$F$4)-'pengestrom_raw_32441483'!$F$5)<=2,"✓","⚠ "&TEXT(('pengestrom_raw_32441483'!$F$2+'pengestrom_raw_32441483'!$F$3+'pengestrom_raw_32441483'!$F$4)-'pengestrom_raw_32441483'!$F$5,"+#,##0;-#,##0"))

Sheet res_raw_32441483
A1: Hatting A/S (CVR 32441483) — Resultatopgørelse & nøgleoplysninger (t.kr.) | B1: 2021 | C1: 2022 | D1: 2023 | E1: 2024 | F1: 2025
A2: Nettoomsætning
A3: Produktionsomkostninger
A4: Bruttoresultat | B4: 82237 | C4: 66263 | D4: 85909 | E4: 90585 | F4: 93347
A5: Salgs- og distributionsomkostninger | B5: 35839 | C5: 30749 | D5: 31050 | E5: 32335 | F5: 34964
A6: Administrationsomkostninger | B6: 22842 | C6: 19691 | D6: 20745 | E6: 20902 | F6: 21597
A7: Andre driftsindtægter | C7: 13004 | D7: 0 | E7: 25 | F7: 0
A8: Andre driftsomkostninger | C8: -13004
A9: Resultat af primær drift | B9: 23556 | C9: 28827 | D9: 34114 | E9: 37349 | F9: 36787
A10: Indtægter af kapitalandele, dattervirksomheder | B10: -665 | C10: 856 | D10: -41 | E10: -104 | F10: -88
A11: Finansielle indtægter | B11: 995 | C11: 623 | D11: 3884 | E11: 3908 | F11: 1745
A12: Finansielle omkostninger | B12: 163 | C12: 196 | D12: 153 | E12: 27 | F12: 110
A13: Finansielle poster, netto | D13: 3690 | E13: 3777 | F13: 1547
A14: Resultat før skat | B14: 23723 | C14: 30109 | D14: 37803 | E14: 41126 | F14: 38334
A15: Skat af årets resultat | B15: 5347 | C15: 6353 | D15: 8314 | E15: 9071 | F15: 8435
A16: Årets resultat | B16: 18376 | C16: 23757 | D16: 29490 | E16: 32055 | F16: 29899
A17: Gns. antal medarbejdere | D17: 120 | E17: 118 | F17: 119
A18: Investering i materielle anlægsaktiver | B18: -270 | C18: 577 | D18: 318 | E18: 691 | F18: 466

Sheet balance_raw_32441483
A1: Hatting A/S (CVR 32441483) — Balance (t.kr.) | B1: 2021 | C1: 2022 | D1: 2023 | E1: 2024 | F1: 2025
A2: Udviklingsprojekter | F2: 1769
A3: Patenter, varemærker mv.
A4: Goodwill
A5: Immaterielle anlægsaktiver | F5: 1769
A6: Grunde og bygninger | B6: 82734 | C6: 71822 | D6: 62160 | E6: 54179 | F6: 46197
A7: Produktionsanlæg og maskiner
A8: Driftsmateriel og inventar | B8: 11869 | C8: 9270 | D8: 7277 | E8: 6010 | F8: 4727
A9: Indretning af lejede lokaler
A10: Forudbetaling og anlægsaktiver under opførelse | B10: 155 | C10: 140 | D10: 0 | E10: 145 | F10: 0
A11: Materielle anlægsaktiver | B11: 94758 | C11: 81232 | D11: 69437 | E11: 60334 | F11: 50924
A12: Kapitalandele, dattervirksomheder | B12: 220 | C12: 636 | D12: 594 | E12: 491 | F12: 404
A13: Deposita
A14: Finansielle anlægsaktiver | B14: 5593 | C14: 9728 | D14: 10301 | E14: 10677 | F14: 11062
A15: Anlægsaktiver | B15: 100351 | C15: 90960 | D15: 79738 | E15: 71011 | F15: 63755
A16: Råvarer og hjælpematerialer | B16: 4903 | C16: 6514 | D16: 6796 | E16: 7946 | F16: 6580
A17: Varer under fremstilling
A18: Færdigvarer og handelsvarer | B18: 25346 | C18: 27310 | D18: 24984 | E18: 26580 | F18: 32172
A19: Varebeholdninger | B19: 30577 | C19: 33824 | D19: 31780 | E19: 34526 | F19: 38751
A20: Tilgodehavender fra salg og tjenesteydelser | B20: 31432 | C20: 28720 | D20: 30964 | E20: 28880 | F20: 30932
A21: Tilgodehavender hos tilknyttede virksomheder | B21: 91911 | C21: 105320 | D21: 119698 | E21: 113037 | F21: 109110
A22: Andre tilgodehavender | B22: 359 | C22: 157 | D22: 309 | E22: 113 | F22: 138
A23: Periodeafgrænsningsposter (aktiver) | B23: 587 | C23: 665 | D23: 202 | E23: 508 | F23: 129
A24: Udskudt skatteaktiv | B24: 5373 | C24: 9093 | D24: 9707 | E24: 10186 | F24: 10658
A25: Tilgodehavende skat hos tilknyttede virksomheder
A26: Kortfristede skattetilgodehavender
A27: Tilgodehavender | B27: 124288 | C27: 134862 | D27: 151173 | E27: 142538 | F27: 140309
A28: Værdipapirer | B28: 1093 | C28: 1129 | D28: 1736 | E28: 1794 | F28: 1799
A29: Likvide beholdninger | B29: 991 | C29: 362 | D29: 0 | E29: 0 | F29: 0
A30: Omsætningsaktiver | B30: 156949 | C30: 170176 | D30: 184689 | E30: 178858 | F30: 180859
A31: Aktiver | B31: 257300 | C31: 261136 | D31: 264427 | E31: 249869 | F31: 244613
A32: Selskabskapital | B32: 20000 | C32: 20000 | D32: 20000 | E32: 20000 | F32: 20000
A33: Reserve for nettoopskrivning (indre værdis metode)
A34: Reserve for udviklingsomkostninger
A35: Reserve for sikringstransaktioner
A36: Andre reserver | F36: -2
A37: Overført resultat | B37: 142042 | C37: 141799 | D37: 141789 | E37: 141847 | F37: 142246
A38: Egenkapital i alt | B38: 180042 | C38: 185799 | D38: 191289 | E38: 193844 | F38: 191743
A39: Hensatte forpligtelser | B39: 0 | C39: 12160 | D39: 12060 | E39: 12060 | F39: 12060
A40: Ansvarlig lånekapital (langfristet)
A41: Langfristede lån | B41: 26716 | C41: 24313 | D41: 21917 | E41: 4173 | F41: 3766
A42: Leasingforpligtelser (langfristet)
A43: Anden gæld (langfristet) | B43: 0 | C43: 0
A44: Langfristede gældsforpligtelser | B44: 26716 | C44: 24313 | D44: 21917 | E44: 4173 | F44: 3766
A45: Ansvarlig lånekapital (kortfristet)
A46: Kortfristet del af langfristede gældsforpligtelser | B46: 2410 | C46: 2403 | D46: 2396 | E46: 411 | F46: 406
A47: Kreditinstitutter
A48: Leasingforpligtelser (kortfristet)
A49: Leverandører af varer og tjenesteydelser | B49: 5631 | C49: 9624 | D49: 7949 | E49: 8013 | F49: 4452
A50: Gæld til tilknyttede virksomheder | B50: 2164 | C50: 2220 | D50: 2130 | E50: 2832 | F50: 2578
A51: Gæld til selskabsdeltagere og ledelse
A52: Selskabsskat
A53: Gæld til tilknyttede virksomheder vedr. selskabsskat | F53: 8929
A54: Anden gæld (kortfristet) | B54: 26883 | C54: 24618 | D54: 26686 | E54: 28537 | F54: 20679
A55: Periodeafgrænsningsposter (passiver) | B55: 13454 | C55: 0
A56: Kortfristede gældsforpligtelser | B56: 50542 | C56: 38865 | D56: 39161 | E56: 39792 | F56: 37044
A57: Gældsforpligtelser | B57: 77258 | C57: 63177 | D57: 61078 | E57: 43965 | F57: 40810
A58: Passiver | B58: 257300 | C58: 261136 | D58: 264427 | E58: 249869 | F58: 244613

Sheet pengestrom_raw_32441483
A1: Hatting A/S (CVR 32441483) — Pengestrømsopgørelse (t.kr.) | B1: 2021 | C1: 2022 | D1: 2023 | E1: 2024 | F1: 2025
A2: Pengestrømme fra driftsaktivitet | B2: 15829 | C2: 6320 | D2: 25931 | E2: 49825 | F2: 34600
A3: Pengestrømme fra investeringsaktivitet | B3: 540 | C3: 13460 | D3: 109 | E3: -666 | F3: -2189
A4: Pengestrømme fra finansieringsaktivitet | B4: -16417 | C4: -20410 | D4: -26403 | E4: -49159 | F4: -32412
A5: Årets pengestrøm

Sheet Simpel_funktion
A1: Hatting A/S (CVR 32441483) — Regnskabs- og nøgletal (CVR: 32441483) — funktionsopdelt
A3: Beløb i 1.000 kr. | B3: 2025 | C3: 2024 | D3: 2023 | F3: Note / XBRL-felt
A4: Uddrag af resultatopgørelse
A5: Nettoomsætning | B5: ='res_raw_32441483'!$F$2 | C5: ='res_raw_32441483'!$E$2 | D5: ='res_raw_32441483'!$D$2 | F5: fsa:Revenue
A6: Produktionsomkostninger | B6: =-'res_raw_32441483'!$F$3 | C6: =-'res_raw_32441483'!$E$3 | D6: =-'res_raw_32441483'!$D$3 | F6: fsa:CostOfProduction (vises negativt). Materialer, lønninger, produktionsoverhead.
A7: Bruttoresultat | B7: =IF(COUNT('res_raw_32441483'!$F$2,'res_raw_32441483'!$F$3)=0,'res_raw_32441483'!$F$4,SUM(B5:B6)) | C7: =IF(COUNT('res_raw_32441483'!$E$2,'res_raw_32441483'!$E$3)=0,'res_raw_32441483'!$E$4,SUM(C5:C6)) | D7: =IF(COUNT('res_raw_32441483'!$D$2,'res_raw_32441483'!$D$3)=0,'res_raw_32441483'!$D$4,SUM(D5:D6)) | F7: Beregnet: Nettoomsætning − Produktionsomkostninger. Matcher fsa:GrossResult. Er komponenterne ikke indberettet, vises rapporteret fsa:GrossResult direkte.
A8: Salgs- og distributionsomk. | B8: =-'res_raw_32441483'!$F$5 | C8: =-'res_raw_32441483'!$E$5 | D8: =-'res_raw_32441483'!$D$5 | F8: fsa:DistributionCosts (vises negativt). Marketing, salg, distribution.
A9: Administrationsomkostninger mv. | B9: =-'res_raw_32441483'!$F$6 | C9: =-'res_raw_32441483'!$E$6 | D9: =-'res_raw_32441483'!$D$6 | F9: fsa:AdministrativeExpenses (vises negativt). Generel administration.
A10: Andre driftsindtægter | B10: ='res_raw_32441483'!$F$7 | C10: ='res_raw_32441483'!$E$7 | D10: ='res_raw_32441483'!$D$7 | F10: fsa:OtherOperatingIncome. Sekundære driftsindtægter (huslejeindtægter, off. tilskud, avancer mv.).
A11: Andre driftsomkostninger | B11: =-'res_raw_32441483'!$F$8 | C11: =-'res_raw_32441483'!$E$8 | D11: =-'res_raw_32441483'!$D$8 | F11: fsa:OtherOperatingExpenses (vises negativt). Sekundære driftsomkostninger.
A12: Resultat af primær drift | B12: =SUM(B7:B11) | C12: =SUM(C7:C11) | D12: =SUM(D7:D11) | F12: Beregnet: Bruttoresultat − Salgs/dist. − Administration + Andre driftsindt. − Andre driftsomk. EBIT.
A13: Finansielle indtægter mv. | B13: =N('res_raw_32441483'!$F$10)+N('res_raw_32441483'!$F$11) | C13: =N('res_raw_32441483'!$E$10)+N('res_raw_32441483'!$E$11) | D13: =N('res_raw_32441483'!$D$10)+N('res_raw_32441483'!$D$11) | F13: fsa:IncomeFromSubsidiaries + fsa:OtherFinanceIncome.
A14: Finansielle omkostninger mv. | B14: =-'res_raw_32441483'!$F$12 | C14: =-'res_raw_32441483'!$E$12 | D14: =-'res_raw_32441483'!$D$12 | F14: fsa:OtherFinanceExpenses (vises negativt). Renteomkostninger, kurstab.
A15: Resultat før skat | B15: =SUM(B12:B14) | C15: =SUM(C12:C14) | D15: =SUM(D12:D14) | F15: Beregnet: EBIT + Fin. indtægter + Fin. omk. EBT.
A17: Uddrag af balance
A18: Anlægsaktiver | B18: ='balance_raw_32441483'!$F$15 | C18: ='balance_raw_32441483'!$E$15 | D18: ='balance_raw_32441483'!$D$15 | F18: fsa:NoncurrentAssets. Materielle, immaterielle og finansielle anlægsaktiver.
A19: Omsætningsaktiver | B19: ='balance_raw_32441483'!$F$30 | C19: ='balance_raw_32441483'!$E$30 | D19: ='balance_raw_32441483'!$D$30 | F19: fsa:CurrentAssets. Varebeholdninger, tilgodehavender, likvider.
A20: Aktiver i alt | B20: =SUM(B18:B19) | C20: =SUM(C18:C19) | D20: =SUM(D18:D19) | F20: Beregnet: Anlægsaktiver + Omsætningsaktiver. Bør matche fsa:Assets.
A22: Egenkapital | B22: ='balance_raw_32441483'!$F$38 | C22: ='balance_raw_32441483'!$E$38 | D22: ='balance_raw_32441483'!$D$38 | F22: fsa:Equity. Selskabskapital, overført resultat, reserver.
A23: Forpligtelser | B23: ='balance_raw_32441483'!$F$58-'balance_raw_32441483'!$F$38 | C23: ='balance_raw_32441483'!$E$58-'balance_raw_32441483'!$E$38 | D23: ='balance_raw_32441483'!$D$58-'balance_raw_32441483'!$D$38 | F23: Beregnet: Passiver (fsa:LiabilitiesAndEquity) − Egenkapital. Hensættelser + kort- og langfristet gæld.
A24: Passiver i alt | B24: =SUM(B22:B23) | C24: =SUM(C22:C23) | D24: =SUM(D22:D23) | F24: Beregnet: Egenkapital + Forpligtelser. Bør matche Aktiver i alt.
A26: Udvalgte balanceposter
A27: Varebeholdninger | B27: ='balance_raw_32441483'!$F$19 | C27: ='balance_raw_32441483'!$E$19 | D27: ='balance_raw_32441483'!$D$19 | F27: fsa:Inventories (eller fsa:ManufacturedGoodsAndGoodsForResale hvis total mangler).
A28: Tilgodehavender fra salg | B28: ='balance_raw_32441483'!$F$20 | C28: ='balance_raw_32441483'!$E$20 | D28: ='balance_raw_32441483'!$D$20 | F28: fsa:ShorttermTradeReceivables. Kortfristede tilgodehavender fra kunder.
A29: Kortfristede gældsforpligtelser | B29: ='balance_raw_32441483'!$F$56 | C29: ='balance_raw_32441483'!$E$56 | D29: ='balance_raw_32441483'!$D$56 | F29: fsa:ShorttermLiabilitiesOtherThanProvisions. Gæld der forfalder inden for 1 år.
A31: Rentabilitet
A32: Afkastningsgrad, % | B32: =IFERROR((B12+B13)/B20*100,"") | C32: =IFERROR((C12+C13)/C20*100,"") | D32: =IFERROR((D12+D13)/D20*100,"")
A33: Overskudsgrad (af bruttofortjeneste), % | B33: =IFERROR((B12+B13)/B7*100,"") | C33: =IFERROR((C12+C13)/C7*100,"") | D33: =IFERROR((D12+D13)/D7*100,"")
A34: Aktivernes omsætningshastighed (af bruttofortjeneste), gange | B34: =IFERROR(B7/B20,"") | C34: =IFERROR(C7/C20,"") | D34: =IFERROR(D7/D20,"")
A35: Gældsrente, % | B35: =IFERROR(-B14*100/B23,"") | C35: =IFERROR(-C14*100/C23,"") | D35: =IFERROR(-D14*100/D23,"")
A36: Egenkapitalens forrentning, % | B36: =IFERROR(B15/B22*100,"") | C36: =IFERROR(C15/C22*100,"") | D36: =IFERROR(D15/D22*100,"")
A37: Gearing, gange | B37: =IFERROR(B23/B22,"") | C37: =IFERROR(C23/C22,"") | D37: =IFERROR(D23/D22,"")
A39: Indekstal for indtjeningsevne (2023=100)
A40: Bruttofortjeneste | B40: =IFERROR(B7/$D7*100,"") | C40: =IFERROR(C7/$D7*100,"") | D40: =IFERROR(D7/$D7*100,"")
A41: Produktionsomkostninger | B41: =IFERROR(B6/$D6*100,"") | C41: =IFERROR(C6/$D6*100,"") | D41: =IFERROR(D6/$D6*100,"")
A42: Salgs- og distributionsomk. | B42: =IFERROR(B8/$D8*100,"") | C42: =IFERROR(C8/$D8*100,"") | D42: =IFERROR(D8/$D8*100,"")
A43: Administrationsomk. | B43: =IFERROR(B9/$D9*100,"") | C43: =IFERROR(C9/$D9*100,"") | D43: =IFERROR(D9/$D9*100,"")
A44: Andre driftsomkostninger | B44: =IFERROR(B11/$D11*100,"") | C44: =IFERROR(C11/$D11*100,"") | D44: =IFERROR(D11/$D11*100,"")
A46: Indekstal for kapitaltilpasningsevne (2023=100)
A47: Bruttofortjeneste | B47: =IFERROR(B7*100/$D7,"") | C47: =IFERROR(C7*100/$D7,"") | D47: =IFERROR(D7*100/$D7,"")
A48: Anlægsaktiver | B48: =IFERROR(B18*100/$D18,"") | C48: =IFERROR(C18*100/$D18,"") | D48: =IFERROR(D18*100/$D18,"")
A49: Varebeholdninger | B49: =IFERROR(B27*100/$D27,"") | C49: =IFERROR(C27*100/$D27,"") | D49: =IFERROR(D27*100/$D27,"")
A50: Tilgodehavender fra salg | B50: =IFERROR(B28*100/$D28,"") | C50: =IFERROR(C28*100/$D28,"") | D50: =IFERROR(D28*100/$D28,"")
A52: Soliditet og likviditet
A53: Soliditetsgrad, % | B53: =IFERROR(B22*100/B20,"") | C53: =IFERROR(C22*100/C20,"") | D53: =IFERROR(D22*100/D20,"")
A54: Gældsandel, % | B54: =IFERROR(B23*100/B20,"") | C54: =IFERROR(C23*100/C20,"") | D54: =IFERROR(D23*100/D20,"")
A55: Likviditetsgrad, % | B55: =IFERROR(B19*100/B29,"") | C55: =IFERROR(C19*100/C29,"") | D55: =IFERROR(D19*100/D29,"")
A57: Kilde: Bearbejdet uddrag af årsrapporter for 2023-2025. Alle dataceller er live formler der peger på res_raw / balance_raw.
A59: Krydstjek mod rådata (tolerance: 1 t.kr.)
A60: Aktiver i alt = fsa:Assets | B60: =IF('balance_raw_32441483'!$F$31="","—",IF(ABS(B20-'balance_raw_32441483'!$F$31)<=1,"✓ OK","❌ "&TEXT(B20-'balance_raw_32441483'!$F$31,"+#,##0;-#,##0")&" t.kr.")) | C60: =IF('balance_raw_32441483'!$E$31="","—",IF(ABS(C20-'balance_raw_32441483'!$E$31)<=1,"✓ OK","❌ "&TEXT(C20-'balance_raw_32441483'!$E$31,"+#,##0;-#,##0")&" t.kr.")) | D60: =IF('balance_raw_32441483'!$D$31="","—",IF(ABS(D20-'balance_raw_32441483'!$D$31)<=1,"✓ OK","❌ "&TEXT(D20-'balance_raw_32441483'!$D$31,"+#,##0;-#,##0")&" t.kr.")) | F60: Verificerer at sum(Anlæg+Omsætning) matcher Assets-totalen.
A61: Passiver i alt = fsa:LiabilitiesAndEquity | B61: =IF('balance_raw_32441483'!$F$58="","—",IF(ABS(B24-'balance_raw_32441483'!$F$58)<=1,"✓ OK","❌ "&TEXT(B24-'balance_raw_32441483'!$F$58,"+#,##0;-#,##0")&" t.kr.")) | C61: =IF('balance_raw_32441483'!$E$58="","—",IF(ABS(C24-'balance_raw_32441483'!$E$58)<=1,"✓ OK","❌ "&TEXT(C24-'balance_raw_32441483'!$E$58,"+#,##0;-#,##0")&" t.kr.")) | D61: =IF('balance_raw_32441483'!$D$58="","—",IF(ABS(D24-'balance_raw_32441483'!$D$58)<=1,"✓ OK","❌ "&TEXT(D24-'balance_raw_32441483'!$D$58,"+#,##0;-#,##0")&" t.kr.")) | F61: Verificerer at sum(EK+Forpligtelser) matcher Passiver-totalen.
A62: Aktiver i alt = Passiver i alt | B62: =IF(ABS(B20-B24)<=1,"✓ OK","❌ "&TEXT(B20-B24,"+#,##0;-#,##0")&" t.kr.") | C62: =IF(ABS(C20-C24)<=1,"✓ OK","❌ "&TEXT(C20-C24,"+#,##0;-#,##0")&" t.kr.") | D62: =IF(ABS(D20-D24)<=1,"✓ OK","❌ "&TEXT(D20-D24,"+#,##0;-#,##0")&" t.kr.") | F62: Balance-identitet på arket selv. Skal altid være 0 differance.
A63: Bruttoresultat (beregnet) = fsa:GrossResult | B63: =IF('res_raw_32441483'!$F$4="","—",IF(ABS(B7-'res_raw_32441483'!$F$4)<=1,"✓ OK","❌ "&TEXT(B7-'res_raw_32441483'!$F$4,"+#,##0;-#,##0")&" t.kr.")) | C63: =IF('res_raw_32441483'!$E$4="","—",IF(ABS(C7-'res_raw_32441483'!$E$4)<=1,"✓ OK","❌ "&TEXT(C7-'res_raw_32441483'!$E$4,"+#,##0;-#,##0")&" t.kr.")) | D63: =IF('res_raw_32441483'!$D$4="","—",IF(ABS(D7-'res_raw_32441483'!$D$4)<=1,"✓ OK","❌ "&TEXT(D7-'res_raw_32441483'!$D$4,"+#,##0;-#,##0")&" t.kr.")) | F63: Hvis Nettoomsætning eller omkostninger mangler, vil sumberegnet bruttoresultat afvige.
A64: EBIT (beregnet) = fsa:ProfitLossFromOrdinaryOperatingActivities | B64: =IF('res_raw_32441483'!$F$9="","—",IF(ABS(B12-'res_raw_32441483'!$F$9)<=1,"✓ OK","❌ "&TEXT(B12-'res_raw_32441483'!$F$9,"+#,##0;-#,##0")&" t.kr.")) | C64: =IF('res_raw_32441483'!$E$9="","—",IF(ABS(C12-'res_raw_32441483'!$E$9)<=1,"✓ OK","❌ "&TEXT(C12-'res_raw_32441483'!$E$9,"+#,##0;-#,##0")&" t.kr.")) | D64: =IF('res_raw_32441483'!$D$9="","—",IF(ABS(D12-'res_raw_32441483'!$D$9)<=1,"✓ OK","❌ "&TEXT(D12-'res_raw_32441483'!$D$9,"+#,##0;-#,##0")&" t.kr.")) | F64: Verificerer at sumberegnet EBIT matcher det rapporterede.
A65: EBT (beregnet) = fsa:ProfitLossFromOrdinaryActivitiesBeforeTax | B65: =IF('res_raw_32441483'!$F$14="","—",IF(ABS(B15-'res_raw_32441483'!$F$14)<=1,"✓ OK","❌ "&TEXT(B15-'res_raw_32441483'!$F$14,"+#,##0;-#,##0")&" t.kr.")) | C65: =IF('res_raw_32441483'!$E$14="","—",IF(ABS(C15-'res_raw_32441483'!$E$14)<=1,"✓ OK","❌ "&TEXT(C15-'res_raw_32441483'!$E$14,"+#,##0;-#,##0")&" t.kr.")) | D65: =IF('res_raw_32441483'!$D$14="","—",IF(ABS(D15-'res_raw_32441483'!$D$14)<=1,"✓ OK","❌ "&TEXT(D15-'res_raw_32441483'!$D$14,"+#,##0;-#,##0")&" t.kr.")) | F65: Verificerer at sumberegnet resultat før skat matcher det rapporterede.

Sheet Noter_info
A1: Hatting A/S (CVR 32441483) — Ukendte XBRL-felter — disse er noter og ikke en del af hoved-regnskabet
A2: Kategori | B2: Dansk navn | C2: XBRL feltnavn | D2: 2021 t.kr. | E2: 2022 t.kr. | F2: 2023 t.kr. | G2: 2024 t.kr. | H2: 2025 t.kr. | I2: Forklaring
A3: Øvrige (ukendt) | B3: fsa:ReserveForCurrentValueAdjustmentsOfCurrencyGains | C3: fsa:ReserveForCurrentValueAdjustmentsOfCurrencyGains | F3: 0 | G3: -3 | I3: Ingen forklaring tilgængelig.
