Workbook

Sheet Overblik_33034482
A1: Danske Lotteri Spil A/S (CVR 33034482) — Regnskabsanalyse – Resultatopgørelse & Balance (t.kr.) · Revision
H2: Indekstal (2021=100)
A3: Resultatopgørelse t.kr. | B3: 2021 | C3: 2022 | D3: 2023 | E3: 2024 | F3: 2025 | H3: 2021 | I3: 2022 | J3: 2023 | K3: 2024 | L3: 2025
A4: Nettoomsætning | B4: ='res_raw_33034482'!$B$2 | C4: ='res_raw_33034482'!$C$2 | D4: ='res_raw_33034482'!$D$2 | E4: ='res_raw_33034482'!$E$2 | F4: ='res_raw_33034482'!$F$2 | H4: =IFERROR(B4/$B$4*100,"") | I4: =IFERROR(C4/$B$4*100,"") | J4: =IFERROR(D4/$B$4*100,"") | K4: =IFERROR(E4/$B$4*100,"") | L4: =IFERROR(F4/$B$4*100,"")
A5: Andre driftsindtægter | B5: ='res_raw_33034482'!$B$3 | C5: ='res_raw_33034482'!$C$3 | D5: ='res_raw_33034482'!$D$3 | E5: ='res_raw_33034482'!$E$3 | F5: ='res_raw_33034482'!$F$3 | H5: =IFERROR(B5/$B$5*100,"") | I5: =IFERROR(C5/$B$5*100,"") | J5: =IFERROR(D5/$B$5*100,"") | K5: =IFERROR(E5/$B$5*100,"") | L5: =IFERROR(F5/$B$5*100,"")
A6: Vareforbrug | B6: ='res_raw_33034482'!$B$4 | C6: ='res_raw_33034482'!$C$4 | D6: ='res_raw_33034482'!$D$4 | E6: ='res_raw_33034482'!$E$4 | F6: ='res_raw_33034482'!$F$4 | H6: =IFERROR(B6/$B$6*100,"") | I6: =IFERROR(C6/$B$6*100,"") | J6: =IFERROR(D6/$B$6*100,"") | K6: =IFERROR(E6/$B$6*100,"") | L6: =IFERROR(F6/$B$6*100,"")
A7: Andre eksterne omkostninger | B7: ='res_raw_33034482'!$B$5 | C7: ='res_raw_33034482'!$C$5 | D7: ='res_raw_33034482'!$D$5 | E7: ='res_raw_33034482'!$E$5 | F7: ='res_raw_33034482'!$F$5 | H7: =IFERROR(B7/$B$7*100,"") | I7: =IFERROR(C7/$B$7*100,"") | J7: =IFERROR(D7/$B$7*100,"") | K7: =IFERROR(E7/$B$7*100,"") | L7: =IFERROR(F7/$B$7*100,"")
A8: Bruttoresultat | B8: ='res_raw_33034482'!$B$6 | C8: ='res_raw_33034482'!$C$6 | D8: ='res_raw_33034482'!$D$6 | E8: ='res_raw_33034482'!$E$6 | F8: ='res_raw_33034482'!$F$6 | H8: =IFERROR(B8/$B$8*100,"") | I8: =IFERROR(C8/$B$8*100,"") | J8: =IFERROR(D8/$B$8*100,"") | K8: =IFERROR(E8/$B$8*100,"") | L8: =IFERROR(F8/$B$8*100,"")
A9: Personaleomkostninger | B9: ='res_raw_33034482'!$B$7 | C9: ='res_raw_33034482'!$C$7 | D9: ='res_raw_33034482'!$D$7 | E9: ='res_raw_33034482'!$E$7 | F9: ='res_raw_33034482'!$F$7 | H9: =IFERROR(B9/$B$9*100,"") | I9: =IFERROR(C9/$B$9*100,"") | J9: =IFERROR(D9/$B$9*100,"") | K9: =IFERROR(E9/$B$9*100,"") | L9: =IFERROR(F9/$B$9*100,"")
A10: Resultat før afskrivninger | B10: =IFERROR($B$8-ABS($B$9),"") | C10: =IFERROR($C$8-ABS($C$9),"") | D10: =IFERROR($D$8-ABS($D$9),"") | E10: =IFERROR($E$8-ABS($E$9),"") | F10: =IFERROR($F$8-ABS($F$9),"") | H10: =IFERROR(B10/$B$10*100,"") | I10: =IFERROR(C10/$B$10*100,"") | J10: =IFERROR(D10/$B$10*100,"") | K10: =IFERROR(E10/$B$10*100,"") | L10: =IFERROR(F10/$B$10*100,"")
A11: Af- og nedskrivninger | B11: ='res_raw_33034482'!$B$9 | C11: ='res_raw_33034482'!$C$9 | D11: ='res_raw_33034482'!$D$9 | E11: ='res_raw_33034482'!$E$9 | F11: ='res_raw_33034482'!$F$9 | H11: =IFERROR(B11/$B$11*100,"") | I11: =IFERROR(C11/$B$11*100,"") | J11: =IFERROR(D11/$B$11*100,"") | K11: =IFERROR(E11/$B$11*100,"") | L11: =IFERROR(F11/$B$11*100,"")
A12: Andre driftsomkostninger | B12: ='res_raw_33034482'!$B$10 | C12: ='res_raw_33034482'!$C$10 | D12: ='res_raw_33034482'!$D$10 | E12: ='res_raw_33034482'!$E$10 | F12: ='res_raw_33034482'!$F$10 | H12: =IFERROR(B12/$B$12*100,"") | I12: =IFERROR(C12/$B$12*100,"") | J12: =IFERROR(D12/$B$12*100,"") | K12: =IFERROR(E12/$B$12*100,"") | L12: =IFERROR(F12/$B$12*100,"")
A13: Resultat af primær drift | B13: ='res_raw_33034482'!$B$11 | C13: ='res_raw_33034482'!$C$11 | D13: ='res_raw_33034482'!$D$11 | E13: ='res_raw_33034482'!$E$11 | F13: ='res_raw_33034482'!$F$11 | H13: =IFERROR(B13/$B$13*100,"") | I13: =IFERROR(C13/$B$13*100,"") | J13: =IFERROR(D13/$B$13*100,"") | K13: =IFERROR(E13/$B$13*100,"") | L13: =IFERROR(F13/$B$13*100,"")
A14: Indtægter af kapitalandele, dattervirksomheder | B14: ='res_raw_33034482'!$B$12 | C14: ='res_raw_33034482'!$C$12 | D14: ='res_raw_33034482'!$D$12 | E14: ='res_raw_33034482'!$E$12 | F14: ='res_raw_33034482'!$F$12 | H14: =IFERROR(B14/$B$14*100,"") | I14: =IFERROR(C14/$B$14*100,"") | J14: =IFERROR(D14/$B$14*100,"") | K14: =IFERROR(E14/$B$14*100,"") | L14: =IFERROR(F14/$B$14*100,"")
A15: Finansielle indtægter | B15: ='res_raw_33034482'!$B$13 | C15: ='res_raw_33034482'!$C$13 | D15: ='res_raw_33034482'!$D$13 | E15: ='res_raw_33034482'!$E$13 | F15: ='res_raw_33034482'!$F$13 | H15: =IFERROR(B15/$B$15*100,"") | I15: =IFERROR(C15/$B$15*100,"") | J15: =IFERROR(D15/$B$15*100,"") | K15: =IFERROR(E15/$B$15*100,"") | L15: =IFERROR(F15/$B$15*100,"")
A16: Finansielle omkostninger | B16: ='res_raw_33034482'!$B$14 | C16: ='res_raw_33034482'!$C$14 | D16: ='res_raw_33034482'!$D$14 | E16: ='res_raw_33034482'!$E$14 | F16: ='res_raw_33034482'!$F$14 | H16: =IFERROR(B16/$B$16*100,"") | I16: =IFERROR(C16/$B$16*100,"") | J16: =IFERROR(D16/$B$16*100,"") | K16: =IFERROR(E16/$B$16*100,"") | L16: =IFERROR(F16/$B$16*100,"")
A17: Finansielle poster, netto | B17: ='res_raw_33034482'!$B$15 | C17: ='res_raw_33034482'!$C$15 | D17: ='res_raw_33034482'!$D$15 | E17: ='res_raw_33034482'!$E$15 | F17: ='res_raw_33034482'!$F$15 | H17: =IFERROR(B17/$B$17*100,"") | I17: =IFERROR(C17/$B$17*100,"") | J17: =IFERROR(D17/$B$17*100,"") | K17: =IFERROR(E17/$B$17*100,"") | L17: =IFERROR(F17/$B$17*100,"")
A18: Resultat før skat | B18: ='res_raw_33034482'!$B$16 | C18: ='res_raw_33034482'!$C$16 | D18: ='res_raw_33034482'!$D$16 | E18: ='res_raw_33034482'!$E$16 | F18: ='res_raw_33034482'!$F$16 | H18: =IFERROR(B18/$B$18*100,"") | I18: =IFERROR(C18/$B$18*100,"") | J18: =IFERROR(D18/$B$18*100,"") | K18: =IFERROR(E18/$B$18*100,"") | L18: =IFERROR(F18/$B$18*100,"")
A19: Skat af årets resultat | B19: ='res_raw_33034482'!$B$17 | C19: ='res_raw_33034482'!$C$17 | D19: ='res_raw_33034482'!$D$17 | E19: ='res_raw_33034482'!$E$17 | F19: ='res_raw_33034482'!$F$17 | H19: =IFERROR(B19/$B$19*100,"") | I19: =IFERROR(C19/$B$19*100,"") | J19: =IFERROR(D19/$B$19*100,"") | K19: =IFERROR(E19/$B$19*100,"") | L19: =IFERROR(F19/$B$19*100,"")
A20: Årets resultat | B20: ='res_raw_33034482'!$B$18 | C20: ='res_raw_33034482'!$C$18 | D20: ='res_raw_33034482'!$D$18 | E20: ='res_raw_33034482'!$E$18 | F20: ='res_raw_33034482'!$F$18 | H20: =IFERROR(B20/$B$20*100,"") | I20: =IFERROR(C20/$B$20*100,"") | J20: =IFERROR(D20/$B$20*100,"") | K20: =IFERROR(E20/$B$20*100,"") | L20: =IFERROR(F20/$B$20*100,"")
A22: AKTIVER t.kr. | B22: 2021 | C22: 2022 | D22: 2023 | E22: 2024 | F22: 2025 | H22: 2021 | I22: 2022 | J22: 2023 | K22: 2024 | L22: 2025
A23: Udviklingsprojekter | B23: ='balance_raw_33034482'!$B$2 | C23: ='balance_raw_33034482'!$C$2 | D23: ='balance_raw_33034482'!$D$2 | E23: ='balance_raw_33034482'!$E$2 | F23: ='balance_raw_33034482'!$F$2 | H23: =IFERROR(B23/$B$23*100,"") | I23: =IFERROR(C23/$B$23*100,"") | J23: =IFERROR(D23/$B$23*100,"") | K23: =IFERROR(E23/$B$23*100,"") | L23: =IFERROR(F23/$B$23*100,"")
A24: Patenter, varemærker mv. | B24: ='balance_raw_33034482'!$B$3 | C24: ='balance_raw_33034482'!$C$3 | D24: ='balance_raw_33034482'!$D$3 | E24: ='balance_raw_33034482'!$E$3 | F24: ='balance_raw_33034482'!$F$3 | H24: =IFERROR(B24/$B$24*100,"") | I24: =IFERROR(C24/$B$24*100,"") | J24: =IFERROR(D24/$B$24*100,"") | K24: =IFERROR(E24/$B$24*100,"") | L24: =IFERROR(F24/$B$24*100,"")
A25: Goodwill | B25: ='balance_raw_33034482'!$B$4 | C25: ='balance_raw_33034482'!$C$4 | D25: ='balance_raw_33034482'!$D$4 | E25: ='balance_raw_33034482'!$E$4 | F25: ='balance_raw_33034482'!$F$4 | H25: =IFERROR(B25/$B$25*100,"") | I25: =IFERROR(C25/$B$25*100,"") | J25: =IFERROR(D25/$B$25*100,"") | K25: =IFERROR(E25/$B$25*100,"") | L25: =IFERROR(F25/$B$25*100,"")
A26: Immaterielle anlægsaktiver | B26: ='balance_raw_33034482'!$B$5 | C26: ='balance_raw_33034482'!$C$5 | D26: ='balance_raw_33034482'!$D$5 | E26: ='balance_raw_33034482'!$E$5 | F26: ='balance_raw_33034482'!$F$5 | H26: =IFERROR(B26/$B$26*100,"") | I26: =IFERROR(C26/$B$26*100,"") | J26: =IFERROR(D26/$B$26*100,"") | K26: =IFERROR(E26/$B$26*100,"") | L26: =IFERROR(F26/$B$26*100,"")
A27: Materielle anlægsaktiver | B27: ='balance_raw_33034482'!$B$6 | C27: ='balance_raw_33034482'!$C$6 | D27: ='balance_raw_33034482'!$D$6 | E27: ='balance_raw_33034482'!$E$6 | F27: ='balance_raw_33034482'!$F$6 | H27: =IFERROR(B27/$B$27*100,"") | I27: =IFERROR(C27/$B$27*100,"") | J27: =IFERROR(D27/$B$27*100,"") | K27: =IFERROR(E27/$B$27*100,"") | L27: =IFERROR(F27/$B$27*100,"")
A28: Kapitalandele, dattervirksomheder | B28: ='balance_raw_33034482'!$B$7 | C28: ='balance_raw_33034482'!$C$7 | D28: ='balance_raw_33034482'!$D$7 | E28: ='balance_raw_33034482'!$E$7 | F28: ='balance_raw_33034482'!$F$7 | H28: =IFERROR(B28/$B$28*100,"") | I28: =IFERROR(C28/$B$28*100,"") | J28: =IFERROR(D28/$B$28*100,"") | K28: =IFERROR(E28/$B$28*100,"") | L28: =IFERROR(F28/$B$28*100,"")
A29: Deposita | B29: ='balance_raw_33034482'!$B$8 | C29: ='balance_raw_33034482'!$C$8 | D29: ='balance_raw_33034482'!$D$8 | E29: ='balance_raw_33034482'!$E$8 | F29: ='balance_raw_33034482'!$F$8 | H29: =IFERROR(B29/$B$29*100,"") | I29: =IFERROR(C29/$B$29*100,"") | J29: =IFERROR(D29/$B$29*100,"") | K29: =IFERROR(E29/$B$29*100,"") | L29: =IFERROR(F29/$B$29*100,"")
A30: Finansielle anlægsaktiver | B30: ='balance_raw_33034482'!$B$9 | C30: ='balance_raw_33034482'!$C$9 | D30: ='balance_raw_33034482'!$D$9 | E30: ='balance_raw_33034482'!$E$9 | F30: ='balance_raw_33034482'!$F$9 | H30: =IFERROR(B30/$B$30*100,"") | I30: =IFERROR(C30/$B$30*100,"") | J30: =IFERROR(D30/$B$30*100,"") | K30: =IFERROR(E30/$B$30*100,"") | L30: =IFERROR(F30/$B$30*100,"")
A31: Anlægsaktiver | B31: ='balance_raw_33034482'!$B$10 | C31: ='balance_raw_33034482'!$C$10 | D31: ='balance_raw_33034482'!$D$10 | E31: ='balance_raw_33034482'!$E$10 | F31: ='balance_raw_33034482'!$F$10 | H31: =IFERROR(B31/$B$31*100,"") | I31: =IFERROR(C31/$B$31*100,"") | J31: =IFERROR(D31/$B$31*100,"") | K31: =IFERROR(E31/$B$31*100,"") | L31: =IFERROR(F31/$B$31*100,"")
A32: Varebeholdninger | B32: ='balance_raw_33034482'!$B$11 | C32: ='balance_raw_33034482'!$C$11 | D32: ='balance_raw_33034482'!$D$11 | E32: ='balance_raw_33034482'!$E$11 | F32: ='balance_raw_33034482'!$F$11 | H32: =IFERROR(B32/$B$32*100,"") | I32: =IFERROR(C32/$B$32*100,"") | J32: =IFERROR(D32/$B$32*100,"") | K32: =IFERROR(E32/$B$32*100,"") | L32: =IFERROR(F32/$B$32*100,"")
A33: Tilgodehavender fra salg og tjenesteydelser | B33: ='balance_raw_33034482'!$B$12 | C33: ='balance_raw_33034482'!$C$12 | D33: ='balance_raw_33034482'!$D$12 | E33: ='balance_raw_33034482'!$E$12 | F33: ='balance_raw_33034482'!$F$12 | H33: =IFERROR(B33/$B$33*100,"") | I33: =IFERROR(C33/$B$33*100,"") | J33: =IFERROR(D33/$B$33*100,"") | K33: =IFERROR(E33/$B$33*100,"") | L33: =IFERROR(F33/$B$33*100,"")
A34: Tilgodehavender hos tilknyttede virksomheder | B34: ='balance_raw_33034482'!$B$13 | C34: ='balance_raw_33034482'!$C$13 | D34: ='balance_raw_33034482'!$D$13 | E34: ='balance_raw_33034482'!$E$13 | F34: ='balance_raw_33034482'!$F$13 | H34: =IFERROR(B34/$B$34*100,"") | I34: =IFERROR(C34/$B$34*100,"") | J34: =IFERROR(D34/$B$34*100,"") | K34: =IFERROR(E34/$B$34*100,"") | L34: =IFERROR(F34/$B$34*100,"")
A35: Andre tilgodehavender | B35: ='balance_raw_33034482'!$B$14 | C35: ='balance_raw_33034482'!$C$14 | D35: ='balance_raw_33034482'!$D$14 | E35: ='balance_raw_33034482'!$E$14 | F35: ='balance_raw_33034482'!$F$14 | H35: =IFERROR(B35/$B$35*100,"") | I35: =IFERROR(C35/$B$35*100,"") | J35: =IFERROR(D35/$B$35*100,"") | K35: =IFERROR(E35/$B$35*100,"") | L35: =IFERROR(F35/$B$35*100,"")
A36: Periodeafgrænsningsposter (aktiver) | B36: ='balance_raw_33034482'!$B$15 | C36: ='balance_raw_33034482'!$C$15 | D36: ='balance_raw_33034482'!$D$15 | E36: ='balance_raw_33034482'!$E$15 | F36: ='balance_raw_33034482'!$F$15 | H36: =IFERROR(B36/$B$36*100,"") | I36: =IFERROR(C36/$B$36*100,"") | J36: =IFERROR(D36/$B$36*100,"") | K36: =IFERROR(E36/$B$36*100,"") | L36: =IFERROR(F36/$B$36*100,"")
A37: Udskudt skatteaktiv | B37: ='balance_raw_33034482'!$B$16 | C37: ='balance_raw_33034482'!$C$16 | D37: ='balance_raw_33034482'!$D$16 | E37: ='balance_raw_33034482'!$E$16 | F37: ='balance_raw_33034482'!$F$16 | H37: =IFERROR(B37/$B$37*100,"") | I37: =IFERROR(C37/$B$37*100,"") | J37: =IFERROR(D37/$B$37*100,"") | K37: =IFERROR(E37/$B$37*100,"") | L37: =IFERROR(F37/$B$37*100,"")
A38: Tilgodehavende skat hos tilknyttede virksomheder | B38: ='balance_raw_33034482'!$B$17 | C38: ='balance_raw_33034482'!$C$17 | D38: ='balance_raw_33034482'!$D$17 | E38: ='balance_raw_33034482'!$E$17 | F38: ='balance_raw_33034482'!$F$17 | H38: =IFERROR(B38/$B$38*100,"") | I38: =IFERROR(C38/$B$38*100,"") | J38: =IFERROR(D38/$B$38*100,"") | K38: =IFERROR(E38/$B$38*100,"") | L38: =IFERROR(F38/$B$38*100,"")
A39: Kortfristede skattetilgodehavender | B39: ='balance_raw_33034482'!$B$18 | C39: ='balance_raw_33034482'!$C$18 | D39: ='balance_raw_33034482'!$D$18 | E39: ='balance_raw_33034482'!$E$18 | F39: ='balance_raw_33034482'!$F$18 | H39: =IFERROR(B39/$B$39*100,"") | I39: =IFERROR(C39/$B$39*100,"") | J39: =IFERROR(D39/$B$39*100,"") | K39: =IFERROR(E39/$B$39*100,"") | L39: =IFERROR(F39/$B$39*100,"")
A40: Tilgodehavender | B40: ='balance_raw_33034482'!$B$19 | C40: ='balance_raw_33034482'!$C$19 | D40: ='balance_raw_33034482'!$D$19 | E40: ='balance_raw_33034482'!$E$19 | F40: ='balance_raw_33034482'!$F$19 | H40: =IFERROR(B40/$B$40*100,"") | I40: =IFERROR(C40/$B$40*100,"") | J40: =IFERROR(D40/$B$40*100,"") | K40: =IFERROR(E40/$B$40*100,"") | L40: =IFERROR(F40/$B$40*100,"")
A41: Værdipapirer | B41: ='balance_raw_33034482'!$B$20 | C41: ='balance_raw_33034482'!$C$20 | D41: ='balance_raw_33034482'!$D$20 | E41: ='balance_raw_33034482'!$E$20 | F41: ='balance_raw_33034482'!$F$20 | H41: =IFERROR(B41/$B$41*100,"") | I41: =IFERROR(C41/$B$41*100,"") | J41: =IFERROR(D41/$B$41*100,"") | K41: =IFERROR(E41/$B$41*100,"") | L41: =IFERROR(F41/$B$41*100,"")
A42: Likvide beholdninger | B42: ='balance_raw_33034482'!$B$21 | C42: ='balance_raw_33034482'!$C$21 | D42: ='balance_raw_33034482'!$D$21 | E42: ='balance_raw_33034482'!$E$21 | F42: ='balance_raw_33034482'!$F$21 | H42: =IFERROR(B42/$B$42*100,"") | I42: =IFERROR(C42/$B$42*100,"") | J42: =IFERROR(D42/$B$42*100,"") | K42: =IFERROR(E42/$B$42*100,"") | L42: =IFERROR(F42/$B$42*100,"")
A43: Omsætningsaktiver | B43: ='balance_raw_33034482'!$B$22 | C43: ='balance_raw_33034482'!$C$22 | D43: ='balance_raw_33034482'!$D$22 | E43: ='balance_raw_33034482'!$E$22 | F43: ='balance_raw_33034482'!$F$22 | H43: =IFERROR(B43/$B$43*100,"") | I43: =IFERROR(C43/$B$43*100,"") | J43: =IFERROR(D43/$B$43*100,"") | K43: =IFERROR(E43/$B$43*100,"") | L43: =IFERROR(F43/$B$43*100,"")
A44: Aktiver | B44: ='balance_raw_33034482'!$B$23 | C44: ='balance_raw_33034482'!$C$23 | D44: ='balance_raw_33034482'!$D$23 | E44: ='balance_raw_33034482'!$E$23 | F44: ='balance_raw_33034482'!$F$23 | H44: =IFERROR(B44/$B$44*100,"") | I44: =IFERROR(C44/$B$44*100,"") | J44: =IFERROR(D44/$B$44*100,"") | K44: =IFERROR(E44/$B$44*100,"") | L44: =IFERROR(F44/$B$44*100,"")
A46: PASSIVER t.kr. | B46: 2021 | C46: 2022 | D46: 2023 | E46: 2024 | F46: 2025 | H46: 2021 | I46: 2022 | J46: 2023 | K46: 2024 | L46: 2025
A47: Selskabskapital | B47: ='balance_raw_33034482'!$B$24 | C47: ='balance_raw_33034482'!$C$24 | D47: ='balance_raw_33034482'!$D$24 | E47: ='balance_raw_33034482'!$E$24 | F47: ='balance_raw_33034482'!$F$24 | H47: =IFERROR(B47/$B$47*100,"") | I47: =IFERROR(C47/$B$47*100,"") | J47: =IFERROR(D47/$B$47*100,"") | K47: =IFERROR(E47/$B$47*100,"") | L47: =IFERROR(F47/$B$47*100,"")
A48: Reserve for nettoopskrivning (indre værdis metode) | B48: ='balance_raw_33034482'!$B$25 | C48: ='balance_raw_33034482'!$C$25 | D48: ='balance_raw_33034482'!$D$25 | E48: ='balance_raw_33034482'!$E$25 | F48: ='balance_raw_33034482'!$F$25 | H48: =IFERROR(B48/$B$48*100,"") | I48: =IFERROR(C48/$B$48*100,"") | J48: =IFERROR(D48/$B$48*100,"") | K48: =IFERROR(E48/$B$48*100,"") | L48: =IFERROR(F48/$B$48*100,"")
A49: Reserve for udviklingsomkostninger | B49: ='balance_raw_33034482'!$B$26 | C49: ='balance_raw_33034482'!$C$26 | D49: ='balance_raw_33034482'!$D$26 | E49: ='balance_raw_33034482'!$E$26 | F49: ='balance_raw_33034482'!$F$26 | H49: =IFERROR(B49/$B$49*100,"") | I49: =IFERROR(C49/$B$49*100,"") | J49: =IFERROR(D49/$B$49*100,"") | K49: =IFERROR(E49/$B$49*100,"") | L49: =IFERROR(F49/$B$49*100,"")
A50: Reserve for sikringstransaktioner | B50: ='balance_raw_33034482'!$B$27 | C50: ='balance_raw_33034482'!$C$27 | D50: ='balance_raw_33034482'!$D$27 | E50: ='balance_raw_33034482'!$E$27 | F50: ='balance_raw_33034482'!$F$27 | H50: =IFERROR(B50/$B$50*100,"") | I50: =IFERROR(C50/$B$50*100,"") | J50: =IFERROR(D50/$B$50*100,"") | K50: =IFERROR(E50/$B$50*100,"") | L50: =IFERROR(F50/$B$50*100,"")
A51: Andre reserver | B51: ='balance_raw_33034482'!$B$28 | C51: ='balance_raw_33034482'!$C$28 | D51: ='balance_raw_33034482'!$D$28 | E51: ='balance_raw_33034482'!$E$28 | F51: ='balance_raw_33034482'!$F$28 | H51: =IFERROR(B51/$B$51*100,"") | I51: =IFERROR(C51/$B$51*100,"") | J51: =IFERROR(D51/$B$51*100,"") | K51: =IFERROR(E51/$B$51*100,"") | L51: =IFERROR(F51/$B$51*100,"")
A52: Overført resultat | B52: ='balance_raw_33034482'!$B$29 | C52: ='balance_raw_33034482'!$C$29 | D52: ='balance_raw_33034482'!$D$29 | E52: ='balance_raw_33034482'!$E$29 | F52: ='balance_raw_33034482'!$F$29 | H52: =IFERROR(B52/$B$52*100,"") | I52: =IFERROR(C52/$B$52*100,"") | J52: =IFERROR(D52/$B$52*100,"") | K52: =IFERROR(E52/$B$52*100,"") | L52: =IFERROR(F52/$B$52*100,"")
A53: Egenkapital i alt | B53: ='balance_raw_33034482'!$B$30 | C53: ='balance_raw_33034482'!$C$30 | D53: ='balance_raw_33034482'!$D$30 | E53: ='balance_raw_33034482'!$E$30 | F53: ='balance_raw_33034482'!$F$30 | H53: =IFERROR(B53/$B$53*100,"") | I53: =IFERROR(C53/$B$53*100,"") | J53: =IFERROR(D53/$B$53*100,"") | K53: =IFERROR(E53/$B$53*100,"") | L53: =IFERROR(F53/$B$53*100,"")
A54: Hensættelse til udskudt skat | B54: ='balance_raw_33034482'!$B$31 | C54: ='balance_raw_33034482'!$C$31 | D54: ='balance_raw_33034482'!$D$31 | E54: ='balance_raw_33034482'!$E$31 | F54: ='balance_raw_33034482'!$F$31 | H54: =IFERROR(B54/$B$54*100,"") | I54: =IFERROR(C54/$B$54*100,"") | J54: =IFERROR(D54/$B$54*100,"") | K54: =IFERROR(E54/$B$54*100,"") | L54: =IFERROR(F54/$B$54*100,"")
A55: Hensatte forpligtelser | B55: ='balance_raw_33034482'!$B$32 | C55: ='balance_raw_33034482'!$C$32 | D55: ='balance_raw_33034482'!$D$32 | E55: ='balance_raw_33034482'!$E$32 | F55: ='balance_raw_33034482'!$F$32 | H55: =IFERROR(B55/$B$55*100,"") | I55: =IFERROR(C55/$B$55*100,"") | J55: =IFERROR(D55/$B$55*100,"") | K55: =IFERROR(E55/$B$55*100,"") | L55: =IFERROR(F55/$B$55*100,"")
A56: Langfristede gældsforpligtelser | B56: ='balance_raw_33034482'!$B$33 | C56: ='balance_raw_33034482'!$C$33 | D56: ='balance_raw_33034482'!$D$33 | E56: ='balance_raw_33034482'!$E$33 | F56: ='balance_raw_33034482'!$F$33 | H56: =IFERROR(B56/$B$56*100,"") | I56: =IFERROR(C56/$B$56*100,"") | J56: =IFERROR(D56/$B$56*100,"") | K56: =IFERROR(E56/$B$56*100,"") | L56: =IFERROR(F56/$B$56*100,"")
A57: Ansvarlig lånekapital (kortfristet) | B57: ='balance_raw_33034482'!$B$34 | C57: ='balance_raw_33034482'!$C$34 | D57: ='balance_raw_33034482'!$D$34 | E57: ='balance_raw_33034482'!$E$34 | F57: ='balance_raw_33034482'!$F$34 | H57: =IFERROR(B57/$B$57*100,"") | I57: =IFERROR(C57/$B$57*100,"") | J57: =IFERROR(D57/$B$57*100,"") | K57: =IFERROR(E57/$B$57*100,"") | L57: =IFERROR(F57/$B$57*100,"")
A58: Kortfristet del af langfristede gældsforpligtelser | B58: ='balance_raw_33034482'!$B$35 | C58: ='balance_raw_33034482'!$C$35 | D58: ='balance_raw_33034482'!$D$35 | E58: ='balance_raw_33034482'!$E$35 | F58: ='balance_raw_33034482'!$F$35 | H58: =IFERROR(B58/$B$58*100,"") | I58: =IFERROR(C58/$B$58*100,"") | J58: =IFERROR(D58/$B$58*100,"") | K58: =IFERROR(E58/$B$58*100,"") | L58: =IFERROR(F58/$B$58*100,"")
A59: Kreditinstitutter | B59: ='balance_raw_33034482'!$B$36 | C59: ='balance_raw_33034482'!$C$36 | D59: ='balance_raw_33034482'!$D$36 | E59: ='balance_raw_33034482'!$E$36 | F59: ='balance_raw_33034482'!$F$36 | H59: =IFERROR(B59/$B$59*100,"") | I59: =IFERROR(C59/$B$59*100,"") | J59: =IFERROR(D59/$B$59*100,"") | K59: =IFERROR(E59/$B$59*100,"") | L59: =IFERROR(F59/$B$59*100,"")
A60: Leasingforpligtelser (kortfristet) | B60: ='balance_raw_33034482'!$B$37 | C60: ='balance_raw_33034482'!$C$37 | D60: ='balance_raw_33034482'!$D$37 | E60: ='balance_raw_33034482'!$E$37 | F60: ='balance_raw_33034482'!$F$37 | H60: =IFERROR(B60/$B$60*100,"") | I60: =IFERROR(C60/$B$60*100,"") | J60: =IFERROR(D60/$B$60*100,"") | K60: =IFERROR(E60/$B$60*100,"") | L60: =IFERROR(F60/$B$60*100,"")
A61: Leverandører af varer og tjenesteydelser | B61: ='balance_raw_33034482'!$B$38 | C61: ='balance_raw_33034482'!$C$38 | D61: ='balance_raw_33034482'!$D$38 | E61: ='balance_raw_33034482'!$E$38 | F61: ='balance_raw_33034482'!$F$38 | H61: =IFERROR(B61/$B$61*100,"") | I61: =IFERROR(C61/$B$61*100,"") | J61: =IFERROR(D61/$B$61*100,"") | K61: =IFERROR(E61/$B$61*100,"") | L61: =IFERROR(F61/$B$61*100,"")
A62: Gæld til tilknyttede virksomheder | B62: ='balance_raw_33034482'!$B$39 | C62: ='balance_raw_33034482'!$C$39 | D62: ='balance_raw_33034482'!$D$39 | E62: ='balance_raw_33034482'!$E$39 | F62: ='balance_raw_33034482'!$F$39 | H62: =IFERROR(B62/$B$62*100,"") | I62: =IFERROR(C62/$B$62*100,"") | J62: =IFERROR(D62/$B$62*100,"") | K62: =IFERROR(E62/$B$62*100,"") | L62: =IFERROR(F62/$B$62*100,"")
A63: Gæld til selskabsdeltagere og ledelse | B63: ='balance_raw_33034482'!$B$40 | C63: ='balance_raw_33034482'!$C$40 | D63: ='balance_raw_33034482'!$D$40 | E63: ='balance_raw_33034482'!$E$40 | F63: ='balance_raw_33034482'!$F$40 | H63: =IFERROR(B63/$B$63*100,"") | I63: =IFERROR(C63/$B$63*100,"") | J63: =IFERROR(D63/$B$63*100,"") | K63: =IFERROR(E63/$B$63*100,"") | L63: =IFERROR(F63/$B$63*100,"")
A64: Selskabsskat | B64: ='balance_raw_33034482'!$B$41 | C64: ='balance_raw_33034482'!$C$41 | D64: ='balance_raw_33034482'!$D$41 | E64: ='balance_raw_33034482'!$E$41 | F64: ='balance_raw_33034482'!$F$41 | H64: =IFERROR(B64/$B$64*100,"") | I64: =IFERROR(C64/$B$64*100,"") | J64: =IFERROR(D64/$B$64*100,"") | K64: =IFERROR(E64/$B$64*100,"") | L64: =IFERROR(F64/$B$64*100,"")
A65: Gæld til tilknyttede virksomheder vedr. selskabsskat | B65: ='balance_raw_33034482'!$B$42 | C65: ='balance_raw_33034482'!$C$42 | D65: ='balance_raw_33034482'!$D$42 | E65: ='balance_raw_33034482'!$E$42 | F65: ='balance_raw_33034482'!$F$42 | H65: =IFERROR(B65/$B$65*100,"") | I65: =IFERROR(C65/$B$65*100,"") | J65: =IFERROR(D65/$B$65*100,"") | K65: =IFERROR(E65/$B$65*100,"") | L65: =IFERROR(F65/$B$65*100,"")
A66: Anden gæld (kortfristet) | B66: ='balance_raw_33034482'!$B$43 | C66: ='balance_raw_33034482'!$C$43 | D66: ='balance_raw_33034482'!$D$43 | E66: ='balance_raw_33034482'!$E$43 | F66: ='balance_raw_33034482'!$F$43 | H66: =IFERROR(B66/$B$66*100,"") | I66: =IFERROR(C66/$B$66*100,"") | J66: =IFERROR(D66/$B$66*100,"") | K66: =IFERROR(E66/$B$66*100,"") | L66: =IFERROR(F66/$B$66*100,"")
A67: Periodeafgrænsningsposter (passiver) | B67: ='balance_raw_33034482'!$B$44 | C67: ='balance_raw_33034482'!$C$44 | D67: ='balance_raw_33034482'!$D$44 | E67: ='balance_raw_33034482'!$E$44 | F67: ='balance_raw_33034482'!$F$44 | H67: =IFERROR(B67/$B$67*100,"") | I67: =IFERROR(C67/$B$67*100,"") | J67: =IFERROR(D67/$B$67*100,"") | K67: =IFERROR(E67/$B$67*100,"") | L67: =IFERROR(F67/$B$67*100,"")
A68: Kortfristede gældsforpligtelser | B68: ='balance_raw_33034482'!$B$45 | C68: ='balance_raw_33034482'!$C$45 | D68: ='balance_raw_33034482'!$D$45 | E68: ='balance_raw_33034482'!$E$45 | F68: ='balance_raw_33034482'!$F$45 | H68: =IFERROR(B68/$B$68*100,"") | I68: =IFERROR(C68/$B$68*100,"") | J68: =IFERROR(D68/$B$68*100,"") | K68: =IFERROR(E68/$B$68*100,"") | L68: =IFERROR(F68/$B$68*100,"")
A69: Gældsforpligtelser | B69: ='balance_raw_33034482'!$B$46 | C69: ='balance_raw_33034482'!$C$46 | D69: ='balance_raw_33034482'!$D$46 | E69: ='balance_raw_33034482'!$E$46 | F69: ='balance_raw_33034482'!$F$46 | H69: =IFERROR(B69/$B$69*100,"") | I69: =IFERROR(C69/$B$69*100,"") | J69: =IFERROR(D69/$B$69*100,"") | K69: =IFERROR(E69/$B$69*100,"") | L69: =IFERROR(F69/$B$69*100,"")
A70: Passiver | B70: ='balance_raw_33034482'!$B$47 | C70: ='balance_raw_33034482'!$C$47 | D70: ='balance_raw_33034482'!$D$47 | E70: ='balance_raw_33034482'!$E$47 | F70: ='balance_raw_33034482'!$F$47 | H70: =IFERROR(B70/$B$70*100,"") | I70: =IFERROR(C70/$B$70*100,"") | J70: =IFERROR(D70/$B$70*100,"") | K70: =IFERROR(E70/$B$70*100,"") | L70: =IFERROR(F70/$B$70*100,"")
A72: NØGLEOPLYSNINGER | B72: 2021 | C72: 2022 | D72: 2023 | E72: 2024 | F72: 2025
A73: Gns. antal medarbejdere | B73: ='res_raw_33034482'!$B$19 | C73: ='res_raw_33034482'!$C$19 | D73: ='res_raw_33034482'!$D$19 | E73: ='res_raw_33034482'!$E$19 | F73: ='res_raw_33034482'!$F$19 | H73: =IFERROR(B73/$B$73*100,"") | I73: =IFERROR(C73/$B$73*100,"") | J73: =IFERROR(D73/$B$73*100,"") | K73: =IFERROR(E73/$B$73*100,"") | L73: =IFERROR(F73/$B$73*100,"")
A74: Investering i materielle anlægsaktiver | B74: ='res_raw_33034482'!$B$20 | C74: ='res_raw_33034482'!$C$20 | D74: ='res_raw_33034482'!$D$20 | E74: ='res_raw_33034482'!$E$20 | F74: ='res_raw_33034482'!$F$20 | H74: =IFERROR(B74/$B$74*100,"") | I74: =IFERROR(C74/$B$74*100,"") | J74: =IFERROR(D74/$B$74*100,"") | K74: =IFERROR(E74/$B$74*100,"") | L74: =IFERROR(F74/$B$74*100,"")
A76: NØGLETAL | B76: 2021 | C76: 2022 | D76: 2023 | E76: 2024 | F76: 2025
A77: Afkastningsgrad, % | B77: =IFERROR(($B$13+$B$15+$B$14)/$B$44*100,"") | C77: =IFERROR(($C$13+$C$15+$C$14)/$C$44*100,"") | D77: =IFERROR(($D$13+$D$15+$D$14)/$D$44*100,"") | E77: =IFERROR(($E$13+$E$15+$E$14)/$E$44*100,"") | F77: =IFERROR(($F$13+$F$15+$F$14)/$F$44*100,"")
A78: Overskudsgrad (af bruttofortjeneste), % | B78: =IFERROR(($B$13+$B$15+$B$14)/$B$8*100,"") | C78: =IFERROR(($C$13+$C$15+$C$14)/$C$8*100,"") | D78: =IFERROR(($D$13+$D$15+$D$14)/$D$8*100,"") | E78: =IFERROR(($E$13+$E$15+$E$14)/$E$8*100,"") | F78: =IFERROR(($F$13+$F$15+$F$14)/$F$8*100,"")
A79: Aktivernes omsætningshastighed (af bruttofortjeneste), gange | B79: =IFERROR($B$8/$B$44,"") | C79: =IFERROR($C$8/$C$44,"") | D79: =IFERROR($D$8/$D$44,"") | E79: =IFERROR($E$8/$E$44,"") | F79: =IFERROR($F$8/$F$44,"")
A80: Egenkapitalens forrentning, % | B80: =IFERROR($B$18/$B$53*100,"") | C80: =IFERROR($C$18/$C$53*100,"") | D80: =IFERROR($D$18/$D$53*100,"") | E80: =IFERROR($E$18/$E$53*100,"") | F80: =IFERROR($F$18/$F$53*100,"")
A81: Gældsrente, % | B81: =IFERROR($B$16/($B$70-$B$53)*100,"") | C81: =IFERROR($C$16/($C$70-$C$53)*100,"") | D81: =IFERROR($D$16/($D$70-$D$53)*100,"") | E81: =IFERROR($E$16/($E$70-$E$53)*100,"") | F81: =IFERROR($F$16/($F$70-$F$53)*100,"")
A82: Soliditetsgrad, % | B82: =IFERROR($B$53/$B$44*100,"") | C82: =IFERROR($C$53/$C$44*100,"") | D82: =IFERROR($D$53/$D$44*100,"") | E82: =IFERROR($E$53/$E$44*100,"") | F82: =IFERROR($F$53/$F$44*100,"")
A83: Gearing | B83: =IFERROR(($B$70-$B$53)/$B$53,"") | C83: =IFERROR(($C$70-$C$53)/$C$53,"") | D83: =IFERROR(($D$70-$D$53)/$D$53,"") | E83: =IFERROR(($E$70-$E$53)/$E$53,"") | F83: =IFERROR(($F$70-$F$53)/$F$53,"")
A84: Likviditetsgrad, % | B84: =IFERROR($B$43/$B$68*100,"") | C84: =IFERROR($C$43/$C$68*100,"") | D84: =IFERROR($D$43/$D$68*100,"") | E84: =IFERROR($E$43/$E$68*100,"") | F84: =IFERROR($F$43/$F$68*100,"")
A85: Rentemarginal, % | B85: =IFERROR(B77-B81,"") | C85: =IFERROR(C77-C81,"") | D85: =IFERROR(D77-D81,"") | E85: =IFERROR(E77-E81,"") | F85: =IFERROR(F77-F81,"")
A86: Gældsandel, % | B86: =IFERROR(($B$70-$B$53)/$B$44*100,"") | C86: =IFERROR(($C$70-$C$53)/$C$44*100,"") | D86: =IFERROR(($D$70-$D$53)/$D$44*100,"") | E86: =IFERROR(($E$70-$E$53)/$E$44*100,"") | F86: =IFERROR(($F$70-$F$53)/$F$44*100,"")
A87: Kapitalbindingsgrad, % | B87: =IFERROR($B$31/($B$53+$B$56)*100,"") | C87: =IFERROR($C$31/($C$53+$C$56)*100,"") | D87: =IFERROR($D$31/($D$53+$D$56)*100,"") | E87: =IFERROR($E$31/($E$53+$E$56)*100,"") | F87: =IFERROR($F$31/($F$53+$F$56)*100,"")
A89: PENGESTRØMSOPGØRELSE t.kr.
A90: Pengestrømme fra driftsaktivitet | B90: ='pengestrom_raw_33034482'!$B$2 | C90: ='pengestrom_raw_33034482'!$C$2 | D90: ='pengestrom_raw_33034482'!$D$2 | E90: ='pengestrom_raw_33034482'!$E$2 | F90: ='pengestrom_raw_33034482'!$F$2
A91: Pengestrømme fra investeringsaktivitet | B91: ='pengestrom_raw_33034482'!$B$3 | C91: ='pengestrom_raw_33034482'!$C$3 | D91: ='pengestrom_raw_33034482'!$D$3 | E91: ='pengestrom_raw_33034482'!$E$3 | F91: ='pengestrom_raw_33034482'!$F$3
A92: Pengestrømme fra finansieringsaktivitet | B92: ='pengestrom_raw_33034482'!$B$4 | C92: ='pengestrom_raw_33034482'!$C$4 | D92: ='pengestrom_raw_33034482'!$D$4 | E92: ='pengestrom_raw_33034482'!$E$4 | F92: ='pengestrom_raw_33034482'!$F$4
A93: Årets pengestrøm (rapporteret) | B93: ='pengestrom_raw_33034482'!$B$5 | C93: ='pengestrom_raw_33034482'!$C$5 | D93: ='pengestrom_raw_33034482'!$D$5 | E93: ='pengestrom_raw_33034482'!$E$5 | F93: ='pengestrom_raw_33034482'!$F$5
A94: Krydstjek: drift + inv. + fin. = årets pengestrøm | B94: =IF(ABS(('pengestrom_raw_33034482'!$B$2+'pengestrom_raw_33034482'!$B$3+'pengestrom_raw_33034482'!$B$4)-'pengestrom_raw_33034482'!$B$5)<=2,"✓","⚠ "&TEXT(('pengestrom_raw_33034482'!$B$2+'pengestrom_raw_33034482'!$B$3+'pengestrom_raw_33034482'!$B$4)-'pengestrom_raw_33034482'!$B$5,"+#,##0;-#,##0")) | C94: =IF(ABS(('pengestrom_raw_33034482'!$C$2+'pengestrom_raw_33034482'!$C$3+'pengestrom_raw_33034482'!$C$4)-'pengestrom_raw_33034482'!$C$5)<=2,"✓","⚠ "&TEXT(('pengestrom_raw_33034482'!$C$2+'pengestrom_raw_33034482'!$C$3+'pengestrom_raw_33034482'!$C$4)-'pengestrom_raw_33034482'!$C$5,"+#,##0;-#,##0")) | D94: =IF(ABS(('pengestrom_raw_33034482'!$D$2+'pengestrom_raw_33034482'!$D$3+'pengestrom_raw_33034482'!$D$4)-'pengestrom_raw_33034482'!$D$5)<=2,"✓","⚠ "&TEXT(('pengestrom_raw_33034482'!$D$2+'pengestrom_raw_33034482'!$D$3+'pengestrom_raw_33034482'!$D$4)-'pengestrom_raw_33034482'!$D$5,"+#,##0;-#,##0")) | E94: =IF(ABS(('pengestrom_raw_33034482'!$E$2+'pengestrom_raw_33034482'!$E$3+'pengestrom_raw_33034482'!$E$4)-'pengestrom_raw_33034482'!$E$5)<=2,"✓","⚠ "&TEXT(('pengestrom_raw_33034482'!$E$2+'pengestrom_raw_33034482'!$E$3+'pengestrom_raw_33034482'!$E$4)-'pengestrom_raw_33034482'!$E$5,"+#,##0;-#,##0")) | F94: =IF(ABS(('pengestrom_raw_33034482'!$F$2+'pengestrom_raw_33034482'!$F$3+'pengestrom_raw_33034482'!$F$4)-'pengestrom_raw_33034482'!$F$5)<=2,"✓","⚠ "&TEXT(('pengestrom_raw_33034482'!$F$2+'pengestrom_raw_33034482'!$F$3+'pengestrom_raw_33034482'!$F$4)-'pengestrom_raw_33034482'!$F$5,"+#,##0;-#,##0"))

Sheet res_raw_33034482
A1: Danske Lotteri Spil A/S (CVR 33034482) — Resultatopgørelse & nøgleoplysninger (t.kr.) | B1: 2021 | C1: 2022 | D1: 2023 | E1: 2024 | F1: 2025
A2: Nettoomsætning
A3: Andre driftsindtægter | B3: 31561 | C3: 33152 | D3: 30140 | E3: 28919 | F3: 30614
A4: Vareforbrug
A5: Andre eksterne omkostninger | B5: 473491 | C5: 460536 | D5: 460972 | E5: 487839 | F5: 477818
A6: Bruttoresultat
A7: Personaleomkostninger | B7: 55221 | C7: 59265 | D7: 65764 | E7: 64044 | F7: 66029
A8: Resultat før afskrivninger
A9: Af- og nedskrivninger | B9: 84163 | C9: 50642 | D9: 45945 | E9: 60154 | F9: 26865
A10: Andre driftsomkostninger
A11: Resultat af primær drift | B11: 1868655 | C11: 1932005 | D11: 1985700 | E11: 2153655 | F11: 2155883
A12: Indtægter af kapitalandele, dattervirksomheder
A13: Finansielle indtægter | B13: 27099 | C13: 8542 | D13: 46819 | E13: 50646 | F13: 29575
A14: Finansielle omkostninger | B14: 3908 | C14: 37171 | D14: 1507 | E14: 1580 | F14: 3916
A15: Finansielle poster, netto | B15: 23191 | C15: -28629 | D15: 45312 | E15: 49066 | F15: 25659
A16: Resultat før skat | B16: 1891846 | C16: 1903376 | D16: 2031012 | E16: 2202721 | F16: 2181542
A17: Skat af årets resultat | B17: 414203 | C17: 421125 | D17: 446997 | E17: 487348 | F17: 480697
A18: Årets resultat | B18: 1477643 | C18: 1482251 | D18: 1584014 | E18: 1715373 | F18: 1700845
A19: Gns. antal medarbejdere
A20: Investering i materielle anlægsaktiver | B20: 22975

Sheet balance_raw_33034482
A1: Danske Lotteri Spil A/S (CVR 33034482) — Balance (t.kr.) | B1: 2021 | C1: 2022 | D1: 2023 | E1: 2024 | F1: 2025
A2: Udviklingsprojekter | B2: 114755 | C2: 95298 | D2: 63955 | E2: 55636 | F2: 72554
A3: Patenter, varemærker mv.
A4: Goodwill
A5: Immaterielle anlægsaktiver | B5: 140450 | C5: 115893 | D5: 103761 | E5: 108253 | F5: 148206
A6: Materielle anlægsaktiver | B6: 14027 | C6: 7994 | D6: 5641 | E6: 12239 | F6: 9886
A7: Kapitalandele, dattervirksomheder | B7: 937 | C7: 937 | D7: 937 | E7: 937 | F7: 937
A8: Deposita
A9: Finansielle anlægsaktiver
A10: Anlægsaktiver | B10: 169220 | C10: 139279 | D10: 137680 | E10: 139200 | F10: 204982
A11: Varebeholdninger | B11: 6087 | C11: 5809 | D11: 6880 | E11: 5917 | F11: 10371
A12: Tilgodehavender fra salg og tjenesteydelser | B12: 79399 | C12: 102151 | D12: 64628 | E12: 118724 | F12: 86278
A13: Tilgodehavender hos tilknyttede virksomheder
A14: Andre tilgodehavender
A15: Periodeafgrænsningsposter (aktiver) | B15: 6537 | C15: 4352 | D15: 4130 | E15: 4112 | F15: 10262
A16: Udskudt skatteaktiv
A17: Tilgodehavende skat hos tilknyttede virksomheder
A18: Kortfristede skattetilgodehavender | B18: 0 | C18: 14658 | D18: 4855 | E18: 0 | F18: 0
A19: Tilgodehavender | B19: 982 | C19: 1737 | D19: 3597 | E19: 4023 | F19: 4811
A20: Værdipapirer
A21: Likvide beholdninger | B21: 155073 | C21: 354305 | D21: 224138 | E21: 168288 | F21: 208490
A22: Omsætningsaktiver | B22: 669406 | C22: 865982 | D22: 725813 | E22: 956853 | F22: 790893
A23: Aktiver | B23: 838626 | C23: 1005261 | D23: 863493 | E23: 1096053 | F23: 995875
A24: Selskabskapital | B24: 10000 | C24: 10000 | D24: 10000 | E24: 10000 | F24: 10000
A25: Reserve for nettoopskrivning (indre værdis metode)
A26: Reserve for udviklingsomkostninger
A27: Reserve for sikringstransaktioner
A28: Andre reserver
A29: Overført resultat | B29: 0 | C29: 0 | D29: 0 | E29: 0 | F29: 0
A30: Egenkapital i alt | B30: 153914 | C30: 138521 | D30: 136253 | E30: 145411 | F30: 182273
A31: Hensættelse til udskudt skat | B31: 20542 | C31: 13513 | D31: 10490 | E31: 9599 | F31: 9523
A32: Hensatte forpligtelser | B32: 20542 | C32: 13513 | D32: 10490 | E32: 9599 | F32: 9523
A33: Langfristede gældsforpligtelser | B33: 45492 | C33: 46967 | D33: 41037 | E33: 43667 | F33: 44666
A34: Ansvarlig lånekapital (kortfristet)
A35: Kortfristet del af langfristede gældsforpligtelser
A36: Kreditinstitutter
A37: Leasingforpligtelser (kortfristet)
A38: Leverandører af varer og tjenesteydelser | B38: 25028 | C38: 25100 | D38: 25273 | E38: 40362 | F38: 28753
A39: Gæld til tilknyttede virksomheder
A40: Gæld til selskabsdeltagere og ledelse
A41: Selskabsskat
A42: Gæld til tilknyttede virksomheder vedr. selskabsskat
A43: Anden gæld (kortfristet) | B43: 176809 | C43: 234703 | D43: 138381 | E43: 169189 | F43: 220391
A44: Periodeafgrænsningsposter (passiver)
A45: Kortfristede gældsforpligtelser | B45: 639220 | C45: 819773 | D45: 686203 | E45: 906975 | F45: 768936
A46: Gældsforpligtelser | B46: 684711 | C46: 866740 | D46: 727240 | E46: 950642 | F46: 813602
A47: Passiver | B47: 838626 | C47: 1005261 | D47: 863493 | E47: 1096053 | F47: 995875

Sheet pengestrom_raw_33034482
A1: Danske Lotteri Spil A/S (CVR 33034482) — Pengestrømsopgørelse (t.kr.) | B1: 2021 | C1: 2022 | D1: 2023 | E1: 2024 | F1: 2025
A2: Pengestrømme fra driftsaktivitet | B2: 1545427 | C2: 1737508 | D2: 1483673 | E2: 1723326 | F2: 1824621
A3: Pengestrømme fra investeringsaktivitet | B3: -28358 | C3: -17770 | D3: -58147 | E3: -69601 | F3: -123902
A4: Pengestrømme fra finansieringsaktivitet | B4: -1516595 | C4: -1520506 | D4: -1555693 | E4: -1709574 | F4: -1660516
A5: Årets pengestrøm | B5: 474 | C5: 199232 | D5: -130167 | E5: -55850 | F5: 40202

Sheet Simpel_arts
A1: Danske Lotteri Spil A/S (CVR 33034482) — Regnskabs- og nøgletal (CVR: 33034482) — artsopdelt
A3: Beløb i 1.000 kr. | B3: 2025 | C3: 2024 | D3: 2023 | F3: Note / XBRL-felt
A4: Uddrag af resultatopgørelse
A5: Nettoomsætning | B5: ='res_raw_33034482'!$F$2 | C5: ='res_raw_33034482'!$E$2 | D5: ='res_raw_33034482'!$D$2 | F5: fsa:Revenue
A6: Andre driftsindtægter | B6: ='res_raw_33034482'!$F$3 | C6: ='res_raw_33034482'!$E$3 | D6: ='res_raw_33034482'!$D$3 | F6: fsa:OtherOperatingIncome. Indtægter fra sekundære aktiviteter (huslejeindtægter, avance ved salg af anlæg mv.).
A7: Vareforbrug | B7: =-'res_raw_33034482'!$F$4 | C7: =-'res_raw_33034482'!$E$4 | D7: =-'res_raw_33034482'!$D$4 | F7: fsa:CostOfSales (vises negativt for korrekt SUM-formel).
A8: Andre eksterne omk. mv. | B8: =-'res_raw_33034482'!$F$5 | C8: =-'res_raw_33034482'!$E$5 | D8: =-'res_raw_33034482'!$D$5 | F8: fsa:OtherExternalExpenses (vises negativt). Husleje, energi, kontorhold mv.
A9: Bruttofortjeneste | B9: =IF(ABS((SUM(B5:B8))-'res_raw_33034482'!$F$6)<=2,SUM(B5:B8),'res_raw_33034482'!$F$6) | C9: =IF(ABS((SUM(C5:C8))-'res_raw_33034482'!$E$6)<=2,SUM(C5:C8),'res_raw_33034482'!$E$6) | D9: =IF(ABS((SUM(D5:D8))-'res_raw_33034482'!$D$6)<=2,SUM(D5:D8),'res_raw_33034482'!$D$6) | F9: Beregnet: Nettoomsætning + Andre driftsindt. − Vareforbrug − Andre ext. omk. Er komponenterne ikke indberettet, vises rapporteret bruttoresultat (fsa:GrossResult) direkte.
A10: Personaleomkostninger | B10: =-'res_raw_33034482'!$F$7 | C10: =-'res_raw_33034482'!$E$7 | D10: =-'res_raw_33034482'!$D$7 | F10: fsa:EmployeeBenefitsExpense (vises negativt). Lønninger, pension, sociale ydelser.
A11: Af- og nedskrivninger | B11: =-'res_raw_33034482'!$F$9 | C11: =-'res_raw_33034482'!$E$9 | D11: =-'res_raw_33034482'!$D$9 | F11: fsa:Depreciation (vises negativt). Af- og nedskrivninger på materielle og immaterielle anlægsaktiver.
A12: Andre driftsomkostninger | B12: =-'res_raw_33034482'!$F$10 | C12: =-'res_raw_33034482'!$E$10 | D12: =-'res_raw_33034482'!$D$10 | F12: fsa:OtherOperatingExpenses (vises negativt). Typisk 0 eller meget lille post.
A13: Resultat af primær drift | B13: =IF(ABS((SUM(B9:B12))-'res_raw_33034482'!$F$11)<=2,SUM(B9:B12),'res_raw_33034482'!$F$11) | C13: =IF(ABS((SUM(C9:C12))-'res_raw_33034482'!$E$11)<=2,SUM(C9:C12),'res_raw_33034482'!$E$11) | D13: =IF(ABS((SUM(D9:D12))-'res_raw_33034482'!$D$11)<=2,SUM(D9:D12),'res_raw_33034482'!$D$11) | F13: Beregnet: Bruttofortjeneste − Personaleomk. − Af- og nedskrivninger − Andre driftsomk. EBIT.
A14: Finansielle indtægter mv. | B14: =N('res_raw_33034482'!$F$12)+N('res_raw_33034482'!$F$13) | C14: =N('res_raw_33034482'!$E$12)+N('res_raw_33034482'!$E$13) | D14: =N('res_raw_33034482'!$D$12)+N('res_raw_33034482'!$D$13) | F14: fsa:IncomeFromSubsidiaries + fsa:OtherFinanceIncome.
A15: Finansielle omkostninger mv. | B15: =-'res_raw_33034482'!$F$14 | C15: =-'res_raw_33034482'!$E$14 | D15: =-'res_raw_33034482'!$D$14 | F15: fsa:OtherFinanceExpenses (vises negativt). Renteomkostninger, kurstab mv.
A16: Resultat før skat | B16: =IF(ABS((SUM(B13:B15))-'res_raw_33034482'!$F$16)<=2,SUM(B13:B15),'res_raw_33034482'!$F$16) | C16: =IF(ABS((SUM(C13:C15))-'res_raw_33034482'!$E$16)<=2,SUM(C13:C15),'res_raw_33034482'!$E$16) | D16: =IF(ABS((SUM(D13:D15))-'res_raw_33034482'!$D$16)<=2,SUM(D13:D15),'res_raw_33034482'!$D$16) | F16: Beregnet: EBIT + Fin. indtægter + Fin. omk. EBT.
A18: Uddrag af balance
A19: Anlægsaktiver | B19: ='balance_raw_33034482'!$F$10 | C19: ='balance_raw_33034482'!$E$10 | D19: ='balance_raw_33034482'!$D$10 | F19: fsa:NoncurrentAssets. Materielle, immaterielle og finansielle anlægsaktiver.
A20: Omsætningsaktiver | B20: ='balance_raw_33034482'!$F$22 | C20: ='balance_raw_33034482'!$E$22 | D20: ='balance_raw_33034482'!$D$22 | F20: fsa:CurrentAssets. Varebeholdninger, tilgodehavender, likvider.
A21: Aktiver i alt | B21: =SUM(B19:B20) | C21: =SUM(C19:C20) | D21: =SUM(D19:D20) | F21: Beregnet: Anlægsaktiver + Omsætningsaktiver. Bør matche fsa:Assets.
A23: Egenkapital | B23: ='balance_raw_33034482'!$F$30 | C23: ='balance_raw_33034482'!$E$30 | D23: ='balance_raw_33034482'!$D$30 | F23: fsa:Equity. Selskabskapital, overført resultat, reserver.
A24: Forpligtelser | B24: ='balance_raw_33034482'!$F$47-'balance_raw_33034482'!$F$30 | C24: ='balance_raw_33034482'!$E$47-'balance_raw_33034482'!$E$30 | D24: ='balance_raw_33034482'!$D$47-'balance_raw_33034482'!$D$30 | F24: Beregnet: Passiver (fsa:LiabilitiesAndEquity) − Egenkapital. Hensættelser + kort- og langfristet gæld.
A25: Passiver i alt | B25: =SUM(B23:B24) | C25: =SUM(C23:C24) | D25: =SUM(D23:D24) | F25: Beregnet: Egenkapital + Forpligtelser. Bør matche Aktiver i alt.
A27: Udvalgte balanceposter
A28: Varebeholdninger | B28: ='balance_raw_33034482'!$F$11 | C28: ='balance_raw_33034482'!$E$11 | D28: ='balance_raw_33034482'!$D$11 | F28: fsa:Inventories (eller fsa:ManufacturedGoodsAndGoodsForResale hvis total mangler).
A29: Tilgodehavender fra salg | B29: ='balance_raw_33034482'!$F$12 | C29: ='balance_raw_33034482'!$E$12 | D29: ='balance_raw_33034482'!$D$12 | F29: fsa:ShorttermTradeReceivables. Kortfristede tilgodehavender fra kunder.
A30: Kortfristede gældsforpligtelser | B30: ='balance_raw_33034482'!$F$45 | C30: ='balance_raw_33034482'!$E$45 | D30: ='balance_raw_33034482'!$D$45 | F30: fsa:ShorttermLiabilitiesOtherThanProvisions. Gæld der forfalder inden for 1 år.
A32: Rentabilitet
A33: Afkastningsgrad, % | B33: =IFERROR((B13+B14)/B21*100,"") | C33: =IFERROR((C13+C14)/C21*100,"") | D33: =IFERROR((D13+D14)/D21*100,"")
A34: Overskudsgrad (af bruttofortjeneste), % | B34: =IFERROR((B13+B14)/B9*100,"") | C34: =IFERROR((C13+C14)/C9*100,"") | D34: =IFERROR((D13+D14)/D9*100,"")
A35: Aktivernes omsætningshastighed (af bruttofortjeneste), gange | B35: =IFERROR(B9/B21,"") | C35: =IFERROR(C9/C21,"") | D35: =IFERROR(D9/D21,"")
A36: Gældsrente, % | B36: =IFERROR(-B15*100/B24,"") | C36: =IFERROR(-C15*100/C24,"") | D36: =IFERROR(-D15*100/D24,"")
A37: Egenkapitalens forrentning, % | B37: =IFERROR(B16/B23*100,"") | C37: =IFERROR(C16/C23*100,"") | D37: =IFERROR(D16/D23*100,"")
A38: Gearing, gange | B38: =IFERROR(B24/B23,"") | C38: =IFERROR(C24/C23,"") | D38: =IFERROR(D24/D23,"")
A40: Indekstal for indtjeningsevne (2023=100)
A41: Bruttofortjeneste | B41: =IFERROR(B9/$D9*100,"") | C41: =IFERROR(C9/$D9*100,"") | D41: =IFERROR(D9/$D9*100,"")
A42: Vareforbrug | B42: =IFERROR(B7/$D7*100,"") | C42: =IFERROR(C7/$D7*100,"") | D42: =IFERROR(D7/$D7*100,"")
A43: Andre eksterne omk. | B43: =IFERROR(B8/$D8*100,"") | C43: =IFERROR(C8/$D8*100,"") | D43: =IFERROR(D8/$D8*100,"")
A44: Personaleomkostninger | B44: =IFERROR(B10/$D10*100,"") | C44: =IFERROR(C10/$D10*100,"") | D44: =IFERROR(D10/$D10*100,"")
A45: Af- og nedskrivninger | B45: =IFERROR(B11/$D11*100,"") | C45: =IFERROR(C11/$D11*100,"") | D45: =IFERROR(D11/$D11*100,"")
A47: Indekstal for kapitaltilpasningsevne (2023=100)
A48: Bruttofortjeneste | B48: =IFERROR(B9*100/$D9,"") | C48: =IFERROR(C9*100/$D9,"") | D48: =IFERROR(D9*100/$D9,"")
A49: Anlægsaktiver | B49: =IFERROR(B19*100/$D19,"") | C49: =IFERROR(C19*100/$D19,"") | D49: =IFERROR(D19*100/$D19,"")
A50: Varebeholdninger | B50: =IFERROR(B28*100/$D28,"") | C50: =IFERROR(C28*100/$D28,"") | D50: =IFERROR(D28*100/$D28,"")
A51: Tilgodehavender fra salg | B51: =IFERROR(B29*100/$D29,"") | C51: =IFERROR(C29*100/$D29,"") | D51: =IFERROR(D29*100/$D29,"")
A53: Soliditet og likviditet
A54: Soliditetsgrad, % | B54: =IFERROR(B23*100/B21,"") | C54: =IFERROR(C23*100/C21,"") | D54: =IFERROR(D23*100/D21,"")
A55: Gældsandel, % | B55: =IFERROR(B24*100/B21,"") | C55: =IFERROR(C24*100/C21,"") | D55: =IFERROR(D24*100/D21,"")
A56: Likviditetsgrad, % | B56: =IFERROR(B20*100/B30,"") | C56: =IFERROR(C20*100/C30,"") | D56: =IFERROR(D20*100/D30,"")
A58: Kilde: Bearbejdet uddrag af årsrapporter for 2023-2025. Alle dataceller er live formler der peger på res_raw / balance_raw.
A60: Krydstjek mod rådata (tolerance: 1 t.kr.)
A61: Aktiver i alt = fsa:Assets | B61: =IF('balance_raw_33034482'!$F$23="","—",IF(ABS(B21-'balance_raw_33034482'!$F$23)<=1,"✓ OK","❌ "&TEXT(B21-'balance_raw_33034482'!$F$23,"+#,##0;-#,##0")&" t.kr.")) | C61: =IF('balance_raw_33034482'!$E$23="","—",IF(ABS(C21-'balance_raw_33034482'!$E$23)<=1,"✓ OK","❌ "&TEXT(C21-'balance_raw_33034482'!$E$23,"+#,##0;-#,##0")&" t.kr.")) | D61: =IF('balance_raw_33034482'!$D$23="","—",IF(ABS(D21-'balance_raw_33034482'!$D$23)<=1,"✓ OK","❌ "&TEXT(D21-'balance_raw_33034482'!$D$23,"+#,##0;-#,##0")&" t.kr.")) | F61: Verificerer at sum(Anlæg+Omsætning) matcher Assets-totalen.
A62: Passiver i alt = fsa:LiabilitiesAndEquity | B62: =IF('balance_raw_33034482'!$F$47="","—",IF(ABS(B25-'balance_raw_33034482'!$F$47)<=1,"✓ OK","❌ "&TEXT(B25-'balance_raw_33034482'!$F$47,"+#,##0;-#,##0")&" t.kr.")) | C62: =IF('balance_raw_33034482'!$E$47="","—",IF(ABS(C25-'balance_raw_33034482'!$E$47)<=1,"✓ OK","❌ "&TEXT(C25-'balance_raw_33034482'!$E$47,"+#,##0;-#,##0")&" t.kr.")) | D62: =IF('balance_raw_33034482'!$D$47="","—",IF(ABS(D25-'balance_raw_33034482'!$D$47)<=1,"✓ OK","❌ "&TEXT(D25-'balance_raw_33034482'!$D$47,"+#,##0;-#,##0")&" t.kr.")) | F62: Verificerer at sum(EK+Forpligtelser) matcher Passiver-totalen.
A63: Aktiver i alt = Passiver i alt | B63: =IF(ABS(B21-B25)<=1,"✓ OK","❌ "&TEXT(B21-B25,"+#,##0;-#,##0")&" t.kr.") | C63: =IF(ABS(C21-C25)<=1,"✓ OK","❌ "&TEXT(C21-C25,"+#,##0;-#,##0")&" t.kr.") | D63: =IF(ABS(D21-D25)<=1,"✓ OK","❌ "&TEXT(D21-D25,"+#,##0;-#,##0")&" t.kr.") | F63: Balance-identitet på arket selv. Skal altid være 0 differance.
A64: Bruttoresultat (beregnet) = fsa:GrossResult | B64: =IF('res_raw_33034482'!$F$6="","—",IF(ABS(B9-'res_raw_33034482'!$F$6)<=1,"✓ OK","❌ "&TEXT(B9-'res_raw_33034482'!$F$6,"+#,##0;-#,##0")&" t.kr.")) | C64: =IF('res_raw_33034482'!$E$6="","—",IF(ABS(C9-'res_raw_33034482'!$E$6)<=1,"✓ OK","❌ "&TEXT(C9-'res_raw_33034482'!$E$6,"+#,##0;-#,##0")&" t.kr.")) | D64: =IF('res_raw_33034482'!$D$6="","—",IF(ABS(D9-'res_raw_33034482'!$D$6)<=1,"✓ OK","❌ "&TEXT(D9-'res_raw_33034482'!$D$6,"+#,##0;-#,##0")&" t.kr.")) | F64: Hvis Nettoomsætning eller omkostninger mangler, vil sumberegnet bruttoresultat afvige.
A65: EBIT (beregnet) = fsa:ProfitLossFromOrdinaryOperatingActivities | B65: =IF('res_raw_33034482'!$F$11="","—",IF(ABS(B13-'res_raw_33034482'!$F$11)<=1,"✓ OK","❌ "&TEXT(B13-'res_raw_33034482'!$F$11,"+#,##0;-#,##0")&" t.kr.")) | C65: =IF('res_raw_33034482'!$E$11="","—",IF(ABS(C13-'res_raw_33034482'!$E$11)<=1,"✓ OK","❌ "&TEXT(C13-'res_raw_33034482'!$E$11,"+#,##0;-#,##0")&" t.kr.")) | D65: =IF('res_raw_33034482'!$D$11="","—",IF(ABS(D13-'res_raw_33034482'!$D$11)<=1,"✓ OK","❌ "&TEXT(D13-'res_raw_33034482'!$D$11,"+#,##0;-#,##0")&" t.kr.")) | F65: Verificerer at sumberegnet EBIT matcher det rapporterede.
A66: EBT (beregnet) = fsa:ProfitLossFromOrdinaryActivitiesBeforeTax | B66: =IF('res_raw_33034482'!$F$16="","—",IF(ABS(B16-'res_raw_33034482'!$F$16)<=1,"✓ OK","❌ "&TEXT(B16-'res_raw_33034482'!$F$16,"+#,##0;-#,##0")&" t.kr.")) | C66: =IF('res_raw_33034482'!$E$16="","—",IF(ABS(C16-'res_raw_33034482'!$E$16)<=1,"✓ OK","❌ "&TEXT(C16-'res_raw_33034482'!$E$16,"+#,##0;-#,##0")&" t.kr.")) | D66: =IF('res_raw_33034482'!$D$16="","—",IF(ABS(D16-'res_raw_33034482'!$D$16)<=1,"✓ OK","❌ "&TEXT(D16-'res_raw_33034482'!$D$16,"+#,##0;-#,##0")&" t.kr.")) | F66: Verificerer at sumberegnet resultat før skat matcher det rapporterede.

Sheet Noter_info
A1: Danske Lotteri Spil A/S (CVR 33034482) — Ukendte XBRL-felter — disse er noter og ikke en del af hoved-regnskabet
A2: Kategori | B2: Dansk navn | C2: XBRL feltnavn | D2: 2021 t.kr. | E2: 2022 t.kr. | F2: 2023 t.kr. | G2: 2024 t.kr. | H2: 2025 t.kr. | I2: Forklaring
A3: Øvrige (ukendt) | B3: ifrs-full:AdjustmentsForFinanceCosts | C3: ifrs-full:AdjustmentsForFinanceCosts | I3: Ingen forklaring tilgængelig.
A4: Øvrige (ukendt) | B4: ifrs-full:AdjustmentsForFinanceIncome | C4: ifrs-full:AdjustmentsForFinanceIncome | I4: Ingen forklaring tilgængelig.
A5: Øvrige (ukendt) | B5: ifrs-full:AdjustmentsForIncomeTaxExpense | C5: ifrs-full:AdjustmentsForIncomeTaxExpense | D5: 414203 | E5: 421125 | F5: 446997 | G5: 487348 | H5: 480697 | I5: Ingen forklaring tilgængelig.
A6: Øvrige (ukendt) | B6: ifrs-full:AdjustmentsForInterestExpense | C6: ifrs-full:AdjustmentsForInterestExpense | D6: 3908 | E6: 37171 | F6: 1507 | G6: 1580 | H6: 3916 | I6: Ingen forklaring tilgængelig.
A7: Øvrige (ukendt) | B7: ifrs-full:AdjustmentsForInterestIncome | C7: ifrs-full:AdjustmentsForInterestIncome | D7: 27099 | E7: 8542 | F7: 46819 | G7: 50646 | H7: 29575 | I7: Ingen forklaring tilgængelig.
A8: Øvrige (ukendt) | B8: ifrs-full:CurrentDividendPayables | C8: ifrs-full:CurrentDividendPayables | D8: 19676 | E8: 23767 | F8: 24737 | G8: 21378 | H8: 24845 | I8: Ingen forklaring tilgængelig.
A9: Øvrige (ukendt) | B9: ifrs-full:CurrentFinancialAssetsAtFairValueThroughProfitOrLoss | C9: ifrs-full:CurrentFinancialAssetsAtFairValueThroughProfitOrLoss | D9: 421328 | E9: 382970 | F9: 416141 | G9: 438969 | H9: 470681 | I9: Ingen forklaring tilgængelig.
A10: Øvrige (ukendt) | B10: ifrs-full:CurrentFinancialLiabilitiesAtFairValueThroughProfitOrLoss | C10: ifrs-full:CurrentFinancialLiabilitiesAtFairValueThroughProfitOrLoss | D10: 52817 | E10: 40835 | F10: 44563 | G10: 42092 | H10: 40691 | I10: Ingen forklaring tilgængelig.
A11: Øvrige (ukendt) | B11: ifrs-full:FeeAndCommissionExpense | C11: ifrs-full:FeeAndCommissionExpense | D11: 279912 | E11: 263289 | F11: 254880 | G11: 252804 | H11: 226777 | I11: Ingen forklaring tilgængelig.
A12: Øvrige (ukendt) | B12: ifrs-full:InvestmentsInJointVentures | C12: ifrs-full:InvestmentsInJointVentures | I12: Ingen forklaring tilgængelig.
A13: Øvrige (ukendt) | B13: ifrs-full:RevenueFromRenderingOfGamingServices | C13: ifrs-full:RevenueFromRenderingOfGamingServices | D13: 2787090 | E13: 2805411 | F13: 2874551 | G13: 3079640 | H13: 3011072 | I13: Ingen forklaring tilgængelig.
A14: Øvrige (ukendt) | B14: ifrs-full:TaxExpenseOtherThanIncomeTaxExpense | C14: ifrs-full:TaxExpenseOtherThanIncomeTaxExpense | D14: 9879 | E14: 9834 | F14: 9921 | G14: 8545 | H14: 9851 | I14: Ingen forklaring tilgængelig.
A15: Øvrige (ukendt) | B15: ifrs-full:TradeAndOtherCurrentReceivablesDueFromRelatedParties | C15: ifrs-full:TradeAndOtherCurrentReceivablesDueFromRelatedParties | E15: 0 | F15: 1443 | G15: 216820 | H15: 0 | I15: Ingen forklaring tilgængelig.
