Workbook

Sheet Overblik
A1: bogo (CVR None) — Regnskabsanalyse – Resultatopgørelse & Balance (t.kr.)
H2: Indekstal (2022=100)
A3: Resultatopgørelse t.kr. | B3: 2022 | C3: 2023 | D3: 2024 | E3: 2025 | F3: 2026 | H3: 2022 | I3: 2023 | J3: 2024 | K3: 2025 | L3: 2026
A4: Nettoomsætning | B4: ='res_raw'!$B$2 | C4: ='res_raw'!$C$2 | D4: ='res_raw'!$D$2 | E4: ='res_raw'!$E$2 | F4: ='res_raw'!$F$2 | H4: =IFERROR(B4/$B$4*100,"") | I4: =IFERROR(C4/$B$4*100,"") | J4: =IFERROR(D4/$B$4*100,"") | K4: =IFERROR(E4/$B$4*100,"") | L4: =IFERROR(F4/$B$4*100,"")
A5: Produktionsomkostninger | B5: ='res_raw'!$B$3 | C5: ='res_raw'!$C$3 | D5: ='res_raw'!$D$3 | E5: ='res_raw'!$E$3 | F5: ='res_raw'!$F$3 | H5: =IFERROR(B5/$B$5*100,"") | I5: =IFERROR(C5/$B$5*100,"") | J5: =IFERROR(D5/$B$5*100,"") | K5: =IFERROR(E5/$B$5*100,"") | L5: =IFERROR(F5/$B$5*100,"")
A6: Bruttoresultat | B6: ='res_raw'!$B$4 | C6: ='res_raw'!$C$4 | D6: ='res_raw'!$D$4 | E6: ='res_raw'!$E$4 | F6: ='res_raw'!$F$4 | H6: =IFERROR(B6/$B$6*100,"") | I6: =IFERROR(C6/$B$6*100,"") | J6: =IFERROR(D6/$B$6*100,"") | K6: =IFERROR(E6/$B$6*100,"") | L6: =IFERROR(F6/$B$6*100,"")
A7: Salgs- og distributionsomkostninger | B7: ='res_raw'!$B$5 | C7: ='res_raw'!$C$5 | D7: ='res_raw'!$D$5 | E7: ='res_raw'!$E$5 | F7: ='res_raw'!$F$5 | H7: =IFERROR(B7/$B$7*100,"") | I7: =IFERROR(C7/$B$7*100,"") | J7: =IFERROR(D7/$B$7*100,"") | K7: =IFERROR(E7/$B$7*100,"") | L7: =IFERROR(F7/$B$7*100,"")
A8: Administrationsomkostninger | B8: ='res_raw'!$B$6 | C8: ='res_raw'!$C$6 | D8: ='res_raw'!$D$6 | E8: ='res_raw'!$E$6 | F8: ='res_raw'!$F$6 | H8: =IFERROR(B8/$B$8*100,"") | I8: =IFERROR(C8/$B$8*100,"") | J8: =IFERROR(D8/$B$8*100,"") | K8: =IFERROR(E8/$B$8*100,"") | L8: =IFERROR(F8/$B$8*100,"")
A9: Andre driftsindtægter | B9: ='res_raw'!$B$7 | C9: ='res_raw'!$C$7 | D9: ='res_raw'!$D$7 | E9: ='res_raw'!$E$7 | F9: ='res_raw'!$F$7 | H9: =IFERROR(B9/$B$9*100,"") | I9: =IFERROR(C9/$B$9*100,"") | J9: =IFERROR(D9/$B$9*100,"") | K9: =IFERROR(E9/$B$9*100,"") | L9: =IFERROR(F9/$B$9*100,"")
A10: Andre driftsomkostninger | B10: ='res_raw'!$B$8 | C10: ='res_raw'!$C$8 | D10: ='res_raw'!$D$8 | E10: ='res_raw'!$E$8 | F10: ='res_raw'!$F$8 | H10: =IFERROR(B10/$B$10*100,"") | I10: =IFERROR(C10/$B$10*100,"") | J10: =IFERROR(D10/$B$10*100,"") | K10: =IFERROR(E10/$B$10*100,"") | L10: =IFERROR(F10/$B$10*100,"")
A11: Resultat af primær drift | B11: ='res_raw'!$B$9 | C11: ='res_raw'!$C$9 | D11: ='res_raw'!$D$9 | E11: ='res_raw'!$E$9 | F11: ='res_raw'!$F$9 | H11: =IFERROR(B11/$B$11*100,"") | I11: =IFERROR(C11/$B$11*100,"") | J11: =IFERROR(D11/$B$11*100,"") | K11: =IFERROR(E11/$B$11*100,"") | L11: =IFERROR(F11/$B$11*100,"")
A12: Indtægter af kapitalandele, dattervirksomheder | B12: ='res_raw'!$B$10 | C12: ='res_raw'!$C$10 | D12: ='res_raw'!$D$10 | E12: ='res_raw'!$E$10 | F12: ='res_raw'!$F$10 | H12: =IFERROR(B12/$B$12*100,"") | I12: =IFERROR(C12/$B$12*100,"") | J12: =IFERROR(D12/$B$12*100,"") | K12: =IFERROR(E12/$B$12*100,"") | L12: =IFERROR(F12/$B$12*100,"")
A13: Finansielle indtægter | B13: ='res_raw'!$B$11 | C13: ='res_raw'!$C$11 | D13: ='res_raw'!$D$11 | E13: ='res_raw'!$E$11 | F13: ='res_raw'!$F$11 | H13: =IFERROR(B13/$B$13*100,"") | I13: =IFERROR(C13/$B$13*100,"") | J13: =IFERROR(D13/$B$13*100,"") | K13: =IFERROR(E13/$B$13*100,"") | L13: =IFERROR(F13/$B$13*100,"")
A14: Finansielle omkostninger | B14: ='res_raw'!$B$12 | C14: ='res_raw'!$C$12 | D14: ='res_raw'!$D$12 | E14: ='res_raw'!$E$12 | F14: ='res_raw'!$F$12 | H14: =IFERROR(B14/$B$14*100,"") | I14: =IFERROR(C14/$B$14*100,"") | J14: =IFERROR(D14/$B$14*100,"") | K14: =IFERROR(E14/$B$14*100,"") | L14: =IFERROR(F14/$B$14*100,"")
A15: Finansielle poster, netto | B15: ='res_raw'!$B$13 | C15: ='res_raw'!$C$13 | D15: ='res_raw'!$D$13 | E15: ='res_raw'!$E$13 | F15: ='res_raw'!$F$13 | H15: =IFERROR(B15/$B$15*100,"") | I15: =IFERROR(C15/$B$15*100,"") | J15: =IFERROR(D15/$B$15*100,"") | K15: =IFERROR(E15/$B$15*100,"") | L15: =IFERROR(F15/$B$15*100,"")
A16: Resultat før skat | B16: ='res_raw'!$B$14 | C16: ='res_raw'!$C$14 | D16: ='res_raw'!$D$14 | E16: ='res_raw'!$E$14 | F16: ='res_raw'!$F$14 | H16: =IFERROR(B16/$B$16*100,"") | I16: =IFERROR(C16/$B$16*100,"") | J16: =IFERROR(D16/$B$16*100,"") | K16: =IFERROR(E16/$B$16*100,"") | L16: =IFERROR(F16/$B$16*100,"")
A17: Skat af årets resultat | B17: ='res_raw'!$B$15 | C17: ='res_raw'!$C$15 | D17: ='res_raw'!$D$15 | E17: ='res_raw'!$E$15 | F17: ='res_raw'!$F$15 | H17: =IFERROR(B17/$B$17*100,"") | I17: =IFERROR(C17/$B$17*100,"") | J17: =IFERROR(D17/$B$17*100,"") | K17: =IFERROR(E17/$B$17*100,"") | L17: =IFERROR(F17/$B$17*100,"")
A18: Årets resultat | B18: ='res_raw'!$B$16 | C18: ='res_raw'!$C$16 | D18: ='res_raw'!$D$16 | E18: ='res_raw'!$E$16 | F18: ='res_raw'!$F$16 | H18: =IFERROR(B18/$B$18*100,"") | I18: =IFERROR(C18/$B$18*100,"") | J18: =IFERROR(D18/$B$18*100,"") | K18: =IFERROR(E18/$B$18*100,"") | L18: =IFERROR(F18/$B$18*100,"")
A20: AKTIVER t.kr. | B20: 2022 | C20: 2023 | D20: 2024 | E20: 2025 | F20: 2026 | H20: 2022 | I20: 2023 | J20: 2024 | K20: 2025 | L20: 2026
A21: Udviklingsprojekter | B21: ='balance_raw'!$B$2 | C21: ='balance_raw'!$C$2 | D21: ='balance_raw'!$D$2 | E21: ='balance_raw'!$E$2 | F21: ='balance_raw'!$F$2 | H21: =IFERROR(B21/$B$21*100,"") | I21: =IFERROR(C21/$B$21*100,"") | J21: =IFERROR(D21/$B$21*100,"") | K21: =IFERROR(E21/$B$21*100,"") | L21: =IFERROR(F21/$B$21*100,"")
A22: Patenter, varemærker mv. | B22: ='balance_raw'!$B$3 | C22: ='balance_raw'!$C$3 | D22: ='balance_raw'!$D$3 | E22: ='balance_raw'!$E$3 | F22: ='balance_raw'!$F$3 | H22: =IFERROR(B22/$B$22*100,"") | I22: =IFERROR(C22/$B$22*100,"") | J22: =IFERROR(D22/$B$22*100,"") | K22: =IFERROR(E22/$B$22*100,"") | L22: =IFERROR(F22/$B$22*100,"")
A23: Goodwill | B23: ='balance_raw'!$B$4 | C23: ='balance_raw'!$C$4 | D23: ='balance_raw'!$D$4 | E23: ='balance_raw'!$E$4 | F23: ='balance_raw'!$F$4 | H23: =IFERROR(B23/$B$23*100,"") | I23: =IFERROR(C23/$B$23*100,"") | J23: =IFERROR(D23/$B$23*100,"") | K23: =IFERROR(E23/$B$23*100,"") | L23: =IFERROR(F23/$B$23*100,"")
A24: Immaterielle anlægsaktiver | B24: ='balance_raw'!$B$5 | C24: ='balance_raw'!$C$5 | D24: ='balance_raw'!$D$5 | E24: ='balance_raw'!$E$5 | F24: ='balance_raw'!$F$5 | H24: =IFERROR(B24/$B$24*100,"") | I24: =IFERROR(C24/$B$24*100,"") | J24: =IFERROR(D24/$B$24*100,"") | K24: =IFERROR(E24/$B$24*100,"") | L24: =IFERROR(F24/$B$24*100,"")
A25: Materielle anlægsaktiver | B25: ='balance_raw'!$B$6 | C25: ='balance_raw'!$C$6 | D25: ='balance_raw'!$D$6 | E25: ='balance_raw'!$E$6 | F25: ='balance_raw'!$F$6 | H25: =IFERROR(B25/$B$25*100,"") | I25: =IFERROR(C25/$B$25*100,"") | J25: =IFERROR(D25/$B$25*100,"") | K25: =IFERROR(E25/$B$25*100,"") | L25: =IFERROR(F25/$B$25*100,"")
A26: Anlægsaktiver | B26: ='balance_raw'!$B$7 | C26: ='balance_raw'!$C$7 | D26: ='balance_raw'!$D$7 | E26: ='balance_raw'!$E$7 | F26: ='balance_raw'!$F$7 | H26: =IFERROR(B26/$B$26*100,"") | I26: =IFERROR(C26/$B$26*100,"") | J26: =IFERROR(D26/$B$26*100,"") | K26: =IFERROR(E26/$B$26*100,"") | L26: =IFERROR(F26/$B$26*100,"")
A27: Varebeholdninger | B27: ='balance_raw'!$B$8 | C27: ='balance_raw'!$C$8 | D27: ='balance_raw'!$D$8 | E27: ='balance_raw'!$E$8 | F27: ='balance_raw'!$F$8 | H27: =IFERROR(B27/$B$27*100,"") | I27: =IFERROR(C27/$B$27*100,"") | J27: =IFERROR(D27/$B$27*100,"") | K27: =IFERROR(E27/$B$27*100,"") | L27: =IFERROR(F27/$B$27*100,"")
A28: Tilgodehavender fra salg og tjenesteydelser | B28: ='balance_raw'!$B$9 | C28: ='balance_raw'!$C$9 | D28: ='balance_raw'!$D$9 | E28: ='balance_raw'!$E$9 | F28: ='balance_raw'!$F$9 | H28: =IFERROR(B28/$B$28*100,"") | I28: =IFERROR(C28/$B$28*100,"") | J28: =IFERROR(D28/$B$28*100,"") | K28: =IFERROR(E28/$B$28*100,"") | L28: =IFERROR(F28/$B$28*100,"")
A29: Tilgodehavender hos tilknyttede virksomheder | B29: ='balance_raw'!$B$10 | C29: ='balance_raw'!$C$10 | D29: ='balance_raw'!$D$10 | E29: ='balance_raw'!$E$10 | F29: ='balance_raw'!$F$10 | H29: =IFERROR(B29/$B$29*100,"") | I29: =IFERROR(C29/$B$29*100,"") | J29: =IFERROR(D29/$B$29*100,"") | K29: =IFERROR(E29/$B$29*100,"") | L29: =IFERROR(F29/$B$29*100,"")
A30: Andre tilgodehavender | B30: ='balance_raw'!$B$11 | C30: ='balance_raw'!$C$11 | D30: ='balance_raw'!$D$11 | E30: ='balance_raw'!$E$11 | F30: ='balance_raw'!$F$11 | H30: =IFERROR(B30/$B$30*100,"") | I30: =IFERROR(C30/$B$30*100,"") | J30: =IFERROR(D30/$B$30*100,"") | K30: =IFERROR(E30/$B$30*100,"") | L30: =IFERROR(F30/$B$30*100,"")
A31: Periodeafgrænsningsposter (aktiver) | B31: ='balance_raw'!$B$12 | C31: ='balance_raw'!$C$12 | D31: ='balance_raw'!$D$12 | E31: ='balance_raw'!$E$12 | F31: ='balance_raw'!$F$12 | H31: =IFERROR(B31/$B$31*100,"") | I31: =IFERROR(C31/$B$31*100,"") | J31: =IFERROR(D31/$B$31*100,"") | K31: =IFERROR(E31/$B$31*100,"") | L31: =IFERROR(F31/$B$31*100,"")
A32: Udskudt skatteaktiv | B32: ='balance_raw'!$B$13 | C32: ='balance_raw'!$C$13 | D32: ='balance_raw'!$D$13 | E32: ='balance_raw'!$E$13 | F32: ='balance_raw'!$F$13 | H32: =IFERROR(B32/$B$32*100,"") | I32: =IFERROR(C32/$B$32*100,"") | J32: =IFERROR(D32/$B$32*100,"") | K32: =IFERROR(E32/$B$32*100,"") | L32: =IFERROR(F32/$B$32*100,"")
A33: Tilgodehavende skat hos tilknyttede virksomheder | B33: ='balance_raw'!$B$14 | C33: ='balance_raw'!$C$14 | D33: ='balance_raw'!$D$14 | E33: ='balance_raw'!$E$14 | F33: ='balance_raw'!$F$14 | H33: =IFERROR(B33/$B$33*100,"") | I33: =IFERROR(C33/$B$33*100,"") | J33: =IFERROR(D33/$B$33*100,"") | K33: =IFERROR(E33/$B$33*100,"") | L33: =IFERROR(F33/$B$33*100,"")
A34: Kortfristede skattetilgodehavender | B34: ='balance_raw'!$B$15 | C34: ='balance_raw'!$C$15 | D34: ='balance_raw'!$D$15 | E34: ='balance_raw'!$E$15 | F34: ='balance_raw'!$F$15 | H34: =IFERROR(B34/$B$34*100,"") | I34: =IFERROR(C34/$B$34*100,"") | J34: =IFERROR(D34/$B$34*100,"") | K34: =IFERROR(E34/$B$34*100,"") | L34: =IFERROR(F34/$B$34*100,"")
A35: Tilgodehavender | B35: ='balance_raw'!$B$16 | C35: ='balance_raw'!$C$16 | D35: ='balance_raw'!$D$16 | E35: ='balance_raw'!$E$16 | F35: ='balance_raw'!$F$16 | H35: =IFERROR(B35/$B$35*100,"") | I35: =IFERROR(C35/$B$35*100,"") | J35: =IFERROR(D35/$B$35*100,"") | K35: =IFERROR(E35/$B$35*100,"") | L35: =IFERROR(F35/$B$35*100,"")
A36: Værdipapirer | B36: ='balance_raw'!$B$17 | C36: ='balance_raw'!$C$17 | D36: ='balance_raw'!$D$17 | E36: ='balance_raw'!$E$17 | F36: ='balance_raw'!$F$17 | H36: =IFERROR(B36/$B$36*100,"") | I36: =IFERROR(C36/$B$36*100,"") | J36: =IFERROR(D36/$B$36*100,"") | K36: =IFERROR(E36/$B$36*100,"") | L36: =IFERROR(F36/$B$36*100,"")
A37: Likvide beholdninger | B37: ='balance_raw'!$B$18 | C37: ='balance_raw'!$C$18 | D37: ='balance_raw'!$D$18 | E37: ='balance_raw'!$E$18 | F37: ='balance_raw'!$F$18 | H37: =IFERROR(B37/$B$37*100,"") | I37: =IFERROR(C37/$B$37*100,"") | J37: =IFERROR(D37/$B$37*100,"") | K37: =IFERROR(E37/$B$37*100,"") | L37: =IFERROR(F37/$B$37*100,"")
A38: Omsætningsaktiver | B38: ='balance_raw'!$B$19 | C38: ='balance_raw'!$C$19 | D38: ='balance_raw'!$D$19 | E38: ='balance_raw'!$E$19 | F38: ='balance_raw'!$F$19 | H38: =IFERROR(B38/$B$38*100,"") | I38: =IFERROR(C38/$B$38*100,"") | J38: =IFERROR(D38/$B$38*100,"") | K38: =IFERROR(E38/$B$38*100,"") | L38: =IFERROR(F38/$B$38*100,"")
A39: Aktiver | B39: ='balance_raw'!$B$20 | C39: ='balance_raw'!$C$20 | D39: ='balance_raw'!$D$20 | E39: ='balance_raw'!$E$20 | F39: ='balance_raw'!$F$20 | H39: =IFERROR(B39/$B$39*100,"") | I39: =IFERROR(C39/$B$39*100,"") | J39: =IFERROR(D39/$B$39*100,"") | K39: =IFERROR(E39/$B$39*100,"") | L39: =IFERROR(F39/$B$39*100,"")
A41: PASSIVER t.kr. | B41: 2022 | C41: 2023 | D41: 2024 | E41: 2025 | F41: 2026 | H41: 2022 | I41: 2023 | J41: 2024 | K41: 2025 | L41: 2026
A42: Selskabskapital | B42: ='balance_raw'!$B$21 | C42: ='balance_raw'!$C$21 | D42: ='balance_raw'!$D$21 | E42: ='balance_raw'!$E$21 | F42: ='balance_raw'!$F$21 | H42: =IFERROR(B42/$B$42*100,"") | I42: =IFERROR(C42/$B$42*100,"") | J42: =IFERROR(D42/$B$42*100,"") | K42: =IFERROR(E42/$B$42*100,"") | L42: =IFERROR(F42/$B$42*100,"")
A43: Reserve for nettoopskrivning (indre værdis metode) | B43: ='balance_raw'!$B$22 | C43: ='balance_raw'!$C$22 | D43: ='balance_raw'!$D$22 | E43: ='balance_raw'!$E$22 | F43: ='balance_raw'!$F$22 | H43: =IFERROR(B43/$B$43*100,"") | I43: =IFERROR(C43/$B$43*100,"") | J43: =IFERROR(D43/$B$43*100,"") | K43: =IFERROR(E43/$B$43*100,"") | L43: =IFERROR(F43/$B$43*100,"")
A44: Reserve for udviklingsomkostninger | B44: ='balance_raw'!$B$23 | C44: ='balance_raw'!$C$23 | D44: ='balance_raw'!$D$23 | E44: ='balance_raw'!$E$23 | F44: ='balance_raw'!$F$23 | H44: =IFERROR(B44/$B$44*100,"") | I44: =IFERROR(C44/$B$44*100,"") | J44: =IFERROR(D44/$B$44*100,"") | K44: =IFERROR(E44/$B$44*100,"") | L44: =IFERROR(F44/$B$44*100,"")
A45: Reserve for sikringstransaktioner | B45: ='balance_raw'!$B$24 | C45: ='balance_raw'!$C$24 | D45: ='balance_raw'!$D$24 | E45: ='balance_raw'!$E$24 | F45: ='balance_raw'!$F$24 | H45: =IFERROR(B45/$B$45*100,"") | I45: =IFERROR(C45/$B$45*100,"") | J45: =IFERROR(D45/$B$45*100,"") | K45: =IFERROR(E45/$B$45*100,"") | L45: =IFERROR(F45/$B$45*100,"")
A46: Andre reserver | B46: ='balance_raw'!$B$25 | C46: ='balance_raw'!$C$25 | D46: ='balance_raw'!$D$25 | E46: ='balance_raw'!$E$25 | F46: ='balance_raw'!$F$25 | H46: =IFERROR(B46/$B$46*100,"") | I46: =IFERROR(C46/$B$46*100,"") | J46: =IFERROR(D46/$B$46*100,"") | K46: =IFERROR(E46/$B$46*100,"") | L46: =IFERROR(F46/$B$46*100,"")
A47: Overført resultat | B47: ='balance_raw'!$B$26 | C47: ='balance_raw'!$C$26 | D47: ='balance_raw'!$D$26 | E47: ='balance_raw'!$E$26 | F47: ='balance_raw'!$F$26 | H47: =IFERROR(B47/$B$47*100,"") | I47: =IFERROR(C47/$B$47*100,"") | J47: =IFERROR(D47/$B$47*100,"") | K47: =IFERROR(E47/$B$47*100,"") | L47: =IFERROR(F47/$B$47*100,"")
A48: Egenkapital i alt | B48: ='balance_raw'!$B$27 | C48: ='balance_raw'!$C$27 | D48: ='balance_raw'!$D$27 | E48: ='balance_raw'!$E$27 | F48: ='balance_raw'!$F$27 | H48: =IFERROR(B48/$B$48*100,"") | I48: =IFERROR(C48/$B$48*100,"") | J48: =IFERROR(D48/$B$48*100,"") | K48: =IFERROR(E48/$B$48*100,"") | L48: =IFERROR(F48/$B$48*100,"")
A49: Hensættelse til udskudt skat | B49: ='balance_raw'!$B$28 | C49: ='balance_raw'!$C$28 | D49: ='balance_raw'!$D$28 | E49: ='balance_raw'!$E$28 | F49: ='balance_raw'!$F$28 | H49: =IFERROR(B49/$B$49*100,"") | I49: =IFERROR(C49/$B$49*100,"") | J49: =IFERROR(D49/$B$49*100,"") | K49: =IFERROR(E49/$B$49*100,"") | L49: =IFERROR(F49/$B$49*100,"")
A50: Hensatte forpligtelser | B50: ='balance_raw'!$B$29 | C50: ='balance_raw'!$C$29 | D50: ='balance_raw'!$D$29 | E50: ='balance_raw'!$E$29 | F50: ='balance_raw'!$F$29 | H50: =IFERROR(B50/$B$50*100,"") | I50: =IFERROR(C50/$B$50*100,"") | J50: =IFERROR(D50/$B$50*100,"") | K50: =IFERROR(E50/$B$50*100,"") | L50: =IFERROR(F50/$B$50*100,"")
A51: Ansvarlig lånekapital (langfristet) | B51: ='balance_raw'!$B$30 | C51: ='balance_raw'!$C$30 | D51: ='balance_raw'!$D$30 | E51: ='balance_raw'!$E$30 | F51: ='balance_raw'!$F$30 | H51: =IFERROR(B51/$B$51*100,"") | I51: =IFERROR(C51/$B$51*100,"") | J51: =IFERROR(D51/$B$51*100,"") | K51: =IFERROR(E51/$B$51*100,"") | L51: =IFERROR(F51/$B$51*100,"")
A52: Langfristede lån | B52: ='balance_raw'!$B$31 | C52: ='balance_raw'!$C$31 | D52: ='balance_raw'!$D$31 | E52: ='balance_raw'!$E$31 | F52: ='balance_raw'!$F$31 | H52: =IFERROR(B52/$B$52*100,"") | I52: =IFERROR(C52/$B$52*100,"") | J52: =IFERROR(D52/$B$52*100,"") | K52: =IFERROR(E52/$B$52*100,"") | L52: =IFERROR(F52/$B$52*100,"")
A53: Leasingforpligtelser (langfristet) | B53: ='balance_raw'!$B$32 | C53: ='balance_raw'!$C$32 | D53: ='balance_raw'!$D$32 | E53: ='balance_raw'!$E$32 | F53: ='balance_raw'!$F$32 | H53: =IFERROR(B53/$B$53*100,"") | I53: =IFERROR(C53/$B$53*100,"") | J53: =IFERROR(D53/$B$53*100,"") | K53: =IFERROR(E53/$B$53*100,"") | L53: =IFERROR(F53/$B$53*100,"")
A54: Anden gæld (langfristet) | B54: ='balance_raw'!$B$33 | C54: ='balance_raw'!$C$33 | D54: ='balance_raw'!$D$33 | E54: ='balance_raw'!$E$33 | F54: ='balance_raw'!$F$33 | H54: =IFERROR(B54/$B$54*100,"") | I54: =IFERROR(C54/$B$54*100,"") | J54: =IFERROR(D54/$B$54*100,"") | K54: =IFERROR(E54/$B$54*100,"") | L54: =IFERROR(F54/$B$54*100,"")
A55: Langfristede gældsforpligtelser | B55: ='balance_raw'!$B$34 | C55: ='balance_raw'!$C$34 | D55: ='balance_raw'!$D$34 | E55: ='balance_raw'!$E$34 | F55: ='balance_raw'!$F$34 | H55: =IFERROR(B55/$B$55*100,"") | I55: =IFERROR(C55/$B$55*100,"") | J55: =IFERROR(D55/$B$55*100,"") | K55: =IFERROR(E55/$B$55*100,"") | L55: =IFERROR(F55/$B$55*100,"")
A56: Ansvarlig lånekapital (kortfristet) | B56: ='balance_raw'!$B$35 | C56: ='balance_raw'!$C$35 | D56: ='balance_raw'!$D$35 | E56: ='balance_raw'!$E$35 | F56: ='balance_raw'!$F$35 | H56: =IFERROR(B56/$B$56*100,"") | I56: =IFERROR(C56/$B$56*100,"") | J56: =IFERROR(D56/$B$56*100,"") | K56: =IFERROR(E56/$B$56*100,"") | L56: =IFERROR(F56/$B$56*100,"")
A57: Kortfristet del af langfristede gældsforpligtelser | B57: ='balance_raw'!$B$36 | C57: ='balance_raw'!$C$36 | D57: ='balance_raw'!$D$36 | E57: ='balance_raw'!$E$36 | F57: ='balance_raw'!$F$36 | H57: =IFERROR(B57/$B$57*100,"") | I57: =IFERROR(C57/$B$57*100,"") | J57: =IFERROR(D57/$B$57*100,"") | K57: =IFERROR(E57/$B$57*100,"") | L57: =IFERROR(F57/$B$57*100,"")
A58: Kreditinstitutter | B58: ='balance_raw'!$B$37 | C58: ='balance_raw'!$C$37 | D58: ='balance_raw'!$D$37 | E58: ='balance_raw'!$E$37 | F58: ='balance_raw'!$F$37 | H58: =IFERROR(B58/$B$58*100,"") | I58: =IFERROR(C58/$B$58*100,"") | J58: =IFERROR(D58/$B$58*100,"") | K58: =IFERROR(E58/$B$58*100,"") | L58: =IFERROR(F58/$B$58*100,"")
A59: Leasingforpligtelser (kortfristet) | B59: ='balance_raw'!$B$38 | C59: ='balance_raw'!$C$38 | D59: ='balance_raw'!$D$38 | E59: ='balance_raw'!$E$38 | F59: ='balance_raw'!$F$38 | H59: =IFERROR(B59/$B$59*100,"") | I59: =IFERROR(C59/$B$59*100,"") | J59: =IFERROR(D59/$B$59*100,"") | K59: =IFERROR(E59/$B$59*100,"") | L59: =IFERROR(F59/$B$59*100,"")
A60: Leverandører af varer og tjenesteydelser | B60: ='balance_raw'!$B$39 | C60: ='balance_raw'!$C$39 | D60: ='balance_raw'!$D$39 | E60: ='balance_raw'!$E$39 | F60: ='balance_raw'!$F$39 | H60: =IFERROR(B60/$B$60*100,"") | I60: =IFERROR(C60/$B$60*100,"") | J60: =IFERROR(D60/$B$60*100,"") | K60: =IFERROR(E60/$B$60*100,"") | L60: =IFERROR(F60/$B$60*100,"")
A61: Gæld til tilknyttede virksomheder | B61: ='balance_raw'!$B$40 | C61: ='balance_raw'!$C$40 | D61: ='balance_raw'!$D$40 | E61: ='balance_raw'!$E$40 | F61: ='balance_raw'!$F$40 | H61: =IFERROR(B61/$B$61*100,"") | I61: =IFERROR(C61/$B$61*100,"") | J61: =IFERROR(D61/$B$61*100,"") | K61: =IFERROR(E61/$B$61*100,"") | L61: =IFERROR(F61/$B$61*100,"")
A62: Gæld til selskabsdeltagere og ledelse | B62: ='balance_raw'!$B$41 | C62: ='balance_raw'!$C$41 | D62: ='balance_raw'!$D$41 | E62: ='balance_raw'!$E$41 | F62: ='balance_raw'!$F$41 | H62: =IFERROR(B62/$B$62*100,"") | I62: =IFERROR(C62/$B$62*100,"") | J62: =IFERROR(D62/$B$62*100,"") | K62: =IFERROR(E62/$B$62*100,"") | L62: =IFERROR(F62/$B$62*100,"")
A63: Selskabsskat | B63: ='balance_raw'!$B$42 | C63: ='balance_raw'!$C$42 | D63: ='balance_raw'!$D$42 | E63: ='balance_raw'!$E$42 | F63: ='balance_raw'!$F$42 | H63: =IFERROR(B63/$B$63*100,"") | I63: =IFERROR(C63/$B$63*100,"") | J63: =IFERROR(D63/$B$63*100,"") | K63: =IFERROR(E63/$B$63*100,"") | L63: =IFERROR(F63/$B$63*100,"")
A64: Gæld til tilknyttede virksomheder vedr. selskabsskat | B64: ='balance_raw'!$B$43 | C64: ='balance_raw'!$C$43 | D64: ='balance_raw'!$D$43 | E64: ='balance_raw'!$E$43 | F64: ='balance_raw'!$F$43 | H64: =IFERROR(B64/$B$64*100,"") | I64: =IFERROR(C64/$B$64*100,"") | J64: =IFERROR(D64/$B$64*100,"") | K64: =IFERROR(E64/$B$64*100,"") | L64: =IFERROR(F64/$B$64*100,"")
A65: Anden gæld (kortfristet) | B65: ='balance_raw'!$B$44 | C65: ='balance_raw'!$C$44 | D65: ='balance_raw'!$D$44 | E65: ='balance_raw'!$E$44 | F65: ='balance_raw'!$F$44 | H65: =IFERROR(B65/$B$65*100,"") | I65: =IFERROR(C65/$B$65*100,"") | J65: =IFERROR(D65/$B$65*100,"") | K65: =IFERROR(E65/$B$65*100,"") | L65: =IFERROR(F65/$B$65*100,"")
A66: Periodeafgrænsningsposter (passiver) | B66: ='balance_raw'!$B$45 | C66: ='balance_raw'!$C$45 | D66: ='balance_raw'!$D$45 | E66: ='balance_raw'!$E$45 | F66: ='balance_raw'!$F$45 | H66: =IFERROR(B66/$B$66*100,"") | I66: =IFERROR(C66/$B$66*100,"") | J66: =IFERROR(D66/$B$66*100,"") | K66: =IFERROR(E66/$B$66*100,"") | L66: =IFERROR(F66/$B$66*100,"")
A67: Kortfristede gældsforpligtelser | B67: ='balance_raw'!$B$46 | C67: ='balance_raw'!$C$46 | D67: ='balance_raw'!$D$46 | E67: ='balance_raw'!$E$46 | F67: ='balance_raw'!$F$46 | H67: =IFERROR(B67/$B$67*100,"") | I67: =IFERROR(C67/$B$67*100,"") | J67: =IFERROR(D67/$B$67*100,"") | K67: =IFERROR(E67/$B$67*100,"") | L67: =IFERROR(F67/$B$67*100,"")
A68: Gældsforpligtelser | B68: ='balance_raw'!$B$47 | C68: ='balance_raw'!$C$47 | D68: ='balance_raw'!$D$47 | E68: ='balance_raw'!$E$47 | F68: ='balance_raw'!$F$47 | H68: =IFERROR(B68/$B$68*100,"") | I68: =IFERROR(C68/$B$68*100,"") | J68: =IFERROR(D68/$B$68*100,"") | K68: =IFERROR(E68/$B$68*100,"") | L68: =IFERROR(F68/$B$68*100,"")
A69: Passiver | B69: ='balance_raw'!$B$48 | C69: ='balance_raw'!$C$48 | D69: ='balance_raw'!$D$48 | E69: ='balance_raw'!$E$48 | F69: ='balance_raw'!$F$48 | H69: =IFERROR(B69/$B$69*100,"") | I69: =IFERROR(C69/$B$69*100,"") | J69: =IFERROR(D69/$B$69*100,"") | K69: =IFERROR(E69/$B$69*100,"") | L69: =IFERROR(F69/$B$69*100,"")
A71: NØGLEOPLYSNINGER | B71: 2022 | C71: 2023 | D71: 2024 | E71: 2025 | F71: 2026
A72: Gns. antal medarbejdere | B72: ='res_raw'!$B$17 | C72: ='res_raw'!$C$17 | D72: ='res_raw'!$D$17 | E72: ='res_raw'!$E$17 | F72: ='res_raw'!$F$17 | H72: =IFERROR(B72/$B$72*100,"") | I72: =IFERROR(C72/$B$72*100,"") | J72: =IFERROR(D72/$B$72*100,"") | K72: =IFERROR(E72/$B$72*100,"") | L72: =IFERROR(F72/$B$72*100,"")
A73: Investering i materielle anlægsaktiver | B73: ='res_raw'!$B$18 | C73: ='res_raw'!$C$18 | D73: ='res_raw'!$D$18 | E73: ='res_raw'!$E$18 | F73: ='res_raw'!$F$18 | H73: =IFERROR(B73/$B$73*100,"") | I73: =IFERROR(C73/$B$73*100,"") | J73: =IFERROR(D73/$B$73*100,"") | K73: =IFERROR(E73/$B$73*100,"") | L73: =IFERROR(F73/$B$73*100,"")
A75: NØGLETAL | B75: 2022 | C75: 2023 | D75: 2024 | E75: 2025 | F75: 2026
A76: Afkastningsgrad, % | B76: =IFERROR(($B$11+$B$13+$B$12)/$B$39*100,"") | C76: =IFERROR(($C$11+$C$13+$C$12)/$C$39*100,"") | D76: =IFERROR(($D$11+$D$13+$D$12)/$D$39*100,"") | E76: =IFERROR(($E$11+$E$13+$E$12)/$E$39*100,"") | F76: =IFERROR(($F$11+$F$13+$F$12)/$F$39*100,"")
A77: Overskudsgrad, % | B77: =IFERROR(($B$11+$B$13+$B$12)/$B$4*100,"") | C77: =IFERROR(($C$11+$C$13+$C$12)/$C$4*100,"") | D77: =IFERROR(($D$11+$D$13+$D$12)/$D$4*100,"") | E77: =IFERROR(($E$11+$E$13+$E$12)/$E$4*100,"") | F77: =IFERROR(($F$11+$F$13+$F$12)/$F$4*100,"")
A78: Aktivernes omsætningshastighed, gange | B78: =IFERROR($B$4/$B$39,"") | C78: =IFERROR($C$4/$C$39,"") | D78: =IFERROR($D$4/$D$39,"") | E78: =IFERROR($E$4/$E$39,"") | F78: =IFERROR($F$4/$F$39,"")
A79: Egenkapitalens forrentning, % | B79: =IFERROR($B$16/$B$48*100,"") | C79: =IFERROR($C$16/$C$48*100,"") | D79: =IFERROR($D$16/$D$48*100,"") | E79: =IFERROR($E$16/$E$48*100,"") | F79: =IFERROR($F$16/$F$48*100,"")
A80: Gældsrente, % | B80: =IFERROR($B$14/($B$69-$B$48)*100,"") | C80: =IFERROR($C$14/($C$69-$C$48)*100,"") | D80: =IFERROR($D$14/($D$69-$D$48)*100,"") | E80: =IFERROR($E$14/($E$69-$E$48)*100,"") | F80: =IFERROR($F$14/($F$69-$F$48)*100,"")
A81: Soliditetsgrad, % | B81: =IFERROR($B$48/$B$39*100,"") | C81: =IFERROR($C$48/$C$39*100,"") | D81: =IFERROR($D$48/$D$39*100,"") | E81: =IFERROR($E$48/$E$39*100,"") | F81: =IFERROR($F$48/$F$39*100,"")
A82: Gearing | B82: =IFERROR(($B$69-$B$48)/$B$48,"") | C82: =IFERROR(($C$69-$C$48)/$C$48,"") | D82: =IFERROR(($D$69-$D$48)/$D$48,"") | E82: =IFERROR(($E$69-$E$48)/$E$48,"") | F82: =IFERROR(($F$69-$F$48)/$F$48,"")
A83: Likviditetsgrad, % | B83: =IFERROR($B$38/$B$67*100,"") | C83: =IFERROR($C$38/$C$67*100,"") | D83: =IFERROR($D$38/$D$67*100,"") | E83: =IFERROR($E$38/$E$67*100,"") | F83: =IFERROR($F$38/$F$67*100,"")
A84: Rentemarginal, % | B84: =IFERROR(B76-B80,"") | C84: =IFERROR(C76-C80,"") | D84: =IFERROR(D76-D80,"") | E84: =IFERROR(E76-E80,"") | F84: =IFERROR(F76-F80,"")
A85: Gældsandel, % | B85: =IFERROR(($B$69-$B$48)/$B$39*100,"") | C85: =IFERROR(($C$69-$C$48)/$C$39*100,"") | D85: =IFERROR(($D$69-$D$48)/$D$39*100,"") | E85: =IFERROR(($E$69-$E$48)/$E$39*100,"") | F85: =IFERROR(($F$69-$F$48)/$F$39*100,"")
A86: Kapitalbindingsgrad, % | B86: =IFERROR($B$26/($B$48+$B$55)*100,"") | C86: =IFERROR($C$26/($C$48+$C$55)*100,"") | D86: =IFERROR($D$26/($D$48+$D$55)*100,"") | E86: =IFERROR($E$26/($E$48+$E$55)*100,"") | F86: =IFERROR($F$26/($F$48+$F$55)*100,"")
A88: PENGESTRØMSOPGØRELSE t.kr.
A89: Pengestrømme fra driftsaktivitet | B89: ='pengestrom_raw'!$B$2 | C89: ='pengestrom_raw'!$C$2 | D89: ='pengestrom_raw'!$D$2 | E89: ='pengestrom_raw'!$E$2 | F89: ='pengestrom_raw'!$F$2
A90: Pengestrømme fra investeringsaktivitet | B90: ='pengestrom_raw'!$B$3 | C90: ='pengestrom_raw'!$C$3 | D90: ='pengestrom_raw'!$D$3 | E90: ='pengestrom_raw'!$E$3 | F90: ='pengestrom_raw'!$F$3
A91: Pengestrømme fra finansieringsaktivitet | B91: ='pengestrom_raw'!$B$4 | C91: ='pengestrom_raw'!$C$4 | D91: ='pengestrom_raw'!$D$4 | E91: ='pengestrom_raw'!$E$4 | F91: ='pengestrom_raw'!$F$4
A92: Årets pengestrøm (rapporteret) | B92: ='pengestrom_raw'!$B$5 | C92: ='pengestrom_raw'!$C$5 | D92: ='pengestrom_raw'!$D$5 | E92: ='pengestrom_raw'!$E$5 | F92: ='pengestrom_raw'!$F$5
A93: Krydstjek: drift + inv. + fin. = årets pengestrøm | B93: =IF(ABS(('pengestrom_raw'!$B$2+'pengestrom_raw'!$B$3+'pengestrom_raw'!$B$4)-'pengestrom_raw'!$B$5)<=2,"✓","⚠ "&TEXT(('pengestrom_raw'!$B$2+'pengestrom_raw'!$B$3+'pengestrom_raw'!$B$4)-'pengestrom_raw'!$B$5,"+#,##0;-#,##0")) | C93: =IF(ABS(('pengestrom_raw'!$C$2+'pengestrom_raw'!$C$3+'pengestrom_raw'!$C$4)-'pengestrom_raw'!$C$5)<=2,"✓","⚠ "&TEXT(('pengestrom_raw'!$C$2+'pengestrom_raw'!$C$3+'pengestrom_raw'!$C$4)-'pengestrom_raw'!$C$5,"+#,##0;-#,##0")) | D93: =IF(ABS(('pengestrom_raw'!$D$2+'pengestrom_raw'!$D$3+'pengestrom_raw'!$D$4)-'pengestrom_raw'!$D$5)<=2,"✓","⚠ "&TEXT(('pengestrom_raw'!$D$2+'pengestrom_raw'!$D$3+'pengestrom_raw'!$D$4)-'pengestrom_raw'!$D$5,"+#,##0;-#,##0")) | E93: =IF(ABS(('pengestrom_raw'!$E$2+'pengestrom_raw'!$E$3+'pengestrom_raw'!$E$4)-'pengestrom_raw'!$E$5)<=2,"✓","⚠ "&TEXT(('pengestrom_raw'!$E$2+'pengestrom_raw'!$E$3+'pengestrom_raw'!$E$4)-'pengestrom_raw'!$E$5,"+#,##0;-#,##0")) | F93: =IF(ABS(('pengestrom_raw'!$F$2+'pengestrom_raw'!$F$3+'pengestrom_raw'!$F$4)-'pengestrom_raw'!$F$5)<=2,"✓","⚠ "&TEXT(('pengestrom_raw'!$F$2+'pengestrom_raw'!$F$3+'pengestrom_raw'!$F$4)-'pengestrom_raw'!$F$5,"+#,##0;-#,##0"))

Sheet res_raw
A1: bogo (CVR None) — Resultatopgørelse & nøgleoplysninger (t.kr.) | B1: 2022 | C1: 2023 | D1: 2024 | E1: 2025 | F1: 2026
A2: Nettoomsætning | B2: 2948000 | C2: 2752000 | D2: 2588000 | E2: 2553000 | F2: 2468000
A3: Produktionsomkostninger | B3: 1612000 | C3: 1537000 | D3: 1209000 | E3: 1149000 | F3: 1032000
A4: Bruttoresultat | B4: 1336000 | C4: 1215000 | D4: 1379000 | E4: 1404000 | F4: 1436000
A5: Salgs- og distributionsomkostninger
A6: Administrationsomkostninger | B6: 136000 | C6: 128000 | D6: 135000 | E6: 153000 | F6: 139000
A7: Andre driftsindtægter | E7: 0 | F7: 11000
A8: Andre driftsomkostninger
A9: Resultat af primær drift | B9: 46000 | C9: -124000 | D9: 18000 | E9: 16000 | F9: -76000
A10: Indtægter af kapitalandele, dattervirksomheder
A11: Finansielle indtægter | B11: 11000 | C11: 28000 | D11: 50000 | E11: 68000 | F11: 84000
A12: Finansielle omkostninger | B12: 65000 | C12: 56000 | D12: 75000 | E12: 82000 | F12: 71000
A13: Finansielle poster, netto
A14: Resultat før skat | B14: -8000 | C14: -152000 | D14: -7000 | E14: 2000 | F14: -63000
A15: Skat af årets resultat | B15: 22000 | C15: -11000 | D15: 10000 | E15: 31000 | F15: 44000
A16: Årets resultat | B16: -30000 | C16: -141000 | D16: -17000 | E16: -29000 | F16: -107000
A17: Gns. antal medarbejdere
A18: Investering i materielle anlægsaktiver | B18: 68000 | C18: 54000 | D18: 55000 | E18: 39000 | F18: 57000

Sheet balance_raw
A1: bogo (CVR None) — Balance (t.kr.) | B1: 2022 | C1: 2023 | D1: 2024 | E1: 2025 | F1: 2026
A2: Udviklingsprojekter | B2: 97000 | C2: 129000 | D2: 150000 | E2: 159000 | F2: 179000
A3: Patenter, varemærker mv.
A4: Goodwill | B4: 42000 | C4: 42000 | D4: 42000 | E4: 42000 | F4: 42000
A5: Immaterielle anlægsaktiver | B5: 334000 | C5: 375000 | D5: 396000 | E5: 447000 | F5: 485000
A6: Materielle anlægsaktiver | B6: 215000 | C6: 215000 | D6: 220000 | E6: 211000 | F6: 214000
A7: Anlægsaktiver | B7: 761000 | C7: 832000 | D7: 864000 | E7: 889000 | F7: 1009000
A8: Varebeholdninger | B8: 629000 | C8: 499000 | D8: 447000 | E8: 447000 | F8: 418000
A9: Tilgodehavender fra salg og tjenesteydelser | B9: 397000 | C9: 341000 | D9: 309000 | E9: 348000 | F9: 300000
A10: Tilgodehavender hos tilknyttede virksomheder
A11: Andre tilgodehavender
A12: Periodeafgrænsningsposter (aktiver) | B12: 28000 | C12: 24000 | D12: 27000 | E12: 42000 | F12: 33000
A13: Udskudt skatteaktiv | B13: 77000 | C13: 99000 | D13: 92000 | E13: 75000 | F13: 41000
A14: Tilgodehavende skat hos tilknyttede virksomheder
A15: Kortfristede skattetilgodehavender | B15: 37000 | C15: 11000 | D15: 32000 | E15: 28000 | F15: 27000
A16: Tilgodehavender | B16: 89000 | C16: 68000 | D16: 53000 | E16: 61000 | F16: 61000
A17: Værdipapirer
A18: Likvide beholdninger | B18: 162000 | C18: 216000 | D18: 177000 | E18: 145000 | F18: 134000
A19: Omsætningsaktiver | B19: 1757000 | C19: 1553000 | D19: 1433000 | E19: 1451000 | F19: 1213000
A20: Aktiver | B20: 2518000 | C20: 2385000 | D20: 2297000 | E20: 2340000 | F20: 2222000
A21: Selskabskapital | B21: 613000 | C21: 613000 | D21: 613000 | E21: 737000 | F21: 737000
A22: Reserve for nettoopskrivning (indre værdis metode)
A23: Reserve for udviklingsomkostninger
A24: Reserve for sikringstransaktioner
A25: Andre reserver | B25: -5000 | C25: -4000 | D25: -2000 | E25: -2000 | F25: -3000
A26: Overført resultat | B26: 460000 | C26: 329000 | D26: 329000 | E26: 402000 | F26: 264000
A27: Egenkapital i alt | B27: 1100000 | C27: 958000 | D27: 956000 | E27: 1144000 | F27: 1006000
A28: Hensættelse til udskudt skat | B28: 6000 | C28: 6000 | D28: 8000 | E28: 8000 | F28: 9000
A29: Hensatte forpligtelser | B29: 12000 | C29: 11000 | D29: 10000 | E29: 15000 | F29: 10000
A30: Ansvarlig lånekapital (langfristet)
A31: Langfristede lån
A32: Leasingforpligtelser (langfristet) | B32: 95000 | C32: 109000 | D32: 117000 | E32: 104000 | F32: 221000
A33: Anden gæld (langfristet) | B33: 58000 | C33: 56000 | D33: 53000 | E33: 50000 | F33: 42000
A34: Langfristede gældsforpligtelser | B34: 233000 | C34: 225000 | D34: 236000 | E34: 216000 | F34: 313000
A35: Ansvarlig lånekapital (kortfristet)
A36: Kortfristet del af langfristede gældsforpligtelser
A37: Kreditinstitutter | B37: 4000 | C37: 3000 | D37: 3000 | E37: 3000 | F37: 3000
A38: Leasingforpligtelser (kortfristet) | B38: 39000 | C38: 37000 | D38: 45000 | E38: 59000 | F38: 70000
A39: Leverandører af varer og tjenesteydelser | B39: 581000 | C39: 565000 | D39: 401000 | E39: 453000 | F39: 313000
A40: Gæld til tilknyttede virksomheder
A41: Gæld til selskabsdeltagere og ledelse
A42: Selskabsskat
A43: Gæld til tilknyttede virksomheder vedr. selskabsskat
A44: Anden gæld (kortfristet) | B44: 212000 | C44: 143000 | D44: 171000 | E44: 227000 | F44: 150000
A45: Periodeafgrænsningsposter (passiver)
A46: Kortfristede gældsforpligtelser | B46: 1185000 | C46: 1202000 | D46: 1105000 | E46: 980000 | F46: 903000
A47: Gældsforpligtelser | B47: 1418000 | C47: 1427000 | D47: 1341000 | E47: 1196000 | F47: 1216000
A48: Passiver | B48: 2518000 | C48: 2385000 | D48: 2297000 | E48: 2340000 | F48: 2222000

Sheet pengestrom_raw
A1: bogo (CVR None) — Pengestrømsopgørelse (t.kr.) | B1: 2022 | C1: 2023 | D1: 2024 | E1: 2025 | F1: 2026
A2: Pengestrømme fra driftsaktivitet | B2: 76000 | C2: 198000 | D2: 226000 | E2: 256000 | F2: 104000
A3: Pengestrømme fra investeringsaktivitet | B3: -239000 | C3: -204000 | D3: -209000 | E3: -231000 | F3: -105000
A4: Pengestrømme fra finansieringsaktivitet | B4: 145000 | C4: 64000 | D4: -54000 | E4: -58000 | F4: -8000
A5: Årets pengestrøm

Sheet Simpel_funktion
A1: bogo (CVR None) — Regnskabs- og nøgletal — funktionsopdelt
A3: Beløb i 1.000 kr. | B3: 2026 | C3: 2025 | D3: 2024 | F3: Note / XBRL-felt
A4: Uddrag af resultatopgørelse
A5: Nettoomsætning | B5: ='res_raw'!$F$2 | C5: ='res_raw'!$E$2 | D5: ='res_raw'!$D$2 | F5: fsa:Revenue
A6: Produktionsomkostninger | B6: =-'res_raw'!$F$3 | C6: =-'res_raw'!$E$3 | D6: =-'res_raw'!$D$3 | F6: fsa:CostOfProduction (vises negativt). Materialer, lønninger, produktionsoverhead.
A7: Bruttoresultat | B7: =IF(COUNT('res_raw'!$F$2,'res_raw'!$F$3)=0,'res_raw'!$F$4,SUM(B5:B6)) | C7: =IF(COUNT('res_raw'!$E$2,'res_raw'!$E$3)=0,'res_raw'!$E$4,SUM(C5:C6)) | D7: =IF(COUNT('res_raw'!$D$2,'res_raw'!$D$3)=0,'res_raw'!$D$4,SUM(D5:D6)) | F7: Beregnet: Nettoomsætning − Produktionsomkostninger. Matcher fsa:GrossResult. Er komponenterne ikke indberettet, vises rapporteret fsa:GrossResult direkte.
A8: Salgs- og distributionsomk. | B8: =-'res_raw'!$F$5 | C8: =-'res_raw'!$E$5 | D8: =-'res_raw'!$D$5 | F8: fsa:DistributionCosts (vises negativt). Marketing, salg, distribution.
A9: Administrationsomkostninger mv. | B9: =-'res_raw'!$F$6 | C9: =-'res_raw'!$E$6 | D9: =-'res_raw'!$D$6 | F9: fsa:AdministrativeExpenses (vises negativt). Generel administration.
A10: Andre driftsindtægter | B10: ='res_raw'!$F$7 | C10: ='res_raw'!$E$7 | D10: ='res_raw'!$D$7 | F10: fsa:OtherOperatingIncome. Sekundære driftsindtægter (huslejeindtægter, off. tilskud, avancer mv.).
A11: Andre driftsomkostninger | B11: =-'res_raw'!$F$8 | C11: =-'res_raw'!$E$8 | D11: =-'res_raw'!$D$8 | F11: fsa:OtherOperatingExpenses (vises negativt). Sekundære driftsomkostninger.
A12: Resultat af primær drift | B12: =SUM(B7:B11) | C12: =SUM(C7:C11) | D12: =SUM(D7:D11) | F12: Beregnet: Bruttoresultat − Salgs/dist. − Administration + Andre driftsindt. − Andre driftsomk. EBIT.
A13: Finansielle indtægter mv. | B13: =N('res_raw'!$F$10)+N('res_raw'!$F$11) | C13: =N('res_raw'!$E$10)+N('res_raw'!$E$11) | D13: =N('res_raw'!$D$10)+N('res_raw'!$D$11) | F13: fsa:IncomeFromSubsidiaries + fsa:OtherFinanceIncome.
A14: Finansielle omkostninger mv. | B14: =-'res_raw'!$F$12 | C14: =-'res_raw'!$E$12 | D14: =-'res_raw'!$D$12 | F14: fsa:OtherFinanceExpenses (vises negativt). Renteomkostninger, kurstab.
A15: Resultat før skat | B15: =SUM(B12:B14) | C15: =SUM(C12:C14) | D15: =SUM(D12:D14) | F15: Beregnet: EBIT + Fin. indtægter + Fin. omk. EBT.
A17: Uddrag af balance
A18: Anlægsaktiver | B18: ='balance_raw'!$F$7 | C18: ='balance_raw'!$E$7 | D18: ='balance_raw'!$D$7 | F18: fsa:NoncurrentAssets. Materielle, immaterielle og finansielle anlægsaktiver.
A19: Omsætningsaktiver | B19: ='balance_raw'!$F$19 | C19: ='balance_raw'!$E$19 | D19: ='balance_raw'!$D$19 | F19: fsa:CurrentAssets. Varebeholdninger, tilgodehavender, likvider.
A20: Aktiver i alt | B20: =SUM(B18:B19) | C20: =SUM(C18:C19) | D20: =SUM(D18:D19) | F20: Beregnet: Anlægsaktiver + Omsætningsaktiver. Bør matche fsa:Assets.
A22: Egenkapital | B22: ='balance_raw'!$F$27 | C22: ='balance_raw'!$E$27 | D22: ='balance_raw'!$D$27 | F22: fsa:Equity. Selskabskapital, overført resultat, reserver.
A23: Forpligtelser | B23: ='balance_raw'!$F$48-'balance_raw'!$F$27 | C23: ='balance_raw'!$E$48-'balance_raw'!$E$27 | D23: ='balance_raw'!$D$48-'balance_raw'!$D$27 | F23: Beregnet: Passiver (fsa:LiabilitiesAndEquity) − Egenkapital. Hensættelser + kort- og langfristet gæld.
A24: Passiver i alt | B24: =SUM(B22:B23) | C24: =SUM(C22:C23) | D24: =SUM(D22:D23) | F24: Beregnet: Egenkapital + Forpligtelser. Bør matche Aktiver i alt.
A26: Udvalgte balanceposter
A27: Varebeholdninger | B27: ='balance_raw'!$F$8 | C27: ='balance_raw'!$E$8 | D27: ='balance_raw'!$D$8 | F27: fsa:Inventories (eller fsa:ManufacturedGoodsAndGoodsForResale hvis total mangler).
A28: Tilgodehavender fra salg | B28: ='balance_raw'!$F$9 | C28: ='balance_raw'!$E$9 | D28: ='balance_raw'!$D$9 | F28: fsa:ShorttermTradeReceivables. Kortfristede tilgodehavender fra kunder.
A29: Kortfristede gældsforpligtelser | B29: ='balance_raw'!$F$46 | C29: ='balance_raw'!$E$46 | D29: ='balance_raw'!$D$46 | F29: fsa:ShorttermLiabilitiesOtherThanProvisions. Gæld der forfalder inden for 1 år.
A31: Rentabilitet
A32: Afkastningsgrad, % | B32: =IFERROR((B12+B13)/B20*100,"") | C32: =IFERROR((C12+C13)/C20*100,"") | D32: =IFERROR((D12+D13)/D20*100,"")
A33: Overskudsgrad, % | B33: =IFERROR((B12+B13)/B5*100,"") | C33: =IFERROR((C12+C13)/C5*100,"") | D33: =IFERROR((D12+D13)/D5*100,"")
A34: Aktivernes omsætningshastighed, gange | B34: =IFERROR(B5/B20,"") | C34: =IFERROR(C5/C20,"") | D34: =IFERROR(D5/D20,"")
A35: Gældsrente, % | B35: =IFERROR(-B14*100/B23,"") | C35: =IFERROR(-C14*100/C23,"") | D35: =IFERROR(-D14*100/D23,"")
A36: Egenkapitalens forrentning, % | B36: =IFERROR(B15/B22*100,"") | C36: =IFERROR(C15/C22*100,"") | D36: =IFERROR(D15/D22*100,"")
A37: Gearing, gange | B37: =IFERROR(B23/B22,"") | C37: =IFERROR(C23/C22,"") | D37: =IFERROR(D23/D22,"")
A39: Indekstal for indtjeningsevne (2024=100)
A40: Nettoomsætning | B40: =IFERROR(B5/$D5*100,"") | C40: =IFERROR(C5/$D5*100,"") | D40: =IFERROR(D5/$D5*100,"")
A41: Produktionsomkostninger | B41: =IFERROR(B6/$D6*100,"") | C41: =IFERROR(C6/$D6*100,"") | D41: =IFERROR(D6/$D6*100,"")
A42: Salgs- og distributionsomk. | B42: =IFERROR(B8/$D8*100,"") | C42: =IFERROR(C8/$D8*100,"") | D42: =IFERROR(D8/$D8*100,"")
A43: Administrationsomk. | B43: =IFERROR(B9/$D9*100,"") | C43: =IFERROR(C9/$D9*100,"") | D43: =IFERROR(D9/$D9*100,"")
A44: Andre driftsomkostninger | B44: =IFERROR(B11/$D11*100,"") | C44: =IFERROR(C11/$D11*100,"") | D44: =IFERROR(D11/$D11*100,"")
A46: Indekstal for kapitaltilpasningsevne (2024=100)
A47: Nettoomsætning | B47: =IFERROR(B5*100/$D5,"") | C47: =IFERROR(C5*100/$D5,"") | D47: =IFERROR(D5*100/$D5,"")
A48: Anlægsaktiver | B48: =IFERROR(B18*100/$D18,"") | C48: =IFERROR(C18*100/$D18,"") | D48: =IFERROR(D18*100/$D18,"")
A49: Varebeholdninger | B49: =IFERROR(B27*100/$D27,"") | C49: =IFERROR(C27*100/$D27,"") | D49: =IFERROR(D27*100/$D27,"")
A50: Tilgodehavender fra salg | B50: =IFERROR(B28*100/$D28,"") | C50: =IFERROR(C28*100/$D28,"") | D50: =IFERROR(D28*100/$D28,"")
A52: Soliditet og likviditet
A53: Soliditetsgrad, % | B53: =IFERROR(B22*100/B20,"") | C53: =IFERROR(C22*100/C20,"") | D53: =IFERROR(D22*100/D20,"")
A54: Gældsandel, % | B54: =IFERROR(B23*100/B20,"") | C54: =IFERROR(C23*100/C20,"") | D54: =IFERROR(D23*100/D20,"")
A55: Likviditetsgrad, % | B55: =IFERROR(B19*100/B29,"") | C55: =IFERROR(C19*100/C29,"") | D55: =IFERROR(D19*100/D29,"")
A57: Kilde: Bearbejdet uddrag af årsrapporter for 2024-2026. Alle dataceller er live formler der peger på res_raw / balance_raw.
A59: Krydstjek mod rådata (tolerance: 1 t.kr.)
A60: Aktiver i alt = fsa:Assets | B60: =IF('balance_raw'!$F$20="","—",IF(ABS(B20-'balance_raw'!$F$20)<=1,"✓ OK","❌ "&TEXT(B20-'balance_raw'!$F$20,"+#,##0;-#,##0")&" t.kr.")) | C60: =IF('balance_raw'!$E$20="","—",IF(ABS(C20-'balance_raw'!$E$20)<=1,"✓ OK","❌ "&TEXT(C20-'balance_raw'!$E$20,"+#,##0;-#,##0")&" t.kr.")) | D60: =IF('balance_raw'!$D$20="","—",IF(ABS(D20-'balance_raw'!$D$20)<=1,"✓ OK","❌ "&TEXT(D20-'balance_raw'!$D$20,"+#,##0;-#,##0")&" t.kr.")) | F60: Verificerer at sum(Anlæg+Omsætning) matcher Assets-totalen.
A61: Passiver i alt = fsa:LiabilitiesAndEquity | B61: =IF('balance_raw'!$F$48="","—",IF(ABS(B24-'balance_raw'!$F$48)<=1,"✓ OK","❌ "&TEXT(B24-'balance_raw'!$F$48,"+#,##0;-#,##0")&" t.kr.")) | C61: =IF('balance_raw'!$E$48="","—",IF(ABS(C24-'balance_raw'!$E$48)<=1,"✓ OK","❌ "&TEXT(C24-'balance_raw'!$E$48,"+#,##0;-#,##0")&" t.kr.")) | D61: =IF('balance_raw'!$D$48="","—",IF(ABS(D24-'balance_raw'!$D$48)<=1,"✓ OK","❌ "&TEXT(D24-'balance_raw'!$D$48,"+#,##0;-#,##0")&" t.kr.")) | F61: Verificerer at sum(EK+Forpligtelser) matcher Passiver-totalen.
A62: Aktiver i alt = Passiver i alt | B62: =IF(ABS(B20-B24)<=1,"✓ OK","❌ "&TEXT(B20-B24,"+#,##0;-#,##0")&" t.kr.") | C62: =IF(ABS(C20-C24)<=1,"✓ OK","❌ "&TEXT(C20-C24,"+#,##0;-#,##0")&" t.kr.") | D62: =IF(ABS(D20-D24)<=1,"✓ OK","❌ "&TEXT(D20-D24,"+#,##0;-#,##0")&" t.kr.") | F62: Balance-identitet på arket selv. Skal altid være 0 differance.
A63: Bruttoresultat (beregnet) = fsa:GrossResult | B63: =IF('res_raw'!$F$4="","—",IF(ABS(B7-'res_raw'!$F$4)<=1,"✓ OK","❌ "&TEXT(B7-'res_raw'!$F$4,"+#,##0;-#,##0")&" t.kr.")) | C63: =IF('res_raw'!$E$4="","—",IF(ABS(C7-'res_raw'!$E$4)<=1,"✓ OK","❌ "&TEXT(C7-'res_raw'!$E$4,"+#,##0;-#,##0")&" t.kr.")) | D63: =IF('res_raw'!$D$4="","—",IF(ABS(D7-'res_raw'!$D$4)<=1,"✓ OK","❌ "&TEXT(D7-'res_raw'!$D$4,"+#,##0;-#,##0")&" t.kr.")) | F63: Hvis Nettoomsætning eller omkostninger mangler, vil sumberegnet bruttoresultat afvige.
A64: EBIT (beregnet) = fsa:ProfitLossFromOrdinaryOperatingActivities | B64: =IF('res_raw'!$F$9="","—",IF(ABS(B12-'res_raw'!$F$9)<=1,"✓ OK","❌ "&TEXT(B12-'res_raw'!$F$9,"+#,##0;-#,##0")&" t.kr.")) | C64: =IF('res_raw'!$E$9="","—",IF(ABS(C12-'res_raw'!$E$9)<=1,"✓ OK","❌ "&TEXT(C12-'res_raw'!$E$9,"+#,##0;-#,##0")&" t.kr.")) | D64: =IF('res_raw'!$D$9="","—",IF(ABS(D12-'res_raw'!$D$9)<=1,"✓ OK","❌ "&TEXT(D12-'res_raw'!$D$9,"+#,##0;-#,##0")&" t.kr.")) | F64: Verificerer at sumberegnet EBIT matcher det rapporterede.
A65: EBT (beregnet) = fsa:ProfitLossFromOrdinaryActivitiesBeforeTax | B65: =IF('res_raw'!$F$14="","—",IF(ABS(B15-'res_raw'!$F$14)<=1,"✓ OK","❌ "&TEXT(B15-'res_raw'!$F$14,"+#,##0;-#,##0")&" t.kr.")) | C65: =IF('res_raw'!$E$14="","—",IF(ABS(C15-'res_raw'!$E$14)<=1,"✓ OK","❌ "&TEXT(C15-'res_raw'!$E$14,"+#,##0;-#,##0")&" t.kr.")) | D65: =IF('res_raw'!$D$14="","—",IF(ABS(D15-'res_raw'!$D$14)<=1,"✓ OK","❌ "&TEXT(D15-'res_raw'!$D$14,"+#,##0;-#,##0")&" t.kr.")) | F65: Verificerer at sumberegnet resultat før skat matcher det rapporterede.

Sheet Noter_info
A1: bogo (CVR None) — Ukendte XBRL-felter — disse er noter og ikke en del af hoved-regnskabet
A2: Kategori | B2: Dansk navn | C2: XBRL feltnavn | D2: 2022 t.kr. | E2: 2023 t.kr. | F2: 2024 t.kr. | G2: 2025 t.kr. | H2: 2026 t.kr. | I2: Forklaring
A3: Øvrige (ukendt) | B3: ifrs-full:AdjustmentsForFinanceIncomeCost | C3: ifrs-full:AdjustmentsForFinanceIncomeCost | D3: -54000 | E3: -28000 | F3: -25000 | G3: -14000 | H3: 13000 | I3: Ingen forklaring tilgængelig.
A4: Øvrige (ukendt) | B4: ifrs-full:OtherInflowsOutflowsOfCashClassifiedAsFinancingActivities | C4: ifrs-full:OtherInflowsOutflowsOfCashClassifiedAsFinancingActivities | D4: -34000 | E4: 0 | I4: Ingen forklaring tilgængelig.
A5: Øvrige (ukendt) | B5: ifrs-full:OtherInflowsOutflowsOfCashClassifiedAsInvestingActivities | C5: ifrs-full:OtherInflowsOutflowsOfCashClassifiedAsInvestingActivities | D5: -2000 | E5: 3000 | F5: 1000 | G5: -2000 | H5: 0 | I5: Ingen forklaring tilgængelig.
A6: Øvrige (ukendt) | B6: ifrs-full:OtherInflowsOutflowsOfCashClassifiedAsOperatingActivities | C6: ifrs-full:OtherInflowsOutflowsOfCashClassifiedAsOperatingActivities | G6: 0 | H6: 25000 | I6: Ingen forklaring tilgængelig.
A7: Øvrige (ukendt) | B7: ifrs-full:ReserveOfExchangeDifferencesOnTranslation | C7: ifrs-full:ReserveOfExchangeDifferencesOnTranslation | D7: 32000 | E7: 20000 | F7: 16000 | G7: 7000 | H7: 8000 | I7: Ingen forklaring tilgængelig.
A8: Øvrige (ukendt) | B8: ifrs-full:SalesAndMarketingExpense | C8: ifrs-full:SalesAndMarketingExpense | D8: 875000 | E8: 910000 | F8: 940000 | G8: 895000 | H8: 1009000 | I8: Ingen forklaring tilgængelig.
