Workbook

Sheet Overblik_41852119
A1: Tetra Pak Processing Systems A/S (CVR 41852119) — Regnskabsanalyse – Resultatopgørelse & Balance (t.kr.) · Klasse C-mellem · Revision
H2: Indekstal (2021=100)
A3: Resultatopgørelse t.kr. | B3: 2021 | C3: 2022 | D3: 2023 | E3: 2024 | F3: 2025 | H3: 2021 | I3: 2022 | J3: 2023 | K3: 2024 | L3: 2025
A4: Nettoomsætning | B4: ='res_raw_41852119'!$B$2 | C4: ='res_raw_41852119'!$C$2 | D4: ='res_raw_41852119'!$D$2 | E4: ='res_raw_41852119'!$E$2 | F4: ='res_raw_41852119'!$F$2 | H4: =IFERROR(B4/$B$4*100,"") | I4: =IFERROR(C4/$B$4*100,"") | J4: =IFERROR(D4/$B$4*100,"") | K4: =IFERROR(E4/$B$4*100,"") | L4: =IFERROR(F4/$B$4*100,"")
A5: Produktionsomkostninger | B5: ='res_raw_41852119'!$B$3 | C5: ='res_raw_41852119'!$C$3 | D5: ='res_raw_41852119'!$D$3 | E5: ='res_raw_41852119'!$E$3 | F5: ='res_raw_41852119'!$F$3 | H5: =IFERROR(B5/$B$5*100,"") | I5: =IFERROR(C5/$B$5*100,"") | J5: =IFERROR(D5/$B$5*100,"") | K5: =IFERROR(E5/$B$5*100,"") | L5: =IFERROR(F5/$B$5*100,"")
A6: Bruttoresultat | B6: ='res_raw_41852119'!$B$4 | C6: ='res_raw_41852119'!$C$4 | D6: ='res_raw_41852119'!$D$4 | E6: ='res_raw_41852119'!$E$4 | F6: ='res_raw_41852119'!$F$4 | H6: =IFERROR(B6/$B$6*100,"") | I6: =IFERROR(C6/$B$6*100,"") | J6: =IFERROR(D6/$B$6*100,"") | K6: =IFERROR(E6/$B$6*100,"") | L6: =IFERROR(F6/$B$6*100,"")
A7: Udviklingsomkostninger | B7: ='res_raw_41852119'!$B$5 | C7: ='res_raw_41852119'!$C$5 | D7: ='res_raw_41852119'!$D$5 | E7: ='res_raw_41852119'!$E$5 | F7: ='res_raw_41852119'!$F$5 | H7: =IFERROR(B7/$B$7*100,"") | I7: =IFERROR(C7/$B$7*100,"") | J7: =IFERROR(D7/$B$7*100,"") | K7: =IFERROR(E7/$B$7*100,"") | L7: =IFERROR(F7/$B$7*100,"")
A8: Salgs- og distributionsomkostninger | B8: ='res_raw_41852119'!$B$6 | C8: ='res_raw_41852119'!$C$6 | D8: ='res_raw_41852119'!$D$6 | E8: ='res_raw_41852119'!$E$6 | F8: ='res_raw_41852119'!$F$6 | H8: =IFERROR(B8/$B$8*100,"") | I8: =IFERROR(C8/$B$8*100,"") | J8: =IFERROR(D8/$B$8*100,"") | K8: =IFERROR(E8/$B$8*100,"") | L8: =IFERROR(F8/$B$8*100,"")
A9: Administrationsomkostninger | B9: ='res_raw_41852119'!$B$7 | C9: ='res_raw_41852119'!$C$7 | D9: ='res_raw_41852119'!$D$7 | E9: ='res_raw_41852119'!$E$7 | F9: ='res_raw_41852119'!$F$7 | H9: =IFERROR(B9/$B$9*100,"") | I9: =IFERROR(C9/$B$9*100,"") | J9: =IFERROR(D9/$B$9*100,"") | K9: =IFERROR(E9/$B$9*100,"") | L9: =IFERROR(F9/$B$9*100,"")
A10: Andre driftsindtægter | B10: ='res_raw_41852119'!$B$8 | C10: ='res_raw_41852119'!$C$8 | D10: ='res_raw_41852119'!$D$8 | E10: ='res_raw_41852119'!$E$8 | F10: ='res_raw_41852119'!$F$8 | H10: =IFERROR(B10/$B$10*100,"") | I10: =IFERROR(C10/$B$10*100,"") | J10: =IFERROR(D10/$B$10*100,"") | K10: =IFERROR(E10/$B$10*100,"") | L10: =IFERROR(F10/$B$10*100,"")
A11: Andre driftsomkostninger | B11: ='res_raw_41852119'!$B$9 | C11: ='res_raw_41852119'!$C$9 | D11: ='res_raw_41852119'!$D$9 | E11: ='res_raw_41852119'!$E$9 | F11: ='res_raw_41852119'!$F$9 | H11: =IFERROR(B11/$B$11*100,"") | I11: =IFERROR(C11/$B$11*100,"") | J11: =IFERROR(D11/$B$11*100,"") | K11: =IFERROR(E11/$B$11*100,"") | L11: =IFERROR(F11/$B$11*100,"")
A12: Resultat af primær drift | B12: ='res_raw_41852119'!$B$10 | C12: ='res_raw_41852119'!$C$10 | D12: ='res_raw_41852119'!$D$10 | E12: ='res_raw_41852119'!$E$10 | F12: ='res_raw_41852119'!$F$10 | H12: =IFERROR(B12/$B$12*100,"") | I12: =IFERROR(C12/$B$12*100,"") | J12: =IFERROR(D12/$B$12*100,"") | K12: =IFERROR(E12/$B$12*100,"") | L12: =IFERROR(F12/$B$12*100,"")
A13: Indtægter af kapitalandele, dattervirksomheder | B13: ='res_raw_41852119'!$B$11 | C13: ='res_raw_41852119'!$C$11 | D13: ='res_raw_41852119'!$D$11 | E13: ='res_raw_41852119'!$E$11 | F13: ='res_raw_41852119'!$F$11 | H13: =IFERROR(B13/$B$13*100,"") | I13: =IFERROR(C13/$B$13*100,"") | J13: =IFERROR(D13/$B$13*100,"") | K13: =IFERROR(E13/$B$13*100,"") | L13: =IFERROR(F13/$B$13*100,"")
A14: Finansielle indtægter | B14: ='res_raw_41852119'!$B$12 | C14: ='res_raw_41852119'!$C$12 | D14: ='res_raw_41852119'!$D$12 | E14: ='res_raw_41852119'!$E$12 | F14: ='res_raw_41852119'!$F$12 | H14: =IFERROR(B14/$B$14*100,"") | I14: =IFERROR(C14/$B$14*100,"") | J14: =IFERROR(D14/$B$14*100,"") | K14: =IFERROR(E14/$B$14*100,"") | L14: =IFERROR(F14/$B$14*100,"")
A15: Finansielle omkostninger | B15: ='res_raw_41852119'!$B$13 | C15: ='res_raw_41852119'!$C$13 | D15: ='res_raw_41852119'!$D$13 | E15: ='res_raw_41852119'!$E$13 | F15: ='res_raw_41852119'!$F$13 | H15: =IFERROR(B15/$B$15*100,"") | I15: =IFERROR(C15/$B$15*100,"") | J15: =IFERROR(D15/$B$15*100,"") | K15: =IFERROR(E15/$B$15*100,"") | L15: =IFERROR(F15/$B$15*100,"")
A16: Finansielle poster, netto | B16: ='res_raw_41852119'!$B$14 | C16: ='res_raw_41852119'!$C$14 | D16: ='res_raw_41852119'!$D$14 | E16: ='res_raw_41852119'!$E$14 | F16: ='res_raw_41852119'!$F$14 | H16: =IFERROR(B16/$B$16*100,"") | I16: =IFERROR(C16/$B$16*100,"") | J16: =IFERROR(D16/$B$16*100,"") | K16: =IFERROR(E16/$B$16*100,"") | L16: =IFERROR(F16/$B$16*100,"")
A17: Resultat før skat | B17: ='res_raw_41852119'!$B$15 | C17: ='res_raw_41852119'!$C$15 | D17: ='res_raw_41852119'!$D$15 | E17: ='res_raw_41852119'!$E$15 | F17: ='res_raw_41852119'!$F$15 | H17: =IFERROR(B17/$B$17*100,"") | I17: =IFERROR(C17/$B$17*100,"") | J17: =IFERROR(D17/$B$17*100,"") | K17: =IFERROR(E17/$B$17*100,"") | L17: =IFERROR(F17/$B$17*100,"")
A18: Skat af årets resultat | B18: ='res_raw_41852119'!$B$16 | C18: ='res_raw_41852119'!$C$16 | D18: ='res_raw_41852119'!$D$16 | E18: ='res_raw_41852119'!$E$16 | F18: ='res_raw_41852119'!$F$16 | H18: =IFERROR(B18/$B$18*100,"") | I18: =IFERROR(C18/$B$18*100,"") | J18: =IFERROR(D18/$B$18*100,"") | K18: =IFERROR(E18/$B$18*100,"") | L18: =IFERROR(F18/$B$18*100,"")
A19: Årets resultat | B19: ='res_raw_41852119'!$B$17 | C19: ='res_raw_41852119'!$C$17 | D19: ='res_raw_41852119'!$D$17 | E19: ='res_raw_41852119'!$E$17 | F19: ='res_raw_41852119'!$F$17 | H19: =IFERROR(B19/$B$19*100,"") | I19: =IFERROR(C19/$B$19*100,"") | J19: =IFERROR(D19/$B$19*100,"") | K19: =IFERROR(E19/$B$19*100,"") | L19: =IFERROR(F19/$B$19*100,"")
A21: AKTIVER t.kr. | B21: 2021 | C21: 2022 | D21: 2023 | E21: 2024 | F21: 2025 | H21: 2021 | I21: 2022 | J21: 2023 | K21: 2024 | L21: 2025
A22: Grunde og bygninger | B22: ='balance_raw_41852119'!$B$2 | C22: ='balance_raw_41852119'!$C$2 | D22: ='balance_raw_41852119'!$D$2 | E22: ='balance_raw_41852119'!$E$2 | F22: ='balance_raw_41852119'!$F$2 | H22: =IFERROR(B22/$B$22*100,"") | I22: =IFERROR(C22/$B$22*100,"") | J22: =IFERROR(D22/$B$22*100,"") | K22: =IFERROR(E22/$B$22*100,"") | L22: =IFERROR(F22/$B$22*100,"")
A23: Produktionsanlæg og maskiner | B23: ='balance_raw_41852119'!$B$3 | C23: ='balance_raw_41852119'!$C$3 | D23: ='balance_raw_41852119'!$D$3 | E23: ='balance_raw_41852119'!$E$3 | F23: ='balance_raw_41852119'!$F$3 | H23: =IFERROR(B23/$B$23*100,"") | I23: =IFERROR(C23/$B$23*100,"") | J23: =IFERROR(D23/$B$23*100,"") | K23: =IFERROR(E23/$B$23*100,"") | L23: =IFERROR(F23/$B$23*100,"")
A24: Driftsmateriel og inventar | B24: ='balance_raw_41852119'!$B$4 | C24: ='balance_raw_41852119'!$C$4 | D24: ='balance_raw_41852119'!$D$4 | E24: ='balance_raw_41852119'!$E$4 | F24: ='balance_raw_41852119'!$F$4 | H24: =IFERROR(B24/$B$24*100,"") | I24: =IFERROR(C24/$B$24*100,"") | J24: =IFERROR(D24/$B$24*100,"") | K24: =IFERROR(E24/$B$24*100,"") | L24: =IFERROR(F24/$B$24*100,"")
A25: Indretning af lejede lokaler | B25: ='balance_raw_41852119'!$B$5 | C25: ='balance_raw_41852119'!$C$5 | D25: ='balance_raw_41852119'!$D$5 | E25: ='balance_raw_41852119'!$E$5 | F25: ='balance_raw_41852119'!$F$5 | H25: =IFERROR(B25/$B$25*100,"") | I25: =IFERROR(C25/$B$25*100,"") | J25: =IFERROR(D25/$B$25*100,"") | K25: =IFERROR(E25/$B$25*100,"") | L25: =IFERROR(F25/$B$25*100,"")
A26: Forudbetaling og anlægsaktiver under opførelse | B26: ='balance_raw_41852119'!$B$6 | C26: ='balance_raw_41852119'!$C$6 | D26: ='balance_raw_41852119'!$D$6 | E26: ='balance_raw_41852119'!$E$6 | F26: ='balance_raw_41852119'!$F$6 | H26: =IFERROR(B26/$B$26*100,"") | I26: =IFERROR(C26/$B$26*100,"") | J26: =IFERROR(D26/$B$26*100,"") | K26: =IFERROR(E26/$B$26*100,"") | L26: =IFERROR(F26/$B$26*100,"")
A27: Materielle anlægsaktiver | B27: ='balance_raw_41852119'!$B$7 | C27: ='balance_raw_41852119'!$C$7 | D27: ='balance_raw_41852119'!$D$7 | E27: ='balance_raw_41852119'!$E$7 | F27: ='balance_raw_41852119'!$F$7 | H27: =IFERROR(B27/$B$27*100,"") | I27: =IFERROR(C27/$B$27*100,"") | J27: =IFERROR(D27/$B$27*100,"") | K27: =IFERROR(E27/$B$27*100,"") | L27: =IFERROR(F27/$B$27*100,"")
A28: Anlægsaktiver | B28: ='balance_raw_41852119'!$B$8 | C28: ='balance_raw_41852119'!$C$8 | D28: ='balance_raw_41852119'!$D$8 | E28: ='balance_raw_41852119'!$E$8 | F28: ='balance_raw_41852119'!$F$8 | H28: =IFERROR(B28/$B$28*100,"") | I28: =IFERROR(C28/$B$28*100,"") | J28: =IFERROR(D28/$B$28*100,"") | K28: =IFERROR(E28/$B$28*100,"") | L28: =IFERROR(F28/$B$28*100,"")
A29: Råvarer og hjælpematerialer | B29: ='balance_raw_41852119'!$B$9 | C29: ='balance_raw_41852119'!$C$9 | D29: ='balance_raw_41852119'!$D$9 | E29: ='balance_raw_41852119'!$E$9 | F29: ='balance_raw_41852119'!$F$9 | H29: =IFERROR(B29/$B$29*100,"") | I29: =IFERROR(C29/$B$29*100,"") | J29: =IFERROR(D29/$B$29*100,"") | K29: =IFERROR(E29/$B$29*100,"") | L29: =IFERROR(F29/$B$29*100,"")
A30: Varer under fremstilling | B30: ='balance_raw_41852119'!$B$10 | C30: ='balance_raw_41852119'!$C$10 | D30: ='balance_raw_41852119'!$D$10 | E30: ='balance_raw_41852119'!$E$10 | F30: ='balance_raw_41852119'!$F$10 | H30: =IFERROR(B30/$B$30*100,"") | I30: =IFERROR(C30/$B$30*100,"") | J30: =IFERROR(D30/$B$30*100,"") | K30: =IFERROR(E30/$B$30*100,"") | L30: =IFERROR(F30/$B$30*100,"")
A31: Færdigvarer og handelsvarer | B31: ='balance_raw_41852119'!$B$11 | C31: ='balance_raw_41852119'!$C$11 | D31: ='balance_raw_41852119'!$D$11 | E31: ='balance_raw_41852119'!$E$11 | F31: ='balance_raw_41852119'!$F$11 | H31: =IFERROR(B31/$B$31*100,"") | I31: =IFERROR(C31/$B$31*100,"") | J31: =IFERROR(D31/$B$31*100,"") | K31: =IFERROR(E31/$B$31*100,"") | L31: =IFERROR(F31/$B$31*100,"")
A32: Varebeholdninger | B32: ='balance_raw_41852119'!$B$12 | C32: ='balance_raw_41852119'!$C$12 | D32: ='balance_raw_41852119'!$D$12 | E32: ='balance_raw_41852119'!$E$12 | F32: ='balance_raw_41852119'!$F$12 | H32: =IFERROR(B32/$B$32*100,"") | I32: =IFERROR(C32/$B$32*100,"") | J32: =IFERROR(D32/$B$32*100,"") | K32: =IFERROR(E32/$B$32*100,"") | L32: =IFERROR(F32/$B$32*100,"")
A33: Tilgodehavender fra salg og tjenesteydelser | B33: ='balance_raw_41852119'!$B$13 | C33: ='balance_raw_41852119'!$C$13 | D33: ='balance_raw_41852119'!$D$13 | E33: ='balance_raw_41852119'!$E$13 | F33: ='balance_raw_41852119'!$F$13 | H33: =IFERROR(B33/$B$33*100,"") | I33: =IFERROR(C33/$B$33*100,"") | J33: =IFERROR(D33/$B$33*100,"") | K33: =IFERROR(E33/$B$33*100,"") | L33: =IFERROR(F33/$B$33*100,"")
A34: Tilgodehavender hos tilknyttede virksomheder | B34: ='balance_raw_41852119'!$B$14 | C34: ='balance_raw_41852119'!$C$14 | D34: ='balance_raw_41852119'!$D$14 | E34: ='balance_raw_41852119'!$E$14 | F34: ='balance_raw_41852119'!$F$14 | H34: =IFERROR(B34/$B$34*100,"") | I34: =IFERROR(C34/$B$34*100,"") | J34: =IFERROR(D34/$B$34*100,"") | K34: =IFERROR(E34/$B$34*100,"") | L34: =IFERROR(F34/$B$34*100,"")
A35: Andre tilgodehavender | B35: ='balance_raw_41852119'!$B$15 | C35: ='balance_raw_41852119'!$C$15 | D35: ='balance_raw_41852119'!$D$15 | E35: ='balance_raw_41852119'!$E$15 | F35: ='balance_raw_41852119'!$F$15 | H35: =IFERROR(B35/$B$35*100,"") | I35: =IFERROR(C35/$B$35*100,"") | J35: =IFERROR(D35/$B$35*100,"") | K35: =IFERROR(E35/$B$35*100,"") | L35: =IFERROR(F35/$B$35*100,"")
A36: Periodeafgrænsningsposter (aktiver) | B36: ='balance_raw_41852119'!$B$16 | C36: ='balance_raw_41852119'!$C$16 | D36: ='balance_raw_41852119'!$D$16 | E36: ='balance_raw_41852119'!$E$16 | F36: ='balance_raw_41852119'!$F$16 | H36: =IFERROR(B36/$B$36*100,"") | I36: =IFERROR(C36/$B$36*100,"") | J36: =IFERROR(D36/$B$36*100,"") | K36: =IFERROR(E36/$B$36*100,"") | L36: =IFERROR(F36/$B$36*100,"")
A37: Udskudt skatteaktiv | B37: ='balance_raw_41852119'!$B$17 | C37: ='balance_raw_41852119'!$C$17 | D37: ='balance_raw_41852119'!$D$17 | E37: ='balance_raw_41852119'!$E$17 | F37: ='balance_raw_41852119'!$F$17 | H37: =IFERROR(B37/$B$37*100,"") | I37: =IFERROR(C37/$B$37*100,"") | J37: =IFERROR(D37/$B$37*100,"") | K37: =IFERROR(E37/$B$37*100,"") | L37: =IFERROR(F37/$B$37*100,"")
A38: Tilgodehavende skat hos tilknyttede virksomheder | B38: ='balance_raw_41852119'!$B$18 | C38: ='balance_raw_41852119'!$C$18 | D38: ='balance_raw_41852119'!$D$18 | E38: ='balance_raw_41852119'!$E$18 | F38: ='balance_raw_41852119'!$F$18 | H38: =IFERROR(B38/$B$38*100,"") | I38: =IFERROR(C38/$B$38*100,"") | J38: =IFERROR(D38/$B$38*100,"") | K38: =IFERROR(E38/$B$38*100,"") | L38: =IFERROR(F38/$B$38*100,"")
A39: Kortfristede skattetilgodehavender | B39: ='balance_raw_41852119'!$B$19 | C39: ='balance_raw_41852119'!$C$19 | D39: ='balance_raw_41852119'!$D$19 | E39: ='balance_raw_41852119'!$E$19 | F39: ='balance_raw_41852119'!$F$19 | H39: =IFERROR(B39/$B$39*100,"") | I39: =IFERROR(C39/$B$39*100,"") | J39: =IFERROR(D39/$B$39*100,"") | K39: =IFERROR(E39/$B$39*100,"") | L39: =IFERROR(F39/$B$39*100,"")
A40: Tilgodehavender | B40: ='balance_raw_41852119'!$B$20 | C40: ='balance_raw_41852119'!$C$20 | D40: ='balance_raw_41852119'!$D$20 | E40: ='balance_raw_41852119'!$E$20 | F40: ='balance_raw_41852119'!$F$20 | H40: =IFERROR(B40/$B$40*100,"") | I40: =IFERROR(C40/$B$40*100,"") | J40: =IFERROR(D40/$B$40*100,"") | K40: =IFERROR(E40/$B$40*100,"") | L40: =IFERROR(F40/$B$40*100,"")
A41: Værdipapirer | B41: ='balance_raw_41852119'!$B$21 | C41: ='balance_raw_41852119'!$C$21 | D41: ='balance_raw_41852119'!$D$21 | E41: ='balance_raw_41852119'!$E$21 | F41: ='balance_raw_41852119'!$F$21 | H41: =IFERROR(B41/$B$41*100,"") | I41: =IFERROR(C41/$B$41*100,"") | J41: =IFERROR(D41/$B$41*100,"") | K41: =IFERROR(E41/$B$41*100,"") | L41: =IFERROR(F41/$B$41*100,"")
A42: Likvide beholdninger | B42: ='balance_raw_41852119'!$B$22 | C42: ='balance_raw_41852119'!$C$22 | D42: ='balance_raw_41852119'!$D$22 | E42: ='balance_raw_41852119'!$E$22 | F42: ='balance_raw_41852119'!$F$22 | H42: =IFERROR(B42/$B$42*100,"") | I42: =IFERROR(C42/$B$42*100,"") | J42: =IFERROR(D42/$B$42*100,"") | K42: =IFERROR(E42/$B$42*100,"") | L42: =IFERROR(F42/$B$42*100,"")
A43: Omsætningsaktiver | B43: ='balance_raw_41852119'!$B$23 | C43: ='balance_raw_41852119'!$C$23 | D43: ='balance_raw_41852119'!$D$23 | E43: ='balance_raw_41852119'!$E$23 | F43: ='balance_raw_41852119'!$F$23 | H43: =IFERROR(B43/$B$43*100,"") | I43: =IFERROR(C43/$B$43*100,"") | J43: =IFERROR(D43/$B$43*100,"") | K43: =IFERROR(E43/$B$43*100,"") | L43: =IFERROR(F43/$B$43*100,"")
A44: Aktiver | B44: ='balance_raw_41852119'!$B$24 | C44: ='balance_raw_41852119'!$C$24 | D44: ='balance_raw_41852119'!$D$24 | E44: ='balance_raw_41852119'!$E$24 | F44: ='balance_raw_41852119'!$F$24 | H44: =IFERROR(B44/$B$44*100,"") | I44: =IFERROR(C44/$B$44*100,"") | J44: =IFERROR(D44/$B$44*100,"") | K44: =IFERROR(E44/$B$44*100,"") | L44: =IFERROR(F44/$B$44*100,"")
A46: PASSIVER t.kr. | B46: 2021 | C46: 2022 | D46: 2023 | E46: 2024 | F46: 2025 | H46: 2021 | I46: 2022 | J46: 2023 | K46: 2024 | L46: 2025
A47: Selskabskapital | B47: ='balance_raw_41852119'!$B$25 | C47: ='balance_raw_41852119'!$C$25 | D47: ='balance_raw_41852119'!$D$25 | E47: ='balance_raw_41852119'!$E$25 | F47: ='balance_raw_41852119'!$F$25 | H47: =IFERROR(B47/$B$47*100,"") | I47: =IFERROR(C47/$B$47*100,"") | J47: =IFERROR(D47/$B$47*100,"") | K47: =IFERROR(E47/$B$47*100,"") | L47: =IFERROR(F47/$B$47*100,"")
A48: Reserve for nettoopskrivning (indre værdis metode) | B48: ='balance_raw_41852119'!$B$26 | C48: ='balance_raw_41852119'!$C$26 | D48: ='balance_raw_41852119'!$D$26 | E48: ='balance_raw_41852119'!$E$26 | F48: ='balance_raw_41852119'!$F$26 | H48: =IFERROR(B48/$B$48*100,"") | I48: =IFERROR(C48/$B$48*100,"") | J48: =IFERROR(D48/$B$48*100,"") | K48: =IFERROR(E48/$B$48*100,"") | L48: =IFERROR(F48/$B$48*100,"")
A49: Reserve for udviklingsomkostninger | B49: ='balance_raw_41852119'!$B$27 | C49: ='balance_raw_41852119'!$C$27 | D49: ='balance_raw_41852119'!$D$27 | E49: ='balance_raw_41852119'!$E$27 | F49: ='balance_raw_41852119'!$F$27 | H49: =IFERROR(B49/$B$49*100,"") | I49: =IFERROR(C49/$B$49*100,"") | J49: =IFERROR(D49/$B$49*100,"") | K49: =IFERROR(E49/$B$49*100,"") | L49: =IFERROR(F49/$B$49*100,"")
A50: Reserve for sikringstransaktioner | B50: ='balance_raw_41852119'!$B$28 | C50: ='balance_raw_41852119'!$C$28 | D50: ='balance_raw_41852119'!$D$28 | E50: ='balance_raw_41852119'!$E$28 | F50: ='balance_raw_41852119'!$F$28 | H50: =IFERROR(B50/$B$50*100,"") | I50: =IFERROR(C50/$B$50*100,"") | J50: =IFERROR(D50/$B$50*100,"") | K50: =IFERROR(E50/$B$50*100,"") | L50: =IFERROR(F50/$B$50*100,"")
A51: Andre reserver | B51: ='balance_raw_41852119'!$B$29 | C51: ='balance_raw_41852119'!$C$29 | D51: ='balance_raw_41852119'!$D$29 | E51: ='balance_raw_41852119'!$E$29 | F51: ='balance_raw_41852119'!$F$29 | H51: =IFERROR(B51/$B$51*100,"") | I51: =IFERROR(C51/$B$51*100,"") | J51: =IFERROR(D51/$B$51*100,"") | K51: =IFERROR(E51/$B$51*100,"") | L51: =IFERROR(F51/$B$51*100,"")
A52: Overført resultat | B52: ='balance_raw_41852119'!$B$30 | C52: ='balance_raw_41852119'!$C$30 | D52: ='balance_raw_41852119'!$D$30 | E52: ='balance_raw_41852119'!$E$30 | F52: ='balance_raw_41852119'!$F$30 | H52: =IFERROR(B52/$B$52*100,"") | I52: =IFERROR(C52/$B$52*100,"") | J52: =IFERROR(D52/$B$52*100,"") | K52: =IFERROR(E52/$B$52*100,"") | L52: =IFERROR(F52/$B$52*100,"")
A53: Egenkapital i alt | B53: ='balance_raw_41852119'!$B$31 | C53: ='balance_raw_41852119'!$C$31 | D53: ='balance_raw_41852119'!$D$31 | E53: ='balance_raw_41852119'!$E$31 | F53: ='balance_raw_41852119'!$F$31 | H53: =IFERROR(B53/$B$53*100,"") | I53: =IFERROR(C53/$B$53*100,"") | J53: =IFERROR(D53/$B$53*100,"") | K53: =IFERROR(E53/$B$53*100,"") | L53: =IFERROR(F53/$B$53*100,"")
A54: Hensættelse til udskudt skat | B54: ='balance_raw_41852119'!$B$32 | C54: ='balance_raw_41852119'!$C$32 | D54: ='balance_raw_41852119'!$D$32 | E54: ='balance_raw_41852119'!$E$32 | F54: ='balance_raw_41852119'!$F$32 | H54: =IFERROR(B54/$B$54*100,"") | I54: =IFERROR(C54/$B$54*100,"") | J54: =IFERROR(D54/$B$54*100,"") | K54: =IFERROR(E54/$B$54*100,"") | L54: =IFERROR(F54/$B$54*100,"")
A55: Hensatte forpligtelser | B55: ='balance_raw_41852119'!$B$33 | C55: ='balance_raw_41852119'!$C$33 | D55: ='balance_raw_41852119'!$D$33 | E55: ='balance_raw_41852119'!$E$33 | F55: ='balance_raw_41852119'!$F$33 | H55: =IFERROR(B55/$B$55*100,"") | I55: =IFERROR(C55/$B$55*100,"") | J55: =IFERROR(D55/$B$55*100,"") | K55: =IFERROR(E55/$B$55*100,"") | L55: =IFERROR(F55/$B$55*100,"")
A56: Ansvarlig lånekapital (langfristet) | B56: ='balance_raw_41852119'!$B$34 | C56: ='balance_raw_41852119'!$C$34 | D56: ='balance_raw_41852119'!$D$34 | E56: ='balance_raw_41852119'!$E$34 | F56: ='balance_raw_41852119'!$F$34 | H56: =IFERROR(B56/$B$56*100,"") | I56: =IFERROR(C56/$B$56*100,"") | J56: =IFERROR(D56/$B$56*100,"") | K56: =IFERROR(E56/$B$56*100,"") | L56: =IFERROR(F56/$B$56*100,"")
A57: Langfristede lån | B57: ='balance_raw_41852119'!$B$35 | C57: ='balance_raw_41852119'!$C$35 | D57: ='balance_raw_41852119'!$D$35 | E57: ='balance_raw_41852119'!$E$35 | F57: ='balance_raw_41852119'!$F$35 | H57: =IFERROR(B57/$B$57*100,"") | I57: =IFERROR(C57/$B$57*100,"") | J57: =IFERROR(D57/$B$57*100,"") | K57: =IFERROR(E57/$B$57*100,"") | L57: =IFERROR(F57/$B$57*100,"")
A58: Leasingforpligtelser (langfristet) | B58: ='balance_raw_41852119'!$B$36 | C58: ='balance_raw_41852119'!$C$36 | D58: ='balance_raw_41852119'!$D$36 | E58: ='balance_raw_41852119'!$E$36 | F58: ='balance_raw_41852119'!$F$36 | H58: =IFERROR(B58/$B$58*100,"") | I58: =IFERROR(C58/$B$58*100,"") | J58: =IFERROR(D58/$B$58*100,"") | K58: =IFERROR(E58/$B$58*100,"") | L58: =IFERROR(F58/$B$58*100,"")
A59: Anden gæld (langfristet) | B59: ='balance_raw_41852119'!$B$37 | C59: ='balance_raw_41852119'!$C$37 | D59: ='balance_raw_41852119'!$D$37 | E59: ='balance_raw_41852119'!$E$37 | F59: ='balance_raw_41852119'!$F$37 | H59: =IFERROR(B59/$B$59*100,"") | I59: =IFERROR(C59/$B$59*100,"") | J59: =IFERROR(D59/$B$59*100,"") | K59: =IFERROR(E59/$B$59*100,"") | L59: =IFERROR(F59/$B$59*100,"")
A60: Langfristede gældsforpligtelser | B60: ='balance_raw_41852119'!$B$38 | C60: ='balance_raw_41852119'!$C$38 | D60: ='balance_raw_41852119'!$D$38 | E60: ='balance_raw_41852119'!$E$38 | F60: ='balance_raw_41852119'!$F$38 | H60: =IFERROR(B60/$B$60*100,"") | I60: =IFERROR(C60/$B$60*100,"") | J60: =IFERROR(D60/$B$60*100,"") | K60: =IFERROR(E60/$B$60*100,"") | L60: =IFERROR(F60/$B$60*100,"")
A61: Ansvarlig lånekapital (kortfristet) | B61: ='balance_raw_41852119'!$B$39 | C61: ='balance_raw_41852119'!$C$39 | D61: ='balance_raw_41852119'!$D$39 | E61: ='balance_raw_41852119'!$E$39 | F61: ='balance_raw_41852119'!$F$39 | H61: =IFERROR(B61/$B$61*100,"") | I61: =IFERROR(C61/$B$61*100,"") | J61: =IFERROR(D61/$B$61*100,"") | K61: =IFERROR(E61/$B$61*100,"") | L61: =IFERROR(F61/$B$61*100,"")
A62: Kortfristet del af langfristede gældsforpligtelser | B62: ='balance_raw_41852119'!$B$40 | C62: ='balance_raw_41852119'!$C$40 | D62: ='balance_raw_41852119'!$D$40 | E62: ='balance_raw_41852119'!$E$40 | F62: ='balance_raw_41852119'!$F$40 | H62: =IFERROR(B62/$B$62*100,"") | I62: =IFERROR(C62/$B$62*100,"") | J62: =IFERROR(D62/$B$62*100,"") | K62: =IFERROR(E62/$B$62*100,"") | L62: =IFERROR(F62/$B$62*100,"")
A63: Kreditinstitutter | B63: ='balance_raw_41852119'!$B$41 | C63: ='balance_raw_41852119'!$C$41 | D63: ='balance_raw_41852119'!$D$41 | E63: ='balance_raw_41852119'!$E$41 | F63: ='balance_raw_41852119'!$F$41 | H63: =IFERROR(B63/$B$63*100,"") | I63: =IFERROR(C63/$B$63*100,"") | J63: =IFERROR(D63/$B$63*100,"") | K63: =IFERROR(E63/$B$63*100,"") | L63: =IFERROR(F63/$B$63*100,"")
A64: Leasingforpligtelser (kortfristet) | B64: ='balance_raw_41852119'!$B$42 | C64: ='balance_raw_41852119'!$C$42 | D64: ='balance_raw_41852119'!$D$42 | E64: ='balance_raw_41852119'!$E$42 | F64: ='balance_raw_41852119'!$F$42 | H64: =IFERROR(B64/$B$64*100,"") | I64: =IFERROR(C64/$B$64*100,"") | J64: =IFERROR(D64/$B$64*100,"") | K64: =IFERROR(E64/$B$64*100,"") | L64: =IFERROR(F64/$B$64*100,"")
A65: Leverandører af varer og tjenesteydelser | B65: ='balance_raw_41852119'!$B$43 | C65: ='balance_raw_41852119'!$C$43 | D65: ='balance_raw_41852119'!$D$43 | E65: ='balance_raw_41852119'!$E$43 | F65: ='balance_raw_41852119'!$F$43 | H65: =IFERROR(B65/$B$65*100,"") | I65: =IFERROR(C65/$B$65*100,"") | J65: =IFERROR(D65/$B$65*100,"") | K65: =IFERROR(E65/$B$65*100,"") | L65: =IFERROR(F65/$B$65*100,"")
A66: Gæld til tilknyttede virksomheder | B66: ='balance_raw_41852119'!$B$44 | C66: ='balance_raw_41852119'!$C$44 | D66: ='balance_raw_41852119'!$D$44 | E66: ='balance_raw_41852119'!$E$44 | F66: ='balance_raw_41852119'!$F$44 | H66: =IFERROR(B66/$B$66*100,"") | I66: =IFERROR(C66/$B$66*100,"") | J66: =IFERROR(D66/$B$66*100,"") | K66: =IFERROR(E66/$B$66*100,"") | L66: =IFERROR(F66/$B$66*100,"")
A67: Gæld til selskabsdeltagere og ledelse | B67: ='balance_raw_41852119'!$B$45 | C67: ='balance_raw_41852119'!$C$45 | D67: ='balance_raw_41852119'!$D$45 | E67: ='balance_raw_41852119'!$E$45 | F67: ='balance_raw_41852119'!$F$45 | H67: =IFERROR(B67/$B$67*100,"") | I67: =IFERROR(C67/$B$67*100,"") | J67: =IFERROR(D67/$B$67*100,"") | K67: =IFERROR(E67/$B$67*100,"") | L67: =IFERROR(F67/$B$67*100,"")
A68: Selskabsskat | B68: ='balance_raw_41852119'!$B$46 | C68: ='balance_raw_41852119'!$C$46 | D68: ='balance_raw_41852119'!$D$46 | E68: ='balance_raw_41852119'!$E$46 | F68: ='balance_raw_41852119'!$F$46 | H68: =IFERROR(B68/$B$68*100,"") | I68: =IFERROR(C68/$B$68*100,"") | J68: =IFERROR(D68/$B$68*100,"") | K68: =IFERROR(E68/$B$68*100,"") | L68: =IFERROR(F68/$B$68*100,"")
A69: Gæld til tilknyttede virksomheder vedr. selskabsskat | B69: ='balance_raw_41852119'!$B$47 | C69: ='balance_raw_41852119'!$C$47 | D69: ='balance_raw_41852119'!$D$47 | E69: ='balance_raw_41852119'!$E$47 | F69: ='balance_raw_41852119'!$F$47 | H69: =IFERROR(B69/$B$69*100,"") | I69: =IFERROR(C69/$B$69*100,"") | J69: =IFERROR(D69/$B$69*100,"") | K69: =IFERROR(E69/$B$69*100,"") | L69: =IFERROR(F69/$B$69*100,"")
A70: Anden gæld (kortfristet) | B70: ='balance_raw_41852119'!$B$48 | C70: ='balance_raw_41852119'!$C$48 | D70: ='balance_raw_41852119'!$D$48 | E70: ='balance_raw_41852119'!$E$48 | F70: ='balance_raw_41852119'!$F$48 | H70: =IFERROR(B70/$B$70*100,"") | I70: =IFERROR(C70/$B$70*100,"") | J70: =IFERROR(D70/$B$70*100,"") | K70: =IFERROR(E70/$B$70*100,"") | L70: =IFERROR(F70/$B$70*100,"")
A71: Periodeafgrænsningsposter (passiver) | B71: ='balance_raw_41852119'!$B$49 | C71: ='balance_raw_41852119'!$C$49 | D71: ='balance_raw_41852119'!$D$49 | E71: ='balance_raw_41852119'!$E$49 | F71: ='balance_raw_41852119'!$F$49 | H71: =IFERROR(B71/$B$71*100,"") | I71: =IFERROR(C71/$B$71*100,"") | J71: =IFERROR(D71/$B$71*100,"") | K71: =IFERROR(E71/$B$71*100,"") | L71: =IFERROR(F71/$B$71*100,"")
A72: Kortfristede gældsforpligtelser | B72: ='balance_raw_41852119'!$B$50 | C72: ='balance_raw_41852119'!$C$50 | D72: ='balance_raw_41852119'!$D$50 | E72: ='balance_raw_41852119'!$E$50 | F72: ='balance_raw_41852119'!$F$50 | H72: =IFERROR(B72/$B$72*100,"") | I72: =IFERROR(C72/$B$72*100,"") | J72: =IFERROR(D72/$B$72*100,"") | K72: =IFERROR(E72/$B$72*100,"") | L72: =IFERROR(F72/$B$72*100,"")
A73: Gældsforpligtelser | B73: ='balance_raw_41852119'!$B$51 | C73: ='balance_raw_41852119'!$C$51 | D73: ='balance_raw_41852119'!$D$51 | E73: ='balance_raw_41852119'!$E$51 | F73: ='balance_raw_41852119'!$F$51 | H73: =IFERROR(B73/$B$73*100,"") | I73: =IFERROR(C73/$B$73*100,"") | J73: =IFERROR(D73/$B$73*100,"") | K73: =IFERROR(E73/$B$73*100,"") | L73: =IFERROR(F73/$B$73*100,"")
A74: Passiver | B74: ='balance_raw_41852119'!$B$52 | C74: ='balance_raw_41852119'!$C$52 | D74: ='balance_raw_41852119'!$D$52 | E74: ='balance_raw_41852119'!$E$52 | F74: ='balance_raw_41852119'!$F$52 | H74: =IFERROR(B74/$B$74*100,"") | I74: =IFERROR(C74/$B$74*100,"") | J74: =IFERROR(D74/$B$74*100,"") | K74: =IFERROR(E74/$B$74*100,"") | L74: =IFERROR(F74/$B$74*100,"")
A76: NØGLEOPLYSNINGER | B76: 2021 | C76: 2022 | D76: 2023 | E76: 2024 | F76: 2025
A77: Gns. antal medarbejdere | B77: ='res_raw_41852119'!$B$18 | C77: ='res_raw_41852119'!$C$18 | D77: ='res_raw_41852119'!$D$18 | E77: ='res_raw_41852119'!$E$18 | F77: ='res_raw_41852119'!$F$18 | H77: =IFERROR(B77/$B$77*100,"") | I77: =IFERROR(C77/$B$77*100,"") | J77: =IFERROR(D77/$B$77*100,"") | K77: =IFERROR(E77/$B$77*100,"") | L77: =IFERROR(F77/$B$77*100,"")
A78: Investering i materielle anlægsaktiver | B78: ='res_raw_41852119'!$B$19 | C78: ='res_raw_41852119'!$C$19 | D78: ='res_raw_41852119'!$D$19 | E78: ='res_raw_41852119'!$E$19 | F78: ='res_raw_41852119'!$F$19 | H78: =IFERROR(B78/$B$78*100,"") | I78: =IFERROR(C78/$B$78*100,"") | J78: =IFERROR(D78/$B$78*100,"") | K78: =IFERROR(E78/$B$78*100,"") | L78: =IFERROR(F78/$B$78*100,"")
A80: NØGLETAL | B80: 2021 | C80: 2022 | D80: 2023 | E80: 2024 | F80: 2025
A81: Afkastningsgrad, % | B81: =IFERROR(($B$12+$B$14+$B$13)/$B$44*100,"") | C81: =IFERROR(($C$12+$C$14+$C$13)/$C$44*100,"") | D81: =IFERROR(($D$12+$D$14+$D$13)/$D$44*100,"") | E81: =IFERROR(($E$12+$E$14+$E$13)/$E$44*100,"") | F81: =IFERROR(($F$12+$F$14+$F$13)/$F$44*100,"")
A82: Overskudsgrad, % | B82: =IFERROR(($B$12+$B$14+$B$13)/$B$4*100,"") | C82: =IFERROR(($C$12+$C$14+$C$13)/$C$4*100,"") | D82: =IFERROR(($D$12+$D$14+$D$13)/$D$4*100,"") | E82: =IFERROR(($E$12+$E$14+$E$13)/$E$4*100,"") | F82: =IFERROR(($F$12+$F$14+$F$13)/$F$4*100,"")
A83: Aktivernes omsætningshastighed, gange | B83: =IFERROR($B$4/$B$44,"") | C83: =IFERROR($C$4/$C$44,"") | D83: =IFERROR($D$4/$D$44,"") | E83: =IFERROR($E$4/$E$44,"") | F83: =IFERROR($F$4/$F$44,"")
A84: Egenkapitalens forrentning, % | B84: =IFERROR($B$17/$B$53*100,"") | C84: =IFERROR($C$17/$C$53*100,"") | D84: =IFERROR($D$17/$D$53*100,"") | E84: =IFERROR($E$17/$E$53*100,"") | F84: =IFERROR($F$17/$F$53*100,"")
A85: Gældsrente, % | B85: =IFERROR($B$15/($B$74-$B$53)*100,"") | C85: =IFERROR($C$15/($C$74-$C$53)*100,"") | D85: =IFERROR($D$15/($D$74-$D$53)*100,"") | E85: =IFERROR($E$15/($E$74-$E$53)*100,"") | F85: =IFERROR($F$15/($F$74-$F$53)*100,"")
A86: Soliditetsgrad, % | B86: =IFERROR($B$53/$B$44*100,"") | C86: =IFERROR($C$53/$C$44*100,"") | D86: =IFERROR($D$53/$D$44*100,"") | E86: =IFERROR($E$53/$E$44*100,"") | F86: =IFERROR($F$53/$F$44*100,"")
A87: Gearing | B87: =IFERROR(($B$74-$B$53)/$B$53,"") | C87: =IFERROR(($C$74-$C$53)/$C$53,"") | D87: =IFERROR(($D$74-$D$53)/$D$53,"") | E87: =IFERROR(($E$74-$E$53)/$E$53,"") | F87: =IFERROR(($F$74-$F$53)/$F$53,"")
A88: Likviditetsgrad, % | B88: =IFERROR($B$43/$B$72*100,"") | C88: =IFERROR($C$43/$C$72*100,"") | D88: =IFERROR($D$43/$D$72*100,"") | E88: =IFERROR($E$43/$E$72*100,"") | F88: =IFERROR($F$43/$F$72*100,"")
A89: Rentemarginal, % | B89: =IFERROR(B81-B85,"") | C89: =IFERROR(C81-C85,"") | D89: =IFERROR(D81-D85,"") | E89: =IFERROR(E81-E85,"") | F89: =IFERROR(F81-F85,"")
A90: Gældsandel, % | B90: =IFERROR(($B$74-$B$53)/$B$44*100,"") | C90: =IFERROR(($C$74-$C$53)/$C$44*100,"") | D90: =IFERROR(($D$74-$D$53)/$D$44*100,"") | E90: =IFERROR(($E$74-$E$53)/$E$44*100,"") | F90: =IFERROR(($F$74-$F$53)/$F$44*100,"")
A91: Kapitalbindingsgrad, % | B91: =IFERROR($B$28/($B$53+$B$60)*100,"") | C91: =IFERROR($C$28/($C$53+$C$60)*100,"") | D91: =IFERROR($D$28/($D$53+$D$60)*100,"") | E91: =IFERROR($E$28/($E$53+$E$60)*100,"") | F91: =IFERROR($F$28/($F$53+$F$60)*100,"")
A93: PENGESTRØMSOPGØRELSE t.kr.
A94: Pengestrømme fra driftsaktivitet | B94: ='pengestrom_raw_41852119'!$B$2 | C94: ='pengestrom_raw_41852119'!$C$2 | D94: ='pengestrom_raw_41852119'!$D$2 | E94: ='pengestrom_raw_41852119'!$E$2 | F94: ='pengestrom_raw_41852119'!$F$2
A95: Pengestrømme fra investeringsaktivitet | B95: ='pengestrom_raw_41852119'!$B$3 | C95: ='pengestrom_raw_41852119'!$C$3 | D95: ='pengestrom_raw_41852119'!$D$3 | E95: ='pengestrom_raw_41852119'!$E$3 | F95: ='pengestrom_raw_41852119'!$F$3
A96: Pengestrømme fra finansieringsaktivitet | B96: ='pengestrom_raw_41852119'!$B$4 | C96: ='pengestrom_raw_41852119'!$C$4 | D96: ='pengestrom_raw_41852119'!$D$4 | E96: ='pengestrom_raw_41852119'!$E$4 | F96: ='pengestrom_raw_41852119'!$F$4
A97: Årets pengestrøm (rapporteret) | B97: ='pengestrom_raw_41852119'!$B$5 | C97: ='pengestrom_raw_41852119'!$C$5 | D97: ='pengestrom_raw_41852119'!$D$5 | E97: ='pengestrom_raw_41852119'!$E$5 | F97: ='pengestrom_raw_41852119'!$F$5
A98: Krydstjek: drift + inv. + fin. = årets pengestrøm | B98: =IF(ABS(('pengestrom_raw_41852119'!$B$2+'pengestrom_raw_41852119'!$B$3+'pengestrom_raw_41852119'!$B$4)-'pengestrom_raw_41852119'!$B$5)<=2,"✓","⚠ "&TEXT(('pengestrom_raw_41852119'!$B$2+'pengestrom_raw_41852119'!$B$3+'pengestrom_raw_41852119'!$B$4)-'pengestrom_raw_41852119'!$B$5,"+#,##0;-#,##0")) | C98: =IF(ABS(('pengestrom_raw_41852119'!$C$2+'pengestrom_raw_41852119'!$C$3+'pengestrom_raw_41852119'!$C$4)-'pengestrom_raw_41852119'!$C$5)<=2,"✓","⚠ "&TEXT(('pengestrom_raw_41852119'!$C$2+'pengestrom_raw_41852119'!$C$3+'pengestrom_raw_41852119'!$C$4)-'pengestrom_raw_41852119'!$C$5,"+#,##0;-#,##0")) | D98: =IF(ABS(('pengestrom_raw_41852119'!$D$2+'pengestrom_raw_41852119'!$D$3+'pengestrom_raw_41852119'!$D$4)-'pengestrom_raw_41852119'!$D$5)<=2,"✓","⚠ "&TEXT(('pengestrom_raw_41852119'!$D$2+'pengestrom_raw_41852119'!$D$3+'pengestrom_raw_41852119'!$D$4)-'pengestrom_raw_41852119'!$D$5,"+#,##0;-#,##0")) | E98: =IF(ABS(('pengestrom_raw_41852119'!$E$2+'pengestrom_raw_41852119'!$E$3+'pengestrom_raw_41852119'!$E$4)-'pengestrom_raw_41852119'!$E$5)<=2,"✓","⚠ "&TEXT(('pengestrom_raw_41852119'!$E$2+'pengestrom_raw_41852119'!$E$3+'pengestrom_raw_41852119'!$E$4)-'pengestrom_raw_41852119'!$E$5,"+#,##0;-#,##0")) | F98: =IF(ABS(('pengestrom_raw_41852119'!$F$2+'pengestrom_raw_41852119'!$F$3+'pengestrom_raw_41852119'!$F$4)-'pengestrom_raw_41852119'!$F$5)<=2,"✓","⚠ "&TEXT(('pengestrom_raw_41852119'!$F$2+'pengestrom_raw_41852119'!$F$3+'pengestrom_raw_41852119'!$F$4)-'pengestrom_raw_41852119'!$F$5,"+#,##0;-#,##0"))

Sheet res_raw_41852119
A1: Tetra Pak Processing Systems A/S (CVR 41852119) — Resultatopgørelse & nøgleoplysninger (t.kr.) | B1: 2021 | C1: 2022 | D1: 2023 | E1: 2024 | F1: 2025
A2: Nettoomsætning | B2: 1125847 | C2: 1384459 | D2: 1423500 | E2: 1275850 | F2: 1352275
A3: Produktionsomkostninger | B3: 902140 | C3: 1120637 | D3: 1209012 | E3: 1088031 | F3: 1121335
A4: Bruttoresultat | B4: 223707 | C4: 263822 | D4: 214488 | E4: 187819 | F4: 230940
A5: Udviklingsomkostninger
A6: Salgs- og distributionsomkostninger | B6: 122354 | C6: 112287 | D6: 102672 | E6: 108950 | F6: 102255
A7: Administrationsomkostninger | B7: 46165 | C7: 65131 | D7: 62691 | E7: 68033 | F7: 62537
A8: Andre driftsindtægter | B8: 1815 | C8: 0 | E8: 744 | F8: 467571
A9: Andre driftsomkostninger | B9: 0 | D9: 67 | E9: 414 | F9: 787
A10: Resultat af primær drift | B10: 57003 | C10: 86404 | D10: 49058 | E10: 11166 | F10: 532932
A11: Indtægter af kapitalandele, dattervirksomheder
A12: Finansielle indtægter | B12: 3 | C12: 97 | D12: 212 | E12: 576 | F12: 37178
A13: Finansielle omkostninger | B13: 3534 | C13: 4786 | D13: 17919 | E13: -3000 | F13: -12939
A14: Finansielle poster, netto | B14: -3531 | C14: -4689 | D14: -17707 | E14: -17674 | F14: 14264
A15: Resultat før skat | B15: 53472 | C15: 81715 | D15: 31351 | E15: -6508 | F15: 547196
A16: Skat af årets resultat | B16: -808 | C16: 17046 | D16: 7430 | E16: 1255 | F16: -123107
A17: Årets resultat | B17: 54280 | C17: 64669 | D17: 23921 | E17: -5253 | F17: 424089
A18: Gns. antal medarbejdere | B18: 406 | C18: 402 | D18: 400 | E18: 401000 | F18: 412000
A19: Investering i materielle anlægsaktiver | B19: -10001 | C19: -11785 | D19: -12606 | E19: -46585 | F19: -33181

Sheet balance_raw_41852119
A1: Tetra Pak Processing Systems A/S (CVR 41852119) — Balance (t.kr.) | B1: 2021 | C1: 2022 | D1: 2023 | E1: 2024 | F1: 2025
A2: Grunde og bygninger | B2: 16468 | C2: 15776 | D2: 14639 | E2: 15256 | F2: 46159
A3: Produktionsanlæg og maskiner | B3: 12513 | C3: 12809 | D3: 11226 | E3: 10547 | F3: 10512
A4: Driftsmateriel og inventar | B4: 13094 | C4: 16443 | D4: 18503 | E4: 20770 | F4: 31275
A5: Indretning af lejede lokaler | B5: 152 | C5: 148 | D5: 144 | E5: 140 | F5: 5402
A6: Forudbetaling og anlægsaktiver under opførelse | B6: 1236 | C6: 37 | D6: 3472 | E6: 28624 | F6: 4273
A7: Materielle anlægsaktiver | B7: 63107 | C7: 58898 | D7: 66789 | E7: 108847 | F7: 115417
A8: Anlægsaktiver | B8: 63107 | C8: 58898 | D8: 66789 | E8: 108847 | F8: 115417
A9: Råvarer og hjælpematerialer | B9: 100594 | C9: 175600 | D9: 192401 | E9: 156102 | F9: 154065
A10: Varer under fremstilling | B10: 148210 | C10: 113060 | D10: 127365 | E10: 129336 | F10: 112565
A11: Færdigvarer og handelsvarer | B11: 26566 | C11: 43239 | D11: 54871 | E11: 42987 | F11: 31985
A12: Varebeholdninger | B12: 283333 | C12: 346327 | D12: 376133 | E12: 336840 | F12: 305999
... A15: Andre tilgodehavender | B15: 48866 | C15: 54524 | D15: 43079 | E15: 53113 | F15: 41334
A16: Periodeafgrænsningsposter (aktiver) | B16: 908 | C16: 171
A17: Udskudt skatteaktiv
A18: Tilgodehavende skat hos tilknyttede virksomheder
A19: Kortfristede skattetilgodehavender | C19: 1515 | D19: 8209 | E19: 9195 | F19: 0
A20: Tilgodehavender | B20: 241577 | C20: 293567 | D20: 357525 | E20: 260864 | F20: 598713
A21: Værdipapirer
A22: Likvide beholdninger | B22: 990 | C22: 5743 | D22: 4262 | E22: 0 | F22: 956
A23: Omsætningsaktiver | B23: 525900 | C23: 645637 | D23: 737920 | E23: 597704 | F23: 905668
A24: Aktiver | B24: 589007 | C24: 704535 | D24: 804709 | E24: 706551 | F24: 1021085
A25: Selskabskapital | B25: 12000 | C25: 12000 | D25: 12000 | E25: 12000 | F25: 12000
A26: Reserve for nettoopskrivning (indre værdis metode)
A27: Reserve for udviklingsomkostninger
A28: Reserve for sikringstransaktioner
A29: Andre reserver
A30: Overført resultat | B30: 93732 | C30: 93732 | D30: 117653 | E30: 112400 | F30: 116489
A31: Egenkapital i alt | B31: 160012 | C31: 170401 | D31: 129653 | E31: 124400 | F31: 548489
A32: Hensættelse til udskudt skat | B32: 5067 | C32: 7263 | D32: 9287 | E32: 10557 | F32: 10019
A33: Hensatte forpligtelser | B33: 156 | C33: 0 | D33: 9287 | E33: 10557 | F33: 10019
A34: Ansvarlig lånekapital (langfristet)
A35: Langfristede lån
A36: Leasingforpligtelser (langfristet) | B36: 12430 | C36: 7494 | D36: 11105 | E36: 26642 | F36: 14168
A37: Anden gæld (langfristet) | B37: 0
A38: Langfristede gældsforpligtelser | B38: 17653 | C38: 14757 | D38: 20392 | E38: 37199 | F38: 24187
A39: Ansvarlig lånekapital (kortfristet)
A40: Kortfristet del af langfristede gældsforpligtelser
A41: Kreditinstitutter | E41: 2505 | F41: 0
A42: Leasingforpligtelser (kortfristet) | B42: 6935 | C42: 5642 | D42: 7429 | E42: 6392 | F42: 3756
A43: Leverandører af varer og tjenesteydelser | B43: 116719 | C43: 139922 | D43: 128237 | E43: 99434 | F43: 106670
A44: Gæld til tilknyttede virksomheder | B44: 148840 | C44: 246056 | D44: 367641 | E44: 291846 | F44: 61191
A45: Gæld til selskabsdeltagere og ledelse
A46: Selskabsskat | B46: 4983 | C46: 0 | E46: 0 | F46: 121210
A47: Gæld til tilknyttede virksomheder vedr. selskabsskat
A48: Anden gæld (kortfristet) | B48: 93264 | C48: 82025 | D48: 103553 | E48: 99890 | F48: 98954
A49: Periodeafgrænsningsposter (passiver) | B49: 27615 | C49: 31437 | D49: 31347 | E49: 138 | F49: 189
A50: Kortfristede gældsforpligtelser | B50: 411342 | C50: 519377 | D50: 654664 | E50: 544952 | F50: 448409
A51: Gældsforpligtelser | B51: 428995 | C51: 534134 | D51: 675056 | E51: 582151 | F51: 472596
A52: Passiver | B52: 589007 | C52: 704535 | D52: 804709 | E52: 706551 | F52: 1021085

Sheet pengestrom_raw_41852119
A1: Tetra Pak Processing Systems A/S (CVR 41852119) — Pengestrømsopgørelse (t.kr.) | B1: 2021 | C1: 2022 | D1: 2023 | E1: 2024 | F1: 2025
A2: Pengestrømme fra driftsaktivitet | B2: -27641 | C2: -18739 | D2: 42013 | E2: -17706 | F2: 165049
A3: Pengestrømme fra investeringsaktivitet | B3: -5514 | C3: -10263 | D3: -12020
A4: Pengestrømme fra finansieringsaktivitet | B4: 30095 | C4: 33755 | D4: -31474 | E4: 50492 | F4: -131544
A5: Årets pengestrøm

Sheet Simpel_funktion
A1: Tetra Pak Processing Systems A/S (CVR 41852119) — Regnskabs- og nøgletal (CVR: 41852119) — funktionsopdelt
A3: Beløb i 1.000 kr. | B3: 2025 | C3: 2024 | D3: 2023 | F3: Note / XBRL-felt
A4: Uddrag af resultatopgørelse
A5: Nettoomsætning | B5: ='res_raw_41852119'!$F$2 | C5: ='res_raw_41852119'!$E$2 | D5: ='res_raw_41852119'!$D$2 | F5: fsa:Revenue
A6: Produktionsomkostninger | B6: =-'res_raw_41852119'!$F$3 | C6: =-'res_raw_41852119'!$E$3 | D6: =-'res_raw_41852119'!$D$3 | F6: fsa:CostOfProduction (vises negativt). Materialer, lønninger, produktionsoverhead.
A7: Bruttoresultat | B7: =IF(ABS((SUM(B5:B6))-'res_raw_41852119'!$F$4)<=2,SUM(B5:B6),'res_raw_41852119'!$F$4) | C7: =IF(ABS((SUM(C5:C6))-'res_raw_41852119'!$E$4)<=2,SUM(C5:C6),'res_raw_41852119'!$E$4) | D7: =IF(ABS((SUM(D5:D6))-'res_raw_41852119'!$D$4)<=2,SUM(D5:D6),'res_raw_41852119'!$D$4) | F7: Beregnet: Nettoomsætning − Produktionsomkostninger. Matcher fsa:GrossResult. Er komponenterne ikke indberettet, vises rapporteret fsa:GrossResult direkte.
A8: Udviklingsomkostninger | B8: =-'res_raw_41852119'!$F$5 | C8: =-'res_raw_41852119'!$E$5 | D8: =-'res_raw_41852119'!$D$5 | F8: ifrs-full:ResearchAndDevelopmentExpense (vises negativt). Udviklingsomkostninger ført i resultatet (v15_21; B&O m.fl.).
A9: Salgs- og distributionsomk. | B9: =-'res_raw_41852119'!$F$6 | C9: =-'res_raw_41852119'!$E$6 | D9: =-'res_raw_41852119'!$D$6 | F9: fsa:DistributionCosts (vises negativt). Marketing, salg, distribution.
A10: Administrationsomkostninger mv. | B10: =-'res_raw_41852119'!$F$7 | C10: =-'res_raw_41852119'!$E$7 | D10: =-'res_raw_41852119'!$D$7 | F10: fsa:AdministrativeExpenses (vises negativt). Generel administration.
A11: Andre driftsindtægter | B11: ='res_raw_41852119'!$F$8 | C11: ='res_raw_41852119'!$E$8 | D11: ='res_raw_41852119'!$D$8 | F11: fsa:OtherOperatingIncome. Sekundære driftsindtægter (huslejeindtægter, off. tilskud, avancer mv.).
A12: Andre driftsomkostninger | B12: =-'res_raw_41852119'!$F$9 | C12: =-'res_raw_41852119'!$E$9 | D12: =-'res_raw_41852119'!$D$9 | F12: fsa:OtherOperatingExpenses (vises negativt). Sekundære driftsomkostninger.
A13: Resultat af primær drift | B13: =IF(ABS((SUM(B7:B12))-'res_raw_41852119'!$F$10)<=2,SUM(B7:B12),'res_raw_41852119'!$F$10) | C13: =IF(ABS((SUM(C7:C12))-'res_raw_41852119'!$E$10)<=2,SUM(C7:C12),'res_raw_41852119'!$E$10) | D13: =IF(ABS((SUM(D7:D12))-'res_raw_41852119'!$D$10)<=2,SUM(D7:D12),'res_raw_41852119'!$D$10) | F13: Beregnet: Bruttoresultat − Udviklingsomk. − Salgs/dist. − Administration + Andre driftsindt. − Andre driftsomk. EBIT.
A14: Finansielle indtægter mv. | B14: =N('res_raw_41852119'!$F$11)+N('res_raw_41852119'!$F$12) | C14: =N('res_raw_41852119'!$E$11)+N('res_raw_41852119'!$E$12) | D14: =N('res_raw_41852119'!$D$11)+N('res_raw_41852119'!$D$12) | F14: fsa:IncomeFromSubsidiaries + fsa:OtherFinanceIncome.
A15: Finansielle omkostninger mv. | B15: =-'res_raw_41852119'!$F$13 | C15: =-'res_raw_41852119'!$E$13 | D15: =-'res_raw_41852119'!$D$13 | F15: fsa:OtherFinanceExpenses (vises negativt). Renteomkostninger, kurstab.
A16: Resultat før skat | B16: =IF(ABS((SUM(B13:B15))-'res_raw_41852119'!$F$15)<=2,SUM(B13:B15),'res_raw_41852119'!$F$15) | C16: =IF(ABS((SUM(C13:C15))-'res_raw_41852119'!$E$15)<=2,SUM(C13:C15),'res_raw_41852119'!$E$15) | D16: =IF(ABS((SUM(D13:D15))-'res_raw_41852119'!$D$15)<=2,SUM(D13:D15),'res_raw_41852119'!$D$15) | F16: Beregnet: EBIT + Fin. indtægter + Fin. omk. EBT.
A18: Uddrag af balance
A19: Anlægsaktiver | B19: ='balance_raw_41852119'!$F$8 | C19: ='balance_raw_41852119'!$E$8 | D19: ='balance_raw_41852119'!$D$8 | F19: fsa:NoncurrentAssets. Materielle, immaterielle og finansielle anlægsaktiver.
A20: Omsætningsaktiver | B20: ='balance_raw_41852119'!$F$23 | C20: ='balance_raw_41852119'!$E$23 | D20: ='balance_raw_41852119'!$D$23 | F20: fsa:CurrentAssets. Varebeholdninger, tilgodehavender, likvider.
A21: Aktiver i alt | B21: =SUM(B19:B20) | C21: =SUM(C19:C20) | D21: =SUM(D19:D20) | F21: Beregnet: Anlægsaktiver + Omsætningsaktiver. Bør matche fsa:Assets.
A23: Egenkapital | B23: ='balance_raw_41852119'!$F$31 | C23: ='balance_raw_41852119'!$E$31 | D23: ='balance_raw_41852119'!$D$31 | F23: fsa:Equity. Selskabskapital, overført resultat, reserver.
A24: Forpligtelser | B24: ='balance_raw_41852119'!$F$52-'balance_raw_41852119'!$F$31 | C24: ='balance_raw_41852119'!$E$52-'balance_raw_41852119'!$E$31 | D24: ='balance_raw_41852119'!$D$52-'balance_raw_41852119'!$D$31 | F24: Beregnet: Passiver (fsa:LiabilitiesAndEquity) − Egenkapital. Hensættelser + kort- og langfristet gæld.
A25: Passiver i alt | B25: =SUM(B23:B24) | C25: =SUM(C23:C24) | D25: =SUM(D23:D24) | F25: Beregnet: Egenkapital + Forpligtelser. Bør matche Aktiver i alt.
A27: Udvalgte balanceposter
A28: Varebeholdninger | B28: ='balance_raw_41852119'!$F$12 | C28: ='balance_raw_41852119'!$E$12 | D28: ='balance_raw_41852119'!$D$12 | F28: fsa:Inventories (eller fsa:ManufacturedGoodsAndGoodsForResale hvis total mangler).
A29: Tilgodehavender fra salg | B29: ='balance_raw_41852119'!$F$13 | C29: ='balance_raw_41852119'!$E$13 | D29: ='balance_raw_41852119'!$D$13 | F29: fsa:ShorttermTradeReceivables. Kortfristede tilgodehavender fra kunder.
A30: Kortfristede gældsforpligtelser | B30: ='balance_raw_41852119'!$F$50 | C30: ='balance_raw_41852119'!$E$50 | D30: ='balance_raw_41852119'!$D$50 | F30: fsa:ShorttermLiabilitiesOtherThanProvisions. Gæld der forfalder inden for 1 år.
A32: Rentabilitet
A33: Afkastningsgrad, % | B33: =IFERROR((B13+B14)/B21*100,"") | C33: =IFERROR((C13+C14)/C21*100,"") | D33: =IFERROR((D13+D14)/D21*100,"")
A34: Overskudsgrad, % | B34: =IFERROR((B13+B14)/B5*100,"") | C34: =IFERROR((C13+C14)/C5*100,"") | D34: =IFERROR((D13+D14)/D5*100,"")
A35: Aktivernes omsætningshastighed, gange | B35: =IFERROR(B5/B21,"") | C35: =IFERROR(C5/C21,"") | D35: =IFERROR(D5/D21,"")
A36: Gældsrente, % | B36: =IFERROR(-B15*100/B24,"") | C36: =IFERROR(-C15*100/C24,"") | D36: =IFERROR(-D15*100/D24,"")
A37: Egenkapitalens forrentning, % | B37: =IFERROR(B16/B23*100,"") | C37: =IFERROR(C16/C23*100,"") | D37: =IFERROR(D16/D23*100,"")
A38: Gearing, gange | B38: =IFERROR(B24/B23,"") | C38: =IFERROR(C24/C23,"") | D38: =IFERROR(D24/D23,"")
A40: Indekstal for indtjeningsevne (2023=100)
A41: Nettoomsætning | B41: =IFERROR(B5/$D5*100,"") | C41: =IFERROR(C5/$D5*100,"") | D41: =IFERROR(D5/$D5*100,"")
A42: Produktionsomkostninger | B42: =IFERROR(B6/$D6*100,"") | C42: =IFERROR(C6/$D6*100,"") | D42: =IFERROR(D6/$D6*100,"")
A43: Udviklingsomkostninger | B43: =IFERROR(B8/$D8*100,"") | C43: =IFERROR(C8/$D8*100,"") | D43: =IFERROR(D8/$D8*100,"")
A44: Salgs- og distributionsomk. | B44: =IFERROR(B9/$D9*100,"") | C44: =IFERROR(C9/$D9*100,"") | D44: =IFERROR(D9/$D9*100,"")
A45: Administrationsomk. | B45: =IFERROR(B10/$D10*100,"") | C45: =IFERROR(C10/$D10*100,"") | D45: =IFERROR(D10/$D10*100,"")
A46: Andre driftsomkostninger | B46: =IFERROR(B12/$D12*100,"") | C46: =IFERROR(C12/$D12*100,"") | D46: =IFERROR(D12/$D12*100,"")
A48: Indekstal for kapitaltilpasningsevne (2023=100)
A49: Nettoomsætning | B49: =IFERROR(B5*100/$D5,"") | C49: =IFERROR(C5*100/$D5,"") | D49: =IFERROR(D5*100/$D5,"")
A50: Anlægsaktiver | B50: =IFERROR(B19*100/$D19,"") | C50: =IFERROR(C19*100/$D19,"") | D50: =IFERROR(D19*100/$D19,"")
A51: Varebeholdninger | B51: =IFERROR(B28*100/$D28,"") | C51: =IFERROR(C28*100/$D28,"") | D51: =IFERROR(D28*100/$D28,"")
A52: Tilgodehavender fra salg | B52: =IFERROR(B29*100/$D29,"") | C52: =IFERROR(C29*100/$D29,"") | D52: =IFERROR(D29*100/$D29,"")
A54: Soliditet og likviditet
A55: Soliditetsgrad, % | B55: =IFERROR(B23*100/B21,"") | C55: =IFERROR(C23*100/C21,"") | D55: =IFERROR(D23*100/D21,"")
A56: Gældsandel, % | B56: =IFERROR(B24*100/B21,"") | C56: =IFERROR(C24*100/C21,"") | D56: =IFERROR(D24*100/D21,"")
A57: Likviditetsgrad, % | B57: =IFERROR(B20*100/B30,"") | C57: =IFERROR(C20*100/C30,"") | D57: =IFERROR(D20*100/D30,"")
A59: Kilde: Bearbejdet uddrag af årsrapporter for 2023-2025. Alle dataceller er live formler der peger på res_raw / balance_raw.
A61: Krydstjek mod rådata (tolerance: 1 t.kr.)
A62: Aktiver i alt = fsa:Assets | B62: =IF('balance_raw_41852119'!$F$24="","—",IF(ABS(B21-'balance_raw_41852119'!$F$24)<=1,"✓ OK","❌ "&TEXT(B21-'balance_raw_41852119'!$F$24,"+#,##0;-#,##0")&" t.kr.")) | C62: =IF('balance_raw_41852119'!$E$24="","—",IF(ABS(C21-'balance_raw_41852119'!$E$24)<=1,"✓ OK","❌ "&TEXT(C21-'balance_raw_41852119'!$E$24,"+#,##0;-#,##0")&" t.kr.")) | D62: =IF('balance_raw_41852119'!$D$24="","—",IF(ABS(D21-'balance_raw_41852119'!$D$24)<=1,"✓ OK","❌ "&TEXT(D21-'balance_raw_41852119'!$D$24,"+#,##0;-#,##0")&" t.kr.")) | F62: Verificerer at sum(Anlæg+Omsætning) matcher Assets-totalen.
A63: Passiver i alt = fsa:LiabilitiesAndEquity | B63: =IF('balance_raw_41852119'!$F$52="","—",IF(ABS(B25-'balance_raw_41852119'!$F$52)<=1,"✓ OK","❌ "&TEXT(B25-'balance_raw_41852119'!$F$52,"+#,##0;-#,##0")&" t.kr.")) | C63: =IF('balance_raw_41852119'!$E$52="","—",IF(ABS(C25-'balance_raw_41852119'!$E$52)<=1,"✓ OK","❌ "&TEXT(C25-'balance_raw_41852119'!$E$52,"+#,##0;-#,##0")&" t.kr.")) | D63: =IF('balance_raw_41852119'!$D$52="","—",IF(ABS(D25-'balance_raw_41852119'!$D$52)<=1,"✓ OK","❌ "&TEXT(D25-'balance_raw_41852119'!$D$52,"+#,##0;-#,##0")&" t.kr.")) | F63: Verificerer at sum(EK+Forpligtelser) matcher Passiver-totalen.
A64: Aktiver i alt = Passiver i alt | B64: =IF(ABS(B21-B25)<=1,"✓ OK","❌ "&TEXT(B21-B25,"+#,##0;-#,##0")&" t.kr.") | C64: =IF(ABS(C21-C25)<=1,"✓ OK","❌ "&TEXT(C21-C25,"+#,##0;-#,##0")&" t.kr.") | D64: =IF(ABS(D21-D25)<=1,"✓ OK","❌ "&TEXT(D21-D25,"+#,##0;-#,##0")&" t.kr.") | F64: Balance-identitet på arket selv. Skal altid være 0 differance.
A65: Bruttoresultat (beregnet) = fsa:GrossResult | B65: =IF('res_raw_41852119'!$F$4="","—",IF(ABS(B7-'res_raw_41852119'!$F$4)<=1,"✓ OK","❌ "&TEXT(B7-'res_raw_41852119'!$F$4,"+#,##0;-#,##0")&" t.kr.")) | C65: =IF('res_raw_41852119'!$E$4="","—",IF(ABS(C7-'res_raw_41852119'!$E$4)<=1,"✓ OK","❌ "&TEXT(C7-'res_raw_41852119'!$E$4,"+#,##0;-#,##0")&" t.kr.")) | D65: =IF('res_raw_41852119'!$D$4="","—",IF(ABS(D7-'res_raw_41852119'!$D$4)<=1,"✓ OK","❌ "&TEXT(D7-'res_raw_41852119'!$D$4,"+#,##0;-#,##0")&" t.kr.")) | F65: Hvis Nettoomsætning eller omkostninger mangler, vil sumberegnet bruttoresultat afvige.
A66: EBIT (beregnet) = fsa:ProfitLossFromOrdinaryOperatingActivities | B66: =IF('res_raw_41852119'!$F$10="","—",IF(ABS(B13-'res_raw_41852119'!$F$10)<=1,"✓ OK","❌ "&TEXT(B13-'res_raw_41852119'!$F$10,"+#,##0;-#,##0")&" t.kr.")) | C66: =IF('res_raw_41852119'!$E$10="","—",IF(ABS(C13-'res_raw_41852119'!$E$10)<=1,"✓ OK","❌ "&TEXT(C13-'res_raw_41852119'!$E$10,"+#,##0;-#,##0")&" t.kr.")) | D66: =IF('res_raw_41852119'!$D$10="","—",IF(ABS(D13-'res_raw_41852119'!$D$10)<=1,"✓ OK","❌ "&TEXT(D13-'res_raw_41852119'!$D$10,"+#,##0;-#,##0")&" t.kr.")) | F66: Verificerer at sumberegnet EBIT matcher det rapporterede.
A67: EBT (beregnet) = fsa:ProfitLossFromOrdinaryActivitiesBeforeTax | B67: =IF('res_raw_41852119'!$F$15="","—",IF(ABS(B16-'res_raw_41852119'!$F$15)<=1,"✓ OK","❌ "&TEXT(B16-'res_raw_41852119'!$F$15,"+#,##0;-#,##0")&" t.kr.")) | C67: =IF('res_raw_41852119'!$E$15="","—",IF(ABS(C16-'res_raw_41852119'!$E$15)<=1,"✓ OK","❌ "&TEXT(C16-'res_raw_41852119'!$E$15,"+#,##0;-#,##0")&" t.kr.")) | D67: =IF('res_raw_41852119'!$D$15="","—",IF(ABS(D16-'res_raw_41852119'!$D$15)<=1,"✓ OK","❌ "&TEXT(D16-'res_raw_41852119'!$D$15,"+#,##0;-#,##0")&" t.kr.")) | F67: Verificerer at sumberegnet resultat før skat matcher det rapporterede.

Sheet Noter_info
A1: Tetra Pak Processing Systems A/S (CVR 41852119) — Ukendte XBRL-felter — disse er noter og ikke en del af hoved-regnskabet
A2: Kategori | B2: Dansk navn | C2: XBRL feltnavn | D2: 2021 t.kr. | E2: 2022 t.kr. | F2: 2023 t.kr. | G2: 2024 t.kr. | H2: 2025 t.kr. | I2: Forklaring
A3: Øvrige (ukendt) | B3: fsa:CashCapitalIncrease | C3: fsa:CashCapitalIncrease | D3: 31737 | E3: 16261 | F3: 41586 | I3: Ingen forklaring tilgængelig.
A4: Øvrige (ukendt) | B4: fsa:ExchangeRateAdjustmentsOtherFinanceExpenses | C4: fsa:ExchangeRateAdjustmentsOtherFinanceExpenses | D4: 180 | E4: 79 | F4: 359 | G4: 884 | H4: 764 | I4: Ingen forklaring tilgængelig.
A5: Øvrige (ukendt) | B5: fsa:InformationOnAuditorsFees | C5: fsa:InformationOnAuditorsFees | H5: 0 | I5: Ingen forklaring tilgængelig.
A6: Øvrige (ukendt) | B6: fsa:InterestIncomeFromParticipatingInterests | C6: fsa:InterestIncomeFromParticipatingInterests | G6: 0 | H6: 35627 | I6: Ingen forklaring tilgængelig.
A7: Øvrige (ukendt) | B7: fsa:NominalValueOfIssuedShares | C7: fsa:NominalValueOfIssuedShares | G7: 12000 | H7: 12000 | I7: Ingen forklaring tilgængelig.
A8: Øvrige (ukendt) | B8: fsa:OtherProvisionsLiabilitiesShortterm | C8: fsa:OtherProvisionsLiabilitiesShortterm | G8: 19619 | H8: 21169 | I8: Ingen forklaring tilgængelig.
A9: Øvrige (ukendt) | B9: fsa:OtherReceivables | C9: fsa:OtherReceivables | F9: 43079 | I9: Ingen forklaring tilgængelig.
A10: Øvrige (ukendt) | B10: fsa:Planes | C10: fsa:Planes | D10: 2823 | E10: 3019 | F10: 1814 | G10: 32605 | H10: 16607 | I10: Ingen forklaring tilgængelig.
A11: Øvrige (ukendt) | B11: fsa:RaisingOfLongtermDebt | C11: fsa:RaisingOfLongtermDebt | D11: 0 | I11: Ingen forklaring tilgængelig.
A12: Øvrige (ukendt) | B12: fsa:ReductionOfLeaseCommitments | C12: fsa:ReductionOfLeaseCommitments | G12: -7826 | H12: -7539 | I12: Ingen forklaring tilgængelig.
A13: Øvrige (ukendt) | B13: fsa:RestOfOtherReceivables | C13: fsa:RestOfOtherReceivables | F13: 43079 | I13: Ingen forklaring tilgængelig.
A14: Øvrige (ukendt) | B14: fsa:SaleOfTreasuryShares | C14: fsa:SaleOfTreasuryShares | D14: -9829 | E14: -8226 | F14: -8391 | I14: Ingen forklaring tilgængelig.
A15: Øvrige (ukendt) | B15: fsa:Ships | C15: fsa:Ships | D15: 16821 | E15: 10666 | F15: 16991 | G15: 905 | H15: 1189 | I15: Ingen forklaring tilgængelig.
