Workbook

Sheet Overblik_43705660
A1: THURØ BRYGHUS APS (CVR 43705660) — Regnskabsanalyse – Resultatopgørelse & Balance (t.kr.) · Klasse B · Andre erklæringer uden sikkerh
G2: Indekstal (2022=100)
A3: Resultatopgørelse t.kr. | B3: 2022 | C3: 2023 | D3: 2024 | E3: 2025 | G3: 2022 | H3: 2023 | I3: 2024 | J3: 2025
A4: Nettoomsætning | B4: ='res_raw_43705660'!$B$2 | C4: ='res_raw_43705660'!$C$2 | D4: ='res_raw_43705660'!$D$2 | E4: ='res_raw_43705660'!$E$2 | G4: =IFERROR(B4/$B$4*100,"") | H4: =IFERROR(C4/$B$4*100,"") | I4: =IFERROR(D4/$B$4*100,"") | J4: =IFERROR(E4/$B$4*100,"")
A5: Andre driftsindtægter | B5: ='res_raw_43705660'!$B$3 | C5: ='res_raw_43705660'!$C$3 | D5: ='res_raw_43705660'!$D$3 | E5: ='res_raw_43705660'!$E$3 | G5: =IFERROR(B5/$B$5*100,"") | H5: =IFERROR(C5/$B$5*100,"") | I5: =IFERROR(D5/$B$5*100,"") | J5: =IFERROR(E5/$B$5*100,"")
A6: Vareforbrug | B6: ='res_raw_43705660'!$B$4 | C6: ='res_raw_43705660'!$C$4 | D6: ='res_raw_43705660'!$D$4 | E6: ='res_raw_43705660'!$E$4 | G6: =IFERROR(B6/$B$6*100,"") | H6: =IFERROR(C6/$B$6*100,"") | I6: =IFERROR(D6/$B$6*100,"") | J6: =IFERROR(E6/$B$6*100,"")
A7: Andre eksterne omkostninger | B7: ='res_raw_43705660'!$B$5 | C7: ='res_raw_43705660'!$C$5 | D7: ='res_raw_43705660'!$D$5 | E7: ='res_raw_43705660'!$E$5 | G7: =IFERROR(B7/$B$7*100,"") | H7: =IFERROR(C7/$B$7*100,"") | I7: =IFERROR(D7/$B$7*100,"") | J7: =IFERROR(E7/$B$7*100,"")
A8: Bruttoresultat | B8: ='res_raw_43705660'!$B$6 | C8: ='res_raw_43705660'!$C$6 | D8: ='res_raw_43705660'!$D$6 | E8: ='res_raw_43705660'!$E$6 | G8: =IFERROR(B8/$B$8*100,"") | H8: =IFERROR(C8/$B$8*100,"") | I8: =IFERROR(D8/$B$8*100,"") | J8: =IFERROR(E8/$B$8*100,"")
A9: Personaleomkostninger | B9: ='res_raw_43705660'!$B$7 | C9: ='res_raw_43705660'!$C$7 | D9: ='res_raw_43705660'!$D$7 | E9: ='res_raw_43705660'!$E$7 | G9: =IFERROR(B9/$B$9*100,"") | H9: =IFERROR(C9/$B$9*100,"") | I9: =IFERROR(D9/$B$9*100,"") | J9: =IFERROR(E9/$B$9*100,"")
A10: Resultat før afskrivninger | B10: =IFERROR($B$8-ABS($B$9),"") | C10: =IFERROR($C$8-ABS($C$9),"") | D10: =IFERROR($D$8-ABS($D$9),"") | E10: =IFERROR($E$8-ABS($E$9),"") | G10: =IFERROR(B10/$B$10*100,"") | H10: =IFERROR(C10/$B$10*100,"") | I10: =IFERROR(D10/$B$10*100,"") | J10: =IFERROR(E10/$B$10*100,"")
A11: Af- og nedskrivninger | B11: ='res_raw_43705660'!$B$9 | C11: ='res_raw_43705660'!$C$9 | D11: ='res_raw_43705660'!$D$9 | E11: ='res_raw_43705660'!$E$9 | G11: =IFERROR(B11/$B$11*100,"") | H11: =IFERROR(C11/$B$11*100,"") | I11: =IFERROR(D11/$B$11*100,"") | J11: =IFERROR(E11/$B$11*100,"")
A12: Andre driftsomkostninger | B12: ='res_raw_43705660'!$B$10 | C12: ='res_raw_43705660'!$C$10 | D12: ='res_raw_43705660'!$D$10 | E12: ='res_raw_43705660'!$E$10 | G12: =IFERROR(B12/$B$12*100,"") | H12: =IFERROR(C12/$B$12*100,"") | I12: =IFERROR(D12/$B$12*100,"") | J12: =IFERROR(E12/$B$12*100,"")
A13: Resultat af primær drift | B13: ='res_raw_43705660'!$B$11 | C13: ='res_raw_43705660'!$C$11 | D13: ='res_raw_43705660'!$D$11 | E13: ='res_raw_43705660'!$E$11 | G13: =IFERROR(B13/$B$13*100,"") | H13: =IFERROR(C13/$B$13*100,"") | I13: =IFERROR(D13/$B$13*100,"") | J13: =IFERROR(E13/$B$13*100,"")
A14: Indtægter af kapitalandele, dattervirksomheder | B14: ='res_raw_43705660'!$B$12 | C14: ='res_raw_43705660'!$C$12 | D14: ='res_raw_43705660'!$D$12 | E14: ='res_raw_43705660'!$E$12 | G14: =IFERROR(B14/$B$14*100,"") | H14: =IFERROR(C14/$B$14*100,"") | I14: =IFERROR(D14/$B$14*100,"") | J14: =IFERROR(E14/$B$14*100,"")
A15: Finansielle indtægter | B15: ='res_raw_43705660'!$B$13 | C15: ='res_raw_43705660'!$C$13 | D15: ='res_raw_43705660'!$D$13 | E15: ='res_raw_43705660'!$E$13 | G15: =IFERROR(B15/$B$15*100,"") | H15: =IFERROR(C15/$B$15*100,"") | I15: =IFERROR(D15/$B$15*100,"") | J15: =IFERROR(E15/$B$15*100,"")
A16: Finansielle omkostninger | B16: ='res_raw_43705660'!$B$14 | C16: ='res_raw_43705660'!$C$14 | D16: ='res_raw_43705660'!$D$14 | E16: ='res_raw_43705660'!$E$14 | G16: =IFERROR(B16/$B$16*100,"") | H16: =IFERROR(C16/$B$16*100,"") | I16: =IFERROR(D16/$B$16*100,"") | J16: =IFERROR(E16/$B$16*100,"")
A17: Finansielle poster, netto | B17: ='res_raw_43705660'!$B$15 | C17: ='res_raw_43705660'!$C$15 | D17: ='res_raw_43705660'!$D$15 | E17: ='res_raw_43705660'!$E$15 | G17: =IFERROR(B17/$B$17*100,"") | H17: =IFERROR(C17/$B$17*100,"") | I17: =IFERROR(D17/$B$17*100,"") | J17: =IFERROR(E17/$B$17*100,"")
A18: Resultat før skat | B18: ='res_raw_43705660'!$B$16 | C18: ='res_raw_43705660'!$C$16 | D18: ='res_raw_43705660'!$D$16 | E18: ='res_raw_43705660'!$E$16 | G18: =IFERROR(B18/$B$18*100,"") | H18: =IFERROR(C18/$B$18*100,"") | I18: =IFERROR(D18/$B$18*100,"") | J18: =IFERROR(E18/$B$18*100,"")
A19: Skat af årets resultat | B19: ='res_raw_43705660'!$B$17 | C19: ='res_raw_43705660'!$C$17 | D19: ='res_raw_43705660'!$D$17 | E19: ='res_raw_43705660'!$E$17 | G19: =IFERROR(B19/$B$19*100,"") | H19: =IFERROR(C19/$B$19*100,"") | I19: =IFERROR(D19/$B$19*100,"") | J19: =IFERROR(E19/$B$19*100,"")
A20: Årets resultat | B20: ='res_raw_43705660'!$B$18 | C20: ='res_raw_43705660'!$C$18 | D20: ='res_raw_43705660'!$D$18 | E20: ='res_raw_43705660'!$E$18 | G20: =IFERROR(B20/$B$20*100,"") | H20: =IFERROR(C20/$B$20*100,"") | I20: =IFERROR(D20/$B$20*100,"") | J20: =IFERROR(E20/$B$20*100,"")
A22: AKTIVER t.kr. | B22: 2022 | C22: 2023 | D22: 2024 | E22: 2025 | G22: 2022 | H22: 2023 | I22: 2024 | J22: 2025
A23: Grunde og bygninger | B23: ='balance_raw_43705660'!$B$2 | C23: ='balance_raw_43705660'!$C$2 | D23: ='balance_raw_43705660'!$D$2 | E23: ='balance_raw_43705660'!$E$2 | G23: =IFERROR(B23/$B$23*100,"") | H23: =IFERROR(C23/$B$23*100,"") | I23: =IFERROR(D23/$B$23*100,"") | J23: =IFERROR(E23/$B$23*100,"")
A24: Produktionsanlæg og maskiner | B24: ='balance_raw_43705660'!$B$3 | C24: ='balance_raw_43705660'!$C$3 | D24: ='balance_raw_43705660'!$D$3 | E24: ='balance_raw_43705660'!$E$3 | G24: =IFERROR(B24/$B$24*100,"") | H24: =IFERROR(C24/$B$24*100,"") | I24: =IFERROR(D24/$B$24*100,"") | J24: =IFERROR(E24/$B$24*100,"")
A25: Driftsmateriel og inventar | B25: ='balance_raw_43705660'!$B$4 | C25: ='balance_raw_43705660'!$C$4 | D25: ='balance_raw_43705660'!$D$4 | E25: ='balance_raw_43705660'!$E$4 | G25: =IFERROR(B25/$B$25*100,"") | H25: =IFERROR(C25/$B$25*100,"") | I25: =IFERROR(D25/$B$25*100,"") | J25: =IFERROR(E25/$B$25*100,"")
A26: Indretning af lejede lokaler | B26: ='balance_raw_43705660'!$B$5 | C26: ='balance_raw_43705660'!$C$5 | D26: ='balance_raw_43705660'!$D$5 | E26: ='balance_raw_43705660'!$E$5 | G26: =IFERROR(B26/$B$26*100,"") | H26: =IFERROR(C26/$B$26*100,"") | I26: =IFERROR(D26/$B$26*100,"") | J26: =IFERROR(E26/$B$26*100,"")
A27: Forudbetaling og anlægsaktiver under opførelse | B27: ='balance_raw_43705660'!$B$6 | C27: ='balance_raw_43705660'!$C$6 | D27: ='balance_raw_43705660'!$D$6 | E27: ='balance_raw_43705660'!$E$6 | G27: =IFERROR(B27/$B$27*100,"") | H27: =IFERROR(C27/$B$27*100,"") | I27: =IFERROR(D27/$B$27*100,"") | J27: =IFERROR(E27/$B$27*100,"")
A28: Materielle anlægsaktiver | B28: ='balance_raw_43705660'!$B$7 | C28: ='balance_raw_43705660'!$C$7 | D28: ='balance_raw_43705660'!$D$7 | E28: ='balance_raw_43705660'!$E$7 | G28: =IFERROR(B28/$B$28*100,"") | H28: =IFERROR(C28/$B$28*100,"") | I28: =IFERROR(D28/$B$28*100,"") | J28: =IFERROR(E28/$B$28*100,"")
A29: Kapitalandele, dattervirksomheder | B29: ='balance_raw_43705660'!$B$8 | C29: ='balance_raw_43705660'!$C$8 | D29: ='balance_raw_43705660'!$D$8 | E29: ='balance_raw_43705660'!$E$8 | G29: =IFERROR(B29/$B$29*100,"") | H29: =IFERROR(C29/$B$29*100,"") | I29: =IFERROR(D29/$B$29*100,"") | J29: =IFERROR(E29/$B$29*100,"")
A30: Deposita | B30: ='balance_raw_43705660'!$B$9 | C30: ='balance_raw_43705660'!$C$9 | D30: ='balance_raw_43705660'!$D$9 | E30: ='balance_raw_43705660'!$E$9 | G30: =IFERROR(B30/$B$30*100,"") | H30: =IFERROR(C30/$B$30*100,"") | I30: =IFERROR(D30/$B$30*100,"") | J30: =IFERROR(E30/$B$30*100,"")
A31: Finansielle anlægsaktiver | B31: ='balance_raw_43705660'!$B$10 | C31: ='balance_raw_43705660'!$C$10 | D31: ='balance_raw_43705660'!$D$10 | E31: ='balance_raw_43705660'!$E$10 | G31: =IFERROR(B31/$B$31*100,"") | H31: =IFERROR(C31/$B$31*100,"") | I31: =IFERROR(D31/$B$31*100,"") | J31: =IFERROR(E31/$B$31*100,"")
A32: Anlægsaktiver | B32: ='balance_raw_43705660'!$B$11 | C32: ='balance_raw_43705660'!$C$11 | D32: ='balance_raw_43705660'!$D$11 | E32: ='balance_raw_43705660'!$E$11 | G32: =IFERROR(B32/$B$32*100,"") | H32: =IFERROR(C32/$B$32*100,"") | I32: =IFERROR(D32/$B$32*100,"") | J32: =IFERROR(E32/$B$32*100,"")
A33: Råvarer og hjælpematerialer | B33: ='balance_raw_43705660'!$B$12 | C33: ='balance_raw_43705660'!$C$12 | D33: ='balance_raw_43705660'!$D$12 | E33: ='balance_raw_43705660'!$E$12 | G33: =IFERROR(B33/$B$33*100,"") | H33: =IFERROR(C33/$B$33*100,"") | I33: =IFERROR(D33/$B$33*100,"") | J33: =IFERROR(E33/$B$33*100,"")
A34: Varer under fremstilling | B34: ='balance_raw_43705660'!$B$13 | C34: ='balance_raw_43705660'!$C$13 | D34: ='balance_raw_43705660'!$D$13 | E34: ='balance_raw_43705660'!$E$13 | G34: =IFERROR(B34/$B$34*100,"") | H34: =IFERROR(C34/$B$34*100,"") | I34: =IFERROR(D34/$B$34*100,"") | J34: =IFERROR(E34/$B$34*100,"")
A35: Færdigvarer og handelsvarer | B35: ='balance_raw_43705660'!$B$14 | C35: ='balance_raw_43705660'!$C$14 | D35: ='balance_raw_43705660'!$D$14 | E35: ='balance_raw_43705660'!$E$14 | G35: =IFERROR(B35/$B$35*100,"") | H35: =IFERROR(C35/$B$35*100,"") | I35: =IFERROR(D35/$B$35*100,"") | J35: =IFERROR(E35/$B$35*100,"")
A36: Varebeholdninger | B36: ='balance_raw_43705660'!$B$15 | C36: ='balance_raw_43705660'!$C$15 | D36: ='balance_raw_43705660'!$D$15 | E36: ='balance_raw_43705660'!$E$15 | G36: =IFERROR(B36/$B$36*100,"") | H36: =IFERROR(C36/$B$36*100,"") | I36: =IFERROR(D36/$B$36*100,"") | J36: =IFERROR(E36/$B$36*100,"")
A37: Tilgodehavender fra salg og tjenesteydelser | B37: ='balance_raw_43705660'!$B$16 | C37: ='balance_raw_43705660'!$C$16 | D37: ='balance_raw_43705660'!$D$16 | E37: ='balance_raw_43705660'!$E$16 | G37: =IFERROR(B37/$B$37*100,"") | H37: =IFERROR(C37/$B$37*100,"") | I37: =IFERROR(D37/$B$37*100,"") | J37: =IFERROR(E37/$B$37*100,"")
A38: Tilgodehavender hos tilknyttede virksomheder | B38: ='balance_raw_43705660'!$B$17 | C38: ='balance_raw_43705660'!$C$17 | D38: ='balance_raw_43705660'!$D$17 | E38: ='balance_raw_43705660'!$E$17 | G38: =IFERROR(B38/$B$38*100,"") | H38: =IFERROR(C38/$B$38*100,"") | I38: =IFERROR(D38/$B$38*100,"") | J38: =IFERROR(E38/$B$38*100,"")
A39: Andre tilgodehavender | B39: ='balance_raw_43705660'!$B$18 | C39: ='balance_raw_43705660'!$C$18 | D39: ='balance_raw_43705660'!$D$18 | E39: ='balance_raw_43705660'!$E$18 | G39: =IFERROR(B39/$B$39*100,"") | H39: =IFERROR(C39/$B$39*100,"") | I39: =IFERROR(D39/$B$39*100,"") | J39: =IFERROR(E39/$B$39*100,"")
A40: Periodeafgrænsningsposter (aktiver) | B40: ='balance_raw_43705660'!$B$19 | C40: ='balance_raw_43705660'!$C$19 | D40: ='balance_raw_43705660'!$D$19 | E40: ='balance_raw_43705660'!$E$19 | G40: =IFERROR(B40/$B$40*100,"") | H40: =IFERROR(C40/$B$40*100,"") | I40: =IFERROR(D40/$B$40*100,"") | J40: =IFERROR(E40/$B$40*100,"")
A41: Udskudt skatteaktiv | B41: ='balance_raw_43705660'!$B$20 | C41: ='balance_raw_43705660'!$C$20 | D41: ='balance_raw_43705660'!$D$20 | E41: ='balance_raw_43705660'!$E$20 | G41: =IFERROR(B41/$B$41*100,"") | H41: =IFERROR(C41/$B$41*100,"") | I41: =IFERROR(D41/$B$41*100,"") | J41: =IFERROR(E41/$B$41*100,"")
A42: Tilgodehavende skat hos tilknyttede virksomheder | B42: ='balance_raw_43705660'!$B$21 | C42: ='balance_raw_43705660'!$C$21 | D42: ='balance_raw_43705660'!$D$21 | E42: ='balance_raw_43705660'!$E$21 | G42: =IFERROR(B42/$B$42*100,"") | H42: =IFERROR(C42/$B$42*100,"") | I42: =IFERROR(D42/$B$42*100,"") | J42: =IFERROR(E42/$B$42*100,"")
A43: Kortfristede skattetilgodehavender | B43: ='balance_raw_43705660'!$B$22 | C43: ='balance_raw_43705660'!$C$22 | D43: ='balance_raw_43705660'!$D$22 | E43: ='balance_raw_43705660'!$E$22 | G43: =IFERROR(B43/$B$43*100,"") | H43: =IFERROR(C43/$B$43*100,"") | I43: =IFERROR(D43/$B$43*100,"") | J43: =IFERROR(E43/$B$43*100,"")
A44: Tilgodehavender | B44: ='balance_raw_43705660'!$B$23 | C44: ='balance_raw_43705660'!$C$23 | D44: ='balance_raw_43705660'!$D$23 | E44: ='balance_raw_43705660'!$E$23 | G44: =IFERROR(B44/$B$44*100,"") | H44: =IFERROR(C44/$B$44*100,"") | I44: =IFERROR(D44/$B$44*100,"") | J44: =IFERROR(E44/$B$44*100,"")
A45: Værdipapirer | B45: ='balance_raw_43705660'!$B$24 | C45: ='balance_raw_43705660'!$C$24 | D45: ='balance_raw_43705660'!$D$24 | E45: ='balance_raw_43705660'!$E$24 | G45: =IFERROR(B45/$B$45*100,"") | H45: =IFERROR(C45/$B$45*100,"") | I45: =IFERROR(D45/$B$45*100,"") | J45: =IFERROR(E45/$B$45*100,"")
A46: Likvide beholdninger | B46: ='balance_raw_43705660'!$B$25 | C46: ='balance_raw_43705660'!$C$25 | D46: ='balance_raw_43705660'!$D$25 | E46: ='balance_raw_43705660'!$E$25 | G46: =IFERROR(B46/$B$46*100,"") | H46: =IFERROR(C46/$B$46*100,"") | I46: =IFERROR(D46/$B$46*100,"") | J46: =IFERROR(E46/$B$46*100,"")
A47: Omsætningsaktiver | B47: ='balance_raw_43705660'!$B$26 | C47: ='balance_raw_43705660'!$C$26 | D47: ='balance_raw_43705660'!$D$26 | E47: ='balance_raw_43705660'!$E$26 | G47: =IFERROR(B47/$B$47*100,"") | H47: =IFERROR(C47/$B$47*100,"") | I47: =IFERROR(D47/$B$47*100,"") | J47: =IFERROR(E47/$B$47*100,"")
A48: Aktiver | B48: ='balance_raw_43705660'!$B$27 | C48: ='balance_raw_43705660'!$C$27 | D48: ='balance_raw_43705660'!$D$27 | E48: ='balance_raw_43705660'!$E$27 | G48: =IFERROR(B48/$B$48*100,"") | H48: =IFERROR(C48/$B$48*100,"") | I48: =IFERROR(D48/$B$48*100,"") | J48: =IFERROR(E48/$B$48*100,"")
A50: PASSIVER t.kr. | B50: 2022 | C50: 2023 | D50: 2024 | E50: 2025 | G50: 2022 | H50: 2023 | I50: 2024 | J50: 2025
A51: Selskabskapital | B51: ='balance_raw_43705660'!$B$28 | C51: ='balance_raw_43705660'!$C$28 | D51: ='balance_raw_43705660'!$D$28 | E51: ='balance_raw_43705660'!$E$28 | G51: =IFERROR(B51/$B$51*100,"") | H51: =IFERROR(C51/$B$51*100,"") | I51: =IFERROR(D51/$B$51*100,"") | J51: =IFERROR(E51/$B$51*100,"")
A52: Reserve for nettoopskrivning (indre værdis metode) | B52: ='balance_raw_43705660'!$B$29 | C52: ='balance_raw_43705660'!$C$29 | D52: ='balance_raw_43705660'!$D$29 | E52: ='balance_raw_43705660'!$E$29 | G52: =IFERROR(B52/$B$52*100,"") | H52: =IFERROR(C52/$B$52*100,"") | I52: =IFERROR(D52/$B$52*100,"") | J52: =IFERROR(E52/$B$52*100,"")
A53: Reserve for udviklingsomkostninger | B53: ='balance_raw_43705660'!$B$30 | C53: ='balance_raw_43705660'!$C$30 | D53: ='balance_raw_43705660'!$D$30 | E53: ='balance_raw_43705660'!$E$30 | G53: =IFERROR(B53/$B$53*100,"") | H53: =IFERROR(C53/$B$53*100,"") | I53: =IFERROR(D53/$B$53*100,"") | J53: =IFERROR(E53/$B$53*100,"")
A54: Reserve for sikringstransaktioner | B54: ='balance_raw_43705660'!$B$31 | C54: ='balance_raw_43705660'!$C$31 | D54: ='balance_raw_43705660'!$D$31 | E54: ='balance_raw_43705660'!$E$31 | G54: =IFERROR(B54/$B$54*100,"") | H54: =IFERROR(C54/$B$54*100,"") | I54: =IFERROR(D54/$B$54*100,"") | J54: =IFERROR(E54/$B$54*100,"")
A55: Andre reserver | B55: ='balance_raw_43705660'!$B$32 | C55: ='balance_raw_43705660'!$C$32 | D55: ='balance_raw_43705660'!$D$32 | E55: ='balance_raw_43705660'!$E$32 | G55: =IFERROR(B55/$B$55*100,"") | H55: =IFERROR(C55/$B$55*100,"") | I55: =IFERROR(D55/$B$55*100,"") | J55: =IFERROR(E55/$B$55*100,"")
A56: Overført resultat | B56: ='balance_raw_43705660'!$B$33 | C56: ='balance_raw_43705660'!$C$33 | D56: ='balance_raw_43705660'!$D$33 | E56: ='balance_raw_43705660'!$E$33 | G56: =IFERROR(B56/$B$56*100,"") | H56: =IFERROR(C56/$B$56*100,"") | I56: =IFERROR(D56/$B$56*100,"") | J56: =IFERROR(E56/$B$56*100,"")
A57: Egenkapital i alt | B57: ='balance_raw_43705660'!$B$34 | C57: ='balance_raw_43705660'!$C$34 | D57: ='balance_raw_43705660'!$D$34 | E57: ='balance_raw_43705660'!$E$34 | G57: =IFERROR(B57/$B$57*100,"") | H57: =IFERROR(C57/$B$57*100,"") | I57: =IFERROR(D57/$B$57*100,"") | J57: =IFERROR(E57/$B$57*100,"")
A58: Hensættelse til udskudt skat | B58: ='balance_raw_43705660'!$B$35 | C58: ='balance_raw_43705660'!$C$35 | D58: ='balance_raw_43705660'!$D$35 | E58: ='balance_raw_43705660'!$E$35 | G58: =IFERROR(B58/$B$58*100,"") | H58: =IFERROR(C58/$B$58*100,"") | I58: =IFERROR(D58/$B$58*100,"") | J58: =IFERROR(E58/$B$58*100,"")
A59: Hensatte forpligtelser | B59: ='balance_raw_43705660'!$B$36 | C59: ='balance_raw_43705660'!$C$36 | D59: ='balance_raw_43705660'!$D$36 | E59: ='balance_raw_43705660'!$E$36 | G59: =IFERROR(B59/$B$59*100,"") | H59: =IFERROR(C59/$B$59*100,"") | I59: =IFERROR(D59/$B$59*100,"") | J59: =IFERROR(E59/$B$59*100,"")
A60: Ansvarlig lånekapital (langfristet) | B60: ='balance_raw_43705660'!$B$37 | C60: ='balance_raw_43705660'!$C$37 | D60: ='balance_raw_43705660'!$D$37 | E60: ='balance_raw_43705660'!$E$37 | G60: =IFERROR(B60/$B$60*100,"") | H60: =IFERROR(C60/$B$60*100,"") | I60: =IFERROR(D60/$B$60*100,"") | J60: =IFERROR(E60/$B$60*100,"")
A61: Langfristede lån | B61: ='balance_raw_43705660'!$B$38 | C61: ='balance_raw_43705660'!$C$38 | D61: ='balance_raw_43705660'!$D$38 | E61: ='balance_raw_43705660'!$E$38 | G61: =IFERROR(B61/$B$61*100,"") | H61: =IFERROR(C61/$B$61*100,"") | I61: =IFERROR(D61/$B$61*100,"") | J61: =IFERROR(E61/$B$61*100,"")
A62: Leasingforpligtelser (langfristet) | B62: ='balance_raw_43705660'!$B$39 | C62: ='balance_raw_43705660'!$C$39 | D62: ='balance_raw_43705660'!$D$39 | E62: ='balance_raw_43705660'!$E$39 | G62: =IFERROR(B62/$B$62*100,"") | H62: =IFERROR(C62/$B$62*100,"") | I62: =IFERROR(D62/$B$62*100,"") | J62: =IFERROR(E62/$B$62*100,"")
A63: Anden gæld (langfristet) | B63: ='balance_raw_43705660'!$B$40 | C63: ='balance_raw_43705660'!$C$40 | D63: ='balance_raw_43705660'!$D$40 | E63: ='balance_raw_43705660'!$E$40 | G63: =IFERROR(B63/$B$63*100,"") | H63: =IFERROR(C63/$B$63*100,"") | I63: =IFERROR(D63/$B$63*100,"") | J63: =IFERROR(E63/$B$63*100,"")
A64: Langfristede gældsforpligtelser | B64: ='balance_raw_43705660'!$B$41 | C64: ='balance_raw_43705660'!$C$41 | D64: ='balance_raw_43705660'!$D$41 | E64: ='balance_raw_43705660'!$E$41 | G64: =IFERROR(B64/$B$64*100,"") | H64: =IFERROR(C64/$B$64*100,"") | I64: =IFERROR(D64/$B$64*100,"") | J64: =IFERROR(E64/$B$64*100,"")
A65: Ansvarlig lånekapital (kortfristet) | B65: ='balance_raw_43705660'!$B$42 | C65: ='balance_raw_43705660'!$C$42 | D65: ='balance_raw_43705660'!$D$42 | E65: ='balance_raw_43705660'!$E$42 | G65: =IFERROR(B65/$B$65*100,"") | H65: =IFERROR(C65/$B$65*100,"") | I65: =IFERROR(D65/$B$65*100,"") | J65: =IFERROR(E65/$B$65*100,"")
A66: Kortfristet del af langfristede gældsforpligtelser | B66: ='balance_raw_43705660'!$B$43 | C66: ='balance_raw_43705660'!$C$43 | D66: ='balance_raw_43705660'!$D$43 | E66: ='balance_raw_43705660'!$E$43 | G66: =IFERROR(B66/$B$66*100,"") | H66: =IFERROR(C66/$B$66*100,"") | I66: =IFERROR(D66/$B$66*100,"") | J66: =IFERROR(E66/$B$66*100,"")
A67: Kreditinstitutter | B67: ='balance_raw_43705660'!$B$44 | C67: ='balance_raw_43705660'!$C$44 | D67: ='balance_raw_43705660'!$D$44 | E67: ='balance_raw_43705660'!$E$44 | G67: =IFERROR(B67/$B$67*100,"") | H67: =IFERROR(C67/$B$67*100,"") | I67: =IFERROR(D67/$B$67*100,"") | J67: =IFERROR(E67/$B$67*100,"")
A68: Leasingforpligtelser (kortfristet) | B68: ='balance_raw_43705660'!$B$45 | C68: ='balance_raw_43705660'!$C$45 | D68: ='balance_raw_43705660'!$D$45 | E68: ='balance_raw_43705660'!$E$45 | G68: =IFERROR(B68/$B$68*100,"") | H68: =IFERROR(C68/$B$68*100,"") | I68: =IFERROR(D68/$B$68*100,"") | J68: =IFERROR(E68/$B$68*100,"")
A69: Leverandører af varer og tjenesteydelser | B69: ='balance_raw_43705660'!$B$46 | C69: ='balance_raw_43705660'!$C$46 | D69: ='balance_raw_43705660'!$D$46 | E69: ='balance_raw_43705660'!$E$46 | G69: =IFERROR(B69/$B$69*100,"") | H69: =IFERROR(C69/$B$69*100,"") | I69: =IFERROR(D69/$B$69*100,"") | J69: =IFERROR(E69/$B$69*100,"")
A70: Gæld til tilknyttede virksomheder | B70: ='balance_raw_43705660'!$B$47 | C70: ='balance_raw_43705660'!$C$47 | D70: ='balance_raw_43705660'!$D$47 | E70: ='balance_raw_43705660'!$E$47 | G70: =IFERROR(B70/$B$70*100,"") | H70: =IFERROR(C70/$B$70*100,"") | I70: =IFERROR(D70/$B$70*100,"") | J70: =IFERROR(E70/$B$70*100,"")
A71: Gæld til selskabsdeltagere og ledelse | B71: ='balance_raw_43705660'!$B$48 | C71: ='balance_raw_43705660'!$C$48 | D71: ='balance_raw_43705660'!$D$48 | E71: ='balance_raw_43705660'!$E$48 | G71: =IFERROR(B71/$B$71*100,"") | H71: =IFERROR(C71/$B$71*100,"") | I71: =IFERROR(D71/$B$71*100,"") | J71: =IFERROR(E71/$B$71*100,"")
A72: Selskabsskat | B72: ='balance_raw_43705660'!$B$49 | C72: ='balance_raw_43705660'!$C$49 | D72: ='balance_raw_43705660'!$D$49 | E72: ='balance_raw_43705660'!$E$49 | G72: =IFERROR(B72/$B$72*100,"") | H72: =IFERROR(C72/$B$72*100,"") | I72: =IFERROR(D72/$B$72*100,"") | J72: =IFERROR(E72/$B$72*100,"")
A73: Gæld til tilknyttede virksomheder vedr. selskabsskat | B73: ='balance_raw_43705660'!$B$50 | C73: ='balance_raw_43705660'!$C$50 | D73: ='balance_raw_43705660'!$D$50 | E73: ='balance_raw_43705660'!$E$50 | G73: =IFERROR(B73/$B$73*100,"") | H73: =IFERROR(C73/$B$73*100,"") | I73: =IFERROR(D73/$B$73*100,"") | J73: =IFERROR(E73/$B$73*100,"")
A74: Anden gæld (kortfristet) | B74: ='balance_raw_43705660'!$B$51 | C74: ='balance_raw_43705660'!$C$51 | D74: ='balance_raw_43705660'!$D$51 | E74: ='balance_raw_43705660'!$E$51 | G74: =IFERROR(B74/$B$74*100,"") | H74: =IFERROR(C74/$B$74*100,"") | I74: =IFERROR(D74/$B$74*100,"") | J74: =IFERROR(E74/$B$74*100,"")
A75: Periodeafgrænsningsposter (passiver) | B75: ='balance_raw_43705660'!$B$52 | C75: ='balance_raw_43705660'!$C$52 | D75: ='balance_raw_43705660'!$D$52 | E75: ='balance_raw_43705660'!$E$52 | G75: =IFERROR(B75/$B$75*100,"") | H75: =IFERROR(C75/$B$75*100,"") | I75: =IFERROR(D75/$B$75*100,"") | J75: =IFERROR(E75/$B$75*100,"")
A76: Kortfristede gældsforpligtelser | B76: ='balance_raw_43705660'!$B$53 | C76: ='balance_raw_43705660'!$C$53 | D76: ='balance_raw_43705660'!$D$53 | E76: ='balance_raw_43705660'!$E$53 | G76: =IFERROR(B76/$B$76*100,"") | H76: =IFERROR(C76/$B$76*100,"") | I76: =IFERROR(D76/$B$76*100,"") | J76: =IFERROR(E76/$B$76*100,"")
A77: Gældsforpligtelser | B77: ='balance_raw_43705660'!$B$54 | C77: ='balance_raw_43705660'!$C$54 | D77: ='balance_raw_43705660'!$D$54 | E77: ='balance_raw_43705660'!$E$54 | G77: =IFERROR(B77/$B$77*100,"") | H77: =IFERROR(C77/$B$77*100,"") | I77: =IFERROR(D77/$B$77*100,"") | J77: =IFERROR(E77/$B$77*100,"")
A78: Passiver | B78: ='balance_raw_43705660'!$B$55 | C78: ='balance_raw_43705660'!$C$55 | D78: ='balance_raw_43705660'!$D$55 | E78: ='balance_raw_43705660'!$E$55 | G78: =IFERROR(B78/$B$78*100,"") | H78: =IFERROR(C78/$B$78*100,"") | I78: =IFERROR(D78/$B$78*100,"") | J78: =IFERROR(E78/$B$78*100,"")
A80: NØGLEOPLYSNINGER | B80: 2022 | C80: 2023 | D80: 2024 | E80: 2025
A81: Gns. antal medarbejdere | B81: ='res_raw_43705660'!$B$19 | C81: ='res_raw_43705660'!$C$19 | D81: ='res_raw_43705660'!$D$19 | E81: ='res_raw_43705660'!$E$19 | G81: =IFERROR(B81/$B$81*100,"") | H81: =IFERROR(C81/$B$81*100,"") | I81: =IFERROR(D81/$B$81*100,"") | J81: =IFERROR(E81/$B$81*100,"")
A82: Investering i materielle anlægsaktiver | B82: ='res_raw_43705660'!$B$20 | C82: ='res_raw_43705660'!$C$20 | D82: ='res_raw_43705660'!$D$20 | E82: ='res_raw_43705660'!$E$20 | G82: =IFERROR(B82/$B$82*100,"") | H82: =IFERROR(C82/$B$82*100,"") | I82: =IFERROR(D82/$B$82*100,"") | J82: =IFERROR(E82/$B$82*100,"")
A84: NØGLETAL | B84: 2022 | C84: 2023 | D84: 2024 | E84: 2025
A85: Afkastningsgrad, % | B85: =IFERROR(($B$13+$B$15+$B$14)/$B$48*100,"") | C85: =IFERROR(($C$13+$C$15+$C$14)/$C$48*100,"") | D85: =IFERROR(($D$13+$D$15+$D$14)/$D$48*100,"") | E85: =IFERROR(($E$13+$E$15+$E$14)/$E$48*100,"")
A86: Overskudsgrad (af bruttofortjeneste), % | B86: =IFERROR(($B$13+$B$15+$B$14)/$B$8*100,"") | C86: =IFERROR(($C$13+$C$15+$C$14)/$C$8*100,"") | D86: =IFERROR(($D$13+$D$15+$D$14)/$D$8*100,"") | E86: =IFERROR(($E$13+$E$15+$E$14)/$E$8*100,"")
A87: Aktivernes omsætningshastighed (af bruttofortjeneste), gange | B87: =IFERROR($B$8/$B$48,"") | C87: =IFERROR($C$8/$C$48,"") | D87: =IFERROR($D$8/$D$48,"") | E87: =IFERROR($E$8/$E$48,"")
A88: Egenkapitalens forrentning, % | B88: =IFERROR($B$18/$B$57*100,"") | C88: =IFERROR($C$18/$C$57*100,"") | D88: =IFERROR($D$18/$D$57*100,"") | E88: =IFERROR($E$18/$E$57*100,"")
A89: Gældsrente, % | B89: =IFERROR($B$16/($B$78-$B$57)*100,"") | C89: =IFERROR($C$16/($C$78-$C$57)*100,"") | D89: =IFERROR($D$16/($D$78-$D$57)*100,"") | E89: =IFERROR($E$16/($E$78-$E$57)*100,"")
A90: Soliditetsgrad, % | B90: =IFERROR($B$57/$B$48*100,"") | C90: =IFERROR($C$57/$C$48*100,"") | D90: =IFERROR($D$57/$D$48*100,"") | E90: =IFERROR($E$57/$E$48*100,"")
A91: Gearing | B91: =IFERROR(($B$78-$B$57)/$B$57,"") | C91: =IFERROR(($C$78-$C$57)/$C$57,"") | D91: =IFERROR(($D$78-$D$57)/$D$57,"") | E91: =IFERROR(($E$78-$E$57)/$E$57,"")
A92: Likviditetsgrad, % | B92: =IFERROR($B$47/$B$76*100,"") | C92: =IFERROR($C$47/$C$76*100,"") | D92: =IFERROR($D$47/$D$76*100,"") | E92: =IFERROR($E$47/$E$76*100,"")
A93: Rentemarginal, % | B93: =IFERROR(B85-B89,"") | C93: =IFERROR(C85-C89,"") | D93: =IFERROR(D85-D89,"") | E93: =IFERROR(E85-E89,"")
A94: Gældsandel, % | B94: =IFERROR(($B$78-$B$57)/$B$48*100,"") | C94: =IFERROR(($C$78-$C$57)/$C$48*100,"") | D94: =IFERROR(($D$78-$D$57)/$D$48*100,"") | E94: =IFERROR(($E$78-$E$57)/$E$48*100,"")
A95: Kapitalbindingsgrad, % | B95: =IFERROR($B$32/($B$57+$B$64)*100,"") | C95: =IFERROR($C$32/($C$57+$C$64)*100,"") | D95: =IFERROR($D$32/($D$57+$D$64)*100,"") | E95: =IFERROR($E$32/($E$57+$E$64)*100,"")
A97: Pengestrømsopgørelse ikke offentliggjort (jf. koncernfritagelse, ÅRL §86, stk. 4)

Sheet res_raw_43705660
A1: THURØ BRYGHUS APS (CVR 43705660) — Resultatopgørelse & nøgleoplysninger (t.kr.) | B1: 2022 | C1: 2023 | D1: 2024 | E1: 2025
A2: Nettoomsætning
A3: Andre driftsindtægter
A4: Vareforbrug
A5: Andre eksterne omkostninger
A6: Bruttoresultat | C6: 316 | D6: 781 | E6: 858
A7: Personaleomkostninger | C7: 328 | D7: 414 | E7: 400
A8: Resultat før afskrivninger
A9: Af- og nedskrivninger | C9: 78 | D9: 111 | E9: 132
A10: Andre driftsomkostninger
A11: Resultat af primær drift | C11: -90 | D11: 256 | E11: 325
A12: Indtægter af kapitalandele, dattervirksomheder
A13: Finansielle indtægter | C13: 0 | D13: 0 | E13: 0
A14: Finansielle omkostninger | C14: 72 | D14: 68 | E14: 72
A15: Finansielle poster, netto | C15: -72 | D15: -68 | E15: -72
A16: Resultat før skat | C16: -162 | D16: 188 | E16: 254
A17: Skat af årets resultat | C17: -29 | D17: 43 | E17: 57
A18: Årets resultat | C18: -133 | D18: 145 | E18: 197
A19: Gns. antal medarbejdere | C19: 2 | D19: 2 | E19: 2
A20: Investering i materielle anlægsaktiver

Sheet balance_raw_43705660
A1: THURØ BRYGHUS APS (CVR 43705660) — Balance (t.kr.) | B1: 2022 | C1: 2023 | D1: 2024 | E1: 2025
A2: Grunde og bygninger
A3: Produktionsanlæg og maskiner
A4: Driftsmateriel og inventar | C4: 916 | D4: 1146 | E4: 1071
A5: Indretning af lejede lokaler
A6: Forudbetaling og anlægsaktiver under opførelse | E6: 295
A7: Materielle anlægsaktiver | C7: 916 | D7: 1146 | E7: 1366
A8: Kapitalandele, dattervirksomheder
A9: Deposita | C9: 10 | D9: 10 | E9: 10
A10: Finansielle anlægsaktiver | C10: 10 | D10: 10 | E10: 10
A11: Anlægsaktiver | C11: 926 | D11: 1156 | E11: 1376
A12: Råvarer og hjælpematerialer | C12: 79 | D12: 142 | E12: 39
A13: Varer under fremstilling
A14: Færdigvarer og handelsvarer | C14: 259 | D14: 260 | E14: 274
A15: Varebeholdninger | C15: 338 | D15: 402 | E15: 314
A16: Tilgodehavender fra salg og tjenesteydelser | C16: 57 | D16: 111 | E16: 97
A17: Tilgodehavender hos tilknyttede virksomheder | E17: 6
A18: Andre tilgodehavender | C18: 25 | D18: 22 | E18: 17
A19: Periodeafgrænsningsposter (aktiver) | C19: 27 | D19: 0
A20: Udskudt skatteaktiv | C20: 29 | D20: 0
A21: Tilgodehavende skat hos tilknyttede virksomheder
A22: Kortfristede skattetilgodehavender | C22: 0 | D22: 0
A23: Tilgodehavender | C23: 138 | D23: 133 | E23: 119
A24: Værdipapirer
A25: Likvide beholdninger | C25: 16 | D25: 3 | E25: 131
A26: Omsætningsaktiver | C26: 492 | D26: 538 | E26: 563
A27: Aktiver | C27: 1418 | D27: 1694 | E27: 1940
A28: Selskabskapital | C28: 40 | D28: 40 | E28: 40
A29: Reserve for nettoopskrivning (indre værdis metode)
A30: Reserve for udviklingsomkostninger
A31: Reserve for sikringstransaktioner
A32: Andre reserver
A33: Overført resultat | C33: -132 | D33: 13 | E33: 210
A34: Egenkapital i alt | B34: 40 | C34: -92 | D34: 53 | E34: 250
A35: Hensættelse til udskudt skat | C35: 0 | D35: 13 | E35: 70
A36: Hensatte forpligtelser | C36: 0 | D36: 13 | E36: 70
A37: Ansvarlig lånekapital (langfristet)
A38: Langfristede lån | C38: 662 | D38: 727 | E38: 851
A39: Leasingforpligtelser (langfristet)
A40: Anden gæld (langfristet)
A41: Langfristede gældsforpligtelser | C41: 662 | D41: 727 | E41: 851
A42: Ansvarlig lånekapital (kortfristet)
A43: Kortfristet del af langfristede gældsforpligtelser | C43: 107 | D43: 146 | E43: 176
A44: Kreditinstitutter | C44: 127 | D44: 65 | E44: 0
A45: Leasingforpligtelser (kortfristet)
A46: Leverandører af varer og tjenesteydelser | C46: 127 | D46: 146 | E46: 140
A47: Gæld til tilknyttede virksomheder
A48: Gæld til selskabsdeltagere og ledelse | C48: 471 | D48: 510 | E48: 208
A49: Selskabsskat
A50: Gæld til tilknyttede virksomheder vedr. selskabsskat
A51: Anden gæld (kortfristet) | C51: 16 | D51: 34 | E51: 244
A52: Periodeafgrænsningsposter (passiver)
A53: Kortfristede gældsforpligtelser | C53: 848 | D53: 901 | E53: 768
A54: Gældsforpligtelser | C54: 1510 | D54: 1628 | E54: 1620
A55: Passiver | C55: 1418 | D55: 1694 | E55: 1940

Sheet Simpel_arts
A1: THURØ BRYGHUS APS (CVR 43705660) — Regnskabs- og nøgletal (CVR: 43705660) — artsopdelt
A3: Beløb i 1.000 kr. | B3: 2025 | C3: 2024 | D3: 2023 | F3: Note / XBRL-felt
A4: Uddrag af resultatopgørelse
A5: Nettoomsætning | B5: ='res_raw_43705660'!$E$2 | C5: ='res_raw_43705660'!$D$2 | D5: ='res_raw_43705660'!$C$2 | F5: fsa:Revenue
A6: Andre driftsindtægter | B6: ='res_raw_43705660'!$E$3 | C6: ='res_raw_43705660'!$D$3 | D6: ='res_raw_43705660'!$C$3 | F6: fsa:OtherOperatingIncome. Indtægter fra sekundære aktiviteter (huslejeindtægter, avance ved salg af anlæg mv.).
A7: Vareforbrug | B7: =-'res_raw_43705660'!$E$4 | C7: =-'res_raw_43705660'!$D$4 | D7: =-'res_raw_43705660'!$C$4 | F7: fsa:CostOfSales (vises negativt for korrekt SUM-formel).
A8: Andre eksterne omk. mv. | B8: =-'res_raw_43705660'!$E$5 | C8: =-'res_raw_43705660'!$D$5 | D8: =-'res_raw_43705660'!$C$5 | F8: fsa:OtherExternalExpenses (vises negativt). Husleje, energi, kontorhold mv.
A9: Bruttofortjeneste | B9: =IF(ABS((SUM(B5:B8))-'res_raw_43705660'!$E$6)<=2,SUM(B5:B8),'res_raw_43705660'!$E$6) | C9: =IF(ABS((SUM(C5:C8))-'res_raw_43705660'!$D$6)<=2,SUM(C5:C8),'res_raw_43705660'!$D$6) | D9: =IF(ABS((SUM(D5:D8))-'res_raw_43705660'!$C$6)<=2,SUM(D5:D8),'res_raw_43705660'!$C$6) | F9: Beregnet: Nettoomsætning + Andre driftsindt. − Vareforbrug − Andre ext. omk. Er komponenterne ikke indberettet, vises rapporteret bruttoresultat (fsa:GrossResult) direkte.
A10: Personaleomkostninger | B10: =-'res_raw_43705660'!$E$7 | C10: =-'res_raw_43705660'!$D$7 | D10: =-'res_raw_43705660'!$C$7 | F10: fsa:EmployeeBenefitsExpense (vises negativt). Lønninger, pension, sociale ydelser.
A11: Af- og nedskrivninger | B11: =-'res_raw_43705660'!$E$9 | C11: =-'res_raw_43705660'!$D$9 | D11: =-'res_raw_43705660'!$C$9 | F11: fsa:Depreciation (vises negativt). Af- og nedskrivninger på materielle og immaterielle anlægsaktiver.
A12: Andre driftsomkostninger | B12: =-'res_raw_43705660'!$E$10 | C12: =-'res_raw_43705660'!$D$10 | D12: =-'res_raw_43705660'!$C$10 | F12: fsa:OtherOperatingExpenses (vises negativt). Typisk 0 eller meget lille post.
A13: Resultat af primær drift | B13: =IF(ABS((SUM(B9:B12))-'res_raw_43705660'!$E$11)<=2,SUM(B9:B12),'res_raw_43705660'!$E$11) | C13: =IF(ABS((SUM(C9:C12))-'res_raw_43705660'!$D$11)<=2,SUM(C9:C12),'res_raw_43705660'!$D$11) | D13: =IF(ABS((SUM(D9:D12))-'res_raw_43705660'!$C$11)<=2,SUM(D9:D12),'res_raw_43705660'!$C$11) | F13: Beregnet: Bruttofortjeneste − Personaleomk. − Af- og nedskrivninger − Andre driftsomk. EBIT.
A14: Finansielle indtægter mv. | B14: =N('res_raw_43705660'!$E$12)+N('res_raw_43705660'!$E$13) | C14: =N('res_raw_43705660'!$D$12)+N('res_raw_43705660'!$D$13) | D14: =N('res_raw_43705660'!$C$12)+N('res_raw_43705660'!$C$13) | F14: fsa:IncomeFromSubsidiaries + fsa:OtherFinanceIncome.
A15: Finansielle omkostninger mv. | B15: =-'res_raw_43705660'!$E$14 | C15: =-'res_raw_43705660'!$D$14 | D15: =-'res_raw_43705660'!$C$14 | F15: fsa:OtherFinanceExpenses (vises negativt). Renteomkostninger, kurstab mv.
A16: Resultat før skat | B16: =IF(ABS((SUM(B13:B15))-'res_raw_43705660'!$E$16)<=2,SUM(B13:B15),'res_raw_43705660'!$E$16) | C16: =IF(ABS((SUM(C13:C15))-'res_raw_43705660'!$D$16)<=2,SUM(C13:C15),'res_raw_43705660'!$D$16) | D16: =IF(ABS((SUM(D13:D15))-'res_raw_43705660'!$C$16)<=2,SUM(D13:D15),'res_raw_43705660'!$C$16) | F16: Beregnet: EBIT + Fin. indtægter + Fin. omk. EBT.
A18: Uddrag af balance
A19: Anlægsaktiver | B19: ='balance_raw_43705660'!$E$11 | C19: ='balance_raw_43705660'!$D$11 | D19: ='balance_raw_43705660'!$C$11 | F19: fsa:NoncurrentAssets. Materielle, immaterielle og finansielle anlægsaktiver.
A20: Omsætningsaktiver | B20: ='balance_raw_43705660'!$E$26 | C20: ='balance_raw_43705660'!$D$26 | D20: ='balance_raw_43705660'!$C$26 | F20: fsa:CurrentAssets. Varebeholdninger, tilgodehavender, likvider.
A21: Aktiver i alt | B21: =SUM(B19:B20) | C21: =SUM(C19:C20) | D21: =SUM(D19:D20) | F21: Beregnet: Anlægsaktiver + Omsætningsaktiver. Bør matche fsa:Assets.
A23: Egenkapital | B23: ='balance_raw_43705660'!$E$34 | C23: ='balance_raw_43705660'!$D$34 | D23: ='balance_raw_43705660'!$C$34 | F23: fsa:Equity. Selskabskapital, overført resultat, reserver.
A24: Forpligtelser | B24: ='balance_raw_43705660'!$E$55-'balance_raw_43705660'!$E$34 | C24: ='balance_raw_43705660'!$D$55-'balance_raw_43705660'!$D$34 | D24: ='balance_raw_43705660'!$C$55-'balance_raw_43705660'!$C$34 | F24: Beregnet: Passiver (fsa:LiabilitiesAndEquity) − Egenkapital. Hensættelser + kort- og langfristet gæld.
A25: Passiver i alt | B25: =SUM(B23:B24) | C25: =SUM(C23:C24) | D25: =SUM(D23:D24) | F25: Beregnet: Egenkapital + Forpligtelser. Bør matche Aktiver i alt.
A27: Udvalgte balanceposter
A28: Varebeholdninger | B28: ='balance_raw_43705660'!$E$15 | C28: ='balance_raw_43705660'!$D$15 | D28: ='balance_raw_43705660'!$C$15 | F28: fsa:Inventories (eller fsa:ManufacturedGoodsAndGoodsForResale hvis total mangler).
A29: Tilgodehavender fra salg | B29: ='balance_raw_43705660'!$E$16 | C29: ='balance_raw_43705660'!$D$16 | D29: ='balance_raw_43705660'!$C$16 | F29: fsa:ShorttermTradeReceivables. Kortfristede tilgodehavender fra kunder.
A30: Kortfristede gældsforpligtelser | B30: ='balance_raw_43705660'!$E$53 | C30: ='balance_raw_43705660'!$D$53 | D30: ='balance_raw_43705660'!$C$53 | F30: fsa:ShorttermLiabilitiesOtherThanProvisions. Gæld der forfalder inden for 1 år.
A32: Rentabilitet
A33: Afkastningsgrad, % | B33: =IFERROR((B13+B14)/B21*100,"") | C33: =IFERROR((C13+C14)/C21*100,"") | D33: =IFERROR((D13+D14)/D21*100,"")
A34: Overskudsgrad (af bruttofortjeneste), % | B34: =IFERROR((B13+B14)/B9*100,"") | C34: =IFERROR((C13+C14)/C9*100,"") | D34: =IFERROR((D13+D14)/D9*100,"")
A35: Aktivernes omsætningshastighed (af bruttofortjeneste), gange | B35: =IFERROR(B9/B21,"") | C35: =IFERROR(C9/C21,"") | D35: =IFERROR(D9/D21,"")
A36: Gældsrente, % | B36: =IFERROR(-B15*100/B24,"") | C36: =IFERROR(-C15*100/C24,"") | D36: =IFERROR(-D15*100/D24,"")
A37: Egenkapitalens forrentning, % | B37: =IFERROR(B16/B23*100,"") | C37: =IFERROR(C16/C23*100,"") | D37: =IFERROR(D16/D23*100,"")
A38: Gearing, gange | B38: =IFERROR(B24/B23,"") | C38: =IFERROR(C24/C23,"") | D38: =IFERROR(D24/D23,"")
A40: Indekstal for indtjeningsevne (2023=100)
A41: Bruttofortjeneste | B41: =IFERROR(B9/$D9*100,"") | C41: =IFERROR(C9/$D9*100,"") | D41: =IFERROR(D9/$D9*100,"")
A42: Vareforbrug | B42: =IFERROR(B7/$D7*100,"") | C42: =IFERROR(C7/$D7*100,"") | D42: =IFERROR(D7/$D7*100,"")
A43: Andre eksterne omk. | B43: =IFERROR(B8/$D8*100,"") | C43: =IFERROR(C8/$D8*100,"") | D43: =IFERROR(D8/$D8*100,"")
A44: Personaleomkostninger | B44: =IFERROR(B10/$D10*100,"") | C44: =IFERROR(C10/$D10*100,"") | D44: =IFERROR(D10/$D10*100,"")
A45: Af- og nedskrivninger | B45: =IFERROR(B11/$D11*100,"") | C45: =IFERROR(C11/$D11*100,"") | D45: =IFERROR(D11/$D11*100,"")
A47: Indekstal for kapitaltilpasningsevne (2023=100)
A48: Bruttofortjeneste | B48: =IFERROR(B9*100/$D9,"") | C48: =IFERROR(C9*100/$D9,"") | D48: =IFERROR(D9*100/$D9,"")
A49: Anlægsaktiver | B49: =IFERROR(B19*100/$D19,"") | C49: =IFERROR(C19*100/$D19,"") | D49: =IFERROR(D19*100/$D19,"")
A50: Varebeholdninger | B50: =IFERROR(B28*100/$D28,"") | C50: =IFERROR(C28*100/$D28,"") | D50: =IFERROR(D28*100/$D28,"")
A51: Tilgodehavender fra salg | B51: =IFERROR(B29*100/$D29,"") | C51: =IFERROR(C29*100/$D29,"") | D51: =IFERROR(D29*100/$D29,"")
A53: Soliditet og likviditet
A54: Soliditetsgrad, % | B54: =IFERROR(B23*100/B21,"") | C54: =IFERROR(C23*100/C21,"") | D54: =IFERROR(D23*100/D21,"")
A55: Gældsandel, % | B55: =IFERROR(B24*100/B21,"") | C55: =IFERROR(C24*100/C21,"") | D55: =IFERROR(D24*100/D21,"")
A56: Likviditetsgrad, % | B56: =IFERROR(B20*100/B30,"") | C56: =IFERROR(C20*100/C30,"") | D56: =IFERROR(D20*100/D30,"")
A58: Kilde: Bearbejdet uddrag af årsrapporter for 2023-2025. Alle dataceller er live formler der peger på res_raw / balance_raw.
A60: Krydstjek mod rådata (tolerance: 1 t.kr.)
A61: Aktiver i alt = fsa:Assets | B61: =IF('balance_raw_43705660'!$E$27="","—",IF(ABS(B21-'balance_raw_43705660'!$E$27)<=1,"✓ OK","❌ "&TEXT(B21-'balance_raw_43705660'!$E$27,"+#,##0;-#,##0")&" t.kr.")) | C61: =IF('balance_raw_43705660'!$D$27="","—",IF(ABS(C21-'balance_raw_43705660'!$D$27)<=1,"✓ OK","❌ "&TEXT(C21-'balance_raw_43705660'!$D$27,"+#,##0;-#,##0")&" t.kr.")) | D61: =IF('balance_raw_43705660'!$C$27="","—",IF(ABS(D21-'balance_raw_43705660'!$C$27)<=1,"✓ OK","❌ "&TEXT(D21-'balance_raw_43705660'!$C$27,"+#,##0;-#,##0")&" t.kr.")) | F61: Verificerer at sum(Anlæg+Omsætning) matcher Assets-totalen.
A62: Passiver i alt = fsa:LiabilitiesAndEquity | B62: =IF('balance_raw_43705660'!$E$55="","—",IF(ABS(B25-'balance_raw_43705660'!$E$55)<=1,"✓ OK","❌ "&TEXT(B25-'balance_raw_43705660'!$E$55,"+#,##0;-#,##0")&" t.kr.")) | C62: =IF('balance_raw_43705660'!$D$55="","—",IF(ABS(C25-'balance_raw_43705660'!$D$55)<=1,"✓ OK","❌ "&TEXT(C25-'balance_raw_43705660'!$D$55,"+#,##0;-#,##0")&" t.kr.")) | D62: =IF('balance_raw_43705660'!$C$55="","—",IF(ABS(D25-'balance_raw_43705660'!$C$55)<=1,"✓ OK","❌ "&TEXT(D25-'balance_raw_43705660'!$C$55,"+#,##0;-#,##0")&" t.kr.")) | F62: Verificerer at sum(EK+Forpligtelser) matcher Passiver-totalen.
A63: Aktiver i alt = Passiver i alt | B63: =IF(ABS(B21-B25)<=1,"✓ OK","❌ "&TEXT(B21-B25,"+#,##0;-#,##0")&" t.kr.") | C63: =IF(ABS(C21-C25)<=1,"✓ OK","❌ "&TEXT(C21-C25,"+#,##0;-#,##0")&" t.kr.") | D63: =IF(ABS(D21-D25)<=1,"✓ OK","❌ "&TEXT(D21-D25,"+#,##0;-#,##0")&" t.kr.") | F63: Balance-identitet på arket selv. Skal altid være 0 differance.
A64: Bruttoresultat (beregnet) = fsa:GrossResult | B64: =IF('res_raw_43705660'!$E$6="","—",IF(ABS(B9-'res_raw_43705660'!$E$6)<=1,"✓ OK","❌ "&TEXT(B9-'res_raw_43705660'!$E$6,"+#,##0;-#,##0")&" t.kr.")) | C64: =IF('res_raw_43705660'!$D$6="","—",IF(ABS(C9-'res_raw_43705660'!$D$6)<=1,"✓ OK","❌ "&TEXT(C9-'res_raw_43705660'!$D$6,"+#,##0;-#,##0")&" t.kr.")) | D64: =IF('res_raw_43705660'!$C$6="","—",IF(ABS(D9-'res_raw_43705660'!$C$6)<=1,"✓ OK","❌ "&TEXT(D9-'res_raw_43705660'!$C$6,"+#,##0;-#,##0")&" t.kr.")) | F64: Hvis Nettoomsætning eller omkostninger mangler, vil sumberegnet bruttoresultat afvige.
A65: EBIT (beregnet) = fsa:ProfitLossFromOrdinaryOperatingActivities | B65: =IF('res_raw_43705660'!$E$11="","—",IF(ABS(B13-'res_raw_43705660'!$E$11)<=1,"✓ OK","❌ "&TEXT(B13-'res_raw_43705660'!$E$11,"+#,##0;-#,##0")&" t.kr.")) | C65: =IF('res_raw_43705660'!$D$11="","—",IF(ABS(C13-'res_raw_43705660'!$D$11)<=1,"✓ OK","❌ "&TEXT(C13-'res_raw_43705660'!$D$11,"+#,##0;-#,##0")&" t.kr.")) | D65: =IF('res_raw_43705660'!$C$11="","—",IF(ABS(D13-'res_raw_43705660'!$C$11)<=1,"✓ OK","❌ "&TEXT(D13-'res_raw_43705660'!$C$11,"+#,##0;-#,##0")&" t.kr.")) | F65: Verificerer at sumberegnet EBIT matcher det rapporterede.
A66: EBT (beregnet) = fsa:ProfitLossFromOrdinaryActivitiesBeforeTax | B66: =IF('res_raw_43705660'!$E$16="","—",IF(ABS(B16-'res_raw_43705660'!$E$16)<=1,"✓ OK","❌ "&TEXT(B16-'res_raw_43705660'!$E$16,"+#,##0;-#,##0")&" t.kr.")) | C66: =IF('res_raw_43705660'!$D$16="","—",IF(ABS(C16-'res_raw_43705660'!$D$16)<=1,"✓ OK","❌ "&TEXT(C16-'res_raw_43705660'!$D$16,"+#,##0;-#,##0")&" t.kr.")) | D66: =IF('res_raw_43705660'!$C$16="","—",IF(ABS(D16-'res_raw_43705660'!$C$16)<=1,"✓ OK","❌ "&TEXT(D16-'res_raw_43705660'!$C$16,"+#,##0;-#,##0")&" t.kr.")) | F66: Verificerer at sumberegnet resultat før skat matcher det rapporterede.

Sheet Noter_info
A1: THURØ BRYGHUS APS (CVR 43705660) — Ukendte XBRL-felter — disse er noter og ikke en del af hoved-regnskabet
A2: Kategori | B2: Dansk navn | C2: XBRL feltnavn | D2: 2022 t.kr. | E2: 2023 t.kr. | F2: 2024 t.kr. | G2: 2025 t.kr. | H2: Forklaring
A3: Øvrige (ukendt) | B3: fsa:IncreaseDecreaseOfEquityThroughChangesInAccountingPolicies | C3: fsa:IncreaseDecreaseOfEquityThroughChangesInAccountingPolicies | F3: 32 | H3: Ingen forklaring tilgængelig.
