Workbook

Sheet Overblik_12425694
A1: Thise Mejeri A.M.B.A. (CVR 12425694) — Regnskabsanalyse – Resultatopgørelse & Balance (t.kr.) · Klasse C-stor · Revision
H2: Indekstal (2021=100)
A3: Resultatopgørelse t.kr. | B3: 2021 | C3: 2022 | D3: 2023 | E3: 2024 | F3: 2025 | H3: 2021 | I3: 2022 | J3: 2023 | K3: 2024 | L3: 2025
A4: Nettoomsætning | B4: ='res_raw_12425694'!$B$2 | C4: ='res_raw_12425694'!$C$2 | D4: ='res_raw_12425694'!$D$2 | E4: ='res_raw_12425694'!$E$2 | F4: ='res_raw_12425694'!$F$2 | H4: =IFERROR(B4/$B$4*100,"") | I4: =IFERROR(C4/$B$4*100,"") | J4: =IFERROR(D4/$B$4*100,"") | K4: =IFERROR(E4/$B$4*100,"") | L4: =IFERROR(F4/$B$4*100,"")
A5: Produktionsomkostninger | B5: ='res_raw_12425694'!$B$3 | C5: ='res_raw_12425694'!$C$3 | D5: ='res_raw_12425694'!$D$3 | E5: ='res_raw_12425694'!$E$3 | F5: ='res_raw_12425694'!$F$3 | H5: =IFERROR(B5/$B$5*100,"") | I5: =IFERROR(C5/$B$5*100,"") | J5: =IFERROR(D5/$B$5*100,"") | K5: =IFERROR(E5/$B$5*100,"") | L5: =IFERROR(F5/$B$5*100,"")
A6: Bruttoresultat | B6: ='res_raw_12425694'!$B$4 | C6: ='res_raw_12425694'!$C$4 | D6: ='res_raw_12425694'!$D$4 | E6: ='res_raw_12425694'!$E$4 | F6: ='res_raw_12425694'!$F$4 | H6: =IFERROR(B6/$B$6*100,"") | I6: =IFERROR(C6/$B$6*100,"") | J6: =IFERROR(D6/$B$6*100,"") | K6: =IFERROR(E6/$B$6*100,"") | L6: =IFERROR(F6/$B$6*100,"")
A7: Udviklingsomkostninger | B7: ='res_raw_12425694'!$B$5 | C7: ='res_raw_12425694'!$C$5 | D7: ='res_raw_12425694'!$D$5 | E7: ='res_raw_12425694'!$E$5 | F7: ='res_raw_12425694'!$F$5 | H7: =IFERROR(B7/$B$7*100,"") | I7: =IFERROR(C7/$B$7*100,"") | J7: =IFERROR(D7/$B$7*100,"") | K7: =IFERROR(E7/$B$7*100,"") | L7: =IFERROR(F7/$B$7*100,"")
A8: Salgs- og distributionsomkostninger | B8: ='res_raw_12425694'!$B$6 | C8: ='res_raw_12425694'!$C$6 | D8: ='res_raw_12425694'!$D$6 | E8: ='res_raw_12425694'!$E$6 | F8: ='res_raw_12425694'!$F$6 | H8: =IFERROR(B8/$B$8*100,"") | I8: =IFERROR(C8/$B$8*100,"") | J8: =IFERROR(D8/$B$8*100,"") | K8: =IFERROR(E8/$B$8*100,"") | L8: =IFERROR(F8/$B$8*100,"")
A9: Administrationsomkostninger | B9: ='res_raw_12425694'!$B$7 | C9: ='res_raw_12425694'!$C$7 | D9: ='res_raw_12425694'!$D$7 | E9: ='res_raw_12425694'!$E$7 | F9: ='res_raw_12425694'!$F$7 | H9: =IFERROR(B9/$B$9*100,"") | I9: =IFERROR(C9/$B$9*100,"") | J9: =IFERROR(D9/$B$9*100,"") | K9: =IFERROR(E9/$B$9*100,"") | L9: =IFERROR(F9/$B$9*100,"")
A10: Andre driftsindtægter | B10: ='res_raw_12425694'!$B$8 | C10: ='res_raw_12425694'!$C$8 | D10: ='res_raw_12425694'!$D$8 | E10: ='res_raw_12425694'!$E$8 | F10: ='res_raw_12425694'!$F$8 | H10: =IFERROR(B10/$B$10*100,"") | I10: =IFERROR(C10/$B$10*100,"") | J10: =IFERROR(D10/$B$10*100,"") | K10: =IFERROR(E10/$B$10*100,"") | L10: =IFERROR(F10/$B$10*100,"")
A11: Andre driftsomkostninger | B11: ='res_raw_12425694'!$B$9 | C11: ='res_raw_12425694'!$C$9 | D11: ='res_raw_12425694'!$D$9 | E11: ='res_raw_12425694'!$E$9 | F11: ='res_raw_12425694'!$F$9 | H11: =IFERROR(B11/$B$11*100,"") | I11: =IFERROR(C11/$B$11*100,"") | J11: =IFERROR(D11/$B$11*100,"") | K11: =IFERROR(E11/$B$11*100,"") | L11: =IFERROR(F11/$B$11*100,"")
A12: Resultat af primær drift | B12: ='res_raw_12425694'!$B$10 | C12: ='res_raw_12425694'!$C$10 | D12: ='res_raw_12425694'!$D$10 | E12: ='res_raw_12425694'!$E$10 | F12: ='res_raw_12425694'!$F$10 | H12: =IFERROR(B12/$B$12*100,"") | I12: =IFERROR(C12/$B$12*100,"") | J12: =IFERROR(D12/$B$12*100,"") | K12: =IFERROR(E12/$B$12*100,"") | L12: =IFERROR(F12/$B$12*100,"")
A13: Indtægter af kapitalandele, dattervirksomheder | B13: ='res_raw_12425694'!$B$11 | C13: ='res_raw_12425694'!$C$11 | D13: ='res_raw_12425694'!$D$11 | E13: ='res_raw_12425694'!$E$11 | F13: ='res_raw_12425694'!$F$11 | H13: =IFERROR(B13/$B$13*100,"") | I13: =IFERROR(C13/$B$13*100,"") | J13: =IFERROR(D13/$B$13*100,"") | K13: =IFERROR(E13/$B$13*100,"") | L13: =IFERROR(F13/$B$13*100,"")
A14: Finansielle indtægter | B14: ='res_raw_12425694'!$B$12 | C14: ='res_raw_12425694'!$C$12 | D14: ='res_raw_12425694'!$D$12 | E14: ='res_raw_12425694'!$E$12 | F14: ='res_raw_12425694'!$F$12 | H14: =IFERROR(B14/$B$14*100,"") | I14: =IFERROR(C14/$B$14*100,"") | J14: =IFERROR(D14/$B$14*100,"") | K14: =IFERROR(E14/$B$14*100,"") | L14: =IFERROR(F14/$B$14*100,"")
A15: Finansielle omkostninger | B15: ='res_raw_12425694'!$B$13 | C15: ='res_raw_12425694'!$C$13 | D15: ='res_raw_12425694'!$D$13 | E15: ='res_raw_12425694'!$E$13 | F15: ='res_raw_12425694'!$F$13 | H15: =IFERROR(B15/$B$15*100,"") | I15: =IFERROR(C15/$B$15*100,"") | J15: =IFERROR(D15/$B$15*100,"") | K15: =IFERROR(E15/$B$15*100,"") | L15: =IFERROR(F15/$B$15*100,"")
A16: Finansielle poster, netto | B16: ='res_raw_12425694'!$B$14 | C16: ='res_raw_12425694'!$C$14 | D16: ='res_raw_12425694'!$D$14 | E16: ='res_raw_12425694'!$E$14 | F16: ='res_raw_12425694'!$F$14 | H16: =IFERROR(B16/$B$16*100,"") | I16: =IFERROR(C16/$B$16*100,"") | J16: =IFERROR(D16/$B$16*100,"") | K16: =IFERROR(E16/$B$16*100,"") | L16: =IFERROR(F16/$B$16*100,"")
A17: Resultat før skat | B17: ='res_raw_12425694'!$B$15 | C17: ='res_raw_12425694'!$C$15 | D17: ='res_raw_12425694'!$D$15 | E17: ='res_raw_12425694'!$E$15 | F17: ='res_raw_12425694'!$F$15 | H17: =IFERROR(B17/$B$17*100,"") | I17: =IFERROR(C17/$B$17*100,"") | J17: =IFERROR(D17/$B$17*100,"") | K17: =IFERROR(E17/$B$17*100,"") | L17: =IFERROR(F17/$B$17*100,"")
A18: Skat af årets resultat | B18: ='res_raw_12425694'!$B$16 | C18: ='res_raw_12425694'!$C$16 | D18: ='res_raw_12425694'!$D$16 | E18: ='res_raw_12425694'!$E$16 | F18: ='res_raw_12425694'!$F$16 | H18: =IFERROR(B18/$B$18*100,"") | I18: =IFERROR(C18/$B$18*100,"") | J18: =IFERROR(D18/$B$18*100,"") | K18: =IFERROR(E18/$B$18*100,"") | L18: =IFERROR(F18/$B$18*100,"")
A19: Årets resultat | B19: ='res_raw_12425694'!$B$17 | C19: ='res_raw_12425694'!$C$17 | D19: ='res_raw_12425694'!$D$17 | E19: ='res_raw_12425694'!$E$17 | F19: ='res_raw_12425694'!$F$17 | H19: =IFERROR(B19/$B$19*100,"") | I19: =IFERROR(C19/$B$19*100,"") | J19: =IFERROR(D19/$B$19*100,"") | K19: =IFERROR(E19/$B$19*100,"") | L19: =IFERROR(F19/$B$19*100,"")
A21: AKTIVER t.kr. | B21: 2021 | C21: 2022 | D21: 2023 | E21: 2024 | F21: 2025 | H21: 2021 | I21: 2022 | J21: 2023 | K21: 2024 | L21: 2025
A22: Grunde og bygninger | B22: ='balance_raw_12425694'!$B$2 | C22: ='balance_raw_12425694'!$C$2 | D22: ='balance_raw_12425694'!$D$2 | E22: ='balance_raw_12425694'!$E$2 | F22: ='balance_raw_12425694'!$F$2 | H22: =IFERROR(B22/$B$22*100,"") | I22: =IFERROR(C22/$B$22*100,"") | J22: =IFERROR(D22/$B$22*100,"") | K22: =IFERROR(E22/$B$22*100,"") | L22: =IFERROR(F22/$B$22*100,"")
A23: Produktionsanlæg og maskiner | B23: ='balance_raw_12425694'!$B$3 | C23: ='balance_raw_12425694'!$C$3 | D23: ='balance_raw_12425694'!$D$3 | E23: ='balance_raw_12425694'!$E$3 | F23: ='balance_raw_12425694'!$F$3 | H23: =IFERROR(B23/$B$23*100,"") | I23: =IFERROR(C23/$B$23*100,"") | J23: =IFERROR(D23/$B$23*100,"") | K23: =IFERROR(E23/$B$23*100,"") | L23: =IFERROR(F23/$B$23*100,"")
A24: Driftsmateriel og inventar | B24: ='balance_raw_12425694'!$B$4 | C24: ='balance_raw_12425694'!$C$4 | D24: ='balance_raw_12425694'!$D$4 | E24: ='balance_raw_12425694'!$E$4 | F24: ='balance_raw_12425694'!$F$4 | H24: =IFERROR(B24/$B$24*100,"") | I24: =IFERROR(C24/$B$24*100,"") | J24: =IFERROR(D24/$B$24*100,"") | K24: =IFERROR(E24/$B$24*100,"") | L24: =IFERROR(F24/$B$24*100,"")
A25: Indretning af lejede lokaler | B25: ='balance_raw_12425694'!$B$5 | C25: ='balance_raw_12425694'!$C$5 | D25: ='balance_raw_12425694'!$D$5 | E25: ='balance_raw_12425694'!$E$5 | F25: ='balance_raw_12425694'!$F$5 | H25: =IFERROR(B25/$B$25*100,"") | I25: =IFERROR(C25/$B$25*100,"") | J25: =IFERROR(D25/$B$25*100,"") | K25: =IFERROR(E25/$B$25*100,"") | L25: =IFERROR(F25/$B$25*100,"")
A26: Forudbetaling og anlægsaktiver under opførelse | B26: ='balance_raw_12425694'!$B$6 | C26: ='balance_raw_12425694'!$C$6 | D26: ='balance_raw_12425694'!$D$6 | E26: ='balance_raw_12425694'!$E$6 | F26: ='balance_raw_12425694'!$F$6 | H26: =IFERROR(B26/$B$26*100,"") | I26: =IFERROR(C26/$B$26*100,"") | J26: =IFERROR(D26/$B$26*100,"") | K26: =IFERROR(E26/$B$26*100,"") | L26: =IFERROR(F26/$B$26*100,"")
A27: Materielle anlægsaktiver | B27: ='balance_raw_12425694'!$B$7 | C27: ='balance_raw_12425694'!$C$7 | D27: ='balance_raw_12425694'!$D$7 | E27: ='balance_raw_12425694'!$E$7 | F27: ='balance_raw_12425694'!$F$7 | H27: =IFERROR(B27/$B$27*100,"") | I27: =IFERROR(C27/$B$27*100,"") | J27: =IFERROR(D27/$B$27*100,"") | K27: =IFERROR(E27/$B$27*100,"") | L27: =IFERROR(F27/$B$27*100,"")
A28: Kapitalandele, dattervirksomheder | B28: ='balance_raw_12425694'!$B$8 | C28: ='balance_raw_12425694'!$C$8 | D28: ='balance_raw_12425694'!$D$8 | E28: ='balance_raw_12425694'!$E$8 | F28: ='balance_raw_12425694'!$F$8 | H28: =IFERROR(B28/$B$28*100,"") | I28: =IFERROR(C28/$B$28*100,"") | J28: =IFERROR(D28/$B$28*100,"") | K28: =IFERROR(E28/$B$28*100,"") | L28: =IFERROR(F28/$B$28*100,"")
A29: Deposita | B29: ='balance_raw_12425694'!$B$9 | C29: ='balance_raw_12425694'!$C$9 | D29: ='balance_raw_12425694'!$D$9 | E29: ='balance_raw_12425694'!$E$9 | F29: ='balance_raw_12425694'!$F$9 | H29: =IFERROR(B29/$B$29*100,"") | I29: =IFERROR(C29/$B$29*100,"") | J29: =IFERROR(D29/$B$29*100,"") | K29: =IFERROR(E29/$B$29*100,"") | L29: =IFERROR(F29/$B$29*100,"")
A30: Finansielle anlægsaktiver | B30: ='balance_raw_12425694'!$B$10 | C30: ='balance_raw_12425694'!$C$10 | D30: ='balance_raw_12425694'!$D$10 | E30: ='balance_raw_12425694'!$E$10 | F30: ='balance_raw_12425694'!$F$10 | H30: =IFERROR(B30/$B$30*100,"") | I30: =IFERROR(C30/$B$30*100,"") | J30: =IFERROR(D30/$B$30*100,"") | K30: =IFERROR(E30/$B$30*100,"") | L30: =IFERROR(F30/$B$30*100,"")
A31: Anlægsaktiver | B31: ='balance_raw_12425694'!$B$11 | C31: ='balance_raw_12425694'!$C$11 | D31: ='balance_raw_12425694'!$D$11 | E31: ='balance_raw_12425694'!$E$11 | F31: ='balance_raw_12425694'!$F$11 | H31: =IFERROR(B31/$B$31*100,"") | I31: =IFERROR(C31/$B$31*100,"") | J31: =IFERROR(D31/$B$31*100,"") | K31: =IFERROR(E31/$B$31*100,"") | L31: =IFERROR(F31/$B$31*100,"")
A32: Råvarer og hjælpematerialer | B32: ='balance_raw_12425694'!$B$12 | C32: ='balance_raw_12425694'!$C$12 | D32: ='balance_raw_12425694'!$D$12 | E32: ='balance_raw_12425694'!$E$12 | F32: ='balance_raw_12425694'!$F$12 | H32: =IFERROR(B32/$B$32*100,"") | I32: =IFERROR(C32/$B$32*100,"") | J32: =IFERROR(D32/$B$32*100,"") | K32: =IFERROR(E32/$B$32*100,"") | L32: =IFERROR(F32/$B$32*100,"")
A33: Varer under fremstilling | B33: ='balance_raw_12425694'!$B$13 | C33: ='balance_raw_12425694'!$C$13 | D33: ='balance_raw_12425694'!$D$13 | E33: ='balance_raw_12425694'!$E$13 | F33: ='balance_raw_12425694'!$F$13 | H33: =IFERROR(B33/$B$33*100,"") | I33: =IFERROR(C33/$B$33*100,"") | J33: =IFERROR(D33/$B$33*100,"") | K33: =IFERROR(E33/$B$33*100,"") | L33: =IFERROR(F33/$B$33*100,"")
A34: Færdigvarer og handelsvarer | B34: ='balance_raw_12425694'!$B$14 | C34: ='balance_raw_12425694'!$C$14 | D34: ='balance_raw_12425694'!$D$14 | E34: ='balance_raw_12425694'!$E$14 | F34: ='balance_raw_12425694'!$F$14 | H34: =IFERROR(B34/$B$34*100,"") | I34: =IFERROR(C34/$B$34*100,"") | J34: =IFERROR(D34/$B$34*100,"") | K34: =IFERROR(E34/$B$34*100,"") | L34: =IFERROR(F34/$B$34*100,"")
A35: Varebeholdninger | B35: ='balance_raw_12425694'!$B$15 | C35: ='balance_raw_12425694'!$C$15 | D35: ='balance_raw_12425694'!$D$15 | E35: ='balance_raw_12425694'!$E$15 | F35: ='balance_raw_12425694'!$F$15 | H35: =IFERROR(B35/$B$35*100,"") | I35: =IFERROR(C35/$B$35*100,"") | J35: =IFERROR(D35/$B$35*100,"") | K35: =IFERROR(E35/$B$35*100,"") | L35: =IFERROR(F35/$B$35*100,"")
A36: Tilgodehavender fra salg og tjenesteydelser | B36: ='balance_raw_12425694'!$B$16 | C36: ='balance_raw_12425694'!$C$16 | D36: ='balance_raw_12425694'!$D$16 | E36: ='balance_raw_12425694'!$E$16 | F36: ='balance_raw_12425694'!$F$16 | H36: =IFERROR(B36/$B$36*100,"") | I36: =IFERROR(C36/$B$36*100,"") | J36: =IFERROR(D36/$B$36*100,"") | K36: =IFERROR(E36/$B$36*100,"") | L36: =IFERROR(F36/$B$36*100,"")
A37: Tilgodehavender hos tilknyttede virksomheder | B37: ='balance_raw_12425694'!$B$17 | C37: ='balance_raw_12425694'!$C$17 | D37: ='balance_raw_12425694'!$D$17 | E37: ='balance_raw_12425694'!$E$17 | F37: ='balance_raw_12425694'!$F$17 | H37: =IFERROR(B37/$B$37*100,"") | I37: =IFERROR(C37/$B$37*100,"") | J37: =IFERROR(D37/$B$37*100,"") | K37: =IFERROR(E37/$B$37*100,"") | L37: =IFERROR(F37/$B$37*100,"")
A38: Andre tilgodehavender | B38: ='balance_raw_12425694'!$B$18 | C38: ='balance_raw_12425694'!$C$18 | D38: ='balance_raw_12425694'!$D$18 | E38: ='balance_raw_12425694'!$E$18 | F38: ='balance_raw_12425694'!$F$18 | H38: =IFERROR(B38/$B$38*100,"") | I38: =IFERROR(C38/$B$38*100,"") | J38: =IFERROR(D38/$B$38*100,"") | K38: =IFERROR(E38/$B$38*100,"") | L38: =IFERROR(F38/$B$38*100,"")
A39: Periodeafgrænsningsposter (aktiver) | B39: ='balance_raw_12425694'!$B$19 | C39: ='balance_raw_12425694'!$C$19 | D39: ='balance_raw_12425694'!$D$19 | E39: ='balance_raw_12425694'!$E$19 | F39: ='balance_raw_12425694'!$F$19 | H39: =IFERROR(B39/$B$39*100,"") | I39: =IFERROR(C39/$B$39*100,"") | J39: =IFERROR(D39/$B$39*100,"") | K39: =IFERROR(E39/$B$39*100,"") | L39: =IFERROR(F39/$B$39*100,"")
A40: Udskudt skatteaktiv | B40: ='balance_raw_12425694'!$B$20 | C40: ='balance_raw_12425694'!$C$20 | D40: ='balance_raw_12425694'!$D$20 | E40: ='balance_raw_12425694'!$E$20 | F40: ='balance_raw_12425694'!$F$20 | H40: =IFERROR(B40/$B$40*100,"") | I40: =IFERROR(C40/$B$40*100,"") | J40: =IFERROR(D40/$B$40*100,"") | K40: =IFERROR(E40/$B$40*100,"") | L40: =IFERROR(F40/$B$40*100,"")
A41: Tilgodehavende skat hos tilknyttede virksomheder | B41: ='balance_raw_12425694'!$B$21 | C41: ='balance_raw_12425694'!$C$21 | D41: ='balance_raw_12425694'!$D$21 | E41: ='balance_raw_12425694'!$E$21 | F41: ='balance_raw_12425694'!$F$21 | H41: =IFERROR(B41/$B$41*100,"") | I41: =IFERROR(C41/$B$41*100,"") | J41: =IFERROR(D41/$B$41*100,"") | K41: =IFERROR(E41/$B$41*100,"") | L41: =IFERROR(F41/$B$41*100,"")
A42: Kortfristede skattetilgodehavender | B42: ='balance_raw_12425694'!$B$22 | C42: ='balance_raw_12425694'!$C$22 | D42: ='balance_raw_12425694'!$D$22 | E42: ='balance_raw_12425694'!$E$22 | F42: ='balance_raw_12425694'!$F$22 | H42: =IFERROR(B42/$B$42*100,"") | I42: =IFERROR(C42/$B$42*100,"") | J42: =IFERROR(D42/$B$42*100,"") | K42: =IFERROR(E42/$B$42*100,"") | L42: =IFERROR(F42/$B$42*100,"")
A43: Tilgodehavender | B43: ='balance_raw_12425694'!$B$23 | C43: ='balance_raw_12425694'!$C$23 | D43: ='balance_raw_12425694'!$D$23 | E43: ='balance_raw_12425694'!$E$23 | F43: ='balance_raw_12425694'!$F$23 | H43: =IFERROR(B43/$B$43*100,"") | I43: =IFERROR(C43/$B$43*100,"") | J43: =IFERROR(D43/$B$43*100,"") | K43: =IFERROR(E43/$B$43*100,"") | L43: =IFERROR(F43/$B$43*100,"")
A44: Værdipapirer | B44: ='balance_raw_12425694'!$B$24 | C44: ='balance_raw_12425694'!$C$24 | D44: ='balance_raw_12425694'!$D$24 | E44: ='balance_raw_12425694'!$E$24 | F44: ='balance_raw_12425694'!$F$24 | H44: =IFERROR(B44/$B$44*100,"") | I44: =IFERROR(C44/$B$44*100,"") | J44: =IFERROR(D44/$B$44*100,"") | K44: =IFERROR(E44/$B$44*100,"") | L44: =IFERROR(F44/$B$44*100,"")
A45: Likvide beholdninger | B45: ='balance_raw_12425694'!$B$25 | C45: ='balance_raw_12425694'!$C$25 | D45: ='balance_raw_12425694'!$D$25 | E45: ='balance_raw_12425694'!$E$25 | F45: ='balance_raw_12425694'!$F$25 | H45: =IFERROR(B45/$B$45*100,"") | I45: =IFERROR(C45/$B$45*100,"") | J45: =IFERROR(D45/$B$45*100,"") | K45: =IFERROR(E45/$B$45*100,"") | L45: =IFERROR(F45/$B$45*100,"")
A46: Omsætningsaktiver | B46: ='balance_raw_12425694'!$B$26 | C46: ='balance_raw_12425694'!$C$26 | D46: ='balance_raw_12425694'!$D$26 | E46: ='balance_raw_12425694'!$E$26 | F46: ='balance_raw_12425694'!$F$26 | H46: =IFERROR(B46/$B$46*100,"") | I46: =IFERROR(C46/$B$46*100,"") | J46: =IFERROR(D46/$B$46*100,"") | K46: =IFERROR(E46/$B$46*100,"") | L46: =IFERROR(F46/$B$46*100,"")
A47: Aktiver | B47: ='balance_raw_12425694'!$B$27 | C47: ='balance_raw_12425694'!$C$27 | D47: ='balance_raw_12425694'!$D$27 | E47: ='balance_raw_12425694'!$E$27 | F47: ='balance_raw_12425694'!$F$27 | H47: =IFERROR(B47/$B$47*100,"") | I47: =IFERROR(C47/$B$47*100,"") | J47: =IFERROR(D47/$B$47*100,"") | K47: =IFERROR(E47/$B$47*100,"") | L47: =IFERROR(F47/$B$47*100,"")
A49: PASSIVER t.kr. | B49: 2021 | C49: 2022 | D49: 2023 | E49: 2024 | F49: 2025 | H49: 2021 | I49: 2022 | J49: 2023 | K49: 2024 | L49: 2025
A50: Selskabskapital | B50: ='balance_raw_12425694'!$B$28 | C50: ='balance_raw_12425694'!$C$28 | D50: ='balance_raw_12425694'!$D$28 | E50: ='balance_raw_12425694'!$E$28 | F50: ='balance_raw_12425694'!$F$28 | H50: =IFERROR(B50/$B$50*100,"") | I50: =IFERROR(C50/$B$50*100,"") | J50: =IFERROR(D50/$B$50*100,"") | K50: =IFERROR(E50/$B$50*100,"") | L50: =IFERROR(F50/$B$50*100,"")
A51: Reserve for nettoopskrivning (indre værdis metode) | B51: ='balance_raw_12425694'!$B$29 | C51: ='balance_raw_12425694'!$C$29 | D51: ='balance_raw_12425694'!$D$29 | E51: ='balance_raw_12425694'!$E$29 | F51: ='balance_raw_12425694'!$F$29 | H51: =IFERROR(B51/$B$51*100,"") | I51: =IFERROR(C51/$B$51*100,"") | J51: =IFERROR(D51/$B$51*100,"") | K51: =IFERROR(E51/$B$51*100,"") | L51: =IFERROR(F51/$B$51*100,"")
A52: Reserve for udviklingsomkostninger | B52: ='balance_raw_12425694'!$B$30 | C52: ='balance_raw_12425694'!$C$30 | D52: ='balance_raw_12425694'!$D$30 | E52: ='balance_raw_12425694'!$E$30 | F52: ='balance_raw_12425694'!$F$30 | H52: =IFERROR(B52/$B$52*100,"") | I52: =IFERROR(C52/$B$52*100,"") | J52: =IFERROR(D52/$B$52*100,"") | K52: =IFERROR(E52/$B$52*100,"") | L52: =IFERROR(F52/$B$52*100,"")
A53: Reserve for sikringstransaktioner | B53: ='balance_raw_12425694'!$B$31 | C53: ='balance_raw_12425694'!$C$31 | D53: ='balance_raw_12425694'!$D$31 | E53: ='balance_raw_12425694'!$E$31 | F53: ='balance_raw_12425694'!$F$31 | H53: =IFERROR(B53/$B$53*100,"") | I53: =IFERROR(C53/$B$53*100,"") | J53: =IFERROR(D53/$B$53*100,"") | K53: =IFERROR(E53/$B$53*100,"") | L53: =IFERROR(F53/$B$53*100,"")
A54: Andre reserver | B54: ='balance_raw_12425694'!$B$32 | C54: ='balance_raw_12425694'!$C$32 | D54: ='balance_raw_12425694'!$D$32 | E54: ='balance_raw_12425694'!$E$32 | F54: ='balance_raw_12425694'!$F$32 | H54: =IFERROR(B54/$B$54*100,"") | I54: =IFERROR(C54/$B$54*100,"") | J54: =IFERROR(D54/$B$54*100,"") | K54: =IFERROR(E54/$B$54*100,"") | L54: =IFERROR(F54/$B$54*100,"")
A55: Overført resultat | B55: ='balance_raw_12425694'!$B$33 | C55: ='balance_raw_12425694'!$C$33 | D55: ='balance_raw_12425694'!$D$33 | E55: ='balance_raw_12425694'!$E$33 | F55: ='balance_raw_12425694'!$F$33 | H55: =IFERROR(B55/$B$55*100,"") | I55: =IFERROR(C55/$B$55*100,"") | J55: =IFERROR(D55/$B$55*100,"") | K55: =IFERROR(E55/$B$55*100,"") | L55: =IFERROR(F55/$B$55*100,"")
A56: Egenkapital i alt | B56: ='balance_raw_12425694'!$B$34 | C56: ='balance_raw_12425694'!$C$34 | D56: ='balance_raw_12425694'!$D$34 | E56: ='balance_raw_12425694'!$E$34 | F56: ='balance_raw_12425694'!$F$34 | H56: =IFERROR(B56/$B$56*100,"") | I56: =IFERROR(C56/$B$56*100,"") | J56: =IFERROR(D56/$B$56*100,"") | K56: =IFERROR(E56/$B$56*100,"") | L56: =IFERROR(F56/$B$56*100,"")
A57: Ansvarlig lånekapital (langfristet) | B57: ='balance_raw_12425694'!$B$35 | C57: ='balance_raw_12425694'!$C$35 | D57: ='balance_raw_12425694'!$D$35 | E57: ='balance_raw_12425694'!$E$35 | F57: ='balance_raw_12425694'!$F$35 | H57: =IFERROR(B57/$B$57*100,"") | I57: =IFERROR(C57/$B$57*100,"") | J57: =IFERROR(D57/$B$57*100,"") | K57: =IFERROR(E57/$B$57*100,"") | L57: =IFERROR(F57/$B$57*100,"")
A58: Langfristede lån | B58: ='balance_raw_12425694'!$B$36 | C58: ='balance_raw_12425694'!$C$36 | D58: ='balance_raw_12425694'!$D$36 | E58: ='balance_raw_12425694'!$E$36 | F58: ='balance_raw_12425694'!$F$36 | H58: =IFERROR(B58/$B$58*100,"") | I58: =IFERROR(C58/$B$58*100,"") | J58: =IFERROR(D58/$B$58*100,"") | K58: =IFERROR(E58/$B$58*100,"") | L58: =IFERROR(F58/$B$58*100,"")
A59: Leasingforpligtelser (langfristet) | B59: ='balance_raw_12425694'!$B$37 | C59: ='balance_raw_12425694'!$C$37 | D59: ='balance_raw_12425694'!$D$37 | E59: ='balance_raw_12425694'!$E$37 | F59: ='balance_raw_12425694'!$F$37 | H59: =IFERROR(B59/$B$59*100,"") | I59: =IFERROR(C59/$B$59*100,"") | J59: =IFERROR(D59/$B$59*100,"") | K59: =IFERROR(E59/$B$59*100,"") | L59: =IFERROR(F59/$B$59*100,"")
A60: Anden gæld (langfristet) | B60: ='balance_raw_12425694'!$B$38 | C60: ='balance_raw_12425694'!$C$38 | D60: ='balance_raw_12425694'!$D$38 | E60: ='balance_raw_12425694'!$E$38 | F60: ='balance_raw_12425694'!$F$38 | H60: =IFERROR(B60/$B$60*100,"") | I60: =IFERROR(C60/$B$60*100,"") | J60: =IFERROR(D60/$B$60*100,"") | K60: =IFERROR(E60/$B$60*100,"") | L60: =IFERROR(F60/$B$60*100,"")
A61: Langfristede gældsforpligtelser | B61: ='balance_raw_12425694'!$B$39 | C61: ='balance_raw_12425694'!$C$39 | D61: ='balance_raw_12425694'!$D$39 | E61: ='balance_raw_12425694'!$E$39 | F61: ='balance_raw_12425694'!$F$39 | H61: =IFERROR(B61/$B$61*100,"") | I61: =IFERROR(C61/$B$61*100,"") | J61: =IFERROR(D61/$B$61*100,"") | K61: =IFERROR(E61/$B$61*100,"") | L61: =IFERROR(F61/$B$61*100,"")
A62: Ansvarlig lånekapital (kortfristet) | B62: ='balance_raw_12425694'!$B$40 | C62: ='balance_raw_12425694'!$C$40 | D62: ='balance_raw_12425694'!$D$40 | E62: ='balance_raw_12425694'!$E$40 | F62: ='balance_raw_12425694'!$F$40 | H62: =IFERROR(B62/$B$62*100,"") | I62: =IFERROR(C62/$B$62*100,"") | J62: =IFERROR(D62/$B$62*100,"") | K62: =IFERROR(E62/$B$62*100,"") | L62: =IFERROR(F62/$B$62*100,"")
A63: Kortfristet del af langfristede gældsforpligtelser | B63: ='balance_raw_12425694'!$B$41 | C63: ='balance_raw_12425694'!$C$41 | D63: ='balance_raw_12425694'!$D$41 | E63: ='balance_raw_12425694'!$E$41 | F63: ='balance_raw_12425694'!$F$41 | H63: =IFERROR(B63/$B$63*100,"") | I63: =IFERROR(C63/$B$63*100,"") | J63: =IFERROR(D63/$B$63*100,"") | K63: =IFERROR(E63/$B$63*100,"") | L63: =IFERROR(F63/$B$63*100,"")
A64: Kreditinstitutter | B64: ='balance_raw_12425694'!$B$42 | C64: ='balance_raw_12425694'!$C$42 | D64: ='balance_raw_12425694'!$D$42 | E64: ='balance_raw_12425694'!$E$42 | F64: ='balance_raw_12425694'!$F$42 | H64: =IFERROR(B64/$B$64*100,"") | I64: =IFERROR(C64/$B$64*100,"") | J64: =IFERROR(D64/$B$64*100,"") | K64: =IFERROR(E64/$B$64*100,"") | L64: =IFERROR(F64/$B$64*100,"")
A65: Leasingforpligtelser (kortfristet) | B65: ='balance_raw_12425694'!$B$43 | C65: ='balance_raw_12425694'!$C$43 | D65: ='balance_raw_12425694'!$D$43 | E65: ='balance_raw_12425694'!$E$43 | F65: ='balance_raw_12425694'!$F$43 | H65: =IFERROR(B65/$B$65*100,"") | I65: =IFERROR(C65/$B$65*100,"") | J65: =IFERROR(D65/$B$65*100,"") | K65: =IFERROR(E65/$B$65*100,"") | L65: =IFERROR(F65/$B$65*100,"")
A66: Leverandører af varer og tjenesteydelser | B66: ='balance_raw_12425694'!$B$44 | C66: ='balance_raw_12425694'!$C$44 | D66: ='balance_raw_12425694'!$D$44 | E66: ='balance_raw_12425694'!$E$44 | F66: ='balance_raw_12425694'!$F$44 | H66: =IFERROR(B66/$B$66*100,"") | I66: =IFERROR(C66/$B$66*100,"") | J66: =IFERROR(D66/$B$66*100,"") | K66: =IFERROR(E66/$B$66*100,"") | L66: =IFERROR(F66/$B$66*100,"")
A67: Gæld til tilknyttede virksomheder | B67: ='balance_raw_12425694'!$B$45 | C67: ='balance_raw_12425694'!$C$45 | D67: ='balance_raw_12425694'!$D$45 | E67: ='balance_raw_12425694'!$E$45 | F67: ='balance_raw_12425694'!$F$45 | H67: =IFERROR(B67/$B$67*100,"") | I67: =IFERROR(C67/$B$67*100,"") | J67: =IFERROR(D67/$B$67*100,"") | K67: =IFERROR(E67/$B$67*100,"") | L67: =IFERROR(F67/$B$67*100,"")
A68: Gæld til selskabsdeltagere og ledelse | B68: ='balance_raw_12425694'!$B$46 | C68: ='balance_raw_12425694'!$C$46 | D68: ='balance_raw_12425694'!$D$46 | E68: ='balance_raw_12425694'!$E$46 | F68: ='balance_raw_12425694'!$F$46 | H68: =IFERROR(B68/$B$68*100,"") | I68: =IFERROR(C68/$B$68*100,"") | J68: =IFERROR(D68/$B$68*100,"") | K68: =IFERROR(E68/$B$68*100,"") | L68: =IFERROR(F68/$B$68*100,"")
A69: Selskabsskat | B69: ='balance_raw_12425694'!$B$47 | C69: ='balance_raw_12425694'!$C$47 | D69: ='balance_raw_12425694'!$D$47 | E69: ='balance_raw_12425694'!$E$47 | F69: ='balance_raw_12425694'!$F$47 | H69: =IFERROR(B69/$B$69*100,"") | I69: =IFERROR(C69/$B$69*100,"") | J69: =IFERROR(D69/$B$69*100,"") | K69: =IFERROR(E69/$B$69*100,"") | L69: =IFERROR(F69/$B$69*100,"")
A70: Gæld til tilknyttede virksomheder vedr. selskabsskat | B70: ='balance_raw_12425694'!$B$48 | C70: ='balance_raw_12425694'!$C$48 | D70: ='balance_raw_12425694'!$D$48 | E70: ='balance_raw_12425694'!$E$48 | F70: ='balance_raw_12425694'!$F$48 | H70: =IFERROR(B70/$B$70*100,"") | I70: =IFERROR(C70/$B$70*100,"") | J70: =IFERROR(D70/$B$70*100,"") | K70: =IFERROR(E70/$B$70*100,"") | L70: =IFERROR(F70/$B$70*100,"")
A71: Anden gæld (kortfristet) | B71: ='balance_raw_12425694'!$B$49 | C71: ='balance_raw_12425694'!$C$49 | D71: ='balance_raw_12425694'!$D$49 | E71: ='balance_raw_12425694'!$E$49 | F71: ='balance_raw_12425694'!$F$49 | H71: =IFERROR(B71/$B$71*100,"") | I71: =IFERROR(C71/$B$71*100,"") | J71: =IFERROR(D71/$B$71*100,"") | K71: =IFERROR(E71/$B$71*100,"") | L71: =IFERROR(F71/$B$71*100,"")
A72: Periodeafgrænsningsposter (passiver) | B72: ='balance_raw_12425694'!$B$50 | C72: ='balance_raw_12425694'!$C$50 | D72: ='balance_raw_12425694'!$D$50 | E72: ='balance_raw_12425694'!$E$50 | F72: ='balance_raw_12425694'!$F$50 | H72: =IFERROR(B72/$B$72*100,"") | I72: =IFERROR(C72/$B$72*100,"") | J72: =IFERROR(D72/$B$72*100,"") | K72: =IFERROR(E72/$B$72*100,"") | L72: =IFERROR(F72/$B$72*100,"")
A73: Kortfristede gældsforpligtelser | B73: ='balance_raw_12425694'!$B$51 | C73: ='balance_raw_12425694'!$C$51 | D73: ='balance_raw_12425694'!$D$51 | E73: ='balance_raw_12425694'!$E$51 | F73: ='balance_raw_12425694'!$F$51 | H73: =IFERROR(B73/$B$73*100,"") | I73: =IFERROR(C73/$B$73*100,"") | J73: =IFERROR(D73/$B$73*100,"") | K73: =IFERROR(E73/$B$73*100,"") | L73: =IFERROR(F73/$B$73*100,"")
A74: Gældsforpligtelser | B74: ='balance_raw_12425694'!$B$52 | C74: ='balance_raw_12425694'!$C$52 | D74: ='balance_raw_12425694'!$D$52 | E74: ='balance_raw_12425694'!$E$52 | F74: ='balance_raw_12425694'!$F$52 | H74: =IFERROR(B74/$B$74*100,"") | I74: =IFERROR(C74/$B$74*100,"") | J74: =IFERROR(D74/$B$74*100,"") | K74: =IFERROR(E74/$B$74*100,"") | L74: =IFERROR(F74/$B$74*100,"")
A75: Passiver | B75: ='balance_raw_12425694'!$B$53 | C75: ='balance_raw_12425694'!$C$53 | D75: ='balance_raw_12425694'!$D$53 | E75: ='balance_raw_12425694'!$E$53 | F75: ='balance_raw_12425694'!$F$53 | H75: =IFERROR(B75/$B$75*100,"") | I75: =IFERROR(C75/$B$75*100,"") | J75: =IFERROR(D75/$B$75*100,"") | K75: =IFERROR(E75/$B$75*100,"") | L75: =IFERROR(F75/$B$75*100,"")
A77: NØGLEOPLYSNINGER | B77: 2021 | C77: 2022 | D77: 2023 | E77: 2024 | F77: 2025
A78: Gns. antal medarbejdere | B78: ='res_raw_12425694'!$B$18 | C78: ='res_raw_12425694'!$C$18 | D78: ='res_raw_12425694'!$D$18 | E78: ='res_raw_12425694'!$E$18 | F78: ='res_raw_12425694'!$F$18 | H78: =IFERROR(B78/$B$78*100,"") | I78: =IFERROR(C78/$B$78*100,"") | J78: =IFERROR(D78/$B$78*100,"") | K78: =IFERROR(E78/$B$78*100,"") | L78: =IFERROR(F78/$B$78*100,"")
A79: Investering i materielle anlægsaktiver | B79: ='res_raw_12425694'!$B$19 | C79: ='res_raw_12425694'!$C$19 | D79: ='res_raw_12425694'!$D$19 | E79: ='res_raw_12425694'!$E$19 | F79: ='res_raw_12425694'!$F$19 | H79: =IFERROR(B79/$B$79*100,"") | I79: =IFERROR(C79/$B$79*100,"") | J79: =IFERROR(D79/$B$79*100,"") | K79: =IFERROR(E79/$B$79*100,"") | L79: =IFERROR(F79/$B$79*100,"")
A81: NØGLETAL | B81: 2021 | C81: 2022 | D81: 2023 | E81: 2024 | F81: 2025
A82: Afkastningsgrad, % | B82: =IFERROR(($B$12+$B$14+$B$13)/$B$47*100,"") | C82: =IFERROR(($C$12+$C$14+$C$13)/$C$47*100,"") | D82: =IFERROR(($D$12+$D$14+$D$13)/$D$47*100,"") | E82: =IFERROR(($E$12+$E$14+$E$13)/$E$47*100,"") | F82: =IFERROR(($F$12+$F$14+$F$13)/$F$47*100,"")
A83: Overskudsgrad, % | B83: =IFERROR(($B$12+$B$14+$B$13)/$B$4*100,"") | C83: =IFERROR(($C$12+$C$14+$C$13)/$C$4*100,"") | D83: =IFERROR(($D$12+$D$14+$D$13)/$D$4*100,"") | E83: =IFERROR(($E$12+$E$14+$E$13)/$E$4*100,"") | F83: =IFERROR(($F$12+$F$14+$F$13)/$F$4*100,"")
A84: Aktivernes omsætningshastighed, gange | B84: =IFERROR($B$4/$B$47,"") | C84: =IFERROR($C$4/$C$47,"") | D84: =IFERROR($D$4/$D$47,"") | E84: =IFERROR($E$4/$E$47,"") | F84: =IFERROR($F$4/$F$47,"")
A85: Egenkapitalens forrentning, % | B85: =IFERROR($B$17/$B$56*100,"") | C85: =IFERROR($C$17/$C$56*100,"") | D85: =IFERROR($D$17/$D$56*100,"") | E85: =IFERROR($E$17/$E$56*100,"") | F85: =IFERROR($F$17/$F$56*100,"")
A86: Gældsrente, % | B86: =IFERROR($B$15/($B$75-$B$56)*100,"") | C86: =IFERROR($C$15/($C$75-$C$56)*100,"") | D86: =IFERROR($D$15/($D$75-$D$56)*100,"") | E86: =IFERROR($E$15/($E$75-$E$56)*100,"") | F86: =IFERROR($F$15/($F$75-$F$56)*100,"")
A87: Soliditetsgrad, % | B87: =IFERROR($B$56/$B$47*100,"") | C87: =IFERROR($C$56/$C$47*100,"") | D87: =IFERROR($D$56/$D$47*100,"") | E87: =IFERROR($E$56/$E$47*100,"") | F87: =IFERROR($F$56/$F$47*100,"")
A88: Gearing | B88: =IFERROR(($B$75-$B$56)/$B$56,"") | C88: =IFERROR(($C$75-$C$56)/$C$56,"") | D88: =IFERROR(($D$75-$D$56)/$D$56,"") | E88: =IFERROR(($E$75-$E$56)/$E$56,"") | F88: =IFERROR(($F$75-$F$56)/$F$56,"")
A89: Likviditetsgrad, % | B89: =IFERROR($B$46/$B$73*100,"") | C89: =IFERROR($C$46/$C$73*100,"") | D89: =IFERROR($D$46/$D$73*100,"") | E89: =IFERROR($E$46/$E$73*100,"") | F89: =IFERROR($F$46/$F$73*100,"")
A90: Rentemarginal, % | B90: =IFERROR(B82-B86,"") | C90: =IFERROR(C82-C86,"") | D90: =IFERROR(D82-D86,"") | E90: =IFERROR(E82-E86,"") | F90: =IFERROR(F82-F86,"")
A91: Gældsandel, % | B91: =IFERROR(($B$75-$B$56)/$B$47*100,"") | C91: =IFERROR(($C$75-$C$56)/$C$47*100,"") | D91: =IFERROR(($D$75-$D$56)/$D$47*100,"") | E91: =IFERROR(($E$75-$E$56)/$E$47*100,"") | F91: =IFERROR(($F$75-$F$56)/$F$47*100,"")
A92: Kapitalbindingsgrad, % | B92: =IFERROR($B$31/($B$56+$B$61)*100,"") | C92: =IFERROR($C$31/($C$56+$C$61)*100,"") | D92: =IFERROR($D$31/($D$56+$D$61)*100,"") | E92: =IFERROR($E$31/($E$56+$E$61)*100,"") | F92: =IFERROR($F$31/($F$56+$F$61)*100,"")
A94: PENGESTRØMSOPGØRELSE t.kr.
A95: Pengestrømme fra driftsaktivitet | B95: ='pengestrom_raw_12425694'!$B$2 | C95: ='pengestrom_raw_12425694'!$C$2 | D95: ='pengestrom_raw_12425694'!$D$2 | E95: ='pengestrom_raw_12425694'!$E$2 | F95: ='pengestrom_raw_12425694'!$F$2
A96: Pengestrømme fra investeringsaktivitet | B96: ='pengestrom_raw_12425694'!$B$3 | C96: ='pengestrom_raw_12425694'!$C$3 | D96: ='pengestrom_raw_12425694'!$D$3 | E96: ='pengestrom_raw_12425694'!$E$3 | F96: ='pengestrom_raw_12425694'!$F$3
A97: Pengestrømme fra finansieringsaktivitet | B97: ='pengestrom_raw_12425694'!$B$4 | C97: ='pengestrom_raw_12425694'!$C$4 | D97: ='pengestrom_raw_12425694'!$D$4 | E97: ='pengestrom_raw_12425694'!$E$4 | F97: ='pengestrom_raw_12425694'!$F$4
A98: Årets pengestrøm (rapporteret) | B98: ='pengestrom_raw_12425694'!$B$5 | C98: ='pengestrom_raw_12425694'!$C$5 | D98: ='pengestrom_raw_12425694'!$D$5 | E98: ='pengestrom_raw_12425694'!$E$5 | F98: ='pengestrom_raw_12425694'!$F$5
A99: Krydstjek: drift + inv. + fin. = årets pengestrøm | B99: =IF(ABS(('pengestrom_raw_12425694'!$B$2+'pengestrom_raw_12425694'!$B$3+'pengestrom_raw_12425694'!$B$4)-'pengestrom_raw_12425694'!$B$5)<=2,"✓","⚠ "&TEXT(('pengestrom_raw_12425694'!$B$2+'pengestrom_raw_12425694'!$B$3+'pengestrom_raw_12425694'!$B$4)-'pengestrom_raw_12425694'!$B$5,"+#,##0;-#,##0")) | C99: =IF(ABS(('pengestrom_raw_12425694'!$C$2+'pengestrom_raw_12425694'!$C$3+'pengestrom_raw_12425694'!$C$4)-'pengestrom_raw_12425694'!$C$5)<=2,"✓","⚠ "&TEXT(('pengestrom_raw_12425694'!$C$2+'pengestrom_raw_12425694'!$C$3+'pengestrom_raw_12425694'!$C$4)-'pengestrom_raw_12425694'!$C$5,"+#,##0;-#,##0")) | D99: =IF(ABS(('pengestrom_raw_12425694'!$D$2+'pengestrom_raw_12425694'!$D$3+'pengestrom_raw_12425694'!$D$4)-'pengestrom_raw_12425694'!$D$5)<=2,"✓","⚠ "&TEXT(('pengestrom_raw_12425694'!$D$2+'pengestrom_raw_12425694'!$D$3+'pengestrom_raw_12425694'!$D$4)-'pengestrom_raw_12425694'!$D$5,"+#,##0;-#,##0")) | E99: =IF(ABS(('pengestrom_raw_12425694'!$E$2+'pengestrom_raw_12425694'!$E$3+'pengestrom_raw_12425694'!$E$4)-'pengestrom_raw_12425694'!$E$5)<=2,"✓","⚠ "&TEXT(('pengestrom_raw_12425694'!$E$2+'pengestrom_raw_12425694'!$E$3+'pengestrom_raw_12425694'!$E$4)-'pengestrom_raw_12425694'!$E$5,"+#,##0;-#,##0")) | F99: =IF(ABS(('pengestrom_raw_12425694'!$F$2+'pengestrom_raw_12425694'!$F$3+'pengestrom_raw_12425694'!$F$4)-'pengestrom_raw_12425694'!$F$5)<=2,"✓","⚠ "&TEXT(('pengestrom_raw_12425694'!$F$2+'pengestrom_raw_12425694'!$F$3+'pengestrom_raw_12425694'!$F$4)-'pengestrom_raw_12425694'!$F$5,"+#,##0;-#,##0"))

Sheet res_raw_12425694
A1: Thise Mejeri A.M.B.A. (CVR 12425694) — Resultatopgørelse & nøgleoplysninger (t.kr.) | B1: 2021 | C1: 2022 | D1: 2023 | E1: 2024 | F1: 2025
A2: Nettoomsætning | B2: 1203839 | C2: 1332973 | D2: 1424152 | E2: 1480905 | F2: 1762090
A3: Produktionsomkostninger | B3: 1083098 | C3: 1208344 | D3: 1263074 | E3: 1320738 | F3: 1588064
A4: Bruttoresultat | B4: 120741 | C4: 124629 | D4: 161078 | E4: 160167 | F4: 174026
A5: Udviklingsomkostninger
A6: Salgs- og distributionsomkostninger | B6: 61177 | C6: 71235 | D6: 73892 | E6: 80457 | F6: 89718
A7: Administrationsomkostninger | B7: 27275 | C7: 29604 | D7: 47354 | E7: 41770 | F7: 46262
A8: Andre driftsindtægter | B8: -124 | C8: -497 | D8: -80 | E8: -25 | F8: -1149
A9: Andre driftsomkostninger
A10: Resultat af primær drift | B10: 32289 | C10: 23790 | D10: 39832 | E10: 37940 | F10: 38046
A11: Indtægter af kapitalandele, dattervirksomheder | B11: 0 | C11: 0 | D11: 0 | E11: 0 | F11: 0
A12: Finansielle indtægter | B12: -2 | C12: 3008 | D12: 164 | E12: 216 | F12: 568
A13: Finansielle omkostninger | B13: 5542 | C13: 6560 | D13: 8564 | E13: 7155 | F13: 5751
A14: Finansielle poster, netto | B14: -5544 | C14: -3552 | D14: -8400 | E14: -6939 | F14: -5183
A15: Resultat før skat | B15: 26788 | C15: 20268 | D15: 31484 | E15: 30554 | F15: 33012
A16: Skat af årets resultat | B16: 120 | C16: 158 | D16: 129 | E16: 3 | F16: 251
A17: Årets resultat | B17: 26668 | C17: 20110 | D17: 31355 | E17: 30551 | F17: 32761
A18: Gns. antal medarbejdere | B18: 256 | C18: 270 | D18: 273 | E18: 291 | F18: 302
A19: Investering i materielle anlægsaktiver | B19: -56303 | C19: -66659 | D19: -23554 | E19: -14325

Sheet balance_raw_12425694
A1: Thise Mejeri A.M.B.A. (CVR 12425694) — Balance (t.kr.) | B1: 2021 | C1: 2022 | D1: 2023 | E1: 2024 | F1: 2025
A2: Grunde og bygninger | B2: 177115 | C2: 233612 | D2: 220687 | E2: 205107 | F2: 202238
A3: Produktionsanlæg og maskiner | B3: 53566 | C3: 68824 | D3: 64710 | E3: 53917 | F3: 50264
A4: Driftsmateriel og inventar | B4: 2200 | C4: 6360 | D4: 6560 | E4: 4928 | F4: 4891
A5: Indretning af lejede lokaler
A6: Forudbetaling og anlægsaktiver under opførelse | B6: 39918 | C6: 0 | D6: 8210 | E6: 13816 | F6: 27332
A7: Materielle anlægsaktiver | B7: 272799 | C7: 308796 | D7: 300167 | E7: 277768 | F7: 284725
A8: Kapitalandele, dattervirksomheder | B8: 0 | C8: 0 | D8: 0 | E8: 0 | F8: 0
A9: Deposita | B9: 30 | C9: 30 | D9: 30 | E9: 30 | F9: 30
A10: Finansielle anlægsaktiver | B10: 1551 | C10: 1580 | D10: 1630 | E10: 1182 | F10: 1330
A11: Anlægsaktiver | B11: 274350 | C11: 310376 | D11: 301797 | E11: 278950 | F11: 286055
A12: Råvarer og hjælpematerialer | B12: 22132 | C12: 22165 | D12: 24140 | E12: 23768 | F12: 22377
A13: Varer under fremstilling | B13: 43032 | C13: 37242 | D13: 36537 | E13: 51167 | F13: 44888
A14: Færdigvarer og handelsvarer | B14: 31956 | C14: 35538 | D14: 22808 | E14: 17603 | F14: 27271
A15: Varebeholdninger | B15: 97120 | C15: 94945 | D15: 83485 | E15: 92538 | F15: 94536
A16: Tilgodehavender fra salg og tjenesteydelser | B16: 110310 | C16: 145587 | D16: 146742 | E16: 173293 | F16: 200448
A17: Tilgodehavender hos tilknyttede virksomheder | B17: 0 | C17: 0 | D17: 0 | E17: 0 | F17: 0
... A19: Periodeafgrænsningsposter (aktiver) | B19: 962 | C19: 1358 | D19: 1674 | E19: 2563 | F19: 1765
A20: Udskudt skatteaktiv | B20: 9 | C20: 9 | D20: 0
A21: Tilgodehavende skat hos tilknyttede virksomheder
A22: Kortfristede skattetilgodehavender
A23: Tilgodehavender | B23: 122612 | C23: 157286 | D23: 155437 | E23: 199311 | F23: 212039
A24: Værdipapirer
A25: Likvide beholdninger | B25: 139 | C25: 69 | D25: 43 | E25: 89 | F25: 1661
A26: Omsætningsaktiver | B26: 219871 | C26: 252300 | D26: 238965 | E26: 291938 | F26: 308236
A27: Aktiver | B27: 494221 | C27: 562676 | D27: 540762 | E27: 570888 | F27: 594291
A28: Selskabskapital
A29: Reserve for nettoopskrivning (indre værdis metode) | B29: 0 | C29: 0 | D29: 0 | E29: 0 | F29: 0
A30: Reserve for udviklingsomkostninger
A31: Reserve for sikringstransaktioner
A32: Andre reserver | B32: 20731 | C32: 23785 | D32: 25315 | E32: 26817
A33: Overført resultat | B33: 152834 | C33: 158058 | D33: 168881 | E33: 177260 | F33: 184572
A34: Egenkapital i alt | B34: 186797 | C34: 195421 | D34: 209829 | E34: 221368 | F34: 233221
A35: Ansvarlig lånekapital (langfristet)
A36: Langfristede lån | B36: 59677 | C36: 114454 | D36: 108007 | E36: 99447 | F36: 89959
A37: Leasingforpligtelser (langfristet) | B37: 15921 | C37: 19272 | D37: 17616 | E37: 26857 | F37: 41058
A38: Anden gæld (langfristet) | B38: 3280 | C38: 532 | D38: 490 | E38: 337 | F38: 177
A39: Langfristede gældsforpligtelser | B39: 79408 | C39: 134258 | D39: 126126 | E39: 126654 | F39: 131307
A40: Ansvarlig lånekapital (kortfristet)
A41: Kortfristet del af langfristede gældsforpligtelser
A42: Kreditinstitutter | B42: 52692 | C42: 56370 | D42: 16681 | E42: 33823 | F42: 7900
A43: Leasingforpligtelser (kortfristet) | B43: 6477 | C43: 9383 | D43: 4038 | E43: 3996 | F43: 5292
A44: Leverandører af varer og tjenesteydelser | B44: 117336 | C44: 114138 | D44: 123932 | E44: 125528 | F44: 143048
A45: Gæld til tilknyttede virksomheder | B45: 0 | C45: 0 | D45: 0
A46: Gæld til selskabsdeltagere og ledelse
A47: Selskabsskat | B47: 129 | C47: 231 | D47: 314 | E47: 244 | F47: 264
A48: Gæld til tilknyttede virksomheder vedr. selskabsskat
A49: Anden gæld (kortfristet) | B49: 44168 | F49: 63906
A50: Periodeafgrænsningsposter (passiver) | B50: 130 | C50: 329 | D50: 0
A51: Kortfristede gældsforpligtelser | B51: 228016 | C51: 232997 | D51: 204807 | E51: 222866 | F51: 229763
A52: Gældsforpligtelser | B52: 307424 | C52: 367255 | D52: 330933 | E52: 349520 | F52: 361070
A53: Passiver | B53: 494221 | C53: 562676 | D53: 540762 | E53: 570888 | F53: 594291

Sheet pengestrom_raw_12425694
A1: Thise Mejeri A.M.B.A. (CVR 12425694) — Pengestrømsopgørelse (t.kr.) | B1: 2021 | C1: 2022 | D1: 2023 | E1: 2024 | F1: 2025
A2: Pengestrømme fra driftsaktivitet | B2: 41714 | C2: 5396 | D2: 84914 | E2: 10408 | F2: 81340
A3: Pengestrømme fra investeringsaktivitet | B3: -55596 | C3: -53101 | D3: -21464 | E3: -658 | F3: -24216
A4: Pengestrømme fra finansieringsaktivitet | B4: -38274 | C4: 47635 | D4: -63476 | E4: -9704 | F4: -55552
A5: Årets pengestrøm

Sheet Simpel_funktion
A1: Thise Mejeri A.M.B.A. (CVR 12425694) — Regnskabs- og nøgletal (CVR: 12425694) — funktionsopdelt
A3: Beløb i 1.000 kr. | B3: 2025 | C3: 2024 | D3: 2023 | F3: Note / XBRL-felt
A4: Uddrag af resultatopgørelse
A5: Nettoomsætning | B5: ='res_raw_12425694'!$F$2 | C5: ='res_raw_12425694'!$E$2 | D5: ='res_raw_12425694'!$D$2 | F5: fsa:Revenue
A6: Produktionsomkostninger | B6: =-'res_raw_12425694'!$F$3 | C6: =-'res_raw_12425694'!$E$3 | D6: =-'res_raw_12425694'!$D$3 | F6: fsa:CostOfProduction (vises negativt). Materialer, lønninger, produktionsoverhead.
A7: Bruttoresultat | B7: =IF(ABS((SUM(B5:B6))-'res_raw_12425694'!$F$4)<=2,SUM(B5:B6),'res_raw_12425694'!$F$4) | C7: =IF(ABS((SUM(C5:C6))-'res_raw_12425694'!$E$4)<=2,SUM(C5:C6),'res_raw_12425694'!$E$4) | D7: =IF(ABS((SUM(D5:D6))-'res_raw_12425694'!$D$4)<=2,SUM(D5:D6),'res_raw_12425694'!$D$4) | F7: Beregnet: Nettoomsætning − Produktionsomkostninger. Matcher fsa:GrossResult. Er komponenterne ikke indberettet, vises rapporteret fsa:GrossResult direkte.
A8: Udviklingsomkostninger | B8: =-'res_raw_12425694'!$F$5 | C8: =-'res_raw_12425694'!$E$5 | D8: =-'res_raw_12425694'!$D$5 | F8: ifrs-full:ResearchAndDevelopmentExpense (vises negativt). Udviklingsomkostninger ført i resultatet (v15_21; B&O m.fl.).
A9: Salgs- og distributionsomk. | B9: =-'res_raw_12425694'!$F$6 | C9: =-'res_raw_12425694'!$E$6 | D9: =-'res_raw_12425694'!$D$6 | F9: fsa:DistributionCosts (vises negativt). Marketing, salg, distribution.
A10: Administrationsomkostninger mv. | B10: =-'res_raw_12425694'!$F$7 | C10: =-'res_raw_12425694'!$E$7 | D10: =-'res_raw_12425694'!$D$7 | F10: fsa:AdministrativeExpenses (vises negativt). Generel administration.
A11: Andre driftsindtægter | B11: ='res_raw_12425694'!$F$8 | C11: ='res_raw_12425694'!$E$8 | D11: ='res_raw_12425694'!$D$8 | F11: fsa:OtherOperatingIncome. Sekundære driftsindtægter (huslejeindtægter, off. tilskud, avancer mv.).
A12: Andre driftsomkostninger | B12: =-'res_raw_12425694'!$F$9 | C12: =-'res_raw_12425694'!$E$9 | D12: =-'res_raw_12425694'!$D$9 | F12: fsa:OtherOperatingExpenses (vises negativt). Sekundære driftsomkostninger.
A13: Resultat af primær drift | B13: =IF(ABS((SUM(B7:B12))-'res_raw_12425694'!$F$10)<=2,SUM(B7:B12),'res_raw_12425694'!$F$10) | C13: =IF(ABS((SUM(C7:C12))-'res_raw_12425694'!$E$10)<=2,SUM(C7:C12),'res_raw_12425694'!$E$10) | D13: =IF(ABS((SUM(D7:D12))-'res_raw_12425694'!$D$10)<=2,SUM(D7:D12),'res_raw_12425694'!$D$10) | F13: Beregnet: Bruttoresultat − Udviklingsomk. − Salgs/dist. − Administration + Andre driftsindt. − Andre driftsomk. EBIT.
A14: Finansielle indtægter mv. | B14: =N('res_raw_12425694'!$F$11)+N('res_raw_12425694'!$F$12) | C14: =N('res_raw_12425694'!$E$11)+N('res_raw_12425694'!$E$12) | D14: =N('res_raw_12425694'!$D$11)+N('res_raw_12425694'!$D$12) | F14: fsa:IncomeFromSubsidiaries + fsa:OtherFinanceIncome.
A15: Finansielle omkostninger mv. | B15: =-'res_raw_12425694'!$F$13 | C15: =-'res_raw_12425694'!$E$13 | D15: =-'res_raw_12425694'!$D$13 | F15: fsa:OtherFinanceExpenses (vises negativt). Renteomkostninger, kurstab.
A16: Resultat før skat | B16: =IF(ABS((SUM(B13:B15))-'res_raw_12425694'!$F$15)<=2,SUM(B13:B15),'res_raw_12425694'!$F$15) | C16: =IF(ABS((SUM(C13:C15))-'res_raw_12425694'!$E$15)<=2,SUM(C13:C15),'res_raw_12425694'!$E$15) | D16: =IF(ABS((SUM(D13:D15))-'res_raw_12425694'!$D$15)<=2,SUM(D13:D15),'res_raw_12425694'!$D$15) | F16: Beregnet: EBIT + Fin. indtægter + Fin. omk. EBT.
A18: Uddrag af balance
A19: Anlægsaktiver | B19: ='balance_raw_12425694'!$F$11 | C19: ='balance_raw_12425694'!$E$11 | D19: ='balance_raw_12425694'!$D$11 | F19: fsa:NoncurrentAssets. Materielle, immaterielle og finansielle anlægsaktiver.
A20: Omsætningsaktiver | B20: ='balance_raw_12425694'!$F$26 | C20: ='balance_raw_12425694'!$E$26 | D20: ='balance_raw_12425694'!$D$26 | F20: fsa:CurrentAssets. Varebeholdninger, tilgodehavender, likvider.
A21: Aktiver i alt | B21: =SUM(B19:B20) | C21: =SUM(C19:C20) | D21: =SUM(D19:D20) | F21: Beregnet: Anlægsaktiver + Omsætningsaktiver. Bør matche fsa:Assets.
A23: Egenkapital | B23: ='balance_raw_12425694'!$F$34 | C23: ='balance_raw_12425694'!$E$34 | D23: ='balance_raw_12425694'!$D$34 | F23: fsa:Equity. Selskabskapital, overført resultat, reserver.
A24: Forpligtelser | B24: ='balance_raw_12425694'!$F$53-'balance_raw_12425694'!$F$34 | C24: ='balance_raw_12425694'!$E$53-'balance_raw_12425694'!$E$34 | D24: ='balance_raw_12425694'!$D$53-'balance_raw_12425694'!$D$34 | F24: Beregnet: Passiver (fsa:LiabilitiesAndEquity) − Egenkapital. Hensættelser + kort- og langfristet gæld.
A25: Passiver i alt | B25: =SUM(B23:B24) | C25: =SUM(C23:C24) | D25: =SUM(D23:D24) | F25: Beregnet: Egenkapital + Forpligtelser. Bør matche Aktiver i alt.
A27: Udvalgte balanceposter
A28: Varebeholdninger | B28: ='balance_raw_12425694'!$F$15 | C28: ='balance_raw_12425694'!$E$15 | D28: ='balance_raw_12425694'!$D$15 | F28: fsa:Inventories (eller fsa:ManufacturedGoodsAndGoodsForResale hvis total mangler).
A29: Tilgodehavender fra salg | B29: ='balance_raw_12425694'!$F$16 | C29: ='balance_raw_12425694'!$E$16 | D29: ='balance_raw_12425694'!$D$16 | F29: fsa:ShorttermTradeReceivables. Kortfristede tilgodehavender fra kunder.
A30: Kortfristede gældsforpligtelser | B30: ='balance_raw_12425694'!$F$51 | C30: ='balance_raw_12425694'!$E$51 | D30: ='balance_raw_12425694'!$D$51 | F30: fsa:ShorttermLiabilitiesOtherThanProvisions. Gæld der forfalder inden for 1 år.
A32: Rentabilitet
A33: Afkastningsgrad, % | B33: =IFERROR((B13+B14)/B21*100,"") | C33: =IFERROR((C13+C14)/C21*100,"") | D33: =IFERROR((D13+D14)/D21*100,"")
A34: Overskudsgrad, % | B34: =IFERROR((B13+B14)/B5*100,"") | C34: =IFERROR((C13+C14)/C5*100,"") | D34: =IFERROR((D13+D14)/D5*100,"")
A35: Aktivernes omsætningshastighed, gange | B35: =IFERROR(B5/B21,"") | C35: =IFERROR(C5/C21,"") | D35: =IFERROR(D5/D21,"")
A36: Gældsrente, % | B36: =IFERROR(-B15*100/B24,"") | C36: =IFERROR(-C15*100/C24,"") | D36: =IFERROR(-D15*100/D24,"")
A37: Egenkapitalens forrentning, % | B37: =IFERROR(B16/B23*100,"") | C37: =IFERROR(C16/C23*100,"") | D37: =IFERROR(D16/D23*100,"")
A38: Gearing, gange | B38: =IFERROR(B24/B23,"") | C38: =IFERROR(C24/C23,"") | D38: =IFERROR(D24/D23,"")
A40: Indekstal for indtjeningsevne (2023=100)
A41: Nettoomsætning | B41: =IFERROR(B5/$D5*100,"") | C41: =IFERROR(C5/$D5*100,"") | D41: =IFERROR(D5/$D5*100,"")
A42: Produktionsomkostninger | B42: =IFERROR(B6/$D6*100,"") | C42: =IFERROR(C6/$D6*100,"") | D42: =IFERROR(D6/$D6*100,"")
A43: Udviklingsomkostninger | B43: =IFERROR(B8/$D8*100,"") | C43: =IFERROR(C8/$D8*100,"") | D43: =IFERROR(D8/$D8*100,"")
A44: Salgs- og distributionsomk. | B44: =IFERROR(B9/$D9*100,"") | C44: =IFERROR(C9/$D9*100,"") | D44: =IFERROR(D9/$D9*100,"")
A45: Administrationsomk. | B45: =IFERROR(B10/$D10*100,"") | C45: =IFERROR(C10/$D10*100,"") | D45: =IFERROR(D10/$D10*100,"")
A46: Andre driftsomkostninger | B46: =IFERROR(B12/$D12*100,"") | C46: =IFERROR(C12/$D12*100,"") | D46: =IFERROR(D12/$D12*100,"")
A48: Indekstal for kapitaltilpasningsevne (2023=100)
A49: Nettoomsætning | B49: =IFERROR(B5*100/$D5,"") | C49: =IFERROR(C5*100/$D5,"") | D49: =IFERROR(D5*100/$D5,"")
A50: Anlægsaktiver | B50: =IFERROR(B19*100/$D19,"") | C50: =IFERROR(C19*100/$D19,"") | D50: =IFERROR(D19*100/$D19,"")
A51: Varebeholdninger | B51: =IFERROR(B28*100/$D28,"") | C51: =IFERROR(C28*100/$D28,"") | D51: =IFERROR(D28*100/$D28,"")
A52: Tilgodehavender fra salg | B52: =IFERROR(B29*100/$D29,"") | C52: =IFERROR(C29*100/$D29,"") | D52: =IFERROR(D29*100/$D29,"")
A54: Soliditet og likviditet
A55: Soliditetsgrad, % | B55: =IFERROR(B23*100/B21,"") | C55: =IFERROR(C23*100/C21,"") | D55: =IFERROR(D23*100/D21,"")
A56: Gældsandel, % | B56: =IFERROR(B24*100/B21,"") | C56: =IFERROR(C24*100/C21,"") | D56: =IFERROR(D24*100/D21,"")
A57: Likviditetsgrad, % | B57: =IFERROR(B20*100/B30,"") | C57: =IFERROR(C20*100/C30,"") | D57: =IFERROR(D20*100/D30,"")
A59: Kilde: Bearbejdet uddrag af årsrapporter for 2023-2025. Alle dataceller er live formler der peger på res_raw / balance_raw.
A61: Krydstjek mod rådata (tolerance: 1 t.kr.)
A62: Aktiver i alt = fsa:Assets | B62: =IF('balance_raw_12425694'!$F$27="","—",IF(ABS(B21-'balance_raw_12425694'!$F$27)<=1,"✓ OK","❌ "&TEXT(B21-'balance_raw_12425694'!$F$27,"+#,##0;-#,##0")&" t.kr.")) | C62: =IF('balance_raw_12425694'!$E$27="","—",IF(ABS(C21-'balance_raw_12425694'!$E$27)<=1,"✓ OK","❌ "&TEXT(C21-'balance_raw_12425694'!$E$27,"+#,##0;-#,##0")&" t.kr.")) | D62: =IF('balance_raw_12425694'!$D$27="","—",IF(ABS(D21-'balance_raw_12425694'!$D$27)<=1,"✓ OK","❌ "&TEXT(D21-'balance_raw_12425694'!$D$27,"+#,##0;-#,##0")&" t.kr.")) | F62: Verificerer at sum(Anlæg+Omsætning) matcher Assets-totalen.
A63: Passiver i alt = fsa:LiabilitiesAndEquity | B63: =IF('balance_raw_12425694'!$F$53="","—",IF(ABS(B25-'balance_raw_12425694'!$F$53)<=1,"✓ OK","❌ "&TEXT(B25-'balance_raw_12425694'!$F$53,"+#,##0;-#,##0")&" t.kr.")) | C63: =IF('balance_raw_12425694'!$E$53="","—",IF(ABS(C25-'balance_raw_12425694'!$E$53)<=1,"✓ OK","❌ "&TEXT(C25-'balance_raw_12425694'!$E$53,"+#,##0;-#,##0")&" t.kr.")) | D63: =IF('balance_raw_12425694'!$D$53="","—",IF(ABS(D25-'balance_raw_12425694'!$D$53)<=1,"✓ OK","❌ "&TEXT(D25-'balance_raw_12425694'!$D$53,"+#,##0;-#,##0")&" t.kr.")) | F63: Verificerer at sum(EK+Forpligtelser) matcher Passiver-totalen.
A64: Aktiver i alt = Passiver i alt | B64: =IF(ABS(B21-B25)<=1,"✓ OK","❌ "&TEXT(B21-B25,"+#,##0;-#,##0")&" t.kr.") | C64: =IF(ABS(C21-C25)<=1,"✓ OK","❌ "&TEXT(C21-C25,"+#,##0;-#,##0")&" t.kr.") | D64: =IF(ABS(D21-D25)<=1,"✓ OK","❌ "&TEXT(D21-D25,"+#,##0;-#,##0")&" t.kr.") | F64: Balance-identitet på arket selv. Skal altid være 0 differance.
A65: Bruttoresultat (beregnet) = fsa:GrossResult | B65: =IF('res_raw_12425694'!$F$4="","—",IF(ABS(B7-'res_raw_12425694'!$F$4)<=1,"✓ OK","❌ "&TEXT(B7-'res_raw_12425694'!$F$4,"+#,##0;-#,##0")&" t.kr.")) | C65: =IF('res_raw_12425694'!$E$4="","—",IF(ABS(C7-'res_raw_12425694'!$E$4)<=1,"✓ OK","❌ "&TEXT(C7-'res_raw_12425694'!$E$4,"+#,##0;-#,##0")&" t.kr.")) | D65: =IF('res_raw_12425694'!$D$4="","—",IF(ABS(D7-'res_raw_12425694'!$D$4)<=1,"✓ OK","❌ "&TEXT(D7-'res_raw_12425694'!$D$4,"+#,##0;-#,##0")&" t.kr.")) | F65: Hvis Nettoomsætning eller omkostninger mangler, vil sumberegnet bruttoresultat afvige.
A66: EBIT (beregnet) = fsa:ProfitLossFromOrdinaryOperatingActivities | B66: =IF('res_raw_12425694'!$F$10="","—",IF(ABS(B13-'res_raw_12425694'!$F$10)<=1,"✓ OK","❌ "&TEXT(B13-'res_raw_12425694'!$F$10,"+#,##0;-#,##0")&" t.kr.")) | C66: =IF('res_raw_12425694'!$E$10="","—",IF(ABS(C13-'res_raw_12425694'!$E$10)<=1,"✓ OK","❌ "&TEXT(C13-'res_raw_12425694'!$E$10,"+#,##0;-#,##0")&" t.kr.")) | D66: =IF('res_raw_12425694'!$D$10="","—",IF(ABS(D13-'res_raw_12425694'!$D$10)<=1,"✓ OK","❌ "&TEXT(D13-'res_raw_12425694'!$D$10,"+#,##0;-#,##0")&" t.kr.")) | F66: Verificerer at sumberegnet EBIT matcher det rapporterede.
A67: EBT (beregnet) = fsa:ProfitLossFromOrdinaryActivitiesBeforeTax | B67: =IF('res_raw_12425694'!$F$15="","—",IF(ABS(B16-'res_raw_12425694'!$F$15)<=1,"✓ OK","❌ "&TEXT(B16-'res_raw_12425694'!$F$15,"+#,##0;-#,##0")&" t.kr.")) | C67: =IF('res_raw_12425694'!$E$15="","—",IF(ABS(C16-'res_raw_12425694'!$E$15)<=1,"✓ OK","❌ "&TEXT(C16-'res_raw_12425694'!$E$15,"+#,##0;-#,##0")&" t.kr.")) | D67: =IF('res_raw_12425694'!$D$15="","—",IF(ABS(D16-'res_raw_12425694'!$D$15)<=1,"✓ OK","❌ "&TEXT(D16-'res_raw_12425694'!$D$15,"+#,##0;-#,##0")&" t.kr.")) | F67: Verificerer at sumberegnet resultat før skat matcher det rapporterede.

Sheet Noter_info
A1: Thise Mejeri A.M.B.A. (CVR 12425694) — Ukendte XBRL-felter — disse er noter og ikke en del af hoved-regnskabet
A2: Kategori | B2: Dansk navn | C2: XBRL feltnavn | D2: 2021 t.kr. | E2: 2022 t.kr. | F2: 2023 t.kr. | G2: 2024 t.kr. | H2: 2025 t.kr. | I2: Forklaring
A3: Øvrige (ukendt) | B3: fsa:IncomeFromOtherLongtermInvestmentsAndReceivables | C3: fsa:IncomeFromOtherLongtermInvestmentsAndReceivables | D3: 43 | E3: 30 | F3: 52 | G3: -447 | H3: 149 | I3: Ingen forklaring tilgængelig.
A4: Øvrige (ukendt) | B4: fsa:LongtermDeferredIncome | C4: fsa:LongtermDeferredIncome | D4: 266 | E4: 0 | H4: 100 | I4: Ingen forklaring tilgængelig.
A5: Øvrige (ukendt) | B5: fsa:NotPaidContributedCapital | C5: fsa:NotPaidContributedCapital | H5: 19122 | I5: Ingen forklaring tilgængelig.
A6: Øvrige (ukendt) | B6: fsa:OtherShorttermDebtRaisedByIssuanceOfBonds | C6: fsa:OtherShorttermDebtRaisedByIssuanceOfBonds | D6: 0 | I6: Ingen forklaring tilgængelig.
A7: Øvrige (ukendt) | B7: fsa:ReserveFund | C7: fsa:ReserveFund | H7: 29527 | I7: Ingen forklaring tilgængelig.
A8: Øvrige (ukendt) | B8: fsa:TransferredFromToReserveFund | C8: fsa:TransferredFromToReserveFund | H8: 6527 | I8: Ingen forklaring tilgængelig.
