Workbook

Sheet Overblik_27528406
A1: Matas A/S (CVR 27528406) — Regnskabsanalyse – Resultatopgørelse & Balance (t.kr.) · Revision · Regnskabsår 1/4–31/3 (forskudt)
H2: Indekstal (2021=100)
A3: Resultatopgørelse t.kr. | B3: 2021 | C3: 2022 | D3: 2023 | E3: 2024 | F3: 2025 | H3: 2021 | I3: 2022 | J3: 2023 | K3: 2024 | L3: 2025
A4: Nettoomsætning | B4: ='res_raw_27528406'!$B$2 | C4: ='res_raw_27528406'!$C$2 | D4: ='res_raw_27528406'!$D$2 | E4: ='res_raw_27528406'!$E$2 | F4: ='res_raw_27528406'!$F$2 | H4: =IFERROR(B4/$B$4*100,"") | I4: =IFERROR(C4/$B$4*100,"") | J4: =IFERROR(D4/$B$4*100,"") | K4: =IFERROR(E4/$B$4*100,"") | L4: =IFERROR(F4/$B$4*100,"")
A5: Produktionsomkostninger | B5: ='res_raw_27528406'!$B$3 | C5: ='res_raw_27528406'!$C$3 | D5: ='res_raw_27528406'!$D$3 | E5: ='res_raw_27528406'!$E$3 | F5: ='res_raw_27528406'!$F$3 | H5: =IFERROR(B5/$B$5*100,"") | I5: =IFERROR(C5/$B$5*100,"") | J5: =IFERROR(D5/$B$5*100,"") | K5: =IFERROR(E5/$B$5*100,"") | L5: =IFERROR(F5/$B$5*100,"")
A6: Bruttoresultat | B6: ='res_raw_27528406'!$B$4 | C6: ='res_raw_27528406'!$C$4 | D6: ='res_raw_27528406'!$D$4 | E6: ='res_raw_27528406'!$E$4 | F6: ='res_raw_27528406'!$F$4 | H6: =IFERROR(B6/$B$6*100,"") | I6: =IFERROR(C6/$B$6*100,"") | J6: =IFERROR(D6/$B$6*100,"") | K6: =IFERROR(E6/$B$6*100,"") | L6: =IFERROR(F6/$B$6*100,"")
A7: Udviklingsomkostninger | B7: ='res_raw_27528406'!$B$5 | C7: ='res_raw_27528406'!$C$5 | D7: ='res_raw_27528406'!$D$5 | E7: ='res_raw_27528406'!$E$5 | F7: ='res_raw_27528406'!$F$5 | H7: =IFERROR(B7/$B$7*100,"") | I7: =IFERROR(C7/$B$7*100,"") | J7: =IFERROR(D7/$B$7*100,"") | K7: =IFERROR(E7/$B$7*100,"") | L7: =IFERROR(F7/$B$7*100,"")
A8: Salgs- og distributionsomkostninger | B8: ='res_raw_27528406'!$B$6 | C8: ='res_raw_27528406'!$C$6 | D8: ='res_raw_27528406'!$D$6 | E8: ='res_raw_27528406'!$E$6 | F8: ='res_raw_27528406'!$F$6 | H8: =IFERROR(B8/$B$8*100,"") | I8: =IFERROR(C8/$B$8*100,"") | J8: =IFERROR(D8/$B$8*100,"") | K8: =IFERROR(E8/$B$8*100,"") | L8: =IFERROR(F8/$B$8*100,"")
A9: Administrationsomkostninger | B9: ='res_raw_27528406'!$B$7 | C9: ='res_raw_27528406'!$C$7 | D9: ='res_raw_27528406'!$D$7 | E9: ='res_raw_27528406'!$E$7 | F9: ='res_raw_27528406'!$F$7 | H9: =IFERROR(B9/$B$9*100,"") | I9: =IFERROR(C9/$B$9*100,"") | J9: =IFERROR(D9/$B$9*100,"") | K9: =IFERROR(E9/$B$9*100,"") | L9: =IFERROR(F9/$B$9*100,"")
A10: Andre driftsindtægter | B10: ='res_raw_27528406'!$B$8 | C10: ='res_raw_27528406'!$C$8 | D10: ='res_raw_27528406'!$D$8 | E10: ='res_raw_27528406'!$E$8 | F10: ='res_raw_27528406'!$F$8 | H10: =IFERROR(B10/$B$10*100,"") | I10: =IFERROR(C10/$B$10*100,"") | J10: =IFERROR(D10/$B$10*100,"") | K10: =IFERROR(E10/$B$10*100,"") | L10: =IFERROR(F10/$B$10*100,"")
A11: Andre driftsomkostninger | B11: ='res_raw_27528406'!$B$9 | C11: ='res_raw_27528406'!$C$9 | D11: ='res_raw_27528406'!$D$9 | E11: ='res_raw_27528406'!$E$9 | F11: ='res_raw_27528406'!$F$9 | H11: =IFERROR(B11/$B$11*100,"") | I11: =IFERROR(C11/$B$11*100,"") | J11: =IFERROR(D11/$B$11*100,"") | K11: =IFERROR(E11/$B$11*100,"") | L11: =IFERROR(F11/$B$11*100,"")
A12: Andre eksterne omkostninger | B12: ='res_raw_27528406'!$B$10 | C12: ='res_raw_27528406'!$C$10 | D12: ='res_raw_27528406'!$D$10 | E12: ='res_raw_27528406'!$E$10 | F12: ='res_raw_27528406'!$F$10 | H12: =IFERROR(B12/$B$12*100,"") | I12: =IFERROR(C12/$B$12*100,"") | J12: =IFERROR(D12/$B$12*100,"") | K12: =IFERROR(E12/$B$12*100,"") | L12: =IFERROR(F12/$B$12*100,"")
A13: Personaleomkostninger | B13: ='res_raw_27528406'!$B$11 | C13: ='res_raw_27528406'!$C$11 | D13: ='res_raw_27528406'!$D$11 | E13: ='res_raw_27528406'!$E$11 | F13: ='res_raw_27528406'!$F$11 | H13: =IFERROR(B13/$B$13*100,"") | I13: =IFERROR(C13/$B$13*100,"") | J13: =IFERROR(D13/$B$13*100,"") | K13: =IFERROR(E13/$B$13*100,"") | L13: =IFERROR(F13/$B$13*100,"")
A14: Af- og nedskrivninger | B14: ='res_raw_27528406'!$B$12 | C14: ='res_raw_27528406'!$C$12 | D14: ='res_raw_27528406'!$D$12 | E14: ='res_raw_27528406'!$E$12 | F14: ='res_raw_27528406'!$F$12 | H14: =IFERROR(B14/$B$14*100,"") | I14: =IFERROR(C14/$B$14*100,"") | J14: =IFERROR(D14/$B$14*100,"") | K14: =IFERROR(E14/$B$14*100,"") | L14: =IFERROR(F14/$B$14*100,"")
A15: Resultat af primær drift | B15: ='res_raw_27528406'!$B$13 | C15: ='res_raw_27528406'!$C$13 | D15: ='res_raw_27528406'!$D$13 | E15: ='res_raw_27528406'!$E$13 | F15: ='res_raw_27528406'!$F$13 | H15: =IFERROR(B15/$B$15*100,"") | I15: =IFERROR(C15/$B$15*100,"") | J15: =IFERROR(D15/$B$15*100,"") | K15: =IFERROR(E15/$B$15*100,"") | L15: =IFERROR(F15/$B$15*100,"")
A16: Indtægter af kapitalandele, dattervirksomheder | B16: ='res_raw_27528406'!$B$14 | C16: ='res_raw_27528406'!$C$14 | D16: ='res_raw_27528406'!$D$14 | E16: ='res_raw_27528406'!$E$14 | F16: ='res_raw_27528406'!$F$14 | H16: =IFERROR(B16/$B$16*100,"") | I16: =IFERROR(C16/$B$16*100,"") | J16: =IFERROR(D16/$B$16*100,"") | K16: =IFERROR(E16/$B$16*100,"") | L16: =IFERROR(F16/$B$16*100,"")
A17: Finansielle indtægter | B17: ='res_raw_27528406'!$B$15 | C17: ='res_raw_27528406'!$C$15 | D17: ='res_raw_27528406'!$D$15 | E17: ='res_raw_27528406'!$E$15 | F17: ='res_raw_27528406'!$F$15 | H17: =IFERROR(B17/$B$17*100,"") | I17: =IFERROR(C17/$B$17*100,"") | J17: =IFERROR(D17/$B$17*100,"") | K17: =IFERROR(E17/$B$17*100,"") | L17: =IFERROR(F17/$B$17*100,"")
A18: Finansielle omkostninger | B18: ='res_raw_27528406'!$B$16 | C18: ='res_raw_27528406'!$C$16 | D18: ='res_raw_27528406'!$D$16 | E18: ='res_raw_27528406'!$E$16 | F18: ='res_raw_27528406'!$F$16 | H18: =IFERROR(B18/$B$18*100,"") | I18: =IFERROR(C18/$B$18*100,"") | J18: =IFERROR(D18/$B$18*100,"") | K18: =IFERROR(E18/$B$18*100,"") | L18: =IFERROR(F18/$B$18*100,"")
A19: Finansielle poster, netto | B19: ='res_raw_27528406'!$B$17 | C19: ='res_raw_27528406'!$C$17 | D19: ='res_raw_27528406'!$D$17 | E19: ='res_raw_27528406'!$E$17 | F19: ='res_raw_27528406'!$F$17 | H19: =IFERROR(B19/$B$19*100,"") | I19: =IFERROR(C19/$B$19*100,"") | J19: =IFERROR(D19/$B$19*100,"") | K19: =IFERROR(E19/$B$19*100,"") | L19: =IFERROR(F19/$B$19*100,"")
A20: Resultat før skat | B20: ='res_raw_27528406'!$B$18 | C20: ='res_raw_27528406'!$C$18 | D20: ='res_raw_27528406'!$D$18 | E20: ='res_raw_27528406'!$E$18 | F20: ='res_raw_27528406'!$F$18 | H20: =IFERROR(B20/$B$20*100,"") | I20: =IFERROR(C20/$B$20*100,"") | J20: =IFERROR(D20/$B$20*100,"") | K20: =IFERROR(E20/$B$20*100,"") | L20: =IFERROR(F20/$B$20*100,"")
A21: Skat af årets resultat | B21: ='res_raw_27528406'!$B$19 | C21: ='res_raw_27528406'!$C$19 | D21: ='res_raw_27528406'!$D$19 | E21: ='res_raw_27528406'!$E$19 | F21: ='res_raw_27528406'!$F$19 | H21: =IFERROR(B21/$B$21*100,"") | I21: =IFERROR(C21/$B$21*100,"") | J21: =IFERROR(D21/$B$21*100,"") | K21: =IFERROR(E21/$B$21*100,"") | L21: =IFERROR(F21/$B$21*100,"")
A22: Årets resultat | B22: ='res_raw_27528406'!$B$20 | C22: ='res_raw_27528406'!$C$20 | D22: ='res_raw_27528406'!$D$20 | E22: ='res_raw_27528406'!$E$20 | F22: ='res_raw_27528406'!$F$20 | H22: =IFERROR(B22/$B$22*100,"") | I22: =IFERROR(C22/$B$22*100,"") | J22: =IFERROR(D22/$B$22*100,"") | K22: =IFERROR(E22/$B$22*100,"") | L22: =IFERROR(F22/$B$22*100,"")
A24: AKTIVER t.kr. | B24: 2021 | C24: 2022 | D24: 2023 | E24: 2024 | F24: 2025 | H24: 2021 | I24: 2022 | J24: 2023 | K24: 2024 | L24: 2025
A25: Udviklingsprojekter | B25: ='balance_raw_27528406'!$B$2 | C25: ='balance_raw_27528406'!$C$2 | D25: ='balance_raw_27528406'!$D$2 | E25: ='balance_raw_27528406'!$E$2 | F25: ='balance_raw_27528406'!$F$2 | H25: =IFERROR(B25/$B$25*100,"") | I25: =IFERROR(C25/$B$25*100,"") | J25: =IFERROR(D25/$B$25*100,"") | K25: =IFERROR(E25/$B$25*100,"") | L25: =IFERROR(F25/$B$25*100,"")
A26: Patenter, varemærker mv. | B26: ='balance_raw_27528406'!$B$3 | C26: ='balance_raw_27528406'!$C$3 | D26: ='balance_raw_27528406'!$D$3 | E26: ='balance_raw_27528406'!$E$3 | F26: ='balance_raw_27528406'!$F$3 | H26: =IFERROR(B26/$B$26*100,"") | I26: =IFERROR(C26/$B$26*100,"") | J26: =IFERROR(D26/$B$26*100,"") | K26: =IFERROR(E26/$B$26*100,"") | L26: =IFERROR(F26/$B$26*100,"")
A27: Goodwill | B27: ='balance_raw_27528406'!$B$4 | C27: ='balance_raw_27528406'!$C$4 | D27: ='balance_raw_27528406'!$D$4 | E27: ='balance_raw_27528406'!$E$4 | F27: ='balance_raw_27528406'!$F$4 | H27: =IFERROR(B27/$B$27*100,"") | I27: =IFERROR(C27/$B$27*100,"") | J27: =IFERROR(D27/$B$27*100,"") | K27: =IFERROR(E27/$B$27*100,"") | L27: =IFERROR(F27/$B$27*100,"")
A28: Immaterielle anlægsaktiver | B28: ='balance_raw_27528406'!$B$5 | C28: ='balance_raw_27528406'!$C$5 | D28: ='balance_raw_27528406'!$D$5 | E28: ='balance_raw_27528406'!$E$5 | F28: ='balance_raw_27528406'!$F$5 | H28: =IFERROR(B28/$B$28*100,"") | I28: =IFERROR(C28/$B$28*100,"") | J28: =IFERROR(D28/$B$28*100,"") | K28: =IFERROR(E28/$B$28*100,"") | L28: =IFERROR(F28/$B$28*100,"")
A29: Grunde og bygninger | B29: ='balance_raw_27528406'!$B$6 | C29: ='balance_raw_27528406'!$C$6 | D29: ='balance_raw_27528406'!$D$6 | E29: ='balance_raw_27528406'!$E$6 | F29: ='balance_raw_27528406'!$F$6 | H29: =IFERROR(B29/$B$29*100,"") | I29: =IFERROR(C29/$B$29*100,"") | J29: =IFERROR(D29/$B$29*100,"") | K29: =IFERROR(E29/$B$29*100,"") | L29: =IFERROR(F29/$B$29*100,"")
A30: Produktionsanlæg og maskiner | B30: ='balance_raw_27528406'!$B$7 | C30: ='balance_raw_27528406'!$C$7 | D30: ='balance_raw_27528406'!$D$7 | E30: ='balance_raw_27528406'!$E$7 | F30: ='balance_raw_27528406'!$F$7 | H30: =IFERROR(B30/$B$30*100,"") | I30: =IFERROR(C30/$B$30*100,"") | J30: =IFERROR(D30/$B$30*100,"") | K30: =IFERROR(E30/$B$30*100,"") | L30: =IFERROR(F30/$B$30*100,"")
A31: Driftsmateriel og inventar | B31: ='balance_raw_27528406'!$B$8 | C31: ='balance_raw_27528406'!$C$8 | D31: ='balance_raw_27528406'!$D$8 | E31: ='balance_raw_27528406'!$E$8 | F31: ='balance_raw_27528406'!$F$8 | H31: =IFERROR(B31/$B$31*100,"") | I31: =IFERROR(C31/$B$31*100,"") | J31: =IFERROR(D31/$B$31*100,"") | K31: =IFERROR(E31/$B$31*100,"") | L31: =IFERROR(F31/$B$31*100,"")
A32: Indretning af lejede lokaler | B32: ='balance_raw_27528406'!$B$9 | C32: ='balance_raw_27528406'!$C$9 | D32: ='balance_raw_27528406'!$D$9 | E32: ='balance_raw_27528406'!$E$9 | F32: ='balance_raw_27528406'!$F$9 | H32: =IFERROR(B32/$B$32*100,"") | I32: =IFERROR(C32/$B$32*100,"") | J32: =IFERROR(D32/$B$32*100,"") | K32: =IFERROR(E32/$B$32*100,"") | L32: =IFERROR(F32/$B$32*100,"")
A33: Forudbetaling og anlægsaktiver under opførelse | B33: ='balance_raw_27528406'!$B$10 | C33: ='balance_raw_27528406'!$C$10 | D33: ='balance_raw_27528406'!$D$10 | E33: ='balance_raw_27528406'!$E$10 | F33: ='balance_raw_27528406'!$F$10 | H33: =IFERROR(B33/$B$33*100,"") | I33: =IFERROR(C33/$B$33*100,"") | J33: =IFERROR(D33/$B$33*100,"") | K33: =IFERROR(E33/$B$33*100,"") | L33: =IFERROR(F33/$B$33*100,"")
A34: Materielle anlægsaktiver | B34: ='balance_raw_27528406'!$B$11 | C34: ='balance_raw_27528406'!$C$11 | D34: ='balance_raw_27528406'!$D$11 | E34: ='balance_raw_27528406'!$E$11 | F34: ='balance_raw_27528406'!$F$11 | H34: =IFERROR(B34/$B$34*100,"") | I34: =IFERROR(C34/$B$34*100,"") | J34: =IFERROR(D34/$B$34*100,"") | K34: =IFERROR(E34/$B$34*100,"") | L34: =IFERROR(F34/$B$34*100,"")
A35: Kapitalandele, dattervirksomheder | B35: ='balance_raw_27528406'!$B$12 | C35: ='balance_raw_27528406'!$C$12 | D35: ='balance_raw_27528406'!$D$12 | E35: ='balance_raw_27528406'!$E$12 | F35: ='balance_raw_27528406'!$F$12 | H35: =IFERROR(B35/$B$35*100,"") | I35: =IFERROR(C35/$B$35*100,"") | J35: =IFERROR(D35/$B$35*100,"") | K35: =IFERROR(E35/$B$35*100,"") | L35: =IFERROR(F35/$B$35*100,"")
A36: Deposita | B36: ='balance_raw_27528406'!$B$13 | C36: ='balance_raw_27528406'!$C$13 | D36: ='balance_raw_27528406'!$D$13 | E36: ='balance_raw_27528406'!$E$13 | F36: ='balance_raw_27528406'!$F$13 | H36: =IFERROR(B36/$B$36*100,"") | I36: =IFERROR(C36/$B$36*100,"") | J36: =IFERROR(D36/$B$36*100,"") | K36: =IFERROR(E36/$B$36*100,"") | L36: =IFERROR(F36/$B$36*100,"")
A37: Finansielle anlægsaktiver | B37: ='balance_raw_27528406'!$B$14 | C37: ='balance_raw_27528406'!$C$14 | D37: ='balance_raw_27528406'!$D$14 | E37: ='balance_raw_27528406'!$E$14 | F37: ='balance_raw_27528406'!$F$14 | H37: =IFERROR(B37/$B$37*100,"") | I37: =IFERROR(C37/$B$37*100,"") | J37: =IFERROR(D37/$B$37*100,"") | K37: =IFERROR(E37/$B$37*100,"") | L37: =IFERROR(F37/$B$37*100,"")
A38: Anlægsaktiver | B38: ='balance_raw_27528406'!$B$15 | C38: ='balance_raw_27528406'!$C$15 | D38: ='balance_raw_27528406'!$D$15 | E38: ='balance_raw_27528406'!$E$15 | F38: ='balance_raw_27528406'!$F$15 | H38: =IFERROR(B38/$B$38*100,"") | I38: =IFERROR(C38/$B$38*100,"") | J38: =IFERROR(D38/$B$38*100,"") | K38: =IFERROR(E38/$B$38*100,"") | L38: =IFERROR(F38/$B$38*100,"")
A39: Råvarer og hjælpematerialer | B39: ='balance_raw_27528406'!$B$16 | C39: ='balance_raw_27528406'!$C$16 | D39: ='balance_raw_27528406'!$D$16 | E39: ='balance_raw_27528406'!$E$16 | F39: ='balance_raw_27528406'!$F$16 | H39: =IFERROR(B39/$B$39*100,"") | I39: =IFERROR(C39/$B$39*100,"") | J39: =IFERROR(D39/$B$39*100,"") | K39: =IFERROR(E39/$B$39*100,"") | L39: =IFERROR(F39/$B$39*100,"")
A40: Varer under fremstilling | B40: ='balance_raw_27528406'!$B$17 | C40: ='balance_raw_27528406'!$C$17 | D40: ='balance_raw_27528406'!$D$17 | E40: ='balance_raw_27528406'!$E$17 | F40: ='balance_raw_27528406'!$F$17 | H40: =IFERROR(B40/$B$40*100,"") | I40: =IFERROR(C40/$B$40*100,"") | J40: =IFERROR(D40/$B$40*100,"") | K40: =IFERROR(E40/$B$40*100,"") | L40: =IFERROR(F40/$B$40*100,"")
A41: Færdigvarer og handelsvarer | B41: ='balance_raw_27528406'!$B$18 | C41: ='balance_raw_27528406'!$C$18 | D41: ='balance_raw_27528406'!$D$18 | E41: ='balance_raw_27528406'!$E$18 | F41: ='balance_raw_27528406'!$F$18 | H41: =IFERROR(B41/$B$41*100,"") | I41: =IFERROR(C41/$B$41*100,"") | J41: =IFERROR(D41/$B$41*100,"") | K41: =IFERROR(E41/$B$41*100,"") | L41: =IFERROR(F41/$B$41*100,"")
A42: Varebeholdninger | B42: ='balance_raw_27528406'!$B$19 | C42: ='balance_raw_27528406'!$C$19 | D42: ='balance_raw_27528406'!$D$19 | E42: ='balance_raw_27528406'!$E$19 | F42: ='balance_raw_27528406'!$F$19 | H42: =IFERROR(B42/$B$42*100,"") | I42: =IFERROR(C42/$B$42*100,"") | J42: =IFERROR(D42/$B$42*100,"") | K42: =IFERROR(E42/$B$42*100,"") | L42: =IFERROR(F42/$B$42*100,"")
A43: Tilgodehavender fra salg og tjenesteydelser | B43: ='balance_raw_27528406'!$B$20 | C43: ='balance_raw_27528406'!$C$20 | D43: ='balance_raw_27528406'!$D$20 | E43: ='balance_raw_27528406'!$E$20 | F43: ='balance_raw_27528406'!$F$20 | H43: =IFERROR(B43/$B$43*100,"") | I43: =IFERROR(C43/$B$43*100,"") | J43: =IFERROR(D43/$B$43*100,"") | K43: =IFERROR(E43/$B$43*100,"") | L43: =IFERROR(F43/$B$43*100,"")
A44: Tilgodehavender hos tilknyttede virksomheder | B44: ='balance_raw_27528406'!$B$21 | C44: ='balance_raw_27528406'!$C$21 | D44: ='balance_raw_27528406'!$D$21 | E44: ='balance_raw_27528406'!$E$21 | F44: ='balance_raw_27528406'!$F$21 | H44: =IFERROR(B44/$B$44*100,"") | I44: =IFERROR(C44/$B$44*100,"") | J44: =IFERROR(D44/$B$44*100,"") | K44: =IFERROR(E44/$B$44*100,"") | L44: =IFERROR(F44/$B$44*100,"")
A45: Andre tilgodehavender | B45: ='balance_raw_27528406'!$B$22 | C45: ='balance_raw_27528406'!$C$22 | D45: ='balance_raw_27528406'!$D$22 | E45: ='balance_raw_27528406'!$E$22 | F45: ='balance_raw_27528406'!$F$22 | H45: =IFERROR(B45/$B$45*100,"") | I45: =IFERROR(C45/$B$45*100,"") | J45: =IFERROR(D45/$B$45*100,"") | K45: =IFERROR(E45/$B$45*100,"") | L45: =IFERROR(F45/$B$45*100,"")
A46: Periodeafgrænsningsposter (aktiver) | B46: ='balance_raw_27528406'!$B$23 | C46: ='balance_raw_27528406'!$C$23 | D46: ='balance_raw_27528406'!$D$23 | E46: ='balance_raw_27528406'!$E$23 | F46: ='balance_raw_27528406'!$F$23 | H46: =IFERROR(B46/$B$46*100,"") | I46: =IFERROR(C46/$B$46*100,"") | J46: =IFERROR(D46/$B$46*100,"") | K46: =IFERROR(E46/$B$46*100,"") | L46: =IFERROR(F46/$B$46*100,"")
A47: Udskudt skatteaktiv | B47: ='balance_raw_27528406'!$B$24 | C47: ='balance_raw_27528406'!$C$24 | D47: ='balance_raw_27528406'!$D$24 | E47: ='balance_raw_27528406'!$E$24 | F47: ='balance_raw_27528406'!$F$24 | H47: =IFERROR(B47/$B$47*100,"") | I47: =IFERROR(C47/$B$47*100,"") | J47: =IFERROR(D47/$B$47*100,"") | K47: =IFERROR(E47/$B$47*100,"") | L47: =IFERROR(F47/$B$47*100,"")
A48: Tilgodehavende skat hos tilknyttede virksomheder | B48: ='balance_raw_27528406'!$B$25 | C48: ='balance_raw_27528406'!$C$25 | D48: ='balance_raw_27528406'!$D$25 | E48: ='balance_raw_27528406'!$E$25 | F48: ='balance_raw_27528406'!$F$25 | H48: =IFERROR(B48/$B$48*100,"") | I48: =IFERROR(C48/$B$48*100,"") | J48: =IFERROR(D48/$B$48*100,"") | K48: =IFERROR(E48/$B$48*100,"") | L48: =IFERROR(F48/$B$48*100,"")
A49: Kortfristede skattetilgodehavender | B49: ='balance_raw_27528406'!$B$26 | C49: ='balance_raw_27528406'!$C$26 | D49: ='balance_raw_27528406'!$D$26 | E49: ='balance_raw_27528406'!$E$26 | F49: ='balance_raw_27528406'!$F$26 | H49: =IFERROR(B49/$B$49*100,"") | I49: =IFERROR(C49/$B$49*100,"") | J49: =IFERROR(D49/$B$49*100,"") | K49: =IFERROR(E49/$B$49*100,"") | L49: =IFERROR(F49/$B$49*100,"")
A50: Tilgodehavender | B50: ='balance_raw_27528406'!$B$27 | C50: ='balance_raw_27528406'!$C$27 | D50: ='balance_raw_27528406'!$D$27 | E50: ='balance_raw_27528406'!$E$27 | F50: ='balance_raw_27528406'!$F$27 | H50: =IFERROR(B50/$B$50*100,"") | I50: =IFERROR(C50/$B$50*100,"") | J50: =IFERROR(D50/$B$50*100,"") | K50: =IFERROR(E50/$B$50*100,"") | L50: =IFERROR(F50/$B$50*100,"")
A51: Værdipapirer | B51: ='balance_raw_27528406'!$B$28 | C51: ='balance_raw_27528406'!$C$28 | D51: ='balance_raw_27528406'!$D$28 | E51: ='balance_raw_27528406'!$E$28 | F51: ='balance_raw_27528406'!$F$28 | H51: =IFERROR(B51/$B$51*100,"") | I51: =IFERROR(C51/$B$51*100,"") | J51: =IFERROR(D51/$B$51*100,"") | K51: =IFERROR(E51/$B$51*100,"") | L51: =IFERROR(F51/$B$51*100,"")
A52: Likvide beholdninger | B52: ='balance_raw_27528406'!$B$29 | C52: ='balance_raw_27528406'!$C$29 | D52: ='balance_raw_27528406'!$D$29 | E52: ='balance_raw_27528406'!$E$29 | F52: ='balance_raw_27528406'!$F$29 | H52: =IFERROR(B52/$B$52*100,"") | I52: =IFERROR(C52/$B$52*100,"") | J52: =IFERROR(D52/$B$52*100,"") | K52: =IFERROR(E52/$B$52*100,"") | L52: =IFERROR(F52/$B$52*100,"")
A53: Omsætningsaktiver | B53: ='balance_raw_27528406'!$B$30 | C53: ='balance_raw_27528406'!$C$30 | D53: ='balance_raw_27528406'!$D$30 | E53: ='balance_raw_27528406'!$E$30 | F53: ='balance_raw_27528406'!$F$30 | H53: =IFERROR(B53/$B$53*100,"") | I53: =IFERROR(C53/$B$53*100,"") | J53: =IFERROR(D53/$B$53*100,"") | K53: =IFERROR(E53/$B$53*100,"") | L53: =IFERROR(F53/$B$53*100,"")
A54: Aktiver | B54: ='balance_raw_27528406'!$B$31 | C54: ='balance_raw_27528406'!$C$31 | D54: ='balance_raw_27528406'!$D$31 | E54: ='balance_raw_27528406'!$E$31 | F54: ='balance_raw_27528406'!$F$31 | H54: =IFERROR(B54/$B$54*100,"") | I54: =IFERROR(C54/$B$54*100,"") | J54: =IFERROR(D54/$B$54*100,"") | K54: =IFERROR(E54/$B$54*100,"") | L54: =IFERROR(F54/$B$54*100,"")
A56: PASSIVER t.kr. | B56: 2021 | C56: 2022 | D56: 2023 | E56: 2024 | F56: 2025 | H56: 2021 | I56: 2022 | J56: 2023 | K56: 2024 | L56: 2025
A57: Selskabskapital | B57: ='balance_raw_27528406'!$B$32 | C57: ='balance_raw_27528406'!$C$32 | D57: ='balance_raw_27528406'!$D$32 | E57: ='balance_raw_27528406'!$E$32 | F57: ='balance_raw_27528406'!$F$32 | H57: =IFERROR(B57/$B$57*100,"") | I57: =IFERROR(C57/$B$57*100,"") | J57: =IFERROR(D57/$B$57*100,"") | K57: =IFERROR(E57/$B$57*100,"") | L57: =IFERROR(F57/$B$57*100,"")
A58: Reserve for nettoopskrivning (indre værdis metode) | B58: ='balance_raw_27528406'!$B$33 | C58: ='balance_raw_27528406'!$C$33 | D58: ='balance_raw_27528406'!$D$33 | E58: ='balance_raw_27528406'!$E$33 | F58: ='balance_raw_27528406'!$F$33 | H58: =IFERROR(B58/$B$58*100,"") | I58: =IFERROR(C58/$B$58*100,"") | J58: =IFERROR(D58/$B$58*100,"") | K58: =IFERROR(E58/$B$58*100,"") | L58: =IFERROR(F58/$B$58*100,"")
A59: Reserve for udviklingsomkostninger | B59: ='balance_raw_27528406'!$B$34 | C59: ='balance_raw_27528406'!$C$34 | D59: ='balance_raw_27528406'!$D$34 | E59: ='balance_raw_27528406'!$E$34 | F59: ='balance_raw_27528406'!$F$34 | H59: =IFERROR(B59/$B$59*100,"") | I59: =IFERROR(C59/$B$59*100,"") | J59: =IFERROR(D59/$B$59*100,"") | K59: =IFERROR(E59/$B$59*100,"") | L59: =IFERROR(F59/$B$59*100,"")
A60: Reserve for sikringstransaktioner | B60: ='balance_raw_27528406'!$B$35 | C60: ='balance_raw_27528406'!$C$35 | D60: ='balance_raw_27528406'!$D$35 | E60: ='balance_raw_27528406'!$E$35 | F60: ='balance_raw_27528406'!$F$35 | H60: =IFERROR(B60/$B$60*100,"") | I60: =IFERROR(C60/$B$60*100,"") | J60: =IFERROR(D60/$B$60*100,"") | K60: =IFERROR(E60/$B$60*100,"") | L60: =IFERROR(F60/$B$60*100,"")
A61: Andre reserver | B61: ='balance_raw_27528406'!$B$36 | C61: ='balance_raw_27528406'!$C$36 | D61: ='balance_raw_27528406'!$D$36 | E61: ='balance_raw_27528406'!$E$36 | F61: ='balance_raw_27528406'!$F$36 | H61: =IFERROR(B61/$B$61*100,"") | I61: =IFERROR(C61/$B$61*100,"") | J61: =IFERROR(D61/$B$61*100,"") | K61: =IFERROR(E61/$B$61*100,"") | L61: =IFERROR(F61/$B$61*100,"")
A62: Overført resultat | B62: ='balance_raw_27528406'!$B$37 | C62: ='balance_raw_27528406'!$C$37 | D62: ='balance_raw_27528406'!$D$37 | E62: ='balance_raw_27528406'!$E$37 | F62: ='balance_raw_27528406'!$F$37 | H62: =IFERROR(B62/$B$62*100,"") | I62: =IFERROR(C62/$B$62*100,"") | J62: =IFERROR(D62/$B$62*100,"") | K62: =IFERROR(E62/$B$62*100,"") | L62: =IFERROR(F62/$B$62*100,"")
A63: Egenkapital i alt | B63: ='balance_raw_27528406'!$B$38 | C63: ='balance_raw_27528406'!$C$38 | D63: ='balance_raw_27528406'!$D$38 | E63: ='balance_raw_27528406'!$E$38 | F63: ='balance_raw_27528406'!$F$38 | H63: =IFERROR(B63/$B$63*100,"") | I63: =IFERROR(C63/$B$63*100,"") | J63: =IFERROR(D63/$B$63*100,"") | K63: =IFERROR(E63/$B$63*100,"") | L63: =IFERROR(F63/$B$63*100,"")
A64: Hensættelse til udskudt skat | B64: ='balance_raw_27528406'!$B$39 | C64: ='balance_raw_27528406'!$C$39 | D64: ='balance_raw_27528406'!$D$39 | E64: ='balance_raw_27528406'!$E$39 | F64: ='balance_raw_27528406'!$F$39 | H64: =IFERROR(B64/$B$64*100,"") | I64: =IFERROR(C64/$B$64*100,"") | J64: =IFERROR(D64/$B$64*100,"") | K64: =IFERROR(E64/$B$64*100,"") | L64: =IFERROR(F64/$B$64*100,"")
A65: Hensatte forpligtelser | B65: ='balance_raw_27528406'!$B$40 | C65: ='balance_raw_27528406'!$C$40 | D65: ='balance_raw_27528406'!$D$40 | E65: ='balance_raw_27528406'!$E$40 | F65: ='balance_raw_27528406'!$F$40 | H65: =IFERROR(B65/$B$65*100,"") | I65: =IFERROR(C65/$B$65*100,"") | J65: =IFERROR(D65/$B$65*100,"") | K65: =IFERROR(E65/$B$65*100,"") | L65: =IFERROR(F65/$B$65*100,"")
A66: Ansvarlig lånekapital (langfristet) | B66: ='balance_raw_27528406'!$B$41 | C66: ='balance_raw_27528406'!$C$41 | D66: ='balance_raw_27528406'!$D$41 | E66: ='balance_raw_27528406'!$E$41 | F66: ='balance_raw_27528406'!$F$41 | H66: =IFERROR(B66/$B$66*100,"") | I66: =IFERROR(C66/$B$66*100,"") | J66: =IFERROR(D66/$B$66*100,"") | K66: =IFERROR(E66/$B$66*100,"") | L66: =IFERROR(F66/$B$66*100,"")
A67: Langfristede lån | B67: ='balance_raw_27528406'!$B$42 | C67: ='balance_raw_27528406'!$C$42 | D67: ='balance_raw_27528406'!$D$42 | E67: ='balance_raw_27528406'!$E$42 | F67: ='balance_raw_27528406'!$F$42 | H67: =IFERROR(B67/$B$67*100,"") | I67: =IFERROR(C67/$B$67*100,"") | J67: =IFERROR(D67/$B$67*100,"") | K67: =IFERROR(E67/$B$67*100,"") | L67: =IFERROR(F67/$B$67*100,"")
A68: Leasingforpligtelser (langfristet) | B68: ='balance_raw_27528406'!$B$43 | C68: ='balance_raw_27528406'!$C$43 | D68: ='balance_raw_27528406'!$D$43 | E68: ='balance_raw_27528406'!$E$43 | F68: ='balance_raw_27528406'!$F$43 | H68: =IFERROR(B68/$B$68*100,"") | I68: =IFERROR(C68/$B$68*100,"") | J68: =IFERROR(D68/$B$68*100,"") | K68: =IFERROR(E68/$B$68*100,"") | L68: =IFERROR(F68/$B$68*100,"")
A69: Anden gæld (langfristet) | B69: ='balance_raw_27528406'!$B$44 | C69: ='balance_raw_27528406'!$C$44 | D69: ='balance_raw_27528406'!$D$44 | E69: ='balance_raw_27528406'!$E$44 | F69: ='balance_raw_27528406'!$F$44 | H69: =IFERROR(B69/$B$69*100,"") | I69: =IFERROR(C69/$B$69*100,"") | J69: =IFERROR(D69/$B$69*100,"") | K69: =IFERROR(E69/$B$69*100,"") | L69: =IFERROR(F69/$B$69*100,"")
A70: Langfristede gældsforpligtelser | B70: ='balance_raw_27528406'!$B$45 | C70: ='balance_raw_27528406'!$C$45 | D70: ='balance_raw_27528406'!$D$45 | E70: ='balance_raw_27528406'!$E$45 | F70: ='balance_raw_27528406'!$F$45 | H70: =IFERROR(B70/$B$70*100,"") | I70: =IFERROR(C70/$B$70*100,"") | J70: =IFERROR(D70/$B$70*100,"") | K70: =IFERROR(E70/$B$70*100,"") | L70: =IFERROR(F70/$B$70*100,"")
A71: Ansvarlig lånekapital (kortfristet) | B71: ='balance_raw_27528406'!$B$46 | C71: ='balance_raw_27528406'!$C$46 | D71: ='balance_raw_27528406'!$D$46 | E71: ='balance_raw_27528406'!$E$46 | F71: ='balance_raw_27528406'!$F$46 | H71: =IFERROR(B71/$B$71*100,"") | I71: =IFERROR(C71/$B$71*100,"") | J71: =IFERROR(D71/$B$71*100,"") | K71: =IFERROR(E71/$B$71*100,"") | L71: =IFERROR(F71/$B$71*100,"")
A72: Kortfristet del af langfristede gældsforpligtelser | B72: ='balance_raw_27528406'!$B$47 | C72: ='balance_raw_27528406'!$C$47 | D72: ='balance_raw_27528406'!$D$47 | E72: ='balance_raw_27528406'!$E$47 | F72: ='balance_raw_27528406'!$F$47 | H72: =IFERROR(B72/$B$72*100,"") | I72: =IFERROR(C72/$B$72*100,"") | J72: =IFERROR(D72/$B$72*100,"") | K72: =IFERROR(E72/$B$72*100,"") | L72: =IFERROR(F72/$B$72*100,"")
A73: Kreditinstitutter | B73: ='balance_raw_27528406'!$B$48 | C73: ='balance_raw_27528406'!$C$48 | D73: ='balance_raw_27528406'!$D$48 | E73: ='balance_raw_27528406'!$E$48 | F73: ='balance_raw_27528406'!$F$48 | H73: =IFERROR(B73/$B$73*100,"") | I73: =IFERROR(C73/$B$73*100,"") | J73: =IFERROR(D73/$B$73*100,"") | K73: =IFERROR(E73/$B$73*100,"") | L73: =IFERROR(F73/$B$73*100,"")
A74: Leasingforpligtelser (kortfristet) | B74: ='balance_raw_27528406'!$B$49 | C74: ='balance_raw_27528406'!$C$49 | D74: ='balance_raw_27528406'!$D$49 | E74: ='balance_raw_27528406'!$E$49 | F74: ='balance_raw_27528406'!$F$49 | H74: =IFERROR(B74/$B$74*100,"") | I74: =IFERROR(C74/$B$74*100,"") | J74: =IFERROR(D74/$B$74*100,"") | K74: =IFERROR(E74/$B$74*100,"") | L74: =IFERROR(F74/$B$74*100,"")
A75: Leverandører af varer og tjenesteydelser | B75: ='balance_raw_27528406'!$B$50 | C75: ='balance_raw_27528406'!$C$50 | D75: ='balance_raw_27528406'!$D$50 | E75: ='balance_raw_27528406'!$E$50 | F75: ='balance_raw_27528406'!$F$50 | H75: =IFERROR(B75/$B$75*100,"") | I75: =IFERROR(C75/$B$75*100,"") | J75: =IFERROR(D75/$B$75*100,"") | K75: =IFERROR(E75/$B$75*100,"") | L75: =IFERROR(F75/$B$75*100,"")
A76: Gæld til tilknyttede virksomheder | B76: ='balance_raw_27528406'!$B$51 | C76: ='balance_raw_27528406'!$C$51 | D76: ='balance_raw_27528406'!$D$51 | E76: ='balance_raw_27528406'!$E$51 | F76: ='balance_raw_27528406'!$F$51 | H76: =IFERROR(B76/$B$76*100,"") | I76: =IFERROR(C76/$B$76*100,"") | J76: =IFERROR(D76/$B$76*100,"") | K76: =IFERROR(E76/$B$76*100,"") | L76: =IFERROR(F76/$B$76*100,"")
A77: Gæld til selskabsdeltagere og ledelse | B77: ='balance_raw_27528406'!$B$52 | C77: ='balance_raw_27528406'!$C$52 | D77: ='balance_raw_27528406'!$D$52 | E77: ='balance_raw_27528406'!$E$52 | F77: ='balance_raw_27528406'!$F$52 | H77: =IFERROR(B77/$B$77*100,"") | I77: =IFERROR(C77/$B$77*100,"") | J77: =IFERROR(D77/$B$77*100,"") | K77: =IFERROR(E77/$B$77*100,"") | L77: =IFERROR(F77/$B$77*100,"")
A78: Selskabsskat | B78: ='balance_raw_27528406'!$B$53 | C78: ='balance_raw_27528406'!$C$53 | D78: ='balance_raw_27528406'!$D$53 | E78: ='balance_raw_27528406'!$E$53 | F78: ='balance_raw_27528406'!$F$53 | H78: =IFERROR(B78/$B$78*100,"") | I78: =IFERROR(C78/$B$78*100,"") | J78: =IFERROR(D78/$B$78*100,"") | K78: =IFERROR(E78/$B$78*100,"") | L78: =IFERROR(F78/$B$78*100,"")
A79: Gæld til tilknyttede virksomheder vedr. selskabsskat | B79: ='balance_raw_27528406'!$B$54 | C79: ='balance_raw_27528406'!$C$54 | D79: ='balance_raw_27528406'!$D$54 | E79: ='balance_raw_27528406'!$E$54 | F79: ='balance_raw_27528406'!$F$54 | H79: =IFERROR(B79/$B$79*100,"") | I79: =IFERROR(C79/$B$79*100,"") | J79: =IFERROR(D79/$B$79*100,"") | K79: =IFERROR(E79/$B$79*100,"") | L79: =IFERROR(F79/$B$79*100,"")
A80: Anden gæld (kortfristet) | B80: ='balance_raw_27528406'!$B$55 | C80: ='balance_raw_27528406'!$C$55 | D80: ='balance_raw_27528406'!$D$55 | E80: ='balance_raw_27528406'!$E$55 | F80: ='balance_raw_27528406'!$F$55 | H80: =IFERROR(B80/$B$80*100,"") | I80: =IFERROR(C80/$B$80*100,"") | J80: =IFERROR(D80/$B$80*100,"") | K80: =IFERROR(E80/$B$80*100,"") | L80: =IFERROR(F80/$B$80*100,"")
A81: Periodeafgrænsningsposter (passiver) | B81: ='balance_raw_27528406'!$B$56 | C81: ='balance_raw_27528406'!$C$56 | D81: ='balance_raw_27528406'!$D$56 | E81: ='balance_raw_27528406'!$E$56 | F81: ='balance_raw_27528406'!$F$56 | H81: =IFERROR(B81/$B$81*100,"") | I81: =IFERROR(C81/$B$81*100,"") | J81: =IFERROR(D81/$B$81*100,"") | K81: =IFERROR(E81/$B$81*100,"") | L81: =IFERROR(F81/$B$81*100,"")
A82: Kortfristede gældsforpligtelser | B82: ='balance_raw_27528406'!$B$57 | C82: ='balance_raw_27528406'!$C$57 | D82: ='balance_raw_27528406'!$D$57 | E82: ='balance_raw_27528406'!$E$57 | F82: ='balance_raw_27528406'!$F$57 | H82: =IFERROR(B82/$B$82*100,"") | I82: =IFERROR(C82/$B$82*100,"") | J82: =IFERROR(D82/$B$82*100,"") | K82: =IFERROR(E82/$B$82*100,"") | L82: =IFERROR(F82/$B$82*100,"")
A83: Gældsforpligtelser | B83: ='balance_raw_27528406'!$B$58 | C83: ='balance_raw_27528406'!$C$58 | D83: ='balance_raw_27528406'!$D$58 | E83: ='balance_raw_27528406'!$E$58 | F83: ='balance_raw_27528406'!$F$58 | H83: =IFERROR(B83/$B$83*100,"") | I83: =IFERROR(C83/$B$83*100,"") | J83: =IFERROR(D83/$B$83*100,"") | K83: =IFERROR(E83/$B$83*100,"") | L83: =IFERROR(F83/$B$83*100,"")
A84: Passiver | B84: ='balance_raw_27528406'!$B$59 | C84: ='balance_raw_27528406'!$C$59 | D84: ='balance_raw_27528406'!$D$59 | E84: ='balance_raw_27528406'!$E$59 | F84: ='balance_raw_27528406'!$F$59 | H84: =IFERROR(B84/$B$84*100,"") | I84: =IFERROR(C84/$B$84*100,"") | J84: =IFERROR(D84/$B$84*100,"") | K84: =IFERROR(E84/$B$84*100,"") | L84: =IFERROR(F84/$B$84*100,"")
A86: NØGLEOPLYSNINGER | B86: 2021 | C86: 2022 | D86: 2023 | E86: 2024 | F86: 2025
A87: Gns. antal medarbejdere | B87: ='res_raw_27528406'!$B$21 | C87: ='res_raw_27528406'!$C$21 | D87: ='res_raw_27528406'!$D$21 | E87: ='res_raw_27528406'!$E$21 | F87: ='res_raw_27528406'!$F$21 | H87: =IFERROR(B87/$B$87*100,"") | I87: =IFERROR(C87/$B$87*100,"") | J87: =IFERROR(D87/$B$87*100,"") | K87: =IFERROR(E87/$B$87*100,"") | L87: =IFERROR(F87/$B$87*100,"")
A88: Investering i materielle anlægsaktiver | B88: ='res_raw_27528406'!$B$22 | C88: ='res_raw_27528406'!$C$22 | D88: ='res_raw_27528406'!$D$22 | E88: ='res_raw_27528406'!$E$22 | F88: ='res_raw_27528406'!$F$22 | H88: =IFERROR(B88/$B$88*100,"") | I88: =IFERROR(C88/$B$88*100,"") | J88: =IFERROR(D88/$B$88*100,"") | K88: =IFERROR(E88/$B$88*100,"") | L88: =IFERROR(F88/$B$88*100,"")
A90: NØGLETAL | B90: 2021 | C90: 2022 | D90: 2023 | E90: 2024 | F90: 2025
A91: Afkastningsgrad, % | B91: =IFERROR(($B$15+$B$17+$B$16)/$B$54*100,"") | C91: =IFERROR(($C$15+$C$17+$C$16)/$C$54*100,"") | D91: =IFERROR(($D$15+$D$17+$D$16)/$D$54*100,"") | E91: =IFERROR(($E$15+$E$17+$E$16)/$E$54*100,"") | F91: =IFERROR(($F$15+$F$17+$F$16)/$F$54*100,"")
A92: Overskudsgrad, % | B92: =IFERROR(($B$15+$B$17+$B$16)/$B$4*100,"") | C92: =IFERROR(($C$15+$C$17+$C$16)/$C$4*100,"") | D92: =IFERROR(($D$15+$D$17+$D$16)/$D$4*100,"") | E92: =IFERROR(($E$15+$E$17+$E$16)/$E$4*100,"") | F92: =IFERROR(($F$15+$F$17+$F$16)/$F$4*100,"")
A93: Aktivernes omsætningshastighed, gange | B93: =IFERROR($B$4/$B$54,"") | C93: =IFERROR($C$4/$C$54,"") | D93: =IFERROR($D$4/$D$54,"") | E93: =IFERROR($E$4/$E$54,"") | F93: =IFERROR($F$4/$F$54,"")
A94: Egenkapitalens forrentning, % | B94: =IFERROR($B$20/$B$63*100,"") | C94: =IFERROR($C$20/$C$63*100,"") | D94: =IFERROR($D$20/$D$63*100,"") | E94: =IFERROR($E$20/$E$63*100,"") | F94: =IFERROR($F$20/$F$63*100,"")
A95: Gældsrente, % | B95: =IFERROR($B$18/($B$84-$B$63)*100,"") | C95: =IFERROR($C$18/($C$84-$C$63)*100,"") | D95: =IFERROR($D$18/($D$84-$D$63)*100,"") | E95: =IFERROR($E$18/($E$84-$E$63)*100,"") | F95: =IFERROR($F$18/($F$84-$F$63)*100,"")
A96: Soliditetsgrad, % | B96: =IFERROR($B$63/$B$54*100,"") | C96: =IFERROR($C$63/$C$54*100,"") | D96: =IFERROR($D$63/$D$54*100,"") | E96: =IFERROR($E$63/$E$54*100,"") | F96: =IFERROR($F$63/$F$54*100,"")
A97: Gearing | B97: =IFERROR(($B$84-$B$63)/$B$63,"") | C97: =IFERROR(($C$84-$C$63)/$C$63,"") | D97: =IFERROR(($D$84-$D$63)/$D$63,"") | E97: =IFERROR(($E$84-$E$63)/$E$63,"") | F97: =IFERROR(($F$84-$F$63)/$F$63,"")
A98: Likviditetsgrad, % | B98: =IFERROR($B$53/$B$82*100,"") | C98: =IFERROR($C$53/$C$82*100,"") | D98: =IFERROR($D$53/$D$82*100,"") | E98: =IFERROR($E$53/$E$82*100,"") | F98: =IFERROR($F$53/$F$82*100,"")
A99: Rentemarginal, % | B99: =IFERROR(B91-B95,"") | C99: =IFERROR(C91-C95,"") | D99: =IFERROR(D91-D95,"") | E99: =IFERROR(E91-E95,"") | F99: =IFERROR(F91-F95,"")
A100: Gældsandel, % | B100: =IFERROR(($B$84-$B$63)/$B$54*100,"") | C100: =IFERROR(($C$84-$C$63)/$C$54*100,"") | D100: =IFERROR(($D$84-$D$63)/$D$54*100,"") | E100: =IFERROR(($E$84-$E$63)/$E$54*100,"") | F100: =IFERROR(($F$84-$F$63)/$F$54*100,"")
A101: Kapitalbindingsgrad, % | B101: =IFERROR($B$38/($B$63+$B$70)*100,"") | C101: =IFERROR($C$38/($C$63+$C$70)*100,"") | D101: =IFERROR($D$38/($D$63+$D$70)*100,"") | E101: =IFERROR($E$38/($E$63+$E$70)*100,"") | F101: =IFERROR($F$38/($F$63+$F$70)*100,"")
A103: PENGESTRØMSOPGØRELSE t.kr.
A104: Pengestrømme fra driftsaktivitet | B104: ='pengestrom_raw_27528406'!$B$2 | C104: ='pengestrom_raw_27528406'!$C$2 | D104: ='pengestrom_raw_27528406'!$D$2 | E104: ='pengestrom_raw_27528406'!$E$2 | F104: ='pengestrom_raw_27528406'!$F$2
A105: Pengestrømme fra investeringsaktivitet | B105: ='pengestrom_raw_27528406'!$B$3 | C105: ='pengestrom_raw_27528406'!$C$3 | D105: ='pengestrom_raw_27528406'!$D$3 | E105: ='pengestrom_raw_27528406'!$E$3 | F105: ='pengestrom_raw_27528406'!$F$3
...

Sheet res_raw_27528406
A1: Matas A/S (CVR 27528406) — Resultatopgørelse & nøgleoplysninger (t.kr.) | B1: 2021 | C1: 2022 | D1: 2023 | E1: 2024 | F1: 2025
A2: Nettoomsætning | B2: 4163600 | C2: 4344200 | D2: 4489600 | E2: 6701000 | F2: 8379000
A3: Produktionsomkostninger | B3: 2322400 | C3: 2378200 | D3: 2475200 | E3: 3623000 | F3: 4509000
A4: Bruttoresultat | B4: 1841200 | C4: 1966000 | D4: 2014400 | E4: 3078000 | F4: 3870000
A5: Udviklingsomkostninger
A6: Salgs- og distributionsomkostninger
A7: Administrationsomkostninger
A8: Andre driftsindtægter | B8: 10400
A9: Andre driftsomkostninger
A10: Andre eksterne omkostninger | B10: 301300 | C10: 332300 | D10: 384900 | E10: 792000 | F10: 1021000
A11: Personaleomkostninger | B11: 751900 | C11: 824100 | D11: 825300 | E11: 1299000 | F11: 1654000
A12: Af- og nedskrivninger | B12: 407600 | C12: 421300 | D12: 381100 | E12: 525000 | F12: 624000
A13: Resultat af primær drift | B13: 380400 | C13: 388300 | D13: 423100 | E13: 379000 | F13: 565000
A14: Indtægter af kapitalandele, dattervirksomheder | B14: 700 | C14: -4600 | D14: -4900 | E14: 1000 | F14: 1000
A15: Finansielle indtægter | B15: 17500 | C15: 5300 | D15: 500 | E15: 12000 | F15: 1000
A16: Finansielle omkostninger | B16: 45200 | C16: 37900 | D16: 45900 | E16: 144000 | F16: 183000
A17: Finansielle poster, netto | B17: -27700 | C17: -32600 | D17: -45400 | E17: -132000 | F17: -182000
A18: Resultat før skat | B18: 353400 | C18: 351100 | D18: 372800 | E18: 248000 | F18: 384000
A19: Skat af årets resultat | B19: 84400 | C19: 74600 | D19: 92100 | E19: 79000 | F19: 102000
A20: Årets resultat | B20: 269000 | C20: 276500 | D20: 280700 | E20: 169000 | F20: 282000
A21: Gns. antal medarbejdere | B21: 2152
A22: Investering i materielle anlægsaktiver | B22: 50500 | C22: 50500 | D22: 92200 | E22: 250000 | F22: 477000

Sheet balance_raw_27528406
A1: Matas A/S (CVR 27528406) — Balance (t.kr.) | B1: 2021 | C1: 2022 | D1: 2023 | E1: 2024 | F1: 2025
A2: Udviklingsprojekter | B2: 130300 | C2: 186800 | D2: 235800 | E2: 132000 | F2: 86000
A3: Patenter, varemærker mv. | B3: 143600 | C3: 67800 | D3: 58100 | E3: 184000 | F3: 183000
A4: Goodwill | B4: 3930600 | C4: 3993600 | D4: 3999400 | E4: 4096000 | F4: 4102000
A5: Immaterielle anlægsaktiver | B5: 4204500 | C5: 4248200 | D5: 4293300 | E5: 4671000 | F5: 4741000
A6: Grunde og bygninger | B6: 90800 | C6: 86600 | D6: 87500 | E6: 108000 | F6: 107000
A7: Produktionsanlæg og maskiner
A8: Driftsmateriel og inventar
A9: Indretning af lejede lokaler | B9: 51500 | C9: 40300 | D9: 27300 | E9: 208000 | F9: 243000
A10: Forudbetaling og anlægsaktiver under opførelse | B10: 0 | C10: 9600 | D10: 59700 | E10: 169000 | F10: 510000
A11: Materielle anlægsaktiver | B11: 651800 | C11: 500200 | D11: 622300 | E11: 1157000 | F11: 1178000
A12: Kapitalandele, dattervirksomheder | B12: 12400 | C12: 7300 | D12: 1400 | E12: 1000 | F12: 1000
A13: Deposita | B13: 600 | C13: 600 | D13: 700 | E13: 1000 | F13: 1000
A14: Finansielle anlægsaktiver
A15: Anlægsaktiver | B15: 5158900 | C15: 5026300 | D15: 5201700 | E15: 6468000 | F15: 6965000
A16: Råvarer og hjælpematerialer | E16: 3623000 | F16: 4509000
A17: Varer under fremstilling
A18: Færdigvarer og handelsvarer
A19: Varebeholdninger | B19: 866700 | C19: 890100 | D19: 911800 | E19: 1864000 | F19: 2269000
A20: Tilgodehavender fra salg og tjenesteydelser | B20: 15200 | C20: 26600 | D20: 43700 | E20: 76000 | F20: 93000
A21: Tilgodehavender hos tilknyttede virksomheder
A22: Andre tilgodehavender | B22: 158600 | C22: 154500 | D22: 161400 | E22: 221000 | F22: 235000
A23: Periodeafgrænsningsposter (aktiver) | D23: 40800 | E23: 74000 | F23: 130000
A24: Udskudt skatteaktiv | E24: 17000 | F24: 33000
A25: Tilgodehavende skat hos tilknyttede virksomheder
A26: Kortfristede skattetilgodehavender | B26: 19400 | C26: 45500 | D26: 20600 | E26: 17000 | F26: 19000
A27: Tilgodehavender | B27: 4600 | C27: 7100 | D27: 24900 | E27: 38000 | F27: 22000
A28: Værdipapirer
A29: Likvide beholdninger | B29: 40700 | C29: 28200 | D29: 36700 | E29: 131000 | F29: 76000
A30: Omsætningsaktiver | B30: 984200 | C30: 1029000 | D30: 1078500 | E30: 2200000 | F30: 2609000
A31: Aktiver | B31: 6143100 | C31: 6055300 | D31: 6280200 | E31: 8668000 | F31: 9574000
A32: Selskabskapital | B32: 95700 | C32: 95700 | D32: 95700 | E32: 96000 | F32: 96000
A33: Reserve for nettoopskrivning (indre værdis metode)
A34: Reserve for udviklingsomkostninger
A35: Reserve for sikringstransaktioner
A36: Andre reserver | B36: -1300 | C36: 0 | E36: 0 | F36: 3000
A37: Overført resultat | B37: 2600 | C37: 76000 | D37: 43500 | E37: 43000 | F37: 39000
A38: Egenkapital i alt | B38: 3038900 | C38: 3151800 | D38: 3362600 | E38: 3461000 | F38: 3715000
A39: Hensættelse til udskudt skat | B39: 199200 | C39: 192800 | D39: 198800 | E39: 227000 | F39: 212000
A40: Hensatte forpligtelser | B40: 27700 | C40: 28000 | D40: 28000 | E40: 28000 | F40: 28000
A41: Ansvarlig lånekapital (langfristet)
A42: Langfristede lån
A43: Leasingforpligtelser (langfristet) | B43: 495500 | C43: 343500 | D43: 462600 | E43: 850000 | F43: 870000
A44: Anden gæld (langfristet) | B44: 59200 | C44: 37700 | D44: 13000 | E44: 5000 | F44: 5000
A45: Langfristede gældsforpligtelser | B45: 0 | C45: 996100 | D45: 917700 | E45: 2007000 | F45: 1958000
A46: Ansvarlig lånekapital (kortfristet)
A47: Kortfristet del af langfristede gældsforpligtelser
A48: Kreditinstitutter | B48: 1098300 | C48: 157900 | D48: 110400 | E48: 55000 | F48: 670000
A49: Leasingforpligtelser (kortfristet) | B49: 174100 | C49: 179500 | D49: 188400 | E49: 360000 | F49: 404000
A50: Leverandører af varer og tjenesteydelser | B50: 692400 | C50: 662900 | D50: 634100 | E50: 1070000 | F50: 1090000
A51: Gæld til tilknyttede virksomheder
A52: Gæld til selskabsdeltagere og ledelse
A53: Selskabsskat
A54: Gæld til tilknyttede virksomheder vedr. selskabsskat
A55: Anden gæld (kortfristet) | B55: 199200 | C55: 150100 | D55: 202700 | E55: 364000 | F55: 384000
A56: Periodeafgrænsningsposter (passiver)
A57: Kortfristede gældsforpligtelser | B57: 2322600 | C57: 1304900 | D57: 1297000 | E57: 2089000 | F57: 2785000
A58: Gældsforpligtelser | B58: 3104200 | C58: 2903000 | D58: 2917100 | E58: 5206000 | F58: 5858000
A59: Passiver | B59: 6143100 | C59: 6055300 | D59: 6280200 | E59: 8668000 | F59: 9574000

Sheet pengestrom_raw_27528406
A1: Matas A/S (CVR 27528406) — Pengestrømsopgørelse (t.kr.) | B1: 2021 | C1: 2022 | D1: 2023 | E1: 2024 | F1: 2025
A2: Pengestrømme fra driftsaktivitet | B2: 952000 | C2: 510500 | D2: 679000 | E2: 645000 | F2: 715000
A3: Pengestrømme fra investeringsaktivitet | B3: -177900 | C3: -231600 | D3: -255800 | E3: -1021000 | F3: -717000
A4: Pengestrømme fra finansieringsaktivitet | B4: -840000 | C4: -291400 | D4: -414700 | E4: 466000 | F4: -56000
A5: Årets pengestrøm | B5: -65900 | C5: -12500 | D5: 8500

Sheet Simpel_funktion
A1: Matas A/S (CVR 27528406) — Regnskabs- og nøgletal (CVR: 27528406) — funktionsopdelt
A3: Beløb i 1.000 kr. | B3: 2025 | C3: 2024 | D3: 2023 | F3: Note / XBRL-felt
A4: Uddrag af resultatopgørelse
A5: Nettoomsætning | B5: ='res_raw_27528406'!$F$2 | C5: ='res_raw_27528406'!$E$2 | D5: ='res_raw_27528406'!$D$2 | F5: fsa:Revenue
A6: Produktionsomkostninger | B6: =-'res_raw_27528406'!$F$3 | C6: =-'res_raw_27528406'!$E$3 | D6: =-'res_raw_27528406'!$D$3 | F6: fsa:CostOfProduction (vises negativt). Materialer, lønninger, produktionsoverhead.
A7: Bruttoresultat | B7: =IF(ABS((SUM(B5:B6))-'res_raw_27528406'!$F$4)<=2,SUM(B5:B6),'res_raw_27528406'!$F$4) | C7: =IF(ABS((SUM(C5:C6))-'res_raw_27528406'!$E$4)<=2,SUM(C5:C6),'res_raw_27528406'!$E$4) | D7: =IF(ABS((SUM(D5:D6))-'res_raw_27528406'!$D$4)<=2,SUM(D5:D6),'res_raw_27528406'!$D$4) | F7: Beregnet: Nettoomsætning − Produktionsomkostninger. Matcher fsa:GrossResult. Er komponenterne ikke indberettet, vises rapporteret fsa:GrossResult direkte.
A8: Udviklingsomkostninger | B8: =-'res_raw_27528406'!$F$5 | C8: =-'res_raw_27528406'!$E$5 | D8: =-'res_raw_27528406'!$D$5 | F8: ifrs-full:ResearchAndDevelopmentExpense (vises negativt). Udviklingsomkostninger ført i resultatet (v15_21; B&O m.fl.).
A9: Salgs- og distributionsomk. | B9: =-'res_raw_27528406'!$F$6 | C9: =-'res_raw_27528406'!$E$6 | D9: =-'res_raw_27528406'!$D$6 | F9: fsa:DistributionCosts (vises negativt). Marketing, salg, distribution.
A10: Administrationsomkostninger mv. | B10: =-'res_raw_27528406'!$F$7 | C10: =-'res_raw_27528406'!$E$7 | D10: =-'res_raw_27528406'!$D$7 | F10: fsa:AdministrativeExpenses (vises negativt). Generel administration.
A11: Andre driftsindtægter | B11: ='res_raw_27528406'!$F$8 | C11: ='res_raw_27528406'!$E$8 | D11: ='res_raw_27528406'!$D$8 | F11: fsa:OtherOperatingIncome. Sekundære driftsindtægter (huslejeindtægter, off. tilskud, avancer mv.).
A12: Andre driftsomkostninger | B12: =-'res_raw_27528406'!$F$9 | C12: =-'res_raw_27528406'!$E$9 | D12: =-'res_raw_27528406'!$D$9 | F12: fsa:OtherOperatingExpenses (vises negativt). Sekundære driftsomkostninger.
A13: Resultat af primær drift | B13: =IF(ABS((SUM(B7:B12))-'res_raw_27528406'!$F$13)<=2,SUM(B7:B12),'res_raw_27528406'!$F$13) | C13: =IF(ABS((SUM(C7:C12))-'res_raw_27528406'!$E$13)<=2,SUM(C7:C12),'res_raw_27528406'!$E$13) | D13: =IF(ABS((SUM(D7:D12))-'res_raw_27528406'!$D$13)<=2,SUM(D7:D12),'res_raw_27528406'!$D$13) | F13: Beregnet: Bruttoresultat − Udviklingsomk. − Salgs/dist. − Administration + Andre driftsindt. − Andre driftsomk. EBIT.
A14: Finansielle indtægter mv. | B14: =N('res_raw_27528406'!$F$14)+N('res_raw_27528406'!$F$15) | C14: =N('res_raw_27528406'!$E$14)+N('res_raw_27528406'!$E$15) | D14: =N('res_raw_27528406'!$D$14)+N('res_raw_27528406'!$D$15) | F14: fsa:IncomeFromSubsidiaries + fsa:OtherFinanceIncome.
A15: Finansielle omkostninger mv. | B15: =-'res_raw_27528406'!$F$16 | C15: =-'res_raw_27528406'!$E$16 | D15: =-'res_raw_27528406'!$D$16 | F15: fsa:OtherFinanceExpenses (vises negativt). Renteomkostninger, kurstab.
A16: Resultat før skat | B16: =IF(ABS((SUM(B13:B15))-'res_raw_27528406'!$F$18)<=2,SUM(B13:B15),'res_raw_27528406'!$F$18) | C16: =IF(ABS((SUM(C13:C15))-'res_raw_27528406'!$E$18)<=2,SUM(C13:C15),'res_raw_27528406'!$E$18) | D16: =IF(ABS((SUM(D13:D15))-'res_raw_27528406'!$D$18)<=2,SUM(D13:D15),'res_raw_27528406'!$D$18) | F16: Beregnet: EBIT + Fin. indtægter + Fin. omk. EBT.
A18: Uddrag af balance
A19: Anlægsaktiver | B19: ='balance_raw_27528406'!$F$15 | C19: ='balance_raw_27528406'!$E$15 | D19: ='balance_raw_27528406'!$D$15 | F19: fsa:NoncurrentAssets. Materielle, immaterielle og finansielle anlægsaktiver.
A20: Omsætningsaktiver | B20: ='balance_raw_27528406'!$F$30 | C20: ='balance_raw_27528406'!$E$30 | D20: ='balance_raw_27528406'!$D$30 | F20: fsa:CurrentAssets. Varebeholdninger, tilgodehavender, likvider.
A21: Aktiver i alt | B21: =SUM(B19:B20) | C21: =SUM(C19:C20) | D21: =SUM(D19:D20) | F21: Beregnet: Anlægsaktiver + Omsætningsaktiver. Bør matche fsa:Assets.
A23: Egenkapital | B23: ='balance_raw_27528406'!$F$38 | C23: ='balance_raw_27528406'!$E$38 | D23: ='balance_raw_27528406'!$D$38 | F23: fsa:Equity. Selskabskapital, overført resultat, reserver.
A24: Forpligtelser | B24: ='balance_raw_27528406'!$F$59-'balance_raw_27528406'!$F$38 | C24: ='balance_raw_27528406'!$E$59-'balance_raw_27528406'!$E$38 | D24: ='balance_raw_27528406'!$D$59-'balance_raw_27528406'!$D$38 | F24: Beregnet: Passiver (fsa:LiabilitiesAndEquity) − Egenkapital. Hensættelser + kort- og langfristet gæld.
A25: Passiver i alt | B25: =SUM(B23:B24) | C25: =SUM(C23:C24) | D25: =SUM(D23:D24) | F25: Beregnet: Egenkapital + Forpligtelser. Bør matche Aktiver i alt.
A27: Udvalgte balanceposter
A28: Varebeholdninger | B28: ='balance_raw_27528406'!$F$19 | C28: ='balance_raw_27528406'!$E$19 | D28: ='balance_raw_27528406'!$D$19 | F28: fsa:Inventories (eller fsa:ManufacturedGoodsAndGoodsForResale hvis total mangler).
A29: Tilgodehavender fra salg | B29: ='balance_raw_27528406'!$F$20 | C29: ='balance_raw_27528406'!$E$20 | D29: ='balance_raw_27528406'!$D$20 | F29: fsa:ShorttermTradeReceivables. Kortfristede tilgodehavender fra kunder.
A30: Kortfristede gældsforpligtelser | B30: ='balance_raw_27528406'!$F$57 | C30: ='balance_raw_27528406'!$E$57 | D30: ='balance_raw_27528406'!$D$57 | F30: fsa:ShorttermLiabilitiesOtherThanProvisions. Gæld der forfalder inden for 1 år.
A32: Rentabilitet
A33: Afkastningsgrad, % | B33: =IFERROR((B13+B14)/B21*100,"") | C33: =IFERROR((C13+C14)/C21*100,"") | D33: =IFERROR((D13+D14)/D21*100,"")
A34: Overskudsgrad, % | B34: =IFERROR((B13+B14)/B5*100,"") | C34: =IFERROR((C13+C14)/C5*100,"") | D34: =IFERROR((D13+D14)/D5*100,"")
A35: Aktivernes omsætningshastighed, gange | B35: =IFERROR(B5/B21,"") | C35: =IFERROR(C5/C21,"") | D35: =IFERROR(D5/D21,"")
A36: Gældsrente, % | B36: =IFERROR(-B15*100/B24,"") | C36: =IFERROR(-C15*100/C24,"") | D36: =IFERROR(-D15*100/D24,"")
A37: Egenkapitalens forrentning, % | B37: =IFERROR(B16/B23*100,"") | C37: =IFERROR(C16/C23*100,"") | D37: =IFERROR(D16/D23*100,"")
A38: Gearing, gange | B38: =IFERROR(B24/B23,"") | C38: =IFERROR(C24/C23,"") | D38: =IFERROR(D24/D23,"")
A40: Indekstal for indtjeningsevne (2023=100)
A41: Nettoomsætning | B41: =IFERROR(B5/$D5*100,"") | C41: =IFERROR(C5/$D5*100,"") | D41: =IFERROR(D5/$D5*100,"")
A42: Produktionsomkostninger | B42: =IFERROR(B6/$D6*100,"") | C42: =IFERROR(C6/$D6*100,"") | D42: =IFERROR(D6/$D6*100,"")
A43: Udviklingsomkostninger | B43: =IFERROR(B8/$D8*100,"") | C43: =IFERROR(C8/$D8*100,"") | D43: =IFERROR(D8/$D8*100,"")
A44: Salgs- og distributionsomk. | B44: =IFERROR(B9/$D9*100,"") | C44: =IFERROR(C9/$D9*100,"") | D44: =IFERROR(D9/$D9*100,"")
A45: Administrationsomk. | B45: =IFERROR(B10/$D10*100,"") | C45: =IFERROR(C10/$D10*100,"") | D45: =IFERROR(D10/$D10*100,"")
A46: Andre driftsomkostninger | B46: =IFERROR(B12/$D12*100,"") | C46: =IFERROR(C12/$D12*100,"") | D46: =IFERROR(D12/$D12*100,"")
A48: Indekstal for kapitaltilpasningsevne (2023=100)
A49: Nettoomsætning | B49: =IFERROR(B5*100/$D5,"") | C49: =IFERROR(C5*100/$D5,"") | D49: =IFERROR(D5*100/$D5,"")
A50: Anlægsaktiver | B50: =IFERROR(B19*100/$D19,"") | C50: =IFERROR(C19*100/$D19,"") | D50: =IFERROR(D19*100/$D19,"")
A51: Varebeholdninger | B51: =IFERROR(B28*100/$D28,"") | C51: =IFERROR(C28*100/$D28,"") | D51: =IFERROR(D28*100/$D28,"")
A52: Tilgodehavender fra salg | B52: =IFERROR(B29*100/$D29,"") | C52: =IFERROR(C29*100/$D29,"") | D52: =IFERROR(D29*100/$D29,"")
A54: Soliditet og likviditet
A55: Soliditetsgrad, % | B55: =IFERROR(B23*100/B21,"") | C55: =IFERROR(C23*100/C21,"") | D55: =IFERROR(D23*100/D21,"")
A56: Gældsandel, % | B56: =IFERROR(B24*100/B21,"") | C56: =IFERROR(C24*100/C21,"") | D56: =IFERROR(D24*100/D21,"")
A57: Likviditetsgrad, % | B57: =IFERROR(B20*100/B30,"") | C57: =IFERROR(C20*100/C30,"") | D57: =IFERROR(D20*100/D30,"")
A59: Kilde: Bearbejdet uddrag af årsrapporter for 2023-2025. Alle dataceller er live formler der peger på res_raw / balance_raw.
A61: Krydstjek mod rådata (tolerance: 1 t.kr.)
A62: Aktiver i alt = fsa:Assets | B62: =IF('balance_raw_27528406'!$F$31="","—",IF(ABS(B21-'balance_raw_27528406'!$F$31)<=1,"✓ OK","❌ "&TEXT(B21-'balance_raw_27528406'!$F$31,"+#,##0;-#,##0")&" t.kr.")) | C62: =IF('balance_raw_27528406'!$E$31="","—",IF(ABS(C21-'balance_raw_27528406'!$E$31)<=1,"✓ OK","❌ "&TEXT(C21-'balance_raw_27528406'!$E$31,"+#,##0;-#,##0")&" t.kr.")) | D62: =IF('balance_raw_27528406'!$D$31="","—",IF(ABS(D21-'balance_raw_27528406'!$D$31)<=1,"✓ OK","❌ "&TEXT(D21-'balance_raw_27528406'!$D$31,"+#,##0;-#,##0")&" t.kr.")) | F62: Verificerer at sum(Anlæg+Omsætning) matcher Assets-totalen.
A63: Passiver i alt = fsa:LiabilitiesAndEquity | B63: =IF('balance_raw_27528406'!$F$59="","—",IF(ABS(B25-'balance_raw_27528406'!$F$59)<=1,"✓ OK","❌ "&TEXT(B25-'balance_raw_27528406'!$F$59,"+#,##0;-#,##0")&" t.kr.")) | C63: =IF('balance_raw_27528406'!$E$59="","—",IF(ABS(C25-'balance_raw_27528406'!$E$59)<=1,"✓ OK","❌ "&TEXT(C25-'balance_raw_27528406'!$E$59,"+#,##0;-#,##0")&" t.kr.")) | D63: =IF('balance_raw_27528406'!$D$59="","—",IF(ABS(D25-'balance_raw_27528406'!$D$59)<=1,"✓ OK","❌ "&TEXT(D25-'balance_raw_27528406'!$D$59,"+#,##0;-#,##0")&" t.kr.")) | F63: Verificerer at sum(EK+Forpligtelser) matcher Passiver-totalen.
A64: Aktiver i alt = Passiver i alt | B64: =IF(ABS(B21-B25)<=1,"✓ OK","❌ "&TEXT(B21-B25,"+#,##0;-#,##0")&" t.kr.") | C64: =IF(ABS(C21-C25)<=1,"✓ OK","❌ "&TEXT(C21-C25,"+#,##0;-#,##0")&" t.kr.") | D64: =IF(ABS(D21-D25)<=1,"✓ OK","❌ "&TEXT(D21-D25,"+#,##0;-#,##0")&" t.kr.") | F64: Balance-identitet på arket selv. Skal altid være 0 differance.
A65: Bruttoresultat (beregnet) = fsa:GrossResult | B65: =IF('res_raw_27528406'!$F$4="","—",IF(ABS(B7-'res_raw_27528406'!$F$4)<=1,"✓ OK","❌ "&TEXT(B7-'res_raw_27528406'!$F$4,"+#,##0;-#,##0")&" t.kr.")) | C65: =IF('res_raw_27528406'!$E$4="","—",IF(ABS(C7-'res_raw_27528406'!$E$4)<=1,"✓ OK","❌ "&TEXT(C7-'res_raw_27528406'!$E$4,"+#,##0;-#,##0")&" t.kr.")) | D65: =IF('res_raw_27528406'!$D$4="","—",IF(ABS(D7-'res_raw_27528406'!$D$4)<=1,"✓ OK","❌ "&TEXT(D7-'res_raw_27528406'!$D$4,"+#,##0;-#,##0")&" t.kr.")) | F65: Hvis Nettoomsætning eller omkostninger mangler, vil sumberegnet bruttoresultat afvige.
A66: EBIT (beregnet) = fsa:ProfitLossFromOrdinaryOperatingActivities | B66: =IF('res_raw_27528406'!$F$13="","—",IF(ABS(B13-'res_raw_27528406'!$F$13)<=1,"✓ OK","❌ "&TEXT(B13-'res_raw_27528406'!$F$13,"+#,##0;-#,##0")&" t.kr.")) | C66: =IF('res_raw_27528406'!$E$13="","—",IF(ABS(C13-'res_raw_27528406'!$E$13)<=1,"✓ OK","❌ "&TEXT(C13-'res_raw_27528406'!$E$13,"+#,##0;-#,##0")&" t.kr.")) | D66: =IF('res_raw_27528406'!$D$13="","—",IF(ABS(D13-'res_raw_27528406'!$D$13)<=1,"✓ OK","❌ "&TEXT(D13-'res_raw_27528406'!$D$13,"+#,##0;-#,##0")&" t.kr.")) | F66: Verificerer at sumberegnet EBIT matcher det rapporterede.
A67: EBT (beregnet) = fsa:ProfitLossFromOrdinaryActivitiesBeforeTax | B67: =IF('res_raw_27528406'!$F$18="","—",IF(ABS(B16-'res_raw_27528406'!$F$18)<=1,"✓ OK","❌ "&TEXT(B16-'res_raw_27528406'!$F$18,"+#,##0;-#,##0")&" t.kr.")) | C67: =IF('res_raw_27528406'!$E$18="","—",IF(ABS(C16-'res_raw_27528406'!$E$18)<=1,"✓ OK","❌ "&TEXT(C16-'res_raw_27528406'!$E$18,"+#,##0;-#,##0")&" t.kr.")) | D67: =IF('res_raw_27528406'!$D$18="","—",IF(ABS(D16-'res_raw_27528406'!$D$18)<=1,"✓ OK","❌ "&TEXT(D16-'res_raw_27528406'!$D$18,"+#,##0;-#,##0")&" t.kr.")) | F67: Verificerer at sumberegnet resultat før skat matcher det rapporterede.

Sheet Noter_info
A1: Matas A/S (CVR 27528406) — Ukendte XBRL-felter — disse er noter og ikke en del af hoved-regnskabet
A2: Kategori | B2: Dansk navn | C2: XBRL feltnavn | D2: 2021 t.kr. | E2: 2022 t.kr. | F2: 2023 t.kr. | G2: 2024 t.kr. | H2: 2025 t.kr. | I2: Forklaring
A3: Øvrige (ukendt) | B3: ifrs-full:AdjustmentsForFinanceCosts | C3: ifrs-full:AdjustmentsForFinanceCosts | D3: 45200 | E3: 37900 | F3: 45900 | G3: 144000 | H3: 183000 | I3: Ingen forklaring tilgængelig.
A4: Øvrige (ukendt) | B4: ifrs-full:AdjustmentsForFinanceIncome | C4: ifrs-full:AdjustmentsForFinanceIncome | D4: 17500 | E4: 5300 | F4: 500 | G4: 12000 | H4: 1000 | I4: Ingen forklaring tilgængelig.
A5: Øvrige (ukendt) | B5: ifrs-full:AdjustmentsForUndistributedProfitsOfAssociates | C5: ifrs-full:AdjustmentsForUndistributedProfitsOfAssociates | D5: 700 | E5: -4600 | F5: -4900 | G5: 1000 | H5: 1000 | I5: Ingen forklaring tilgængelig.
A6: Øvrige (ukendt) | B6: ifrs-full:ComputerSoftware | C6: ifrs-full:ComputerSoftware | G6: 258000 | H6: 253000 | I6: Ingen forklaring tilgængelig.
A7: Øvrige (ukendt) | B7: ifrs-full:DividendsRecognisedAsDistributionsToOwnersPerShare | C7: ifrs-full:DividendsRecognisedAsDistributionsToOwnersPerShare | F7: 0 | G7: 0 | I7: Ingen forklaring tilgængelig.
A8: Øvrige (ukendt) | B8: ifrs-full:ProceedsFromExerciseOfOptions | C8: ifrs-full:ProceedsFromExerciseOfOptions | G8: 0 | H8: 10000 | I8: Ingen forklaring tilgængelig.
A9: Øvrige (ukendt) | B9: ifrs-full:ReserveOfExchangeDifferencesOnTranslation | C9: ifrs-full:ReserveOfExchangeDifferencesOnTranslation | D9: 300 | E9: 300 | F9: 300 | G9: 17000 | H9: 45000 | I9: Ingen forklaring tilgængelig.
