Workbook

Sheet Overblik
A1: royaluni — Regnskabsanalyse – Resultatopgørelse & Balance (t.kr.)
H2: Indekstal (2021=100)
A3: Resultatopgørelse t.kr. | B3: 2021 | C3: 2022 | D3: 2023 | E3: 2024 | F3: 2025 | H3: 2021 | I3: 2022 | J3: 2023 | K3: 2024 | L3: 2025
A4: Nettoomsætning | B4: ='res_raw'!$B$2 | C4: ='res_raw'!$C$2 | D4: ='res_raw'!$D$2 | E4: ='res_raw'!$E$2 | F4: ='res_raw'!$F$2 | H4: =IFERROR(B4/$B$4*100,"") | I4: =IFERROR(C4/$B$4*100,"") | J4: =IFERROR(D4/$B$4*100,"") | K4: =IFERROR(E4/$B$4*100,"") | L4: =IFERROR(F4/$B$4*100,"")
A5: Produktionsomkostninger | B5: ='res_raw'!$B$3 | C5: ='res_raw'!$C$3 | D5: ='res_raw'!$D$3 | E5: ='res_raw'!$E$3 | F5: ='res_raw'!$F$3 | H5: =IFERROR(B5/$B$5*100,"") | I5: =IFERROR(C5/$B$5*100,"") | J5: =IFERROR(D5/$B$5*100,"") | K5: =IFERROR(E5/$B$5*100,"") | L5: =IFERROR(F5/$B$5*100,"")
A6: Bruttoresultat | B6: ='res_raw'!$B$4 | C6: ='res_raw'!$C$4 | D6: ='res_raw'!$D$4 | E6: ='res_raw'!$E$4 | F6: ='res_raw'!$F$4 | H6: =IFERROR(B6/$B$6*100,"") | I6: =IFERROR(C6/$B$6*100,"") | J6: =IFERROR(D6/$B$6*100,"") | K6: =IFERROR(E6/$B$6*100,"") | L6: =IFERROR(F6/$B$6*100,"")
A7: Udviklingsomkostninger | B7: ='res_raw'!$B$5 | C7: ='res_raw'!$C$5 | D7: ='res_raw'!$D$5 | E7: ='res_raw'!$E$5 | F7: ='res_raw'!$F$5 | H7: =IFERROR(B7/$B$7*100,"") | I7: =IFERROR(C7/$B$7*100,"") | J7: =IFERROR(D7/$B$7*100,"") | K7: =IFERROR(E7/$B$7*100,"") | L7: =IFERROR(F7/$B$7*100,"")
A8: Salgs- og distributionsomkostninger | B8: ='res_raw'!$B$6 | C8: ='res_raw'!$C$6 | D8: ='res_raw'!$D$6 | E8: ='res_raw'!$E$6 | F8: ='res_raw'!$F$6 | H8: =IFERROR(B8/$B$8*100,"") | I8: =IFERROR(C8/$B$8*100,"") | J8: =IFERROR(D8/$B$8*100,"") | K8: =IFERROR(E8/$B$8*100,"") | L8: =IFERROR(F8/$B$8*100,"")
A9: Administrationsomkostninger | B9: ='res_raw'!$B$7 | C9: ='res_raw'!$C$7 | D9: ='res_raw'!$D$7 | E9: ='res_raw'!$E$7 | F9: ='res_raw'!$F$7 | H9: =IFERROR(B9/$B$9*100,"") | I9: =IFERROR(C9/$B$9*100,"") | J9: =IFERROR(D9/$B$9*100,"") | K9: =IFERROR(E9/$B$9*100,"") | L9: =IFERROR(F9/$B$9*100,"")
A10: Andre driftsindtægter | B10: ='res_raw'!$B$8 | C10: ='res_raw'!$C$8 | D10: ='res_raw'!$D$8 | E10: ='res_raw'!$E$8 | F10: ='res_raw'!$F$8 | H10: =IFERROR(B10/$B$10*100,"") | I10: =IFERROR(C10/$B$10*100,"") | J10: =IFERROR(D10/$B$10*100,"") | K10: =IFERROR(E10/$B$10*100,"") | L10: =IFERROR(F10/$B$10*100,"")
A11: Andre driftsomkostninger | B11: ='res_raw'!$B$9 | C11: ='res_raw'!$C$9 | D11: ='res_raw'!$D$9 | E11: ='res_raw'!$E$9 | F11: ='res_raw'!$F$9 | H11: =IFERROR(B11/$B$11*100,"") | I11: =IFERROR(C11/$B$11*100,"") | J11: =IFERROR(D11/$B$11*100,"") | K11: =IFERROR(E11/$B$11*100,"") | L11: =IFERROR(F11/$B$11*100,"")
A12: Resultat af primær drift | B12: ='res_raw'!$B$10 | C12: ='res_raw'!$C$10 | D12: ='res_raw'!$D$10 | E12: ='res_raw'!$E$10 | F12: ='res_raw'!$F$10 | H12: =IFERROR(B12/$B$12*100,"") | I12: =IFERROR(C12/$B$12*100,"") | J12: =IFERROR(D12/$B$12*100,"") | K12: =IFERROR(E12/$B$12*100,"") | L12: =IFERROR(F12/$B$12*100,"")
A13: Indtægter af kapitalandele, dattervirksomheder | B13: ='res_raw'!$B$11 | C13: ='res_raw'!$C$11 | D13: ='res_raw'!$D$11 | E13: ='res_raw'!$E$11 | F13: ='res_raw'!$F$11 | H13: =IFERROR(B13/$B$13*100,"") | I13: =IFERROR(C13/$B$13*100,"") | J13: =IFERROR(D13/$B$13*100,"") | K13: =IFERROR(E13/$B$13*100,"") | L13: =IFERROR(F13/$B$13*100,"")
A14: Finansielle indtægter | B14: ='res_raw'!$B$12 | C14: ='res_raw'!$C$12 | D14: ='res_raw'!$D$12 | E14: ='res_raw'!$E$12 | F14: ='res_raw'!$F$12 | H14: =IFERROR(B14/$B$14*100,"") | I14: =IFERROR(C14/$B$14*100,"") | J14: =IFERROR(D14/$B$14*100,"") | K14: =IFERROR(E14/$B$14*100,"") | L14: =IFERROR(F14/$B$14*100,"")
A15: Finansielle omkostninger | B15: ='res_raw'!$B$13 | C15: ='res_raw'!$C$13 | D15: ='res_raw'!$D$13 | E15: ='res_raw'!$E$13 | F15: ='res_raw'!$F$13 | H15: =IFERROR(B15/$B$15*100,"") | I15: =IFERROR(C15/$B$15*100,"") | J15: =IFERROR(D15/$B$15*100,"") | K15: =IFERROR(E15/$B$15*100,"") | L15: =IFERROR(F15/$B$15*100,"")
A16: Finansielle poster, netto | B16: ='res_raw'!$B$14 | C16: ='res_raw'!$C$14 | D16: ='res_raw'!$D$14 | E16: ='res_raw'!$E$14 | F16: ='res_raw'!$F$14 | H16: =IFERROR(B16/$B$16*100,"") | I16: =IFERROR(C16/$B$16*100,"") | J16: =IFERROR(D16/$B$16*100,"") | K16: =IFERROR(E16/$B$16*100,"") | L16: =IFERROR(F16/$B$16*100,"")
A17: Resultat før skat | B17: ='res_raw'!$B$15 | C17: ='res_raw'!$C$15 | D17: ='res_raw'!$D$15 | E17: ='res_raw'!$E$15 | F17: ='res_raw'!$F$15 | H17: =IFERROR(B17/$B$17*100,"") | I17: =IFERROR(C17/$B$17*100,"") | J17: =IFERROR(D17/$B$17*100,"") | K17: =IFERROR(E17/$B$17*100,"") | L17: =IFERROR(F17/$B$17*100,"")
A18: Skat af årets resultat | B18: ='res_raw'!$B$16 | C18: ='res_raw'!$C$16 | D18: ='res_raw'!$D$16 | E18: ='res_raw'!$E$16 | F18: ='res_raw'!$F$16 | H18: =IFERROR(B18/$B$18*100,"") | I18: =IFERROR(C18/$B$18*100,"") | J18: =IFERROR(D18/$B$18*100,"") | K18: =IFERROR(E18/$B$18*100,"") | L18: =IFERROR(F18/$B$18*100,"")
A19: Årets resultat | B19: ='res_raw'!$B$17 | C19: ='res_raw'!$C$17 | D19: ='res_raw'!$D$17 | E19: ='res_raw'!$E$17 | F19: ='res_raw'!$F$17 | H19: =IFERROR(B19/$B$19*100,"") | I19: =IFERROR(C19/$B$19*100,"") | J19: =IFERROR(D19/$B$19*100,"") | K19: =IFERROR(E19/$B$19*100,"") | L19: =IFERROR(F19/$B$19*100,"")
A21: AKTIVER t.kr. | B21: 2021 | C21: 2022 | D21: 2023 | E21: 2024 | F21: 2025 | H21: 2021 | I21: 2022 | J21: 2023 | K21: 2024 | L21: 2025
A22: Udviklingsprojekter | B22: ='balance_raw'!$B$2 | C22: ='balance_raw'!$C$2 | D22: ='balance_raw'!$D$2 | E22: ='balance_raw'!$E$2 | F22: ='balance_raw'!$F$2 | H22: =IFERROR(B22/$B$22*100,"") | I22: =IFERROR(C22/$B$22*100,"") | J22: =IFERROR(D22/$B$22*100,"") | K22: =IFERROR(E22/$B$22*100,"") | L22: =IFERROR(F22/$B$22*100,"")
A23: Patenter, varemærker mv. | B23: ='balance_raw'!$B$3 | C23: ='balance_raw'!$C$3 | D23: ='balance_raw'!$D$3 | E23: ='balance_raw'!$E$3 | F23: ='balance_raw'!$F$3 | H23: =IFERROR(B23/$B$23*100,"") | I23: =IFERROR(C23/$B$23*100,"") | J23: =IFERROR(D23/$B$23*100,"") | K23: =IFERROR(E23/$B$23*100,"") | L23: =IFERROR(F23/$B$23*100,"")
A24: Goodwill | B24: ='balance_raw'!$B$4 | C24: ='balance_raw'!$C$4 | D24: ='balance_raw'!$D$4 | E24: ='balance_raw'!$E$4 | F24: ='balance_raw'!$F$4 | H24: =IFERROR(B24/$B$24*100,"") | I24: =IFERROR(C24/$B$24*100,"") | J24: =IFERROR(D24/$B$24*100,"") | K24: =IFERROR(E24/$B$24*100,"") | L24: =IFERROR(F24/$B$24*100,"")
A25: Immaterielle anlægsaktiver | B25: ='balance_raw'!$B$5 | C25: ='balance_raw'!$C$5 | D25: ='balance_raw'!$D$5 | E25: ='balance_raw'!$E$5 | F25: ='balance_raw'!$F$5 | H25: =IFERROR(B25/$B$25*100,"") | I25: =IFERROR(C25/$B$25*100,"") | J25: =IFERROR(D25/$B$25*100,"") | K25: =IFERROR(E25/$B$25*100,"") | L25: =IFERROR(F25/$B$25*100,"")
A26: Materielle anlægsaktiver | B26: ='balance_raw'!$B$6 | C26: ='balance_raw'!$C$6 | D26: ='balance_raw'!$D$6 | E26: ='balance_raw'!$E$6 | F26: ='balance_raw'!$F$6 | H26: =IFERROR(B26/$B$26*100,"") | I26: =IFERROR(C26/$B$26*100,"") | J26: =IFERROR(D26/$B$26*100,"") | K26: =IFERROR(E26/$B$26*100,"") | L26: =IFERROR(F26/$B$26*100,"")
A27: Kapitalandele, dattervirksomheder | B27: ='balance_raw'!$B$7 | C27: ='balance_raw'!$C$7 | D27: ='balance_raw'!$D$7 | E27: ='balance_raw'!$E$7 | F27: ='balance_raw'!$F$7 | H27: =IFERROR(B27/$B$27*100,"") | I27: =IFERROR(C27/$B$27*100,"") | J27: =IFERROR(D27/$B$27*100,"") | K27: =IFERROR(E27/$B$27*100,"") | L27: =IFERROR(F27/$B$27*100,"")
A28: Deposita | B28: ='balance_raw'!$B$8 | C28: ='balance_raw'!$C$8 | D28: ='balance_raw'!$D$8 | E28: ='balance_raw'!$E$8 | F28: ='balance_raw'!$F$8 | H28: =IFERROR(B28/$B$28*100,"") | I28: =IFERROR(C28/$B$28*100,"") | J28: =IFERROR(D28/$B$28*100,"") | K28: =IFERROR(E28/$B$28*100,"") | L28: =IFERROR(F28/$B$28*100,"")
A29: Finansielle anlægsaktiver | B29: ='balance_raw'!$B$9 | C29: ='balance_raw'!$C$9 | D29: ='balance_raw'!$D$9 | E29: ='balance_raw'!$E$9 | F29: ='balance_raw'!$F$9 | H29: =IFERROR(B29/$B$29*100,"") | I29: =IFERROR(C29/$B$29*100,"") | J29: =IFERROR(D29/$B$29*100,"") | K29: =IFERROR(E29/$B$29*100,"") | L29: =IFERROR(F29/$B$29*100,"")
A30: Anlægsaktiver | B30: ='balance_raw'!$B$10 | C30: ='balance_raw'!$C$10 | D30: ='balance_raw'!$D$10 | E30: ='balance_raw'!$E$10 | F30: ='balance_raw'!$F$10 | H30: =IFERROR(B30/$B$30*100,"") | I30: =IFERROR(C30/$B$30*100,"") | J30: =IFERROR(D30/$B$30*100,"") | K30: =IFERROR(E30/$B$30*100,"") | L30: =IFERROR(F30/$B$30*100,"")
A31: Varebeholdninger | B31: ='balance_raw'!$B$11 | C31: ='balance_raw'!$C$11 | D31: ='balance_raw'!$D$11 | E31: ='balance_raw'!$E$11 | F31: ='balance_raw'!$F$11 | H31: =IFERROR(B31/$B$31*100,"") | I31: =IFERROR(C31/$B$31*100,"") | J31: =IFERROR(D31/$B$31*100,"") | K31: =IFERROR(E31/$B$31*100,"") | L31: =IFERROR(F31/$B$31*100,"")
A32: Tilgodehavender fra salg og tjenesteydelser | B32: ='balance_raw'!$B$12 | C32: ='balance_raw'!$C$12 | D32: ='balance_raw'!$D$12 | E32: ='balance_raw'!$E$12 | F32: ='balance_raw'!$F$12 | H32: =IFERROR(B32/$B$32*100,"") | I32: =IFERROR(C32/$B$32*100,"") | J32: =IFERROR(D32/$B$32*100,"") | K32: =IFERROR(E32/$B$32*100,"") | L32: =IFERROR(F32/$B$32*100,"")
A33: Tilgodehavender hos tilknyttede virksomheder | B33: ='balance_raw'!$B$13 | C33: ='balance_raw'!$C$13 | D33: ='balance_raw'!$D$13 | E33: ='balance_raw'!$E$13 | F33: ='balance_raw'!$F$13 | H33: =IFERROR(B33/$B$33*100,"") | I33: =IFERROR(C33/$B$33*100,"") | J33: =IFERROR(D33/$B$33*100,"") | K33: =IFERROR(E33/$B$33*100,"") | L33: =IFERROR(F33/$B$33*100,"")
A34: Andre tilgodehavender | B34: ='balance_raw'!$B$14 | C34: ='balance_raw'!$C$14 | D34: ='balance_raw'!$D$14 | E34: ='balance_raw'!$E$14 | F34: ='balance_raw'!$F$14 | H34: =IFERROR(B34/$B$34*100,"") | I34: =IFERROR(C34/$B$34*100,"") | J34: =IFERROR(D34/$B$34*100,"") | K34: =IFERROR(E34/$B$34*100,"") | L34: =IFERROR(F34/$B$34*100,"")
A35: Periodeafgrænsningsposter (aktiver) | B35: ='balance_raw'!$B$15 | C35: ='balance_raw'!$C$15 | D35: ='balance_raw'!$D$15 | E35: ='balance_raw'!$E$15 | F35: ='balance_raw'!$F$15 | H35: =IFERROR(B35/$B$35*100,"") | I35: =IFERROR(C35/$B$35*100,"") | J35: =IFERROR(D35/$B$35*100,"") | K35: =IFERROR(E35/$B$35*100,"") | L35: =IFERROR(F35/$B$35*100,"")
A36: Udskudt skatteaktiv | B36: ='balance_raw'!$B$16 | C36: ='balance_raw'!$C$16 | D36: ='balance_raw'!$D$16 | E36: ='balance_raw'!$E$16 | F36: ='balance_raw'!$F$16 | H36: =IFERROR(B36/$B$36*100,"") | I36: =IFERROR(C36/$B$36*100,"") | J36: =IFERROR(D36/$B$36*100,"") | K36: =IFERROR(E36/$B$36*100,"") | L36: =IFERROR(F36/$B$36*100,"")
A37: Tilgodehavende skat hos tilknyttede virksomheder | B37: ='balance_raw'!$B$17 | C37: ='balance_raw'!$C$17 | D37: ='balance_raw'!$D$17 | E37: ='balance_raw'!$E$17 | F37: ='balance_raw'!$F$17 | H37: =IFERROR(B37/$B$37*100,"") | I37: =IFERROR(C37/$B$37*100,"") | J37: =IFERROR(D37/$B$37*100,"") | K37: =IFERROR(E37/$B$37*100,"") | L37: =IFERROR(F37/$B$37*100,"")
A38: Kortfristede skattetilgodehavender | B38: ='balance_raw'!$B$18 | C38: ='balance_raw'!$C$18 | D38: ='balance_raw'!$D$18 | E38: ='balance_raw'!$E$18 | F38: ='balance_raw'!$F$18 | H38: =IFERROR(B38/$B$38*100,"") | I38: =IFERROR(C38/$B$38*100,"") | J38: =IFERROR(D38/$B$38*100,"") | K38: =IFERROR(E38/$B$38*100,"") | L38: =IFERROR(F38/$B$38*100,"")
A39: Tilgodehavender | B39: ='balance_raw'!$B$19 | C39: ='balance_raw'!$C$19 | D39: ='balance_raw'!$D$19 | E39: ='balance_raw'!$E$19 | F39: ='balance_raw'!$F$19 | H39: =IFERROR(B39/$B$39*100,"") | I39: =IFERROR(C39/$B$39*100,"") | J39: =IFERROR(D39/$B$39*100,"") | K39: =IFERROR(E39/$B$39*100,"") | L39: =IFERROR(F39/$B$39*100,"")
A40: Værdipapirer | B40: ='balance_raw'!$B$20 | C40: ='balance_raw'!$C$20 | D40: ='balance_raw'!$D$20 | E40: ='balance_raw'!$E$20 | F40: ='balance_raw'!$F$20 | H40: =IFERROR(B40/$B$40*100,"") | I40: =IFERROR(C40/$B$40*100,"") | J40: =IFERROR(D40/$B$40*100,"") | K40: =IFERROR(E40/$B$40*100,"") | L40: =IFERROR(F40/$B$40*100,"")
A41: Likvide beholdninger | B41: ='balance_raw'!$B$21 | C41: ='balance_raw'!$C$21 | D41: ='balance_raw'!$D$21 | E41: ='balance_raw'!$E$21 | F41: ='balance_raw'!$F$21 | H41: =IFERROR(B41/$B$41*100,"") | I41: =IFERROR(C41/$B$41*100,"") | J41: =IFERROR(D41/$B$41*100,"") | K41: =IFERROR(E41/$B$41*100,"") | L41: =IFERROR(F41/$B$41*100,"")
A42: Omsætningsaktiver | B42: ='balance_raw'!$B$22 | C42: ='balance_raw'!$C$22 | D42: ='balance_raw'!$D$22 | E42: ='balance_raw'!$E$22 | F42: ='balance_raw'!$F$22 | H42: =IFERROR(B42/$B$42*100,"") | I42: =IFERROR(C42/$B$42*100,"") | J42: =IFERROR(D42/$B$42*100,"") | K42: =IFERROR(E42/$B$42*100,"") | L42: =IFERROR(F42/$B$42*100,"")
A43: Aktiver | B43: ='balance_raw'!$B$23 | C43: ='balance_raw'!$C$23 | D43: ='balance_raw'!$D$23 | E43: ='balance_raw'!$E$23 | F43: ='balance_raw'!$F$23 | H43: =IFERROR(B43/$B$43*100,"") | I43: =IFERROR(C43/$B$43*100,"") | J43: =IFERROR(D43/$B$43*100,"") | K43: =IFERROR(E43/$B$43*100,"") | L43: =IFERROR(F43/$B$43*100,"")
A45: PASSIVER t.kr. | B45: 2021 | C45: 2022 | D45: 2023 | E45: 2024 | F45: 2025 | H45: 2021 | I45: 2022 | J45: 2023 | K45: 2024 | L45: 2025
A46: Selskabskapital | B46: ='balance_raw'!$B$24 | C46: ='balance_raw'!$C$24 | D46: ='balance_raw'!$D$24 | E46: ='balance_raw'!$E$24 | F46: ='balance_raw'!$F$24 | H46: =IFERROR(B46/$B$46*100,"") | I46: =IFERROR(C46/$B$46*100,"") | J46: =IFERROR(D46/$B$46*100,"") | K46: =IFERROR(E46/$B$46*100,"") | L46: =IFERROR(F46/$B$46*100,"")
A47: Reserve for nettoopskrivning (indre værdis metode) | B47: ='balance_raw'!$B$25 | C47: ='balance_raw'!$C$25 | D47: ='balance_raw'!$D$25 | E47: ='balance_raw'!$E$25 | F47: ='balance_raw'!$F$25 | H47: =IFERROR(B47/$B$47*100,"") | I47: =IFERROR(C47/$B$47*100,"") | J47: =IFERROR(D47/$B$47*100,"") | K47: =IFERROR(E47/$B$47*100,"") | L47: =IFERROR(F47/$B$47*100,"")
A48: Reserve for udviklingsomkostninger | B48: ='balance_raw'!$B$26 | C48: ='balance_raw'!$C$26 | D48: ='balance_raw'!$D$26 | E48: ='balance_raw'!$E$26 | F48: ='balance_raw'!$F$26 | H48: =IFERROR(B48/$B$48*100,"") | I48: =IFERROR(C48/$B$48*100,"") | J48: =IFERROR(D48/$B$48*100,"") | K48: =IFERROR(E48/$B$48*100,"") | L48: =IFERROR(F48/$B$48*100,"")
A49: Reserve for sikringstransaktioner | B49: ='balance_raw'!$B$27 | C49: ='balance_raw'!$C$27 | D49: ='balance_raw'!$D$27 | E49: ='balance_raw'!$E$27 | F49: ='balance_raw'!$F$27 | H49: =IFERROR(B49/$B$49*100,"") | I49: =IFERROR(C49/$B$49*100,"") | J49: =IFERROR(D49/$B$49*100,"") | K49: =IFERROR(E49/$B$49*100,"") | L49: =IFERROR(F49/$B$49*100,"")
A50: Andre reserver | B50: ='balance_raw'!$B$28 | C50: ='balance_raw'!$C$28 | D50: ='balance_raw'!$D$28 | E50: ='balance_raw'!$E$28 | F50: ='balance_raw'!$F$28 | H50: =IFERROR(B50/$B$50*100,"") | I50: =IFERROR(C50/$B$50*100,"") | J50: =IFERROR(D50/$B$50*100,"") | K50: =IFERROR(E50/$B$50*100,"") | L50: =IFERROR(F50/$B$50*100,"")
A51: Overført resultat | B51: ='balance_raw'!$B$29 | C51: ='balance_raw'!$C$29 | D51: ='balance_raw'!$D$29 | E51: ='balance_raw'!$E$29 | F51: ='balance_raw'!$F$29 | H51: =IFERROR(B51/$B$51*100,"") | I51: =IFERROR(C51/$B$51*100,"") | J51: =IFERROR(D51/$B$51*100,"") | K51: =IFERROR(E51/$B$51*100,"") | L51: =IFERROR(F51/$B$51*100,"")
A52: Egenkapital i alt | B52: ='balance_raw'!$B$30 | C52: ='balance_raw'!$C$30 | D52: ='balance_raw'!$D$30 | E52: ='balance_raw'!$E$30 | F52: ='balance_raw'!$F$30 | H52: =IFERROR(B52/$B$52*100,"") | I52: =IFERROR(C52/$B$52*100,"") | J52: =IFERROR(D52/$B$52*100,"") | K52: =IFERROR(E52/$B$52*100,"") | L52: =IFERROR(F52/$B$52*100,"")
A53: Hensættelse til udskudt skat | B53: ='balance_raw'!$B$31 | C53: ='balance_raw'!$C$31 | D53: ='balance_raw'!$D$31 | E53: ='balance_raw'!$E$31 | F53: ='balance_raw'!$F$31 | H53: =IFERROR(B53/$B$53*100,"") | I53: =IFERROR(C53/$B$53*100,"") | J53: =IFERROR(D53/$B$53*100,"") | K53: =IFERROR(E53/$B$53*100,"") | L53: =IFERROR(F53/$B$53*100,"")
A54: Hensatte forpligtelser | B54: ='balance_raw'!$B$32 | C54: ='balance_raw'!$C$32 | D54: ='balance_raw'!$D$32 | E54: ='balance_raw'!$E$32 | F54: ='balance_raw'!$F$32 | H54: =IFERROR(B54/$B$54*100,"") | I54: =IFERROR(C54/$B$54*100,"") | J54: =IFERROR(D54/$B$54*100,"") | K54: =IFERROR(E54/$B$54*100,"") | L54: =IFERROR(F54/$B$54*100,"")
A55: Ansvarlig lånekapital (langfristet) | B55: ='balance_raw'!$B$33 | C55: ='balance_raw'!$C$33 | D55: ='balance_raw'!$D$33 | E55: ='balance_raw'!$E$33 | F55: ='balance_raw'!$F$33 | H55: =IFERROR(B55/$B$55*100,"") | I55: =IFERROR(C55/$B$55*100,"") | J55: =IFERROR(D55/$B$55*100,"") | K55: =IFERROR(E55/$B$55*100,"") | L55: =IFERROR(F55/$B$55*100,"")
A56: Langfristede lån | B56: ='balance_raw'!$B$34 | C56: ='balance_raw'!$C$34 | D56: ='balance_raw'!$D$34 | E56: ='balance_raw'!$E$34 | F56: ='balance_raw'!$F$34 | H56: =IFERROR(B56/$B$56*100,"") | I56: =IFERROR(C56/$B$56*100,"") | J56: =IFERROR(D56/$B$56*100,"") | K56: =IFERROR(E56/$B$56*100,"") | L56: =IFERROR(F56/$B$56*100,"")
A57: Leasingforpligtelser (langfristet) | B57: ='balance_raw'!$B$35 | C57: ='balance_raw'!$C$35 | D57: ='balance_raw'!$D$35 | E57: ='balance_raw'!$E$35 | F57: ='balance_raw'!$F$35 | H57: =IFERROR(B57/$B$57*100,"") | I57: =IFERROR(C57/$B$57*100,"") | J57: =IFERROR(D57/$B$57*100,"") | K57: =IFERROR(E57/$B$57*100,"") | L57: =IFERROR(F57/$B$57*100,"")
A58: Anden gæld (langfristet) | B58: ='balance_raw'!$B$36 | C58: ='balance_raw'!$C$36 | D58: ='balance_raw'!$D$36 | E58: ='balance_raw'!$E$36 | F58: ='balance_raw'!$F$36 | H58: =IFERROR(B58/$B$58*100,"") | I58: =IFERROR(C58/$B$58*100,"") | J58: =IFERROR(D58/$B$58*100,"") | K58: =IFERROR(E58/$B$58*100,"") | L58: =IFERROR(F58/$B$58*100,"")
A59: Langfristede gældsforpligtelser | B59: ='balance_raw'!$B$37 | C59: ='balance_raw'!$C$37 | D59: ='balance_raw'!$D$37 | E59: ='balance_raw'!$E$37 | F59: ='balance_raw'!$F$37 | H59: =IFERROR(B59/$B$59*100,"") | I59: =IFERROR(C59/$B$59*100,"") | J59: =IFERROR(D59/$B$59*100,"") | K59: =IFERROR(E59/$B$59*100,"") | L59: =IFERROR(F59/$B$59*100,"")
A60: Ansvarlig lånekapital (kortfristet) | B60: ='balance_raw'!$B$38 | C60: ='balance_raw'!$C$38 | D60: ='balance_raw'!$D$38 | E60: ='balance_raw'!$E$38 | F60: ='balance_raw'!$F$38 | H60: =IFERROR(B60/$B$60*100,"") | I60: =IFERROR(C60/$B$60*100,"") | J60: =IFERROR(D60/$B$60*100,"") | K60: =IFERROR(E60/$B$60*100,"") | L60: =IFERROR(F60/$B$60*100,"")
A61: Kortfristet del af langfristede gældsforpligtelser | B61: ='balance_raw'!$B$39 | C61: ='balance_raw'!$C$39 | D61: ='balance_raw'!$D$39 | E61: ='balance_raw'!$E$39 | F61: ='balance_raw'!$F$39 | H61: =IFERROR(B61/$B$61*100,"") | I61: =IFERROR(C61/$B$61*100,"") | J61: =IFERROR(D61/$B$61*100,"") | K61: =IFERROR(E61/$B$61*100,"") | L61: =IFERROR(F61/$B$61*100,"")
A62: Kreditinstitutter | B62: ='balance_raw'!$B$40 | C62: ='balance_raw'!$C$40 | D62: ='balance_raw'!$D$40 | E62: ='balance_raw'!$E$40 | F62: ='balance_raw'!$F$40 | H62: =IFERROR(B62/$B$62*100,"") | I62: =IFERROR(C62/$B$62*100,"") | J62: =IFERROR(D62/$B$62*100,"") | K62: =IFERROR(E62/$B$62*100,"") | L62: =IFERROR(F62/$B$62*100,"")
A63: Leasingforpligtelser (kortfristet) | B63: ='balance_raw'!$B$41 | C63: ='balance_raw'!$C$41 | D63: ='balance_raw'!$D$41 | E63: ='balance_raw'!$E$41 | F63: ='balance_raw'!$F$41 | H63: =IFERROR(B63/$B$63*100,"") | I63: =IFERROR(C63/$B$63*100,"") | J63: =IFERROR(D63/$B$63*100,"") | K63: =IFERROR(E63/$B$63*100,"") | L63: =IFERROR(F63/$B$63*100,"")
A64: Leverandører af varer og tjenesteydelser | B64: ='balance_raw'!$B$42 | C64: ='balance_raw'!$C$42 | D64: ='balance_raw'!$D$42 | E64: ='balance_raw'!$E$42 | F64: ='balance_raw'!$F$42 | H64: =IFERROR(B64/$B$64*100,"") | I64: =IFERROR(C64/$B$64*100,"") | J64: =IFERROR(D64/$B$64*100,"") | K64: =IFERROR(E64/$B$64*100,"") | L64: =IFERROR(F64/$B$64*100,"")
A65: Gæld til tilknyttede virksomheder | B65: ='balance_raw'!$B$43 | C65: ='balance_raw'!$C$43 | D65: ='balance_raw'!$D$43 | E65: ='balance_raw'!$E$43 | F65: ='balance_raw'!$F$43 | H65: =IFERROR(B65/$B$65*100,"") | I65: =IFERROR(C65/$B$65*100,"") | J65: =IFERROR(D65/$B$65*100,"") | K65: =IFERROR(E65/$B$65*100,"") | L65: =IFERROR(F65/$B$65*100,"")
A66: Gæld til selskabsdeltagere og ledelse | B66: ='balance_raw'!$B$44 | C66: ='balance_raw'!$C$44 | D66: ='balance_raw'!$D$44 | E66: ='balance_raw'!$E$44 | F66: ='balance_raw'!$F$44 | H66: =IFERROR(B66/$B$66*100,"") | I66: =IFERROR(C66/$B$66*100,"") | J66: =IFERROR(D66/$B$66*100,"") | K66: =IFERROR(E66/$B$66*100,"") | L66: =IFERROR(F66/$B$66*100,"")
A67: Selskabsskat | B67: ='balance_raw'!$B$45 | C67: ='balance_raw'!$C$45 | D67: ='balance_raw'!$D$45 | E67: ='balance_raw'!$E$45 | F67: ='balance_raw'!$F$45 | H67: =IFERROR(B67/$B$67*100,"") | I67: =IFERROR(C67/$B$67*100,"") | J67: =IFERROR(D67/$B$67*100,"") | K67: =IFERROR(E67/$B$67*100,"") | L67: =IFERROR(F67/$B$67*100,"")
A68: Gæld til tilknyttede virksomheder vedr. selskabsskat | B68: ='balance_raw'!$B$46 | C68: ='balance_raw'!$C$46 | D68: ='balance_raw'!$D$46 | E68: ='balance_raw'!$E$46 | F68: ='balance_raw'!$F$46 | H68: =IFERROR(B68/$B$68*100,"") | I68: =IFERROR(C68/$B$68*100,"") | J68: =IFERROR(D68/$B$68*100,"") | K68: =IFERROR(E68/$B$68*100,"") | L68: =IFERROR(F68/$B$68*100,"")
A69: Anden gæld (kortfristet) | B69: ='balance_raw'!$B$47 | C69: ='balance_raw'!$C$47 | D69: ='balance_raw'!$D$47 | E69: ='balance_raw'!$E$47 | F69: ='balance_raw'!$F$47 | H69: =IFERROR(B69/$B$69*100,"") | I69: =IFERROR(C69/$B$69*100,"") | J69: =IFERROR(D69/$B$69*100,"") | K69: =IFERROR(E69/$B$69*100,"") | L69: =IFERROR(F69/$B$69*100,"")
A70: Periodeafgrænsningsposter (passiver) | B70: ='balance_raw'!$B$48 | C70: ='balance_raw'!$C$48 | D70: ='balance_raw'!$D$48 | E70: ='balance_raw'!$E$48 | F70: ='balance_raw'!$F$48 | H70: =IFERROR(B70/$B$70*100,"") | I70: =IFERROR(C70/$B$70*100,"") | J70: =IFERROR(D70/$B$70*100,"") | K70: =IFERROR(E70/$B$70*100,"") | L70: =IFERROR(F70/$B$70*100,"")
A71: Kortfristede gældsforpligtelser | B71: ='balance_raw'!$B$49 | C71: ='balance_raw'!$C$49 | D71: ='balance_raw'!$D$49 | E71: ='balance_raw'!$E$49 | F71: ='balance_raw'!$F$49 | H71: =IFERROR(B71/$B$71*100,"") | I71: =IFERROR(C71/$B$71*100,"") | J71: =IFERROR(D71/$B$71*100,"") | K71: =IFERROR(E71/$B$71*100,"") | L71: =IFERROR(F71/$B$71*100,"")
A72: Gældsforpligtelser | B72: ='balance_raw'!$B$50 | C72: ='balance_raw'!$C$50 | D72: ='balance_raw'!$D$50 | E72: ='balance_raw'!$E$50 | F72: ='balance_raw'!$F$50 | H72: =IFERROR(B72/$B$72*100,"") | I72: =IFERROR(C72/$B$72*100,"") | J72: =IFERROR(D72/$B$72*100,"") | K72: =IFERROR(E72/$B$72*100,"") | L72: =IFERROR(F72/$B$72*100,"")
A73: Passiver | B73: ='balance_raw'!$B$51 | C73: ='balance_raw'!$C$51 | D73: ='balance_raw'!$D$51 | E73: ='balance_raw'!$E$51 | F73: ='balance_raw'!$F$51 | H73: =IFERROR(B73/$B$73*100,"") | I73: =IFERROR(C73/$B$73*100,"") | J73: =IFERROR(D73/$B$73*100,"") | K73: =IFERROR(E73/$B$73*100,"") | L73: =IFERROR(F73/$B$73*100,"")
A75: NØGLEOPLYSNINGER | B75: 2021 | C75: 2022 | D75: 2023 | E75: 2024 | F75: 2025
A76: Gns. antal medarbejdere | B76: ='res_raw'!$B$18 | C76: ='res_raw'!$C$18 | D76: ='res_raw'!$D$18 | E76: ='res_raw'!$E$18 | F76: ='res_raw'!$F$18 | H76: =IFERROR(B76/$B$76*100,"") | I76: =IFERROR(C76/$B$76*100,"") | J76: =IFERROR(D76/$B$76*100,"") | K76: =IFERROR(E76/$B$76*100,"") | L76: =IFERROR(F76/$B$76*100,"")
A77: Investering i materielle anlægsaktiver | B77: ='res_raw'!$B$19 | C77: ='res_raw'!$C$19 | D77: ='res_raw'!$D$19 | E77: ='res_raw'!$E$19 | F77: ='res_raw'!$F$19 | H77: =IFERROR(B77/$B$77*100,"") | I77: =IFERROR(C77/$B$77*100,"") | J77: =IFERROR(D77/$B$77*100,"") | K77: =IFERROR(E77/$B$77*100,"") | L77: =IFERROR(F77/$B$77*100,"")
A79: NØGLETAL | B79: 2021 | C79: 2022 | D79: 2023 | E79: 2024 | F79: 2025
A80: Afkastningsgrad, % | B80: =IFERROR(($B$12+$B$14+$B$13)/$B$43*100,"") | C80: =IFERROR(($C$12+$C$14+$C$13)/$C$43*100,"") | D80: =IFERROR(($D$12+$D$14+$D$13)/$D$43*100,"") | E80: =IFERROR(($E$12+$E$14+$E$13)/$E$43*100,"") | F80: =IFERROR(($F$12+$F$14+$F$13)/$F$43*100,"")
A81: Overskudsgrad, % | B81: =IFERROR(($B$12+$B$14+$B$13)/$B$4*100,"") | C81: =IFERROR(($C$12+$C$14+$C$13)/$C$4*100,"") | D81: =IFERROR(($D$12+$D$14+$D$13)/$D$4*100,"") | E81: =IFERROR(($E$12+$E$14+$E$13)/$E$4*100,"") | F81: =IFERROR(($F$12+$F$14+$F$13)/$F$4*100,"")
A82: Aktivernes omsætningshastighed, gange | B82: =IFERROR($B$4/$B$43,"") | C82: =IFERROR($C$4/$C$43,"") | D82: =IFERROR($D$4/$D$43,"") | E82: =IFERROR($E$4/$E$43,"") | F82: =IFERROR($F$4/$F$43,"")
A83: Egenkapitalens forrentning, % | B83: =IFERROR($B$17/$B$52*100,"") | C83: =IFERROR($C$17/$C$52*100,"") | D83: =IFERROR($D$17/$D$52*100,"") | E83: =IFERROR($E$17/$E$52*100,"") | F83: =IFERROR($F$17/$F$52*100,"")
A84: Gældsrente, % | B84: =IFERROR($B$15/($B$73-$B$52)*100,"") | C84: =IFERROR($C$15/($C$73-$C$52)*100,"") | D84: =IFERROR($D$15/($D$73-$D$52)*100,"") | E84: =IFERROR($E$15/($E$73-$E$52)*100,"") | F84: =IFERROR($F$15/($F$73-$F$52)*100,"")
A85: Soliditetsgrad, % | B85: =IFERROR($B$52/$B$43*100,"") | C85: =IFERROR($C$52/$C$43*100,"") | D85: =IFERROR($D$52/$D$43*100,"") | E85: =IFERROR($E$52/$E$43*100,"") | F85: =IFERROR($F$52/$F$43*100,"")
A86: Gearing | B86: =IFERROR(($B$73-$B$52)/$B$52,"") | C86: =IFERROR(($C$73-$C$52)/$C$52,"") | D86: =IFERROR(($D$73-$D$52)/$D$52,"") | E86: =IFERROR(($E$73-$E$52)/$E$52,"") | F86: =IFERROR(($F$73-$F$52)/$F$52,"")
A87: Likviditetsgrad, % | B87: =IFERROR($B$42/$B$71*100,"") | C87: =IFERROR($C$42/$C$71*100,"") | D87: =IFERROR($D$42/$D$71*100,"") | E87: =IFERROR($E$42/$E$71*100,"") | F87: =IFERROR($F$42/$F$71*100,"")
A88: Rentemarginal, % | B88: =IFERROR(B80-B84,"") | C88: =IFERROR(C80-C84,"") | D88: =IFERROR(D80-D84,"") | E88: =IFERROR(E80-E84,"") | F88: =IFERROR(F80-F84,"")
A89: Gældsandel, % | B89: =IFERROR(($B$73-$B$52)/$B$43*100,"") | C89: =IFERROR(($C$73-$C$52)/$C$43*100,"") | D89: =IFERROR(($D$73-$D$52)/$D$43*100,"") | E89: =IFERROR(($E$73-$E$52)/$E$43*100,"") | F89: =IFERROR(($F$73-$F$52)/$F$43*100,"")
A90: Kapitalbindingsgrad, % | B90: =IFERROR($B$30/($B$52+$B$59)*100,"") | C90: =IFERROR($C$30/($C$52+$C$59)*100,"") | D90: =IFERROR($D$30/($D$52+$D$59)*100,"") | E90: =IFERROR($E$30/($E$52+$E$59)*100,"") | F90: =IFERROR($F$30/($F$52+$F$59)*100,"")
A92: PENGESTRØMSOPGØRELSE t.kr.
A93: Pengestrømme fra driftsaktivitet | B93: ='pengestrom_raw'!$B$2 | C93: ='pengestrom_raw'!$C$2 | D93: ='pengestrom_raw'!$D$2 | E93: ='pengestrom_raw'!$E$2 | F93: ='pengestrom_raw'!$F$2
A94: Pengestrømme fra investeringsaktivitet | B94: ='pengestrom_raw'!$B$3 | C94: ='pengestrom_raw'!$C$3 | D94: ='pengestrom_raw'!$D$3 | E94: ='pengestrom_raw'!$E$3 | F94: ='pengestrom_raw'!$F$3
A95: Pengestrømme fra finansieringsaktivitet | B95: ='pengestrom_raw'!$B$4 | C95: ='pengestrom_raw'!$C$4 | D95: ='pengestrom_raw'!$D$4 | E95: ='pengestrom_raw'!$E$4 | F95: ='pengestrom_raw'!$F$4
A96: Årets pengestrøm (rapporteret) | B96: ='pengestrom_raw'!$B$5 | C96: ='pengestrom_raw'!$C$5 | D96: ='pengestrom_raw'!$D$5 | E96: ='pengestrom_raw'!$E$5 | F96: ='pengestrom_raw'!$F$5
A97: Krydstjek: drift + inv. + fin. = årets pengestrøm | B97: =IF(ABS(('pengestrom_raw'!$B$2+'pengestrom_raw'!$B$3+'pengestrom_raw'!$B$4)-'pengestrom_raw'!$B$5)<=2,"✓","⚠ "&TEXT(('pengestrom_raw'!$B$2+'pengestrom_raw'!$B$3+'pengestrom_raw'!$B$4)-'pengestrom_raw'!$B$5,"+#,##0;-#,##0")) | C97: =IF(ABS(('pengestrom_raw'!$C$2+'pengestrom_raw'!$C$3+'pengestrom_raw'!$C$4)-'pengestrom_raw'!$C$5)<=2,"✓","⚠ "&TEXT(('pengestrom_raw'!$C$2+'pengestrom_raw'!$C$3+'pengestrom_raw'!$C$4)-'pengestrom_raw'!$C$5,"+#,##0;-#,##0")) | D97: =IF(ABS(('pengestrom_raw'!$D$2+'pengestrom_raw'!$D$3+'pengestrom_raw'!$D$4)-'pengestrom_raw'!$D$5)<=2,"✓","⚠ "&TEXT(('pengestrom_raw'!$D$2+'pengestrom_raw'!$D$3+'pengestrom_raw'!$D$4)-'pengestrom_raw'!$D$5,"+#,##0;-#,##0")) | E97: =IF(ABS(('pengestrom_raw'!$E$2+'pengestrom_raw'!$E$3+'pengestrom_raw'!$E$4)-'pengestrom_raw'!$E$5)<=2,"✓","⚠ "&TEXT(('pengestrom_raw'!$E$2+'pengestrom_raw'!$E$3+'pengestrom_raw'!$E$4)-'pengestrom_raw'!$E$5,"+#,##0;-#,##0")) | F97: =IF(ABS(('pengestrom_raw'!$F$2+'pengestrom_raw'!$F$3+'pengestrom_raw'!$F$4)-'pengestrom_raw'!$F$5)<=2,"✓","⚠ "&TEXT(('pengestrom_raw'!$F$2+'pengestrom_raw'!$F$3+'pengestrom_raw'!$F$4)-'pengestrom_raw'!$F$5,"+#,##0;-#,##0"))

Sheet res_raw
A1: royaluni — Resultatopgørelse & nøgleoplysninger (t.kr.) | B1: 2021 | C1: 2022 | D1: 2023 | E1: 2024 | F1: 2025
A2: Nettoomsætning | B2: 8746000 | C2: 11487000 | D2: 12927000 | E2: 15036000 | F2: 15723000
A3: Produktionsomkostninger | B3: 4490000 | C3: 6618000 | D3: 7533000 | E3: 8648000 | F3: 8957000
A4: Bruttoresultat | B4: 4256000 | C4: 4869000 | D4: 5394000 | E4: 6388000 | F4: 6766000
A5: Udviklingsomkostninger
A6: Salgs- og distributionsomkostninger | B6: 2189000 | C6: 2926000 | D6: 3158000 | E6: 3626000 | F6: 3638000
A7: Administrationsomkostninger | B7: 415000 | C7: 427000 | D7: 628000 | E7: 794000 | F7: 926000
A8: Andre driftsindtægter | D8: 30000 | E8: 0
A9: Andre driftsomkostninger
A10: Resultat af primær drift | B10: 1652000 | C10: 1516000 | D10: 1638000 | E10: 1968000 | F10: 2202000
A11: Indtægter af kapitalandele, dattervirksomheder | B11: 37000 | C11: 2000 | D11: 18000 | E11: -6000 | F11: 18000
A12: Finansielle indtægter | B12: 7000 | C12: 10000 | D12: 10000 | E12: 229000 | F12: 26000
A13: Finansielle omkostninger | B13: 49000 | C13: 103000 | D13: 260000 | E13: 326000 | F13: 280000
A14: Finansielle poster, netto
A15: Resultat før skat | B15: 1647000 | C15: 1785000 | D15: 1406000 | E15: 1865000 | F15: 1966000
A16: Skat af årets resultat | B16: 349000 | C16: 294000 | D16: 311000 | E16: 401000 | F16: 406000
A17: Årets resultat | B17: 1298000 | C17: 1491000 | D17: 1095000 | E17: 1464000 | F17: 1560000
A18: Gns. antal medarbejdere
A19: Investering i materielle anlægsaktiver | B19: 426000 | C19: 475000 | D19: 602000 | E19: 761000 | F19: 797000

Sheet balance_raw
A1: royaluni — Balance (t.kr.) | B1: 2021 | C1: 2022 | D1: 2023 | E1: 2024 | F1: 2025
A2: Udviklingsprojekter
A3: Patenter, varemærker mv.
A4: Goodwill | F4: 5161000
A5: Immaterielle anlægsaktiver | B5: 5861000 | C5: 7558000 | D5: 9469000 | E5: 9513000 | F5: 4485000
A6: Materielle anlægsaktiver | B6: 2734000 | C6: 3680000 | D6: 4662000 | E6: 4749000 | F6: 5120000
A7: Kapitalandele, dattervirksomheder | B7: 153000 | C7: 99000 | D7: 34000 | E7: 17000
A8: Deposita | B8: 23000 | C8: 79000 | D8: 89000 | E8: 73000 | F8: 65000
A9: Finansielle anlægsaktiver
A10: Anlægsaktiver | B10: 8771000 | C10: 11416000 | D10: 14254000 | E10: 14352000 | F10: 14831000
A11: Varebeholdninger | B11: 780000 | C11: 1213000 | D11: 1401000 | E11: 1340000 | F11: 1286000
A12: Tilgodehavender fra salg og tjenesteydelser | B12: 1188000 | C12: 1500000 | D12: 1901000 | E12: 1944000 | F12: 1918000
A13: Tilgodehavender hos tilknyttede virksomheder
A14: Andre tilgodehavender
A15: Periodeafgrænsningsposter (aktiver) | B15: 89000 | C15: 131000 | D15: 165000 | E15: 147000 | F15: 152000
A16: Udskudt skatteaktiv
A17: Tilgodehavende skat hos tilknyttede virksomheder
A18: Kortfristede skattetilgodehavender
A19: Tilgodehavender
A20: Værdipapirer
A21: Likvide beholdninger | B21: 86000 | C21: 214000 | D21: 57000 | E21: 103000 | F21: 82000
A22: Omsætningsaktiver | B22: 2143000 | C22: 3058000 | D22: 3524000 | E22: 3534000 | F22: 3438000
A23: Aktiver | B23: 10914000 | C23: 14474000 | D23: 17778000 | E23: 17886000 | F23: 18269000
A24: Selskabskapital | B24: 98000 | C24: 100000 | D24: 100000 | E24: 100000 | F24: 100000
A25: Reserve for nettoopskrivning (indre værdis metode)
A26: Reserve for udviklingsomkostninger
A27: Reserve for sikringstransaktioner
A28: Andre reserver | B28: 719000 | C28: 1567000 | D28: 1519000 | E28: 1407000 | F28: 1416000
A29: Overført resultat | B29: 1805000 | C29: 2763000 | D29: 4129000 | E29: 4148000 | F29: 4394000
A30: Egenkapital i alt | B30: 3330000 | C30: 5158000 | D30: 5748000 | E30: 6408000 | F30: 6713000
A31: Hensættelse til udskudt skat | B31: 747000 | C31: 1011000 | D31: 1281000 | E31: 1271000 | F31: 1277000
A32: Hensatte forpligtelser | B32: 11000 | C32: 11000 | D32: 11000 | E32: 11000 | F32: 1277000
A33: Ansvarlig lånekapital (langfristet)
A34: Langfristede lån
A35: Leasingforpligtelser (langfristet)
A36: Anden gæld (langfristet) | B36: 1003000 | C36: 1009000 | D36: 998000 | E36: 986000 | F36: 1009000
A37: Langfristede gældsforpligtelser | B37: 3771000 | C37: 4706000 | D37: 6786000 | E37: 5968000 | F37: 6710000
A38: Ansvarlig lånekapital (kortfristet)
A39: Kortfristet del af langfristede gældsforpligtelser
A40: Kreditinstitutter | B40: 14000 | C40: 2000 | D40: 11000 | E40: 19000
A41: Leasingforpligtelser (kortfristet)
A42: Leverandører af varer og tjenesteydelser | B42: 1721000 | C42: 1934000 | D42: 2425000 | E42: 2532000 | F42: 2482000
A43: Gæld til tilknyttede virksomheder
A44: Gæld til selskabsdeltagere og ledelse
A45: Selskabsskat
A46: Gæld til tilknyttede virksomheder vedr. selskabsskat
A47: Anden gæld (kortfristet) | B47: 1427000 | C47: 1669000 | D47: 1785000 | E47: 1806000 | F47: 1950000
A48: Periodeafgrænsningsposter (passiver)
A49: Kortfristede gældsforpligtelser | B49: 3801000 | C49: 4610000 | D49: 5244000 | E49: 5510000 | F49: 4846000
A50: Gældsforpligtelser | B50: 7572000 | C50: 9316000 | D50: 12030000 | E50: 11478000 | F50: 11556000
A51: Passiver | B51: 10914000 | C51: 14474000 | D51: 17778000 | E51: 17886000 | F51: 18269000

Sheet pengestrom_raw
A1: royaluni — Pengestrømsopgørelse (t.kr.) | B1: 2021 | C1: 2022 | D1: 2023 | E1: 2024 | F1: 2025
A2: Pengestrømme fra driftsaktivitet | B2: 1753000 | C2: 1135000 | D2: 1777000 | E2: 2189000 | F2: 2385000
A3: Pengestrømme fra investeringsaktivitet | B3: -1604000 | C3: -744000 | D3: -2925000 | E3: -651000 | F3: -954000
A4: Pengestrømme fra finansieringsaktivitet | B4: -146000 | C4: -252000 | D4: 998000 | E4: -1491000 | F4: -1454000
A5: Årets pengestrøm

Sheet Simpel_funktion
A1: royaluni — Regnskabs- og nøgletal — funktionsopdelt
A3: Beløb i 1.000 kr. | B3: 2025 | C3: 2024 | D3: 2023 | F3: Note / XBRL-felt
A4: Uddrag af resultatopgørelse
A5: Nettoomsætning | B5: ='res_raw'!$F$2 | C5: ='res_raw'!$E$2 | D5: ='res_raw'!$D$2 | F5: fsa:Revenue
A6: Produktionsomkostninger | B6: =-'res_raw'!$F$3 | C6: =-'res_raw'!$E$3 | D6: =-'res_raw'!$D$3 | F6: fsa:CostOfProduction (vises negativt). Materialer, lønninger, produktionsoverhead.
A7: Bruttoresultat | B7: =IF(ABS((SUM(B5:B6))-'res_raw'!$F$4)<=2,SUM(B5:B6),'res_raw'!$F$4) | C7: =IF(ABS((SUM(C5:C6))-'res_raw'!$E$4)<=2,SUM(C5:C6),'res_raw'!$E$4) | D7: =IF(ABS((SUM(D5:D6))-'res_raw'!$D$4)<=2,SUM(D5:D6),'res_raw'!$D$4) | F7: Beregnet: Nettoomsætning − Produktionsomkostninger. Matcher fsa:GrossResult. Er komponenterne ikke indberettet, vises rapporteret fsa:GrossResult direkte.
A8: Udviklingsomkostninger | B8: =-'res_raw'!$F$5 | C8: =-'res_raw'!$E$5 | D8: =-'res_raw'!$D$5 | F8: ifrs-full:ResearchAndDevelopmentExpense (vises negativt). Udviklingsomkostninger ført i resultatet (v15_21; B&O m.fl.).
A9: Salgs- og distributionsomk. | B9: =-'res_raw'!$F$6 | C9: =-'res_raw'!$E$6 | D9: =-'res_raw'!$D$6 | F9: fsa:DistributionCosts (vises negativt). Marketing, salg, distribution.
A10: Administrationsomkostninger mv. | B10: =-'res_raw'!$F$7 | C10: =-'res_raw'!$E$7 | D10: =-'res_raw'!$D$7 | F10: fsa:AdministrativeExpenses (vises negativt). Generel administration.
A11: Andre driftsindtægter | B11: ='res_raw'!$F$8 | C11: ='res_raw'!$E$8 | D11: ='res_raw'!$D$8 | F11: fsa:OtherOperatingIncome. Sekundære driftsindtægter (huslejeindtægter, off. tilskud, avancer mv.).
A12: Andre driftsomkostninger | B12: =-'res_raw'!$F$9 | C12: =-'res_raw'!$E$9 | D12: =-'res_raw'!$D$9 | F12: fsa:OtherOperatingExpenses (vises negativt). Sekundære driftsomkostninger.
A13: Resultat af primær drift | B13: =IF(ABS((SUM(B7:B12))-'res_raw'!$F$10)<=2,SUM(B7:B12),'res_raw'!$F$10) | C13: =IF(ABS((SUM(C7:C12))-'res_raw'!$E$10)<=2,SUM(C7:C12),'res_raw'!$E$10) | D13: =IF(ABS((SUM(D7:D12))-'res_raw'!$D$10)<=2,SUM(D7:D12),'res_raw'!$D$10) | F13: Beregnet: Bruttoresultat − Udviklingsomk. − Salgs/dist. − Administration + Andre driftsindt. − Andre driftsomk. EBIT.
A14: Finansielle indtægter mv. | B14: =N('res_raw'!$F$11)+N('res_raw'!$F$12) | C14: =N('res_raw'!$E$11)+N('res_raw'!$E$12) | D14: =N('res_raw'!$D$11)+N('res_raw'!$D$12) | F14: fsa:IncomeFromSubsidiaries + fsa:OtherFinanceIncome.
A15: Finansielle omkostninger mv. | B15: =-'res_raw'!$F$13 | C15: =-'res_raw'!$E$13 | D15: =-'res_raw'!$D$13 | F15: fsa:OtherFinanceExpenses (vises negativt). Renteomkostninger, kurstab.
A16: Resultat før skat | B16: =IF(ABS((SUM(B13:B15))-'res_raw'!$F$15)<=2,SUM(B13:B15),'res_raw'!$F$15) | C16: =IF(ABS((SUM(C13:C15))-'res_raw'!$E$15)<=2,SUM(C13:C15),'res_raw'!$E$15) | D16: =IF(ABS((SUM(D13:D15))-'res_raw'!$D$15)<=2,SUM(D13:D15),'res_raw'!$D$15) | F16: Beregnet: EBIT + Fin. indtægter + Fin. omk. EBT.
A18: Uddrag af balance
A19: Anlægsaktiver | B19: ='balance_raw'!$F$10 | C19: ='balance_raw'!$E$10 | D19: ='balance_raw'!$D$10 | F19: fsa:NoncurrentAssets. Materielle, immaterielle og finansielle anlægsaktiver.
A20: Omsætningsaktiver | B20: ='balance_raw'!$F$22 | C20: ='balance_raw'!$E$22 | D20: ='balance_raw'!$D$22 | F20: fsa:CurrentAssets. Varebeholdninger, tilgodehavender, likvider.
A21: Aktiver i alt | B21: =SUM(B19:B20) | C21: =SUM(C19:C20) | D21: =SUM(D19:D20) | F21: Beregnet: Anlægsaktiver + Omsætningsaktiver. Bør matche fsa:Assets.
A23: Egenkapital | B23: ='balance_raw'!$F$30 | C23: ='balance_raw'!$E$30 | D23: ='balance_raw'!$D$30 | F23: fsa:Equity. Selskabskapital, overført resultat, reserver.
A24: Forpligtelser | B24: ='balance_raw'!$F$51-'balance_raw'!$F$30 | C24: ='balance_raw'!$E$51-'balance_raw'!$E$30 | D24: ='balance_raw'!$D$51-'balance_raw'!$D$30 | F24: Beregnet: Passiver (fsa:LiabilitiesAndEquity) − Egenkapital. Hensættelser + kort- og langfristet gæld.
A25: Passiver i alt | B25: =SUM(B23:B24) | C25: =SUM(C23:C24) | D25: =SUM(D23:D24) | F25: Beregnet: Egenkapital + Forpligtelser. Bør matche Aktiver i alt.
A27: Udvalgte balanceposter
A28: Varebeholdninger | B28: ='balance_raw'!$F$11 | C28: ='balance_raw'!$E$11 | D28: ='balance_raw'!$D$11 | F28: fsa:Inventories (eller fsa:ManufacturedGoodsAndGoodsForResale hvis total mangler).
A29: Tilgodehavender fra salg | B29: ='balance_raw'!$F$12 | C29: ='balance_raw'!$E$12 | D29: ='balance_raw'!$D$12 | F29: fsa:ShorttermTradeReceivables. Kortfristede tilgodehavender fra kunder.
A30: Kortfristede gældsforpligtelser | B30: ='balance_raw'!$F$49 | C30: ='balance_raw'!$E$49 | D30: ='balance_raw'!$D$49 | F30: fsa:ShorttermLiabilitiesOtherThanProvisions. Gæld der forfalder inden for 1 år.
A32: Rentabilitet
A33: Afkastningsgrad, % | B33: =IFERROR((B13+B14)/B21*100,"") | C33: =IFERROR((C13+C14)/C21*100,"") | D33: =IFERROR((D13+D14)/D21*100,"")
A34: Overskudsgrad, % | B34: =IFERROR((B13+B14)/B5*100,"") | C34: =IFERROR((C13+C14)/C5*100,"") | D34: =IFERROR((D13+D14)/D5*100,"")
A35: Aktivernes omsætningshastighed, gange | B35: =IFERROR(B5/B21,"") | C35: =IFERROR(C5/C21,"") | D35: =IFERROR(D5/D21,"")
A36: Gældsrente, % | B36: =IFERROR(-B15*100/B24,"") | C36: =IFERROR(-C15*100/C24,"") | D36: =IFERROR(-D15*100/D24,"")
A37: Egenkapitalens forrentning, % | B37: =IFERROR(B16/B23*100,"") | C37: =IFERROR(C16/C23*100,"") | D37: =IFERROR(D16/D23*100,"")
A38: Gearing, gange | B38: =IFERROR(B24/B23,"") | C38: =IFERROR(C24/C23,"") | D38: =IFERROR(D24/D23,"")
A40: Indekstal for indtjeningsevne (2023=100)
A41: Nettoomsætning | B41: =IFERROR(B5/$D5*100,"") | C41: =IFERROR(C5/$D5*100,"") | D41: =IFERROR(D5/$D5*100,"")
A42: Produktionsomkostninger | B42: =IFERROR(B6/$D6*100,"") | C42: =IFERROR(C6/$D6*100,"") | D42: =IFERROR(D6/$D6*100,"")
A43: Udviklingsomkostninger | B43: =IFERROR(B8/$D8*100,"") | C43: =IFERROR(C8/$D8*100,"") | D43: =IFERROR(D8/$D8*100,"")
A44: Salgs- og distributionsomk. | B44: =IFERROR(B9/$D9*100,"") | C44: =IFERROR(C9/$D9*100,"") | D44: =IFERROR(D9/$D9*100,"")
A45: Administrationsomk. | B45: =IFERROR(B10/$D10*100,"") | C45: =IFERROR(C10/$D10*100,"") | D45: =IFERROR(D10/$D10*100,"")
A46: Andre driftsomkostninger | B46: =IFERROR(B12/$D12*100,"") | C46: =IFERROR(C12/$D12*100,"") | D46: =IFERROR(D12/$D12*100,"")
A48: Indekstal for kapitaltilpasningsevne (2023=100)
A49: Nettoomsætning | B49: =IFERROR(B5*100/$D5,"") | C49: =IFERROR(C5*100/$D5,"") | D49: =IFERROR(D5*100/$D5,"")
A50: Anlægsaktiver | B50: =IFERROR(B19*100/$D19,"") | C50: =IFERROR(C19*100/$D19,"") | D50: =IFERROR(D19*100/$D19,"")
A51: Varebeholdninger | B51: =IFERROR(B28*100/$D28,"") | C51: =IFERROR(C28*100/$D28,"") | D51: =IFERROR(D28*100/$D28,"")
A52: Tilgodehavender fra salg | B52: =IFERROR(B29*100/$D29,"") | C52: =IFERROR(C29*100/$D29,"") | D52: =IFERROR(D29*100/$D29,"")
A54: Soliditet og likviditet
A55: Soliditetsgrad, % | B55: =IFERROR(B23*100/B21,"") | C55: =IFERROR(C23*100/C21,"") | D55: =IFERROR(D23*100/D21,"")
A56: Gældsandel, % | B56: =IFERROR(B24*100/B21,"") | C56: =IFERROR(C24*100/C21,"") | D56: =IFERROR(D24*100/D21,"")
A57: Likviditetsgrad, % | B57: =IFERROR(B20*100/B30,"") | C57: =IFERROR(C20*100/C30,"") | D57: =IFERROR(D20*100/D30,"")
A59: Kilde: Bearbejdet uddrag af årsrapporter for 2023-2025. Alle dataceller er live formler der peger på res_raw / balance_raw.
A61: Krydstjek mod rådata (tolerance: 1 t.kr.)
A62: Aktiver i alt = fsa:Assets | B62: =IF('balance_raw'!$F$23="","—",IF(ABS(B21-'balance_raw'!$F$23)<=1,"✓ OK","❌ "&TEXT(B21-'balance_raw'!$F$23,"+#,##0;-#,##0")&" t.kr.")) | C62: =IF('balance_raw'!$E$23="","—",IF(ABS(C21-'balance_raw'!$E$23)<=1,"✓ OK","❌ "&TEXT(C21-'balance_raw'!$E$23,"+#,##0;-#,##0")&" t.kr.")) | D62: =IF('balance_raw'!$D$23="","—",IF(ABS(D21-'balance_raw'!$D$23)<=1,"✓ OK","❌ "&TEXT(D21-'balance_raw'!$D$23,"+#,##0;-#,##0")&" t.kr.")) | F62: Verificerer at sum(Anlæg+Omsætning) matcher Assets-totalen.
A63: Passiver i alt = fsa:LiabilitiesAndEquity | B63: =IF('balance_raw'!$F$51="","—",IF(ABS(B25-'balance_raw'!$F$51)<=1,"✓ OK","❌ "&TEXT(B25-'balance_raw'!$F$51,"+#,##0;-#,##0")&" t.kr.")) | C63: =IF('balance_raw'!$E$51="","—",IF(ABS(C25-'balance_raw'!$E$51)<=1,"✓ OK","❌ "&TEXT(C25-'balance_raw'!$E$51,"+#,##0;-#,##0")&" t.kr.")) | D63: =IF('balance_raw'!$D$51="","—",IF(ABS(D25-'balance_raw'!$D$51)<=1,"✓ OK","❌ "&TEXT(D25-'balance_raw'!$D$51,"+#,##0;-#,##0")&" t.kr.")) | F63: Verificerer at sum(EK+Forpligtelser) matcher Passiver-totalen.
A64: Aktiver i alt = Passiver i alt | B64: =IF(ABS(B21-B25)<=1,"✓ OK","❌ "&TEXT(B21-B25,"+#,##0;-#,##0")&" t.kr.") | C64: =IF(ABS(C21-C25)<=1,"✓ OK","❌ "&TEXT(C21-C25,"+#,##0;-#,##0")&" t.kr.") | D64: =IF(ABS(D21-D25)<=1,"✓ OK","❌ "&TEXT(D21-D25,"+#,##0;-#,##0")&" t.kr.") | F64: Balance-identitet på arket selv. Skal altid være 0 differance.
A65: Bruttoresultat (beregnet) = fsa:GrossResult | B65: =IF('res_raw'!$F$4="","—",IF(ABS(B7-'res_raw'!$F$4)<=1,"✓ OK","❌ "&TEXT(B7-'res_raw'!$F$4,"+#,##0;-#,##0")&" t.kr.")) | C65: =IF('res_raw'!$E$4="","—",IF(ABS(C7-'res_raw'!$E$4)<=1,"✓ OK","❌ "&TEXT(C7-'res_raw'!$E$4,"+#,##0;-#,##0")&" t.kr.")) | D65: =IF('res_raw'!$D$4="","—",IF(ABS(D7-'res_raw'!$D$4)<=1,"✓ OK","❌ "&TEXT(D7-'res_raw'!$D$4,"+#,##0;-#,##0")&" t.kr.")) | F65: Hvis Nettoomsætning eller omkostninger mangler, vil sumberegnet bruttoresultat afvige.
A66: EBIT (beregnet) = fsa:ProfitLossFromOrdinaryOperatingActivities | B66: =IF('res_raw'!$F$10="","—",IF(ABS(B13-'res_raw'!$F$10)<=1,"✓ OK","❌ "&TEXT(B13-'res_raw'!$F$10,"+#,##0;-#,##0")&" t.kr.")) | C66: =IF('res_raw'!$E$10="","—",IF(ABS(C13-'res_raw'!$E$10)<=1,"✓ OK","❌ "&TEXT(C13-'res_raw'!$E$10,"+#,##0;-#,##0")&" t.kr.")) | D66: =IF('res_raw'!$D$10="","—",IF(ABS(D13-'res_raw'!$D$10)<=1,"✓ OK","❌ "&TEXT(D13-'res_raw'!$D$10,"+#,##0;-#,##0")&" t.kr.")) | F66: Verificerer at sumberegnet EBIT matcher det rapporterede.
A67: EBT (beregnet) = fsa:ProfitLossFromOrdinaryActivitiesBeforeTax | B67: =IF('res_raw'!$F$15="","—",IF(ABS(B16-'res_raw'!$F$15)<=1,"✓ OK","❌ "&TEXT(B16-'res_raw'!$F$15,"+#,##0;-#,##0")&" t.kr.")) | C67: =IF('res_raw'!$E$15="","—",IF(ABS(C16-'res_raw'!$E$15)<=1,"✓ OK","❌ "&TEXT(C16-'res_raw'!$E$15,"+#,##0;-#,##0")&" t.kr.")) | D67: =IF('res_raw'!$D$15="","—",IF(ABS(D16-'res_raw'!$D$15)<=1,"✓ OK","❌ "&TEXT(D16-'res_raw'!$D$15,"+#,##0;-#,##0")&" t.kr.")) | F67: Verificerer at sumberegnet resultat før skat matcher det rapporterede.
