Workbook

Sheet Overblik_61056416
A1: Carlsberg A/S (CVR 61056416) — Regnskabsanalyse – Resultatopgørelse & Balance (t.kr.) · Klasse D · Revision
H2: Indekstal (2021=100)
A3: Resultatopgørelse t.kr. | B3: 2021 | C3: 2022 | D3: 2023 | E3: 2024 | F3: 2025 | H3: 2021 | I3: 2022 | J3: 2023 | K3: 2024 | L3: 2025
A4: Nettoomsætning | B4: ='res_raw_61056416'!$B$2 | C4: ='res_raw_61056416'!$C$2 | D4: ='res_raw_61056416'!$D$2 | E4: ='res_raw_61056416'!$E$2 | F4: ='res_raw_61056416'!$F$2 | H4: =IFERROR(B4/$B$4*100,"") | I4: =IFERROR(C4/$B$4*100,"") | J4: =IFERROR(D4/$B$4*100,"") | K4: =IFERROR(E4/$B$4*100,"") | L4: =IFERROR(F4/$B$4*100,"")
A5: Produktionsomkostninger | B5: ='res_raw_61056416'!$B$3 | C5: ='res_raw_61056416'!$C$3 | D5: ='res_raw_61056416'!$D$3 | E5: ='res_raw_61056416'!$E$3 | F5: ='res_raw_61056416'!$F$3 | H5: =IFERROR(B5/$B$5*100,"") | I5: =IFERROR(C5/$B$5*100,"") | J5: =IFERROR(D5/$B$5*100,"") | K5: =IFERROR(E5/$B$5*100,"") | L5: =IFERROR(F5/$B$5*100,"")
A6: Bruttoresultat | B6: ='res_raw_61056416'!$B$4 | C6: ='res_raw_61056416'!$C$4 | D6: ='res_raw_61056416'!$D$4 | E6: ='res_raw_61056416'!$E$4 | F6: ='res_raw_61056416'!$F$4 | H6: =IFERROR(B6/$B$6*100,"") | I6: =IFERROR(C6/$B$6*100,"") | J6: =IFERROR(D6/$B$6*100,"") | K6: =IFERROR(E6/$B$6*100,"") | L6: =IFERROR(F6/$B$6*100,"")
A7: Udviklingsomkostninger | B7: ='res_raw_61056416'!$B$5 | C7: ='res_raw_61056416'!$C$5 | D7: ='res_raw_61056416'!$D$5 | E7: ='res_raw_61056416'!$E$5 | F7: ='res_raw_61056416'!$F$5 | H7: =IFERROR(B7/$B$7*100,"") | I7: =IFERROR(C7/$B$7*100,"") | J7: =IFERROR(D7/$B$7*100,"") | K7: =IFERROR(E7/$B$7*100,"") | L7: =IFERROR(F7/$B$7*100,"")
A8: Salgs- og distributionsomkostninger | B8: ='res_raw_61056416'!$B$6 | C8: ='res_raw_61056416'!$C$6 | D8: ='res_raw_61056416'!$D$6 | E8: ='res_raw_61056416'!$E$6 | F8: ='res_raw_61056416'!$F$6 | H8: =IFERROR(B8/$B$8*100,"") | I8: =IFERROR(C8/$B$8*100,"") | J8: =IFERROR(D8/$B$8*100,"") | K8: =IFERROR(E8/$B$8*100,"") | L8: =IFERROR(F8/$B$8*100,"")
A9: Administrationsomkostninger | B9: ='res_raw_61056416'!$B$7 | C9: ='res_raw_61056416'!$C$7 | D9: ='res_raw_61056416'!$D$7 | E9: ='res_raw_61056416'!$E$7 | F9: ='res_raw_61056416'!$F$7 | H9: =IFERROR(B9/$B$9*100,"") | I9: =IFERROR(C9/$B$9*100,"") | J9: =IFERROR(D9/$B$9*100,"") | K9: =IFERROR(E9/$B$9*100,"") | L9: =IFERROR(F9/$B$9*100,"")
A10: Andre driftsindtægter | B10: ='res_raw_61056416'!$B$8 | C10: ='res_raw_61056416'!$C$8 | D10: ='res_raw_61056416'!$D$8 | E10: ='res_raw_61056416'!$E$8 | F10: ='res_raw_61056416'!$F$8 | H10: =IFERROR(B10/$B$10*100,"") | I10: =IFERROR(C10/$B$10*100,"") | J10: =IFERROR(D10/$B$10*100,"") | K10: =IFERROR(E10/$B$10*100,"") | L10: =IFERROR(F10/$B$10*100,"")
A11: Andre driftsomkostninger | B11: ='res_raw_61056416'!$B$9 | C11: ='res_raw_61056416'!$C$9 | D11: ='res_raw_61056416'!$D$9 | E11: ='res_raw_61056416'!$E$9 | F11: ='res_raw_61056416'!$F$9 | H11: =IFERROR(B11/$B$11*100,"") | I11: =IFERROR(C11/$B$11*100,"") | J11: =IFERROR(D11/$B$11*100,"") | K11: =IFERROR(E11/$B$11*100,"") | L11: =IFERROR(F11/$B$11*100,"")
A12: Resultat af primær drift | B12: ='res_raw_61056416'!$B$10 | C12: ='res_raw_61056416'!$C$10 | D12: ='res_raw_61056416'!$D$10 | E12: ='res_raw_61056416'!$E$10 | F12: ='res_raw_61056416'!$F$10 | H12: =IFERROR(B12/$B$12*100,"") | I12: =IFERROR(C12/$B$12*100,"") | J12: =IFERROR(D12/$B$12*100,"") | K12: =IFERROR(E12/$B$12*100,"") | L12: =IFERROR(F12/$B$12*100,"")
A13: Indtægter af kapitalandele, dattervirksomheder | B13: ='res_raw_61056416'!$B$11 | C13: ='res_raw_61056416'!$C$11 | D13: ='res_raw_61056416'!$D$11 | E13: ='res_raw_61056416'!$E$11 | F13: ='res_raw_61056416'!$F$11 | H13: =IFERROR(B13/$B$13*100,"") | I13: =IFERROR(C13/$B$13*100,"") | J13: =IFERROR(D13/$B$13*100,"") | K13: =IFERROR(E13/$B$13*100,"") | L13: =IFERROR(F13/$B$13*100,"")
A14: Finansielle indtægter | B14: ='res_raw_61056416'!$B$12 | C14: ='res_raw_61056416'!$C$12 | D14: ='res_raw_61056416'!$D$12 | E14: ='res_raw_61056416'!$E$12 | F14: ='res_raw_61056416'!$F$12 | H14: =IFERROR(B14/$B$14*100,"") | I14: =IFERROR(C14/$B$14*100,"") | J14: =IFERROR(D14/$B$14*100,"") | K14: =IFERROR(E14/$B$14*100,"") | L14: =IFERROR(F14/$B$14*100,"")
A15: Finansielle omkostninger | B15: ='res_raw_61056416'!$B$13 | C15: ='res_raw_61056416'!$C$13 | D15: ='res_raw_61056416'!$D$13 | E15: ='res_raw_61056416'!$E$13 | F15: ='res_raw_61056416'!$F$13 | H15: =IFERROR(B15/$B$15*100,"") | I15: =IFERROR(C15/$B$15*100,"") | J15: =IFERROR(D15/$B$15*100,"") | K15: =IFERROR(E15/$B$15*100,"") | L15: =IFERROR(F15/$B$15*100,"")
A16: Finansielle poster, netto | B16: ='res_raw_61056416'!$B$14 | C16: ='res_raw_61056416'!$C$14 | D16: ='res_raw_61056416'!$D$14 | E16: ='res_raw_61056416'!$E$14 | F16: ='res_raw_61056416'!$F$14 | H16: =IFERROR(B16/$B$16*100,"") | I16: =IFERROR(C16/$B$16*100,"") | J16: =IFERROR(D16/$B$16*100,"") | K16: =IFERROR(E16/$B$16*100,"") | L16: =IFERROR(F16/$B$16*100,"")
A17: Resultat før skat | B17: ='res_raw_61056416'!$B$15 | C17: ='res_raw_61056416'!$C$15 | D17: ='res_raw_61056416'!$D$15 | E17: ='res_raw_61056416'!$E$15 | F17: ='res_raw_61056416'!$F$15 | H17: =IFERROR(B17/$B$17*100,"") | I17: =IFERROR(C17/$B$17*100,"") | J17: =IFERROR(D17/$B$17*100,"") | K17: =IFERROR(E17/$B$17*100,"") | L17: =IFERROR(F17/$B$17*100,"")
A18: Skat af årets resultat | B18: ='res_raw_61056416'!$B$16 | C18: ='res_raw_61056416'!$C$16 | D18: ='res_raw_61056416'!$D$16 | E18: ='res_raw_61056416'!$E$16 | F18: ='res_raw_61056416'!$F$16 | H18: =IFERROR(B18/$B$18*100,"") | I18: =IFERROR(C18/$B$18*100,"") | J18: =IFERROR(D18/$B$18*100,"") | K18: =IFERROR(E18/$B$18*100,"") | L18: =IFERROR(F18/$B$18*100,"")
A19: Årets resultat | B19: ='res_raw_61056416'!$B$17 | C19: ='res_raw_61056416'!$C$17 | D19: ='res_raw_61056416'!$D$17 | E19: ='res_raw_61056416'!$E$17 | F19: ='res_raw_61056416'!$F$17 | H19: =IFERROR(B19/$B$19*100,"") | I19: =IFERROR(C19/$B$19*100,"") | J19: =IFERROR(D19/$B$19*100,"") | K19: =IFERROR(E19/$B$19*100,"") | L19: =IFERROR(F19/$B$19*100,"")
A21: AKTIVER t.kr. | B21: 2021 | C21: 2022 | D21: 2023 | E21: 2024 | F21: 2025 | H21: 2021 | I21: 2022 | J21: 2023 | K21: 2024 | L21: 2025
A22: Immaterielle anlægsaktiver | B22: ='balance_raw_61056416'!$B$2 | C22: ='balance_raw_61056416'!$C$2 | D22: ='balance_raw_61056416'!$D$2 | E22: ='balance_raw_61056416'!$E$2 | F22: ='balance_raw_61056416'!$F$2 | H22: =IFERROR(B22/$B$22*100,"") | I22: =IFERROR(C22/$B$22*100,"") | J22: =IFERROR(D22/$B$22*100,"") | K22: =IFERROR(E22/$B$22*100,"") | L22: =IFERROR(F22/$B$22*100,"")
A23: Materielle anlægsaktiver | B23: ='balance_raw_61056416'!$B$3 | C23: ='balance_raw_61056416'!$C$3 | D23: ='balance_raw_61056416'!$D$3 | E23: ='balance_raw_61056416'!$E$3 | F23: ='balance_raw_61056416'!$F$3 | H23: =IFERROR(B23/$B$23*100,"") | I23: =IFERROR(C23/$B$23*100,"") | J23: =IFERROR(D23/$B$23*100,"") | K23: =IFERROR(E23/$B$23*100,"") | L23: =IFERROR(F23/$B$23*100,"")
A24: Kapitalandele, dattervirksomheder | B24: ='balance_raw_61056416'!$B$4 | C24: ='balance_raw_61056416'!$C$4 | D24: ='balance_raw_61056416'!$D$4 | E24: ='balance_raw_61056416'!$E$4 | F24: ='balance_raw_61056416'!$F$4 | H24: =IFERROR(B24/$B$24*100,"") | I24: =IFERROR(C24/$B$24*100,"") | J24: =IFERROR(D24/$B$24*100,"") | K24: =IFERROR(E24/$B$24*100,"") | L24: =IFERROR(F24/$B$24*100,"")
A25: Deposita | B25: ='balance_raw_61056416'!$B$5 | C25: ='balance_raw_61056416'!$C$5 | D25: ='balance_raw_61056416'!$D$5 | E25: ='balance_raw_61056416'!$E$5 | F25: ='balance_raw_61056416'!$F$5 | H25: =IFERROR(B25/$B$25*100,"") | I25: =IFERROR(C25/$B$25*100,"") | J25: =IFERROR(D25/$B$25*100,"") | K25: =IFERROR(E25/$B$25*100,"") | L25: =IFERROR(F25/$B$25*100,"")
A26: Finansielle anlægsaktiver | B26: ='balance_raw_61056416'!$B$6 | C26: ='balance_raw_61056416'!$C$6 | D26: ='balance_raw_61056416'!$D$6 | E26: ='balance_raw_61056416'!$E$6 | F26: ='balance_raw_61056416'!$F$6 | H26: =IFERROR(B26/$B$26*100,"") | I26: =IFERROR(C26/$B$26*100,"") | J26: =IFERROR(D26/$B$26*100,"") | K26: =IFERROR(E26/$B$26*100,"") | L26: =IFERROR(F26/$B$26*100,"")
A27: Anlægsaktiver | B27: ='balance_raw_61056416'!$B$7 | C27: ='balance_raw_61056416'!$C$7 | D27: ='balance_raw_61056416'!$D$7 | E27: ='balance_raw_61056416'!$E$7 | F27: ='balance_raw_61056416'!$F$7 | H27: =IFERROR(B27/$B$27*100,"") | I27: =IFERROR(C27/$B$27*100,"") | J27: =IFERROR(D27/$B$27*100,"") | K27: =IFERROR(E27/$B$27*100,"") | L27: =IFERROR(F27/$B$27*100,"")
A28: Varebeholdninger | B28: ='balance_raw_61056416'!$B$8 | C28: ='balance_raw_61056416'!$C$8 | D28: ='balance_raw_61056416'!$D$8 | E28: ='balance_raw_61056416'!$E$8 | F28: ='balance_raw_61056416'!$F$8 | H28: =IFERROR(B28/$B$28*100,"") | I28: =IFERROR(C28/$B$28*100,"") | J28: =IFERROR(D28/$B$28*100,"") | K28: =IFERROR(E28/$B$28*100,"") | L28: =IFERROR(F28/$B$28*100,"")
A29: Tilgodehavender fra salg og tjenesteydelser | B29: ='balance_raw_61056416'!$B$9 | C29: ='balance_raw_61056416'!$C$9 | D29: ='balance_raw_61056416'!$D$9 | E29: ='balance_raw_61056416'!$E$9 | F29: ='balance_raw_61056416'!$F$9 | H29: =IFERROR(B29/$B$29*100,"") | I29: =IFERROR(C29/$B$29*100,"") | J29: =IFERROR(D29/$B$29*100,"") | K29: =IFERROR(E29/$B$29*100,"") | L29: =IFERROR(F29/$B$29*100,"")
A30: Tilgodehavender hos tilknyttede virksomheder | B30: ='balance_raw_61056416'!$B$10 | C30: ='balance_raw_61056416'!$C$10 | D30: ='balance_raw_61056416'!$D$10 | E30: ='balance_raw_61056416'!$E$10 | F30: ='balance_raw_61056416'!$F$10 | H30: =IFERROR(B30/$B$30*100,"") | I30: =IFERROR(C30/$B$30*100,"") | J30: =IFERROR(D30/$B$30*100,"") | K30: =IFERROR(E30/$B$30*100,"") | L30: =IFERROR(F30/$B$30*100,"")
A31: Andre tilgodehavender | B31: ='balance_raw_61056416'!$B$11 | C31: ='balance_raw_61056416'!$C$11 | D31: ='balance_raw_61056416'!$D$11 | E31: ='balance_raw_61056416'!$E$11 | F31: ='balance_raw_61056416'!$F$11 | H31: =IFERROR(B31/$B$31*100,"") | I31: =IFERROR(C31/$B$31*100,"") | J31: =IFERROR(D31/$B$31*100,"") | K31: =IFERROR(E31/$B$31*100,"") | L31: =IFERROR(F31/$B$31*100,"")
A32: Periodeafgrænsningsposter (aktiver) | B32: ='balance_raw_61056416'!$B$12 | C32: ='balance_raw_61056416'!$C$12 | D32: ='balance_raw_61056416'!$D$12 | E32: ='balance_raw_61056416'!$E$12 | F32: ='balance_raw_61056416'!$F$12 | H32: =IFERROR(B32/$B$32*100,"") | I32: =IFERROR(C32/$B$32*100,"") | J32: =IFERROR(D32/$B$32*100,"") | K32: =IFERROR(E32/$B$32*100,"") | L32: =IFERROR(F32/$B$32*100,"")
A33: Udskudt skatteaktiv | B33: ='balance_raw_61056416'!$B$13 | C33: ='balance_raw_61056416'!$C$13 | D33: ='balance_raw_61056416'!$D$13 | E33: ='balance_raw_61056416'!$E$13 | F33: ='balance_raw_61056416'!$F$13 | H33: =IFERROR(B33/$B$33*100,"") | I33: =IFERROR(C33/$B$33*100,"") | J33: =IFERROR(D33/$B$33*100,"") | K33: =IFERROR(E33/$B$33*100,"") | L33: =IFERROR(F33/$B$33*100,"")
A34: Tilgodehavende skat hos tilknyttede virksomheder | B34: ='balance_raw_61056416'!$B$14 | C34: ='balance_raw_61056416'!$C$14 | D34: ='balance_raw_61056416'!$D$14 | E34: ='balance_raw_61056416'!$E$14 | F34: ='balance_raw_61056416'!$F$14 | H34: =IFERROR(B34/$B$34*100,"") | I34: =IFERROR(C34/$B$34*100,"") | J34: =IFERROR(D34/$B$34*100,"") | K34: =IFERROR(E34/$B$34*100,"") | L34: =IFERROR(F34/$B$34*100,"")
A35: Kortfristede skattetilgodehavender | B35: ='balance_raw_61056416'!$B$15 | C35: ='balance_raw_61056416'!$C$15 | D35: ='balance_raw_61056416'!$D$15 | E35: ='balance_raw_61056416'!$E$15 | F35: ='balance_raw_61056416'!$F$15 | H35: =IFERROR(B35/$B$35*100,"") | I35: =IFERROR(C35/$B$35*100,"") | J35: =IFERROR(D35/$B$35*100,"") | K35: =IFERROR(E35/$B$35*100,"") | L35: =IFERROR(F35/$B$35*100,"")
A36: Tilgodehavender | B36: ='balance_raw_61056416'!$B$16 | C36: ='balance_raw_61056416'!$C$16 | D36: ='balance_raw_61056416'!$D$16 | E36: ='balance_raw_61056416'!$E$16 | F36: ='balance_raw_61056416'!$F$16 | H36: =IFERROR(B36/$B$36*100,"") | I36: =IFERROR(C36/$B$36*100,"") | J36: =IFERROR(D36/$B$36*100,"") | K36: =IFERROR(E36/$B$36*100,"") | L36: =IFERROR(F36/$B$36*100,"")
A37: Værdipapirer | B37: ='balance_raw_61056416'!$B$17 | C37: ='balance_raw_61056416'!$C$17 | D37: ='balance_raw_61056416'!$D$17 | E37: ='balance_raw_61056416'!$E$17 | F37: ='balance_raw_61056416'!$F$17 | H37: =IFERROR(B37/$B$37*100,"") | I37: =IFERROR(C37/$B$37*100,"") | J37: =IFERROR(D37/$B$37*100,"") | K37: =IFERROR(E37/$B$37*100,"") | L37: =IFERROR(F37/$B$37*100,"")
A38: Likvide beholdninger | B38: ='balance_raw_61056416'!$B$18 | C38: ='balance_raw_61056416'!$C$18 | D38: ='balance_raw_61056416'!$D$18 | E38: ='balance_raw_61056416'!$E$18 | F38: ='balance_raw_61056416'!$F$18 | H38: =IFERROR(B38/$B$38*100,"") | I38: =IFERROR(C38/$B$38*100,"") | J38: =IFERROR(D38/$B$38*100,"") | K38: =IFERROR(E38/$B$38*100,"") | L38: =IFERROR(F38/$B$38*100,"")
A39: Omsætningsaktiver | B39: ='balance_raw_61056416'!$B$19 | C39: ='balance_raw_61056416'!$C$19 | D39: ='balance_raw_61056416'!$D$19 | E39: ='balance_raw_61056416'!$E$19 | F39: ='balance_raw_61056416'!$F$19 | H39: =IFERROR(B39/$B$39*100,"") | I39: =IFERROR(C39/$B$39*100,"") | J39: =IFERROR(D39/$B$39*100,"") | K39: =IFERROR(E39/$B$39*100,"") | L39: =IFERROR(F39/$B$39*100,"")
A40: Aktiver | B40: ='balance_raw_61056416'!$B$20 | C40: ='balance_raw_61056416'!$C$20 | D40: ='balance_raw_61056416'!$D$20 | E40: ='balance_raw_61056416'!$E$20 | F40: ='balance_raw_61056416'!$F$20 | H40: =IFERROR(B40/$B$40*100,"") | I40: =IFERROR(C40/$B$40*100,"") | J40: =IFERROR(D40/$B$40*100,"") | K40: =IFERROR(E40/$B$40*100,"") | L40: =IFERROR(F40/$B$40*100,"")
A42: PASSIVER t.kr. | B42: 2021 | C42: 2022 | D42: 2023 | E42: 2024 | F42: 2025 | H42: 2021 | I42: 2022 | J42: 2023 | K42: 2024 | L42: 2025
A43: Selskabskapital | B43: ='balance_raw_61056416'!$B$21 | C43: ='balance_raw_61056416'!$C$21 | D43: ='balance_raw_61056416'!$D$21 | E43: ='balance_raw_61056416'!$E$21 | F43: ='balance_raw_61056416'!$F$21 | H43: =IFERROR(B43/$B$43*100,"") | I43: =IFERROR(C43/$B$43*100,"") | J43: =IFERROR(D43/$B$43*100,"") | K43: =IFERROR(E43/$B$43*100,"") | L43: =IFERROR(F43/$B$43*100,"")
A44: Reserve for nettoopskrivning (indre værdis metode) | B44: ='balance_raw_61056416'!$B$22 | C44: ='balance_raw_61056416'!$C$22 | D44: ='balance_raw_61056416'!$D$22 | E44: ='balance_raw_61056416'!$E$22 | F44: ='balance_raw_61056416'!$F$22 | H44: =IFERROR(B44/$B$44*100,"") | I44: =IFERROR(C44/$B$44*100,"") | J44: =IFERROR(D44/$B$44*100,"") | K44: =IFERROR(E44/$B$44*100,"") | L44: =IFERROR(F44/$B$44*100,"")
A45: Reserve for udviklingsomkostninger | B45: ='balance_raw_61056416'!$B$23 | C45: ='balance_raw_61056416'!$C$23 | D45: ='balance_raw_61056416'!$D$23 | E45: ='balance_raw_61056416'!$E$23 | F45: ='balance_raw_61056416'!$F$23 | H45: =IFERROR(B45/$B$45*100,"") | I45: =IFERROR(C45/$B$45*100,"") | J45: =IFERROR(D45/$B$45*100,"") | K45: =IFERROR(E45/$B$45*100,"") | L45: =IFERROR(F45/$B$45*100,"")
A46: Reserve for sikringstransaktioner | B46: ='balance_raw_61056416'!$B$24 | C46: ='balance_raw_61056416'!$C$24 | D46: ='balance_raw_61056416'!$D$24 | E46: ='balance_raw_61056416'!$E$24 | F46: ='balance_raw_61056416'!$F$24 | H46: =IFERROR(B46/$B$46*100,"") | I46: =IFERROR(C46/$B$46*100,"") | J46: =IFERROR(D46/$B$46*100,"") | K46: =IFERROR(E46/$B$46*100,"") | L46: =IFERROR(F46/$B$46*100,"")
A47: Andre reserver | B47: ='balance_raw_61056416'!$B$25 | C47: ='balance_raw_61056416'!$C$25 | D47: ='balance_raw_61056416'!$D$25 | E47: ='balance_raw_61056416'!$E$25 | F47: ='balance_raw_61056416'!$F$25 | H47: =IFERROR(B47/$B$47*100,"") | I47: =IFERROR(C47/$B$47*100,"") | J47: =IFERROR(D47/$B$47*100,"") | K47: =IFERROR(E47/$B$47*100,"") | L47: =IFERROR(F47/$B$47*100,"")
A48: Overført resultat | B48: ='balance_raw_61056416'!$B$26 | C48: ='balance_raw_61056416'!$C$26 | D48: ='balance_raw_61056416'!$D$26 | E48: ='balance_raw_61056416'!$E$26 | F48: ='balance_raw_61056416'!$F$26 | H48: =IFERROR(B48/$B$48*100,"") | I48: =IFERROR(C48/$B$48*100,"") | J48: =IFERROR(D48/$B$48*100,"") | K48: =IFERROR(E48/$B$48*100,"") | L48: =IFERROR(F48/$B$48*100,"")
A49: Egenkapital i alt | B49: ='balance_raw_61056416'!$B$27 | C49: ='balance_raw_61056416'!$C$27 | D49: ='balance_raw_61056416'!$D$27 | E49: ='balance_raw_61056416'!$E$27 | F49: ='balance_raw_61056416'!$F$27 | H49: =IFERROR(B49/$B$49*100,"") | I49: =IFERROR(C49/$B$49*100,"") | J49: =IFERROR(D49/$B$49*100,"") | K49: =IFERROR(E49/$B$49*100,"") | L49: =IFERROR(F49/$B$49*100,"")
A50: Hensættelse til udskudt skat | B50: ='balance_raw_61056416'!$B$28 | C50: ='balance_raw_61056416'!$C$28 | D50: ='balance_raw_61056416'!$D$28 | E50: ='balance_raw_61056416'!$E$28 | F50: ='balance_raw_61056416'!$F$28 | H50: =IFERROR(B50/$B$50*100,"") | I50: =IFERROR(C50/$B$50*100,"") | J50: =IFERROR(D50/$B$50*100,"") | K50: =IFERROR(E50/$B$50*100,"") | L50: =IFERROR(F50/$B$50*100,"")
A51: Hensatte forpligtelser | B51: ='balance_raw_61056416'!$B$29 | C51: ='balance_raw_61056416'!$C$29 | D51: ='balance_raw_61056416'!$D$29 | E51: ='balance_raw_61056416'!$E$29 | F51: ='balance_raw_61056416'!$F$29 | H51: =IFERROR(B51/$B$51*100,"") | I51: =IFERROR(C51/$B$51*100,"") | J51: =IFERROR(D51/$B$51*100,"") | K51: =IFERROR(E51/$B$51*100,"") | L51: =IFERROR(F51/$B$51*100,"")
A52: Ansvarlig lånekapital (langfristet) | B52: ='balance_raw_61056416'!$B$30 | C52: ='balance_raw_61056416'!$C$30 | D52: ='balance_raw_61056416'!$D$30 | E52: ='balance_raw_61056416'!$E$30 | F52: ='balance_raw_61056416'!$F$30 | H52: =IFERROR(B52/$B$52*100,"") | I52: =IFERROR(C52/$B$52*100,"") | J52: =IFERROR(D52/$B$52*100,"") | K52: =IFERROR(E52/$B$52*100,"") | L52: =IFERROR(F52/$B$52*100,"")
A53: Langfristede lån | B53: ='balance_raw_61056416'!$B$31 | C53: ='balance_raw_61056416'!$C$31 | D53: ='balance_raw_61056416'!$D$31 | E53: ='balance_raw_61056416'!$E$31 | F53: ='balance_raw_61056416'!$F$31 | H53: =IFERROR(B53/$B$53*100,"") | I53: =IFERROR(C53/$B$53*100,"") | J53: =IFERROR(D53/$B$53*100,"") | K53: =IFERROR(E53/$B$53*100,"") | L53: =IFERROR(F53/$B$53*100,"")
A54: Leasingforpligtelser (langfristet) | B54: ='balance_raw_61056416'!$B$32 | C54: ='balance_raw_61056416'!$C$32 | D54: ='balance_raw_61056416'!$D$32 | E54: ='balance_raw_61056416'!$E$32 | F54: ='balance_raw_61056416'!$F$32 | H54: =IFERROR(B54/$B$54*100,"") | I54: =IFERROR(C54/$B$54*100,"") | J54: =IFERROR(D54/$B$54*100,"") | K54: =IFERROR(E54/$B$54*100,"") | L54: =IFERROR(F54/$B$54*100,"")
A55: Anden gæld (langfristet) | B55: ='balance_raw_61056416'!$B$33 | C55: ='balance_raw_61056416'!$C$33 | D55: ='balance_raw_61056416'!$D$33 | E55: ='balance_raw_61056416'!$E$33 | F55: ='balance_raw_61056416'!$F$33 | H55: =IFERROR(B55/$B$55*100,"") | I55: =IFERROR(C55/$B$55*100,"") | J55: =IFERROR(D55/$B$55*100,"") | K55: =IFERROR(E55/$B$55*100,"") | L55: =IFERROR(F55/$B$55*100,"")
A56: Langfristede gældsforpligtelser | B56: ='balance_raw_61056416'!$B$34 | C56: ='balance_raw_61056416'!$C$34 | D56: ='balance_raw_61056416'!$D$34 | E56: ='balance_raw_61056416'!$E$34 | F56: ='balance_raw_61056416'!$F$34 | H56: =IFERROR(B56/$B$56*100,"") | I56: =IFERROR(C56/$B$56*100,"") | J56: =IFERROR(D56/$B$56*100,"") | K56: =IFERROR(E56/$B$56*100,"") | L56: =IFERROR(F56/$B$56*100,"")
A57: Ansvarlig lånekapital (kortfristet) | B57: ='balance_raw_61056416'!$B$35 | C57: ='balance_raw_61056416'!$C$35 | D57: ='balance_raw_61056416'!$D$35 | E57: ='balance_raw_61056416'!$E$35 | F57: ='balance_raw_61056416'!$F$35 | H57: =IFERROR(B57/$B$57*100,"") | I57: =IFERROR(C57/$B$57*100,"") | J57: =IFERROR(D57/$B$57*100,"") | K57: =IFERROR(E57/$B$57*100,"") | L57: =IFERROR(F57/$B$57*100,"")
A58: Kortfristet del af langfristede gældsforpligtelser | B58: ='balance_raw_61056416'!$B$36 | C58: ='balance_raw_61056416'!$C$36 | D58: ='balance_raw_61056416'!$D$36 | E58: ='balance_raw_61056416'!$E$36 | F58: ='balance_raw_61056416'!$F$36 | H58: =IFERROR(B58/$B$58*100,"") | I58: =IFERROR(C58/$B$58*100,"") | J58: =IFERROR(D58/$B$58*100,"") | K58: =IFERROR(E58/$B$58*100,"") | L58: =IFERROR(F58/$B$58*100,"")
A59: Kreditinstitutter | B59: ='balance_raw_61056416'!$B$37 | C59: ='balance_raw_61056416'!$C$37 | D59: ='balance_raw_61056416'!$D$37 | E59: ='balance_raw_61056416'!$E$37 | F59: ='balance_raw_61056416'!$F$37 | H59: =IFERROR(B59/$B$59*100,"") | I59: =IFERROR(C59/$B$59*100,"") | J59: =IFERROR(D59/$B$59*100,"") | K59: =IFERROR(E59/$B$59*100,"") | L59: =IFERROR(F59/$B$59*100,"")
A60: Leasingforpligtelser (kortfristet) | B60: ='balance_raw_61056416'!$B$38 | C60: ='balance_raw_61056416'!$C$38 | D60: ='balance_raw_61056416'!$D$38 | E60: ='balance_raw_61056416'!$E$38 | F60: ='balance_raw_61056416'!$F$38 | H60: =IFERROR(B60/$B$60*100,"") | I60: =IFERROR(C60/$B$60*100,"") | J60: =IFERROR(D60/$B$60*100,"") | K60: =IFERROR(E60/$B$60*100,"") | L60: =IFERROR(F60/$B$60*100,"")
A61: Leverandører af varer og tjenesteydelser | B61: ='balance_raw_61056416'!$B$39 | C61: ='balance_raw_61056416'!$C$39 | D61: ='balance_raw_61056416'!$D$39 | E61: ='balance_raw_61056416'!$E$39 | F61: ='balance_raw_61056416'!$F$39 | H61: =IFERROR(B61/$B$61*100,"") | I61: =IFERROR(C61/$B$61*100,"") | J61: =IFERROR(D61/$B$61*100,"") | K61: =IFERROR(E61/$B$61*100,"") | L61: =IFERROR(F61/$B$61*100,"")
A62: Gæld til tilknyttede virksomheder | B62: ='balance_raw_61056416'!$B$40 | C62: ='balance_raw_61056416'!$C$40 | D62: ='balance_raw_61056416'!$D$40 | E62: ='balance_raw_61056416'!$E$40 | F62: ='balance_raw_61056416'!$F$40 | H62: =IFERROR(B62/$B$62*100,"") | I62: =IFERROR(C62/$B$62*100,"") | J62: =IFERROR(D62/$B$62*100,"") | K62: =IFERROR(E62/$B$62*100,"") | L62: =IFERROR(F62/$B$62*100,"")
A63: Gæld til selskabsdeltagere og ledelse | B63: ='balance_raw_61056416'!$B$41 | C63: ='balance_raw_61056416'!$C$41 | D63: ='balance_raw_61056416'!$D$41 | E63: ='balance_raw_61056416'!$E$41 | F63: ='balance_raw_61056416'!$F$41 | H63: =IFERROR(B63/$B$63*100,"") | I63: =IFERROR(C63/$B$63*100,"") | J63: =IFERROR(D63/$B$63*100,"") | K63: =IFERROR(E63/$B$63*100,"") | L63: =IFERROR(F63/$B$63*100,"")
A64: Selskabsskat | B64: ='balance_raw_61056416'!$B$42 | C64: ='balance_raw_61056416'!$C$42 | D64: ='balance_raw_61056416'!$D$42 | E64: ='balance_raw_61056416'!$E$42 | F64: ='balance_raw_61056416'!$F$42 | H64: =IFERROR(B64/$B$64*100,"") | I64: =IFERROR(C64/$B$64*100,"") | J64: =IFERROR(D64/$B$64*100,"") | K64: =IFERROR(E64/$B$64*100,"") | L64: =IFERROR(F64/$B$64*100,"")
A65: Gæld til tilknyttede virksomheder vedr. selskabsskat | B65: ='balance_raw_61056416'!$B$43 | C65: ='balance_raw_61056416'!$C$43 | D65: ='balance_raw_61056416'!$D$43 | E65: ='balance_raw_61056416'!$E$43 | F65: ='balance_raw_61056416'!$F$43 | H65: =IFERROR(B65/$B$65*100,"") | I65: =IFERROR(C65/$B$65*100,"") | J65: =IFERROR(D65/$B$65*100,"") | K65: =IFERROR(E65/$B$65*100,"") | L65: =IFERROR(F65/$B$65*100,"")
A66: Anden gæld (kortfristet) | B66: ='balance_raw_61056416'!$B$44 | C66: ='balance_raw_61056416'!$C$44 | D66: ='balance_raw_61056416'!$D$44 | E66: ='balance_raw_61056416'!$E$44 | F66: ='balance_raw_61056416'!$F$44 | H66: =IFERROR(B66/$B$66*100,"") | I66: =IFERROR(C66/$B$66*100,"") | J66: =IFERROR(D66/$B$66*100,"") | K66: =IFERROR(E66/$B$66*100,"") | L66: =IFERROR(F66/$B$66*100,"")
A67: Periodeafgrænsningsposter (passiver) | B67: ='balance_raw_61056416'!$B$45 | C67: ='balance_raw_61056416'!$C$45 | D67: ='balance_raw_61056416'!$D$45 | E67: ='balance_raw_61056416'!$E$45 | F67: ='balance_raw_61056416'!$F$45 | H67: =IFERROR(B67/$B$67*100,"") | I67: =IFERROR(C67/$B$67*100,"") | J67: =IFERROR(D67/$B$67*100,"") | K67: =IFERROR(E67/$B$67*100,"") | L67: =IFERROR(F67/$B$67*100,"")
A68: Kortfristede gældsforpligtelser | B68: ='balance_raw_61056416'!$B$46 | C68: ='balance_raw_61056416'!$C$46 | D68: ='balance_raw_61056416'!$D$46 | E68: ='balance_raw_61056416'!$E$46 | F68: ='balance_raw_61056416'!$F$46 | H68: =IFERROR(B68/$B$68*100,"") | I68: =IFERROR(C68/$B$68*100,"") | J68: =IFERROR(D68/$B$68*100,"") | K68: =IFERROR(E68/$B$68*100,"") | L68: =IFERROR(F68/$B$68*100,"")
A69: Gældsforpligtelser | B69: ='balance_raw_61056416'!$B$47 | C69: ='balance_raw_61056416'!$C$47 | D69: ='balance_raw_61056416'!$D$47 | E69: ='balance_raw_61056416'!$E$47 | F69: ='balance_raw_61056416'!$F$47 | H69: =IFERROR(B69/$B$69*100,"") | I69: =IFERROR(C69/$B$69*100,"") | J69: =IFERROR(D69/$B$69*100,"") | K69: =IFERROR(E69/$B$69*100,"") | L69: =IFERROR(F69/$B$69*100,"")
A70: Passiver | B70: ='balance_raw_61056416'!$B$48 | C70: ='balance_raw_61056416'!$C$48 | D70: ='balance_raw_61056416'!$D$48 | E70: ='balance_raw_61056416'!$E$48 | F70: ='balance_raw_61056416'!$F$48 | H70: =IFERROR(B70/$B$70*100,"") | I70: =IFERROR(C70/$B$70*100,"") | J70: =IFERROR(D70/$B$70*100,"") | K70: =IFERROR(E70/$B$70*100,"") | L70: =IFERROR(F70/$B$70*100,"")
A72: NØGLEOPLYSNINGER | B72: 2021 | C72: 2022 | D72: 2023 | E72: 2024 | F72: 2025
A73: Gns. antal medarbejdere | B73: ='res_raw_61056416'!$B$18 | C73: ='res_raw_61056416'!$C$18 | D73: ='res_raw_61056416'!$D$18 | E73: ='res_raw_61056416'!$E$18 | F73: ='res_raw_61056416'!$F$18 | H73: =IFERROR(B73/$B$73*100,"") | I73: =IFERROR(C73/$B$73*100,"") | J73: =IFERROR(D73/$B$73*100,"") | K73: =IFERROR(E73/$B$73*100,"") | L73: =IFERROR(F73/$B$73*100,"")
A74: Investering i materielle anlægsaktiver | B74: ='res_raw_61056416'!$B$19 | C74: ='res_raw_61056416'!$C$19 | D74: ='res_raw_61056416'!$D$19 | E74: ='res_raw_61056416'!$E$19 | F74: ='res_raw_61056416'!$F$19 | H74: =IFERROR(B74/$B$74*100,"") | I74: =IFERROR(C74/$B$74*100,"") | J74: =IFERROR(D74/$B$74*100,"") | K74: =IFERROR(E74/$B$74*100,"") | L74: =IFERROR(F74/$B$74*100,"")
A76: NØGLETAL | B76: 2021 | C76: 2022 | D76: 2023 | E76: 2024 | F76: 2025
A77: Afkastningsgrad, % | B77: =IFERROR(($B$12+$B$14+$B$13)/$B$40*100,"") | C77: =IFERROR(($C$12+$C$14+$C$13)/$C$40*100,"") | D77: =IFERROR(($D$12+$D$14+$D$13)/$D$40*100,"") | E77: =IFERROR(($E$12+$E$14+$E$13)/$E$40*100,"") | F77: =IFERROR(($F$12+$F$14+$F$13)/$F$40*100,"")
A78: Overskudsgrad, % | B78: =IFERROR(($B$12+$B$14+$B$13)/$B$4*100,"") | C78: =IFERROR(($C$12+$C$14+$C$13)/$C$4*100,"") | D78: =IFERROR(($D$12+$D$14+$D$13)/$D$4*100,"") | E78: =IFERROR(($E$12+$E$14+$E$13)/$E$4*100,"") | F78: =IFERROR(($F$12+$F$14+$F$13)/$F$4*100,"")
A79: Aktivernes omsætningshastighed, gange | B79: =IFERROR($B$4/$B$40,"") | C79: =IFERROR($C$4/$C$40,"") | D79: =IFERROR($D$4/$D$40,"") | E79: =IFERROR($E$4/$E$40,"") | F79: =IFERROR($F$4/$F$40,"")
A80: Egenkapitalens forrentning, % | B80: =IFERROR($B$17/$B$49*100,"") | C80: =IFERROR($C$17/$C$49*100,"") | D80: =IFERROR($D$17/$D$49*100,"") | E80: =IFERROR($E$17/$E$49*100,"") | F80: =IFERROR($F$17/$F$49*100,"")
A81: Gældsrente, % | B81: =IFERROR($B$15/($B$70-$B$49)*100,"") | C81: =IFERROR($C$15/($C$70-$C$49)*100,"") | D81: =IFERROR($D$15/($D$70-$D$49)*100,"") | E81: =IFERROR($E$15/($E$70-$E$49)*100,"") | F81: =IFERROR($F$15/($F$70-$F$49)*100,"")
A82: Soliditetsgrad, % | B82: =IFERROR($B$49/$B$40*100,"") | C82: =IFERROR($C$49/$C$40*100,"") | D82: =IFERROR($D$49/$D$40*100,"") | E82: =IFERROR($E$49/$E$40*100,"") | F82: =IFERROR($F$49/$F$40*100,"")
A83: Gearing | B83: =IFERROR(($B$70-$B$49)/$B$49,"") | C83: =IFERROR(($C$70-$C$49)/$C$49,"") | D83: =IFERROR(($D$70-$D$49)/$D$49,"") | E83: =IFERROR(($E$70-$E$49)/$E$49,"") | F83: =IFERROR(($F$70-$F$49)/$F$49,"")
A84: Likviditetsgrad, % | B84: =IFERROR($B$39/$B$68*100,"") | C84: =IFERROR($C$39/$C$68*100,"") | D84: =IFERROR($D$39/$D$68*100,"") | E84: =IFERROR($E$39/$E$68*100,"") | F84: =IFERROR($F$39/$F$68*100,"")
A85: Rentemarginal, % | B85: =IFERROR(B77-B81,"") | C85: =IFERROR(C77-C81,"") | D85: =IFERROR(D77-D81,"") | E85: =IFERROR(E77-E81,"") | F85: =IFERROR(F77-F81,"")
A86: Gældsandel, % | B86: =IFERROR(($B$70-$B$49)/$B$40*100,"") | C86: =IFERROR(($C$70-$C$49)/$C$40*100,"") | D86: =IFERROR(($D$70-$D$49)/$D$40*100,"") | E86: =IFERROR(($E$70-$E$49)/$E$40*100,"") | F86: =IFERROR(($F$70-$F$49)/$F$40*100,"")
A87: Kapitalbindingsgrad, % | B87: =IFERROR($B$27/($B$49+$B$56)*100,"") | C87: =IFERROR($C$27/($C$49+$C$56)*100,"") | D87: =IFERROR($D$27/($D$49+$D$56)*100,"") | E87: =IFERROR($E$27/($E$49+$E$56)*100,"") | F87: =IFERROR($F$27/($F$49+$F$56)*100,"")
A89: PENGESTRØMSOPGØRELSE t.kr.
A90: Pengestrømme fra driftsaktivitet | B90: ='pengestrom_raw_61056416'!$B$2 | C90: ='pengestrom_raw_61056416'!$C$2 | D90: ='pengestrom_raw_61056416'!$D$2 | E90: ='pengestrom_raw_61056416'!$E$2 | F90: ='pengestrom_raw_61056416'!$F$2
A91: Pengestrømme fra investeringsaktivitet | B91: ='pengestrom_raw_61056416'!$B$3 | C91: ='pengestrom_raw_61056416'!$C$3 | D91: ='pengestrom_raw_61056416'!$D$3 | E91: ='pengestrom_raw_61056416'!$E$3 | F91: ='pengestrom_raw_61056416'!$F$3
A92: Pengestrømme fra finansieringsaktivitet | B92: ='pengestrom_raw_61056416'!$B$4 | C92: ='pengestrom_raw_61056416'!$C$4 | D92: ='pengestrom_raw_61056416'!$D$4 | E92: ='pengestrom_raw_61056416'!$E$4 | F92: ='pengestrom_raw_61056416'!$F$4
A93: Årets pengestrøm (rapporteret) | B93: ='pengestrom_raw_61056416'!$B$5 | C93: ='pengestrom_raw_61056416'!$C$5 | D93: ='pengestrom_raw_61056416'!$D$5 | E93: ='pengestrom_raw_61056416'!$E$5 | F93: ='pengestrom_raw_61056416'!$F$5
A94: Krydstjek: drift + inv. + fin. = årets pengestrøm | B94: =IF(ABS(('pengestrom_raw_61056416'!$B$2+'pengestrom_raw_61056416'!$B$3+'pengestrom_raw_61056416'!$B$4)-'pengestrom_raw_61056416'!$B$5)<=2,"✓","⚠ "&TEXT(('pengestrom_raw_61056416'!$B$2+'pengestrom_raw_61056416'!$B$3+'pengestrom_raw_61056416'!$B$4)-'pengestrom_raw_61056416'!$B$5,"+#,##0;-#,##0")) | C94: =IF(ABS(('pengestrom_raw_61056416'!$C$2+'pengestrom_raw_61056416'!$C$3+'pengestrom_raw_61056416'!$C$4)-'pengestrom_raw_61056416'!$C$5)<=2,"✓","⚠ "&TEXT(('pengestrom_raw_61056416'!$C$2+'pengestrom_raw_61056416'!$C$3+'pengestrom_raw_61056416'!$C$4)-'pengestrom_raw_61056416'!$C$5,"+#,##0;-#,##0")) | D94: =IF(ABS(('pengestrom_raw_61056416'!$D$2+'pengestrom_raw_61056416'!$D$3+'pengestrom_raw_61056416'!$D$4)-'pengestrom_raw_61056416'!$D$5)<=2,"✓","⚠ "&TEXT(('pengestrom_raw_61056416'!$D$2+'pengestrom_raw_61056416'!$D$3+'pengestrom_raw_61056416'!$D$4)-'pengestrom_raw_61056416'!$D$5,"+#,##0;-#,##0")) | E94: =IF(ABS(('pengestrom_raw_61056416'!$E$2+'pengestrom_raw_61056416'!$E$3+'pengestrom_raw_61056416'!$E$4)-'pengestrom_raw_61056416'!$E$5)<=2,"✓","⚠ "&TEXT(('pengestrom_raw_61056416'!$E$2+'pengestrom_raw_61056416'!$E$3+'pengestrom_raw_61056416'!$E$4)-'pengestrom_raw_61056416'!$E$5,"+#,##0;-#,##0")) | F94: =IF(ABS(('pengestrom_raw_61056416'!$F$2+'pengestrom_raw_61056416'!$F$3+'pengestrom_raw_61056416'!$F$4)-'pengestrom_raw_61056416'!$F$5)<=2,"✓","⚠ "&TEXT(('pengestrom_raw_61056416'!$F$2+'pengestrom_raw_61056416'!$F$3+'pengestrom_raw_61056416'!$F$4)-'pengestrom_raw_61056416'!$F$5,"+#,##0;-#,##0"))

Sheet res_raw_61056416
A1: Carlsberg A/S (CVR 61056416) — Resultatopgørelse & nøgleoplysninger (t.kr.) | B1: 2021 | C1: 2022 | D1: 2023 | E1: 2024 | F1: 2025
A2: Nettoomsætning | B2: 60097000 | C2: 70265000 | D2: 73585000 | E2: 75011000 | F2: 89095000
A3: Produktionsomkostninger | B3: 31528000 | C3: 38198000 | D3: 40753000 | E3: 40631000 | F3: 48859000
A4: Bruttoresultat | B4: 28569000 | C4: 32067000 | D4: 32832000 | E4: 34380000 | F4: 40236000
A5: Udviklingsomkostninger
A6: Salgs- og distributionsomkostninger | B6: 14872000 | C6: 17337000 | D6: 18355000 | E6: 19242000 | F6: 23128000
A7: Administrationsomkostninger | B7: 3979000 | C7: 4229000 | D7: 4077000 | E7: 4381000 | F7: 4961000
A8: Andre driftsindtægter
A9: Andre driftsomkostninger
A10: Resultat af primær drift | B10: 10129000 | C10: 11470000 | D10: 11105000 | E10: 11411000 | F10: 13356000
A11: Indtægter af kapitalandele, dattervirksomheder | B11: 336000 | C11: 901000 | D11: 581000 | E11: 616000 | F11: 660000
A12: Finansielle indtægter | B12: 571000 | C12: 347000 | D12: 695000 | E12: 959000 | F12: 1136000
A13: Finansielle omkostninger | B13: 956000 | C13: 1072000 | D13: 1539000 | E13: 1864000 | F13: 3516000
A14: Finansielle poster, netto | B14: -385000 | C14: -725000 | D14: -844000 | E14: -905000 | F14: -2380000
A15: Resultat før skat | B15: 10447000 | C15: 9961000 | D15: 9830000 | E15: 9987000 | F15: 9050000
A16: Skat af årets resultat | B16: 2154000 | C16: 1778000 | D16: 1859000 | E16: 1982000 | F16: 2072000
A17: Årets resultat | B17: 8293000 | C17: 8183000 | D17: 7971000 | E17: 8005000 | F17: 6978000
A18: Gns. antal medarbejdere | B18: 39375
A19: Investering i materielle anlægsaktiver | B19: -4221000 | D19: 3887000 | E19: 4668000 | F19: 4924000

Sheet balance_raw_61056416
A1: Carlsberg A/S (CVR 61056416) — Balance (t.kr.) | B1: 2021 | C1: 2022 | D1: 2023 | E1: 2024 | F1: 2025
A2: Immaterielle anlægsaktiver | B2: 68475000 | C2: 49223000 | D2: 49100000 | E2: 53176000 | F2: 83231000
A3: Materielle anlægsaktiver | B3: 26648000 | C3: 23679000 | D3: 24405000 | E3: 27053000 | F3: 32780000
A4: Kapitalandele, dattervirksomheder | B4: 5172000 | C4: 5523000 | D4: 5437000 | E4: 4546000 | F4: 4325000
A5: Deposita | B5: 1075000 | C5: 936000 | D5: 881000 | E5: 814000 | F5: 860000
A6: Finansielle anlægsaktiver
A7: Anlægsaktiver | B7: 103292000 | C7: 81092000 | D7: 81633000 | E7: 87645000 | F7: 124706000
A8: Varebeholdninger | B8: 5391000 | C8: 5718000 | D8: 5811000 | E8: 5953000 | F8: 7110000
A9: Tilgodehavender fra salg og tjenesteydelser | B9: 5710000 | C9: 5067000 | D9: 5102000 | E9: 4940000 | F9: 7709000
A10: Tilgodehavender hos tilknyttede virksomheder
A11: Andre tilgodehavender
A12: Periodeafgrænsningsposter (aktiver) | B12: 929000 | C12: 964000 | D12: 835000 | E12: 1185000 | F12: 1469000
A13: Udskudt skatteaktiv | E13: 2056000 | F13: 2511000
A14: Tilgodehavende skat hos tilknyttede virksomheder
A15: Kortfristede skattetilgodehavender | B15: 171000 | C15: 214000 | D15: 356000 | E15: 410000 | F15: 386000
A16: Tilgodehavender | B16: 2355000 | C16: 2505000 | D16: 2476000 | E16: 2258000 | F16: 2990000
A17: Værdipapirer
A18: Likvide beholdninger | B18: 8344000 | C18: 8163000 | D18: 13382000 | E18: 11542000 | F18: 9585000
A19: Omsætningsaktiver | B19: 23091000 | C19: 34249000 | D19: 30198000 | E19: 26347000 | F19: 29249000
A20: Aktiver | B20: 126383000 | C20: 115341000 | D20: 111831000 | E20: 113992000 | F20: 153955000
A21: Selskabskapital | B21: 2905000 | C21: 2837000 | D21: 2747000 | E21: 2685000 | F21: 2653000
A22: Reserve for nettoopskrivning (indre værdis metode)
A23: Reserve for udviklingsomkostninger
A24: Reserve for sikringstransaktioner
A25: Andre reserver | B25: -37691000 | C25: -41711000 | D25: -2819000 | E25: -496000 | F25: -3194000
A26: Overført resultat | B26: 80283000 | C26: 70776000 | D26: 23306000 | E26: 25582000 | F26: 28345000
A27: Egenkapital i alt | B27: 45497000 | C27: 31902000 | D27: 23234000 | E27: 30612000 | F27: 30676000
A28: Hensættelse til udskudt skat | B28: 6350000 | C28: 4841000 | D28: 4823000 | E28: 5081000 | F28: 8675000
A29: Hensatte forpligtelser | B29: 2345000 | C29: 1557000 | D29: 1387000 | E29: 1304000 | F29: 1297000
A30: Ansvarlig lånekapital (langfristet)
A31: Langfristede lån
A32: Leasingforpligtelser (langfristet)
A33: Anden gæld (langfristet) | B33: 449000 | C33: 305000 | D33: 314000 | E33: 1495000 | F33: 1446000
A34: Langfristede gældsforpligtelser | B34: 22755000 | C34: 22865000 | D34: 30763000 | E34: 27392000 | F34: 61452000
A35: Ansvarlig lånekapital (kortfristet)
A36: Kortfristet del af langfristede gældsforpligtelser
A37: Kreditinstitutter | B37: 6167000 | C37: 5781000 | D37: 8338000 | E37: 10748000 | F37: 9171000
A38: Leasingforpligtelser (kortfristet)
A39: Leverandører af varer og tjenesteydelser | B39: 20642000 | C39: 21917000 | D39: 22159000 | E39: 23295000 | F39: 26877000
A40: Gæld til tilknyttede virksomheder
A41: Gæld til selskabsdeltagere og ledelse
A42: Selskabsskat
A43: Gæld til tilknyttede virksomheder vedr. selskabsskat
A44: Anden gæld (kortfristet) | B44: 12677000 | C44: 13503000 | D44: 13020000 | E44: 8098000 | F44: 8178000
A45: Periodeafgrænsningsposter (passiver)
A46: Kortfristede gældsforpligtelser | B46: 43282000 | C46: 48747000 | D46: 47230000 | E46: 46023000 | F46: 48546000
A47: Gældsforpligtelser | B47: 77627000 | C47: 80619000 | D47: 86082000 | E47: 83380000 | F47: 123279000
A48: Passiver | B48: 126383000 | C48: 115341000 | D48: 111831000 | E48: 113992000 | F48: 153955000

Sheet pengestrom_raw_61056416
A1: Carlsberg A/S (CVR 61056416) — Pengestrømsopgørelse (t.kr.) | B1: 2021 | C1: 2022 | D1: 2023 | E1: 2024 | F1: 2025
A2: Pengestrømme fra driftsaktivitet | B2: 12278000 | C2: 12949000 | D2: 11607000 | E2: 11312000 | F2: 12431000
A3: Pengestrømme fra investeringsaktivitet | B3: -4067000 | C3: -3065000 | D3: -6729000 | E3: -1518000 | F3: -34098000
A4: Pengestrømme fra finansieringsaktivitet | B4: -8945000 | C4: -9959000 | D4: 1370000 | E4: -13935000 | F4: 20310000
A5: Årets pengestrøm

Sheet Simpel_funktion
A1: Carlsberg A/S (CVR 61056416) — Regnskabs- og nøgletal (CVR: 61056416) — funktionsopdelt
A3: Beløb i 1.000 kr. | B3: 2025 | C3: 2024 | D3: 2023 | F3: Note / XBRL-felt
A4: Uddrag af resultatopgørelse
A5: Nettoomsætning | B5: ='res_raw_61056416'!$F$2 | C5: ='res_raw_61056416'!$E$2 | D5: ='res_raw_61056416'!$D$2 | F5: fsa:Revenue
A6: Produktionsomkostninger | B6: =-'res_raw_61056416'!$F$3 | C6: =-'res_raw_61056416'!$E$3 | D6: =-'res_raw_61056416'!$D$3 | F6: fsa:CostOfProduction (vises negativt). Materialer, lønninger, produktionsoverhead.
A7: Bruttoresultat | B7: =IF(ABS((SUM(B5:B6))-'res_raw_61056416'!$F$4)<=2,SUM(B5:B6),'res_raw_61056416'!$F$4) | C7: =IF(ABS((SUM(C5:C6))-'res_raw_61056416'!$E$4)<=2,SUM(C5:C6),'res_raw_61056416'!$E$4) | D7: =IF(ABS((SUM(D5:D6))-'res_raw_61056416'!$D$4)<=2,SUM(D5:D6),'res_raw_61056416'!$D$4) | F7: Beregnet: Nettoomsætning − Produktionsomkostninger. Matcher fsa:GrossResult. Er komponenterne ikke indberettet, vises rapporteret fsa:GrossResult direkte.
A8: Udviklingsomkostninger | B8: =-'res_raw_61056416'!$F$5 | C8: =-'res_raw_61056416'!$E$5 | D8: =-'res_raw_61056416'!$D$5 | F8: ifrs-full:ResearchAndDevelopmentExpense (vises negativt). Udviklingsomkostninger ført i resultatet (v15_21; B&O m.fl.).
A9: Salgs- og distributionsomk. | B9: =-'res_raw_61056416'!$F$6 | C9: =-'res_raw_61056416'!$E$6 | D9: =-'res_raw_61056416'!$D$6 | F9: fsa:DistributionCosts (vises negativt). Marketing, salg, distribution.
A10: Administrationsomkostninger mv. | B10: =-'res_raw_61056416'!$F$7 | C10: =-'res_raw_61056416'!$E$7 | D10: =-'res_raw_61056416'!$D$7 | F10: fsa:AdministrativeExpenses (vises negativt). Generel administration.
A11: Andre driftsindtægter | B11: ='res_raw_61056416'!$F$8 | C11: ='res_raw_61056416'!$E$8 | D11: ='res_raw_61056416'!$D$8 | F11: fsa:OtherOperatingIncome. Sekundære driftsindtægter (huslejeindtægter, off. tilskud, avancer mv.).
A12: Andre driftsomkostninger | B12: =-'res_raw_61056416'!$F$9 | C12: =-'res_raw_61056416'!$E$9 | D12: =-'res_raw_61056416'!$D$9 | F12: fsa:OtherOperatingExpenses (vises negativt). Sekundære driftsomkostninger.
A13: Resultat af primær drift | B13: =IF(ABS((SUM(B7:B12))-'res_raw_61056416'!$F$10)<=2,SUM(B7:B12),'res_raw_61056416'!$F$10) | C13: =IF(ABS((SUM(C7:C12))-'res_raw_61056416'!$E$10)<=2,SUM(C7:C12),'res_raw_61056416'!$E$10) | D13: =IF(ABS((SUM(D7:D12))-'res_raw_61056416'!$D$10)<=2,SUM(D7:D12),'res_raw_61056416'!$D$10) | F13: Beregnet: Bruttoresultat − Udviklingsomk. − Salgs/dist. − Administration + Andre driftsindt. − Andre driftsomk. EBIT.
A14: Finansielle indtægter mv. | B14: =N('res_raw_61056416'!$F$11)+N('res_raw_61056416'!$F$12) | C14: =N('res_raw_61056416'!$E$11)+N('res_raw_61056416'!$E$12) | D14: =N('res_raw_61056416'!$D$11)+N('res_raw_61056416'!$D$12) | F14: fsa:IncomeFromSubsidiaries + fsa:OtherFinanceIncome.
A15: Finansielle omkostninger mv. | B15: =-'res_raw_61056416'!$F$13 | C15: =-'res_raw_61056416'!$E$13 | D15: =-'res_raw_61056416'!$D$13 | F15: fsa:OtherFinanceExpenses (vises negativt). Renteomkostninger, kurstab.
A16: Resultat før skat | B16: =IF(ABS((SUM(B13:B15))-'res_raw_61056416'!$F$15)<=2,SUM(B13:B15),'res_raw_61056416'!$F$15) | C16: =IF(ABS((SUM(C13:C15))-'res_raw_61056416'!$E$15)<=2,SUM(C13:C15),'res_raw_61056416'!$E$15) | D16: =IF(ABS((SUM(D13:D15))-'res_raw_61056416'!$D$15)<=2,SUM(D13:D15),'res_raw_61056416'!$D$15) | F16: Beregnet: EBIT + Fin. indtægter + Fin. omk. EBT.
A18: Uddrag af balance
A19: Anlægsaktiver | B19: ='balance_raw_61056416'!$F$7 | C19: ='balance_raw_61056416'!$E$7 | D19: ='balance_raw_61056416'!$D$7 | F19: fsa:NoncurrentAssets. Materielle, immaterielle og finansielle anlægsaktiver.
A20: Omsætningsaktiver | B20: ='balance_raw_61056416'!$F$19 | C20: ='balance_raw_61056416'!$E$19 | D20: ='balance_raw_61056416'!$D$19 | F20: fsa:CurrentAssets. Varebeholdninger, tilgodehavender, likvider.
A21: Aktiver i alt | B21: =SUM(B19:B20) | C21: =SUM(C19:C20) | D21: =SUM(D19:D20) | F21: Beregnet: Anlægsaktiver + Omsætningsaktiver. Bør matche fsa:Assets.
A23: Egenkapital | B23: ='balance_raw_61056416'!$F$27 | C23: ='balance_raw_61056416'!$E$27 | D23: ='balance_raw_61056416'!$D$27 | F23: fsa:Equity. Selskabskapital, overført resultat, reserver.
A24: Forpligtelser | B24: ='balance_raw_61056416'!$F$48-'balance_raw_61056416'!$F$27 | C24: ='balance_raw_61056416'!$E$48-'balance_raw_61056416'!$E$27 | D24: ='balance_raw_61056416'!$D$48-'balance_raw_61056416'!$D$27 | F24: Beregnet: Passiver (fsa:LiabilitiesAndEquity) − Egenkapital. Hensættelser + kort- og langfristet gæld.
A25: Passiver i alt | B25: =SUM(B23:B24) | C25: =SUM(C23:C24) | D25: =SUM(D23:D24) | F25: Beregnet: Egenkapital + Forpligtelser. Bør matche Aktiver i alt.
A27: Udvalgte balanceposter
A28: Varebeholdninger | B28: ='balance_raw_61056416'!$F$8 | C28: ='balance_raw_61056416'!$E$8 | D28: ='balance_raw_61056416'!$D$8 | F28: fsa:Inventories (eller fsa:ManufacturedGoodsAndGoodsForResale hvis total mangler).
A29: Tilgodehavender fra salg | B29: ='balance_raw_61056416'!$F$9 | C29: ='balance_raw_61056416'!$E$9 | D29: ='balance_raw_61056416'!$D$9 | F29: fsa:ShorttermTradeReceivables. Kortfristede tilgodehavender fra kunder.
A30: Kortfristede gældsforpligtelser | B30: ='balance_raw_61056416'!$F$46 | C30: ='balance_raw_61056416'!$E$46 | D30: ='balance_raw_61056416'!$D$46 | F30: fsa:ShorttermLiabilitiesOtherThanProvisions. Gæld der forfalder inden for 1 år.
A32: Rentabilitet
A33: Afkastningsgrad, % | B33: =IFERROR((B13+B14)/B21*100,"") | C33: =IFERROR((C13+C14)/C21*100,"") | D33: =IFERROR((D13+D14)/D21*100,"")
A34: Overskudsgrad, % | B34: =IFERROR((B13+B14)/B5*100,"") | C34: =IFERROR((C13+C14)/C5*100,"") | D34: =IFERROR((D13+D14)/D5*100,"")
A35: Aktivernes omsætningshastighed, gange | B35: =IFERROR(B5/B21,"") | C35: =IFERROR(C5/C21,"") | D35: =IFERROR(D5/D21,"")
A36: Gældsrente, % | B36: =IFERROR(-B15*100/B24,"") | C36: =IFERROR(-C15*100/C24,"") | D36: =IFERROR(-D15*100/D24,"")
A37: Egenkapitalens forrentning, % | B37: =IFERROR(B16/B23*100,"") | C37: =IFERROR(C16/C23*100,"") | D37: =IFERROR(D16/D23*100,"")
A38: Gearing, gange | B38: =IFERROR(B24/B23,"") | C38: =IFERROR(C24/C23,"") | D38: =IFERROR(D24/D23,"")
A40: Indekstal for indtjeningsevne (2023=100)
A41: Nettoomsætning | B41: =IFERROR(B5/$D5*100,"") | C41: =IFERROR(C5/$D5*100,"") | D41: =IFERROR(D5/$D5*100,"")
A42: Produktionsomkostninger | B42: =IFERROR(B6/$D6*100,"") | C42: =IFERROR(C6/$D6*100,"") | D42: =IFERROR(D6/$D6*100,"")
A43: Udviklingsomkostninger | B43: =IFERROR(B8/$D8*100,"") | C43: =IFERROR(C8/$D8*100,"") | D43: =IFERROR(D8/$D8*100,"")
A44: Salgs- og distributionsomk. | B44: =IFERROR(B9/$D9*100,"") | C44: =IFERROR(C9/$D9*100,"") | D44: =IFERROR(D9/$D9*100,"")
A45: Administrationsomk. | B45: =IFERROR(B10/$D10*100,"") | C45: =IFERROR(C10/$D10*100,"") | D45: =IFERROR(D10/$D10*100,"")
A46: Andre driftsomkostninger | B46: =IFERROR(B12/$D12*100,"") | C46: =IFERROR(C12/$D12*100,"") | D46: =IFERROR(D12/$D12*100,"")
A48: Indekstal for kapitaltilpasningsevne (2023=100)
A49: Nettoomsætning | B49: =IFERROR(B5*100/$D5,"") | C49: =IFERROR(C5*100/$D5,"") | D49: =IFERROR(D5*100/$D5,"")
A50: Anlægsaktiver | B50: =IFERROR(B19*100/$D19,"") | C50: =IFERROR(C19*100/$D19,"") | D50: =IFERROR(D19*100/$D19,"")
A51: Varebeholdninger | B51: =IFERROR(B28*100/$D28,"") | C51: =IFERROR(C28*100/$D28,"") | D51: =IFERROR(D28*100/$D28,"")
A52: Tilgodehavender fra salg | B52: =IFERROR(B29*100/$D29,"") | C52: =IFERROR(C29*100/$D29,"") | D52: =IFERROR(D29*100/$D29,"")
A54: Soliditet og likviditet
A55: Soliditetsgrad, % | B55: =IFERROR(B23*100/B21,"") | C55: =IFERROR(C23*100/C21,"") | D55: =IFERROR(D23*100/D21,"")
A56: Gældsandel, % | B56: =IFERROR(B24*100/B21,"") | C56: =IFERROR(C24*100/C21,"") | D56: =IFERROR(D24*100/D21,"")
A57: Likviditetsgrad, % | B57: =IFERROR(B20*100/B30,"") | C57: =IFERROR(C20*100/C30,"") | D57: =IFERROR(D20*100/D30,"")
A59: Kilde: Bearbejdet uddrag af årsrapporter for 2023-2025. Alle dataceller er live formler der peger på res_raw / balance_raw.
A61: Krydstjek mod rådata (tolerance: 1 t.kr.)
A62: Aktiver i alt = fsa:Assets | B62: =IF('balance_raw_61056416'!$F$20="","—",IF(ABS(B21-'balance_raw_61056416'!$F$20)<=1,"✓ OK","❌ "&TEXT(B21-'balance_raw_61056416'!$F$20,"+#,##0;-#,##0")&" t.kr.")) | C62: =IF('balance_raw_61056416'!$E$20="","—",IF(ABS(C21-'balance_raw_61056416'!$E$20)<=1,"✓ OK","❌ "&TEXT(C21-'balance_raw_61056416'!$E$20,"+#,##0;-#,##0")&" t.kr.")) | D62: =IF('balance_raw_61056416'!$D$20="","—",IF(ABS(D21-'balance_raw_61056416'!$D$20)<=1,"✓ OK","❌ "&TEXT(D21-'balance_raw_61056416'!$D$20,"+#,##0;-#,##0")&" t.kr.")) | F62: Verificerer at sum(Anlæg+Omsætning) matcher Assets-totalen.
A63: Passiver i alt = fsa:LiabilitiesAndEquity | B63: =IF('balance_raw_61056416'!$F$48="","—",IF(ABS(B25-'balance_raw_61056416'!$F$48)<=1,"✓ OK","❌ "&TEXT(B25-'balance_raw_61056416'!$F$48,"+#,##0;-#,##0")&" t.kr.")) | C63: =IF('balance_raw_61056416'!$E$48="","—",IF(ABS(C25-'balance_raw_61056416'!$E$48)<=1,"✓ OK","❌ "&TEXT(C25-'balance_raw_61056416'!$E$48,"+#,##0;-#,##0")&" t.kr.")) | D63: =IF('balance_raw_61056416'!$D$48="","—",IF(ABS(D25-'balance_raw_61056416'!$D$48)<=1,"✓ OK","❌ "&TEXT(D25-'balance_raw_61056416'!$D$48,"+#,##0;-#,##0")&" t.kr.")) | F63: Verificerer at sum(EK+Forpligtelser) matcher Passiver-totalen.
A64: Aktiver i alt = Passiver i alt | B64: =IF(ABS(B21-B25)<=1,"✓ OK","❌ "&TEXT(B21-B25,"+#,##0;-#,##0")&" t.kr.") | C64: =IF(ABS(C21-C25)<=1,"✓ OK","❌ "&TEXT(C21-C25,"+#,##0;-#,##0")&" t.kr.") | D64: =IF(ABS(D21-D25)<=1,"✓ OK","❌ "&TEXT(D21-D25,"+#,##0;-#,##0")&" t.kr.") | F64: Balance-identitet på arket selv. Skal altid være 0 differance.
A65: Bruttoresultat (beregnet) = fsa:GrossResult | B65: =IF('res_raw_61056416'!$F$4="","—",IF(ABS(B7-'res_raw_61056416'!$F$4)<=1,"✓ OK","❌ "&TEXT(B7-'res_raw_61056416'!$F$4,"+#,##0;-#,##0")&" t.kr.")) | C65: =IF('res_raw_61056416'!$E$4="","—",IF(ABS(C7-'res_raw_61056416'!$E$4)<=1,"✓ OK","❌ "&TEXT(C7-'res_raw_61056416'!$E$4,"+#,##0;-#,##0")&" t.kr.")) | D65: =IF('res_raw_61056416'!$D$4="","—",IF(ABS(D7-'res_raw_61056416'!$D$4)<=1,"✓ OK","❌ "&TEXT(D7-'res_raw_61056416'!$D$4,"+#,##0;-#,##0")&" t.kr.")) | F65: Hvis Nettoomsætning eller omkostninger mangler, vil sumberegnet bruttoresultat afvige.
A66: EBIT (beregnet) = fsa:ProfitLossFromOrdinaryOperatingActivities | B66: =IF('res_raw_61056416'!$F$10="","—",IF(ABS(B13-'res_raw_61056416'!$F$10)<=1,"✓ OK","❌ "&TEXT(B13-'res_raw_61056416'!$F$10,"+#,##0;-#,##0")&" t.kr.")) | C66: =IF('res_raw_61056416'!$E$10="","—",IF(ABS(C13-'res_raw_61056416'!$E$10)<=1,"✓ OK","❌ "&TEXT(C13-'res_raw_61056416'!$E$10,"+#,##0;-#,##0")&" t.kr.")) | D66: =IF('res_raw_61056416'!$D$10="","—",IF(ABS(D13-'res_raw_61056416'!$D$10)<=1,"✓ OK","❌ "&TEXT(D13-'res_raw_61056416'!$D$10,"+#,##0;-#,##0")&" t.kr.")) | F66: Verificerer at sumberegnet EBIT matcher det rapporterede.
A67: EBT (beregnet) = fsa:ProfitLossFromOrdinaryActivitiesBeforeTax | B67: =IF('res_raw_61056416'!$F$15="","—",IF(ABS(B16-'res_raw_61056416'!$F$15)<=1,"✓ OK","❌ "&TEXT(B16-'res_raw_61056416'!$F$15,"+#,##0;-#,##0")&" t.kr.")) | C67: =IF('res_raw_61056416'!$E$15="","—",IF(ABS(C16-'res_raw_61056416'!$E$15)<=1,"✓ OK","❌ "&TEXT(C16-'res_raw_61056416'!$E$15,"+#,##0;-#,##0")&" t.kr.")) | D67: =IF('res_raw_61056416'!$D$15="","—",IF(ABS(D16-'res_raw_61056416'!$D$15)<=1,"✓ OK","❌ "&TEXT(D16-'res_raw_61056416'!$D$15,"+#,##0;-#,##0")&" t.kr.")) | F67: Verificerer at sumberegnet resultat før skat matcher det rapporterede.
