Workbook

Sheet Overblik_80673612
A1: Scanpan A/S (CVR 80673612) — Regnskabsanalyse – Resultatopgørelse & Balance (t.kr.) · Klasse C-mellem · Revision
H2: Indekstal (2021=100)
A3: Resultatopgørelse t.kr. | B3: 2021 | C3: 2022 | D3: 2023 | E3: 2024 | F3: 2025 | H3: 2021 | I3: 2022 | J3: 2023 | K3: 2024 | L3: 2025
A4: Nettoomsætning | B4: ='res_raw_80673612'!$B$2 | C4: ='res_raw_80673612'!$C$2 | D4: ='res_raw_80673612'!$D$2 | E4: ='res_raw_80673612'!$E$2 | F4: ='res_raw_80673612'!$F$2 | H4: =IFERROR(B4/$B$4*100,"") | I4: =IFERROR(C4/$B$4*100,"") | J4: =IFERROR(D4/$B$4*100,"") | K4: =IFERROR(E4/$B$4*100,"") | L4: =IFERROR(F4/$B$4*100,"")
A5: Produktionsomkostninger | B5: ='res_raw_80673612'!$B$3 | C5: ='res_raw_80673612'!$C$3 | D5: ='res_raw_80673612'!$D$3 | E5: ='res_raw_80673612'!$E$3 | F5: ='res_raw_80673612'!$F$3 | H5: =IFERROR(B5/$B$5*100,"") | I5: =IFERROR(C5/$B$5*100,"") | J5: =IFERROR(D5/$B$5*100,"") | K5: =IFERROR(E5/$B$5*100,"") | L5: =IFERROR(F5/$B$5*100,"")
A6: Bruttoresultat | B6: ='res_raw_80673612'!$B$4 | C6: ='res_raw_80673612'!$C$4 | D6: ='res_raw_80673612'!$D$4 | E6: ='res_raw_80673612'!$E$4 | F6: ='res_raw_80673612'!$F$4 | H6: =IFERROR(B6/$B$6*100,"") | I6: =IFERROR(C6/$B$6*100,"") | J6: =IFERROR(D6/$B$6*100,"") | K6: =IFERROR(E6/$B$6*100,"") | L6: =IFERROR(F6/$B$6*100,"")
A7: Udviklingsomkostninger | B7: ='res_raw_80673612'!$B$5 | C7: ='res_raw_80673612'!$C$5 | D7: ='res_raw_80673612'!$D$5 | E7: ='res_raw_80673612'!$E$5 | F7: ='res_raw_80673612'!$F$5 | H7: =IFERROR(B7/$B$7*100,"") | I7: =IFERROR(C7/$B$7*100,"") | J7: =IFERROR(D7/$B$7*100,"") | K7: =IFERROR(E7/$B$7*100,"") | L7: =IFERROR(F7/$B$7*100,"")
A8: Salgs- og distributionsomkostninger | B8: ='res_raw_80673612'!$B$6 | C8: ='res_raw_80673612'!$C$6 | D8: ='res_raw_80673612'!$D$6 | E8: ='res_raw_80673612'!$E$6 | F8: ='res_raw_80673612'!$F$6 | H8: =IFERROR(B8/$B$8*100,"") | I8: =IFERROR(C8/$B$8*100,"") | J8: =IFERROR(D8/$B$8*100,"") | K8: =IFERROR(E8/$B$8*100,"") | L8: =IFERROR(F8/$B$8*100,"")
A9: Administrationsomkostninger | B9: ='res_raw_80673612'!$B$7 | C9: ='res_raw_80673612'!$C$7 | D9: ='res_raw_80673612'!$D$7 | E9: ='res_raw_80673612'!$E$7 | F9: ='res_raw_80673612'!$F$7 | H9: =IFERROR(B9/$B$9*100,"") | I9: =IFERROR(C9/$B$9*100,"") | J9: =IFERROR(D9/$B$9*100,"") | K9: =IFERROR(E9/$B$9*100,"") | L9: =IFERROR(F9/$B$9*100,"")
A10: Andre driftsindtægter | B10: ='res_raw_80673612'!$B$8 | C10: ='res_raw_80673612'!$C$8 | D10: ='res_raw_80673612'!$D$8 | E10: ='res_raw_80673612'!$E$8 | F10: ='res_raw_80673612'!$F$8 | H10: =IFERROR(B10/$B$10*100,"") | I10: =IFERROR(C10/$B$10*100,"") | J10: =IFERROR(D10/$B$10*100,"") | K10: =IFERROR(E10/$B$10*100,"") | L10: =IFERROR(F10/$B$10*100,"")
A11: Andre driftsomkostninger | B11: ='res_raw_80673612'!$B$9 | C11: ='res_raw_80673612'!$C$9 | D11: ='res_raw_80673612'!$D$9 | E11: ='res_raw_80673612'!$E$9 | F11: ='res_raw_80673612'!$F$9 | H11: =IFERROR(B11/$B$11*100,"") | I11: =IFERROR(C11/$B$11*100,"") | J11: =IFERROR(D11/$B$11*100,"") | K11: =IFERROR(E11/$B$11*100,"") | L11: =IFERROR(F11/$B$11*100,"")
A12: Resultat af primær drift | B12: ='res_raw_80673612'!$B$10 | C12: ='res_raw_80673612'!$C$10 | D12: ='res_raw_80673612'!$D$10 | E12: ='res_raw_80673612'!$E$10 | F12: ='res_raw_80673612'!$F$10 | H12: =IFERROR(B12/$B$12*100,"") | I12: =IFERROR(C12/$B$12*100,"") | J12: =IFERROR(D12/$B$12*100,"") | K12: =IFERROR(E12/$B$12*100,"") | L12: =IFERROR(F12/$B$12*100,"")
A13: Indtægter af kapitalandele, dattervirksomheder | B13: ='res_raw_80673612'!$B$11 | C13: ='res_raw_80673612'!$C$11 | D13: ='res_raw_80673612'!$D$11 | E13: ='res_raw_80673612'!$E$11 | F13: ='res_raw_80673612'!$F$11 | H13: =IFERROR(B13/$B$13*100,"") | I13: =IFERROR(C13/$B$13*100,"") | J13: =IFERROR(D13/$B$13*100,"") | K13: =IFERROR(E13/$B$13*100,"") | L13: =IFERROR(F13/$B$13*100,"")
A14: Finansielle indtægter | B14: ='res_raw_80673612'!$B$12 | C14: ='res_raw_80673612'!$C$12 | D14: ='res_raw_80673612'!$D$12 | E14: ='res_raw_80673612'!$E$12 | F14: ='res_raw_80673612'!$F$12 | H14: =IFERROR(B14/$B$14*100,"") | I14: =IFERROR(C14/$B$14*100,"") | J14: =IFERROR(D14/$B$14*100,"") | K14: =IFERROR(E14/$B$14*100,"") | L14: =IFERROR(F14/$B$14*100,"")
A15: Finansielle omkostninger | B15: ='res_raw_80673612'!$B$13 | C15: ='res_raw_80673612'!$C$13 | D15: ='res_raw_80673612'!$D$13 | E15: ='res_raw_80673612'!$E$13 | F15: ='res_raw_80673612'!$F$13 | H15: =IFERROR(B15/$B$15*100,"") | I15: =IFERROR(C15/$B$15*100,"") | J15: =IFERROR(D15/$B$15*100,"") | K15: =IFERROR(E15/$B$15*100,"") | L15: =IFERROR(F15/$B$15*100,"")
A16: Finansielle poster, netto | B16: ='res_raw_80673612'!$B$14 | C16: ='res_raw_80673612'!$C$14 | D16: ='res_raw_80673612'!$D$14 | E16: ='res_raw_80673612'!$E$14 | F16: ='res_raw_80673612'!$F$14 | H16: =IFERROR(B16/$B$16*100,"") | I16: =IFERROR(C16/$B$16*100,"") | J16: =IFERROR(D16/$B$16*100,"") | K16: =IFERROR(E16/$B$16*100,"") | L16: =IFERROR(F16/$B$16*100,"")
A17: Resultat før skat | B17: ='res_raw_80673612'!$B$15 | C17: ='res_raw_80673612'!$C$15 | D17: ='res_raw_80673612'!$D$15 | E17: ='res_raw_80673612'!$E$15 | F17: ='res_raw_80673612'!$F$15 | H17: =IFERROR(B17/$B$17*100,"") | I17: =IFERROR(C17/$B$17*100,"") | J17: =IFERROR(D17/$B$17*100,"") | K17: =IFERROR(E17/$B$17*100,"") | L17: =IFERROR(F17/$B$17*100,"")
A18: Skat af årets resultat | B18: ='res_raw_80673612'!$B$16 | C18: ='res_raw_80673612'!$C$16 | D18: ='res_raw_80673612'!$D$16 | E18: ='res_raw_80673612'!$E$16 | F18: ='res_raw_80673612'!$F$16 | H18: =IFERROR(B18/$B$18*100,"") | I18: =IFERROR(C18/$B$18*100,"") | J18: =IFERROR(D18/$B$18*100,"") | K18: =IFERROR(E18/$B$18*100,"") | L18: =IFERROR(F18/$B$18*100,"")
A19: Årets resultat | B19: ='res_raw_80673612'!$B$17 | C19: ='res_raw_80673612'!$C$17 | D19: ='res_raw_80673612'!$D$17 | E19: ='res_raw_80673612'!$E$17 | F19: ='res_raw_80673612'!$F$17 | H19: =IFERROR(B19/$B$19*100,"") | I19: =IFERROR(C19/$B$19*100,"") | J19: =IFERROR(D19/$B$19*100,"") | K19: =IFERROR(E19/$B$19*100,"") | L19: =IFERROR(F19/$B$19*100,"")
A21: AKTIVER t.kr. | B21: 2021 | C21: 2022 | D21: 2023 | E21: 2024 | F21: 2025 | H21: 2021 | I21: 2022 | J21: 2023 | K21: 2024 | L21: 2025
A22: Immaterielle anlægsaktiver | B22: ='balance_raw_80673612'!$B$2 | C22: ='balance_raw_80673612'!$C$2 | D22: ='balance_raw_80673612'!$D$2 | E22: ='balance_raw_80673612'!$E$2 | F22: ='balance_raw_80673612'!$F$2 | H22: =IFERROR(B22/$B$22*100,"") | I22: =IFERROR(C22/$B$22*100,"") | J22: =IFERROR(D22/$B$22*100,"") | K22: =IFERROR(E22/$B$22*100,"") | L22: =IFERROR(F22/$B$22*100,"")
A23: Grunde og bygninger | B23: ='balance_raw_80673612'!$B$3 | C23: ='balance_raw_80673612'!$C$3 | D23: ='balance_raw_80673612'!$D$3 | E23: ='balance_raw_80673612'!$E$3 | F23: ='balance_raw_80673612'!$F$3 | H23: =IFERROR(B23/$B$23*100,"") | I23: =IFERROR(C23/$B$23*100,"") | J23: =IFERROR(D23/$B$23*100,"") | K23: =IFERROR(E23/$B$23*100,"") | L23: =IFERROR(F23/$B$23*100,"")
A24: Produktionsanlæg og maskiner | B24: ='balance_raw_80673612'!$B$4 | C24: ='balance_raw_80673612'!$C$4 | D24: ='balance_raw_80673612'!$D$4 | E24: ='balance_raw_80673612'!$E$4 | F24: ='balance_raw_80673612'!$F$4 | H24: =IFERROR(B24/$B$24*100,"") | I24: =IFERROR(C24/$B$24*100,"") | J24: =IFERROR(D24/$B$24*100,"") | K24: =IFERROR(E24/$B$24*100,"") | L24: =IFERROR(F24/$B$24*100,"")
A25: Driftsmateriel og inventar | B25: ='balance_raw_80673612'!$B$5 | C25: ='balance_raw_80673612'!$C$5 | D25: ='balance_raw_80673612'!$D$5 | E25: ='balance_raw_80673612'!$E$5 | F25: ='balance_raw_80673612'!$F$5 | H25: =IFERROR(B25/$B$25*100,"") | I25: =IFERROR(C25/$B$25*100,"") | J25: =IFERROR(D25/$B$25*100,"") | K25: =IFERROR(E25/$B$25*100,"") | L25: =IFERROR(F25/$B$25*100,"")
A26: Indretning af lejede lokaler | B26: ='balance_raw_80673612'!$B$6 | C26: ='balance_raw_80673612'!$C$6 | D26: ='balance_raw_80673612'!$D$6 | E26: ='balance_raw_80673612'!$E$6 | F26: ='balance_raw_80673612'!$F$6 | H26: =IFERROR(B26/$B$26*100,"") | I26: =IFERROR(C26/$B$26*100,"") | J26: =IFERROR(D26/$B$26*100,"") | K26: =IFERROR(E26/$B$26*100,"") | L26: =IFERROR(F26/$B$26*100,"")
A27: Forudbetaling og anlægsaktiver under opførelse | B27: ='balance_raw_80673612'!$B$7 | C27: ='balance_raw_80673612'!$C$7 | D27: ='balance_raw_80673612'!$D$7 | E27: ='balance_raw_80673612'!$E$7 | F27: ='balance_raw_80673612'!$F$7 | H27: =IFERROR(B27/$B$27*100,"") | I27: =IFERROR(C27/$B$27*100,"") | J27: =IFERROR(D27/$B$27*100,"") | K27: =IFERROR(E27/$B$27*100,"") | L27: =IFERROR(F27/$B$27*100,"")
A28: Materielle anlægsaktiver | B28: ='balance_raw_80673612'!$B$8 | C28: ='balance_raw_80673612'!$C$8 | D28: ='balance_raw_80673612'!$D$8 | E28: ='balance_raw_80673612'!$E$8 | F28: ='balance_raw_80673612'!$F$8 | H28: =IFERROR(B28/$B$28*100,"") | I28: =IFERROR(C28/$B$28*100,"") | J28: =IFERROR(D28/$B$28*100,"") | K28: =IFERROR(E28/$B$28*100,"") | L28: =IFERROR(F28/$B$28*100,"")
A29: Kapitalandele, dattervirksomheder | B29: ='balance_raw_80673612'!$B$9 | C29: ='balance_raw_80673612'!$C$9 | D29: ='balance_raw_80673612'!$D$9 | E29: ='balance_raw_80673612'!$E$9 | F29: ='balance_raw_80673612'!$F$9 | H29: =IFERROR(B29/$B$29*100,"") | I29: =IFERROR(C29/$B$29*100,"") | J29: =IFERROR(D29/$B$29*100,"") | K29: =IFERROR(E29/$B$29*100,"") | L29: =IFERROR(F29/$B$29*100,"")
A30: Deposita | B30: ='balance_raw_80673612'!$B$10 | C30: ='balance_raw_80673612'!$C$10 | D30: ='balance_raw_80673612'!$D$10 | E30: ='balance_raw_80673612'!$E$10 | F30: ='balance_raw_80673612'!$F$10 | H30: =IFERROR(B30/$B$30*100,"") | I30: =IFERROR(C30/$B$30*100,"") | J30: =IFERROR(D30/$B$30*100,"") | K30: =IFERROR(E30/$B$30*100,"") | L30: =IFERROR(F30/$B$30*100,"")
A31: Finansielle anlægsaktiver | B31: ='balance_raw_80673612'!$B$11 | C31: ='balance_raw_80673612'!$C$11 | D31: ='balance_raw_80673612'!$D$11 | E31: ='balance_raw_80673612'!$E$11 | F31: ='balance_raw_80673612'!$F$11 | H31: =IFERROR(B31/$B$31*100,"") | I31: =IFERROR(C31/$B$31*100,"") | J31: =IFERROR(D31/$B$31*100,"") | K31: =IFERROR(E31/$B$31*100,"") | L31: =IFERROR(F31/$B$31*100,"")
A32: Anlægsaktiver | B32: ='balance_raw_80673612'!$B$12 | C32: ='balance_raw_80673612'!$C$12 | D32: ='balance_raw_80673612'!$D$12 | E32: ='balance_raw_80673612'!$E$12 | F32: ='balance_raw_80673612'!$F$12 | H32: =IFERROR(B32/$B$32*100,"") | I32: =IFERROR(C32/$B$32*100,"") | J32: =IFERROR(D32/$B$32*100,"") | K32: =IFERROR(E32/$B$32*100,"") | L32: =IFERROR(F32/$B$32*100,"")
A33: Råvarer og hjælpematerialer | B33: ='balance_raw_80673612'!$B$13 | C33: ='balance_raw_80673612'!$C$13 | D33: ='balance_raw_80673612'!$D$13 | E33: ='balance_raw_80673612'!$E$13 | F33: ='balance_raw_80673612'!$F$13 | H33: =IFERROR(B33/$B$33*100,"") | I33: =IFERROR(C33/$B$33*100,"") | J33: =IFERROR(D33/$B$33*100,"") | K33: =IFERROR(E33/$B$33*100,"") | L33: =IFERROR(F33/$B$33*100,"")
A34: Varer under fremstilling | B34: ='balance_raw_80673612'!$B$14 | C34: ='balance_raw_80673612'!$C$14 | D34: ='balance_raw_80673612'!$D$14 | E34: ='balance_raw_80673612'!$E$14 | F34: ='balance_raw_80673612'!$F$14 | H34: =IFERROR(B34/$B$34*100,"") | I34: =IFERROR(C34/$B$34*100,"") | J34: =IFERROR(D34/$B$34*100,"") | K34: =IFERROR(E34/$B$34*100,"") | L34: =IFERROR(F34/$B$34*100,"")
A35: Færdigvarer og handelsvarer | B35: ='balance_raw_80673612'!$B$15 | C35: ='balance_raw_80673612'!$C$15 | D35: ='balance_raw_80673612'!$D$15 | E35: ='balance_raw_80673612'!$E$15 | F35: ='balance_raw_80673612'!$F$15 | H35: =IFERROR(B35/$B$35*100,"") | I35: =IFERROR(C35/$B$35*100,"") | J35: =IFERROR(D35/$B$35*100,"") | K35: =IFERROR(E35/$B$35*100,"") | L35: =IFERROR(F35/$B$35*100,"")
A36: Varebeholdninger | B36: ='balance_raw_80673612'!$B$16 | C36: ='balance_raw_80673612'!$C$16 | D36: ='balance_raw_80673612'!$D$16 | E36: ='balance_raw_80673612'!$E$16 | F36: ='balance_raw_80673612'!$F$16 | H36: =IFERROR(B36/$B$36*100,"") | I36: =IFERROR(C36/$B$36*100,"") | J36: =IFERROR(D36/$B$36*100,"") | K36: =IFERROR(E36/$B$36*100,"") | L36: =IFERROR(F36/$B$36*100,"")
A37: Tilgodehavender fra salg og tjenesteydelser | B37: ='balance_raw_80673612'!$B$17 | C37: ='balance_raw_80673612'!$C$17 | D37: ='balance_raw_80673612'!$D$17 | E37: ='balance_raw_80673612'!$E$17 | F37: ='balance_raw_80673612'!$F$17 | H37: =IFERROR(B37/$B$37*100,"") | I37: =IFERROR(C37/$B$37*100,"") | J37: =IFERROR(D37/$B$37*100,"") | K37: =IFERROR(E37/$B$37*100,"") | L37: =IFERROR(F37/$B$37*100,"")
A38: Tilgodehavender hos tilknyttede virksomheder | B38: ='balance_raw_80673612'!$B$18 | C38: ='balance_raw_80673612'!$C$18 | D38: ='balance_raw_80673612'!$D$18 | E38: ='balance_raw_80673612'!$E$18 | F38: ='balance_raw_80673612'!$F$18 | H38: =IFERROR(B38/$B$38*100,"") | I38: =IFERROR(C38/$B$38*100,"") | J38: =IFERROR(D38/$B$38*100,"") | K38: =IFERROR(E38/$B$38*100,"") | L38: =IFERROR(F38/$B$38*100,"")
A39: Andre tilgodehavender | B39: ='balance_raw_80673612'!$B$19 | C39: ='balance_raw_80673612'!$C$19 | D39: ='balance_raw_80673612'!$D$19 | E39: ='balance_raw_80673612'!$E$19 | F39: ='balance_raw_80673612'!$F$19 | H39: =IFERROR(B39/$B$39*100,"") | I39: =IFERROR(C39/$B$39*100,"") | J39: =IFERROR(D39/$B$39*100,"") | K39: =IFERROR(E39/$B$39*100,"") | L39: =IFERROR(F39/$B$39*100,"")
A40: Periodeafgrænsningsposter (aktiver) | B40: ='balance_raw_80673612'!$B$20 | C40: ='balance_raw_80673612'!$C$20 | D40: ='balance_raw_80673612'!$D$20 | E40: ='balance_raw_80673612'!$E$20 | F40: ='balance_raw_80673612'!$F$20 | H40: =IFERROR(B40/$B$40*100,"") | I40: =IFERROR(C40/$B$40*100,"") | J40: =IFERROR(D40/$B$40*100,"") | K40: =IFERROR(E40/$B$40*100,"") | L40: =IFERROR(F40/$B$40*100,"")
A41: Udskudt skatteaktiv | B41: ='balance_raw_80673612'!$B$21 | C41: ='balance_raw_80673612'!$C$21 | D41: ='balance_raw_80673612'!$D$21 | E41: ='balance_raw_80673612'!$E$21 | F41: ='balance_raw_80673612'!$F$21 | H41: =IFERROR(B41/$B$41*100,"") | I41: =IFERROR(C41/$B$41*100,"") | J41: =IFERROR(D41/$B$41*100,"") | K41: =IFERROR(E41/$B$41*100,"") | L41: =IFERROR(F41/$B$41*100,"")
A42: Tilgodehavende skat hos tilknyttede virksomheder | B42: ='balance_raw_80673612'!$B$22 | C42: ='balance_raw_80673612'!$C$22 | D42: ='balance_raw_80673612'!$D$22 | E42: ='balance_raw_80673612'!$E$22 | F42: ='balance_raw_80673612'!$F$22 | H42: =IFERROR(B42/$B$42*100,"") | I42: =IFERROR(C42/$B$42*100,"") | J42: =IFERROR(D42/$B$42*100,"") | K42: =IFERROR(E42/$B$42*100,"") | L42: =IFERROR(F42/$B$42*100,"")
A43: Kortfristede skattetilgodehavender | B43: ='balance_raw_80673612'!$B$23 | C43: ='balance_raw_80673612'!$C$23 | D43: ='balance_raw_80673612'!$D$23 | E43: ='balance_raw_80673612'!$E$23 | F43: ='balance_raw_80673612'!$F$23 | H43: =IFERROR(B43/$B$43*100,"") | I43: =IFERROR(C43/$B$43*100,"") | J43: =IFERROR(D43/$B$43*100,"") | K43: =IFERROR(E43/$B$43*100,"") | L43: =IFERROR(F43/$B$43*100,"")
A44: Tilgodehavender | B44: ='balance_raw_80673612'!$B$24 | C44: ='balance_raw_80673612'!$C$24 | D44: ='balance_raw_80673612'!$D$24 | E44: ='balance_raw_80673612'!$E$24 | F44: ='balance_raw_80673612'!$F$24 | H44: =IFERROR(B44/$B$44*100,"") | I44: =IFERROR(C44/$B$44*100,"") | J44: =IFERROR(D44/$B$44*100,"") | K44: =IFERROR(E44/$B$44*100,"") | L44: =IFERROR(F44/$B$44*100,"")
A45: Værdipapirer | B45: ='balance_raw_80673612'!$B$25 | C45: ='balance_raw_80673612'!$C$25 | D45: ='balance_raw_80673612'!$D$25 | E45: ='balance_raw_80673612'!$E$25 | F45: ='balance_raw_80673612'!$F$25 | H45: =IFERROR(B45/$B$45*100,"") | I45: =IFERROR(C45/$B$45*100,"") | J45: =IFERROR(D45/$B$45*100,"") | K45: =IFERROR(E45/$B$45*100,"") | L45: =IFERROR(F45/$B$45*100,"")
A46: Likvide beholdninger | B46: ='balance_raw_80673612'!$B$26 | C46: ='balance_raw_80673612'!$C$26 | D46: ='balance_raw_80673612'!$D$26 | E46: ='balance_raw_80673612'!$E$26 | F46: ='balance_raw_80673612'!$F$26 | H46: =IFERROR(B46/$B$46*100,"") | I46: =IFERROR(C46/$B$46*100,"") | J46: =IFERROR(D46/$B$46*100,"") | K46: =IFERROR(E46/$B$46*100,"") | L46: =IFERROR(F46/$B$46*100,"")
A47: Omsætningsaktiver | B47: ='balance_raw_80673612'!$B$27 | C47: ='balance_raw_80673612'!$C$27 | D47: ='balance_raw_80673612'!$D$27 | E47: ='balance_raw_80673612'!$E$27 | F47: ='balance_raw_80673612'!$F$27 | H47: =IFERROR(B47/$B$47*100,"") | I47: =IFERROR(C47/$B$47*100,"") | J47: =IFERROR(D47/$B$47*100,"") | K47: =IFERROR(E47/$B$47*100,"") | L47: =IFERROR(F47/$B$47*100,"")
A48: Aktiver | B48: ='balance_raw_80673612'!$B$28 | C48: ='balance_raw_80673612'!$C$28 | D48: ='balance_raw_80673612'!$D$28 | E48: ='balance_raw_80673612'!$E$28 | F48: ='balance_raw_80673612'!$F$28 | H48: =IFERROR(B48/$B$48*100,"") | I48: =IFERROR(C48/$B$48*100,"") | J48: =IFERROR(D48/$B$48*100,"") | K48: =IFERROR(E48/$B$48*100,"") | L48: =IFERROR(F48/$B$48*100,"")
A50: PASSIVER t.kr. | B50: 2021 | C50: 2022 | D50: 2023 | E50: 2024 | F50: 2025 | H50: 2021 | I50: 2022 | J50: 2023 | K50: 2024 | L50: 2025
A51: Selskabskapital | B51: ='balance_raw_80673612'!$B$29 | C51: ='balance_raw_80673612'!$C$29 | D51: ='balance_raw_80673612'!$D$29 | E51: ='balance_raw_80673612'!$E$29 | F51: ='balance_raw_80673612'!$F$29 | H51: =IFERROR(B51/$B$51*100,"") | I51: =IFERROR(C51/$B$51*100,"") | J51: =IFERROR(D51/$B$51*100,"") | K51: =IFERROR(E51/$B$51*100,"") | L51: =IFERROR(F51/$B$51*100,"")
A52: Reserve for nettoopskrivning (indre værdis metode) | B52: ='balance_raw_80673612'!$B$30 | C52: ='balance_raw_80673612'!$C$30 | D52: ='balance_raw_80673612'!$D$30 | E52: ='balance_raw_80673612'!$E$30 | F52: ='balance_raw_80673612'!$F$30 | H52: =IFERROR(B52/$B$52*100,"") | I52: =IFERROR(C52/$B$52*100,"") | J52: =IFERROR(D52/$B$52*100,"") | K52: =IFERROR(E52/$B$52*100,"") | L52: =IFERROR(F52/$B$52*100,"")
A53: Reserve for udviklingsomkostninger | B53: ='balance_raw_80673612'!$B$31 | C53: ='balance_raw_80673612'!$C$31 | D53: ='balance_raw_80673612'!$D$31 | E53: ='balance_raw_80673612'!$E$31 | F53: ='balance_raw_80673612'!$F$31 | H53: =IFERROR(B53/$B$53*100,"") | I53: =IFERROR(C53/$B$53*100,"") | J53: =IFERROR(D53/$B$53*100,"") | K53: =IFERROR(E53/$B$53*100,"") | L53: =IFERROR(F53/$B$53*100,"")
A54: Reserve for sikringstransaktioner | B54: ='balance_raw_80673612'!$B$32 | C54: ='balance_raw_80673612'!$C$32 | D54: ='balance_raw_80673612'!$D$32 | E54: ='balance_raw_80673612'!$E$32 | F54: ='balance_raw_80673612'!$F$32 | H54: =IFERROR(B54/$B$54*100,"") | I54: =IFERROR(C54/$B$54*100,"") | J54: =IFERROR(D54/$B$54*100,"") | K54: =IFERROR(E54/$B$54*100,"") | L54: =IFERROR(F54/$B$54*100,"")
A55: Andre reserver | B55: ='balance_raw_80673612'!$B$33 | C55: ='balance_raw_80673612'!$C$33 | D55: ='balance_raw_80673612'!$D$33 | E55: ='balance_raw_80673612'!$E$33 | F55: ='balance_raw_80673612'!$F$33 | H55: =IFERROR(B55/$B$55*100,"") | I55: =IFERROR(C55/$B$55*100,"") | J55: =IFERROR(D55/$B$55*100,"") | K55: =IFERROR(E55/$B$55*100,"") | L55: =IFERROR(F55/$B$55*100,"")
A56: Overført resultat | B56: ='balance_raw_80673612'!$B$34 | C56: ='balance_raw_80673612'!$C$34 | D56: ='balance_raw_80673612'!$D$34 | E56: ='balance_raw_80673612'!$E$34 | F56: ='balance_raw_80673612'!$F$34 | H56: =IFERROR(B56/$B$56*100,"") | I56: =IFERROR(C56/$B$56*100,"") | J56: =IFERROR(D56/$B$56*100,"") | K56: =IFERROR(E56/$B$56*100,"") | L56: =IFERROR(F56/$B$56*100,"")
A57: Egenkapital i alt | B57: ='balance_raw_80673612'!$B$35 | C57: ='balance_raw_80673612'!$C$35 | D57: ='balance_raw_80673612'!$D$35 | E57: ='balance_raw_80673612'!$E$35 | F57: ='balance_raw_80673612'!$F$35 | H57: =IFERROR(B57/$B$57*100,"") | I57: =IFERROR(C57/$B$57*100,"") | J57: =IFERROR(D57/$B$57*100,"") | K57: =IFERROR(E57/$B$57*100,"") | L57: =IFERROR(F57/$B$57*100,"")
A58: Hensættelse til udskudt skat | B58: ='balance_raw_80673612'!$B$36 | C58: ='balance_raw_80673612'!$C$36 | D58: ='balance_raw_80673612'!$D$36 | E58: ='balance_raw_80673612'!$E$36 | F58: ='balance_raw_80673612'!$F$36 | H58: =IFERROR(B58/$B$58*100,"") | I58: =IFERROR(C58/$B$58*100,"") | J58: =IFERROR(D58/$B$58*100,"") | K58: =IFERROR(E58/$B$58*100,"") | L58: =IFERROR(F58/$B$58*100,"")
A59: Hensatte forpligtelser | B59: ='balance_raw_80673612'!$B$37 | C59: ='balance_raw_80673612'!$C$37 | D59: ='balance_raw_80673612'!$D$37 | E59: ='balance_raw_80673612'!$E$37 | F59: ='balance_raw_80673612'!$F$37 | H59: =IFERROR(B59/$B$59*100,"") | I59: =IFERROR(C59/$B$59*100,"") | J59: =IFERROR(D59/$B$59*100,"") | K59: =IFERROR(E59/$B$59*100,"") | L59: =IFERROR(F59/$B$59*100,"")
A60: Ansvarlig lånekapital (langfristet) | B60: ='balance_raw_80673612'!$B$38 | C60: ='balance_raw_80673612'!$C$38 | D60: ='balance_raw_80673612'!$D$38 | E60: ='balance_raw_80673612'!$E$38 | F60: ='balance_raw_80673612'!$F$38 | H60: =IFERROR(B60/$B$60*100,"") | I60: =IFERROR(C60/$B$60*100,"") | J60: =IFERROR(D60/$B$60*100,"") | K60: =IFERROR(E60/$B$60*100,"") | L60: =IFERROR(F60/$B$60*100,"")
A61: Langfristede lån | B61: ='balance_raw_80673612'!$B$39 | C61: ='balance_raw_80673612'!$C$39 | D61: ='balance_raw_80673612'!$D$39 | E61: ='balance_raw_80673612'!$E$39 | F61: ='balance_raw_80673612'!$F$39 | H61: =IFERROR(B61/$B$61*100,"") | I61: =IFERROR(C61/$B$61*100,"") | J61: =IFERROR(D61/$B$61*100,"") | K61: =IFERROR(E61/$B$61*100,"") | L61: =IFERROR(F61/$B$61*100,"")
A62: Leasingforpligtelser (langfristet) | B62: ='balance_raw_80673612'!$B$40 | C62: ='balance_raw_80673612'!$C$40 | D62: ='balance_raw_80673612'!$D$40 | E62: ='balance_raw_80673612'!$E$40 | F62: ='balance_raw_80673612'!$F$40 | H62: =IFERROR(B62/$B$62*100,"") | I62: =IFERROR(C62/$B$62*100,"") | J62: =IFERROR(D62/$B$62*100,"") | K62: =IFERROR(E62/$B$62*100,"") | L62: =IFERROR(F62/$B$62*100,"")
A63: Anden gæld (langfristet) | B63: ='balance_raw_80673612'!$B$41 | C63: ='balance_raw_80673612'!$C$41 | D63: ='balance_raw_80673612'!$D$41 | E63: ='balance_raw_80673612'!$E$41 | F63: ='balance_raw_80673612'!$F$41 | H63: =IFERROR(B63/$B$63*100,"") | I63: =IFERROR(C63/$B$63*100,"") | J63: =IFERROR(D63/$B$63*100,"") | K63: =IFERROR(E63/$B$63*100,"") | L63: =IFERROR(F63/$B$63*100,"")
A64: Langfristede gældsforpligtelser | B64: ='balance_raw_80673612'!$B$42 | C64: ='balance_raw_80673612'!$C$42 | D64: ='balance_raw_80673612'!$D$42 | E64: ='balance_raw_80673612'!$E$42 | F64: ='balance_raw_80673612'!$F$42 | H64: =IFERROR(B64/$B$64*100,"") | I64: =IFERROR(C64/$B$64*100,"") | J64: =IFERROR(D64/$B$64*100,"") | K64: =IFERROR(E64/$B$64*100,"") | L64: =IFERROR(F64/$B$64*100,"")
A65: Ansvarlig lånekapital (kortfristet) | B65: ='balance_raw_80673612'!$B$43 | C65: ='balance_raw_80673612'!$C$43 | D65: ='balance_raw_80673612'!$D$43 | E65: ='balance_raw_80673612'!$E$43 | F65: ='balance_raw_80673612'!$F$43 | H65: =IFERROR(B65/$B$65*100,"") | I65: =IFERROR(C65/$B$65*100,"") | J65: =IFERROR(D65/$B$65*100,"") | K65: =IFERROR(E65/$B$65*100,"") | L65: =IFERROR(F65/$B$65*100,"")
A66: Kortfristet del af langfristede gældsforpligtelser | B66: ='balance_raw_80673612'!$B$44 | C66: ='balance_raw_80673612'!$C$44 | D66: ='balance_raw_80673612'!$D$44 | E66: ='balance_raw_80673612'!$E$44 | F66: ='balance_raw_80673612'!$F$44 | H66: =IFERROR(B66/$B$66*100,"") | I66: =IFERROR(C66/$B$66*100,"") | J66: =IFERROR(D66/$B$66*100,"") | K66: =IFERROR(E66/$B$66*100,"") | L66: =IFERROR(F66/$B$66*100,"")
A67: Kreditinstitutter | B67: ='balance_raw_80673612'!$B$45 | C67: ='balance_raw_80673612'!$C$45 | D67: ='balance_raw_80673612'!$D$45 | E67: ='balance_raw_80673612'!$E$45 | F67: ='balance_raw_80673612'!$F$45 | H67: =IFERROR(B67/$B$67*100,"") | I67: =IFERROR(C67/$B$67*100,"") | J67: =IFERROR(D67/$B$67*100,"") | K67: =IFERROR(E67/$B$67*100,"") | L67: =IFERROR(F67/$B$67*100,"")
A68: Leasingforpligtelser (kortfristet) | B68: ='balance_raw_80673612'!$B$46 | C68: ='balance_raw_80673612'!$C$46 | D68: ='balance_raw_80673612'!$D$46 | E68: ='balance_raw_80673612'!$E$46 | F68: ='balance_raw_80673612'!$F$46 | H68: =IFERROR(B68/$B$68*100,"") | I68: =IFERROR(C68/$B$68*100,"") | J68: =IFERROR(D68/$B$68*100,"") | K68: =IFERROR(E68/$B$68*100,"") | L68: =IFERROR(F68/$B$68*100,"")
A69: Leverandører af varer og tjenesteydelser | B69: ='balance_raw_80673612'!$B$47 | C69: ='balance_raw_80673612'!$C$47 | D69: ='balance_raw_80673612'!$D$47 | E69: ='balance_raw_80673612'!$E$47 | F69: ='balance_raw_80673612'!$F$47 | H69: =IFERROR(B69/$B$69*100,"") | I69: =IFERROR(C69/$B$69*100,"") | J69: =IFERROR(D69/$B$69*100,"") | K69: =IFERROR(E69/$B$69*100,"") | L69: =IFERROR(F69/$B$69*100,"")
A70: Gæld til tilknyttede virksomheder | B70: ='balance_raw_80673612'!$B$48 | C70: ='balance_raw_80673612'!$C$48 | D70: ='balance_raw_80673612'!$D$48 | E70: ='balance_raw_80673612'!$E$48 | F70: ='balance_raw_80673612'!$F$48 | H70: =IFERROR(B70/$B$70*100,"") | I70: =IFERROR(C70/$B$70*100,"") | J70: =IFERROR(D70/$B$70*100,"") | K70: =IFERROR(E70/$B$70*100,"") | L70: =IFERROR(F70/$B$70*100,"")
A71: Gæld til selskabsdeltagere og ledelse | B71: ='balance_raw_80673612'!$B$49 | C71: ='balance_raw_80673612'!$C$49 | D71: ='balance_raw_80673612'!$D$49 | E71: ='balance_raw_80673612'!$E$49 | F71: ='balance_raw_80673612'!$F$49 | H71: =IFERROR(B71/$B$71*100,"") | I71: =IFERROR(C71/$B$71*100,"") | J71: =IFERROR(D71/$B$71*100,"") | K71: =IFERROR(E71/$B$71*100,"") | L71: =IFERROR(F71/$B$71*100,"")
A72: Selskabsskat | B72: ='balance_raw_80673612'!$B$50 | C72: ='balance_raw_80673612'!$C$50 | D72: ='balance_raw_80673612'!$D$50 | E72: ='balance_raw_80673612'!$E$50 | F72: ='balance_raw_80673612'!$F$50 | H72: =IFERROR(B72/$B$72*100,"") | I72: =IFERROR(C72/$B$72*100,"") | J72: =IFERROR(D72/$B$72*100,"") | K72: =IFERROR(E72/$B$72*100,"") | L72: =IFERROR(F72/$B$72*100,"")
A73: Gæld til tilknyttede virksomheder vedr. selskabsskat | B73: ='balance_raw_80673612'!$B$51 | C73: ='balance_raw_80673612'!$C$51 | D73: ='balance_raw_80673612'!$D$51 | E73: ='balance_raw_80673612'!$E$51 | F73: ='balance_raw_80673612'!$F$51 | H73: =IFERROR(B73/$B$73*100,"") | I73: =IFERROR(C73/$B$73*100,"") | J73: =IFERROR(D73/$B$73*100,"") | K73: =IFERROR(E73/$B$73*100,"") | L73: =IFERROR(F73/$B$73*100,"")
A74: Anden gæld (kortfristet) | B74: ='balance_raw_80673612'!$B$52 | C74: ='balance_raw_80673612'!$C$52 | D74: ='balance_raw_80673612'!$D$52 | E74: ='balance_raw_80673612'!$E$52 | F74: ='balance_raw_80673612'!$F$52 | H74: =IFERROR(B74/$B$74*100,"") | I74: =IFERROR(C74/$B$74*100,"") | J74: =IFERROR(D74/$B$74*100,"") | K74: =IFERROR(E74/$B$74*100,"") | L74: =IFERROR(F74/$B$74*100,"")
A75: Periodeafgrænsningsposter (passiver) | B75: ='balance_raw_80673612'!$B$53 | C75: ='balance_raw_80673612'!$C$53 | D75: ='balance_raw_80673612'!$D$53 | E75: ='balance_raw_80673612'!$E$53 | F75: ='balance_raw_80673612'!$F$53 | H75: =IFERROR(B75/$B$75*100,"") | I75: =IFERROR(C75/$B$75*100,"") | J75: =IFERROR(D75/$B$75*100,"") | K75: =IFERROR(E75/$B$75*100,"") | L75: =IFERROR(F75/$B$75*100,"")
A76: Kortfristede gældsforpligtelser | B76: ='balance_raw_80673612'!$B$54 | C76: ='balance_raw_80673612'!$C$54 | D76: ='balance_raw_80673612'!$D$54 | E76: ='balance_raw_80673612'!$E$54 | F76: ='balance_raw_80673612'!$F$54 | H76: =IFERROR(B76/$B$76*100,"") | I76: =IFERROR(C76/$B$76*100,"") | J76: =IFERROR(D76/$B$76*100,"") | K76: =IFERROR(E76/$B$76*100,"") | L76: =IFERROR(F76/$B$76*100,"")
A77: Gældsforpligtelser | B77: ='balance_raw_80673612'!$B$55 | C77: ='balance_raw_80673612'!$C$55 | D77: ='balance_raw_80673612'!$D$55 | E77: ='balance_raw_80673612'!$E$55 | F77: ='balance_raw_80673612'!$F$55 | H77: =IFERROR(B77/$B$77*100,"") | I77: =IFERROR(C77/$B$77*100,"") | J77: =IFERROR(D77/$B$77*100,"") | K77: =IFERROR(E77/$B$77*100,"") | L77: =IFERROR(F77/$B$77*100,"")
A78: Passiver | B78: ='balance_raw_80673612'!$B$56 | C78: ='balance_raw_80673612'!$C$56 | D78: ='balance_raw_80673612'!$D$56 | E78: ='balance_raw_80673612'!$E$56 | F78: ='balance_raw_80673612'!$F$56 | H78: =IFERROR(B78/$B$78*100,"") | I78: =IFERROR(C78/$B$78*100,"") | J78: =IFERROR(D78/$B$78*100,"") | K78: =IFERROR(E78/$B$78*100,"") | L78: =IFERROR(F78/$B$78*100,"")
A80: NØGLEOPLYSNINGER | B80: 2021 | C80: 2022 | D80: 2023 | E80: 2024 | F80: 2025
A81: Gns. antal medarbejdere | B81: ='res_raw_80673612'!$B$18 | C81: ='res_raw_80673612'!$C$18 | D81: ='res_raw_80673612'!$D$18 | E81: ='res_raw_80673612'!$E$18 | F81: ='res_raw_80673612'!$F$18 | H81: =IFERROR(B81/$B$81*100,"") | I81: =IFERROR(C81/$B$81*100,"") | J81: =IFERROR(D81/$B$81*100,"") | K81: =IFERROR(E81/$B$81*100,"") | L81: =IFERROR(F81/$B$81*100,"")
A82: Investering i materielle anlægsaktiver | B82: ='res_raw_80673612'!$B$19 | C82: ='res_raw_80673612'!$C$19 | D82: ='res_raw_80673612'!$D$19 | E82: ='res_raw_80673612'!$E$19 | F82: ='res_raw_80673612'!$F$19 | H82: =IFERROR(B82/$B$82*100,"") | I82: =IFERROR(C82/$B$82*100,"") | J82: =IFERROR(D82/$B$82*100,"") | K82: =IFERROR(E82/$B$82*100,"") | L82: =IFERROR(F82/$B$82*100,"")
A84: NØGLETAL | B84: 2021 | C84: 2022 | D84: 2023 | E84: 2024 | F84: 2025
A85: Afkastningsgrad, % | B85: =IFERROR(($B$12+$B$14+$B$13)/$B$48*100,"") | C85: =IFERROR(($C$12+$C$14+$C$13)/$C$48*100,"") | D85: =IFERROR(($D$12+$D$14+$D$13)/$D$48*100,"") | E85: =IFERROR(($E$12+$E$14+$E$13)/$E$48*100,"") | F85: =IFERROR(($F$12+$F$14+$F$13)/$F$48*100,"")
A86: Overskudsgrad (af bruttofortjeneste), % | B86: =IFERROR(($B$12+$B$14+$B$13)/$B$6*100,"") | C86: =IFERROR(($C$12+$C$14+$C$13)/$C$6*100,"") | D86: =IFERROR(($D$12+$D$14+$D$13)/$D$6*100,"") | E86: =IFERROR(($E$12+$E$14+$E$13)/$E$6*100,"") | F86: =IFERROR(($F$12+$F$14+$F$13)/$F$6*100,"")
A87: Aktivernes omsætningshastighed (af bruttofortjeneste), gange | B87: =IFERROR($B$6/$B$48,"") | C87: =IFERROR($C$6/$C$48,"") | D87: =IFERROR($D$6/$D$48,"") | E87: =IFERROR($E$6/$E$48,"") | F87: =IFERROR($F$6/$F$48,"")
A88: Egenkapitalens forrentning, % | B88: =IFERROR($B$17/$B$57*100,"") | C88: =IFERROR($C$17/$C$57*100,"") | D88: =IFERROR($D$17/$D$57*100,"") | E88: =IFERROR($E$17/$E$57*100,"") | F88: =IFERROR($F$17/$F$57*100,"")
A89: Gældsrente, % | B89: =IFERROR($B$15/($B$78-$B$57)*100,"") | C89: =IFERROR($C$15/($C$78-$C$57)*100,"") | D89: =IFERROR($D$15/($D$78-$D$57)*100,"") | E89: =IFERROR($E$15/($E$78-$E$57)*100,"") | F89: =IFERROR($F$15/($F$78-$F$57)*100,"")
A90: Soliditetsgrad, % | B90: =IFERROR($B$57/$B$48*100,"") | C90: =IFERROR($C$57/$C$48*100,"") | D90: =IFERROR($D$57/$D$48*100,"") | E90: =IFERROR($E$57/$E$48*100,"") | F90: =IFERROR($F$57/$F$48*100,"")
A91: Gearing | B91: =IFERROR(($B$78-$B$57)/$B$57,"") | C91: =IFERROR(($C$78-$C$57)/$C$57,"") | D91: =IFERROR(($D$78-$D$57)/$D$57,"") | E91: =IFERROR(($E$78-$E$57)/$E$57,"") | F91: =IFERROR(($F$78-$F$57)/$F$57,"")
A92: Likviditetsgrad, % | B92: =IFERROR($B$47/$B$76*100,"") | C92: =IFERROR($C$47/$C$76*100,"") | D92: =IFERROR($D$47/$D$76*100,"") | E92: =IFERROR($E$47/$E$76*100,"") | F92: =IFERROR($F$47/$F$76*100,"")
A93: Rentemarginal, % | B93: =IFERROR(B85-B89,"") | C93: =IFERROR(C85-C89,"") | D93: =IFERROR(D85-D89,"") | E93: =IFERROR(E85-E89,"") | F93: =IFERROR(F85-F89,"")
A94: Gældsandel, % | B94: =IFERROR(($B$78-$B$57)/$B$48*100,"") | C94: =IFERROR(($C$78-$C$57)/$C$48*100,"") | D94: =IFERROR(($D$78-$D$57)/$D$48*100,"") | E94: =IFERROR(($E$78-$E$57)/$E$48*100,"") | F94: =IFERROR(($F$78-$F$57)/$F$48*100,"")
A95: Kapitalbindingsgrad, % | B95: =IFERROR($B$32/($B$57+$B$64)*100,"") | C95: =IFERROR($C$32/($C$57+$C$64)*100,"") | D95: =IFERROR($D$32/($D$57+$D$64)*100,"") | E95: =IFERROR($E$32/($E$57+$E$64)*100,"") | F95: =IFERROR($F$32/($F$57+$F$64)*100,"")
A97: PENGESTRØMSOPGØRELSE t.kr.
A98: Pengestrømme fra driftsaktivitet | B98: ='pengestrom_raw_80673612'!$B$2 | C98: ='pengestrom_raw_80673612'!$C$2 | D98: ='pengestrom_raw_80673612'!$D$2 | E98: ='pengestrom_raw_80673612'!$E$2 | F98: ='pengestrom_raw_80673612'!$F$2
A99: Pengestrømme fra investeringsaktivitet | B99: ='pengestrom_raw_80673612'!$B$3 | C99: ='pengestrom_raw_80673612'!$C$3 | D99: ='pengestrom_raw_80673612'!$D$3 | E99: ='pengestrom_raw_80673612'!$E$3 | F99: ='pengestrom_raw_80673612'!$F$3
A100: Pengestrømme fra finansieringsaktivitet | B100: ='pengestrom_raw_80673612'!$B$4 | C100: ='pengestrom_raw_80673612'!$C$4 | D100: ='pengestrom_raw_80673612'!$D$4 | E100: ='pengestrom_raw_80673612'!$E$4 | F100: ='pengestrom_raw_80673612'!$F$4
A101: Årets pengestrøm (rapporteret) | B101: ='pengestrom_raw_80673612'!$B$5 | C101: ='pengestrom_raw_80673612'!$C$5 | D101: ='pengestrom_raw_80673612'!$D$5 | E101: ='pengestrom_raw_80673612'!$E$5 | F101: ='pengestrom_raw_80673612'!$F$5
A102: Krydstjek: drift + inv. + fin. = årets pengestrøm | B102: =IF(ABS(('pengestrom_raw_80673612'!$B$2+'pengestrom_raw_80673612'!$B$3+'pengestrom_raw_80673612'!$B$4)-'pengestrom_raw_80673612'!$B$5)<=2,"✓","⚠ "&TEXT(('pengestrom_raw_80673612'!$B$2+'pengestrom_raw_80673612'!$B$3+'pengestrom_raw_80673612'!$B$4)-'pengestrom_raw_80673612'!$B$5,"+#,##0;-#,##0")) | C102: =IF(ABS(('pengestrom_raw_80673612'!$C$2+'pengestrom_raw_80673612'!$C$3+'pengestrom_raw_80673612'!$C$4)-'pengestrom_raw_80673612'!$C$5)<=2,"✓","⚠ "&TEXT(('pengestrom_raw_80673612'!$C$2+'pengestrom_raw_80673612'!$C$3+'pengestrom_raw_80673612'!$C$4)-'pengestrom_raw_80673612'!$C$5,"+#,##0;-#,##0")) | D102: =IF(ABS(('pengestrom_raw_80673612'!$D$2+'pengestrom_raw_80673612'!$D$3+'pengestrom_raw_80673612'!$D$4)-'pengestrom_raw_80673612'!$D$5)<=2,"✓","⚠ "&TEXT(('pengestrom_raw_80673612'!$D$2+'pengestrom_raw_80673612'!$D$3+'pengestrom_raw_80673612'!$D$4)-'pengestrom_raw_80673612'!$D$5,"+#,##0;-#,##0")) | E102: =IF(ABS(('pengestrom_raw_80673612'!$E$2+'pengestrom_raw_80673612'!$E$3+'pengestrom_raw_80673612'!$E$4)-'pengestrom_raw_80673612'!$E$5)<=2,"✓","⚠ "&TEXT(('pengestrom_raw_80673612'!$E$2+'pengestrom_raw_80673612'!$E$3+'pengestrom_raw_80673612'!$E$4)-'pengestrom_raw_80673612'!$E$5,"+#,##0;-#,##0")) | F102: =IF(ABS(('pengestrom_raw_80673612'!$F$2+'pengestrom_raw_80673612'!$F$3+'pengestrom_raw_80673612'!$F$4)-'pengestrom_raw_80673612'!$F$5)<=2,"✓","⚠ "&TEXT(('pengestrom_raw_80673612'!$F$2+'pengestrom_raw_80673612'!$F$3+'pengestrom_raw_80673612'!$F$4)-'pengestrom_raw_80673612'!$F$5,"+#,##0;-#,##0"))

Sheet res_raw_80673612
A1: Scanpan A/S (CVR 80673612) — Resultatopgørelse & nøgleoplysninger (t.kr.) | B1: 2021 | C1: 2022 | D1: 2023 | E1: 2024 | F1: 2025
A2: Nettoomsætning
A3: Produktionsomkostninger
A4: Bruttoresultat | B4: 75873 | C4: 52019 | D4: 31064 | E4: 44876 | F4: 54264
A5: Udviklingsomkostninger
A6: Salgs- og distributionsomkostninger | B6: 26983 | C6: 25379 | D6: 24645 | E6: 26429 | F6: 27637
A7: Administrationsomkostninger | B7: 17351 | C7: 16466 | D7: 19296 | E7: 21534 | F7: 22151
A8: Andre driftsindtægter
A9: Andre driftsomkostninger | B9: 15 | C9: 0 | D9: 4 | E9: 0 | F9: 5
A10: Resultat af primær drift | B10: 31524 | C10: 10175 | D10: -12881 | E10: -3088 | F10: 4471
A11: Indtægter af kapitalandele, dattervirksomheder | B11: 0 | C11: 0 | D11: 0 | E11: 0 | F11: 0
A12: Finansielle indtægter | B12: 674 | C12: 664 | D12: 338 | E12: 309 | F12: 509
A13: Finansielle omkostninger | B13: 836 | C13: 1067 | D13: 628 | E13: 1603 | F13: 2502
A14: Finansielle poster, netto | B14: -162 | C14: -404 | D14: -290 | E14: -1294 | F14: -1993
A15: Resultat før skat | B15: 46170 | C15: 23988 | D15: -7153 | E15: 1475 | F15: 7257
A16: Skat af årets resultat | B16: 6583 | C16: 2299 | D16: -2815 | E16: -723 | F16: 515
A17: Årets resultat | B17: 39587 | C17: 21689 | D17: -4338 | E17: 2198 | F17: 6742
A18: Gns. antal medarbejdere | B18: 126 | C18: 120 | D18: 107 | E18: 98 | F18: 104
A19: Investering i materielle anlægsaktiver | B19: 4719 | C19: 1831 | D19: 462 | E19: 2585 | F19: 1745

Sheet balance_raw_80673612
A1: Scanpan A/S (CVR 80673612) — Balance (t.kr.) | B1: 2021 | C1: 2022 | D1: 2023 | E1: 2024 | F1: 2025
A2: Immaterielle anlægsaktiver | E2: 750 | F2: 520
A3: Grunde og bygninger | B3: 9802 | C3: 10123 | D3: 9858 | E3: 9327 | F3: 8796
A4: Produktionsanlæg og maskiner | B4: 4968 | C4: 3870 | D4: 2700 | E4: 1626 | F4: 2308
A5: Driftsmateriel og inventar | B5: 3161 | C5: 2074 | D5: 998 | E5: 2263 | F5: 1422
A6: Indretning af lejede lokaler | B6: 1904 | C6: 1425 | D6: 1050 | E6: 736 | F6: 449
A7: Forudbetaling og anlægsaktiver under opførelse
A8: Materielle anlægsaktiver | B8: 19834 | C8: 17492 | D8: 14607 | E8: 13952 | F8: 12974
A9: Kapitalandele, dattervirksomheder | B9: 0 | C9: 0 | D9: 0 | E9: 0 | F9: 0
A10: Deposita | B10: 768 | C10: 858 | D10: 852 | E10: 851 | F10: 851
A11: Finansielle anlægsaktiver | B11: 45793 | C11: 46059 | D11: 40745 | E11: 49360 | F11: 43734
A12: Anlægsaktiver | B12: 65627 | C12: 63551 | D12: 55352 | E12: 64062 | F12: 57228
A13: Råvarer og hjælpematerialer | B13: 31701 | C13: 29329 | D13: 22573 | E13: 27079 | F13: 27956
A14: Varer under fremstilling | B14: 7155 | C14: 7196 | D14: 8674 | E14: 7935 | F14: 7972
A15: Færdigvarer og handelsvarer | B15: 24519 | C15: 37011 | D15: 35611 | E15: 33732 | F15: 38552
A16: Varebeholdninger | B16: 63375 | C16: 73536 | D16: 66858 | E16: 68747 | F16: 74480
A17: Tilgodehavender fra salg og tjenesteydelser | B17: 33119 | C17: 25329 | D17: 25076 | E17: 24017 | F17: 28227
A18: Tilgodehavender hos tilknyttede virksomheder | B18: 0 | C18: 0 | D18: 0 | E18: 0 | F18: 0
A19: Andre tilgodehavender | B19: 728 | C19: 28 | D19: 2745 | E19: 990 | F19: 1604
A20: Periodeafgrænsningsposter (aktiver) | B20: 1473 | C20: 236 | D20: 176 | E20: 522 | F20: 397
A21: Udskudt skatteaktiv | D21: 2104 | E21: 2912 | F21: 2480
A22: Tilgodehavende skat hos tilknyttede virksomheder
A23: Kortfristede skattetilgodehavender | D23: 94 | E23: 534 | F23: 267
A24: Tilgodehavender | B24: 40981 | C24: 26347 | D24: 34743 | E24: 33480 | F24: 34182
A25: Værdipapirer
A26: Likvide beholdninger | B26: 24104 | C26: 18311 | D26: 25798 | E26: 32459 | F26: 22306
A27: Omsætningsaktiver | B27: 128461 | C27: 118195 | D27: 127399 | E27: 134685 | F27: 130968
A28: Aktiver | B28: 194088 | C28: 181746 | D28: 182751 | E28: 198748 | F28: 188196
A29: Selskabskapital | B29: 1000 | C29: 1000 | D29: 1000 | E29: 1000 | F29: 1000
A30: Reserve for nettoopskrivning (indre værdis metode) | B30: 55200 | C30: 56809 | D30: 34732 | E30: 43348 | F30: 37722
A31: Reserve for udviklingsomkostninger
A32: Reserve for sikringstransaktioner | B32: 131 | C32: 0
A33: Andre reserver
A34: Overført resultat | B34: 64913 | C34: 89365 | D34: 105227 | E34: 92146 | F34: 87989
A35: Egenkapital i alt | B35: 125244 | C35: 147174 | D35: 140959 | E35: 146494 | F35: 136711
A36: Hensættelse til udskudt skat | B36: 607 | C36: 727 | D36: 0 | E36: 2104 | F36: 2912
A37: Hensatte forpligtelser | B37: 2774 | C37: 2934 | D37: 2000 | E37: 1866 | F37: 1786
A38: Ansvarlig lånekapital (langfristet)
A39: Langfristede lån | B39: 4203 | C39: 0
A40: Leasingforpligtelser (langfristet) | B40: 2073 | C40: 1182 | D40: 193 | E40: 1908 | F40: 269
A41: Anden gæld (langfristet) | B41: 4376 | C41: 4468
A42: Langfristede gældsforpligtelser | B42: 10652 | C42: 5650 | D42: 4770 | E42: 6481 | F42: 4841
A43: Ansvarlig lånekapital (kortfristet)
A44: Kortfristet del af langfristede gældsforpligtelser | B44: 1262 | C44: 369 | D44: 302 | E44: 221 | F44: 951
A45: Kreditinstitutter | B45: 12972 | C45: 3395 | D45: 8988 | E45: 25002 | F45: 22103
A46: Leasingforpligtelser (kortfristet)
A47: Leverandører af varer og tjenesteydelser | B47: 19187 | C47: 7403 | D47: 12231 | E47: 6616 | F47: 13359
A48: Gæld til tilknyttede virksomheder | B48: 0 | C48: 0 | D48: 0 | E48: 0 | F48: 0
A49: Gæld til selskabsdeltagere og ledelse
A50: Selskabsskat | B50: 6573 | C50: 2202 | D50: 0
A51: Gæld til tilknyttede virksomheder vedr. selskabsskat
A52: Anden gæld (kortfristet) | B52: 14901 | C52: 12572 | D52: 13292 | E52: 11934 | F52: 8223
A53: Periodeafgrænsningsposter (passiver) | B53: 401 | C53: 47 | D53: 209 | E53: 133 | F53: 220
A54: Kortfristede gældsforpligtelser | B54: 55418 | C54: 25988 | D54: 35022 | E54: 43907 | F54: 44857
A55: Gældsforpligtelser | B55: 66070 | C55: 31637 | D55: 39792 | E55: 50388 | F55: 49698
A56: Passiver | B56: 194088 | C56: 181746 | D56: 182751 | E56: 198748 | F56: 188196

Sheet pengestrom_raw_80673612
A1: Scanpan A/S (CVR 80673612) — Pengestrømsopgørelse (t.kr.) | B1: 2021 | C1: 2022 | D1: 2023 | E1: 2024 | F1: 2025
A2: Pengestrømme fra driftsaktivitet | B2: -602 | C2: -5340 | D2: -6923 | E2: -7788 | F2: 27
A3: Pengestrømme fra investeringsaktivitet | B3: 11016 | C3: 16101 | D3: 9873 | E3: -3375 | F3: 3628
A4: Pengestrømme fra finansieringsaktivitet | B4: -1144 | C4: -16554 | D4: 4537 | E4: 17824 | F4: -13808
A5: Årets pengestrøm

Sheet Simpel_funktion
A1: Scanpan A/S (CVR 80673612) — Regnskabs- og nøgletal (CVR: 80673612) — funktionsopdelt
A3: Beløb i 1.000 kr. | B3: 2025 | C3: 2024 | D3: 2023 | F3: Note / XBRL-felt
A4: Uddrag af resultatopgørelse
A5: Nettoomsætning | B5: ='res_raw_80673612'!$F$2 | C5: ='res_raw_80673612'!$E$2 | D5: ='res_raw_80673612'!$D$2 | F5: fsa:Revenue
A6: Produktionsomkostninger | B6: =-'res_raw_80673612'!$F$3 | C6: =-'res_raw_80673612'!$E$3 | D6: =-'res_raw_80673612'!$D$3 | F6: fsa:CostOfProduction (vises negativt). Materialer, lønninger, produktionsoverhead.
A7: Bruttoresultat | B7: =IF(ABS((SUM(B5:B6))-'res_raw_80673612'!$F$4)<=2,SUM(B5:B6),'res_raw_80673612'!$F$4) | C7: =IF(ABS((SUM(C5:C6))-'res_raw_80673612'!$E$4)<=2,SUM(C5:C6),'res_raw_80673612'!$E$4) | D7: =IF(ABS((SUM(D5:D6))-'res_raw_80673612'!$D$4)<=2,SUM(D5:D6),'res_raw_80673612'!$D$4) | F7: Beregnet: Nettoomsætning − Produktionsomkostninger. Matcher fsa:GrossResult. Er komponenterne ikke indberettet, vises rapporteret fsa:GrossResult direkte.
A8: Udviklingsomkostninger | B8: =-'res_raw_80673612'!$F$5 | C8: =-'res_raw_80673612'!$E$5 | D8: =-'res_raw_80673612'!$D$5 | F8: ifrs-full:ResearchAndDevelopmentExpense (vises negativt). Udviklingsomkostninger ført i resultatet (v15_21; B&O m.fl.).
A9: Salgs- og distributionsomk. | B9: =-'res_raw_80673612'!$F$6 | C9: =-'res_raw_80673612'!$E$6 | D9: =-'res_raw_80673612'!$D$6 | F9: fsa:DistributionCosts (vises negativt). Marketing, salg, distribution.
A10: Administrationsomkostninger mv. | B10: =-'res_raw_80673612'!$F$7 | C10: =-'res_raw_80673612'!$E$7 | D10: =-'res_raw_80673612'!$D$7 | F10: fsa:AdministrativeExpenses (vises negativt). Generel administration.
A11: Andre driftsindtægter | B11: ='res_raw_80673612'!$F$8 | C11: ='res_raw_80673612'!$E$8 | D11: ='res_raw_80673612'!$D$8 | F11: fsa:OtherOperatingIncome. Sekundære driftsindtægter (huslejeindtægter, off. tilskud, avancer mv.).
A12: Andre driftsomkostninger | B12: =-'res_raw_80673612'!$F$9 | C12: =-'res_raw_80673612'!$E$9 | D12: =-'res_raw_80673612'!$D$9 | F12: fsa:OtherOperatingExpenses (vises negativt). Sekundære driftsomkostninger.
A13: Resultat af primær drift | B13: =IF(ABS((SUM(B7:B12))-'res_raw_80673612'!$F$10)<=2,SUM(B7:B12),'res_raw_80673612'!$F$10) | C13: =IF(ABS((SUM(C7:C12))-'res_raw_80673612'!$E$10)<=2,SUM(C7:C12),'res_raw_80673612'!$E$10) | D13: =IF(ABS((SUM(D7:D12))-'res_raw_80673612'!$D$10)<=2,SUM(D7:D12),'res_raw_80673612'!$D$10) | F13: Beregnet: Bruttoresultat − Udviklingsomk. − Salgs/dist. − Administration + Andre driftsindt. − Andre driftsomk. EBIT.
A14: Finansielle indtægter mv. | B14: =N('res_raw_80673612'!$F$11)+N('res_raw_80673612'!$F$12) | C14: =N('res_raw_80673612'!$E$11)+N('res_raw_80673612'!$E$12) | D14: =N('res_raw_80673612'!$D$11)+N('res_raw_80673612'!$D$12) | F14: fsa:IncomeFromSubsidiaries + fsa:OtherFinanceIncome.
A15: Finansielle omkostninger mv. | B15: =-'res_raw_80673612'!$F$13 | C15: =-'res_raw_80673612'!$E$13 | D15: =-'res_raw_80673612'!$D$13 | F15: fsa:OtherFinanceExpenses (vises negativt). Renteomkostninger, kurstab.
A16: Resultat før skat | B16: =IF(ABS((SUM(B13:B15))-'res_raw_80673612'!$F$15)<=2,SUM(B13:B15),'res_raw_80673612'!$F$15) | C16: =IF(ABS((SUM(C13:C15))-'res_raw_80673612'!$E$15)<=2,SUM(C13:C15),'res_raw_80673612'!$E$15) | D16: =IF(ABS((SUM(D13:D15))-'res_raw_80673612'!$D$15)<=2,SUM(D13:D15),'res_raw_80673612'!$D$15) | F16: Beregnet: EBIT + Fin. indtægter + Fin. omk. EBT.
A18: Uddrag af balance
A19: Anlægsaktiver | B19: ='balance_raw_80673612'!$F$12 | C19: ='balance_raw_80673612'!$E$12 | D19: ='balance_raw_80673612'!$D$12 | F19: fsa:NoncurrentAssets. Materielle, immaterielle og finansielle anlægsaktiver.
A20: Omsætningsaktiver | B20: ='balance_raw_80673612'!$F$27 | C20: ='balance_raw_80673612'!$E$27 | D20: ='balance_raw_80673612'!$D$27 | F20: fsa:CurrentAssets. Varebeholdninger, tilgodehavender, likvider.
A21: Aktiver i alt | B21: =SUM(B19:B20) | C21: =SUM(C19:C20) | D21: =SUM(D19:D20) | F21: Beregnet: Anlægsaktiver + Omsætningsaktiver. Bør matche fsa:Assets.
A23: Egenkapital | B23: ='balance_raw_80673612'!$F$35 | C23: ='balance_raw_80673612'!$E$35 | D23: ='balance_raw_80673612'!$D$35 | F23: fsa:Equity. Selskabskapital, overført resultat, reserver.
A24: Forpligtelser | B24: ='balance_raw_80673612'!$F$56-'balance_raw_80673612'!$F$35 | C24: ='balance_raw_80673612'!$E$56-'balance_raw_80673612'!$E$35 | D24: ='balance_raw_80673612'!$D$56-'balance_raw_80673612'!$D$35 | F24: Beregnet: Passiver (fsa:LiabilitiesAndEquity) − Egenkapital. Hensættelser + kort- og langfristet gæld.
A25: Passiver i alt | B25: =SUM(B23:B24) | C25: =SUM(C23:C24) | D25: =SUM(D23:D24) | F25: Beregnet: Egenkapital + Forpligtelser. Bør matche Aktiver i alt.
A27: Udvalgte balanceposter
A28: Varebeholdninger | B28: ='balance_raw_80673612'!$F$16 | C28: ='balance_raw_80673612'!$E$16 | D28: ='balance_raw_80673612'!$D$16 | F28: fsa:Inventories (eller fsa:ManufacturedGoodsAndGoodsForResale hvis total mangler).
A29: Tilgodehavender fra salg | B29: ='balance_raw_80673612'!$F$17 | C29: ='balance_raw_80673612'!$E$17 | D29: ='balance_raw_80673612'!$D$17 | F29: fsa:ShorttermTradeReceivables. Kortfristede tilgodehavender fra kunder.
A30: Kortfristede gældsforpligtelser | B30: ='balance_raw_80673612'!$F$54 | C30: ='balance_raw_80673612'!$E$54 | D30: ='balance_raw_80673612'!$D$54 | F30: fsa:ShorttermLiabilitiesOtherThanProvisions. Gæld der forfalder inden for 1 år.
A32: Rentabilitet
A33: Afkastningsgrad, % | B33: =IFERROR((B13+B14)/B21*100,"") | C33: =IFERROR((C13+C14)/C21*100,"") | D33: =IFERROR((D13+D14)/D21*100,"")
A34: Overskudsgrad (af bruttofortjeneste), % | B34: =IFERROR((B13+B14)/B7*100,"") | C34: =IFERROR((C13+C14)/C7*100,"") | D34: =IFERROR((D13+D14)/D7*100,"")
A35: Aktivernes omsætningshastighed (af bruttofortjeneste), gange | B35: =IFERROR(B7/B21,"") | C35: =IFERROR(C7/C21,"") | D35: =IFERROR(D7/D21,"")
A36: Gældsrente, % | B36: =IFERROR(-B15*100/B24,"") | C36: =IFERROR(-C15*100/C24,"") | D36: =IFERROR(-D15*100/D24,"")
A37: Egenkapitalens forrentning, % | B37: =IFERROR(B16/B23*100,"") | C37: =IFERROR(C16/C23*100,"") | D37: =IFERROR(D16/D23*100,"")
A38: Gearing, gange | B38: =IFERROR(B24/B23,"") | C38: =IFERROR(C24/C23,"") | D38: =IFERROR(D24/D23,"")
A40: Indekstal for indtjeningsevne (2023=100)
A41: Bruttofortjeneste | B41: =IFERROR(B7/$D7*100,"") | C41: =IFERROR(C7/$D7*100,"") | D41: =IFERROR(D7/$D7*100,"")
A42: Produktionsomkostninger | B42: =IFERROR(B6/$D6*100,"") | C42: =IFERROR(C6/$D6*100,"") | D42: =IFERROR(D6/$D6*100,"")
A43: Udviklingsomkostninger | B43: =IFERROR(B8/$D8*100,"") | C43: =IFERROR(C8/$D8*100,"") | D43: =IFERROR(D8/$D8*100,"")
A44: Salgs- og distributionsomk. | B44: =IFERROR(B9/$D9*100,"") | C44: =IFERROR(C9/$D9*100,"") | D44: =IFERROR(D9/$D9*100,"")
A45: Administrationsomk. | B45: =IFERROR(B10/$D10*100,"") | C45: =IFERROR(C10/$D10*100,"") | D45: =IFERROR(D10/$D10*100,"")
A46: Andre driftsomkostninger | B46: =IFERROR(B12/$D12*100,"") | C46: =IFERROR(C12/$D12*100,"") | D46: =IFERROR(D12/$D12*100,"")
A48: Indekstal for kapitaltilpasningsevne (2023=100)
A49: Bruttofortjeneste | B49: =IFERROR(B7*100/$D7,"") | C49: =IFERROR(C7*100/$D7,"") | D49: =IFERROR(D7*100/$D7,"")
A50: Anlægsaktiver | B50: =IFERROR(B19*100/$D19,"") | C50: =IFERROR(C19*100/$D19,"") | D50: =IFERROR(D19*100/$D19,"")
A51: Varebeholdninger | B51: =IFERROR(B28*100/$D28,"") | C51: =IFERROR(C28*100/$D28,"") | D51: =IFERROR(D28*100/$D28,"")
A52: Tilgodehavender fra salg | B52: =IFERROR(B29*100/$D29,"") | C52: =IFERROR(C29*100/$D29,"") | D52: =IFERROR(D29*100/$D29,"")
A54: Soliditet og likviditet
A55: Soliditetsgrad, % | B55: =IFERROR(B23*100/B21,"") | C55: =IFERROR(C23*100/C21,"") | D55: =IFERROR(D23*100/D21,"")
A56: Gældsandel, % | B56: =IFERROR(B24*100/B21,"") | C56: =IFERROR(C24*100/C21,"") | D56: =IFERROR(D24*100/D21,"")
A57: Likviditetsgrad, % | B57: =IFERROR(B20*100/B30,"") | C57: =IFERROR(C20*100/C30,"") | D57: =IFERROR(D20*100/D30,"")
A59: Kilde: Bearbejdet uddrag af årsrapporter for 2023-2025. Alle dataceller er live formler der peger på res_raw / balance_raw.
A61: Krydstjek mod rådata (tolerance: 1 t.kr.)
A62: Aktiver i alt = fsa:Assets | B62: =IF('balance_raw_80673612'!$F$28="","—",IF(ABS(B21-'balance_raw_80673612'!$F$28)<=1,"✓ OK","❌ "&TEXT(B21-'balance_raw_80673612'!$F$28,"+#,##0;-#,##0")&" t.kr.")) | C62: =IF('balance_raw_80673612'!$E$28="","—",IF(ABS(C21-'balance_raw_80673612'!$E$28)<=1,"✓ OK","❌ "&TEXT(C21-'balance_raw_80673612'!$E$28,"+#,##0;-#,##0")&" t.kr.")) | D62: =IF('balance_raw_80673612'!$D$28="","—",IF(ABS(D21-'balance_raw_80673612'!$D$28)<=1,"✓ OK","❌ "&TEXT(D21-'balance_raw_80673612'!$D$28,"+#,##0;-#,##0")&" t.kr.")) | F62: Verificerer at sum(Anlæg+Omsætning) matcher Assets-totalen.
A63: Passiver i alt = fsa:LiabilitiesAndEquity | B63: =IF('balance_raw_80673612'!$F$56="","—",IF(ABS(B25-'balance_raw_80673612'!$F$56)<=1,"✓ OK","❌ "&TEXT(B25-'balance_raw_80673612'!$F$56,"+#,##0;-#,##0")&" t.kr.")) | C63: =IF('balance_raw_80673612'!$E$56="","—",IF(ABS(C25-'balance_raw_80673612'!$E$56)<=1,"✓ OK","❌ "&TEXT(C25-'balance_raw_80673612'!$E$56,"+#,##0;-#,##0")&" t.kr.")) | D63: =IF('balance_raw_80673612'!$D$56="","—",IF(ABS(D25-'balance_raw_80673612'!$D$56)<=1,"✓ OK","❌ "&TEXT(D25-'balance_raw_80673612'!$D$56,"+#,##0;-#,##0")&" t.kr.")) | F63: Verificerer at sum(EK+Forpligtelser) matcher Passiver-totalen.
A64: Aktiver i alt = Passiver i alt | B64: =IF(ABS(B21-B25)<=1,"✓ OK","❌ "&TEXT(B21-B25,"+#,##0;-#,##0")&" t.kr.") | C64: =IF(ABS(C21-C25)<=1,"✓ OK","❌ "&TEXT(C21-C25,"+#,##0;-#,##0")&" t.kr.") | D64: =IF(ABS(D21-D25)<=1,"✓ OK","❌ "&TEXT(D21-D25,"+#,##0;-#,##0")&" t.kr.") | F64: Balance-identitet på arket selv. Skal altid være 0 differance.
A65: Bruttoresultat (beregnet) = fsa:GrossResult | B65: =IF('res_raw_80673612'!$F$4="","—",IF(ABS(B7-'res_raw_80673612'!$F$4)<=1,"✓ OK","❌ "&TEXT(B7-'res_raw_80673612'!$F$4,"+#,##0;-#,##0")&" t.kr.")) | C65: =IF('res_raw_80673612'!$E$4="","—",IF(ABS(C7-'res_raw_80673612'!$E$4)<=1,"✓ OK","❌ "&TEXT(C7-'res_raw_80673612'!$E$4,"+#,##0;-#,##0")&" t.kr.")) | D65: =IF('res_raw_80673612'!$D$4="","—",IF(ABS(D7-'res_raw_80673612'!$D$4)<=1,"✓ OK","❌ "&TEXT(D7-'res_raw_80673612'!$D$4,"+#,##0;-#,##0")&" t.kr.")) | F65: Hvis Nettoomsætning eller omkostninger mangler, vil sumberegnet bruttoresultat afvige.
A66: EBIT (beregnet) = fsa:ProfitLossFromOrdinaryOperatingActivities | B66: =IF('res_raw_80673612'!$F$10="","—",IF(ABS(B13-'res_raw_80673612'!$F$10)<=1,"✓ OK","❌ "&TEXT(B13-'res_raw_80673612'!$F$10,"+#,##0;-#,##0")&" t.kr.")) | C66: =IF('res_raw_80673612'!$E$10="","—",IF(ABS(C13-'res_raw_80673612'!$E$10)<=1,"✓ OK","❌ "&TEXT(C13-'res_raw_80673612'!$E$10,"+#,##0;-#,##0")&" t.kr.")) | D66: =IF('res_raw_80673612'!$D$10="","—",IF(ABS(D13-'res_raw_80673612'!$D$10)<=1,"✓ OK","❌ "&TEXT(D13-'res_raw_80673612'!$D$10,"+#,##0;-#,##0")&" t.kr.")) | F66: Verificerer at sumberegnet EBIT matcher det rapporterede.
A67: EBT (beregnet) = fsa:ProfitLossFromOrdinaryActivitiesBeforeTax | B67: =IF('res_raw_80673612'!$F$15="","—",IF(ABS(B16-'res_raw_80673612'!$F$15)<=1,"✓ OK","❌ "&TEXT(B16-'res_raw_80673612'!$F$15,"+#,##0;-#,##0")&" t.kr.")) | C67: =IF('res_raw_80673612'!$E$15="","—",IF(ABS(C16-'res_raw_80673612'!$E$15)<=1,"✓ OK","❌ "&TEXT(C16-'res_raw_80673612'!$E$15,"+#,##0;-#,##0")&" t.kr.")) | D67: =IF('res_raw_80673612'!$D$15="","—",IF(ABS(D16-'res_raw_80673612'!$D$15)<=1,"✓ OK","❌ "&TEXT(D16-'res_raw_80673612'!$D$15,"+#,##0;-#,##0")&" t.kr.")) | F67: Verificerer at sumberegnet resultat før skat matcher det rapporterede.

Sheet Noter_info
A1: Scanpan A/S (CVR 80673612) — Ukendte XBRL-felter — disse er noter og ikke en del af hoved-regnskabet
A2: Kategori | B2: Dansk navn | C2: XBRL feltnavn | D2: 2021 t.kr. | E2: 2022 t.kr. | F2: 2023 t.kr. | G2: 2024 t.kr. | H2: 2025 t.kr. | I2: Forklaring
A3: Øvrige (ukendt) | B3: fsa:ExchangeRateAdjustmentsOtherFinanceExpenses | C3: fsa:ExchangeRateAdjustmentsOtherFinanceExpenses | D3: 8 | E3: 217 | F3: 0 | I3: Ingen forklaring tilgængelig.
A4: Øvrige (ukendt) | B4: fsa:Loans | C4: fsa:Loans | D4: -50 | E4: -90 | F4: 0 | I4: Ingen forklaring tilgængelig.
A5: Øvrige (ukendt) | B5: fsa:RaisingOfLongtermDebt | C5: fsa:RaisingOfLongtermDebt | G5: 1715 | H5: 0 | I5: Ingen forklaring tilgængelig.
A6: Øvrige (ukendt) | B6: fsa:ReductionOfLeaseCommitments | C6: fsa:ReductionOfLeaseCommitments | D6: -1810 | E6: -1236 | F6: -741 | G6: 0 | I6: Ingen forklaring tilgængelig.
A7: Øvrige (ukendt) | B7: fsa:RepaymentOfMortgageDebt | C7: fsa:RepaymentOfMortgageDebt | D7: -335 | E7: -4203 | F7: 0 | I7: Ingen forklaring tilgængelig.
A8: Øvrige (ukendt) | B8: fsa:ShorttermPayablesToAssociates | C8: fsa:ShorttermPayablesToAssociates | D8: 122 | E8: 0 | I8: Ingen forklaring tilgængelig.
