Workbook

Sheet Overblik_11563392
A1: Regnskabsanalyse – Resultatopgørelse & Balance (t.kr.)
H2: Indekstal (2020=100)
A3: Resultatopgørelse t.kr. | B3: 2020 | C3: 2021 | D3: 2022 | E3: 2023 | F3: 2024 | H3: 2020 | I3: 2021 | J3: 2022 | K3: 2023 | L3: 2024
A4: Nettoomsætning | B4: ='res_raw_11563392'!$B$2 | C4: ='res_raw_11563392'!$C$2 | D4: ='res_raw_11563392'!$D$2 | E4: ='res_raw_11563392'!$E$2 | F4: ='res_raw_11563392'!$F$2 | H4: =IFERROR(B4/$B$4*100,"") | I4: =IFERROR(C4/$B$4*100,"") | J4: =IFERROR(D4/$B$4*100,"") | K4: =IFERROR(E4/$B$4*100,"") | L4: =IFERROR(F4/$B$4*100,"")
A5: Andre driftsindtægter | B5: ='res_raw_11563392'!$B$3 | C5: ='res_raw_11563392'!$C$3 | D5: ='res_raw_11563392'!$D$3 | E5: ='res_raw_11563392'!$E$3 | F5: ='res_raw_11563392'!$F$3 | H5: =IFERROR(B5/$B$5*100,"") | I5: =IFERROR(C5/$B$5*100,"") | J5: =IFERROR(D5/$B$5*100,"") | K5: =IFERROR(E5/$B$5*100,"") | L5: =IFERROR(F5/$B$5*100,"")
A6: Vareforbrug | B6: ='res_raw_11563392'!$B$4 | C6: ='res_raw_11563392'!$C$4 | D6: ='res_raw_11563392'!$D$4 | E6: ='res_raw_11563392'!$E$4 | F6: ='res_raw_11563392'!$F$4 | H6: =IFERROR(B6/$B$6*100,"") | I6: =IFERROR(C6/$B$6*100,"") | J6: =IFERROR(D6/$B$6*100,"") | K6: =IFERROR(E6/$B$6*100,"") | L6: =IFERROR(F6/$B$6*100,"")
A7: Andre eksterne omkostninger | B7: ='res_raw_11563392'!$B$5 | C7: ='res_raw_11563392'!$C$5 | D7: ='res_raw_11563392'!$D$5 | E7: ='res_raw_11563392'!$E$5 | F7: ='res_raw_11563392'!$F$5 | H7: =IFERROR(B7/$B$7*100,"") | I7: =IFERROR(C7/$B$7*100,"") | J7: =IFERROR(D7/$B$7*100,"") | K7: =IFERROR(E7/$B$7*100,"") | L7: =IFERROR(F7/$B$7*100,"")
A8: Bruttoresultat | B8: ='res_raw_11563392'!$B$6 | C8: ='res_raw_11563392'!$C$6 | D8: ='res_raw_11563392'!$D$6 | E8: ='res_raw_11563392'!$E$6 | F8: ='res_raw_11563392'!$F$6 | H8: =IFERROR(B8/$B$8*100,"") | I8: =IFERROR(C8/$B$8*100,"") | J8: =IFERROR(D8/$B$8*100,"") | K8: =IFERROR(E8/$B$8*100,"") | L8: =IFERROR(F8/$B$8*100,"")
A9: Personaleomkostninger | B9: ='res_raw_11563392'!$B$7 | C9: ='res_raw_11563392'!$C$7 | D9: ='res_raw_11563392'!$D$7 | E9: ='res_raw_11563392'!$E$7 | F9: ='res_raw_11563392'!$F$7 | H9: =IFERROR(B9/$B$9*100,"") | I9: =IFERROR(C9/$B$9*100,"") | J9: =IFERROR(D9/$B$9*100,"") | K9: =IFERROR(E9/$B$9*100,"") | L9: =IFERROR(F9/$B$9*100,"")
A10: Resultat før afskrivninger | B10: =IFERROR($B$8-ABS($B$9),"") | C10: =IFERROR($C$8-ABS($C$9),"") | D10: =IFERROR($D$8-ABS($D$9),"") | E10: =IFERROR($E$8-ABS($E$9),"") | F10: =IFERROR($F$8-ABS($F$9),"") | H10: =IFERROR(B10/$B$10*100,"") | I10: =IFERROR(C10/$B$10*100,"") | J10: =IFERROR(D10/$B$10*100,"") | K10: =IFERROR(E10/$B$10*100,"") | L10: =IFERROR(F10/$B$10*100,"")
A11: Af- og nedskrivninger | B11: ='res_raw_11563392'!$B$9 | C11: ='res_raw_11563392'!$C$9 | D11: ='res_raw_11563392'!$D$9 | E11: ='res_raw_11563392'!$E$9 | F11: ='res_raw_11563392'!$F$9 | H11: =IFERROR(B11/$B$11*100,"") | I11: =IFERROR(C11/$B$11*100,"") | J11: =IFERROR(D11/$B$11*100,"") | K11: =IFERROR(E11/$B$11*100,"") | L11: =IFERROR(F11/$B$11*100,"")
A12: Andre driftsomkostninger | B12: ='res_raw_11563392'!$B$10 | C12: ='res_raw_11563392'!$C$10 | D12: ='res_raw_11563392'!$D$10 | E12: ='res_raw_11563392'!$E$10 | F12: ='res_raw_11563392'!$F$10 | H12: =IFERROR(B12/$B$12*100,"") | I12: =IFERROR(C12/$B$12*100,"") | J12: =IFERROR(D12/$B$12*100,"") | K12: =IFERROR(E12/$B$12*100,"") | L12: =IFERROR(F12/$B$12*100,"")
A13: Resultat af primær drift | B13: ='res_raw_11563392'!$B$11 | C13: ='res_raw_11563392'!$C$11 | D13: ='res_raw_11563392'!$D$11 | E13: ='res_raw_11563392'!$E$11 | F13: ='res_raw_11563392'!$F$11 | H13: =IFERROR(B13/$B$13*100,"") | I13: =IFERROR(C13/$B$13*100,"") | J13: =IFERROR(D13/$B$13*100,"") | K13: =IFERROR(E13/$B$13*100,"") | L13: =IFERROR(F13/$B$13*100,"")
A14: Indtægter af kapitalandele, dattervirksomheder | B14: ='res_raw_11563392'!$B$12 | C14: ='res_raw_11563392'!$C$12 | D14: ='res_raw_11563392'!$D$12 | E14: ='res_raw_11563392'!$E$12 | F14: ='res_raw_11563392'!$F$12 | H14: =IFERROR(B14/$B$14*100,"") | I14: =IFERROR(C14/$B$14*100,"") | J14: =IFERROR(D14/$B$14*100,"") | K14: =IFERROR(E14/$B$14*100,"") | L14: =IFERROR(F14/$B$14*100,"")
A15: Finansielle indtægter | B15: ='res_raw_11563392'!$B$13 | C15: ='res_raw_11563392'!$C$13 | D15: ='res_raw_11563392'!$D$13 | E15: ='res_raw_11563392'!$E$13 | F15: ='res_raw_11563392'!$F$13 | H15: =IFERROR(B15/$B$15*100,"") | I15: =IFERROR(C15/$B$15*100,"") | J15: =IFERROR(D15/$B$15*100,"") | K15: =IFERROR(E15/$B$15*100,"") | L15: =IFERROR(F15/$B$15*100,"")
A16: Finansielle omkostninger | B16: ='res_raw_11563392'!$B$14 | C16: ='res_raw_11563392'!$C$14 | D16: ='res_raw_11563392'!$D$14 | E16: ='res_raw_11563392'!$E$14 | F16: ='res_raw_11563392'!$F$14 | H16: =IFERROR(B16/$B$16*100,"") | I16: =IFERROR(C16/$B$16*100,"") | J16: =IFERROR(D16/$B$16*100,"") | K16: =IFERROR(E16/$B$16*100,"") | L16: =IFERROR(F16/$B$16*100,"")
A17: Finansielle poster, netto | B17: ='res_raw_11563392'!$B$15 | C17: ='res_raw_11563392'!$C$15 | D17: ='res_raw_11563392'!$D$15 | E17: ='res_raw_11563392'!$E$15 | F17: ='res_raw_11563392'!$F$15 | H17: =IFERROR(B17/$B$17*100,"") | I17: =IFERROR(C17/$B$17*100,"") | J17: =IFERROR(D17/$B$17*100,"") | K17: =IFERROR(E17/$B$17*100,"") | L17: =IFERROR(F17/$B$17*100,"")
A18: Resultat før skat | B18: ='res_raw_11563392'!$B$16 | C18: ='res_raw_11563392'!$C$16 | D18: ='res_raw_11563392'!$D$16 | E18: ='res_raw_11563392'!$E$16 | F18: ='res_raw_11563392'!$F$16 | H18: =IFERROR(B18/$B$18*100,"") | I18: =IFERROR(C18/$B$18*100,"") | J18: =IFERROR(D18/$B$18*100,"") | K18: =IFERROR(E18/$B$18*100,"") | L18: =IFERROR(F18/$B$18*100,"")
A19: Skat af årets resultat | B19: ='res_raw_11563392'!$B$17 | C19: ='res_raw_11563392'!$C$17 | D19: ='res_raw_11563392'!$D$17 | E19: ='res_raw_11563392'!$E$17 | F19: ='res_raw_11563392'!$F$17 | H19: =IFERROR(B19/$B$19*100,"") | I19: =IFERROR(C19/$B$19*100,"") | J19: =IFERROR(D19/$B$19*100,"") | K19: =IFERROR(E19/$B$19*100,"") | L19: =IFERROR(F19/$B$19*100,"")
A20: Årets resultat | B20: ='res_raw_11563392'!$B$18 | C20: ='res_raw_11563392'!$C$18 | D20: ='res_raw_11563392'!$D$18 | E20: ='res_raw_11563392'!$E$18 | F20: ='res_raw_11563392'!$F$18 | H20: =IFERROR(B20/$B$20*100,"") | I20: =IFERROR(C20/$B$20*100,"") | J20: =IFERROR(D20/$B$20*100,"") | K20: =IFERROR(E20/$B$20*100,"") | L20: =IFERROR(F20/$B$20*100,"")
A22: AKTIVER t.kr. | B22: 2020 | C22: 2021 | D22: 2022 | E22: 2023 | F22: 2024 | H22: 2020 | I22: 2021 | J22: 2022 | K22: 2023 | L22: 2024
A23: Grunde og bygninger | B23: ='balance_raw_11563392'!$B$2 | C23: ='balance_raw_11563392'!$C$2 | D23: ='balance_raw_11563392'!$D$2 | E23: ='balance_raw_11563392'!$E$2 | F23: ='balance_raw_11563392'!$F$2 | H23: =IFERROR(B23/$B$23*100,"") | I23: =IFERROR(C23/$B$23*100,"") | J23: =IFERROR(D23/$B$23*100,"") | K23: =IFERROR(E23/$B$23*100,"") | L23: =IFERROR(F23/$B$23*100,"")
A24: Produktionsanlæg og maskiner | B24: ='balance_raw_11563392'!$B$3 | C24: ='balance_raw_11563392'!$C$3 | D24: ='balance_raw_11563392'!$D$3 | E24: ='balance_raw_11563392'!$E$3 | F24: ='balance_raw_11563392'!$F$3 | H24: =IFERROR(B24/$B$24*100,"") | I24: =IFERROR(C24/$B$24*100,"") | J24: =IFERROR(D24/$B$24*100,"") | K24: =IFERROR(E24/$B$24*100,"") | L24: =IFERROR(F24/$B$24*100,"")
A25: Driftsmateriel og inventar | B25: ='balance_raw_11563392'!$B$4 | C25: ='balance_raw_11563392'!$C$4 | D25: ='balance_raw_11563392'!$D$4 | E25: ='balance_raw_11563392'!$E$4 | F25: ='balance_raw_11563392'!$F$4 | H25: =IFERROR(B25/$B$25*100,"") | I25: =IFERROR(C25/$B$25*100,"") | J25: =IFERROR(D25/$B$25*100,"") | K25: =IFERROR(E25/$B$25*100,"") | L25: =IFERROR(F25/$B$25*100,"")
A26: Indretning af lejede lokaler | B26: ='balance_raw_11563392'!$B$5 | C26: ='balance_raw_11563392'!$C$5 | D26: ='balance_raw_11563392'!$D$5 | E26: ='balance_raw_11563392'!$E$5 | F26: ='balance_raw_11563392'!$F$5 | H26: =IFERROR(B26/$B$26*100,"") | I26: =IFERROR(C26/$B$26*100,"") | J26: =IFERROR(D26/$B$26*100,"") | K26: =IFERROR(E26/$B$26*100,"") | L26: =IFERROR(F26/$B$26*100,"")
A27: Forudbetaling og anlægsaktiver under opførelse | B27: ='balance_raw_11563392'!$B$6 | C27: ='balance_raw_11563392'!$C$6 | D27: ='balance_raw_11563392'!$D$6 | E27: ='balance_raw_11563392'!$E$6 | F27: ='balance_raw_11563392'!$F$6 | H27: =IFERROR(B27/$B$27*100,"") | I27: =IFERROR(C27/$B$27*100,"") | J27: =IFERROR(D27/$B$27*100,"") | K27: =IFERROR(E27/$B$27*100,"") | L27: =IFERROR(F27/$B$27*100,"")
A28: Materielle anlægsaktiver | B28: ='balance_raw_11563392'!$B$7 | C28: ='balance_raw_11563392'!$C$7 | D28: ='balance_raw_11563392'!$D$7 | E28: ='balance_raw_11563392'!$E$7 | F28: ='balance_raw_11563392'!$F$7 | H28: =IFERROR(B28/$B$28*100,"") | I28: =IFERROR(C28/$B$28*100,"") | J28: =IFERROR(D28/$B$28*100,"") | K28: =IFERROR(E28/$B$28*100,"") | L28: =IFERROR(F28/$B$28*100,"")
A29: Kapitalandele, dattervirksomheder | B29: ='balance_raw_11563392'!$B$8 | C29: ='balance_raw_11563392'!$C$8 | D29: ='balance_raw_11563392'!$D$8 | E29: ='balance_raw_11563392'!$E$8 | F29: ='balance_raw_11563392'!$F$8 | H29: =IFERROR(B29/$B$29*100,"") | I29: =IFERROR(C29/$B$29*100,"") | J29: =IFERROR(D29/$B$29*100,"") | K29: =IFERROR(E29/$B$29*100,"") | L29: =IFERROR(F29/$B$29*100,"")
A30: Deposita | B30: ='balance_raw_11563392'!$B$9 | C30: ='balance_raw_11563392'!$C$9 | D30: ='balance_raw_11563392'!$D$9 | E30: ='balance_raw_11563392'!$E$9 | F30: ='balance_raw_11563392'!$F$9 | H30: =IFERROR(B30/$B$30*100,"") | I30: =IFERROR(C30/$B$30*100,"") | J30: =IFERROR(D30/$B$30*100,"") | K30: =IFERROR(E30/$B$30*100,"") | L30: =IFERROR(F30/$B$30*100,"")
A31: Finansielle anlægsaktiver | B31: ='balance_raw_11563392'!$B$10 | C31: ='balance_raw_11563392'!$C$10 | D31: ='balance_raw_11563392'!$D$10 | E31: ='balance_raw_11563392'!$E$10 | F31: ='balance_raw_11563392'!$F$10 | H31: =IFERROR(B31/$B$31*100,"") | I31: =IFERROR(C31/$B$31*100,"") | J31: =IFERROR(D31/$B$31*100,"") | K31: =IFERROR(E31/$B$31*100,"") | L31: =IFERROR(F31/$B$31*100,"")
A32: Anlægsaktiver | B32: ='balance_raw_11563392'!$B$11 | C32: ='balance_raw_11563392'!$C$11 | D32: ='balance_raw_11563392'!$D$11 | E32: ='balance_raw_11563392'!$E$11 | F32: ='balance_raw_11563392'!$F$11 | H32: =IFERROR(B32/$B$32*100,"") | I32: =IFERROR(C32/$B$32*100,"") | J32: =IFERROR(D32/$B$32*100,"") | K32: =IFERROR(E32/$B$32*100,"") | L32: =IFERROR(F32/$B$32*100,"")
A33: Tilgodehavender fra salg og tjenesteydelser | B33: ='balance_raw_11563392'!$B$12 | C33: ='balance_raw_11563392'!$C$12 | D33: ='balance_raw_11563392'!$D$12 | E33: ='balance_raw_11563392'!$E$12 | F33: ='balance_raw_11563392'!$F$12 | H33: =IFERROR(B33/$B$33*100,"") | I33: =IFERROR(C33/$B$33*100,"") | J33: =IFERROR(D33/$B$33*100,"") | K33: =IFERROR(E33/$B$33*100,"") | L33: =IFERROR(F33/$B$33*100,"")
A34: Tilgodehavender hos tilknyttede virksomheder | B34: ='balance_raw_11563392'!$B$13 | C34: ='balance_raw_11563392'!$C$13 | D34: ='balance_raw_11563392'!$D$13 | E34: ='balance_raw_11563392'!$E$13 | F34: ='balance_raw_11563392'!$F$13 | H34: =IFERROR(B34/$B$34*100,"") | I34: =IFERROR(C34/$B$34*100,"") | J34: =IFERROR(D34/$B$34*100,"") | K34: =IFERROR(E34/$B$34*100,"") | L34: =IFERROR(F34/$B$34*100,"")
A35: Andre tilgodehavender | B35: ='balance_raw_11563392'!$B$14 | C35: ='balance_raw_11563392'!$C$14 | D35: ='balance_raw_11563392'!$D$14 | E35: ='balance_raw_11563392'!$E$14 | F35: ='balance_raw_11563392'!$F$14 | H35: =IFERROR(B35/$B$35*100,"") | I35: =IFERROR(C35/$B$35*100,"") | J35: =IFERROR(D35/$B$35*100,"") | K35: =IFERROR(E35/$B$35*100,"") | L35: =IFERROR(F35/$B$35*100,"")
A36: Periodeafgrænsningsposter (aktiver) | B36: ='balance_raw_11563392'!$B$15 | C36: ='balance_raw_11563392'!$C$15 | D36: ='balance_raw_11563392'!$D$15 | E36: ='balance_raw_11563392'!$E$15 | F36: ='balance_raw_11563392'!$F$15 | H36: =IFERROR(B36/$B$36*100,"") | I36: =IFERROR(C36/$B$36*100,"") | J36: =IFERROR(D36/$B$36*100,"") | K36: =IFERROR(E36/$B$36*100,"") | L36: =IFERROR(F36/$B$36*100,"")
A37: Udskudt skatteaktiv | B37: ='balance_raw_11563392'!$B$16 | C37: ='balance_raw_11563392'!$C$16 | D37: ='balance_raw_11563392'!$D$16 | E37: ='balance_raw_11563392'!$E$16 | F37: ='balance_raw_11563392'!$F$16 | H37: =IFERROR(B37/$B$37*100,"") | I37: =IFERROR(C37/$B$37*100,"") | J37: =IFERROR(D37/$B$37*100,"") | K37: =IFERROR(E37/$B$37*100,"") | L37: =IFERROR(F37/$B$37*100,"")
A38: Tilgodehavende skat hos tilknyttede virksomheder | B38: ='balance_raw_11563392'!$B$17 | C38: ='balance_raw_11563392'!$C$17 | D38: ='balance_raw_11563392'!$D$17 | E38: ='balance_raw_11563392'!$E$17 | F38: ='balance_raw_11563392'!$F$17 | H38: =IFERROR(B38/$B$38*100,"") | I38: =IFERROR(C38/$B$38*100,"") | J38: =IFERROR(D38/$B$38*100,"") | K38: =IFERROR(E38/$B$38*100,"") | L38: =IFERROR(F38/$B$38*100,"")
A39: Kortfristede skattetilgodehavender | B39: ='balance_raw_11563392'!$B$18 | C39: ='balance_raw_11563392'!$C$18 | D39: ='balance_raw_11563392'!$D$18 | E39: ='balance_raw_11563392'!$E$18 | F39: ='balance_raw_11563392'!$F$18 | H39: =IFERROR(B39/$B$39*100,"") | I39: =IFERROR(C39/$B$39*100,"") | J39: =IFERROR(D39/$B$39*100,"") | K39: =IFERROR(E39/$B$39*100,"") | L39: =IFERROR(F39/$B$39*100,"")
A40: Tilgodehavender | B40: ='balance_raw_11563392'!$B$19 | C40: ='balance_raw_11563392'!$C$19 | D40: ='balance_raw_11563392'!$D$19 | E40: ='balance_raw_11563392'!$E$19 | F40: ='balance_raw_11563392'!$F$19 | H40: =IFERROR(B40/$B$40*100,"") | I40: =IFERROR(C40/$B$40*100,"") | J40: =IFERROR(D40/$B$40*100,"") | K40: =IFERROR(E40/$B$40*100,"") | L40: =IFERROR(F40/$B$40*100,"")
A41: Værdipapirer | B41: ='balance_raw_11563392'!$B$20 | C41: ='balance_raw_11563392'!$C$20 | D41: ='balance_raw_11563392'!$D$20 | E41: ='balance_raw_11563392'!$E$20 | F41: ='balance_raw_11563392'!$F$20 | H41: =IFERROR(B41/$B$41*100,"") | I41: =IFERROR(C41/$B$41*100,"") | J41: =IFERROR(D41/$B$41*100,"") | K41: =IFERROR(E41/$B$41*100,"") | L41: =IFERROR(F41/$B$41*100,"")
A42: Likvide beholdninger | B42: ='balance_raw_11563392'!$B$21 | C42: ='balance_raw_11563392'!$C$21 | D42: ='balance_raw_11563392'!$D$21 | E42: ='balance_raw_11563392'!$E$21 | F42: ='balance_raw_11563392'!$F$21 | H42: =IFERROR(B42/$B$42*100,"") | I42: =IFERROR(C42/$B$42*100,"") | J42: =IFERROR(D42/$B$42*100,"") | K42: =IFERROR(E42/$B$42*100,"") | L42: =IFERROR(F42/$B$42*100,"")
A43: Omsætningsaktiver | B43: ='balance_raw_11563392'!$B$22 | C43: ='balance_raw_11563392'!$C$22 | D43: ='balance_raw_11563392'!$D$22 | E43: ='balance_raw_11563392'!$E$22 | F43: ='balance_raw_11563392'!$F$22 | H43: =IFERROR(B43/$B$43*100,"") | I43: =IFERROR(C43/$B$43*100,"") | J43: =IFERROR(D43/$B$43*100,"") | K43: =IFERROR(E43/$B$43*100,"") | L43: =IFERROR(F43/$B$43*100,"")
A44: Aktiver | B44: ='balance_raw_11563392'!$B$23 | C44: ='balance_raw_11563392'!$C$23 | D44: ='balance_raw_11563392'!$D$23 | E44: ='balance_raw_11563392'!$E$23 | F44: ='balance_raw_11563392'!$F$23 | H44: =IFERROR(B44/$B$44*100,"") | I44: =IFERROR(C44/$B$44*100,"") | J44: =IFERROR(D44/$B$44*100,"") | K44: =IFERROR(E44/$B$44*100,"") | L44: =IFERROR(F44/$B$44*100,"")
A46: PASSIVER t.kr. | B46: 2020 | C46: 2021 | D46: 2022 | E46: 2023 | F46: 2024 | H46: 2020 | I46: 2021 | J46: 2022 | K46: 2023 | L46: 2024
A47: Selskabskapital | B47: ='balance_raw_11563392'!$B$24 | C47: ='balance_raw_11563392'!$C$24 | D47: ='balance_raw_11563392'!$D$24 | E47: ='balance_raw_11563392'!$E$24 | F47: ='balance_raw_11563392'!$F$24 | H47: =IFERROR(B47/$B$47*100,"") | I47: =IFERROR(C47/$B$47*100,"") | J47: =IFERROR(D47/$B$47*100,"") | K47: =IFERROR(E47/$B$47*100,"") | L47: =IFERROR(F47/$B$47*100,"")
A48: Reserve for nettoopskrivning (indre værdis metode) | B48: ='balance_raw_11563392'!$B$25 | C48: ='balance_raw_11563392'!$C$25 | D48: ='balance_raw_11563392'!$D$25 | E48: ='balance_raw_11563392'!$E$25 | F48: ='balance_raw_11563392'!$F$25 | H48: =IFERROR(B48/$B$48*100,"") | I48: =IFERROR(C48/$B$48*100,"") | J48: =IFERROR(D48/$B$48*100,"") | K48: =IFERROR(E48/$B$48*100,"") | L48: =IFERROR(F48/$B$48*100,"")
A49: Reserve for udviklingsomkostninger | B49: ='balance_raw_11563392'!$B$26 | C49: ='balance_raw_11563392'!$C$26 | D49: ='balance_raw_11563392'!$D$26 | E49: ='balance_raw_11563392'!$E$26 | F49: ='balance_raw_11563392'!$F$26 | H49: =IFERROR(B49/$B$49*100,"") | I49: =IFERROR(C49/$B$49*100,"") | J49: =IFERROR(D49/$B$49*100,"") | K49: =IFERROR(E49/$B$49*100,"") | L49: =IFERROR(F49/$B$49*100,"")
A50: Reserve for sikringstransaktioner | B50: ='balance_raw_11563392'!$B$27 | C50: ='balance_raw_11563392'!$C$27 | D50: ='balance_raw_11563392'!$D$27 | E50: ='balance_raw_11563392'!$E$27 | F50: ='balance_raw_11563392'!$F$27 | H50: =IFERROR(B50/$B$50*100,"") | I50: =IFERROR(C50/$B$50*100,"") | J50: =IFERROR(D50/$B$50*100,"") | K50: =IFERROR(E50/$B$50*100,"") | L50: =IFERROR(F50/$B$50*100,"")
A51: Andre reserver | B51: ='balance_raw_11563392'!$B$28 | C51: ='balance_raw_11563392'!$C$28 | D51: ='balance_raw_11563392'!$D$28 | E51: ='balance_raw_11563392'!$E$28 | F51: ='balance_raw_11563392'!$F$28 | H51: =IFERROR(B51/$B$51*100,"") | I51: =IFERROR(C51/$B$51*100,"") | J51: =IFERROR(D51/$B$51*100,"") | K51: =IFERROR(E51/$B$51*100,"") | L51: =IFERROR(F51/$B$51*100,"")
A52: Overført resultat | B52: ='balance_raw_11563392'!$B$29 | C52: ='balance_raw_11563392'!$C$29 | D52: ='balance_raw_11563392'!$D$29 | E52: ='balance_raw_11563392'!$E$29 | F52: ='balance_raw_11563392'!$F$29 | H52: =IFERROR(B52/$B$52*100,"") | I52: =IFERROR(C52/$B$52*100,"") | J52: =IFERROR(D52/$B$52*100,"") | K52: =IFERROR(E52/$B$52*100,"") | L52: =IFERROR(F52/$B$52*100,"")
A53: Egenkapital i alt | B53: ='balance_raw_11563392'!$B$30 | C53: ='balance_raw_11563392'!$C$30 | D53: ='balance_raw_11563392'!$D$30 | E53: ='balance_raw_11563392'!$E$30 | F53: ='balance_raw_11563392'!$F$30 | H53: =IFERROR(B53/$B$53*100,"") | I53: =IFERROR(C53/$B$53*100,"") | J53: =IFERROR(D53/$B$53*100,"") | K53: =IFERROR(E53/$B$53*100,"") | L53: =IFERROR(F53/$B$53*100,"")
A54: Hensættelse til udskudt skat | B54: ='balance_raw_11563392'!$B$31 | C54: ='balance_raw_11563392'!$C$31 | D54: ='balance_raw_11563392'!$D$31 | E54: ='balance_raw_11563392'!$E$31 | F54: ='balance_raw_11563392'!$F$31 | H54: =IFERROR(B54/$B$54*100,"") | I54: =IFERROR(C54/$B$54*100,"") | J54: =IFERROR(D54/$B$54*100,"") | K54: =IFERROR(E54/$B$54*100,"") | L54: =IFERROR(F54/$B$54*100,"")
A55: Hensatte forpligtelser | B55: ='balance_raw_11563392'!$B$32 | C55: ='balance_raw_11563392'!$C$32 | D55: ='balance_raw_11563392'!$D$32 | E55: ='balance_raw_11563392'!$E$32 | F55: ='balance_raw_11563392'!$F$32 | H55: =IFERROR(B55/$B$55*100,"") | I55: =IFERROR(C55/$B$55*100,"") | J55: =IFERROR(D55/$B$55*100,"") | K55: =IFERROR(E55/$B$55*100,"") | L55: =IFERROR(F55/$B$55*100,"")
A56: Ansvarlig lånekapital (langfristet) | B56: ='balance_raw_11563392'!$B$33 | C56: ='balance_raw_11563392'!$C$33 | D56: ='balance_raw_11563392'!$D$33 | E56: ='balance_raw_11563392'!$E$33 | F56: ='balance_raw_11563392'!$F$33 | H56: =IFERROR(B56/$B$56*100,"") | I56: =IFERROR(C56/$B$56*100,"") | J56: =IFERROR(D56/$B$56*100,"") | K56: =IFERROR(E56/$B$56*100,"") | L56: =IFERROR(F56/$B$56*100,"")
A57: Langfristede lån | B57: ='balance_raw_11563392'!$B$34 | C57: ='balance_raw_11563392'!$C$34 | D57: ='balance_raw_11563392'!$D$34 | E57: ='balance_raw_11563392'!$E$34 | F57: ='balance_raw_11563392'!$F$34 | H57: =IFERROR(B57/$B$57*100,"") | I57: =IFERROR(C57/$B$57*100,"") | J57: =IFERROR(D57/$B$57*100,"") | K57: =IFERROR(E57/$B$57*100,"") | L57: =IFERROR(F57/$B$57*100,"")
A58: Leasingforpligtelser (langfristet) | B58: ='balance_raw_11563392'!$B$35 | C58: ='balance_raw_11563392'!$C$35 | D58: ='balance_raw_11563392'!$D$35 | E58: ='balance_raw_11563392'!$E$35 | F58: ='balance_raw_11563392'!$F$35 | H58: =IFERROR(B58/$B$58*100,"") | I58: =IFERROR(C58/$B$58*100,"") | J58: =IFERROR(D58/$B$58*100,"") | K58: =IFERROR(E58/$B$58*100,"") | L58: =IFERROR(F58/$B$58*100,"")
A59: Anden gæld (langfristet) | B59: ='balance_raw_11563392'!$B$36 | C59: ='balance_raw_11563392'!$C$36 | D59: ='balance_raw_11563392'!$D$36 | E59: ='balance_raw_11563392'!$E$36 | F59: ='balance_raw_11563392'!$F$36 | H59: =IFERROR(B59/$B$59*100,"") | I59: =IFERROR(C59/$B$59*100,"") | J59: =IFERROR(D59/$B$59*100,"") | K59: =IFERROR(E59/$B$59*100,"") | L59: =IFERROR(F59/$B$59*100,"")
A60: Langfristede gældsforpligtelser | B60: ='balance_raw_11563392'!$B$37 | C60: ='balance_raw_11563392'!$C$37 | D60: ='balance_raw_11563392'!$D$37 | E60: ='balance_raw_11563392'!$E$37 | F60: ='balance_raw_11563392'!$F$37 | H60: =IFERROR(B60/$B$60*100,"") | I60: =IFERROR(C60/$B$60*100,"") | J60: =IFERROR(D60/$B$60*100,"") | K60: =IFERROR(E60/$B$60*100,"") | L60: =IFERROR(F60/$B$60*100,"")
A61: Ansvarlig lånekapital (kortfristet) | B61: ='balance_raw_11563392'!$B$38 | C61: ='balance_raw_11563392'!$C$38 | D61: ='balance_raw_11563392'!$D$38 | E61: ='balance_raw_11563392'!$E$38 | F61: ='balance_raw_11563392'!$F$38 | H61: =IFERROR(B61/$B$61*100,"") | I61: =IFERROR(C61/$B$61*100,"") | J61: =IFERROR(D61/$B$61*100,"") | K61: =IFERROR(E61/$B$61*100,"") | L61: =IFERROR(F61/$B$61*100,"")
A62: Kortfristet del af langfristede gældsforpligtelser | B62: ='balance_raw_11563392'!$B$39 | C62: ='balance_raw_11563392'!$C$39 | D62: ='balance_raw_11563392'!$D$39 | E62: ='balance_raw_11563392'!$E$39 | F62: ='balance_raw_11563392'!$F$39 | H62: =IFERROR(B62/$B$62*100,"") | I62: =IFERROR(C62/$B$62*100,"") | J62: =IFERROR(D62/$B$62*100,"") | K62: =IFERROR(E62/$B$62*100,"") | L62: =IFERROR(F62/$B$62*100,"")
A63: Kreditinstitutter | B63: ='balance_raw_11563392'!$B$40 | C63: ='balance_raw_11563392'!$C$40 | D63: ='balance_raw_11563392'!$D$40 | E63: ='balance_raw_11563392'!$E$40 | F63: ='balance_raw_11563392'!$F$40 | H63: =IFERROR(B63/$B$63*100,"") | I63: =IFERROR(C63/$B$63*100,"") | J63: =IFERROR(D63/$B$63*100,"") | K63: =IFERROR(E63/$B$63*100,"") | L63: =IFERROR(F63/$B$63*100,"")
A64: Leasingforpligtelser (kortfristet) | B64: ='balance_raw_11563392'!$B$41 | C64: ='balance_raw_11563392'!$C$41 | D64: ='balance_raw_11563392'!$D$41 | E64: ='balance_raw_11563392'!$E$41 | F64: ='balance_raw_11563392'!$F$41 | H64: =IFERROR(B64/$B$64*100,"") | I64: =IFERROR(C64/$B$64*100,"") | J64: =IFERROR(D64/$B$64*100,"") | K64: =IFERROR(E64/$B$64*100,"") | L64: =IFERROR(F64/$B$64*100,"")
A65: Leverandører af varer og tjenesteydelser | B65: ='balance_raw_11563392'!$B$42 | C65: ='balance_raw_11563392'!$C$42 | D65: ='balance_raw_11563392'!$D$42 | E65: ='balance_raw_11563392'!$E$42 | F65: ='balance_raw_11563392'!$F$42 | H65: =IFERROR(B65/$B$65*100,"") | I65: =IFERROR(C65/$B$65*100,"") | J65: =IFERROR(D65/$B$65*100,"") | K65: =IFERROR(E65/$B$65*100,"") | L65: =IFERROR(F65/$B$65*100,"")
A66: Gæld til tilknyttede virksomheder | B66: ='balance_raw_11563392'!$B$43 | C66: ='balance_raw_11563392'!$C$43 | D66: ='balance_raw_11563392'!$D$43 | E66: ='balance_raw_11563392'!$E$43 | F66: ='balance_raw_11563392'!$F$43 | H66: =IFERROR(B66/$B$66*100,"") | I66: =IFERROR(C66/$B$66*100,"") | J66: =IFERROR(D66/$B$66*100,"") | K66: =IFERROR(E66/$B$66*100,"") | L66: =IFERROR(F66/$B$66*100,"")
A67: Gæld til selskabsdeltagere og ledelse | B67: ='balance_raw_11563392'!$B$44 | C67: ='balance_raw_11563392'!$C$44 | D67: ='balance_raw_11563392'!$D$44 | E67: ='balance_raw_11563392'!$E$44 | F67: ='balance_raw_11563392'!$F$44 | H67: =IFERROR(B67/$B$67*100,"") | I67: =IFERROR(C67/$B$67*100,"") | J67: =IFERROR(D67/$B$67*100,"") | K67: =IFERROR(E67/$B$67*100,"") | L67: =IFERROR(F67/$B$67*100,"")
A68: Selskabsskat | B68: ='balance_raw_11563392'!$B$45 | C68: ='balance_raw_11563392'!$C$45 | D68: ='balance_raw_11563392'!$D$45 | E68: ='balance_raw_11563392'!$E$45 | F68: ='balance_raw_11563392'!$F$45 | H68: =IFERROR(B68/$B$68*100,"") | I68: =IFERROR(C68/$B$68*100,"") | J68: =IFERROR(D68/$B$68*100,"") | K68: =IFERROR(E68/$B$68*100,"") | L68: =IFERROR(F68/$B$68*100,"")
A69: Gæld til tilknyttede virksomheder vedr. selskabsskat | B69: ='balance_raw_11563392'!$B$46 | C69: ='balance_raw_11563392'!$C$46 | D69: ='balance_raw_11563392'!$D$46 | E69: ='balance_raw_11563392'!$E$46 | F69: ='balance_raw_11563392'!$F$46 | H69: =IFERROR(B69/$B$69*100,"") | I69: =IFERROR(C69/$B$69*100,"") | J69: =IFERROR(D69/$B$69*100,"") | K69: =IFERROR(E69/$B$69*100,"") | L69: =IFERROR(F69/$B$69*100,"")
A70: Anden gæld (kortfristet) | B70: ='balance_raw_11563392'!$B$47 | C70: ='balance_raw_11563392'!$C$47 | D70: ='balance_raw_11563392'!$D$47 | E70: ='balance_raw_11563392'!$E$47 | F70: ='balance_raw_11563392'!$F$47 | H70: =IFERROR(B70/$B$70*100,"") | I70: =IFERROR(C70/$B$70*100,"") | J70: =IFERROR(D70/$B$70*100,"") | K70: =IFERROR(E70/$B$70*100,"") | L70: =IFERROR(F70/$B$70*100,"")
A71: Periodeafgrænsningsposter (passiver) | B71: ='balance_raw_11563392'!$B$48 | C71: ='balance_raw_11563392'!$C$48 | D71: ='balance_raw_11563392'!$D$48 | E71: ='balance_raw_11563392'!$E$48 | F71: ='balance_raw_11563392'!$F$48 | H71: =IFERROR(B71/$B$71*100,"") | I71: =IFERROR(C71/$B$71*100,"") | J71: =IFERROR(D71/$B$71*100,"") | K71: =IFERROR(E71/$B$71*100,"") | L71: =IFERROR(F71/$B$71*100,"")
A72: Kortfristede gældsforpligtelser | B72: ='balance_raw_11563392'!$B$49 | C72: ='balance_raw_11563392'!$C$49 | D72: ='balance_raw_11563392'!$D$49 | E72: ='balance_raw_11563392'!$E$49 | F72: ='balance_raw_11563392'!$F$49 | H72: =IFERROR(B72/$B$72*100,"") | I72: =IFERROR(C72/$B$72*100,"") | J72: =IFERROR(D72/$B$72*100,"") | K72: =IFERROR(E72/$B$72*100,"") | L72: =IFERROR(F72/$B$72*100,"")
A73: Gældsforpligtelser | B73: ='balance_raw_11563392'!$B$50 | C73: ='balance_raw_11563392'!$C$50 | D73: ='balance_raw_11563392'!$D$50 | E73: ='balance_raw_11563392'!$E$50 | F73: ='balance_raw_11563392'!$F$50 | H73: =IFERROR(B73/$B$73*100,"") | I73: =IFERROR(C73/$B$73*100,"") | J73: =IFERROR(D73/$B$73*100,"") | K73: =IFERROR(E73/$B$73*100,"") | L73: =IFERROR(F73/$B$73*100,"")
A74: Passiver | B74: ='balance_raw_11563392'!$B$51 | C74: ='balance_raw_11563392'!$C$51 | D74: ='balance_raw_11563392'!$D$51 | E74: ='balance_raw_11563392'!$E$51 | F74: ='balance_raw_11563392'!$F$51 | H74: =IFERROR(B74/$B$74*100,"") | I74: =IFERROR(C74/$B$74*100,"") | J74: =IFERROR(D74/$B$74*100,"") | K74: =IFERROR(E74/$B$74*100,"") | L74: =IFERROR(F74/$B$74*100,"")
A76: NØGLEOPLYSNINGER | B76: 2020 | C76: 2021 | D76: 2022 | E76: 2023 | F76: 2024
A77: Gns. antal medarbejdere | B77: ='res_raw_11563392'!$B$19 | C77: ='res_raw_11563392'!$C$19 | D77: ='res_raw_11563392'!$D$19 | E77: ='res_raw_11563392'!$E$19 | F77: ='res_raw_11563392'!$F$19 | H77: =IFERROR(B77/$B$77*100,"") | I77: =IFERROR(C77/$B$77*100,"") | J77: =IFERROR(D77/$B$77*100,"") | K77: =IFERROR(E77/$B$77*100,"") | L77: =IFERROR(F77/$B$77*100,"")
A78: Investering i materielle anlægsaktiver | B78: ='res_raw_11563392'!$B$20 | C78: ='res_raw_11563392'!$C$20 | D78: ='res_raw_11563392'!$D$20 | E78: ='res_raw_11563392'!$E$20 | F78: ='res_raw_11563392'!$F$20 | H78: =IFERROR(B78/$B$78*100,"") | I78: =IFERROR(C78/$B$78*100,"") | J78: =IFERROR(D78/$B$78*100,"") | K78: =IFERROR(E78/$B$78*100,"") | L78: =IFERROR(F78/$B$78*100,"")
A80: NØGLETAL | B80: 2020 | C80: 2021 | D80: 2022 | E80: 2023 | F80: 2024
A81: Afkastningsgrad, % | B81: =IFERROR(($B$13+$B$15+$B$14)/$B$44*100,"") | C81: =IFERROR(($C$13+$C$15+$C$14)/$C$44*100,"") | D81: =IFERROR(($D$13+$D$15+$D$14)/$D$44*100,"") | E81: =IFERROR(($E$13+$E$15+$E$14)/$E$44*100,"") | F81: =IFERROR(($F$13+$F$15+$F$14)/$F$44*100,"")
A82: Overskudsgrad, % | B82: =IFERROR(($B$13+$B$15+$B$14)/$B$4*100,"") | C82: =IFERROR(($C$13+$C$15+$C$14)/$C$4*100,"") | D82: =IFERROR(($D$13+$D$15+$D$14)/$D$4*100,"") | E82: =IFERROR(($E$13+$E$15+$E$14)/$E$4*100,"") | F82: =IFERROR(($F$13+$F$15+$F$14)/$F$4*100,"")
A83: Aktivernes omsætningshastighed, gange | B83: =IFERROR($B$4/$B$44,"") | C83: =IFERROR($C$4/$C$44,"") | D83: =IFERROR($D$4/$D$44,"") | E83: =IFERROR($E$4/$E$44,"") | F83: =IFERROR($F$4/$F$44,"")
A84: Egenkapitalens forrentning, % | B84: =IFERROR($B$18/$B$53*100,"") | C84: =IFERROR($C$18/$C$53*100,"") | D84: =IFERROR($D$18/$D$53*100,"") | E84: =IFERROR($E$18/$E$53*100,"") | F84: =IFERROR($F$18/$F$53*100,"")
A85: Gældsrente, % | B85: =IFERROR($B$16/($B$74-$B$53)*100,"") | C85: =IFERROR($C$16/($C$74-$C$53)*100,"") | D85: =IFERROR($D$16/($D$74-$D$53)*100,"") | E85: =IFERROR($E$16/($E$74-$E$53)*100,"") | F85: =IFERROR($F$16/($F$74-$F$53)*100,"")
A86: Soliditetsgrad, % | B86: =IFERROR($B$53/$B$44*100,"") | C86: =IFERROR($C$53/$C$44*100,"") | D86: =IFERROR($D$53/$D$44*100,"") | E86: =IFERROR($E$53/$E$44*100,"") | F86: =IFERROR($F$53/$F$44*100,"")
A87: Gearing | B87: =IFERROR(($B$74-$B$53)/$B$53,"") | C87: =IFERROR(($C$74-$C$53)/$C$53,"") | D87: =IFERROR(($D$74-$D$53)/$D$53,"") | E87: =IFERROR(($E$74-$E$53)/$E$53,"") | F87: =IFERROR(($F$74-$F$53)/$F$53,"")
A88: Likviditetsgrad, % | B88: =IFERROR($B$43/$B$72*100,"") | C88: =IFERROR($C$43/$C$72*100,"") | D88: =IFERROR($D$43/$D$72*100,"") | E88: =IFERROR($E$43/$E$72*100,"") | F88: =IFERROR($F$43/$F$72*100,"")
A89: Rentemarginal, % | B89: =IFERROR(B81-B85,"") | C89: =IFERROR(C81-C85,"") | D89: =IFERROR(D81-D85,"") | E89: =IFERROR(E81-E85,"") | F89: =IFERROR(F81-F85,"")
A90: Gældsandel, % | B90: =IFERROR(($B$74-$B$53)/$B$44*100,"") | C90: =IFERROR(($C$74-$C$53)/$C$44*100,"") | D90: =IFERROR(($D$74-$D$53)/$D$44*100,"") | E90: =IFERROR(($E$74-$E$53)/$E$44*100,"") | F90: =IFERROR(($F$74-$F$53)/$F$44*100,"")
A91: Kapitalbindingsgrad, % | B91: =IFERROR($B$32/($B$53+$B$60)*100,"") | C91: =IFERROR($C$32/($C$53+$C$60)*100,"") | D91: =IFERROR($D$32/($D$53+$D$60)*100,"") | E91: =IFERROR($E$32/($E$53+$E$60)*100,"") | F91: =IFERROR($F$32/($F$53+$F$60)*100,"")

Sheet res_raw_11563392
A1: Resultatopgørelse & nøgleoplysninger (t.kr.) | B1: 2020 | C1: 2021 | D1: 2022 | E1: 2023 | F1: 2024
A2: Nettoomsætning
A3: Andre driftsindtægter
A4: Vareforbrug
A5: Andre eksterne omkostninger
A6: Bruttoresultat | B6: 7896 | C6: 5697 | D6: 9319 | E6: 13089 | F6: 17701
A7: Personaleomkostninger | B7: 3492 | C7: 3846 | D7: 4307 | E7: 4456 | F7: 5304
A8: Resultat før afskrivninger
A9: Af- og nedskrivninger | B9: 9 | C9: 5 | D9: 5 | E9: 3 | F9: 31
A10: Andre driftsomkostninger | F10: 171
A11: Resultat af primær drift | B11: 4395 | C11: 1846 | D11: 5007 | E11: 8630 | F11: 12196
A12: Indtægter af kapitalandele, dattervirksomheder | F12: 5008
A13: Finansielle indtægter | B13: 372 | C13: 903 | D13: 746 | E13: 1467 | F13: 6766
A14: Finansielle omkostninger | B14: 355 | C14: 535 | D14: 424 | E14: 266 | F14: 498
A15: Finansielle poster, netto | B15: -167 | C15: -518 | D15: -473 | E15: -1351 | F15: -11276
A16: Resultat før skat | B16: 4561 | C16: 2364 | D16: 5480 | E16: 9981 | F16: 23472
A17: Skat af årets resultat | B17: 1004 | C17: 522 | D17: 1207 | E17: 2197 | F17: 4065
A18: Årets resultat | B18: 3558 | C18: 1842 | D18: 4273 | E18: 7784 | F18: 19408
A19: Gns. antal medarbejdere | B19: 6 | C19: 7 | D19: 6 | E19: 7 | F19: 6
A20: Investering i materielle anlægsaktiver | B20: 0 | C20: 0 | D20: 0 | F20: 863

Sheet balance_raw_11563392
A1: Balance (t.kr.) | B1: 2020 | C1: 2021 | D1: 2022 | E1: 2023 | F1: 2024
A2: Grunde og bygninger
A3: Produktionsanlæg og maskiner
A4: Driftsmateriel og inventar | F4: 520
A5: Indretning af lejede lokaler | B5: 14 | C5: 8 | D5: 3 | E5: 0 | F5: 312
A6: Forudbetaling og anlægsaktiver under opførelse
A7: Materielle anlægsaktiver | B7: 14 | C7: 8 | D7: 3 | E7: 0 | F7: 832
A8: Kapitalandele, dattervirksomheder | F8: 24405
A9: Deposita | B9: 3000 | C9: 3000 | D9: 3000 | E9: 3000 | F9: 3000
A10: Finansielle anlægsaktiver | B10: 5011 | C10: 4508 | D10: 4778 | E10: 5091 | F10: 30466
A11: Anlægsaktiver | B11: 5025 | C11: 4516 | D11: 4780 | E11: 5091 | F11: 31298
A12: Tilgodehavender fra salg og tjenesteydelser | B12: 0 | C12: 479 | D12: 1023 | E12: 863 | F12: 1356
A13: Tilgodehavender hos tilknyttede virksomheder | B13: 34998 | C13: 37503 | D13: 45718 | E13: 6430 | F13: 63832
A14: Andre tilgodehavender | B14: 4707 | C14: 8703 | D14: 992 | E14: 1962 | F14: 2307
A15: Periodeafgrænsningsposter (aktiver) | B15: 2616 | C15: 1971 | D15: 3330 | E15: 3158 | F15: 4502
A16: Udskudt skatteaktiv | B16: 2 | C16: 2 | D16: 2 | E16: 2 | F16: 0
A17: Tilgodehavende skat hos tilknyttede virksomheder
A18: Kortfristede skattetilgodehavender
A19: Tilgodehavender | B19: 42323 | C19: 48658 | D19: 51066 | E19: 12415 | F19: 71997
A20: Værdipapirer
A21: Likvide beholdninger | B21: 27067 | C21: 32631 | D21: 31700 | E21: 70914 | F21: 15060
A22: Omsætningsaktiver | B22: 69389 | C22: 81289 | D22: 82766 | E22: 83329 | F22: 87057
A23: Aktiver | B23: 74414 | C23: 85805 | D23: 87546 | E23: 88420 | F23: 118355
A24: Selskabskapital | B24: 600 | C24: 600 | D24: 600 | E24: 600 | F24: 600
A25: Reserve for nettoopskrivning (indre værdis metode) | F25: 5008
A26: Reserve for udviklingsomkostninger
A27: Reserve for sikringstransaktioner
A28: Andre reserver
A29: Overført resultat | B29: 15436 | C29: 17279 | D29: 21552 | E29: 29336 | F29: 43736
A30: Egenkapital i alt | B30: 16036 | C30: 17879 | D30: 22152 | E30: 29936 | F30: 49344
A31: Hensættelse til udskudt skat | F31: 36
A32: Hensatte forpligtelser | F32: 36
A33: Ansvarlig lånekapital (langfristet)
A34: Langfristede lån
A35: Leasingforpligtelser (langfristet)
A36: Anden gæld (langfristet) | B36: 25424 | C36: 19239 | D36: 19239 | E36: 2400 | F36: 2400
A37: Langfristede gældsforpligtelser | B37: 27824 | C37: 21639 | D37: 21639 | E37: 16829 | F37: 12019
A38: Ansvarlig lånekapital (kortfristet)
A39: Kortfristet del af langfristede gældsforpligtelser | C39: 4810 | D39: 4810 | E39: 4810 | F39: 4810
A40: Kreditinstitutter | B40: 12 | C40: 24 | D40: 56 | E40: 29 | F40: 0
A41: Leasingforpligtelser (kortfristet)
A42: Leverandører af varer og tjenesteydelser | B42: 5345 | C42: 6314 | D42: 7327 | E42: 3208 | F42: 2835
A43: Gæld til tilknyttede virksomheder | B43: 8530 | C43: 7965 | D43: 8460 | E43: 4082 | F43: 20833
A44: Gæld til selskabsdeltagere og ledelse
A45: Selskabsskat | B45: 965 | C45: 509 | D45: 1197 | E45: 2187 | F45: 4011
A46: Gæld til tilknyttede virksomheder vedr. selskabsskat
A47: Anden gæld (kortfristet) | B47: 4002 | C47: 3132 | D47: 3046 | E47: 832 | F47: 896
A48: Periodeafgrænsningsposter (passiver) | B48: 11699 | C48: 23534 | D48: 18861 | E48: 26508 | F48: 23572
A49: Kortfristede gældsforpligtelser | B49: 30554 | C49: 46288 | D49: 43756 | E49: 41655 | F49: 56957
A50: Gældsforpligtelser | B50: 58378 | C50: 67927 | D50: 65395 | E50: 58484 | F50: 68976
A51: Passiver | B51: 74414 | C51: 85805 | D51: 87546 | E51: 88420 | F51: 118355

Sheet Simpel_arts
A1: Regnskabs- og nøgletal (CVR: 11563392) — artsopdelt
A3: Beløb i 1.000 kr. | B3: 2024 | C3: 2023 | D3: 2022 | F3: Note / XBRL-felt
A4: Uddrag af resultatopgørelse
A5: Nettoomsætning | B5: ='res_raw_11563392'!$F$2 | C5: ='res_raw_11563392'!$E$2 | D5: ='res_raw_11563392'!$D$2 | F5: fsa:Revenue
A6: Andre driftsindtægter | B6: ='res_raw_11563392'!$F$3 | C6: ='res_raw_11563392'!$E$3 | D6: ='res_raw_11563392'!$D$3 | F6: fsa:OtherOperatingIncome. Indtægter fra sekundære aktiviteter (huslejeindtægter, avance ved salg af anlæg mv.).
A7: Vareforbrug | B7: =-'res_raw_11563392'!$F$4 | C7: =-'res_raw_11563392'!$E$4 | D7: =-'res_raw_11563392'!$D$4 | F7: fsa:CostOfSales (vises negativt for korrekt SUM-formel).
A8: Andre eksterne omk. mv. | B8: =-'res_raw_11563392'!$F$5 | C8: =-'res_raw_11563392'!$E$5 | D8: =-'res_raw_11563392'!$D$5 | F8: fsa:OtherExternalExpenses (vises negativt). Husleje, energi, kontorhold mv.
A9: Bruttofortjeneste | B9: =SUM(B5:B8) | C9: =SUM(C5:C8) | D9: =SUM(D5:D8) | F9: Beregnet: Nettoomsætning + Andre driftsindt. − Vareforbrug − Andre ext. omk.
A10: Personaleomkostninger | B10: =-'res_raw_11563392'!$F$7 | C10: =-'res_raw_11563392'!$E$7 | D10: =-'res_raw_11563392'!$D$7 | F10: fsa:EmployeeBenefitsExpense (vises negativt). Lønninger, pension, sociale ydelser.
A11: Af- og nedskrivninger | B11: =-'res_raw_11563392'!$F$9 | C11: =-'res_raw_11563392'!$E$9 | D11: =-'res_raw_11563392'!$D$9 | F11: fsa:Depreciation (vises negativt). Af- og nedskrivninger på materielle og immaterielle anlægsaktiver.
A12: Andre driftsomkostninger | B12: =-'res_raw_11563392'!$F$10 | C12: =-'res_raw_11563392'!$E$10 | D12: =-'res_raw_11563392'!$D$10 | F12: fsa:OtherOperatingExpenses (vises negativt). Typisk 0 eller meget lille post.
A13: Resultat af primær drift | B13: =SUM(B9:B12) | C13: =SUM(C9:C12) | D13: =SUM(D9:D12) | F13: Beregnet: Bruttofortjeneste − Personaleomk. − Af- og nedskrivninger − Andre driftsomk. EBIT.
A14: Finansielle indtægter mv. | B14: =N('res_raw_11563392'!$F$12)+N('res_raw_11563392'!$F$13) | C14: =N('res_raw_11563392'!$E$12)+N('res_raw_11563392'!$E$13) | D14: =N('res_raw_11563392'!$D$12)+N('res_raw_11563392'!$D$13) | F14: fsa:IncomeFromSubsidiaries + fsa:OtherFinanceIncome.
A15: Finansielle omkostninger mv. | B15: =-'res_raw_11563392'!$F$14 | C15: =-'res_raw_11563392'!$E$14 | D15: =-'res_raw_11563392'!$D$14 | F15: fsa:OtherFinanceExpenses (vises negativt). Renteomkostninger, kurstab mv.
A16: Resultat før skat | B16: =SUM(B13:B15) | C16: =SUM(C13:C15) | D16: =SUM(D13:D15) | F16: Beregnet: EBIT + Fin. indtægter + Fin. omk. EBT.
A18: Uddrag af balance
A19: Anlægsaktiver | B19: ='balance_raw_11563392'!$F$11 | C19: ='balance_raw_11563392'!$E$11 | D19: ='balance_raw_11563392'!$D$11 | F19: fsa:NoncurrentAssets. Materielle, immaterielle og finansielle anlægsaktiver.
A20: Omsætningsaktiver | B20: ='balance_raw_11563392'!$F$22 | C20: ='balance_raw_11563392'!$E$22 | D20: ='balance_raw_11563392'!$D$22 | F20: fsa:CurrentAssets. Varebeholdninger, tilgodehavender, likvider.
A21: Aktiver i alt | B21: =SUM(B19:B20) | C21: =SUM(C19:C20) | D21: =SUM(D19:D20) | F21: Beregnet: Anlægsaktiver + Omsætningsaktiver. Bør matche fsa:Assets.
A23: Egenkapital | B23: ='balance_raw_11563392'!$F$30 | C23: ='balance_raw_11563392'!$E$30 | D23: ='balance_raw_11563392'!$D$30 | F23: fsa:Equity. Selskabskapital, overført resultat, reserver.
A24: Forpligtelser | B24: ='balance_raw_11563392'!$F$51-'balance_raw_11563392'!$F$30 | C24: ='balance_raw_11563392'!$E$51-'balance_raw_11563392'!$E$30 | D24: ='balance_raw_11563392'!$D$51-'balance_raw_11563392'!$D$30 | F24: Beregnet: Passiver (fsa:LiabilitiesAndEquity) − Egenkapital. Hensættelser + kort- og langfristet gæld.
A25: Passiver i alt | B25: =SUM(B23:B24) | C25: =SUM(C23:C24) | D25: =SUM(D23:D24) | F25: Beregnet: Egenkapital + Forpligtelser. Bør matche Aktiver i alt.
A27: Udvalgte balanceposter
A28: Varebeholdninger | F28: fsa:Inventories (eller fsa:ManufacturedGoodsAndGoodsForResale hvis total mangler).
A29: Tilgodehavender fra salg | B29: ='balance_raw_11563392'!$F$12 | C29: ='balance_raw_11563392'!$E$12 | D29: ='balance_raw_11563392'!$D$12 | F29: fsa:ShorttermTradeReceivables. Kortfristede tilgodehavender fra kunder.
A30: Kortfristede gældsforpligtelser | B30: ='balance_raw_11563392'!$F$49 | C30: ='balance_raw_11563392'!$E$49 | D30: ='balance_raw_11563392'!$D$49 | F30: fsa:ShorttermLiabilitiesOtherThanProvisions. Gæld der forfalder inden for 1 år.
A32: Rentabilitet
A33: Afkastningsgrad, % | B33: =IFERROR((B13+B14)/B21*100,"") | C33: =IFERROR((C13+C14)/C21*100,"") | D33: =IFERROR((D13+D14)/D21*100,"")
A34: Overskudsgrad, % | B34: =IFERROR((B13+B14)/B5*100,"") | C34: =IFERROR((C13+C14)/C5*100,"") | D34: =IFERROR((D13+D14)/D5*100,"")
A35: Aktivernes omsætningshastighed, gange | B35: =IFERROR(B5/B21,"") | C35: =IFERROR(C5/C21,"") | D35: =IFERROR(D5/D21,"")
A36: Gældsrente, % | B36: =IFERROR(-B15*100/B24,"") | C36: =IFERROR(-C15*100/C24,"") | D36: =IFERROR(-D15*100/D24,"")
A37: Egenkapitalens forrentning, % | B37: =IFERROR(B16/B23*100,"") | C37: =IFERROR(C16/C23*100,"") | D37: =IFERROR(D16/D23*100,"")
A38: Gearing, gange | B38: =IFERROR(B24/B23,"") | C38: =IFERROR(C24/C23,"") | D38: =IFERROR(D24/D23,"")
A40: Indekstal for indtjeningsevne (2022=100)
A41: Nettoomsætning | B41: =IFERROR(B5/$D5*100,"") | C41: =IFERROR(C5/$D5*100,"") | D41: =IFERROR(D5/$D5*100,"")
A42: Vareforbrug | B42: =IFERROR(B7/$D7*100,"") | C42: =IFERROR(C7/$D7*100,"") | D42: =IFERROR(D7/$D7*100,"")
A43: Andre eksterne omk. | B43: =IFERROR(B8/$D8*100,"") | C43: =IFERROR(C8/$D8*100,"") | D43: =IFERROR(D8/$D8*100,"")
A44: Personaleomkostninger | B44: =IFERROR(B10/$D10*100,"") | C44: =IFERROR(C10/$D10*100,"") | D44: =IFERROR(D10/$D10*100,"")
A45: Af- og nedskrivninger | B45: =IFERROR(B11/$D11*100,"") | C45: =IFERROR(C11/$D11*100,"") | D45: =IFERROR(D11/$D11*100,"")
A47: Indekstal for kapitaltilpasningsevne (2022=100)
A48: Nettoomsætning | B48: =IFERROR(B5*100/$D5,"") | C48: =IFERROR(C5*100/$D5,"") | D48: =IFERROR(D5*100/$D5,"")
A49: Anlægsaktiver | B49: =IFERROR(B19*100/$D19,"") | C49: =IFERROR(C19*100/$D19,"") | D49: =IFERROR(D19*100/$D19,"")
A50: Varebeholdninger | B50: =IFERROR(B28*100/$D28,"") | C50: =IFERROR(C28*100/$D28,"") | D50: =IFERROR(D28*100/$D28,"")
A51: Tilgodehavender fra salg | B51: =IFERROR(B29*100/$D29,"") | C51: =IFERROR(C29*100/$D29,"") | D51: =IFERROR(D29*100/$D29,"")
A53: Soliditet og likviditet
A54: Soliditetsgrad, % | B54: =IFERROR(B23*100/B21,"") | C54: =IFERROR(C23*100/C21,"") | D54: =IFERROR(D23*100/D21,"")
A55: Gældsandel, % | B55: =IFERROR(B24*100/B21,"") | C55: =IFERROR(C24*100/C21,"") | D55: =IFERROR(D24*100/D21,"")
A56: Likviditetsgrad, % | B56: =IFERROR(B20*100/B30,"") | C56: =IFERROR(C20*100/C30,"") | D56: =IFERROR(D20*100/D30,"")
A58: Kilde: Bearbejdet uddrag af årsrapporter for 2022-2024. Alle dataceller er live formler der peger på res_raw / balance_raw.
A60: Krydstjek mod rådata (tolerance: 1 t.kr.)
A61: Aktiver i alt = fsa:Assets | B61: =IF('balance_raw_11563392'!$F$23="","—",IF(ABS(B21-'balance_raw_11563392'!$F$23)<=1,"✓ OK","❌ "&TEXT(B21-'balance_raw_11563392'!$F$23,"+#,##0;-#,##0")&" t.kr.")) | C61: =IF('balance_raw_11563392'!$E$23="","—",IF(ABS(C21-'balance_raw_11563392'!$E$23)<=1,"✓ OK","❌ "&TEXT(C21-'balance_raw_11563392'!$E$23,"+#,##0;-#,##0")&" t.kr.")) | D61: =IF('balance_raw_11563392'!$D$23="","—",IF(ABS(D21-'balance_raw_11563392'!$D$23)<=1,"✓ OK","❌ "&TEXT(D21-'balance_raw_11563392'!$D$23,"+#,##0;-#,##0")&" t.kr.")) | F61: Verificerer at sum(Anlæg+Omsætning) matcher Assets-totalen.
A62: Passiver i alt = fsa:LiabilitiesAndEquity | B62: =IF('balance_raw_11563392'!$F$51="","—",IF(ABS(B25-'balance_raw_11563392'!$F$51)<=1,"✓ OK","❌ "&TEXT(B25-'balance_raw_11563392'!$F$51,"+#,##0;-#,##0")&" t.kr.")) | C62: =IF('balance_raw_11563392'!$E$51="","—",IF(ABS(C25-'balance_raw_11563392'!$E$51)<=1,"✓ OK","❌ "&TEXT(C25-'balance_raw_11563392'!$E$51,"+#,##0;-#,##0")&" t.kr.")) | D62: =IF('balance_raw_11563392'!$D$51="","—",IF(ABS(D25-'balance_raw_11563392'!$D$51)<=1,"✓ OK","❌ "&TEXT(D25-'balance_raw_11563392'!$D$51,"+#,##0;-#,##0")&" t.kr.")) | F62: Verificerer at sum(EK+Forpligtelser) matcher Passiver-totalen.
A63: Aktiver i alt = Passiver i alt | B63: =IF(ABS(B21-B25)<=1,"✓ OK","❌ "&TEXT(B21-B25,"+#,##0;-#,##0")&" t.kr.") | C63: =IF(ABS(C21-C25)<=1,"✓ OK","❌ "&TEXT(C21-C25,"+#,##0;-#,##0")&" t.kr.") | D63: =IF(ABS(D21-D25)<=1,"✓ OK","❌ "&TEXT(D21-D25,"+#,##0;-#,##0")&" t.kr.") | F63: Balance-identitet på arket selv. Skal altid være 0 differance.
A64: Bruttoresultat (beregnet) = fsa:GrossResult | B64: =IF('res_raw_11563392'!$F$6="","—",IF(ABS(B9-'res_raw_11563392'!$F$6)<=1,"✓ OK","❌ "&TEXT(B9-'res_raw_11563392'!$F$6,"+#,##0;-#,##0")&" t.kr.")) | C64: =IF('res_raw_11563392'!$E$6="","—",IF(ABS(C9-'res_raw_11563392'!$E$6)<=1,"✓ OK","❌ "&TEXT(C9-'res_raw_11563392'!$E$6,"+#,##0;-#,##0")&" t.kr.")) | D64: =IF('res_raw_11563392'!$D$6="","—",IF(ABS(D9-'res_raw_11563392'!$D$6)<=1,"✓ OK","❌ "&TEXT(D9-'res_raw_11563392'!$D$6,"+#,##0;-#,##0")&" t.kr.")) | F64: Hvis Nettoomsætning eller omkostninger mangler, vil sumberegnet bruttoresultat afvige.
A65: EBIT (beregnet) = fsa:ProfitLossFromOrdinaryOperatingActivities | B65: =IF('res_raw_11563392'!$F$11="","—",IF(ABS(B13-'res_raw_11563392'!$F$11)<=1,"✓ OK","❌ "&TEXT(B13-'res_raw_11563392'!$F$11,"+#,##0;-#,##0")&" t.kr.")) | C65: =IF('res_raw_11563392'!$E$11="","—",IF(ABS(C13-'res_raw_11563392'!$E$11)<=1,"✓ OK","❌ "&TEXT(C13-'res_raw_11563392'!$E$11,"+#,##0;-#,##0")&" t.kr.")) | D65: =IF('res_raw_11563392'!$D$11="","—",IF(ABS(D13-'res_raw_11563392'!$D$11)<=1,"✓ OK","❌ "&TEXT(D13-'res_raw_11563392'!$D$11,"+#,##0;-#,##0")&" t.kr.")) | F65: Verificerer at sumberegnet EBIT matcher det rapporterede.
A66: EBT (beregnet) = fsa:ProfitLossFromOrdinaryActivitiesBeforeTax | B66: =IF('res_raw_11563392'!$F$16="","—",IF(ABS(B16-'res_raw_11563392'!$F$16)<=1,"✓ OK","❌ "&TEXT(B16-'res_raw_11563392'!$F$16,"+#,##0;-#,##0")&" t.kr.")) | C66: =IF('res_raw_11563392'!$E$16="","—",IF(ABS(C16-'res_raw_11563392'!$E$16)<=1,"✓ OK","❌ "&TEXT(C16-'res_raw_11563392'!$E$16,"+#,##0;-#,##0")&" t.kr.")) | D66: =IF('res_raw_11563392'!$D$16="","—",IF(ABS(D16-'res_raw_11563392'!$D$16)<=1,"✓ OK","❌ "&TEXT(D16-'res_raw_11563392'!$D$16,"+#,##0;-#,##0")&" t.kr.")) | F66: Verificerer at sumberegnet resultat før skat matcher det rapporterede.
