Workbook

Sheet Overblik_13863385
A1: Mascot International A/S (CVR 13863385) — Regnskabsanalyse – Resultatopgørelse & Balance (t.kr.) · Klasse C-stor · Revision
H2: Indekstal (2021=100)
A3: Resultatopgørelse t.kr. | B3: 2021 | C3: 2022 | D3: 2023 | E3: 2024 | F3: 2025 | H3: 2021 | I3: 2022 | J3: 2023 | K3: 2024 | L3: 2025
A4: Nettoomsætning | B4: ='res_raw_13863385'!$B$2 | C4: ='res_raw_13863385'!$C$2 | D4: ='res_raw_13863385'!$D$2 | E4: ='res_raw_13863385'!$E$2 | F4: ='res_raw_13863385'!$F$2 | H4: =IFERROR(B4/$B$4*100,"") | I4: =IFERROR(C4/$B$4*100,"") | J4: =IFERROR(D4/$B$4*100,"") | K4: =IFERROR(E4/$B$4*100,"") | L4: =IFERROR(F4/$B$4*100,"")
A5: Produktionsomkostninger | B5: ='res_raw_13863385'!$B$3 | C5: ='res_raw_13863385'!$C$3 | D5: ='res_raw_13863385'!$D$3 | E5: ='res_raw_13863385'!$E$3 | F5: ='res_raw_13863385'!$F$3 | H5: =IFERROR(B5/$B$5*100,"") | I5: =IFERROR(C5/$B$5*100,"") | J5: =IFERROR(D5/$B$5*100,"") | K5: =IFERROR(E5/$B$5*100,"") | L5: =IFERROR(F5/$B$5*100,"")
A6: Bruttoresultat | B6: ='res_raw_13863385'!$B$4 | C6: ='res_raw_13863385'!$C$4 | D6: ='res_raw_13863385'!$D$4 | E6: ='res_raw_13863385'!$E$4 | F6: ='res_raw_13863385'!$F$4 | H6: =IFERROR(B6/$B$6*100,"") | I6: =IFERROR(C6/$B$6*100,"") | J6: =IFERROR(D6/$B$6*100,"") | K6: =IFERROR(E6/$B$6*100,"") | L6: =IFERROR(F6/$B$6*100,"")
A7: Salgs- og distributionsomkostninger | B7: ='res_raw_13863385'!$B$5 | C7: ='res_raw_13863385'!$C$5 | D7: ='res_raw_13863385'!$D$5 | E7: ='res_raw_13863385'!$E$5 | F7: ='res_raw_13863385'!$F$5 | H7: =IFERROR(B7/$B$7*100,"") | I7: =IFERROR(C7/$B$7*100,"") | J7: =IFERROR(D7/$B$7*100,"") | K7: =IFERROR(E7/$B$7*100,"") | L7: =IFERROR(F7/$B$7*100,"")
A8: Administrationsomkostninger | B8: ='res_raw_13863385'!$B$6 | C8: ='res_raw_13863385'!$C$6 | D8: ='res_raw_13863385'!$D$6 | E8: ='res_raw_13863385'!$E$6 | F8: ='res_raw_13863385'!$F$6 | H8: =IFERROR(B8/$B$8*100,"") | I8: =IFERROR(C8/$B$8*100,"") | J8: =IFERROR(D8/$B$8*100,"") | K8: =IFERROR(E8/$B$8*100,"") | L8: =IFERROR(F8/$B$8*100,"")
A9: Andre driftsindtægter | B9: ='res_raw_13863385'!$B$7 | C9: ='res_raw_13863385'!$C$7 | D9: ='res_raw_13863385'!$D$7 | E9: ='res_raw_13863385'!$E$7 | F9: ='res_raw_13863385'!$F$7 | H9: =IFERROR(B9/$B$9*100,"") | I9: =IFERROR(C9/$B$9*100,"") | J9: =IFERROR(D9/$B$9*100,"") | K9: =IFERROR(E9/$B$9*100,"") | L9: =IFERROR(F9/$B$9*100,"")
A10: Andre driftsomkostninger | B10: ='res_raw_13863385'!$B$8 | C10: ='res_raw_13863385'!$C$8 | D10: ='res_raw_13863385'!$D$8 | E10: ='res_raw_13863385'!$E$8 | F10: ='res_raw_13863385'!$F$8 | H10: =IFERROR(B10/$B$10*100,"") | I10: =IFERROR(C10/$B$10*100,"") | J10: =IFERROR(D10/$B$10*100,"") | K10: =IFERROR(E10/$B$10*100,"") | L10: =IFERROR(F10/$B$10*100,"")
A11: Resultat af primær drift | B11: ='res_raw_13863385'!$B$9 | C11: ='res_raw_13863385'!$C$9 | D11: ='res_raw_13863385'!$D$9 | E11: ='res_raw_13863385'!$E$9 | F11: ='res_raw_13863385'!$F$9 | H11: =IFERROR(B11/$B$11*100,"") | I11: =IFERROR(C11/$B$11*100,"") | J11: =IFERROR(D11/$B$11*100,"") | K11: =IFERROR(E11/$B$11*100,"") | L11: =IFERROR(F11/$B$11*100,"")
A12: Indtægter af kapitalandele, dattervirksomheder | B12: ='res_raw_13863385'!$B$10 | C12: ='res_raw_13863385'!$C$10 | D12: ='res_raw_13863385'!$D$10 | E12: ='res_raw_13863385'!$E$10 | F12: ='res_raw_13863385'!$F$10 | H12: =IFERROR(B12/$B$12*100,"") | I12: =IFERROR(C12/$B$12*100,"") | J12: =IFERROR(D12/$B$12*100,"") | K12: =IFERROR(E12/$B$12*100,"") | L12: =IFERROR(F12/$B$12*100,"")
A13: Finansielle indtægter | B13: ='res_raw_13863385'!$B$11 | C13: ='res_raw_13863385'!$C$11 | D13: ='res_raw_13863385'!$D$11 | E13: ='res_raw_13863385'!$E$11 | F13: ='res_raw_13863385'!$F$11 | H13: =IFERROR(B13/$B$13*100,"") | I13: =IFERROR(C13/$B$13*100,"") | J13: =IFERROR(D13/$B$13*100,"") | K13: =IFERROR(E13/$B$13*100,"") | L13: =IFERROR(F13/$B$13*100,"")
A14: Finansielle omkostninger | B14: ='res_raw_13863385'!$B$12 | C14: ='res_raw_13863385'!$C$12 | D14: ='res_raw_13863385'!$D$12 | E14: ='res_raw_13863385'!$E$12 | F14: ='res_raw_13863385'!$F$12 | H14: =IFERROR(B14/$B$14*100,"") | I14: =IFERROR(C14/$B$14*100,"") | J14: =IFERROR(D14/$B$14*100,"") | K14: =IFERROR(E14/$B$14*100,"") | L14: =IFERROR(F14/$B$14*100,"")
A15: Finansielle poster, netto | B15: ='res_raw_13863385'!$B$13 | C15: ='res_raw_13863385'!$C$13 | D15: ='res_raw_13863385'!$D$13 | E15: ='res_raw_13863385'!$E$13 | F15: ='res_raw_13863385'!$F$13 | H15: =IFERROR(B15/$B$15*100,"") | I15: =IFERROR(C15/$B$15*100,"") | J15: =IFERROR(D15/$B$15*100,"") | K15: =IFERROR(E15/$B$15*100,"") | L15: =IFERROR(F15/$B$15*100,"")
A16: Resultat før skat | B16: ='res_raw_13863385'!$B$14 | C16: ='res_raw_13863385'!$C$14 | D16: ='res_raw_13863385'!$D$14 | E16: ='res_raw_13863385'!$E$14 | F16: ='res_raw_13863385'!$F$14 | H16: =IFERROR(B16/$B$16*100,"") | I16: =IFERROR(C16/$B$16*100,"") | J16: =IFERROR(D16/$B$16*100,"") | K16: =IFERROR(E16/$B$16*100,"") | L16: =IFERROR(F16/$B$16*100,"")
A17: Skat af årets resultat | B17: ='res_raw_13863385'!$B$15 | C17: ='res_raw_13863385'!$C$15 | D17: ='res_raw_13863385'!$D$15 | E17: ='res_raw_13863385'!$E$15 | F17: ='res_raw_13863385'!$F$15 | H17: =IFERROR(B17/$B$17*100,"") | I17: =IFERROR(C17/$B$17*100,"") | J17: =IFERROR(D17/$B$17*100,"") | K17: =IFERROR(E17/$B$17*100,"") | L17: =IFERROR(F17/$B$17*100,"")
A18: Årets resultat | B18: ='res_raw_13863385'!$B$16 | C18: ='res_raw_13863385'!$C$16 | D18: ='res_raw_13863385'!$D$16 | E18: ='res_raw_13863385'!$E$16 | F18: ='res_raw_13863385'!$F$16 | H18: =IFERROR(B18/$B$18*100,"") | I18: =IFERROR(C18/$B$18*100,"") | J18: =IFERROR(D18/$B$18*100,"") | K18: =IFERROR(E18/$B$18*100,"") | L18: =IFERROR(F18/$B$18*100,"")
A20: AKTIVER t.kr. | B20: 2021 | C20: 2022 | D20: 2023 | E20: 2024 | F20: 2025 | H20: 2021 | I20: 2022 | J20: 2023 | K20: 2024 | L20: 2025
A21: Grunde og bygninger | B21: ='balance_raw_13863385'!$B$2 | C21: ='balance_raw_13863385'!$C$2 | D21: ='balance_raw_13863385'!$D$2 | E21: ='balance_raw_13863385'!$E$2 | F21: ='balance_raw_13863385'!$F$2 | H21: =IFERROR(B21/$B$21*100,"") | I21: =IFERROR(C21/$B$21*100,"") | J21: =IFERROR(D21/$B$21*100,"") | K21: =IFERROR(E21/$B$21*100,"") | L21: =IFERROR(F21/$B$21*100,"")
A22: Produktionsanlæg og maskiner | B22: ='balance_raw_13863385'!$B$3 | C22: ='balance_raw_13863385'!$C$3 | D22: ='balance_raw_13863385'!$D$3 | E22: ='balance_raw_13863385'!$E$3 | F22: ='balance_raw_13863385'!$F$3 | H22: =IFERROR(B22/$B$22*100,"") | I22: =IFERROR(C22/$B$22*100,"") | J22: =IFERROR(D22/$B$22*100,"") | K22: =IFERROR(E22/$B$22*100,"") | L22: =IFERROR(F22/$B$22*100,"")
A23: Driftsmateriel og inventar | B23: ='balance_raw_13863385'!$B$4 | C23: ='balance_raw_13863385'!$C$4 | D23: ='balance_raw_13863385'!$D$4 | E23: ='balance_raw_13863385'!$E$4 | F23: ='balance_raw_13863385'!$F$4 | H23: =IFERROR(B23/$B$23*100,"") | I23: =IFERROR(C23/$B$23*100,"") | J23: =IFERROR(D23/$B$23*100,"") | K23: =IFERROR(E23/$B$23*100,"") | L23: =IFERROR(F23/$B$23*100,"")
A24: Indretning af lejede lokaler | B24: ='balance_raw_13863385'!$B$5 | C24: ='balance_raw_13863385'!$C$5 | D24: ='balance_raw_13863385'!$D$5 | E24: ='balance_raw_13863385'!$E$5 | F24: ='balance_raw_13863385'!$F$5 | H24: =IFERROR(B24/$B$24*100,"") | I24: =IFERROR(C24/$B$24*100,"") | J24: =IFERROR(D24/$B$24*100,"") | K24: =IFERROR(E24/$B$24*100,"") | L24: =IFERROR(F24/$B$24*100,"")
A25: Forudbetaling og anlægsaktiver under opførelse | B25: ='balance_raw_13863385'!$B$6 | C25: ='balance_raw_13863385'!$C$6 | D25: ='balance_raw_13863385'!$D$6 | E25: ='balance_raw_13863385'!$E$6 | F25: ='balance_raw_13863385'!$F$6 | H25: =IFERROR(B25/$B$25*100,"") | I25: =IFERROR(C25/$B$25*100,"") | J25: =IFERROR(D25/$B$25*100,"") | K25: =IFERROR(E25/$B$25*100,"") | L25: =IFERROR(F25/$B$25*100,"")
A26: Materielle anlægsaktiver | B26: ='balance_raw_13863385'!$B$7 | C26: ='balance_raw_13863385'!$C$7 | D26: ='balance_raw_13863385'!$D$7 | E26: ='balance_raw_13863385'!$E$7 | F26: ='balance_raw_13863385'!$F$7 | H26: =IFERROR(B26/$B$26*100,"") | I26: =IFERROR(C26/$B$26*100,"") | J26: =IFERROR(D26/$B$26*100,"") | K26: =IFERROR(E26/$B$26*100,"") | L26: =IFERROR(F26/$B$26*100,"")
A27: Kapitalandele, dattervirksomheder | B27: ='balance_raw_13863385'!$B$8 | C27: ='balance_raw_13863385'!$C$8 | D27: ='balance_raw_13863385'!$D$8 | E27: ='balance_raw_13863385'!$E$8 | F27: ='balance_raw_13863385'!$F$8 | H27: =IFERROR(B27/$B$27*100,"") | I27: =IFERROR(C27/$B$27*100,"") | J27: =IFERROR(D27/$B$27*100,"") | K27: =IFERROR(E27/$B$27*100,"") | L27: =IFERROR(F27/$B$27*100,"")
A28: Deposita | B28: ='balance_raw_13863385'!$B$9 | C28: ='balance_raw_13863385'!$C$9 | D28: ='balance_raw_13863385'!$D$9 | E28: ='balance_raw_13863385'!$E$9 | F28: ='balance_raw_13863385'!$F$9 | H28: =IFERROR(B28/$B$28*100,"") | I28: =IFERROR(C28/$B$28*100,"") | J28: =IFERROR(D28/$B$28*100,"") | K28: =IFERROR(E28/$B$28*100,"") | L28: =IFERROR(F28/$B$28*100,"")
A29: Finansielle anlægsaktiver | B29: ='balance_raw_13863385'!$B$10 | C29: ='balance_raw_13863385'!$C$10 | D29: ='balance_raw_13863385'!$D$10 | E29: ='balance_raw_13863385'!$E$10 | F29: ='balance_raw_13863385'!$F$10 | H29: =IFERROR(B29/$B$29*100,"") | I29: =IFERROR(C29/$B$29*100,"") | J29: =IFERROR(D29/$B$29*100,"") | K29: =IFERROR(E29/$B$29*100,"") | L29: =IFERROR(F29/$B$29*100,"")
A30: Anlægsaktiver | B30: ='balance_raw_13863385'!$B$11 | C30: ='balance_raw_13863385'!$C$11 | D30: ='balance_raw_13863385'!$D$11 | E30: ='balance_raw_13863385'!$E$11 | F30: ='balance_raw_13863385'!$F$11 | H30: =IFERROR(B30/$B$30*100,"") | I30: =IFERROR(C30/$B$30*100,"") | J30: =IFERROR(D30/$B$30*100,"") | K30: =IFERROR(E30/$B$30*100,"") | L30: =IFERROR(F30/$B$30*100,"")
A31: Råvarer og hjælpematerialer | B31: ='balance_raw_13863385'!$B$12 | C31: ='balance_raw_13863385'!$C$12 | D31: ='balance_raw_13863385'!$D$12 | E31: ='balance_raw_13863385'!$E$12 | F31: ='balance_raw_13863385'!$F$12 | H31: =IFERROR(B31/$B$31*100,"") | I31: =IFERROR(C31/$B$31*100,"") | J31: =IFERROR(D31/$B$31*100,"") | K31: =IFERROR(E31/$B$31*100,"") | L31: =IFERROR(F31/$B$31*100,"")
A32: Varer under fremstilling | B32: ='balance_raw_13863385'!$B$13 | C32: ='balance_raw_13863385'!$C$13 | D32: ='balance_raw_13863385'!$D$13 | E32: ='balance_raw_13863385'!$E$13 | F32: ='balance_raw_13863385'!$F$13 | H32: =IFERROR(B32/$B$32*100,"") | I32: =IFERROR(C32/$B$32*100,"") | J32: =IFERROR(D32/$B$32*100,"") | K32: =IFERROR(E32/$B$32*100,"") | L32: =IFERROR(F32/$B$32*100,"")
A33: Færdigvarer og handelsvarer | B33: ='balance_raw_13863385'!$B$14 | C33: ='balance_raw_13863385'!$C$14 | D33: ='balance_raw_13863385'!$D$14 | E33: ='balance_raw_13863385'!$E$14 | F33: ='balance_raw_13863385'!$F$14 | H33: =IFERROR(B33/$B$33*100,"") | I33: =IFERROR(C33/$B$33*100,"") | J33: =IFERROR(D33/$B$33*100,"") | K33: =IFERROR(E33/$B$33*100,"") | L33: =IFERROR(F33/$B$33*100,"")
A34: Varebeholdninger | B34: ='balance_raw_13863385'!$B$15 | C34: ='balance_raw_13863385'!$C$15 | D34: ='balance_raw_13863385'!$D$15 | E34: ='balance_raw_13863385'!$E$15 | F34: ='balance_raw_13863385'!$F$15 | H34: =IFERROR(B34/$B$34*100,"") | I34: =IFERROR(C34/$B$34*100,"") | J34: =IFERROR(D34/$B$34*100,"") | K34: =IFERROR(E34/$B$34*100,"") | L34: =IFERROR(F34/$B$34*100,"")
A35: Tilgodehavender fra salg og tjenesteydelser | B35: ='balance_raw_13863385'!$B$16 | C35: ='balance_raw_13863385'!$C$16 | D35: ='balance_raw_13863385'!$D$16 | E35: ='balance_raw_13863385'!$E$16 | F35: ='balance_raw_13863385'!$F$16 | H35: =IFERROR(B35/$B$35*100,"") | I35: =IFERROR(C35/$B$35*100,"") | J35: =IFERROR(D35/$B$35*100,"") | K35: =IFERROR(E35/$B$35*100,"") | L35: =IFERROR(F35/$B$35*100,"")
A36: Tilgodehavender hos tilknyttede virksomheder | B36: ='balance_raw_13863385'!$B$17 | C36: ='balance_raw_13863385'!$C$17 | D36: ='balance_raw_13863385'!$D$17 | E36: ='balance_raw_13863385'!$E$17 | F36: ='balance_raw_13863385'!$F$17 | H36: =IFERROR(B36/$B$36*100,"") | I36: =IFERROR(C36/$B$36*100,"") | J36: =IFERROR(D36/$B$36*100,"") | K36: =IFERROR(E36/$B$36*100,"") | L36: =IFERROR(F36/$B$36*100,"")
A37: Andre tilgodehavender | B37: ='balance_raw_13863385'!$B$18 | C37: ='balance_raw_13863385'!$C$18 | D37: ='balance_raw_13863385'!$D$18 | E37: ='balance_raw_13863385'!$E$18 | F37: ='balance_raw_13863385'!$F$18 | H37: =IFERROR(B37/$B$37*100,"") | I37: =IFERROR(C37/$B$37*100,"") | J37: =IFERROR(D37/$B$37*100,"") | K37: =IFERROR(E37/$B$37*100,"") | L37: =IFERROR(F37/$B$37*100,"")
A38: Periodeafgrænsningsposter (aktiver) | B38: ='balance_raw_13863385'!$B$19 | C38: ='balance_raw_13863385'!$C$19 | D38: ='balance_raw_13863385'!$D$19 | E38: ='balance_raw_13863385'!$E$19 | F38: ='balance_raw_13863385'!$F$19 | H38: =IFERROR(B38/$B$38*100,"") | I38: =IFERROR(C38/$B$38*100,"") | J38: =IFERROR(D38/$B$38*100,"") | K38: =IFERROR(E38/$B$38*100,"") | L38: =IFERROR(F38/$B$38*100,"")
A39: Udskudt skatteaktiv | B39: ='balance_raw_13863385'!$B$20 | C39: ='balance_raw_13863385'!$C$20 | D39: ='balance_raw_13863385'!$D$20 | E39: ='balance_raw_13863385'!$E$20 | F39: ='balance_raw_13863385'!$F$20 | H39: =IFERROR(B39/$B$39*100,"") | I39: =IFERROR(C39/$B$39*100,"") | J39: =IFERROR(D39/$B$39*100,"") | K39: =IFERROR(E39/$B$39*100,"") | L39: =IFERROR(F39/$B$39*100,"")
A40: Tilgodehavende skat hos tilknyttede virksomheder | B40: ='balance_raw_13863385'!$B$21 | C40: ='balance_raw_13863385'!$C$21 | D40: ='balance_raw_13863385'!$D$21 | E40: ='balance_raw_13863385'!$E$21 | F40: ='balance_raw_13863385'!$F$21 | H40: =IFERROR(B40/$B$40*100,"") | I40: =IFERROR(C40/$B$40*100,"") | J40: =IFERROR(D40/$B$40*100,"") | K40: =IFERROR(E40/$B$40*100,"") | L40: =IFERROR(F40/$B$40*100,"")
A41: Kortfristede skattetilgodehavender | B41: ='balance_raw_13863385'!$B$22 | C41: ='balance_raw_13863385'!$C$22 | D41: ='balance_raw_13863385'!$D$22 | E41: ='balance_raw_13863385'!$E$22 | F41: ='balance_raw_13863385'!$F$22 | H41: =IFERROR(B41/$B$41*100,"") | I41: =IFERROR(C41/$B$41*100,"") | J41: =IFERROR(D41/$B$41*100,"") | K41: =IFERROR(E41/$B$41*100,"") | L41: =IFERROR(F41/$B$41*100,"")
A42: Tilgodehavender | B42: ='balance_raw_13863385'!$B$23 | C42: ='balance_raw_13863385'!$C$23 | D42: ='balance_raw_13863385'!$D$23 | E42: ='balance_raw_13863385'!$E$23 | F42: ='balance_raw_13863385'!$F$23 | H42: =IFERROR(B42/$B$42*100,"") | I42: =IFERROR(C42/$B$42*100,"") | J42: =IFERROR(D42/$B$42*100,"") | K42: =IFERROR(E42/$B$42*100,"") | L42: =IFERROR(F42/$B$42*100,"")
A43: Værdipapirer | B43: ='balance_raw_13863385'!$B$24 | C43: ='balance_raw_13863385'!$C$24 | D43: ='balance_raw_13863385'!$D$24 | E43: ='balance_raw_13863385'!$E$24 | F43: ='balance_raw_13863385'!$F$24 | H43: =IFERROR(B43/$B$43*100,"") | I43: =IFERROR(C43/$B$43*100,"") | J43: =IFERROR(D43/$B$43*100,"") | K43: =IFERROR(E43/$B$43*100,"") | L43: =IFERROR(F43/$B$43*100,"")
A44: Likvide beholdninger | B44: ='balance_raw_13863385'!$B$25 | C44: ='balance_raw_13863385'!$C$25 | D44: ='balance_raw_13863385'!$D$25 | E44: ='balance_raw_13863385'!$E$25 | F44: ='balance_raw_13863385'!$F$25 | H44: =IFERROR(B44/$B$44*100,"") | I44: =IFERROR(C44/$B$44*100,"") | J44: =IFERROR(D44/$B$44*100,"") | K44: =IFERROR(E44/$B$44*100,"") | L44: =IFERROR(F44/$B$44*100,"")
A45: Omsætningsaktiver | B45: ='balance_raw_13863385'!$B$26 | C45: ='balance_raw_13863385'!$C$26 | D45: ='balance_raw_13863385'!$D$26 | E45: ='balance_raw_13863385'!$E$26 | F45: ='balance_raw_13863385'!$F$26 | H45: =IFERROR(B45/$B$45*100,"") | I45: =IFERROR(C45/$B$45*100,"") | J45: =IFERROR(D45/$B$45*100,"") | K45: =IFERROR(E45/$B$45*100,"") | L45: =IFERROR(F45/$B$45*100,"")
A46: Aktiver | B46: ='balance_raw_13863385'!$B$27 | C46: ='balance_raw_13863385'!$C$27 | D46: ='balance_raw_13863385'!$D$27 | E46: ='balance_raw_13863385'!$E$27 | F46: ='balance_raw_13863385'!$F$27 | H46: =IFERROR(B46/$B$46*100,"") | I46: =IFERROR(C46/$B$46*100,"") | J46: =IFERROR(D46/$B$46*100,"") | K46: =IFERROR(E46/$B$46*100,"") | L46: =IFERROR(F46/$B$46*100,"")
A48: PASSIVER t.kr. | B48: 2021 | C48: 2022 | D48: 2023 | E48: 2024 | F48: 2025 | H48: 2021 | I48: 2022 | J48: 2023 | K48: 2024 | L48: 2025
A49: Selskabskapital | B49: ='balance_raw_13863385'!$B$28 | C49: ='balance_raw_13863385'!$C$28 | D49: ='balance_raw_13863385'!$D$28 | E49: ='balance_raw_13863385'!$E$28 | F49: ='balance_raw_13863385'!$F$28 | H49: =IFERROR(B49/$B$49*100,"") | I49: =IFERROR(C49/$B$49*100,"") | J49: =IFERROR(D49/$B$49*100,"") | K49: =IFERROR(E49/$B$49*100,"") | L49: =IFERROR(F49/$B$49*100,"")
A50: Reserve for nettoopskrivning (indre værdis metode) | B50: ='balance_raw_13863385'!$B$29 | C50: ='balance_raw_13863385'!$C$29 | D50: ='balance_raw_13863385'!$D$29 | E50: ='balance_raw_13863385'!$E$29 | F50: ='balance_raw_13863385'!$F$29 | H50: =IFERROR(B50/$B$50*100,"") | I50: =IFERROR(C50/$B$50*100,"") | J50: =IFERROR(D50/$B$50*100,"") | K50: =IFERROR(E50/$B$50*100,"") | L50: =IFERROR(F50/$B$50*100,"")
A51: Reserve for udviklingsomkostninger | B51: ='balance_raw_13863385'!$B$30 | C51: ='balance_raw_13863385'!$C$30 | D51: ='balance_raw_13863385'!$D$30 | E51: ='balance_raw_13863385'!$E$30 | F51: ='balance_raw_13863385'!$F$30 | H51: =IFERROR(B51/$B$51*100,"") | I51: =IFERROR(C51/$B$51*100,"") | J51: =IFERROR(D51/$B$51*100,"") | K51: =IFERROR(E51/$B$51*100,"") | L51: =IFERROR(F51/$B$51*100,"")
A52: Reserve for sikringstransaktioner | B52: ='balance_raw_13863385'!$B$31 | C52: ='balance_raw_13863385'!$C$31 | D52: ='balance_raw_13863385'!$D$31 | E52: ='balance_raw_13863385'!$E$31 | F52: ='balance_raw_13863385'!$F$31 | H52: =IFERROR(B52/$B$52*100,"") | I52: =IFERROR(C52/$B$52*100,"") | J52: =IFERROR(D52/$B$52*100,"") | K52: =IFERROR(E52/$B$52*100,"") | L52: =IFERROR(F52/$B$52*100,"")
A53: Andre reserver | B53: ='balance_raw_13863385'!$B$32 | C53: ='balance_raw_13863385'!$C$32 | D53: ='balance_raw_13863385'!$D$32 | E53: ='balance_raw_13863385'!$E$32 | F53: ='balance_raw_13863385'!$F$32 | H53: =IFERROR(B53/$B$53*100,"") | I53: =IFERROR(C53/$B$53*100,"") | J53: =IFERROR(D53/$B$53*100,"") | K53: =IFERROR(E53/$B$53*100,"") | L53: =IFERROR(F53/$B$53*100,"")
A54: Overført resultat | B54: ='balance_raw_13863385'!$B$33 | C54: ='balance_raw_13863385'!$C$33 | D54: ='balance_raw_13863385'!$D$33 | E54: ='balance_raw_13863385'!$E$33 | F54: ='balance_raw_13863385'!$F$33 | H54: =IFERROR(B54/$B$54*100,"") | I54: =IFERROR(C54/$B$54*100,"") | J54: =IFERROR(D54/$B$54*100,"") | K54: =IFERROR(E54/$B$54*100,"") | L54: =IFERROR(F54/$B$54*100,"")
A55: Egenkapital i alt | B55: ='balance_raw_13863385'!$B$34 | C55: ='balance_raw_13863385'!$C$34 | D55: ='balance_raw_13863385'!$D$34 | E55: ='balance_raw_13863385'!$E$34 | F55: ='balance_raw_13863385'!$F$34 | H55: =IFERROR(B55/$B$55*100,"") | I55: =IFERROR(C55/$B$55*100,"") | J55: =IFERROR(D55/$B$55*100,"") | K55: =IFERROR(E55/$B$55*100,"") | L55: =IFERROR(F55/$B$55*100,"")
A56: Hensættelse til udskudt skat | B56: ='balance_raw_13863385'!$B$35 | C56: ='balance_raw_13863385'!$C$35 | D56: ='balance_raw_13863385'!$D$35 | E56: ='balance_raw_13863385'!$E$35 | F56: ='balance_raw_13863385'!$F$35 | H56: =IFERROR(B56/$B$56*100,"") | I56: =IFERROR(C56/$B$56*100,"") | J56: =IFERROR(D56/$B$56*100,"") | K56: =IFERROR(E56/$B$56*100,"") | L56: =IFERROR(F56/$B$56*100,"")
A57: Hensatte forpligtelser | B57: ='balance_raw_13863385'!$B$36 | C57: ='balance_raw_13863385'!$C$36 | D57: ='balance_raw_13863385'!$D$36 | E57: ='balance_raw_13863385'!$E$36 | F57: ='balance_raw_13863385'!$F$36 | H57: =IFERROR(B57/$B$57*100,"") | I57: =IFERROR(C57/$B$57*100,"") | J57: =IFERROR(D57/$B$57*100,"") | K57: =IFERROR(E57/$B$57*100,"") | L57: =IFERROR(F57/$B$57*100,"")
A58: Ansvarlig lånekapital (langfristet) | B58: ='balance_raw_13863385'!$B$37 | C58: ='balance_raw_13863385'!$C$37 | D58: ='balance_raw_13863385'!$D$37 | E58: ='balance_raw_13863385'!$E$37 | F58: ='balance_raw_13863385'!$F$37 | H58: =IFERROR(B58/$B$58*100,"") | I58: =IFERROR(C58/$B$58*100,"") | J58: =IFERROR(D58/$B$58*100,"") | K58: =IFERROR(E58/$B$58*100,"") | L58: =IFERROR(F58/$B$58*100,"")
A59: Langfristede lån | B59: ='balance_raw_13863385'!$B$38 | C59: ='balance_raw_13863385'!$C$38 | D59: ='balance_raw_13863385'!$D$38 | E59: ='balance_raw_13863385'!$E$38 | F59: ='balance_raw_13863385'!$F$38 | H59: =IFERROR(B59/$B$59*100,"") | I59: =IFERROR(C59/$B$59*100,"") | J59: =IFERROR(D59/$B$59*100,"") | K59: =IFERROR(E59/$B$59*100,"") | L59: =IFERROR(F59/$B$59*100,"")
A60: Leasingforpligtelser (langfristet) | B60: ='balance_raw_13863385'!$B$39 | C60: ='balance_raw_13863385'!$C$39 | D60: ='balance_raw_13863385'!$D$39 | E60: ='balance_raw_13863385'!$E$39 | F60: ='balance_raw_13863385'!$F$39 | H60: =IFERROR(B60/$B$60*100,"") | I60: =IFERROR(C60/$B$60*100,"") | J60: =IFERROR(D60/$B$60*100,"") | K60: =IFERROR(E60/$B$60*100,"") | L60: =IFERROR(F60/$B$60*100,"")
A61: Anden gæld (langfristet) | B61: ='balance_raw_13863385'!$B$40 | C61: ='balance_raw_13863385'!$C$40 | D61: ='balance_raw_13863385'!$D$40 | E61: ='balance_raw_13863385'!$E$40 | F61: ='balance_raw_13863385'!$F$40 | H61: =IFERROR(B61/$B$61*100,"") | I61: =IFERROR(C61/$B$61*100,"") | J61: =IFERROR(D61/$B$61*100,"") | K61: =IFERROR(E61/$B$61*100,"") | L61: =IFERROR(F61/$B$61*100,"")
A62: Langfristede gældsforpligtelser | B62: ='balance_raw_13863385'!$B$41 | C62: ='balance_raw_13863385'!$C$41 | D62: ='balance_raw_13863385'!$D$41 | E62: ='balance_raw_13863385'!$E$41 | F62: ='balance_raw_13863385'!$F$41 | H62: =IFERROR(B62/$B$62*100,"") | I62: =IFERROR(C62/$B$62*100,"") | J62: =IFERROR(D62/$B$62*100,"") | K62: =IFERROR(E62/$B$62*100,"") | L62: =IFERROR(F62/$B$62*100,"")
A63: Ansvarlig lånekapital (kortfristet) | B63: ='balance_raw_13863385'!$B$42 | C63: ='balance_raw_13863385'!$C$42 | D63: ='balance_raw_13863385'!$D$42 | E63: ='balance_raw_13863385'!$E$42 | F63: ='balance_raw_13863385'!$F$42 | H63: =IFERROR(B63/$B$63*100,"") | I63: =IFERROR(C63/$B$63*100,"") | J63: =IFERROR(D63/$B$63*100,"") | K63: =IFERROR(E63/$B$63*100,"") | L63: =IFERROR(F63/$B$63*100,"")
A64: Kortfristet del af langfristede gældsforpligtelser | B64: ='balance_raw_13863385'!$B$43 | C64: ='balance_raw_13863385'!$C$43 | D64: ='balance_raw_13863385'!$D$43 | E64: ='balance_raw_13863385'!$E$43 | F64: ='balance_raw_13863385'!$F$43 | H64: =IFERROR(B64/$B$64*100,"") | I64: =IFERROR(C64/$B$64*100,"") | J64: =IFERROR(D64/$B$64*100,"") | K64: =IFERROR(E64/$B$64*100,"") | L64: =IFERROR(F64/$B$64*100,"")
A65: Kreditinstitutter | B65: ='balance_raw_13863385'!$B$44 | C65: ='balance_raw_13863385'!$C$44 | D65: ='balance_raw_13863385'!$D$44 | E65: ='balance_raw_13863385'!$E$44 | F65: ='balance_raw_13863385'!$F$44 | H65: =IFERROR(B65/$B$65*100,"") | I65: =IFERROR(C65/$B$65*100,"") | J65: =IFERROR(D65/$B$65*100,"") | K65: =IFERROR(E65/$B$65*100,"") | L65: =IFERROR(F65/$B$65*100,"")
A66: Leasingforpligtelser (kortfristet) | B66: ='balance_raw_13863385'!$B$45 | C66: ='balance_raw_13863385'!$C$45 | D66: ='balance_raw_13863385'!$D$45 | E66: ='balance_raw_13863385'!$E$45 | F66: ='balance_raw_13863385'!$F$45 | H66: =IFERROR(B66/$B$66*100,"") | I66: =IFERROR(C66/$B$66*100,"") | J66: =IFERROR(D66/$B$66*100,"") | K66: =IFERROR(E66/$B$66*100,"") | L66: =IFERROR(F66/$B$66*100,"")
A67: Leverandører af varer og tjenesteydelser | B67: ='balance_raw_13863385'!$B$46 | C67: ='balance_raw_13863385'!$C$46 | D67: ='balance_raw_13863385'!$D$46 | E67: ='balance_raw_13863385'!$E$46 | F67: ='balance_raw_13863385'!$F$46 | H67: =IFERROR(B67/$B$67*100,"") | I67: =IFERROR(C67/$B$67*100,"") | J67: =IFERROR(D67/$B$67*100,"") | K67: =IFERROR(E67/$B$67*100,"") | L67: =IFERROR(F67/$B$67*100,"")
A68: Gæld til tilknyttede virksomheder | B68: ='balance_raw_13863385'!$B$47 | C68: ='balance_raw_13863385'!$C$47 | D68: ='balance_raw_13863385'!$D$47 | E68: ='balance_raw_13863385'!$E$47 | F68: ='balance_raw_13863385'!$F$47 | H68: =IFERROR(B68/$B$68*100,"") | I68: =IFERROR(C68/$B$68*100,"") | J68: =IFERROR(D68/$B$68*100,"") | K68: =IFERROR(E68/$B$68*100,"") | L68: =IFERROR(F68/$B$68*100,"")
A69: Gæld til selskabsdeltagere og ledelse | B69: ='balance_raw_13863385'!$B$48 | C69: ='balance_raw_13863385'!$C$48 | D69: ='balance_raw_13863385'!$D$48 | E69: ='balance_raw_13863385'!$E$48 | F69: ='balance_raw_13863385'!$F$48 | H69: =IFERROR(B69/$B$69*100,"") | I69: =IFERROR(C69/$B$69*100,"") | J69: =IFERROR(D69/$B$69*100,"") | K69: =IFERROR(E69/$B$69*100,"") | L69: =IFERROR(F69/$B$69*100,"")
A70: Selskabsskat | B70: ='balance_raw_13863385'!$B$49 | C70: ='balance_raw_13863385'!$C$49 | D70: ='balance_raw_13863385'!$D$49 | E70: ='balance_raw_13863385'!$E$49 | F70: ='balance_raw_13863385'!$F$49 | H70: =IFERROR(B70/$B$70*100,"") | I70: =IFERROR(C70/$B$70*100,"") | J70: =IFERROR(D70/$B$70*100,"") | K70: =IFERROR(E70/$B$70*100,"") | L70: =IFERROR(F70/$B$70*100,"")
A71: Gæld til tilknyttede virksomheder vedr. selskabsskat | B71: ='balance_raw_13863385'!$B$50 | C71: ='balance_raw_13863385'!$C$50 | D71: ='balance_raw_13863385'!$D$50 | E71: ='balance_raw_13863385'!$E$50 | F71: ='balance_raw_13863385'!$F$50 | H71: =IFERROR(B71/$B$71*100,"") | I71: =IFERROR(C71/$B$71*100,"") | J71: =IFERROR(D71/$B$71*100,"") | K71: =IFERROR(E71/$B$71*100,"") | L71: =IFERROR(F71/$B$71*100,"")
A72: Anden gæld (kortfristet) | B72: ='balance_raw_13863385'!$B$51 | C72: ='balance_raw_13863385'!$C$51 | D72: ='balance_raw_13863385'!$D$51 | E72: ='balance_raw_13863385'!$E$51 | F72: ='balance_raw_13863385'!$F$51 | H72: =IFERROR(B72/$B$72*100,"") | I72: =IFERROR(C72/$B$72*100,"") | J72: =IFERROR(D72/$B$72*100,"") | K72: =IFERROR(E72/$B$72*100,"") | L72: =IFERROR(F72/$B$72*100,"")
A73: Periodeafgrænsningsposter (passiver) | B73: ='balance_raw_13863385'!$B$52 | C73: ='balance_raw_13863385'!$C$52 | D73: ='balance_raw_13863385'!$D$52 | E73: ='balance_raw_13863385'!$E$52 | F73: ='balance_raw_13863385'!$F$52 | H73: =IFERROR(B73/$B$73*100,"") | I73: =IFERROR(C73/$B$73*100,"") | J73: =IFERROR(D73/$B$73*100,"") | K73: =IFERROR(E73/$B$73*100,"") | L73: =IFERROR(F73/$B$73*100,"")
A74: Kortfristede gældsforpligtelser | B74: ='balance_raw_13863385'!$B$53 | C74: ='balance_raw_13863385'!$C$53 | D74: ='balance_raw_13863385'!$D$53 | E74: ='balance_raw_13863385'!$E$53 | F74: ='balance_raw_13863385'!$F$53 | H74: =IFERROR(B74/$B$74*100,"") | I74: =IFERROR(C74/$B$74*100,"") | J74: =IFERROR(D74/$B$74*100,"") | K74: =IFERROR(E74/$B$74*100,"") | L74: =IFERROR(F74/$B$74*100,"")
A75: Gældsforpligtelser | B75: ='balance_raw_13863385'!$B$54 | C75: ='balance_raw_13863385'!$C$54 | D75: ='balance_raw_13863385'!$D$54 | E75: ='balance_raw_13863385'!$E$54 | F75: ='balance_raw_13863385'!$F$54 | H75: =IFERROR(B75/$B$75*100,"") | I75: =IFERROR(C75/$B$75*100,"") | J75: =IFERROR(D75/$B$75*100,"") | K75: =IFERROR(E75/$B$75*100,"") | L75: =IFERROR(F75/$B$75*100,"")
A76: Passiver | B76: ='balance_raw_13863385'!$B$55 | C76: ='balance_raw_13863385'!$C$55 | D76: ='balance_raw_13863385'!$D$55 | E76: ='balance_raw_13863385'!$E$55 | F76: ='balance_raw_13863385'!$F$55 | H76: =IFERROR(B76/$B$76*100,"") | I76: =IFERROR(C76/$B$76*100,"") | J76: =IFERROR(D76/$B$76*100,"") | K76: =IFERROR(E76/$B$76*100,"") | L76: =IFERROR(F76/$B$76*100,"")
A78: NØGLEOPLYSNINGER | B78: 2021 | C78: 2022 | D78: 2023 | E78: 2024 | F78: 2025
A79: Gns. antal medarbejdere | B79: ='res_raw_13863385'!$B$17 | C79: ='res_raw_13863385'!$C$17 | D79: ='res_raw_13863385'!$D$17 | E79: ='res_raw_13863385'!$E$17 | F79: ='res_raw_13863385'!$F$17 | H79: =IFERROR(B79/$B$79*100,"") | I79: =IFERROR(C79/$B$79*100,"") | J79: =IFERROR(D79/$B$79*100,"") | K79: =IFERROR(E79/$B$79*100,"") | L79: =IFERROR(F79/$B$79*100,"")
A80: Investering i materielle anlægsaktiver | B80: ='res_raw_13863385'!$B$18 | C80: ='res_raw_13863385'!$C$18 | D80: ='res_raw_13863385'!$D$18 | E80: ='res_raw_13863385'!$E$18 | F80: ='res_raw_13863385'!$F$18 | H80: =IFERROR(B80/$B$80*100,"") | I80: =IFERROR(C80/$B$80*100,"") | J80: =IFERROR(D80/$B$80*100,"") | K80: =IFERROR(E80/$B$80*100,"") | L80: =IFERROR(F80/$B$80*100,"")
A82: NØGLETAL | B82: 2021 | C82: 2022 | D82: 2023 | E82: 2024 | F82: 2025
A83: Afkastningsgrad, % | B83: =IFERROR(($B$11+$B$13+$B$12)/$B$46*100,"") | C83: =IFERROR(($C$11+$C$13+$C$12)/$C$46*100,"") | D83: =IFERROR(($D$11+$D$13+$D$12)/$D$46*100,"") | E83: =IFERROR(($E$11+$E$13+$E$12)/$E$46*100,"") | F83: =IFERROR(($F$11+$F$13+$F$12)/$F$46*100,"")
A84: Overskudsgrad, % | B84: =IFERROR(($B$11+$B$13+$B$12)/$B$4*100,"") | C84: =IFERROR(($C$11+$C$13+$C$12)/$C$4*100,"") | D84: =IFERROR(($D$11+$D$13+$D$12)/$D$4*100,"") | E84: =IFERROR(($E$11+$E$13+$E$12)/$E$4*100,"") | F84: =IFERROR(($F$11+$F$13+$F$12)/$F$4*100,"")
A85: Aktivernes omsætningshastighed, gange | B85: =IFERROR($B$4/$B$46,"") | C85: =IFERROR($C$4/$C$46,"") | D85: =IFERROR($D$4/$D$46,"") | E85: =IFERROR($E$4/$E$46,"") | F85: =IFERROR($F$4/$F$46,"")
A86: Egenkapitalens forrentning, % | B86: =IFERROR($B$16/$B$55*100,"") | C86: =IFERROR($C$16/$C$55*100,"") | D86: =IFERROR($D$16/$D$55*100,"") | E86: =IFERROR($E$16/$E$55*100,"") | F86: =IFERROR($F$16/$F$55*100,"")
A87: Gældsrente, % | B87: =IFERROR($B$14/($B$76-$B$55)*100,"") | C87: =IFERROR($C$14/($C$76-$C$55)*100,"") | D87: =IFERROR($D$14/($D$76-$D$55)*100,"") | E87: =IFERROR($E$14/($E$76-$E$55)*100,"") | F87: =IFERROR($F$14/($F$76-$F$55)*100,"")
A88: Soliditetsgrad, % | B88: =IFERROR($B$55/$B$46*100,"") | C88: =IFERROR($C$55/$C$46*100,"") | D88: =IFERROR($D$55/$D$46*100,"") | E88: =IFERROR($E$55/$E$46*100,"") | F88: =IFERROR($F$55/$F$46*100,"")
A89: Gearing | B89: =IFERROR(($B$76-$B$55)/$B$55,"") | C89: =IFERROR(($C$76-$C$55)/$C$55,"") | D89: =IFERROR(($D$76-$D$55)/$D$55,"") | E89: =IFERROR(($E$76-$E$55)/$E$55,"") | F89: =IFERROR(($F$76-$F$55)/$F$55,"")
A90: Likviditetsgrad, % | B90: =IFERROR($B$45/$B$74*100,"") | C90: =IFERROR($C$45/$C$74*100,"") | D90: =IFERROR($D$45/$D$74*100,"") | E90: =IFERROR($E$45/$E$74*100,"") | F90: =IFERROR($F$45/$F$74*100,"")
A91: Rentemarginal, % | B91: =IFERROR(B83-B87,"") | C91: =IFERROR(C83-C87,"") | D91: =IFERROR(D83-D87,"") | E91: =IFERROR(E83-E87,"") | F91: =IFERROR(F83-F87,"")
A92: Gældsandel, % | B92: =IFERROR(($B$76-$B$55)/$B$46*100,"") | C92: =IFERROR(($C$76-$C$55)/$C$46*100,"") | D92: =IFERROR(($D$76-$D$55)/$D$46*100,"") | E92: =IFERROR(($E$76-$E$55)/$E$46*100,"") | F92: =IFERROR(($F$76-$F$55)/$F$46*100,"")
A93: Kapitalbindingsgrad, % | B93: =IFERROR($B$30/($B$55+$B$62)*100,"") | C93: =IFERROR($C$30/($C$55+$C$62)*100,"") | D93: =IFERROR($D$30/($D$55+$D$62)*100,"") | E93: =IFERROR($E$30/($E$55+$E$62)*100,"") | F93: =IFERROR($F$30/($F$55+$F$62)*100,"")
A95: PENGESTRØMSOPGØRELSE t.kr.
A96: Pengestrømme fra driftsaktivitet | B96: ='pengestrom_raw_13863385'!$B$2 | C96: ='pengestrom_raw_13863385'!$C$2 | D96: ='pengestrom_raw_13863385'!$D$2 | E96: ='pengestrom_raw_13863385'!$E$2 | F96: ='pengestrom_raw_13863385'!$F$2
A97: Pengestrømme fra investeringsaktivitet | B97: ='pengestrom_raw_13863385'!$B$3 | C97: ='pengestrom_raw_13863385'!$C$3 | D97: ='pengestrom_raw_13863385'!$D$3 | E97: ='pengestrom_raw_13863385'!$E$3 | F97: ='pengestrom_raw_13863385'!$F$3
A98: Pengestrømme fra finansieringsaktivitet | B98: ='pengestrom_raw_13863385'!$B$4 | C98: ='pengestrom_raw_13863385'!$C$4 | D98: ='pengestrom_raw_13863385'!$D$4 | E98: ='pengestrom_raw_13863385'!$E$4 | F98: ='pengestrom_raw_13863385'!$F$4
A99: Årets pengestrøm (rapporteret) | B99: ='pengestrom_raw_13863385'!$B$5 | C99: ='pengestrom_raw_13863385'!$C$5 | D99: ='pengestrom_raw_13863385'!$D$5 | E99: ='pengestrom_raw_13863385'!$E$5 | F99: ='pengestrom_raw_13863385'!$F$5
A100: Krydstjek: drift + inv. + fin. = årets pengestrøm | B100: =IF(ABS(('pengestrom_raw_13863385'!$B$2+'pengestrom_raw_13863385'!$B$3+'pengestrom_raw_13863385'!$B$4)-'pengestrom_raw_13863385'!$B$5)<=2,"✓","⚠ "&TEXT(('pengestrom_raw_13863385'!$B$2+'pengestrom_raw_13863385'!$B$3+'pengestrom_raw_13863385'!$B$4)-'pengestrom_raw_13863385'!$B$5,"+#,##0;-#,##0")) | C100: =IF(ABS(('pengestrom_raw_13863385'!$C$2+'pengestrom_raw_13863385'!$C$3+'pengestrom_raw_13863385'!$C$4)-'pengestrom_raw_13863385'!$C$5)<=2,"✓","⚠ "&TEXT(('pengestrom_raw_13863385'!$C$2+'pengestrom_raw_13863385'!$C$3+'pengestrom_raw_13863385'!$C$4)-'pengestrom_raw_13863385'!$C$5,"+#,##0;-#,##0")) | D100: =IF(ABS(('pengestrom_raw_13863385'!$D$2+'pengestrom_raw_13863385'!$D$3+'pengestrom_raw_13863385'!$D$4)-'pengestrom_raw_13863385'!$D$5)<=2,"✓","⚠ "&TEXT(('pengestrom_raw_13863385'!$D$2+'pengestrom_raw_13863385'!$D$3+'pengestrom_raw_13863385'!$D$4)-'pengestrom_raw_13863385'!$D$5,"+#,##0;-#,##0")) | E100: =IF(ABS(('pengestrom_raw_13863385'!$E$2+'pengestrom_raw_13863385'!$E$3+'pengestrom_raw_13863385'!$E$4)-'pengestrom_raw_13863385'!$E$5)<=2,"✓","⚠ "&TEXT(('pengestrom_raw_13863385'!$E$2+'pengestrom_raw_13863385'!$E$3+'pengestrom_raw_13863385'!$E$4)-'pengestrom_raw_13863385'!$E$5,"+#,##0;-#,##0")) | F100: =IF(ABS(('pengestrom_raw_13863385'!$F$2+'pengestrom_raw_13863385'!$F$3+'pengestrom_raw_13863385'!$F$4)-'pengestrom_raw_13863385'!$F$5)<=2,"✓","⚠ "&TEXT(('pengestrom_raw_13863385'!$F$2+'pengestrom_raw_13863385'!$F$3+'pengestrom_raw_13863385'!$F$4)-'pengestrom_raw_13863385'!$F$5,"+#,##0;-#,##0"))

Sheet res_raw_13863385
A1: Mascot International A/S (CVR 13863385) — Resultatopgørelse & nøgleoplysninger (t.kr.) | B1: 2021 | C1: 2022 | D1: 2023 | E1: 2024 | F1: 2025
A2: Nettoomsætning | B2: 1334761 | C2: 1656038 | D2: 1811275 | E2: 1982574 | F2: 2112986
A3: Produktionsomkostninger | B3: 681660 | C3: 792537 | D3: 756306 | E3: 799884 | F3: 851623
A4: Bruttoresultat | B4: 653101 | C4: 863501 | D4: 1054969 | E4: 1182690 | F4: 1261363
A5: Salgs- og distributionsomkostninger | B5: 270702 | C5: 309571 | D5: 421647 | E5: 510656 | F5: 488883
A6: Administrationsomkostninger | B6: 126979 | C6: 140368 | D6: 121356 | E6: 123428 | F6: 188951
A7: Andre driftsindtægter | B7: 777 | C7: 820 | D7: 0 | E7: 0 | F7: 0
A8: Andre driftsomkostninger
A9: Resultat af primær drift | B9: 255420 | C9: 413562 | D9: 511966 | E9: 548606 | F9: 583529
A10: Indtægter af kapitalandele, dattervirksomheder | B10: 0 | C10: 0 | D10: 0 | E10: 0 | F10: 0
A11: Finansielle indtægter | B11: 456 | C11: 229 | D11: 20002 | E11: 9435 | F11: 9682
A12: Finansielle omkostninger | B12: 4837 | C12: 7883 | D12: 7616 | E12: 7531 | F12: 21034
A13: Finansielle poster, netto
A14: Resultat før skat | B14: 251039 | C14: 405908 | D14: 524352 | E14: 550510 | F14: 572177
A15: Skat af årets resultat | B15: 51995 | C15: 80410 | D15: 103625 | E15: 106428 | F15: 109682
A16: Årets resultat | B16: 199044 | C16: 325498 | D16: 420727 | E16: 444082 | F16: 462495
A17: Gns. antal medarbejdere | B17: 2933 | C17: 3815 | D17: 4248 | E17: 3637 | F17: 3849
A18: Investering i materielle anlægsaktiver | B18: -114006 | C18: -95125 | D18: -147862

Sheet balance_raw_13863385
A1: Mascot International A/S (CVR 13863385) — Balance (t.kr.) | B1: 2021 | C1: 2022 | D1: 2023 | E1: 2024 | F1: 2025
A2: Grunde og bygninger | B2: 84116 | C2: 104003 | D2: 124476 | E2: 144871 | F2: 120581
A3: Produktionsanlæg og maskiner | B3: 99382 | C3: 103633 | D3: 93284 | E3: 79679 | F3: 278955
A4: Driftsmateriel og inventar | B4: 67997 | C4: 65111 | D4: 71403 | E4: 85546 | F4: 89525
A5: Indretning af lejede lokaler | B5: 1232 | C5: 747 | D5: 366 | E5: 3091 | F5: 3158
A6: Forudbetaling og anlægsaktiver under opførelse | B6: 73900 | C6: 39819 | D6: 81771 | E6: 151593 | F6: 46322
A7: Materielle anlægsaktiver | B7: 326627 | C7: 313313 | D7: 371300 | E7: 464780 | F7: 538541
A8: Kapitalandele, dattervirksomheder | B8: 0 | C8: 0 | D8: 0 | E8: 0 | F8: 0
A9: Deposita | B9: 79653 | C9: 87745 | D9: 90772 | E9: 128870 | F9: 155468
A10: Finansielle anlægsaktiver | B10: 90183 | C10: 89768 | D10: 103484 | E10: 138821 | F10: 168244
A11: Anlægsaktiver | B11: 416810 | C11: 403081 | D11: 474784 | E11: 603601 | F11: 706785
A12: Råvarer og hjælpematerialer | B12: 258282 | C12: 398324 | D12: 267259 | E12: 249715 | F12: 285876
... A19: Periodeafgrænsningsposter (aktiver) | B19: 27698 | C19: 33833 | D19: 26567 | E19: 29570 | F19: 30422
A20: Udskudt skatteaktiv
A21: Tilgodehavende skat hos tilknyttede virksomheder
A22: Kortfristede skattetilgodehavender | B22: 3952 | C22: 0 | D22: 0 | E22: 0 | F22: 0
A23: Tilgodehavender | B23: 287902 | C23: 309254 | D23: 315071 | E23: 369864 | F23: 385190
A24: Værdipapirer | C24: 254 | D24: 231 | E24: 209 | F24: 139
A25: Likvide beholdninger | B25: 32406 | C25: 14334 | D25: 94133 | E25: 205366 | F25: 255427
A26: Omsætningsaktiver | B26: 975817 | C26: 1378650 | D26: 1422293 | E26: 1605924 | F26: 1768494
A27: Aktiver | B27: 1392627 | C27: 1781731 | D27: 1897077 | E27: 2209525 | F27: 2475279
A28: Selskabskapital | B28: 500 | C28: 500 | D28: 500 | E28: 500 | F28: 500
A29: Reserve for nettoopskrivning (indre værdis metode) | B29: 0 | C29: 0 | D29: 0 | E29: 0 | F29: 0
A30: Reserve for udviklingsomkostninger
A31: Reserve for sikringstransaktioner
A32: Andre reserver | B32: -32538 | C32: -99718 | D32: -137785 | E32: -139101 | F32: -169785
A33: Overført resultat | B33: 1047004 | C33: 1272502 | D33: 1543229 | E33: 1837311 | F33: 2149806
A34: Egenkapital i alt | B34: 1089966 | C34: 1273284 | D34: 1555944 | E34: 1848710 | F34: 2130521
A35: Hensættelse til udskudt skat | B35: 14675 | C35: 14683 | D35: 26888 | E35: 31541 | F35: 47688
A36: Hensatte forpligtelser | B36: 25300 | C36: 24805 | D36: 36576 | E36: 40803 | F36: 56534
A37: Ansvarlig lånekapital (langfristet)
A38: Langfristede lån
A39: Leasingforpligtelser (langfristet) | B39: 42435 | C39: 33740 | D39: 67811 | E39: 18583 | F39: 8787
A40: Anden gæld (langfristet) | B40: 0
A41: Langfristede gældsforpligtelser | B41: 42435 | C41: 33740 | D41: 67811 | E41: 18583 | F41: 8787
A42: Ansvarlig lånekapital (kortfristet)
A43: Kortfristet del af langfristede gældsforpligtelser | B43: 9830 | C43: 10680 | D43: 10109 | E43: 9791 | F43: 11266
A44: Kreditinstitutter | C44: 163605 | D44: 0
A45: Leasingforpligtelser (kortfristet)
A46: Leverandører af varer og tjenesteydelser | B46: 85027 | C46: 95186 | D46: 45602 | E46: 91137 | F46: 57104
A47: Gæld til tilknyttede virksomheder | B47: 0 | C47: 0 | D47: 803 | E47: 0 | F47: 0
A48: Gæld til selskabsdeltagere og ledelse
A49: Selskabsskat | B49: 0 | C49: 19812 | D49: 2065 | E49: 4157 | F49: 672
A50: Gæld til tilknyttede virksomheder vedr. selskabsskat
A51: Anden gæld (kortfristet) | B51: 140069 | C51: 160619 | D51: 178167 | E51: 196344 | F51: 210395
A52: Periodeafgrænsningsposter (passiver)
A53: Kortfristede gældsforpligtelser | B53: 234926 | C53: 449902 | D53: 236746 | E53: 301429 | F53: 279437
A54: Gældsforpligtelser | B54: 277361 | C54: 483642 | D54: 304557 | E54: 320012 | F54: 288224
A55: Passiver | B55: 1392627 | C55: 1781731 | D55: 1897077 | E55: 2209525 | F55: 2475279

Sheet pengestrom_raw_13863385
A1: Mascot International A/S (CVR 13863385) — Pengestrømsopgørelse (t.kr.) | B1: 2021 | C1: 2022 | D1: 2023 | E1: 2024 | F1: 2025
A2: Pengestrømme fra driftsaktivitet | B2: 121247 | C2: -9735 | D2: 464735 | E2: 496432 | F2: 390700
A3: Pengestrømme fra investeringsaktivitet | B3: -120189 | C3: -89097 | D3: -154830 | E3: -185653 | F3: -182318
A4: Pengestrømme fra finansieringsaktivitet | B4: -56751 | C4: 80760 | D4: -230106 | E4: -199546 | F4: -158321
A5: Årets pengestrøm

Sheet Simpel_funktion
A1: Mascot International A/S (CVR 13863385) — Regnskabs- og nøgletal (CVR: 13863385) — funktionsopdelt
A3: Beløb i 1.000 kr. | B3: 2025 | C3: 2024 | D3: 2023 | F3: Note / XBRL-felt
A4: Uddrag af resultatopgørelse
A5: Nettoomsætning | B5: ='res_raw_13863385'!$F$2 | C5: ='res_raw_13863385'!$E$2 | D5: ='res_raw_13863385'!$D$2 | F5: fsa:Revenue
A6: Produktionsomkostninger | B6: =-'res_raw_13863385'!$F$3 | C6: =-'res_raw_13863385'!$E$3 | D6: =-'res_raw_13863385'!$D$3 | F6: fsa:CostOfProduction (vises negativt). Materialer, lønninger, produktionsoverhead.
A7: Bruttoresultat | B7: =SUM(B5:B6) | C7: =SUM(C5:C6) | D7: =SUM(D5:D6) | F7: Beregnet: Nettoomsætning − Produktionsomkostninger. Matcher fsa:GrossResult.
A8: Salgs- og distributionsomk. | B8: =-'res_raw_13863385'!$F$5 | C8: =-'res_raw_13863385'!$E$5 | D8: =-'res_raw_13863385'!$D$5 | F8: fsa:DistributionCosts (vises negativt). Marketing, salg, distribution.
A9: Administrationsomkostninger mv. | B9: =-'res_raw_13863385'!$F$6 | C9: =-'res_raw_13863385'!$E$6 | D9: =-'res_raw_13863385'!$D$6 | F9: fsa:AdministrativeExpenses (vises negativt). Generel administration.
A10: Andre driftsindtægter | B10: ='res_raw_13863385'!$F$7 | C10: ='res_raw_13863385'!$E$7 | D10: ='res_raw_13863385'!$D$7 | F10: fsa:OtherOperatingIncome. Sekundære driftsindtægter (huslejeindtægter, off. tilskud, avancer mv.).
A11: Andre driftsomkostninger | B11: =-'res_raw_13863385'!$F$8 | C11: =-'res_raw_13863385'!$E$8 | D11: =-'res_raw_13863385'!$D$8 | F11: fsa:OtherOperatingExpenses (vises negativt). Sekundære driftsomkostninger.
A12: Resultat af primær drift | B12: =SUM(B7:B11) | C12: =SUM(C7:C11) | D12: =SUM(D7:D11) | F12: Beregnet: Bruttoresultat − Salgs/dist. − Administration + Andre driftsindt. − Andre driftsomk. EBIT.
A13: Finansielle indtægter mv. | B13: =N('res_raw_13863385'!$F$10)+N('res_raw_13863385'!$F$11) | C13: =N('res_raw_13863385'!$E$10)+N('res_raw_13863385'!$E$11) | D13: =N('res_raw_13863385'!$D$10)+N('res_raw_13863385'!$D$11) | F13: fsa:IncomeFromSubsidiaries + fsa:OtherFinanceIncome.
A14: Finansielle omkostninger mv. | B14: =-'res_raw_13863385'!$F$12 | C14: =-'res_raw_13863385'!$E$12 | D14: =-'res_raw_13863385'!$D$12 | F14: fsa:OtherFinanceExpenses (vises negativt). Renteomkostninger, kurstab.
A15: Resultat før skat | B15: =SUM(B12:B14) | C15: =SUM(C12:C14) | D15: =SUM(D12:D14) | F15: Beregnet: EBIT + Fin. indtægter + Fin. omk. EBT.
A17: Uddrag af balance
A18: Anlægsaktiver | B18: ='balance_raw_13863385'!$F$11 | C18: ='balance_raw_13863385'!$E$11 | D18: ='balance_raw_13863385'!$D$11 | F18: fsa:NoncurrentAssets. Materielle, immaterielle og finansielle anlægsaktiver.
A19: Omsætningsaktiver | B19: ='balance_raw_13863385'!$F$26 | C19: ='balance_raw_13863385'!$E$26 | D19: ='balance_raw_13863385'!$D$26 | F19: fsa:CurrentAssets. Varebeholdninger, tilgodehavender, likvider.
A20: Aktiver i alt | B20: =SUM(B18:B19) | C20: =SUM(C18:C19) | D20: =SUM(D18:D19) | F20: Beregnet: Anlægsaktiver + Omsætningsaktiver. Bør matche fsa:Assets.
A22: Egenkapital | B22: ='balance_raw_13863385'!$F$34 | C22: ='balance_raw_13863385'!$E$34 | D22: ='balance_raw_13863385'!$D$34 | F22: fsa:Equity. Selskabskapital, overført resultat, reserver.
A23: Forpligtelser | B23: ='balance_raw_13863385'!$F$55-'balance_raw_13863385'!$F$34 | C23: ='balance_raw_13863385'!$E$55-'balance_raw_13863385'!$E$34 | D23: ='balance_raw_13863385'!$D$55-'balance_raw_13863385'!$D$34 | F23: Beregnet: Passiver (fsa:LiabilitiesAndEquity) − Egenkapital. Hensættelser + kort- og langfristet gæld.
A24: Passiver i alt | B24: =SUM(B22:B23) | C24: =SUM(C22:C23) | D24: =SUM(D22:D23) | F24: Beregnet: Egenkapital + Forpligtelser. Bør matche Aktiver i alt.
A26: Udvalgte balanceposter
A27: Varebeholdninger | B27: ='balance_raw_13863385'!$F$15 | C27: ='balance_raw_13863385'!$E$15 | D27: ='balance_raw_13863385'!$D$15 | F27: fsa:Inventories (eller fsa:ManufacturedGoodsAndGoodsForResale hvis total mangler).
A28: Tilgodehavender fra salg | B28: ='balance_raw_13863385'!$F$16 | C28: ='balance_raw_13863385'!$E$16 | D28: ='balance_raw_13863385'!$D$16 | F28: fsa:ShorttermTradeReceivables. Kortfristede tilgodehavender fra kunder.
A29: Kortfristede gældsforpligtelser | B29: ='balance_raw_13863385'!$F$53 | C29: ='balance_raw_13863385'!$E$53 | D29: ='balance_raw_13863385'!$D$53 | F29: fsa:ShorttermLiabilitiesOtherThanProvisions. Gæld der forfalder inden for 1 år.
A31: Rentabilitet
A32: Afkastningsgrad, % | B32: =IFERROR((B12+B13)/B20*100,"") | C32: =IFERROR((C12+C13)/C20*100,"") | D32: =IFERROR((D12+D13)/D20*100,"")
A33: Overskudsgrad, % | B33: =IFERROR((B12+B13)/B5*100,"") | C33: =IFERROR((C12+C13)/C5*100,"") | D33: =IFERROR((D12+D13)/D5*100,"")
A34: Aktivernes omsætningshastighed, gange | B34: =IFERROR(B5/B20,"") | C34: =IFERROR(C5/C20,"") | D34: =IFERROR(D5/D20,"")
A35: Gældsrente, % | B35: =IFERROR(-B14*100/B23,"") | C35: =IFERROR(-C14*100/C23,"") | D35: =IFERROR(-D14*100/D23,"")
A36: Egenkapitalens forrentning, % | B36: =IFERROR(B15/B22*100,"") | C36: =IFERROR(C15/C22*100,"") | D36: =IFERROR(D15/D22*100,"")
A37: Gearing, gange | B37: =IFERROR(B23/B22,"") | C37: =IFERROR(C23/C22,"") | D37: =IFERROR(D23/D22,"")
A39: Indekstal for indtjeningsevne (2023=100)
A40: Nettoomsætning | B40: =IFERROR(B5/$D5*100,"") | C40: =IFERROR(C5/$D5*100,"") | D40: =IFERROR(D5/$D5*100,"")
A41: Produktionsomkostninger | B41: =IFERROR(B6/$D6*100,"") | C41: =IFERROR(C6/$D6*100,"") | D41: =IFERROR(D6/$D6*100,"")
A42: Salgs- og distributionsomk. | B42: =IFERROR(B8/$D8*100,"") | C42: =IFERROR(C8/$D8*100,"") | D42: =IFERROR(D8/$D8*100,"")
A43: Administrationsomk. | B43: =IFERROR(B9/$D9*100,"") | C43: =IFERROR(C9/$D9*100,"") | D43: =IFERROR(D9/$D9*100,"")
A44: Andre driftsomkostninger | B44: =IFERROR(B11/$D11*100,"") | C44: =IFERROR(C11/$D11*100,"") | D44: =IFERROR(D11/$D11*100,"")
A46: Indekstal for kapitaltilpasningsevne (2023=100)
A47: Nettoomsætning | B47: =IFERROR(B5*100/$D5,"") | C47: =IFERROR(C5*100/$D5,"") | D47: =IFERROR(D5*100/$D5,"")
A48: Anlægsaktiver | B48: =IFERROR(B18*100/$D18,"") | C48: =IFERROR(C18*100/$D18,"") | D48: =IFERROR(D18*100/$D18,"")
A49: Varebeholdninger | B49: =IFERROR(B27*100/$D27,"") | C49: =IFERROR(C27*100/$D27,"") | D49: =IFERROR(D27*100/$D27,"")
A50: Tilgodehavender fra salg | B50: =IFERROR(B28*100/$D28,"") | C50: =IFERROR(C28*100/$D28,"") | D50: =IFERROR(D28*100/$D28,"")
A52: Soliditet og likviditet
A53: Soliditetsgrad, % | B53: =IFERROR(B22*100/B20,"") | C53: =IFERROR(C22*100/C20,"") | D53: =IFERROR(D22*100/D20,"")
A54: Gældsandel, % | B54: =IFERROR(B23*100/B20,"") | C54: =IFERROR(C23*100/C20,"") | D54: =IFERROR(D23*100/D20,"")
A55: Likviditetsgrad, % | B55: =IFERROR(B19*100/B29,"") | C55: =IFERROR(C19*100/C29,"") | D55: =IFERROR(D19*100/D29,"")
A57: Kilde: Bearbejdet uddrag af årsrapporter for 2023-2025. Alle dataceller er live formler der peger på res_raw / balance_raw.
A59: Krydstjek mod rådata (tolerance: 1 t.kr.)
A60: Aktiver i alt = fsa:Assets | B60: =IF('balance_raw_13863385'!$F$27="","—",IF(ABS(B20-'balance_raw_13863385'!$F$27)<=1,"✓ OK","❌ "&TEXT(B20-'balance_raw_13863385'!$F$27,"+#,##0;-#,##0")&" t.kr.")) | C60: =IF('balance_raw_13863385'!$E$27="","—",IF(ABS(C20-'balance_raw_13863385'!$E$27)<=1,"✓ OK","❌ "&TEXT(C20-'balance_raw_13863385'!$E$27,"+#,##0;-#,##0")&" t.kr.")) | D60: =IF('balance_raw_13863385'!$D$27="","—",IF(ABS(D20-'balance_raw_13863385'!$D$27)<=1,"✓ OK","❌ "&TEXT(D20-'balance_raw_13863385'!$D$27,"+#,##0;-#,##0")&" t.kr.")) | F60: Verificerer at sum(Anlæg+Omsætning) matcher Assets-totalen.
A61: Passiver i alt = fsa:LiabilitiesAndEquity | B61: =IF('balance_raw_13863385'!$F$55="","—",IF(ABS(B24-'balance_raw_13863385'!$F$55)<=1,"✓ OK","❌ "&TEXT(B24-'balance_raw_13863385'!$F$55,"+#,##0;-#,##0")&" t.kr.")) | C61: =IF('balance_raw_13863385'!$E$55="","—",IF(ABS(C24-'balance_raw_13863385'!$E$55)<=1,"✓ OK","❌ "&TEXT(C24-'balance_raw_13863385'!$E$55,"+#,##0;-#,##0")&" t.kr.")) | D61: =IF('balance_raw_13863385'!$D$55="","—",IF(ABS(D24-'balance_raw_13863385'!$D$55)<=1,"✓ OK","❌ "&TEXT(D24-'balance_raw_13863385'!$D$55,"+#,##0;-#,##0")&" t.kr.")) | F61: Verificerer at sum(EK+Forpligtelser) matcher Passiver-totalen.
A62: Aktiver i alt = Passiver i alt | B62: =IF(ABS(B20-B24)<=1,"✓ OK","❌ "&TEXT(B20-B24,"+#,##0;-#,##0")&" t.kr.") | C62: =IF(ABS(C20-C24)<=1,"✓ OK","❌ "&TEXT(C20-C24,"+#,##0;-#,##0")&" t.kr.") | D62: =IF(ABS(D20-D24)<=1,"✓ OK","❌ "&TEXT(D20-D24,"+#,##0;-#,##0")&" t.kr.") | F62: Balance-identitet på arket selv. Skal altid være 0 differance.
A63: Bruttoresultat (beregnet) = fsa:GrossResult | B63: =IF('res_raw_13863385'!$F$4="","—",IF(ABS(B7-'res_raw_13863385'!$F$4)<=1,"✓ OK","❌ "&TEXT(B7-'res_raw_13863385'!$F$4,"+#,##0;-#,##0")&" t.kr.")) | C63: =IF('res_raw_13863385'!$E$4="","—",IF(ABS(C7-'res_raw_13863385'!$E$4)<=1,"✓ OK","❌ "&TEXT(C7-'res_raw_13863385'!$E$4,"+#,##0;-#,##0")&" t.kr.")) | D63: =IF('res_raw_13863385'!$D$4="","—",IF(ABS(D7-'res_raw_13863385'!$D$4)<=1,"✓ OK","❌ "&TEXT(D7-'res_raw_13863385'!$D$4,"+#,##0;-#,##0")&" t.kr.")) | F63: Hvis Nettoomsætning eller omkostninger mangler, vil sumberegnet bruttoresultat afvige.
A64: EBIT (beregnet) = fsa:ProfitLossFromOrdinaryOperatingActivities | B64: =IF('res_raw_13863385'!$F$9="","—",IF(ABS(B12-'res_raw_13863385'!$F$9)<=1,"✓ OK","❌ "&TEXT(B12-'res_raw_13863385'!$F$9,"+#,##0;-#,##0")&" t.kr.")) | C64: =IF('res_raw_13863385'!$E$9="","—",IF(ABS(C12-'res_raw_13863385'!$E$9)<=1,"✓ OK","❌ "&TEXT(C12-'res_raw_13863385'!$E$9,"+#,##0;-#,##0")&" t.kr.")) | D64: =IF('res_raw_13863385'!$D$9="","—",IF(ABS(D12-'res_raw_13863385'!$D$9)<=1,"✓ OK","❌ "&TEXT(D12-'res_raw_13863385'!$D$9,"+#,##0;-#,##0")&" t.kr.")) | F64: Verificerer at sumberegnet EBIT matcher det rapporterede.
A65: EBT (beregnet) = fsa:ProfitLossFromOrdinaryActivitiesBeforeTax | B65: =IF('res_raw_13863385'!$F$14="","—",IF(ABS(B15-'res_raw_13863385'!$F$14)<=1,"✓ OK","❌ "&TEXT(B15-'res_raw_13863385'!$F$14,"+#,##0;-#,##0")&" t.kr.")) | C65: =IF('res_raw_13863385'!$E$14="","—",IF(ABS(C15-'res_raw_13863385'!$E$14)<=1,"✓ OK","❌ "&TEXT(C15-'res_raw_13863385'!$E$14,"+#,##0;-#,##0")&" t.kr.")) | D65: =IF('res_raw_13863385'!$D$14="","—",IF(ABS(D15-'res_raw_13863385'!$D$14)<=1,"✓ OK","❌ "&TEXT(D15-'res_raw_13863385'!$D$14,"+#,##0;-#,##0")&" t.kr.")) | F65: Verificerer at sumberegnet resultat før skat matcher det rapporterede.

Sheet Noter_info
A1: Mascot International A/S (CVR 13863385) — Ukendte XBRL-felter — disse er noter og ikke en del af hoved-regnskabet
A2: Kategori | B2: Dansk navn | C2: XBRL feltnavn | D2: 2021 t.kr. | E2: 2022 t.kr. | F2: 2023 t.kr. | G2: 2024 t.kr. | H2: 2025 t.kr. | I2: Forklaring
A3: Øvrige (ukendt) | B3: fsa:ConclusionOfLeaseObligations | C3: fsa:ConclusionOfLeaseObligations | D3: 3216 | E3: 2602 | F3: 45500 | G3: 18335 | H3: 3593 | I3: Ingen forklaring tilgængelig.
A4: Øvrige (ukendt) | B4: fsa:Dividend | C4: fsa:Dividend | E4: 0 | F4: 0 | G4: 0 | H4: 0 | I4: Ingen forklaring tilgængelig.
A5: Øvrige (ukendt) | B5: fsa:ReductionOfLeaseCommitments | C5: fsa:ReductionOfLeaseCommitments | D5: 9967 | E5: 10447 | F5: 12001 | G5: 67881 | H5: 11914 | I5: Ingen forklaring tilgængelig.
