Workbook

Sheet Overblik_16499609
A1: Munck Gruppen A/S (CVR 16499609) — Regnskabsanalyse – Resultatopgørelse & Balance (t.kr.) · Klasse C-stor · Revision · Regnskabsår 1/10–30/9 (forskudt)
H2: Indekstal (2021=100)
A3: Resultatopgørelse t.kr. | B3: 2021 | C3: 2022 | D3: 2023 | E3: 2024 | F3: 2025 | H3: 2021 | I3: 2022 | J3: 2023 | K3: 2024 | L3: 2025
A4: Nettoomsætning | B4: ='res_raw_16499609'!$B$2 | C4: ='res_raw_16499609'!$C$2 | D4: ='res_raw_16499609'!$D$2 | E4: ='res_raw_16499609'!$E$2 | F4: ='res_raw_16499609'!$F$2 | H4: =IFERROR(B4/$B$4*100,"") | I4: =IFERROR(C4/$B$4*100,"") | J4: =IFERROR(D4/$B$4*100,"") | K4: =IFERROR(E4/$B$4*100,"") | L4: =IFERROR(F4/$B$4*100,"")
A5: Produktionsomkostninger | B5: ='res_raw_16499609'!$B$3 | C5: ='res_raw_16499609'!$C$3 | D5: ='res_raw_16499609'!$D$3 | E5: ='res_raw_16499609'!$E$3 | F5: ='res_raw_16499609'!$F$3 | H5: =IFERROR(B5/$B$5*100,"") | I5: =IFERROR(C5/$B$5*100,"") | J5: =IFERROR(D5/$B$5*100,"") | K5: =IFERROR(E5/$B$5*100,"") | L5: =IFERROR(F5/$B$5*100,"")
A6: Bruttoresultat | B6: ='res_raw_16499609'!$B$4 | C6: ='res_raw_16499609'!$C$4 | D6: ='res_raw_16499609'!$D$4 | E6: ='res_raw_16499609'!$E$4 | F6: ='res_raw_16499609'!$F$4 | H6: =IFERROR(B6/$B$6*100,"") | I6: =IFERROR(C6/$B$6*100,"") | J6: =IFERROR(D6/$B$6*100,"") | K6: =IFERROR(E6/$B$6*100,"") | L6: =IFERROR(F6/$B$6*100,"")
A7: Salgs- og distributionsomkostninger | B7: ='res_raw_16499609'!$B$5 | C7: ='res_raw_16499609'!$C$5 | D7: ='res_raw_16499609'!$D$5 | E7: ='res_raw_16499609'!$E$5 | F7: ='res_raw_16499609'!$F$5 | H7: =IFERROR(B7/$B$7*100,"") | I7: =IFERROR(C7/$B$7*100,"") | J7: =IFERROR(D7/$B$7*100,"") | K7: =IFERROR(E7/$B$7*100,"") | L7: =IFERROR(F7/$B$7*100,"")
A8: Administrationsomkostninger | B8: ='res_raw_16499609'!$B$6 | C8: ='res_raw_16499609'!$C$6 | D8: ='res_raw_16499609'!$D$6 | E8: ='res_raw_16499609'!$E$6 | F8: ='res_raw_16499609'!$F$6 | H8: =IFERROR(B8/$B$8*100,"") | I8: =IFERROR(C8/$B$8*100,"") | J8: =IFERROR(D8/$B$8*100,"") | K8: =IFERROR(E8/$B$8*100,"") | L8: =IFERROR(F8/$B$8*100,"")
A9: Andre driftsindtægter | B9: ='res_raw_16499609'!$B$7 | C9: ='res_raw_16499609'!$C$7 | D9: ='res_raw_16499609'!$D$7 | E9: ='res_raw_16499609'!$E$7 | F9: ='res_raw_16499609'!$F$7 | H9: =IFERROR(B9/$B$9*100,"") | I9: =IFERROR(C9/$B$9*100,"") | J9: =IFERROR(D9/$B$9*100,"") | K9: =IFERROR(E9/$B$9*100,"") | L9: =IFERROR(F9/$B$9*100,"")
A10: Andre driftsomkostninger | B10: ='res_raw_16499609'!$B$8 | C10: ='res_raw_16499609'!$C$8 | D10: ='res_raw_16499609'!$D$8 | E10: ='res_raw_16499609'!$E$8 | F10: ='res_raw_16499609'!$F$8 | H10: =IFERROR(B10/$B$10*100,"") | I10: =IFERROR(C10/$B$10*100,"") | J10: =IFERROR(D10/$B$10*100,"") | K10: =IFERROR(E10/$B$10*100,"") | L10: =IFERROR(F10/$B$10*100,"")
A11: Resultat af primær drift | B11: =IFERROR($B$6-ABS($B$7)-ABS($B$8)+$B$9-ABS($B$10),"") | C11: =IFERROR($C$6-ABS($C$7)-ABS($C$8)+$C$9-ABS($C$10),"") | D11: =IFERROR($D$6-ABS($D$7)-ABS($D$8)+$D$9-ABS($D$10),"") | E11: =IFERROR($E$6-ABS($E$7)-ABS($E$8)+$E$9-ABS($E$10),"") | F11: =IFERROR($F$6-ABS($F$7)-ABS($F$8)+$F$9-ABS($F$10),"") | H11: =IFERROR(B11/$B$11*100,"") | I11: =IFERROR(C11/$B$11*100,"") | J11: =IFERROR(D11/$B$11*100,"") | K11: =IFERROR(E11/$B$11*100,"") | L11: =IFERROR(F11/$B$11*100,"")
A12: Indtægter af kapitalandele, dattervirksomheder | B12: ='res_raw_16499609'!$B$10 | C12: ='res_raw_16499609'!$C$10 | D12: ='res_raw_16499609'!$D$10 | E12: ='res_raw_16499609'!$E$10 | F12: ='res_raw_16499609'!$F$10 | H12: =IFERROR(B12/$B$12*100,"") | I12: =IFERROR(C12/$B$12*100,"") | J12: =IFERROR(D12/$B$12*100,"") | K12: =IFERROR(E12/$B$12*100,"") | L12: =IFERROR(F12/$B$12*100,"")
A13: Finansielle indtægter | B13: ='res_raw_16499609'!$B$11 | C13: ='res_raw_16499609'!$C$11 | D13: ='res_raw_16499609'!$D$11 | E13: ='res_raw_16499609'!$E$11 | F13: ='res_raw_16499609'!$F$11 | H13: =IFERROR(B13/$B$13*100,"") | I13: =IFERROR(C13/$B$13*100,"") | J13: =IFERROR(D13/$B$13*100,"") | K13: =IFERROR(E13/$B$13*100,"") | L13: =IFERROR(F13/$B$13*100,"")
A14: Finansielle omkostninger | B14: ='res_raw_16499609'!$B$12 | C14: ='res_raw_16499609'!$C$12 | D14: ='res_raw_16499609'!$D$12 | E14: ='res_raw_16499609'!$E$12 | F14: ='res_raw_16499609'!$F$12 | H14: =IFERROR(B14/$B$14*100,"") | I14: =IFERROR(C14/$B$14*100,"") | J14: =IFERROR(D14/$B$14*100,"") | K14: =IFERROR(E14/$B$14*100,"") | L14: =IFERROR(F14/$B$14*100,"")
A15: Finansielle poster, netto | B15: ='res_raw_16499609'!$B$13 | C15: ='res_raw_16499609'!$C$13 | D15: ='res_raw_16499609'!$D$13 | E15: ='res_raw_16499609'!$E$13 | F15: ='res_raw_16499609'!$F$13 | H15: =IFERROR(B15/$B$15*100,"") | I15: =IFERROR(C15/$B$15*100,"") | J15: =IFERROR(D15/$B$15*100,"") | K15: =IFERROR(E15/$B$15*100,"") | L15: =IFERROR(F15/$B$15*100,"")
A16: Resultat før skat | B16: ='res_raw_16499609'!$B$14 | C16: ='res_raw_16499609'!$C$14 | D16: ='res_raw_16499609'!$D$14 | E16: ='res_raw_16499609'!$E$14 | F16: ='res_raw_16499609'!$F$14 | H16: =IFERROR(B16/$B$16*100,"") | I16: =IFERROR(C16/$B$16*100,"") | J16: =IFERROR(D16/$B$16*100,"") | K16: =IFERROR(E16/$B$16*100,"") | L16: =IFERROR(F16/$B$16*100,"")
A17: Skat af årets resultat | B17: ='res_raw_16499609'!$B$15 | C17: ='res_raw_16499609'!$C$15 | D17: ='res_raw_16499609'!$D$15 | E17: ='res_raw_16499609'!$E$15 | F17: ='res_raw_16499609'!$F$15 | H17: =IFERROR(B17/$B$17*100,"") | I17: =IFERROR(C17/$B$17*100,"") | J17: =IFERROR(D17/$B$17*100,"") | K17: =IFERROR(E17/$B$17*100,"") | L17: =IFERROR(F17/$B$17*100,"")
A18: Årets resultat | B18: ='res_raw_16499609'!$B$16 | C18: ='res_raw_16499609'!$C$16 | D18: ='res_raw_16499609'!$D$16 | E18: ='res_raw_16499609'!$E$16 | F18: ='res_raw_16499609'!$F$16 | H18: =IFERROR(B18/$B$18*100,"") | I18: =IFERROR(C18/$B$18*100,"") | J18: =IFERROR(D18/$B$18*100,"") | K18: =IFERROR(E18/$B$18*100,"") | L18: =IFERROR(F18/$B$18*100,"")
A20: AKTIVER t.kr. | B20: 2021 | C20: 2022 | D20: 2023 | E20: 2024 | F20: 2025 | H20: 2021 | I20: 2022 | J20: 2023 | K20: 2024 | L20: 2025
A21: Udviklingsprojekter | B21: ='balance_raw_16499609'!$B$2 | C21: ='balance_raw_16499609'!$C$2 | D21: ='balance_raw_16499609'!$D$2 | E21: ='balance_raw_16499609'!$E$2 | F21: ='balance_raw_16499609'!$F$2 | H21: =IFERROR(B21/$B$21*100,"") | I21: =IFERROR(C21/$B$21*100,"") | J21: =IFERROR(D21/$B$21*100,"") | K21: =IFERROR(E21/$B$21*100,"") | L21: =IFERROR(F21/$B$21*100,"")
A22: Patenter, varemærker mv. | B22: ='balance_raw_16499609'!$B$3 | C22: ='balance_raw_16499609'!$C$3 | D22: ='balance_raw_16499609'!$D$3 | E22: ='balance_raw_16499609'!$E$3 | F22: ='balance_raw_16499609'!$F$3 | H22: =IFERROR(B22/$B$22*100,"") | I22: =IFERROR(C22/$B$22*100,"") | J22: =IFERROR(D22/$B$22*100,"") | K22: =IFERROR(E22/$B$22*100,"") | L22: =IFERROR(F22/$B$22*100,"")
A23: Goodwill | B23: ='balance_raw_16499609'!$B$4 | C23: ='balance_raw_16499609'!$C$4 | D23: ='balance_raw_16499609'!$D$4 | E23: ='balance_raw_16499609'!$E$4 | F23: ='balance_raw_16499609'!$F$4 | H23: =IFERROR(B23/$B$23*100,"") | I23: =IFERROR(C23/$B$23*100,"") | J23: =IFERROR(D23/$B$23*100,"") | K23: =IFERROR(E23/$B$23*100,"") | L23: =IFERROR(F23/$B$23*100,"")
A24: Immaterielle anlægsaktiver | B24: ='balance_raw_16499609'!$B$5 | C24: ='balance_raw_16499609'!$C$5 | D24: ='balance_raw_16499609'!$D$5 | E24: ='balance_raw_16499609'!$E$5 | F24: ='balance_raw_16499609'!$F$5 | H24: =IFERROR(B24/$B$24*100,"") | I24: =IFERROR(C24/$B$24*100,"") | J24: =IFERROR(D24/$B$24*100,"") | K24: =IFERROR(E24/$B$24*100,"") | L24: =IFERROR(F24/$B$24*100,"")
A25: Grunde og bygninger | B25: ='balance_raw_16499609'!$B$6 | C25: ='balance_raw_16499609'!$C$6 | D25: ='balance_raw_16499609'!$D$6 | E25: ='balance_raw_16499609'!$E$6 | F25: ='balance_raw_16499609'!$F$6 | H25: =IFERROR(B25/$B$25*100,"") | I25: =IFERROR(C25/$B$25*100,"") | J25: =IFERROR(D25/$B$25*100,"") | K25: =IFERROR(E25/$B$25*100,"") | L25: =IFERROR(F25/$B$25*100,"")
A26: Produktionsanlæg og maskiner | B26: ='balance_raw_16499609'!$B$7 | C26: ='balance_raw_16499609'!$C$7 | D26: ='balance_raw_16499609'!$D$7 | E26: ='balance_raw_16499609'!$E$7 | F26: ='balance_raw_16499609'!$F$7 | H26: =IFERROR(B26/$B$26*100,"") | I26: =IFERROR(C26/$B$26*100,"") | J26: =IFERROR(D26/$B$26*100,"") | K26: =IFERROR(E26/$B$26*100,"") | L26: =IFERROR(F26/$B$26*100,"")
A27: Driftsmateriel og inventar | B27: ='balance_raw_16499609'!$B$8 | C27: ='balance_raw_16499609'!$C$8 | D27: ='balance_raw_16499609'!$D$8 | E27: ='balance_raw_16499609'!$E$8 | F27: ='balance_raw_16499609'!$F$8 | H27: =IFERROR(B27/$B$27*100,"") | I27: =IFERROR(C27/$B$27*100,"") | J27: =IFERROR(D27/$B$27*100,"") | K27: =IFERROR(E27/$B$27*100,"") | L27: =IFERROR(F27/$B$27*100,"")
A28: Indretning af lejede lokaler | B28: ='balance_raw_16499609'!$B$9 | C28: ='balance_raw_16499609'!$C$9 | D28: ='balance_raw_16499609'!$D$9 | E28: ='balance_raw_16499609'!$E$9 | F28: ='balance_raw_16499609'!$F$9 | H28: =IFERROR(B28/$B$28*100,"") | I28: =IFERROR(C28/$B$28*100,"") | J28: =IFERROR(D28/$B$28*100,"") | K28: =IFERROR(E28/$B$28*100,"") | L28: =IFERROR(F28/$B$28*100,"")
A29: Forudbetaling og anlægsaktiver under opførelse | B29: ='balance_raw_16499609'!$B$10 | C29: ='balance_raw_16499609'!$C$10 | D29: ='balance_raw_16499609'!$D$10 | E29: ='balance_raw_16499609'!$E$10 | F29: ='balance_raw_16499609'!$F$10 | H29: =IFERROR(B29/$B$29*100,"") | I29: =IFERROR(C29/$B$29*100,"") | J29: =IFERROR(D29/$B$29*100,"") | K29: =IFERROR(E29/$B$29*100,"") | L29: =IFERROR(F29/$B$29*100,"")
A30: Materielle anlægsaktiver | B30: ='balance_raw_16499609'!$B$11 | C30: ='balance_raw_16499609'!$C$11 | D30: ='balance_raw_16499609'!$D$11 | E30: ='balance_raw_16499609'!$E$11 | F30: ='balance_raw_16499609'!$F$11 | H30: =IFERROR(B30/$B$30*100,"") | I30: =IFERROR(C30/$B$30*100,"") | J30: =IFERROR(D30/$B$30*100,"") | K30: =IFERROR(E30/$B$30*100,"") | L30: =IFERROR(F30/$B$30*100,"")
A31: Kapitalandele, dattervirksomheder | B31: ='balance_raw_16499609'!$B$12 | C31: ='balance_raw_16499609'!$C$12 | D31: ='balance_raw_16499609'!$D$12 | E31: ='balance_raw_16499609'!$E$12 | F31: ='balance_raw_16499609'!$F$12 | H31: =IFERROR(B31/$B$31*100,"") | I31: =IFERROR(C31/$B$31*100,"") | J31: =IFERROR(D31/$B$31*100,"") | K31: =IFERROR(E31/$B$31*100,"") | L31: =IFERROR(F31/$B$31*100,"")
A32: Deposita | B32: ='balance_raw_16499609'!$B$13 | C32: ='balance_raw_16499609'!$C$13 | D32: ='balance_raw_16499609'!$D$13 | E32: ='balance_raw_16499609'!$E$13 | F32: ='balance_raw_16499609'!$F$13 | H32: =IFERROR(B32/$B$32*100,"") | I32: =IFERROR(C32/$B$32*100,"") | J32: =IFERROR(D32/$B$32*100,"") | K32: =IFERROR(E32/$B$32*100,"") | L32: =IFERROR(F32/$B$32*100,"")
A33: Finansielle anlægsaktiver | B33: ='balance_raw_16499609'!$B$14 | C33: ='balance_raw_16499609'!$C$14 | D33: ='balance_raw_16499609'!$D$14 | E33: ='balance_raw_16499609'!$E$14 | F33: ='balance_raw_16499609'!$F$14 | H33: =IFERROR(B33/$B$33*100,"") | I33: =IFERROR(C33/$B$33*100,"") | J33: =IFERROR(D33/$B$33*100,"") | K33: =IFERROR(E33/$B$33*100,"") | L33: =IFERROR(F33/$B$33*100,"")
A34: Anlægsaktiver | B34: ='balance_raw_16499609'!$B$15 | C34: ='balance_raw_16499609'!$C$15 | D34: ='balance_raw_16499609'!$D$15 | E34: ='balance_raw_16499609'!$E$15 | F34: ='balance_raw_16499609'!$F$15 | H34: =IFERROR(B34/$B$34*100,"") | I34: =IFERROR(C34/$B$34*100,"") | J34: =IFERROR(D34/$B$34*100,"") | K34: =IFERROR(E34/$B$34*100,"") | L34: =IFERROR(F34/$B$34*100,"")
A35: Råvarer og hjælpematerialer | B35: ='balance_raw_16499609'!$B$16 | C35: ='balance_raw_16499609'!$C$16 | D35: ='balance_raw_16499609'!$D$16 | E35: ='balance_raw_16499609'!$E$16 | F35: ='balance_raw_16499609'!$F$16 | H35: =IFERROR(B35/$B$35*100,"") | I35: =IFERROR(C35/$B$35*100,"") | J35: =IFERROR(D35/$B$35*100,"") | K35: =IFERROR(E35/$B$35*100,"") | L35: =IFERROR(F35/$B$35*100,"")
A36: Varer under fremstilling | B36: ='balance_raw_16499609'!$B$17 | C36: ='balance_raw_16499609'!$C$17 | D36: ='balance_raw_16499609'!$D$17 | E36: ='balance_raw_16499609'!$E$17 | F36: ='balance_raw_16499609'!$F$17 | H36: =IFERROR(B36/$B$36*100,"") | I36: =IFERROR(C36/$B$36*100,"") | J36: =IFERROR(D36/$B$36*100,"") | K36: =IFERROR(E36/$B$36*100,"") | L36: =IFERROR(F36/$B$36*100,"")
A37: Færdigvarer og handelsvarer | B37: ='balance_raw_16499609'!$B$18 | C37: ='balance_raw_16499609'!$C$18 | D37: ='balance_raw_16499609'!$D$18 | E37: ='balance_raw_16499609'!$E$18 | F37: ='balance_raw_16499609'!$F$18 | H37: =IFERROR(B37/$B$37*100,"") | I37: =IFERROR(C37/$B$37*100,"") | J37: =IFERROR(D37/$B$37*100,"") | K37: =IFERROR(E37/$B$37*100,"") | L37: =IFERROR(F37/$B$37*100,"")
A38: Varebeholdninger | B38: ='balance_raw_16499609'!$B$19 | C38: ='balance_raw_16499609'!$C$19 | D38: ='balance_raw_16499609'!$D$19 | E38: ='balance_raw_16499609'!$E$19 | F38: ='balance_raw_16499609'!$F$19 | H38: =IFERROR(B38/$B$38*100,"") | I38: =IFERROR(C38/$B$38*100,"") | J38: =IFERROR(D38/$B$38*100,"") | K38: =IFERROR(E38/$B$38*100,"") | L38: =IFERROR(F38/$B$38*100,"")
A39: Tilgodehavender fra salg og tjenesteydelser | B39: ='balance_raw_16499609'!$B$20 | C39: ='balance_raw_16499609'!$C$20 | D39: ='balance_raw_16499609'!$D$20 | E39: ='balance_raw_16499609'!$E$20 | F39: ='balance_raw_16499609'!$F$20 | H39: =IFERROR(B39/$B$39*100,"") | I39: =IFERROR(C39/$B$39*100,"") | J39: =IFERROR(D39/$B$39*100,"") | K39: =IFERROR(E39/$B$39*100,"") | L39: =IFERROR(F39/$B$39*100,"")
A40: Tilgodehavender hos tilknyttede virksomheder | B40: ='balance_raw_16499609'!$B$21 | C40: ='balance_raw_16499609'!$C$21 | D40: ='balance_raw_16499609'!$D$21 | E40: ='balance_raw_16499609'!$E$21 | F40: ='balance_raw_16499609'!$F$21 | H40: =IFERROR(B40/$B$40*100,"") | I40: =IFERROR(C40/$B$40*100,"") | J40: =IFERROR(D40/$B$40*100,"") | K40: =IFERROR(E40/$B$40*100,"") | L40: =IFERROR(F40/$B$40*100,"")
A41: Andre tilgodehavender | B41: ='balance_raw_16499609'!$B$22 | C41: ='balance_raw_16499609'!$C$22 | D41: ='balance_raw_16499609'!$D$22 | E41: ='balance_raw_16499609'!$E$22 | F41: ='balance_raw_16499609'!$F$22 | H41: =IFERROR(B41/$B$41*100,"") | I41: =IFERROR(C41/$B$41*100,"") | J41: =IFERROR(D41/$B$41*100,"") | K41: =IFERROR(E41/$B$41*100,"") | L41: =IFERROR(F41/$B$41*100,"")
A42: Periodeafgrænsningsposter (aktiver) | B42: ='balance_raw_16499609'!$B$23 | C42: ='balance_raw_16499609'!$C$23 | D42: ='balance_raw_16499609'!$D$23 | E42: ='balance_raw_16499609'!$E$23 | F42: ='balance_raw_16499609'!$F$23 | H42: =IFERROR(B42/$B$42*100,"") | I42: =IFERROR(C42/$B$42*100,"") | J42: =IFERROR(D42/$B$42*100,"") | K42: =IFERROR(E42/$B$42*100,"") | L42: =IFERROR(F42/$B$42*100,"")
A43: Udskudt skatteaktiv | B43: ='balance_raw_16499609'!$B$24 | C43: ='balance_raw_16499609'!$C$24 | D43: ='balance_raw_16499609'!$D$24 | E43: ='balance_raw_16499609'!$E$24 | F43: ='balance_raw_16499609'!$F$24 | H43: =IFERROR(B43/$B$43*100,"") | I43: =IFERROR(C43/$B$43*100,"") | J43: =IFERROR(D43/$B$43*100,"") | K43: =IFERROR(E43/$B$43*100,"") | L43: =IFERROR(F43/$B$43*100,"")
A44: Tilgodehavende skat hos tilknyttede virksomheder | B44: ='balance_raw_16499609'!$B$25 | C44: ='balance_raw_16499609'!$C$25 | D44: ='balance_raw_16499609'!$D$25 | E44: ='balance_raw_16499609'!$E$25 | F44: ='balance_raw_16499609'!$F$25 | H44: =IFERROR(B44/$B$44*100,"") | I44: =IFERROR(C44/$B$44*100,"") | J44: =IFERROR(D44/$B$44*100,"") | K44: =IFERROR(E44/$B$44*100,"") | L44: =IFERROR(F44/$B$44*100,"")
A45: Kortfristede skattetilgodehavender | B45: ='balance_raw_16499609'!$B$26 | C45: ='balance_raw_16499609'!$C$26 | D45: ='balance_raw_16499609'!$D$26 | E45: ='balance_raw_16499609'!$E$26 | F45: ='balance_raw_16499609'!$F$26 | H45: =IFERROR(B45/$B$45*100,"") | I45: =IFERROR(C45/$B$45*100,"") | J45: =IFERROR(D45/$B$45*100,"") | K45: =IFERROR(E45/$B$45*100,"") | L45: =IFERROR(F45/$B$45*100,"")
A46: Tilgodehavender | B46: ='balance_raw_16499609'!$B$27 | C46: ='balance_raw_16499609'!$C$27 | D46: ='balance_raw_16499609'!$D$27 | E46: ='balance_raw_16499609'!$E$27 | F46: ='balance_raw_16499609'!$F$27 | H46: =IFERROR(B46/$B$46*100,"") | I46: =IFERROR(C46/$B$46*100,"") | J46: =IFERROR(D46/$B$46*100,"") | K46: =IFERROR(E46/$B$46*100,"") | L46: =IFERROR(F46/$B$46*100,"")
A47: Værdipapirer | B47: ='balance_raw_16499609'!$B$28 | C47: ='balance_raw_16499609'!$C$28 | D47: ='balance_raw_16499609'!$D$28 | E47: ='balance_raw_16499609'!$E$28 | F47: ='balance_raw_16499609'!$F$28 | H47: =IFERROR(B47/$B$47*100,"") | I47: =IFERROR(C47/$B$47*100,"") | J47: =IFERROR(D47/$B$47*100,"") | K47: =IFERROR(E47/$B$47*100,"") | L47: =IFERROR(F47/$B$47*100,"")
A48: Likvide beholdninger | B48: ='balance_raw_16499609'!$B$29 | C48: ='balance_raw_16499609'!$C$29 | D48: ='balance_raw_16499609'!$D$29 | E48: ='balance_raw_16499609'!$E$29 | F48: ='balance_raw_16499609'!$F$29 | H48: =IFERROR(B48/$B$48*100,"") | I48: =IFERROR(C48/$B$48*100,"") | J48: =IFERROR(D48/$B$48*100,"") | K48: =IFERROR(E48/$B$48*100,"") | L48: =IFERROR(F48/$B$48*100,"")
A49: Omsætningsaktiver | B49: ='balance_raw_16499609'!$B$30 | C49: ='balance_raw_16499609'!$C$30 | D49: ='balance_raw_16499609'!$D$30 | E49: ='balance_raw_16499609'!$E$30 | F49: ='balance_raw_16499609'!$F$30 | H49: =IFERROR(B49/$B$49*100,"") | I49: =IFERROR(C49/$B$49*100,"") | J49: =IFERROR(D49/$B$49*100,"") | K49: =IFERROR(E49/$B$49*100,"") | L49: =IFERROR(F49/$B$49*100,"")
A50: Aktiver | B50: ='balance_raw_16499609'!$B$31 | C50: ='balance_raw_16499609'!$C$31 | D50: ='balance_raw_16499609'!$D$31 | E50: ='balance_raw_16499609'!$E$31 | F50: ='balance_raw_16499609'!$F$31 | H50: =IFERROR(B50/$B$50*100,"") | I50: =IFERROR(C50/$B$50*100,"") | J50: =IFERROR(D50/$B$50*100,"") | K50: =IFERROR(E50/$B$50*100,"") | L50: =IFERROR(F50/$B$50*100,"")
A52: PASSIVER t.kr. | B52: 2021 | C52: 2022 | D52: 2023 | E52: 2024 | F52: 2025 | H52: 2021 | I52: 2022 | J52: 2023 | K52: 2024 | L52: 2025
A53: Selskabskapital | B53: ='balance_raw_16499609'!$B$32 | C53: ='balance_raw_16499609'!$C$32 | D53: ='balance_raw_16499609'!$D$32 | E53: ='balance_raw_16499609'!$E$32 | F53: ='balance_raw_16499609'!$F$32 | H53: =IFERROR(B53/$B$53*100,"") | I53: =IFERROR(C53/$B$53*100,"") | J53: =IFERROR(D53/$B$53*100,"") | K53: =IFERROR(E53/$B$53*100,"") | L53: =IFERROR(F53/$B$53*100,"")
A54: Reserve for nettoopskrivning (indre værdis metode) | B54: ='balance_raw_16499609'!$B$33 | C54: ='balance_raw_16499609'!$C$33 | D54: ='balance_raw_16499609'!$D$33 | E54: ='balance_raw_16499609'!$E$33 | F54: ='balance_raw_16499609'!$F$33 | H54: =IFERROR(B54/$B$54*100,"") | I54: =IFERROR(C54/$B$54*100,"") | J54: =IFERROR(D54/$B$54*100,"") | K54: =IFERROR(E54/$B$54*100,"") | L54: =IFERROR(F54/$B$54*100,"")
A55: Reserve for udviklingsomkostninger | B55: ='balance_raw_16499609'!$B$34 | C55: ='balance_raw_16499609'!$C$34 | D55: ='balance_raw_16499609'!$D$34 | E55: ='balance_raw_16499609'!$E$34 | F55: ='balance_raw_16499609'!$F$34 | H55: =IFERROR(B55/$B$55*100,"") | I55: =IFERROR(C55/$B$55*100,"") | J55: =IFERROR(D55/$B$55*100,"") | K55: =IFERROR(E55/$B$55*100,"") | L55: =IFERROR(F55/$B$55*100,"")
A56: Reserve for sikringstransaktioner | B56: ='balance_raw_16499609'!$B$35 | C56: ='balance_raw_16499609'!$C$35 | D56: ='balance_raw_16499609'!$D$35 | E56: ='balance_raw_16499609'!$E$35 | F56: ='balance_raw_16499609'!$F$35 | H56: =IFERROR(B56/$B$56*100,"") | I56: =IFERROR(C56/$B$56*100,"") | J56: =IFERROR(D56/$B$56*100,"") | K56: =IFERROR(E56/$B$56*100,"") | L56: =IFERROR(F56/$B$56*100,"")
A57: Andre reserver | B57: ='balance_raw_16499609'!$B$36 | C57: ='balance_raw_16499609'!$C$36 | D57: ='balance_raw_16499609'!$D$36 | E57: ='balance_raw_16499609'!$E$36 | F57: ='balance_raw_16499609'!$F$36 | H57: =IFERROR(B57/$B$57*100,"") | I57: =IFERROR(C57/$B$57*100,"") | J57: =IFERROR(D57/$B$57*100,"") | K57: =IFERROR(E57/$B$57*100,"") | L57: =IFERROR(F57/$B$57*100,"")
A58: Overført resultat | B58: ='balance_raw_16499609'!$B$37 | C58: ='balance_raw_16499609'!$C$37 | D58: ='balance_raw_16499609'!$D$37 | E58: ='balance_raw_16499609'!$E$37 | F58: ='balance_raw_16499609'!$F$37 | H58: =IFERROR(B58/$B$58*100,"") | I58: =IFERROR(C58/$B$58*100,"") | J58: =IFERROR(D58/$B$58*100,"") | K58: =IFERROR(E58/$B$58*100,"") | L58: =IFERROR(F58/$B$58*100,"")
A59: Egenkapital i alt | B59: ='balance_raw_16499609'!$B$38 | C59: ='balance_raw_16499609'!$C$38 | D59: ='balance_raw_16499609'!$D$38 | E59: ='balance_raw_16499609'!$E$38 | F59: ='balance_raw_16499609'!$F$38 | H59: =IFERROR(B59/$B$59*100,"") | I59: =IFERROR(C59/$B$59*100,"") | J59: =IFERROR(D59/$B$59*100,"") | K59: =IFERROR(E59/$B$59*100,"") | L59: =IFERROR(F59/$B$59*100,"")
A60: Hensættelse til udskudt skat | B60: ='balance_raw_16499609'!$B$39 | C60: ='balance_raw_16499609'!$C$39 | D60: ='balance_raw_16499609'!$D$39 | E60: ='balance_raw_16499609'!$E$39 | F60: ='balance_raw_16499609'!$F$39 | H60: =IFERROR(B60/$B$60*100,"") | I60: =IFERROR(C60/$B$60*100,"") | J60: =IFERROR(D60/$B$60*100,"") | K60: =IFERROR(E60/$B$60*100,"") | L60: =IFERROR(F60/$B$60*100,"")
A61: Hensatte forpligtelser | B61: ='balance_raw_16499609'!$B$40 | C61: ='balance_raw_16499609'!$C$40 | D61: ='balance_raw_16499609'!$D$40 | E61: ='balance_raw_16499609'!$E$40 | F61: ='balance_raw_16499609'!$F$40 | H61: =IFERROR(B61/$B$61*100,"") | I61: =IFERROR(C61/$B$61*100,"") | J61: =IFERROR(D61/$B$61*100,"") | K61: =IFERROR(E61/$B$61*100,"") | L61: =IFERROR(F61/$B$61*100,"")
A62: Ansvarlig lånekapital (langfristet) | B62: ='balance_raw_16499609'!$B$41 | C62: ='balance_raw_16499609'!$C$41 | D62: ='balance_raw_16499609'!$D$41 | E62: ='balance_raw_16499609'!$E$41 | F62: ='balance_raw_16499609'!$F$41 | H62: =IFERROR(B62/$B$62*100,"") | I62: =IFERROR(C62/$B$62*100,"") | J62: =IFERROR(D62/$B$62*100,"") | K62: =IFERROR(E62/$B$62*100,"") | L62: =IFERROR(F62/$B$62*100,"")
A63: Langfristede lån | B63: ='balance_raw_16499609'!$B$42 | C63: ='balance_raw_16499609'!$C$42 | D63: ='balance_raw_16499609'!$D$42 | E63: ='balance_raw_16499609'!$E$42 | F63: ='balance_raw_16499609'!$F$42 | H63: =IFERROR(B63/$B$63*100,"") | I63: =IFERROR(C63/$B$63*100,"") | J63: =IFERROR(D63/$B$63*100,"") | K63: =IFERROR(E63/$B$63*100,"") | L63: =IFERROR(F63/$B$63*100,"")
A64: Leasingforpligtelser (langfristet) | B64: ='balance_raw_16499609'!$B$43 | C64: ='balance_raw_16499609'!$C$43 | D64: ='balance_raw_16499609'!$D$43 | E64: ='balance_raw_16499609'!$E$43 | F64: ='balance_raw_16499609'!$F$43 | H64: =IFERROR(B64/$B$64*100,"") | I64: =IFERROR(C64/$B$64*100,"") | J64: =IFERROR(D64/$B$64*100,"") | K64: =IFERROR(E64/$B$64*100,"") | L64: =IFERROR(F64/$B$64*100,"")
A65: Anden gæld (langfristet) | B65: ='balance_raw_16499609'!$B$44 | C65: ='balance_raw_16499609'!$C$44 | D65: ='balance_raw_16499609'!$D$44 | E65: ='balance_raw_16499609'!$E$44 | F65: ='balance_raw_16499609'!$F$44 | H65: =IFERROR(B65/$B$65*100,"") | I65: =IFERROR(C65/$B$65*100,"") | J65: =IFERROR(D65/$B$65*100,"") | K65: =IFERROR(E65/$B$65*100,"") | L65: =IFERROR(F65/$B$65*100,"")
A66: Langfristede gældsforpligtelser | B66: ='balance_raw_16499609'!$B$45 | C66: ='balance_raw_16499609'!$C$45 | D66: ='balance_raw_16499609'!$D$45 | E66: ='balance_raw_16499609'!$E$45 | F66: ='balance_raw_16499609'!$F$45 | H66: =IFERROR(B66/$B$66*100,"") | I66: =IFERROR(C66/$B$66*100,"") | J66: =IFERROR(D66/$B$66*100,"") | K66: =IFERROR(E66/$B$66*100,"") | L66: =IFERROR(F66/$B$66*100,"")
A67: Ansvarlig lånekapital (kortfristet) | B67: ='balance_raw_16499609'!$B$46 | C67: ='balance_raw_16499609'!$C$46 | D67: ='balance_raw_16499609'!$D$46 | E67: ='balance_raw_16499609'!$E$46 | F67: ='balance_raw_16499609'!$F$46 | H67: =IFERROR(B67/$B$67*100,"") | I67: =IFERROR(C67/$B$67*100,"") | J67: =IFERROR(D67/$B$67*100,"") | K67: =IFERROR(E67/$B$67*100,"") | L67: =IFERROR(F67/$B$67*100,"")
A68: Kortfristet del af langfristede gældsforpligtelser | B68: ='balance_raw_16499609'!$B$47 | C68: ='balance_raw_16499609'!$C$47 | D68: ='balance_raw_16499609'!$D$47 | E68: ='balance_raw_16499609'!$E$47 | F68: ='balance_raw_16499609'!$F$47 | H68: =IFERROR(B68/$B$68*100,"") | I68: =IFERROR(C68/$B$68*100,"") | J68: =IFERROR(D68/$B$68*100,"") | K68: =IFERROR(E68/$B$68*100,"") | L68: =IFERROR(F68/$B$68*100,"")
A69: Kreditinstitutter | B69: ='balance_raw_16499609'!$B$48 | C69: ='balance_raw_16499609'!$C$48 | D69: ='balance_raw_16499609'!$D$48 | E69: ='balance_raw_16499609'!$E$48 | F69: ='balance_raw_16499609'!$F$48 | H69: =IFERROR(B69/$B$69*100,"") | I69: =IFERROR(C69/$B$69*100,"") | J69: =IFERROR(D69/$B$69*100,"") | K69: =IFERROR(E69/$B$69*100,"") | L69: =IFERROR(F69/$B$69*100,"")
A70: Leasingforpligtelser (kortfristet) | B70: ='balance_raw_16499609'!$B$49 | C70: ='balance_raw_16499609'!$C$49 | D70: ='balance_raw_16499609'!$D$49 | E70: ='balance_raw_16499609'!$E$49 | F70: ='balance_raw_16499609'!$F$49 | H70: =IFERROR(B70/$B$70*100,"") | I70: =IFERROR(C70/$B$70*100,"") | J70: =IFERROR(D70/$B$70*100,"") | K70: =IFERROR(E70/$B$70*100,"") | L70: =IFERROR(F70/$B$70*100,"")
A71: Leverandører af varer og tjenesteydelser | B71: ='balance_raw_16499609'!$B$50 | C71: ='balance_raw_16499609'!$C$50 | D71: ='balance_raw_16499609'!$D$50 | E71: ='balance_raw_16499609'!$E$50 | F71: ='balance_raw_16499609'!$F$50 | H71: =IFERROR(B71/$B$71*100,"") | I71: =IFERROR(C71/$B$71*100,"") | J71: =IFERROR(D71/$B$71*100,"") | K71: =IFERROR(E71/$B$71*100,"") | L71: =IFERROR(F71/$B$71*100,"")
A72: Gæld til tilknyttede virksomheder | B72: ='balance_raw_16499609'!$B$51 | C72: ='balance_raw_16499609'!$C$51 | D72: ='balance_raw_16499609'!$D$51 | E72: ='balance_raw_16499609'!$E$51 | F72: ='balance_raw_16499609'!$F$51 | H72: =IFERROR(B72/$B$72*100,"") | I72: =IFERROR(C72/$B$72*100,"") | J72: =IFERROR(D72/$B$72*100,"") | K72: =IFERROR(E72/$B$72*100,"") | L72: =IFERROR(F72/$B$72*100,"")
A73: Gæld til selskabsdeltagere og ledelse | B73: ='balance_raw_16499609'!$B$52 | C73: ='balance_raw_16499609'!$C$52 | D73: ='balance_raw_16499609'!$D$52 | E73: ='balance_raw_16499609'!$E$52 | F73: ='balance_raw_16499609'!$F$52 | H73: =IFERROR(B73/$B$73*100,"") | I73: =IFERROR(C73/$B$73*100,"") | J73: =IFERROR(D73/$B$73*100,"") | K73: =IFERROR(E73/$B$73*100,"") | L73: =IFERROR(F73/$B$73*100,"")
A74: Selskabsskat | B74: ='balance_raw_16499609'!$B$53 | C74: ='balance_raw_16499609'!$C$53 | D74: ='balance_raw_16499609'!$D$53 | E74: ='balance_raw_16499609'!$E$53 | F74: ='balance_raw_16499609'!$F$53 | H74: =IFERROR(B74/$B$74*100,"") | I74: =IFERROR(C74/$B$74*100,"") | J74: =IFERROR(D74/$B$74*100,"") | K74: =IFERROR(E74/$B$74*100,"") | L74: =IFERROR(F74/$B$74*100,"")
A75: Gæld til tilknyttede virksomheder vedr. selskabsskat | B75: ='balance_raw_16499609'!$B$54 | C75: ='balance_raw_16499609'!$C$54 | D75: ='balance_raw_16499609'!$D$54 | E75: ='balance_raw_16499609'!$E$54 | F75: ='balance_raw_16499609'!$F$54 | H75: =IFERROR(B75/$B$75*100,"") | I75: =IFERROR(C75/$B$75*100,"") | J75: =IFERROR(D75/$B$75*100,"") | K75: =IFERROR(E75/$B$75*100,"") | L75: =IFERROR(F75/$B$75*100,"")
A76: Anden gæld (kortfristet) | B76: ='balance_raw_16499609'!$B$55 | C76: ='balance_raw_16499609'!$C$55 | D76: ='balance_raw_16499609'!$D$55 | E76: ='balance_raw_16499609'!$E$55 | F76: ='balance_raw_16499609'!$F$55 | H76: =IFERROR(B76/$B$76*100,"") | I76: =IFERROR(C76/$B$76*100,"") | J76: =IFERROR(D76/$B$76*100,"") | K76: =IFERROR(E76/$B$76*100,"") | L76: =IFERROR(F76/$B$76*100,"")
A77: Periodeafgrænsningsposter (passiver) | B77: ='balance_raw_16499609'!$B$56 | C77: ='balance_raw_16499609'!$C$56 | D77: ='balance_raw_16499609'!$D$56 | E77: ='balance_raw_16499609'!$E$56 | F77: ='balance_raw_16499609'!$F$56 | H77: =IFERROR(B77/$B$77*100,"") | I77: =IFERROR(C77/$B$77*100,"") | J77: =IFERROR(D77/$B$77*100,"") | K77: =IFERROR(E77/$B$77*100,"") | L77: =IFERROR(F77/$B$77*100,"")
A78: Kortfristede gældsforpligtelser | B78: ='balance_raw_16499609'!$B$57 | C78: ='balance_raw_16499609'!$C$57 | D78: ='balance_raw_16499609'!$D$57 | E78: ='balance_raw_16499609'!$E$57 | F78: ='balance_raw_16499609'!$F$57 | H78: =IFERROR(B78/$B$78*100,"") | I78: =IFERROR(C78/$B$78*100,"") | J78: =IFERROR(D78/$B$78*100,"") | K78: =IFERROR(E78/$B$78*100,"") | L78: =IFERROR(F78/$B$78*100,"")
A79: Gældsforpligtelser | B79: ='balance_raw_16499609'!$B$58 | C79: ='balance_raw_16499609'!$C$58 | D79: ='balance_raw_16499609'!$D$58 | E79: ='balance_raw_16499609'!$E$58 | F79: ='balance_raw_16499609'!$F$58 | H79: =IFERROR(B79/$B$79*100,"") | I79: =IFERROR(C79/$B$79*100,"") | J79: =IFERROR(D79/$B$79*100,"") | K79: =IFERROR(E79/$B$79*100,"") | L79: =IFERROR(F79/$B$79*100,"")
A80: Passiver | B80: ='balance_raw_16499609'!$B$59 | C80: ='balance_raw_16499609'!$C$59 | D80: ='balance_raw_16499609'!$D$59 | E80: ='balance_raw_16499609'!$E$59 | F80: ='balance_raw_16499609'!$F$59 | H80: =IFERROR(B80/$B$80*100,"") | I80: =IFERROR(C80/$B$80*100,"") | J80: =IFERROR(D80/$B$80*100,"") | K80: =IFERROR(E80/$B$80*100,"") | L80: =IFERROR(F80/$B$80*100,"")
A82: NØGLEOPLYSNINGER | B82: 2021 | C82: 2022 | D82: 2023 | E82: 2024 | F82: 2025
A83: Gns. antal medarbejdere | B83: ='res_raw_16499609'!$B$17 | C83: ='res_raw_16499609'!$C$17 | D83: ='res_raw_16499609'!$D$17 | E83: ='res_raw_16499609'!$E$17 | F83: ='res_raw_16499609'!$F$17 | H83: =IFERROR(B83/$B$83*100,"") | I83: =IFERROR(C83/$B$83*100,"") | J83: =IFERROR(D83/$B$83*100,"") | K83: =IFERROR(E83/$B$83*100,"") | L83: =IFERROR(F83/$B$83*100,"")
A84: Investering i materielle anlægsaktiver | B84: ='res_raw_16499609'!$B$18 | C84: ='res_raw_16499609'!$C$18 | D84: ='res_raw_16499609'!$D$18 | E84: ='res_raw_16499609'!$E$18 | F84: ='res_raw_16499609'!$F$18 | H84: =IFERROR(B84/$B$84*100,"") | I84: =IFERROR(C84/$B$84*100,"") | J84: =IFERROR(D84/$B$84*100,"") | K84: =IFERROR(E84/$B$84*100,"") | L84: =IFERROR(F84/$B$84*100,"")
A86: NØGLETAL | B86: 2021 | C86: 2022 | D86: 2023 | E86: 2024 | F86: 2025
A87: Afkastningsgrad, % | B87: =IFERROR(($B$11+$B$13+$B$12)/$B$50*100,"") | C87: =IFERROR(($C$11+$C$13+$C$12)/$C$50*100,"") | D87: =IFERROR(($D$11+$D$13+$D$12)/$D$50*100,"") | E87: =IFERROR(($E$11+$E$13+$E$12)/$E$50*100,"") | F87: =IFERROR(($F$11+$F$13+$F$12)/$F$50*100,"")
A88: Overskudsgrad, % | B88: =IFERROR(($B$11+$B$13+$B$12)/$B$4*100,"") | C88: =IFERROR(($C$11+$C$13+$C$12)/$C$4*100,"") | D88: =IFERROR(($D$11+$D$13+$D$12)/$D$4*100,"") | E88: =IFERROR(($E$11+$E$13+$E$12)/$E$4*100,"") | F88: =IFERROR(($F$11+$F$13+$F$12)/$F$4*100,"")
A89: Aktivernes omsætningshastighed, gange | B89: =IFERROR($B$4/$B$50,"") | C89: =IFERROR($C$4/$C$50,"") | D89: =IFERROR($D$4/$D$50,"") | E89: =IFERROR($E$4/$E$50,"") | F89: =IFERROR($F$4/$F$50,"")
A90: Egenkapitalens forrentning, % | B90: =IFERROR($B$16/$B$59*100,"") | C90: =IFERROR($C$16/$C$59*100,"") | D90: =IFERROR($D$16/$D$59*100,"") | E90: =IFERROR($E$16/$E$59*100,"") | F90: =IFERROR($F$16/$F$59*100,"")
A91: Gældsrente, % | B91: =IFERROR($B$14/($B$80-$B$59)*100,"") | C91: =IFERROR($C$14/($C$80-$C$59)*100,"") | D91: =IFERROR($D$14/($D$80-$D$59)*100,"") | E91: =IFERROR($E$14/($E$80-$E$59)*100,"") | F91: =IFERROR($F$14/($F$80-$F$59)*100,"")
A92: Soliditetsgrad, % | B92: =IFERROR($B$59/$B$50*100,"") | C92: =IFERROR($C$59/$C$50*100,"") | D92: =IFERROR($D$59/$D$50*100,"") | E92: =IFERROR($E$59/$E$50*100,"") | F92: =IFERROR($F$59/$F$50*100,"")
A93: Gearing | B93: =IFERROR(($B$80-$B$59)/$B$59,"") | C93: =IFERROR(($C$80-$C$59)/$C$59,"") | D93: =IFERROR(($D$80-$D$59)/$D$59,"") | E93: =IFERROR(($E$80-$E$59)/$E$59,"") | F93: =IFERROR(($F$80-$F$59)/$F$59,"")
A94: Likviditetsgrad, % | B94: =IFERROR($B$49/$B$78*100,"") | C94: =IFERROR($C$49/$C$78*100,"") | D94: =IFERROR($D$49/$D$78*100,"") | E94: =IFERROR($E$49/$E$78*100,"") | F94: =IFERROR($F$49/$F$78*100,"")
A95: Rentemarginal, % | B95: =IFERROR(B87-B91,"") | C95: =IFERROR(C87-C91,"") | D95: =IFERROR(D87-D91,"") | E95: =IFERROR(E87-E91,"") | F95: =IFERROR(F87-F91,"")
A96: Gældsandel, % | B96: =IFERROR(($B$80-$B$59)/$B$50*100,"") | C96: =IFERROR(($C$80-$C$59)/$C$50*100,"") | D96: =IFERROR(($D$80-$D$59)/$D$50*100,"") | E96: =IFERROR(($E$80-$E$59)/$E$50*100,"") | F96: =IFERROR(($F$80-$F$59)/$F$50*100,"")
A97: Kapitalbindingsgrad, % | B97: =IFERROR($B$34/($B$59+$B$66)*100,"") | C97: =IFERROR($C$34/($C$59+$C$66)*100,"") | D97: =IFERROR($D$34/($D$59+$D$66)*100,"") | E97: =IFERROR($E$34/($E$59+$E$66)*100,"") | F97: =IFERROR($F$34/($F$59+$F$66)*100,"")
A99: PENGESTRØMSOPGØRELSE t.kr.
A100: Pengestrømme fra driftsaktivitet | B100: ='pengestrom_raw_16499609'!$B$2 | C100: ='pengestrom_raw_16499609'!$C$2 | D100: ='pengestrom_raw_16499609'!$D$2 | E100: ='pengestrom_raw_16499609'!$E$2 | F100: ='pengestrom_raw_16499609'!$F$2
A101: Pengestrømme fra investeringsaktivitet | B101: ='pengestrom_raw_16499609'!$B$3 | C101: ='pengestrom_raw_16499609'!$C$3 | D101: ='pengestrom_raw_16499609'!$D$3 | E101: ='pengestrom_raw_16499609'!$E$3 | F101: ='pengestrom_raw_16499609'!$F$3
A102: Pengestrømme fra finansieringsaktivitet | B102: ='pengestrom_raw_16499609'!$B$4 | C102: ='pengestrom_raw_16499609'!$C$4 | D102: ='pengestrom_raw_16499609'!$D$4 | E102: ='pengestrom_raw_16499609'!$E$4 | F102: ='pengestrom_raw_16499609'!$F$4
A103: Årets pengestrøm (rapporteret) | B103: ='pengestrom_raw_16499609'!$B$5 | C103: ='pengestrom_raw_16499609'!$C$5 | D103: ='pengestrom_raw_16499609'!$D$5 | E103: ='pengestrom_raw_16499609'!$E$5 | F103: ='pengestrom_raw_16499609'!$F$5
A104: Krydstjek: drift + inv. + fin. = årets pengestrøm | B104: =IF(ABS(('pengestrom_raw_16499609'!$B$2+'pengestrom_raw_16499609'!$B$3+'pengestrom_raw_16499609'!$B$4)-'pengestrom_raw_16499609'!$B$5)<=2,"✓","⚠ "&TEXT(('pengestrom_raw_16499609'!$B$2+'pengestrom_raw_16499609'!$B$3+'pengestrom_raw_16499609'!$B$4)-'pengestrom_raw_16499609'!$B$5,"+#,##0;-#,##0")) | C104: =IF(ABS(('pengestrom_raw_16499609'!$C$2+'pengestrom_raw_16499609'!$C$3+'pengestrom_raw_16499609'!$C$4)-'pengestrom_raw_16499609'!$C$5)<=2,"✓","⚠ "&TEXT(('pengestrom_raw_16499609'!$C$2+'pengestrom_raw_16499609'!$C$3+'pengestrom_raw_16499609'!$C$4)-'pengestrom_raw_16499609'!$C$5,"+#,##0;-#,##0")) | D104: =IF(ABS(('pengestrom_raw_16499609'!$D$2+'pengestrom_raw_16499609'!$D$3+'pengestrom_raw_16499609'!$D$4)-'pengestrom_raw_16499609'!$D$5)<=2,"✓","⚠ "&TEXT(('pengestrom_raw_16499609'!$D$2+'pengestrom_raw_16499609'!$D$3+'pengestrom_raw_16499609'!$D$4)-'pengestrom_raw_16499609'!$D$5,"+#,##0;-#,##0")) | E104: =IF(ABS(('pengestrom_raw_16499609'!$E$2+'pengestrom_raw_16499609'!$E$3+'pengestrom_raw_16499609'!$E$4)-'pengestrom_raw_16499609'!$E$5)<=2,"✓","⚠ "&TEXT(('pengestrom_raw_16499609'!$E$2+'pengestrom_raw_16499609'!$E$3+'pengestrom_raw_16499609'!$E$4)-'pengestrom_raw_16499609'!$E$5,"+#,##0;-#,##0")) | F104: =IF(ABS(('pengestrom_raw_16499609'!$F$2+'pengestrom_raw_16499609'!$F$3+'pengestrom_raw_16499609'!$F$4)-'pengestrom_raw_16499609'!$F$5)<=2,"✓","⚠ "&TEXT(('pengestrom_raw_16499609'!$F$2+'pengestrom_raw_16499609'!$F$3+'pengestrom_raw_16499609'!$F$4)-'pengestrom_raw_16499609'!$F$5,"+#,##0;-#,##0"))

Sheet res_raw_16499609
A1: Munck Gruppen A/S (CVR 16499609) — Resultatopgørelse & nøgleoplysninger (t.kr.) | B1: 2021 | C1: 2022 | D1: 2023 | E1: 2024 | F1: 2025
A2: Nettoomsætning | B2: 2449292 | C2: 3089499 | D2: 3261760 | E2: 4178334 | F2: 4868635
A3: Produktionsomkostninger | B3: 2204242 | C3: 2838459 | D3: 2884377 | E3: 3599912 | F3: 4221459
A4: Bruttoresultat | B4: 245050 | C4: 251040 | D4: 377383 | E4: 578422 | F4: 647176
A5: Salgs- og distributionsomkostninger
A6: Administrationsomkostninger | B6: 146664 | C6: 115458 | D6: 165289 | E6: 106968 | F6: 122221
A7: Andre driftsindtægter | B7: 36564 | C7: 16337 | D7: 4797 | E7: 12928 | F7: 43237
A8: Andre driftsomkostninger | E8: 594 | F8: 750
A9: Resultat af primær drift
A10: Indtægter af kapitalandele, dattervirksomheder | B10: -767 | C10: -1399 | D10: 4255 | E10: 0 | F10: 0
A11: Finansielle indtægter | B11: 10966 | C11: 13017 | D11: 6804 | E11: 16032 | F11: 21906
A12: Finansielle omkostninger | B12: 18760 | C12: 13489 | D12: 6905 | E12: 7333 | F12: 11052
A13: Finansielle poster, netto
A14: Resultat før skat | E14: 490922 | F14: 579416
A15: Skat af årets resultat | B15: 41942 | C15: 34570 | D15: 45446 | E15: 116995 | F15: 125695
A16: Årets resultat | B16: 89964 | C16: 81235 | D16: 146732 | E16: 317875 | F16: 397727
A17: Gns. antal medarbejdere | B17: 1313 | C17: 1435 | D17: 1561 | E17: 1611 | F17: 1608
A18: Investering i materielle anlægsaktiver | B18: 105000 | C18: 102000 | D18: 170000 | E18: 273000 | F18: 175000

Sheet balance_raw_16499609
A1: Munck Gruppen A/S (CVR 16499609) — Balance (t.kr.) | B1: 2021 | C1: 2022 | D1: 2023 | E1: 2024 | F1: 2025
A2: Udviklingsprojekter
A3: Patenter, varemærker mv. | B3: 3918 | C3: 6209 | D3: 6196 | E3: 3108 | F3: 600
A4: Goodwill | B4: 61 | C4: 57 | D4: 36 | E4: 14 | F4: 1
A5: Immaterielle anlægsaktiver | B5: 3979 | C5: 7266 | D5: 6232 | E5: 3122 | F5: 601
A6: Grunde og bygninger | B6: 151522 | C6: 124633 | D6: 109011 | E6: 124669 | F6: 121260
A7: Produktionsanlæg og maskiner | B7: 38325 | C7: 39441 | D7: 85571 | E7: 111833 | F7: 115044
A8: Driftsmateriel og inventar | B8: 299249 | C8: 295599 | D8: 288185 | E8: 354835 | F8: 326813
A9: Indretning af lejede lokaler
A10: Forudbetaling og anlægsaktiver under opførelse | B10: 4883 | C10: 2718 | D10: 22303 | E10: 38542 | F10: 19491
A11: Materielle anlægsaktiver | B11: 493979 | C11: 462391 | D11: 505070 | E11: 629879 | F11: 582608
A12: Kapitalandele, dattervirksomheder | B12: 0 | C12: 0 | D12: 0 | E12: 0 | F12: 0
A13: Deposita | B13: 759 | C13: 794 | D13: 759 | E13: 805 | F13: 811
A14: Finansielle anlægsaktiver | B14: 94679 | C14: 31435 | D14: 22911 | E14: 12228 | F14: 11382
A15: Anlægsaktiver | B15: 592637 | C15: 501092 | D15: 534213 | E15: 645229 | F15: 594591
A16: Råvarer og hjælpematerialer | B16: 101060 | C16: 114757 | D16: 147046 | E16: 98997 | F16: 80302
A17: Varer under fremstilling | B17: 107357 | C17: 175069 | D17: 162374 | E17: 207350 | F17: 195563
A18: Færdigvarer og handelsvarer
A19: Varebeholdninger | B19: 101060 | C19: 114757 | D19: 147046 | E19: 98997 | F19: 80302
A20: Tilgodehavender fra salg og tjenesteydelser | B20: 570579 | C20: 688645 | D20: 733302 | E20: 1028637 | F20: 875455
A21: Tilgodehavender hos tilknyttede virksomheder | B21: 6585 | C21: 1804 | D21: 0 | E21: 0 | F21: 198
A22: Andre tilgodehavender | B22: 233577 | C22: 40894 | D22: 21565 | E22: 21782 | F22: 20664
A23: Periodeafgrænsningsposter (aktiver) | B23: 172 | C23: 4661 | D23: 3093 | E23: 3198 | F23: 8550
A24: Udskudt skatteaktiv | B24: 1934 | C24: 0 | E24: 496 | F24: 6909
A25: Tilgodehavende skat hos tilknyttede virksomheder | B25: 69 | C25: 7946 | D25: 0 | E25: 0 | F25: 0
A26: Kortfristede skattetilgodehavender | B26: 0 | D26: 757 | E26: 0 | F26: 518
A27: Tilgodehavender | B27: 951459 | C27: 926024 | D27: 933386 | E27: 1269290 | F27: 1114339
A28: Værdipapirer | E28: 0 | F28: 26641
A29: Likvide beholdninger | B29: 25578 | C29: 80733 | D29: 117562 | E29: 743986 | F29: 793237
A30: Omsætningsaktiver | B30: 1078097 | C30: 1121514 | D30: 1197994 | E30: 2112273 | F30: 2014519
A31: Aktiver | B31: 1670734 | C31: 1622606 | D31: 1732207 | E31: 2757502 | F31: 2609110
A32: Selskabskapital | B32: 518 | C32: 517 | D32: 517 | E32: 517 | F32: 517
A33: Reserve for nettoopskrivning (indre værdis metode) | B33: 0 | C33: 0 | D33: 0 | E33: 0 | F33: 0
A34: Reserve for udviklingsomkostninger
A35: Reserve for sikringstransaktioner
A36: Andre reserver
A37: Overført resultat | B37: 529384 | C37: 555670 | D37: 599646 | E37: 723922 | F37: 913632
A38: Egenkapital i alt | B38: 632030 | C38: 685047 | D38: 791750 | E38: 1049944 | F38: 1244156
A39: Hensættelse til udskudt skat | C39: 39820 | D39: 32943 | E39: 104427 | F39: 43896
A40: Hensatte forpligtelser | B40: 47406 | C40: 152598 | D40: 139946 | E40: 273363 | F40: 279226
A41: Ansvarlig lånekapital (langfristet)
A42: Langfristede lån | B42: 76719 | C42: 50139 | D42: 47112 | E42: 39044 | F42: 36378
A43: Leasingforpligtelser (langfristet) | B43: 40215 | C43: 25241 | D43: 0
A44: Anden gæld (langfristet)
A45: Langfristede gældsforpligtelser | B45: 116934 | C45: 75380 | D45: 47112 | E45: 39044 | F45: 36378
A46: Ansvarlig lånekapital (kortfristet)
A47: Kortfristet del af langfristede gældsforpligtelser | B47: 21056 | C47: 24030 | D47: 27993 | E47: 2619 | F47: 2656
A48: Kreditinstitutter | B48: 24706 | C48: 24 | D48: 0 | E48: 889 | F48: 11
A49: Leasingforpligtelser (kortfristet)
A50: Leverandører af varer og tjenesteydelser | B50: 252043 | C50: 248352 | D50: 271032 | E50: 499116 | F50: 546573
A51: Gæld til tilknyttede virksomheder | B51: 0 | C51: 0 | D51: 0 | E51: 3202 | F51: 11124
A52: Gæld til selskabsdeltagere og ledelse
A53: Selskabsskat | B53: 8582 | C53: 1003 | D53: 174 | E53: 123 | F53: 407
A54: Gæld til tilknyttede virksomheder vedr. selskabsskat | B54: 31634 | C54: 15134 | D54: 50553 | E54: 42005 | F54: 23695
A55: Anden gæld (kortfristet) | B55: 126213 | C55: 109553 | D55: 134529 | E55: 151325 | F55: 151825
A56: Periodeafgrænsningsposter (passiver) | B56: 665 | C56: 1002 | D56: 1247 | E56: 241 | F56: 642
A57: Kortfristede gældsforpligtelser | B57: 874364 | C57: 709581 | D57: 753399 | E57: 1395151 | F57: 1049350
A58: Gældsforpligtelser | B58: 991298 | C58: 784961 | D58: 800511 | E58: 1434195 | F58: 1085728
A59: Passiver | B59: 1670734 | C59: 1622606 | D59: 1732207 | E59: 2757502 | F59: 2609110

Sheet pengestrom_raw_16499609
A1: Munck Gruppen A/S (CVR 16499609) — Pengestrømsopgørelse (t.kr.) | B1: 2021 | C1: 2022 | D1: 2023 | E1: 2024 | F1: 2025
A2: Pengestrømme fra driftsaktivitet | B2: 31167 | C2: 150246 | D2: 282202 | E2: 1055290 | F2: 602891
A3: Pengestrømme fra investeringsaktivitet | B3: 14986 | C3: 36251 | D3: -146254 | E3: -223739 | F3: -82599
A4: Pengestrømme fra finansieringsaktivitet | B4: -18308 | C4: -106299 | D4: -90482 | E4: -154687 | F4: -240940
A5: Årets pengestrøm

Sheet Simpel_funktion
A1: Munck Gruppen A/S (CVR 16499609) — Regnskabs- og nøgletal (CVR: 16499609) — funktionsopdelt
A3: Beløb i 1.000 kr. | B3: 2025 | C3: 2024 | D3: 2023 | F3: Note / XBRL-felt
A4: Uddrag af resultatopgørelse
A5: Nettoomsætning | B5: ='res_raw_16499609'!$F$2 | C5: ='res_raw_16499609'!$E$2 | D5: ='res_raw_16499609'!$D$2 | F5: fsa:Revenue
A6: Produktionsomkostninger | B6: =-'res_raw_16499609'!$F$3 | C6: =-'res_raw_16499609'!$E$3 | D6: =-'res_raw_16499609'!$D$3 | F6: fsa:CostOfProduction (vises negativt). Materialer, lønninger, produktionsoverhead.
A7: Bruttoresultat | B7: =SUM(B5:B6) | C7: =SUM(C5:C6) | D7: =SUM(D5:D6) | F7: Beregnet: Nettoomsætning − Produktionsomkostninger. Matcher fsa:GrossResult.
A8: Salgs- og distributionsomk. | B8: =-'res_raw_16499609'!$F$5 | C8: =-'res_raw_16499609'!$E$5 | D8: =-'res_raw_16499609'!$D$5 | F8: fsa:DistributionCosts (vises negativt). Marketing, salg, distribution.
A9: Administrationsomkostninger mv. | B9: =-'res_raw_16499609'!$F$6 | C9: =-'res_raw_16499609'!$E$6 | D9: =-'res_raw_16499609'!$D$6 | F9: fsa:AdministrativeExpenses (vises negativt). Generel administration.
A10: Andre driftsindtægter | B10: ='res_raw_16499609'!$F$7 | C10: ='res_raw_16499609'!$E$7 | D10: ='res_raw_16499609'!$D$7 | F10: fsa:OtherOperatingIncome. Sekundære driftsindtægter (huslejeindtægter, off. tilskud, avancer mv.).
A11: Andre driftsomkostninger | B11: =-'res_raw_16499609'!$F$8 | C11: =-'res_raw_16499609'!$E$8 | D11: =-'res_raw_16499609'!$D$8 | F11: fsa:OtherOperatingExpenses (vises negativt). Sekundære driftsomkostninger.
A12: Resultat af primær drift | B12: =SUM(B7:B11) | C12: =SUM(C7:C11) | D12: =SUM(D7:D11) | F12: Beregnet: Bruttoresultat − Salgs/dist. − Administration + Andre driftsindt. − Andre driftsomk. EBIT.
A13: Finansielle indtægter mv. | B13: =N('res_raw_16499609'!$F$10)+N('res_raw_16499609'!$F$11) | C13: =N('res_raw_16499609'!$E$10)+N('res_raw_16499609'!$E$11) | D13: =N('res_raw_16499609'!$D$10)+N('res_raw_16499609'!$D$11) | F13: fsa:IncomeFromSubsidiaries + fsa:OtherFinanceIncome.
A14: Finansielle omkostninger mv. | B14: =-'res_raw_16499609'!$F$12 | C14: =-'res_raw_16499609'!$E$12 | D14: =-'res_raw_16499609'!$D$12 | F14: fsa:OtherFinanceExpenses (vises negativt). Renteomkostninger, kurstab.
A15: Resultat før skat | B15: =SUM(B12:B14) | C15: =SUM(C12:C14) | D15: =SUM(D12:D14) | F15: Beregnet: EBIT + Fin. indtægter + Fin. omk. EBT.
A17: Uddrag af balance
A18: Anlægsaktiver | B18: ='balance_raw_16499609'!$F$15 | C18: ='balance_raw_16499609'!$E$15 | D18: ='balance_raw_16499609'!$D$15 | F18: fsa:NoncurrentAssets. Materielle, immaterielle og finansielle anlægsaktiver.
A19: Omsætningsaktiver | B19: ='balance_raw_16499609'!$F$30 | C19: ='balance_raw_16499609'!$E$30 | D19: ='balance_raw_16499609'!$D$30 | F19: fsa:CurrentAssets. Varebeholdninger, tilgodehavender, likvider.
A20: Aktiver i alt | B20: =SUM(B18:B19) | C20: =SUM(C18:C19) | D20: =SUM(D18:D19) | F20: Beregnet: Anlægsaktiver + Omsætningsaktiver. Bør matche fsa:Assets.
A22: Egenkapital | B22: ='balance_raw_16499609'!$F$38 | C22: ='balance_raw_16499609'!$E$38 | D22: ='balance_raw_16499609'!$D$38 | F22: fsa:Equity. Selskabskapital, overført resultat, reserver.
A23: Forpligtelser | B23: ='balance_raw_16499609'!$F$59-'balance_raw_16499609'!$F$38 | C23: ='balance_raw_16499609'!$E$59-'balance_raw_16499609'!$E$38 | D23: ='balance_raw_16499609'!$D$59-'balance_raw_16499609'!$D$38 | F23: Beregnet: Passiver (fsa:LiabilitiesAndEquity) − Egenkapital. Hensættelser + kort- og langfristet gæld.
A24: Passiver i alt | B24: =SUM(B22:B23) | C24: =SUM(C22:C23) | D24: =SUM(D22:D23) | F24: Beregnet: Egenkapital + Forpligtelser. Bør matche Aktiver i alt.
A26: Udvalgte balanceposter
A27: Varebeholdninger | B27: ='balance_raw_16499609'!$F$19 | C27: ='balance_raw_16499609'!$E$19 | D27: ='balance_raw_16499609'!$D$19 | F27: fsa:Inventories (eller fsa:ManufacturedGoodsAndGoodsForResale hvis total mangler).
A28: Tilgodehavender fra salg | B28: ='balance_raw_16499609'!$F$20 | C28: ='balance_raw_16499609'!$E$20 | D28: ='balance_raw_16499609'!$D$20 | F28: fsa:ShorttermTradeReceivables. Kortfristede tilgodehavender fra kunder.
A29: Kortfristede gældsforpligtelser | B29: ='balance_raw_16499609'!$F$57 | C29: ='balance_raw_16499609'!$E$57 | D29: ='balance_raw_16499609'!$D$57 | F29: fsa:ShorttermLiabilitiesOtherThanProvisions. Gæld der forfalder inden for 1 år.
A31: Rentabilitet
A32: Afkastningsgrad, % | B32: =IFERROR((B12+B13)/B20*100,"") | C32: =IFERROR((C12+C13)/C20*100,"") | D32: =IFERROR((D12+D13)/D20*100,"")
A33: Overskudsgrad, % | B33: =IFERROR((B12+B13)/B5*100,"") | C33: =IFERROR((C12+C13)/C5*100,"") | D33: =IFERROR((D12+D13)/D5*100,"")
A34: Aktivernes omsætningshastighed, gange | B34: =IFERROR(B5/B20,"") | C34: =IFERROR(C5/C20,"") | D34: =IFERROR(D5/D20,"")
A35: Gældsrente, % | B35: =IFERROR(-B14*100/B23,"") | C35: =IFERROR(-C14*100/C23,"") | D35: =IFERROR(-D14*100/D23,"")
A36: Egenkapitalens forrentning, % | B36: =IFERROR(B15/B22*100,"") | C36: =IFERROR(C15/C22*100,"") | D36: =IFERROR(D15/D22*100,"")
A37: Gearing, gange | B37: =IFERROR(B23/B22,"") | C37: =IFERROR(C23/C22,"") | D37: =IFERROR(D23/D22,"")
A39: Indekstal for indtjeningsevne (2023=100)
A40: Nettoomsætning | B40: =IFERROR(B5/$D5*100,"") | C40: =IFERROR(C5/$D5*100,"") | D40: =IFERROR(D5/$D5*100,"")
A41: Produktionsomkostninger | B41: =IFERROR(B6/$D6*100,"") | C41: =IFERROR(C6/$D6*100,"") | D41: =IFERROR(D6/$D6*100,"")
A42: Salgs- og distributionsomk. | B42: =IFERROR(B8/$D8*100,"") | C42: =IFERROR(C8/$D8*100,"") | D42: =IFERROR(D8/$D8*100,"")
A43: Administrationsomk. | B43: =IFERROR(B9/$D9*100,"") | C43: =IFERROR(C9/$D9*100,"") | D43: =IFERROR(D9/$D9*100,"")
A44: Andre driftsomkostninger | B44: =IFERROR(B11/$D11*100,"") | C44: =IFERROR(C11/$D11*100,"") | D44: =IFERROR(D11/$D11*100,"")
A46: Indekstal for kapitaltilpasningsevne (2023=100)
A47: Nettoomsætning | B47: =IFERROR(B5*100/$D5,"") | C47: =IFERROR(C5*100/$D5,"") | D47: =IFERROR(D5*100/$D5,"")
A48: Anlægsaktiver | B48: =IFERROR(B18*100/$D18,"") | C48: =IFERROR(C18*100/$D18,"") | D48: =IFERROR(D18*100/$D18,"")
A49: Varebeholdninger | B49: =IFERROR(B27*100/$D27,"") | C49: =IFERROR(C27*100/$D27,"") | D49: =IFERROR(D27*100/$D27,"")
A50: Tilgodehavender fra salg | B50: =IFERROR(B28*100/$D28,"") | C50: =IFERROR(C28*100/$D28,"") | D50: =IFERROR(D28*100/$D28,"")
A52: Soliditet og likviditet
A53: Soliditetsgrad, % | B53: =IFERROR(B22*100/B20,"") | C53: =IFERROR(C22*100/C20,"") | D53: =IFERROR(D22*100/D20,"")
A54: Gældsandel, % | B54: =IFERROR(B23*100/B20,"") | C54: =IFERROR(C23*100/C20,"") | D54: =IFERROR(D23*100/D20,"")
A55: Likviditetsgrad, % | B55: =IFERROR(B19*100/B29,"") | C55: =IFERROR(C19*100/C29,"") | D55: =IFERROR(D19*100/D29,"")
A57: Kilde: Bearbejdet uddrag af årsrapporter for 2023-2025. Alle dataceller er live formler der peger på res_raw / balance_raw.
A59: Krydstjek mod rådata (tolerance: 1 t.kr.)
A60: Aktiver i alt = fsa:Assets | B60: =IF('balance_raw_16499609'!$F$31="","—",IF(ABS(B20-'balance_raw_16499609'!$F$31)<=1,"✓ OK","❌ "&TEXT(B20-'balance_raw_16499609'!$F$31,"+#,##0;-#,##0")&" t.kr.")) | C60: =IF('balance_raw_16499609'!$E$31="","—",IF(ABS(C20-'balance_raw_16499609'!$E$31)<=1,"✓ OK","❌ "&TEXT(C20-'balance_raw_16499609'!$E$31,"+#,##0;-#,##0")&" t.kr.")) | D60: =IF('balance_raw_16499609'!$D$31="","—",IF(ABS(D20-'balance_raw_16499609'!$D$31)<=1,"✓ OK","❌ "&TEXT(D20-'balance_raw_16499609'!$D$31,"+#,##0;-#,##0")&" t.kr.")) | F60: Verificerer at sum(Anlæg+Omsætning) matcher Assets-totalen.
A61: Passiver i alt = fsa:LiabilitiesAndEquity | B61: =IF('balance_raw_16499609'!$F$59="","—",IF(ABS(B24-'balance_raw_16499609'!$F$59)<=1,"✓ OK","❌ "&TEXT(B24-'balance_raw_16499609'!$F$59,"+#,##0;-#,##0")&" t.kr.")) | C61: =IF('balance_raw_16499609'!$E$59="","—",IF(ABS(C24-'balance_raw_16499609'!$E$59)<=1,"✓ OK","❌ "&TEXT(C24-'balance_raw_16499609'!$E$59,"+#,##0;-#,##0")&" t.kr.")) | D61: =IF('balance_raw_16499609'!$D$59="","—",IF(ABS(D24-'balance_raw_16499609'!$D$59)<=1,"✓ OK","❌ "&TEXT(D24-'balance_raw_16499609'!$D$59,"+#,##0;-#,##0")&" t.kr.")) | F61: Verificerer at sum(EK+Forpligtelser) matcher Passiver-totalen.
A62: Aktiver i alt = Passiver i alt | B62: =IF(ABS(B20-B24)<=1,"✓ OK","❌ "&TEXT(B20-B24,"+#,##0;-#,##0")&" t.kr.") | C62: =IF(ABS(C20-C24)<=1,"✓ OK","❌ "&TEXT(C20-C24,"+#,##0;-#,##0")&" t.kr.") | D62: =IF(ABS(D20-D24)<=1,"✓ OK","❌ "&TEXT(D20-D24,"+#,##0;-#,##0")&" t.kr.") | F62: Balance-identitet på arket selv. Skal altid være 0 differance.
A63: Bruttoresultat (beregnet) = fsa:GrossResult | B63: =IF('res_raw_16499609'!$F$4="","—",IF(ABS(B7-'res_raw_16499609'!$F$4)<=1,"✓ OK","❌ "&TEXT(B7-'res_raw_16499609'!$F$4,"+#,##0;-#,##0")&" t.kr.")) | C63: =IF('res_raw_16499609'!$E$4="","—",IF(ABS(C7-'res_raw_16499609'!$E$4)<=1,"✓ OK","❌ "&TEXT(C7-'res_raw_16499609'!$E$4,"+#,##0;-#,##0")&" t.kr.")) | D63: =IF('res_raw_16499609'!$D$4="","—",IF(ABS(D7-'res_raw_16499609'!$D$4)<=1,"✓ OK","❌ "&TEXT(D7-'res_raw_16499609'!$D$4,"+#,##0;-#,##0")&" t.kr.")) | F63: Hvis Nettoomsætning eller omkostninger mangler, vil sumberegnet bruttoresultat afvige.
A64: EBIT (beregnet) = fsa:ProfitLossFromOrdinaryOperatingActivities | B64: =IF('res_raw_16499609'!$F$9="","—",IF(ABS(B12-'res_raw_16499609'!$F$9)<=1,"✓ OK","❌ "&TEXT(B12-'res_raw_16499609'!$F$9,"+#,##0;-#,##0")&" t.kr.")) | C64: =IF('res_raw_16499609'!$E$9="","—",IF(ABS(C12-'res_raw_16499609'!$E$9)<=1,"✓ OK","❌ "&TEXT(C12-'res_raw_16499609'!$E$9,"+#,##0;-#,##0")&" t.kr.")) | D64: =IF('res_raw_16499609'!$D$9="","—",IF(ABS(D12-'res_raw_16499609'!$D$9)<=1,"✓ OK","❌ "&TEXT(D12-'res_raw_16499609'!$D$9,"+#,##0;-#,##0")&" t.kr.")) | F64: Verificerer at sumberegnet EBIT matcher det rapporterede.
A65: EBT (beregnet) = fsa:ProfitLossFromOrdinaryActivitiesBeforeTax | B65: =IF('res_raw_16499609'!$F$14="","—",IF(ABS(B15-'res_raw_16499609'!$F$14)<=1,"✓ OK","❌ "&TEXT(B15-'res_raw_16499609'!$F$14,"+#,##0;-#,##0")&" t.kr.")) | C65: =IF('res_raw_16499609'!$E$14="","—",IF(ABS(C15-'res_raw_16499609'!$E$14)<=1,"✓ OK","❌ "&TEXT(C15-'res_raw_16499609'!$E$14,"+#,##0;-#,##0")&" t.kr.")) | D65: =IF('res_raw_16499609'!$D$14="","—",IF(ABS(D15-'res_raw_16499609'!$D$14)<=1,"✓ OK","❌ "&TEXT(D15-'res_raw_16499609'!$D$14,"+#,##0;-#,##0")&" t.kr.")) | F65: Verificerer at sumberegnet resultat før skat matcher det rapporterede.
