Workbook

Sheet Overblik_19555305
A1: Regnskabsanalyse – Resultatopgørelse & Balance (t.kr.) · Klasse C-stor · Revision
H2: Indekstal (2021=100)
A3: Resultatopgørelse t.kr. | B3: 2021 | C3: 2022 | D3: 2023 | E3: 2024 | F3: 2025 | H3: 2021 | I3: 2022 | J3: 2023 | K3: 2024 | L3: 2025
A4: Nettoomsætning | B4: ='res_raw_19555305'!$B$2 | C4: ='res_raw_19555305'!$C$2 | D4: ='res_raw_19555305'!$D$2 | E4: ='res_raw_19555305'!$E$2 | F4: ='res_raw_19555305'!$F$2 | H4: =IFERROR(B4/$B$4*100,"") | I4: =IFERROR(C4/$B$4*100,"") | J4: =IFERROR(D4/$B$4*100,"") | K4: =IFERROR(E4/$B$4*100,"") | L4: =IFERROR(F4/$B$4*100,"")
A5: Andre driftsindtægter | B5: ='res_raw_19555305'!$B$3 | C5: ='res_raw_19555305'!$C$3 | D5: ='res_raw_19555305'!$D$3 | E5: ='res_raw_19555305'!$E$3 | F5: ='res_raw_19555305'!$F$3 | H5: =IFERROR(B5/$B$5*100,"") | I5: =IFERROR(C5/$B$5*100,"") | J5: =IFERROR(D5/$B$5*100,"") | K5: =IFERROR(E5/$B$5*100,"") | L5: =IFERROR(F5/$B$5*100,"")
A6: Vareforbrug | B6: ='res_raw_19555305'!$B$4 | C6: ='res_raw_19555305'!$C$4 | D6: ='res_raw_19555305'!$D$4 | E6: ='res_raw_19555305'!$E$4 | F6: ='res_raw_19555305'!$F$4 | H6: =IFERROR(B6/$B$6*100,"") | I6: =IFERROR(C6/$B$6*100,"") | J6: =IFERROR(D6/$B$6*100,"") | K6: =IFERROR(E6/$B$6*100,"") | L6: =IFERROR(F6/$B$6*100,"")
A7: Andre eksterne omkostninger | B7: ='res_raw_19555305'!$B$5 | C7: ='res_raw_19555305'!$C$5 | D7: ='res_raw_19555305'!$D$5 | E7: ='res_raw_19555305'!$E$5 | F7: ='res_raw_19555305'!$F$5 | H7: =IFERROR(B7/$B$7*100,"") | I7: =IFERROR(C7/$B$7*100,"") | J7: =IFERROR(D7/$B$7*100,"") | K7: =IFERROR(E7/$B$7*100,"") | L7: =IFERROR(F7/$B$7*100,"")
A8: Bruttoresultat | B8: ='res_raw_19555305'!$B$6 | C8: ='res_raw_19555305'!$C$6 | D8: ='res_raw_19555305'!$D$6 | E8: ='res_raw_19555305'!$E$6 | F8: ='res_raw_19555305'!$F$6 | H8: =IFERROR(B8/$B$8*100,"") | I8: =IFERROR(C8/$B$8*100,"") | J8: =IFERROR(D8/$B$8*100,"") | K8: =IFERROR(E8/$B$8*100,"") | L8: =IFERROR(F8/$B$8*100,"")
A9: Personaleomkostninger | B9: ='res_raw_19555305'!$B$7 | C9: ='res_raw_19555305'!$C$7 | D9: ='res_raw_19555305'!$D$7 | E9: ='res_raw_19555305'!$E$7 | F9: ='res_raw_19555305'!$F$7 | H9: =IFERROR(B9/$B$9*100,"") | I9: =IFERROR(C9/$B$9*100,"") | J9: =IFERROR(D9/$B$9*100,"") | K9: =IFERROR(E9/$B$9*100,"") | L9: =IFERROR(F9/$B$9*100,"")
A10: Resultat før afskrivninger | B10: =IFERROR($B$8-ABS($B$9),"") | C10: =IFERROR($C$8-ABS($C$9),"") | D10: =IFERROR($D$8-ABS($D$9),"") | E10: =IFERROR($E$8-ABS($E$9),"") | F10: =IFERROR($F$8-ABS($F$9),"") | H10: =IFERROR(B10/$B$10*100,"") | I10: =IFERROR(C10/$B$10*100,"") | J10: =IFERROR(D10/$B$10*100,"") | K10: =IFERROR(E10/$B$10*100,"") | L10: =IFERROR(F10/$B$10*100,"")
A11: Af- og nedskrivninger | B11: ='res_raw_19555305'!$B$9 | C11: ='res_raw_19555305'!$C$9 | D11: ='res_raw_19555305'!$D$9 | E11: ='res_raw_19555305'!$E$9 | F11: ='res_raw_19555305'!$F$9 | H11: =IFERROR(B11/$B$11*100,"") | I11: =IFERROR(C11/$B$11*100,"") | J11: =IFERROR(D11/$B$11*100,"") | K11: =IFERROR(E11/$B$11*100,"") | L11: =IFERROR(F11/$B$11*100,"")
A12: Andre driftsomkostninger | B12: ='res_raw_19555305'!$B$10 | C12: ='res_raw_19555305'!$C$10 | D12: ='res_raw_19555305'!$D$10 | E12: ='res_raw_19555305'!$E$10 | F12: ='res_raw_19555305'!$F$10 | H12: =IFERROR(B12/$B$12*100,"") | I12: =IFERROR(C12/$B$12*100,"") | J12: =IFERROR(D12/$B$12*100,"") | K12: =IFERROR(E12/$B$12*100,"") | L12: =IFERROR(F12/$B$12*100,"")
A13: Resultat af primær drift | B13: ='res_raw_19555305'!$B$11 | C13: ='res_raw_19555305'!$C$11 | D13: ='res_raw_19555305'!$D$11 | E13: ='res_raw_19555305'!$E$11 | F13: ='res_raw_19555305'!$F$11 | H13: =IFERROR(B13/$B$13*100,"") | I13: =IFERROR(C13/$B$13*100,"") | J13: =IFERROR(D13/$B$13*100,"") | K13: =IFERROR(E13/$B$13*100,"") | L13: =IFERROR(F13/$B$13*100,"")
A14: Indtægter af kapitalandele, dattervirksomheder | B14: ='res_raw_19555305'!$B$12 | C14: ='res_raw_19555305'!$C$12 | D14: ='res_raw_19555305'!$D$12 | E14: ='res_raw_19555305'!$E$12 | F14: ='res_raw_19555305'!$F$12 | H14: =IFERROR(B14/$B$14*100,"") | I14: =IFERROR(C14/$B$14*100,"") | J14: =IFERROR(D14/$B$14*100,"") | K14: =IFERROR(E14/$B$14*100,"") | L14: =IFERROR(F14/$B$14*100,"")
A15: Finansielle indtægter | B15: ='res_raw_19555305'!$B$13 | C15: ='res_raw_19555305'!$C$13 | D15: ='res_raw_19555305'!$D$13 | E15: ='res_raw_19555305'!$E$13 | F15: ='res_raw_19555305'!$F$13 | H15: =IFERROR(B15/$B$15*100,"") | I15: =IFERROR(C15/$B$15*100,"") | J15: =IFERROR(D15/$B$15*100,"") | K15: =IFERROR(E15/$B$15*100,"") | L15: =IFERROR(F15/$B$15*100,"")
A16: Finansielle omkostninger | B16: ='res_raw_19555305'!$B$14 | C16: ='res_raw_19555305'!$C$14 | D16: ='res_raw_19555305'!$D$14 | E16: ='res_raw_19555305'!$E$14 | F16: ='res_raw_19555305'!$F$14 | H16: =IFERROR(B16/$B$16*100,"") | I16: =IFERROR(C16/$B$16*100,"") | J16: =IFERROR(D16/$B$16*100,"") | K16: =IFERROR(E16/$B$16*100,"") | L16: =IFERROR(F16/$B$16*100,"")
A17: Finansielle poster, netto | B17: ='res_raw_19555305'!$B$15 | C17: ='res_raw_19555305'!$C$15 | D17: ='res_raw_19555305'!$D$15 | E17: ='res_raw_19555305'!$E$15 | F17: ='res_raw_19555305'!$F$15 | H17: =IFERROR(B17/$B$17*100,"") | I17: =IFERROR(C17/$B$17*100,"") | J17: =IFERROR(D17/$B$17*100,"") | K17: =IFERROR(E17/$B$17*100,"") | L17: =IFERROR(F17/$B$17*100,"")
A18: Resultat før skat | B18: ='res_raw_19555305'!$B$16 | C18: ='res_raw_19555305'!$C$16 | D18: ='res_raw_19555305'!$D$16 | E18: ='res_raw_19555305'!$E$16 | F18: ='res_raw_19555305'!$F$16 | H18: =IFERROR(B18/$B$18*100,"") | I18: =IFERROR(C18/$B$18*100,"") | J18: =IFERROR(D18/$B$18*100,"") | K18: =IFERROR(E18/$B$18*100,"") | L18: =IFERROR(F18/$B$18*100,"")
A19: Skat af årets resultat | B19: ='res_raw_19555305'!$B$17 | C19: ='res_raw_19555305'!$C$17 | D19: ='res_raw_19555305'!$D$17 | E19: ='res_raw_19555305'!$E$17 | F19: ='res_raw_19555305'!$F$17 | H19: =IFERROR(B19/$B$19*100,"") | I19: =IFERROR(C19/$B$19*100,"") | J19: =IFERROR(D19/$B$19*100,"") | K19: =IFERROR(E19/$B$19*100,"") | L19: =IFERROR(F19/$B$19*100,"")
A20: Årets resultat | B20: ='res_raw_19555305'!$B$18 | C20: ='res_raw_19555305'!$C$18 | D20: ='res_raw_19555305'!$D$18 | E20: ='res_raw_19555305'!$E$18 | F20: ='res_raw_19555305'!$F$18 | H20: =IFERROR(B20/$B$20*100,"") | I20: =IFERROR(C20/$B$20*100,"") | J20: =IFERROR(D20/$B$20*100,"") | K20: =IFERROR(E20/$B$20*100,"") | L20: =IFERROR(F20/$B$20*100,"")
A22: AKTIVER t.kr. | B22: 2021 | C22: 2022 | D22: 2023 | E22: 2024 | F22: 2025 | H22: 2021 | I22: 2022 | J22: 2023 | K22: 2024 | L22: 2025
A23: Immaterielle anlægsaktiver | B23: ='balance_raw_19555305'!$B$2 | C23: ='balance_raw_19555305'!$C$2 | D23: ='balance_raw_19555305'!$D$2 | E23: ='balance_raw_19555305'!$E$2 | F23: ='balance_raw_19555305'!$F$2 | H23: =IFERROR(B23/$B$23*100,"") | I23: =IFERROR(C23/$B$23*100,"") | J23: =IFERROR(D23/$B$23*100,"") | K23: =IFERROR(E23/$B$23*100,"") | L23: =IFERROR(F23/$B$23*100,"")
A24: Grunde og bygninger | B24: ='balance_raw_19555305'!$B$3 | C24: ='balance_raw_19555305'!$C$3 | D24: ='balance_raw_19555305'!$D$3 | E24: ='balance_raw_19555305'!$E$3 | F24: ='balance_raw_19555305'!$F$3 | H24: =IFERROR(B24/$B$24*100,"") | I24: =IFERROR(C24/$B$24*100,"") | J24: =IFERROR(D24/$B$24*100,"") | K24: =IFERROR(E24/$B$24*100,"") | L24: =IFERROR(F24/$B$24*100,"")
A25: Produktionsanlæg og maskiner | B25: ='balance_raw_19555305'!$B$4 | C25: ='balance_raw_19555305'!$C$4 | D25: ='balance_raw_19555305'!$D$4 | E25: ='balance_raw_19555305'!$E$4 | F25: ='balance_raw_19555305'!$F$4 | H25: =IFERROR(B25/$B$25*100,"") | I25: =IFERROR(C25/$B$25*100,"") | J25: =IFERROR(D25/$B$25*100,"") | K25: =IFERROR(E25/$B$25*100,"") | L25: =IFERROR(F25/$B$25*100,"")
A26: Driftsmateriel og inventar | B26: ='balance_raw_19555305'!$B$5 | C26: ='balance_raw_19555305'!$C$5 | D26: ='balance_raw_19555305'!$D$5 | E26: ='balance_raw_19555305'!$E$5 | F26: ='balance_raw_19555305'!$F$5 | H26: =IFERROR(B26/$B$26*100,"") | I26: =IFERROR(C26/$B$26*100,"") | J26: =IFERROR(D26/$B$26*100,"") | K26: =IFERROR(E26/$B$26*100,"") | L26: =IFERROR(F26/$B$26*100,"")
A27: Indretning af lejede lokaler | B27: ='balance_raw_19555305'!$B$6 | C27: ='balance_raw_19555305'!$C$6 | D27: ='balance_raw_19555305'!$D$6 | E27: ='balance_raw_19555305'!$E$6 | F27: ='balance_raw_19555305'!$F$6 | H27: =IFERROR(B27/$B$27*100,"") | I27: =IFERROR(C27/$B$27*100,"") | J27: =IFERROR(D27/$B$27*100,"") | K27: =IFERROR(E27/$B$27*100,"") | L27: =IFERROR(F27/$B$27*100,"")
A28: Forudbetaling og anlægsaktiver under opførelse | B28: ='balance_raw_19555305'!$B$7 | C28: ='balance_raw_19555305'!$C$7 | D28: ='balance_raw_19555305'!$D$7 | E28: ='balance_raw_19555305'!$E$7 | F28: ='balance_raw_19555305'!$F$7 | H28: =IFERROR(B28/$B$28*100,"") | I28: =IFERROR(C28/$B$28*100,"") | J28: =IFERROR(D28/$B$28*100,"") | K28: =IFERROR(E28/$B$28*100,"") | L28: =IFERROR(F28/$B$28*100,"")
A29: Materielle anlægsaktiver | B29: ='balance_raw_19555305'!$B$8 | C29: ='balance_raw_19555305'!$C$8 | D29: ='balance_raw_19555305'!$D$8 | E29: ='balance_raw_19555305'!$E$8 | F29: ='balance_raw_19555305'!$F$8 | H29: =IFERROR(B29/$B$29*100,"") | I29: =IFERROR(C29/$B$29*100,"") | J29: =IFERROR(D29/$B$29*100,"") | K29: =IFERROR(E29/$B$29*100,"") | L29: =IFERROR(F29/$B$29*100,"")
A30: Anlægsaktiver | B30: ='balance_raw_19555305'!$B$9 | C30: ='balance_raw_19555305'!$C$9 | D30: ='balance_raw_19555305'!$D$9 | E30: ='balance_raw_19555305'!$E$9 | F30: ='balance_raw_19555305'!$F$9 | H30: =IFERROR(B30/$B$30*100,"") | I30: =IFERROR(C30/$B$30*100,"") | J30: =IFERROR(D30/$B$30*100,"") | K30: =IFERROR(E30/$B$30*100,"") | L30: =IFERROR(F30/$B$30*100,"")
A31: Råvarer og hjælpematerialer | B31: ='balance_raw_19555305'!$B$10 | C31: ='balance_raw_19555305'!$C$10 | D31: ='balance_raw_19555305'!$D$10 | E31: ='balance_raw_19555305'!$E$10 | F31: ='balance_raw_19555305'!$F$10 | H31: =IFERROR(B31/$B$31*100,"") | I31: =IFERROR(C31/$B$31*100,"") | J31: =IFERROR(D31/$B$31*100,"") | K31: =IFERROR(E31/$B$31*100,"") | L31: =IFERROR(F31/$B$31*100,"")
A32: Varer under fremstilling | B32: ='balance_raw_19555305'!$B$11 | C32: ='balance_raw_19555305'!$C$11 | D32: ='balance_raw_19555305'!$D$11 | E32: ='balance_raw_19555305'!$E$11 | F32: ='balance_raw_19555305'!$F$11 | H32: =IFERROR(B32/$B$32*100,"") | I32: =IFERROR(C32/$B$32*100,"") | J32: =IFERROR(D32/$B$32*100,"") | K32: =IFERROR(E32/$B$32*100,"") | L32: =IFERROR(F32/$B$32*100,"")
A33: Færdigvarer og handelsvarer | B33: ='balance_raw_19555305'!$B$12 | C33: ='balance_raw_19555305'!$C$12 | D33: ='balance_raw_19555305'!$D$12 | E33: ='balance_raw_19555305'!$E$12 | F33: ='balance_raw_19555305'!$F$12 | H33: =IFERROR(B33/$B$33*100,"") | I33: =IFERROR(C33/$B$33*100,"") | J33: =IFERROR(D33/$B$33*100,"") | K33: =IFERROR(E33/$B$33*100,"") | L33: =IFERROR(F33/$B$33*100,"")
A34: Varebeholdninger | B34: ='balance_raw_19555305'!$B$13 | C34: ='balance_raw_19555305'!$C$13 | D34: ='balance_raw_19555305'!$D$13 | E34: ='balance_raw_19555305'!$E$13 | F34: ='balance_raw_19555305'!$F$13 | H34: =IFERROR(B34/$B$34*100,"") | I34: =IFERROR(C34/$B$34*100,"") | J34: =IFERROR(D34/$B$34*100,"") | K34: =IFERROR(E34/$B$34*100,"") | L34: =IFERROR(F34/$B$34*100,"")
A35: Tilgodehavender fra salg og tjenesteydelser | B35: ='balance_raw_19555305'!$B$14 | C35: ='balance_raw_19555305'!$C$14 | D35: ='balance_raw_19555305'!$D$14 | E35: ='balance_raw_19555305'!$E$14 | F35: ='balance_raw_19555305'!$F$14 | H35: =IFERROR(B35/$B$35*100,"") | I35: =IFERROR(C35/$B$35*100,"") | J35: =IFERROR(D35/$B$35*100,"") | K35: =IFERROR(E35/$B$35*100,"") | L35: =IFERROR(F35/$B$35*100,"")
A36: Tilgodehavender hos tilknyttede virksomheder | B36: ='balance_raw_19555305'!$B$15 | C36: ='balance_raw_19555305'!$C$15 | D36: ='balance_raw_19555305'!$D$15 | E36: ='balance_raw_19555305'!$E$15 | F36: ='balance_raw_19555305'!$F$15 | H36: =IFERROR(B36/$B$36*100,"") | I36: =IFERROR(C36/$B$36*100,"") | J36: =IFERROR(D36/$B$36*100,"") | K36: =IFERROR(E36/$B$36*100,"") | L36: =IFERROR(F36/$B$36*100,"")
A37: Andre tilgodehavender | B37: ='balance_raw_19555305'!$B$16 | C37: ='balance_raw_19555305'!$C$16 | D37: ='balance_raw_19555305'!$D$16 | E37: ='balance_raw_19555305'!$E$16 | F37: ='balance_raw_19555305'!$F$16 | H37: =IFERROR(B37/$B$37*100,"") | I37: =IFERROR(C37/$B$37*100,"") | J37: =IFERROR(D37/$B$37*100,"") | K37: =IFERROR(E37/$B$37*100,"") | L37: =IFERROR(F37/$B$37*100,"")
A38: Periodeafgrænsningsposter (aktiver) | B38: ='balance_raw_19555305'!$B$17 | C38: ='balance_raw_19555305'!$C$17 | D38: ='balance_raw_19555305'!$D$17 | E38: ='balance_raw_19555305'!$E$17 | F38: ='balance_raw_19555305'!$F$17 | H38: =IFERROR(B38/$B$38*100,"") | I38: =IFERROR(C38/$B$38*100,"") | J38: =IFERROR(D38/$B$38*100,"") | K38: =IFERROR(E38/$B$38*100,"") | L38: =IFERROR(F38/$B$38*100,"")
A39: Udskudt skatteaktiv | B39: ='balance_raw_19555305'!$B$18 | C39: ='balance_raw_19555305'!$C$18 | D39: ='balance_raw_19555305'!$D$18 | E39: ='balance_raw_19555305'!$E$18 | F39: ='balance_raw_19555305'!$F$18 | H39: =IFERROR(B39/$B$39*100,"") | I39: =IFERROR(C39/$B$39*100,"") | J39: =IFERROR(D39/$B$39*100,"") | K39: =IFERROR(E39/$B$39*100,"") | L39: =IFERROR(F39/$B$39*100,"")
A40: Tilgodehavende skat hos tilknyttede virksomheder | B40: ='balance_raw_19555305'!$B$19 | C40: ='balance_raw_19555305'!$C$19 | D40: ='balance_raw_19555305'!$D$19 | E40: ='balance_raw_19555305'!$E$19 | F40: ='balance_raw_19555305'!$F$19 | H40: =IFERROR(B40/$B$40*100,"") | I40: =IFERROR(C40/$B$40*100,"") | J40: =IFERROR(D40/$B$40*100,"") | K40: =IFERROR(E40/$B$40*100,"") | L40: =IFERROR(F40/$B$40*100,"")
A41: Kortfristede skattetilgodehavender | B41: ='balance_raw_19555305'!$B$20 | C41: ='balance_raw_19555305'!$C$20 | D41: ='balance_raw_19555305'!$D$20 | E41: ='balance_raw_19555305'!$E$20 | F41: ='balance_raw_19555305'!$F$20 | H41: =IFERROR(B41/$B$41*100,"") | I41: =IFERROR(C41/$B$41*100,"") | J41: =IFERROR(D41/$B$41*100,"") | K41: =IFERROR(E41/$B$41*100,"") | L41: =IFERROR(F41/$B$41*100,"")
A42: Tilgodehavender | B42: ='balance_raw_19555305'!$B$21 | C42: ='balance_raw_19555305'!$C$21 | D42: ='balance_raw_19555305'!$D$21 | E42: ='balance_raw_19555305'!$E$21 | F42: ='balance_raw_19555305'!$F$21 | H42: =IFERROR(B42/$B$42*100,"") | I42: =IFERROR(C42/$B$42*100,"") | J42: =IFERROR(D42/$B$42*100,"") | K42: =IFERROR(E42/$B$42*100,"") | L42: =IFERROR(F42/$B$42*100,"")
A43: Værdipapirer | B43: ='balance_raw_19555305'!$B$22 | C43: ='balance_raw_19555305'!$C$22 | D43: ='balance_raw_19555305'!$D$22 | E43: ='balance_raw_19555305'!$E$22 | F43: ='balance_raw_19555305'!$F$22 | H43: =IFERROR(B43/$B$43*100,"") | I43: =IFERROR(C43/$B$43*100,"") | J43: =IFERROR(D43/$B$43*100,"") | K43: =IFERROR(E43/$B$43*100,"") | L43: =IFERROR(F43/$B$43*100,"")
A44: Likvide beholdninger | B44: ='balance_raw_19555305'!$B$23 | C44: ='balance_raw_19555305'!$C$23 | D44: ='balance_raw_19555305'!$D$23 | E44: ='balance_raw_19555305'!$E$23 | F44: ='balance_raw_19555305'!$F$23 | H44: =IFERROR(B44/$B$44*100,"") | I44: =IFERROR(C44/$B$44*100,"") | J44: =IFERROR(D44/$B$44*100,"") | K44: =IFERROR(E44/$B$44*100,"") | L44: =IFERROR(F44/$B$44*100,"")
A45: Omsætningsaktiver | B45: ='balance_raw_19555305'!$B$24 | C45: ='balance_raw_19555305'!$C$24 | D45: ='balance_raw_19555305'!$D$24 | E45: ='balance_raw_19555305'!$E$24 | F45: ='balance_raw_19555305'!$F$24 | H45: =IFERROR(B45/$B$45*100,"") | I45: =IFERROR(C45/$B$45*100,"") | J45: =IFERROR(D45/$B$45*100,"") | K45: =IFERROR(E45/$B$45*100,"") | L45: =IFERROR(F45/$B$45*100,"")
A46: Aktiver | B46: ='balance_raw_19555305'!$B$25 | C46: ='balance_raw_19555305'!$C$25 | D46: ='balance_raw_19555305'!$D$25 | E46: ='balance_raw_19555305'!$E$25 | F46: ='balance_raw_19555305'!$F$25 | H46: =IFERROR(B46/$B$46*100,"") | I46: =IFERROR(C46/$B$46*100,"") | J46: =IFERROR(D46/$B$46*100,"") | K46: =IFERROR(E46/$B$46*100,"") | L46: =IFERROR(F46/$B$46*100,"")
A48: PASSIVER t.kr. | B48: 2021 | C48: 2022 | D48: 2023 | E48: 2024 | F48: 2025 | H48: 2021 | I48: 2022 | J48: 2023 | K48: 2024 | L48: 2025
A49: Selskabskapital | B49: ='balance_raw_19555305'!$B$26 | C49: ='balance_raw_19555305'!$C$26 | D49: ='balance_raw_19555305'!$D$26 | E49: ='balance_raw_19555305'!$E$26 | F49: ='balance_raw_19555305'!$F$26 | H49: =IFERROR(B49/$B$49*100,"") | I49: =IFERROR(C49/$B$49*100,"") | J49: =IFERROR(D49/$B$49*100,"") | K49: =IFERROR(E49/$B$49*100,"") | L49: =IFERROR(F49/$B$49*100,"")
A50: Reserve for nettoopskrivning (indre værdis metode) | B50: ='balance_raw_19555305'!$B$27 | C50: ='balance_raw_19555305'!$C$27 | D50: ='balance_raw_19555305'!$D$27 | E50: ='balance_raw_19555305'!$E$27 | F50: ='balance_raw_19555305'!$F$27 | H50: =IFERROR(B50/$B$50*100,"") | I50: =IFERROR(C50/$B$50*100,"") | J50: =IFERROR(D50/$B$50*100,"") | K50: =IFERROR(E50/$B$50*100,"") | L50: =IFERROR(F50/$B$50*100,"")
A51: Reserve for udviklingsomkostninger | B51: ='balance_raw_19555305'!$B$28 | C51: ='balance_raw_19555305'!$C$28 | D51: ='balance_raw_19555305'!$D$28 | E51: ='balance_raw_19555305'!$E$28 | F51: ='balance_raw_19555305'!$F$28 | H51: =IFERROR(B51/$B$51*100,"") | I51: =IFERROR(C51/$B$51*100,"") | J51: =IFERROR(D51/$B$51*100,"") | K51: =IFERROR(E51/$B$51*100,"") | L51: =IFERROR(F51/$B$51*100,"")
A52: Reserve for sikringstransaktioner | B52: ='balance_raw_19555305'!$B$29 | C52: ='balance_raw_19555305'!$C$29 | D52: ='balance_raw_19555305'!$D$29 | E52: ='balance_raw_19555305'!$E$29 | F52: ='balance_raw_19555305'!$F$29 | H52: =IFERROR(B52/$B$52*100,"") | I52: =IFERROR(C52/$B$52*100,"") | J52: =IFERROR(D52/$B$52*100,"") | K52: =IFERROR(E52/$B$52*100,"") | L52: =IFERROR(F52/$B$52*100,"")
A53: Andre reserver | B53: ='balance_raw_19555305'!$B$30 | C53: ='balance_raw_19555305'!$C$30 | D53: ='balance_raw_19555305'!$D$30 | E53: ='balance_raw_19555305'!$E$30 | F53: ='balance_raw_19555305'!$F$30 | H53: =IFERROR(B53/$B$53*100,"") | I53: =IFERROR(C53/$B$53*100,"") | J53: =IFERROR(D53/$B$53*100,"") | K53: =IFERROR(E53/$B$53*100,"") | L53: =IFERROR(F53/$B$53*100,"")
A54: Overført resultat | B54: ='balance_raw_19555305'!$B$31 | C54: ='balance_raw_19555305'!$C$31 | D54: ='balance_raw_19555305'!$D$31 | E54: ='balance_raw_19555305'!$E$31 | F54: ='balance_raw_19555305'!$F$31 | H54: =IFERROR(B54/$B$54*100,"") | I54: =IFERROR(C54/$B$54*100,"") | J54: =IFERROR(D54/$B$54*100,"") | K54: =IFERROR(E54/$B$54*100,"") | L54: =IFERROR(F54/$B$54*100,"")
A55: Egenkapital i alt | B55: ='balance_raw_19555305'!$B$32 | C55: ='balance_raw_19555305'!$C$32 | D55: ='balance_raw_19555305'!$D$32 | E55: ='balance_raw_19555305'!$E$32 | F55: ='balance_raw_19555305'!$F$32 | H55: =IFERROR(B55/$B$55*100,"") | I55: =IFERROR(C55/$B$55*100,"") | J55: =IFERROR(D55/$B$55*100,"") | K55: =IFERROR(E55/$B$55*100,"") | L55: =IFERROR(F55/$B$55*100,"")
A56: Hensættelse til udskudt skat | B56: ='balance_raw_19555305'!$B$33 | C56: ='balance_raw_19555305'!$C$33 | D56: ='balance_raw_19555305'!$D$33 | E56: ='balance_raw_19555305'!$E$33 | F56: ='balance_raw_19555305'!$F$33 | H56: =IFERROR(B56/$B$56*100,"") | I56: =IFERROR(C56/$B$56*100,"") | J56: =IFERROR(D56/$B$56*100,"") | K56: =IFERROR(E56/$B$56*100,"") | L56: =IFERROR(F56/$B$56*100,"")
A57: Hensatte forpligtelser | B57: ='balance_raw_19555305'!$B$34 | C57: ='balance_raw_19555305'!$C$34 | D57: ='balance_raw_19555305'!$D$34 | E57: ='balance_raw_19555305'!$E$34 | F57: ='balance_raw_19555305'!$F$34 | H57: =IFERROR(B57/$B$57*100,"") | I57: =IFERROR(C57/$B$57*100,"") | J57: =IFERROR(D57/$B$57*100,"") | K57: =IFERROR(E57/$B$57*100,"") | L57: =IFERROR(F57/$B$57*100,"")
A58: Ansvarlig lånekapital (langfristet) | B58: ='balance_raw_19555305'!$B$35 | C58: ='balance_raw_19555305'!$C$35 | D58: ='balance_raw_19555305'!$D$35 | E58: ='balance_raw_19555305'!$E$35 | F58: ='balance_raw_19555305'!$F$35 | H58: =IFERROR(B58/$B$58*100,"") | I58: =IFERROR(C58/$B$58*100,"") | J58: =IFERROR(D58/$B$58*100,"") | K58: =IFERROR(E58/$B$58*100,"") | L58: =IFERROR(F58/$B$58*100,"")
A59: Langfristede lån | B59: ='balance_raw_19555305'!$B$36 | C59: ='balance_raw_19555305'!$C$36 | D59: ='balance_raw_19555305'!$D$36 | E59: ='balance_raw_19555305'!$E$36 | F59: ='balance_raw_19555305'!$F$36 | H59: =IFERROR(B59/$B$59*100,"") | I59: =IFERROR(C59/$B$59*100,"") | J59: =IFERROR(D59/$B$59*100,"") | K59: =IFERROR(E59/$B$59*100,"") | L59: =IFERROR(F59/$B$59*100,"")
A60: Leasingforpligtelser (langfristet) | B60: ='balance_raw_19555305'!$B$37 | C60: ='balance_raw_19555305'!$C$37 | D60: ='balance_raw_19555305'!$D$37 | E60: ='balance_raw_19555305'!$E$37 | F60: ='balance_raw_19555305'!$F$37 | H60: =IFERROR(B60/$B$60*100,"") | I60: =IFERROR(C60/$B$60*100,"") | J60: =IFERROR(D60/$B$60*100,"") | K60: =IFERROR(E60/$B$60*100,"") | L60: =IFERROR(F60/$B$60*100,"")
A61: Anden gæld (langfristet) | B61: ='balance_raw_19555305'!$B$38 | C61: ='balance_raw_19555305'!$C$38 | D61: ='balance_raw_19555305'!$D$38 | E61: ='balance_raw_19555305'!$E$38 | F61: ='balance_raw_19555305'!$F$38 | H61: =IFERROR(B61/$B$61*100,"") | I61: =IFERROR(C61/$B$61*100,"") | J61: =IFERROR(D61/$B$61*100,"") | K61: =IFERROR(E61/$B$61*100,"") | L61: =IFERROR(F61/$B$61*100,"")
A62: Langfristede gældsforpligtelser | B62: ='balance_raw_19555305'!$B$39 | C62: ='balance_raw_19555305'!$C$39 | D62: ='balance_raw_19555305'!$D$39 | E62: ='balance_raw_19555305'!$E$39 | F62: ='balance_raw_19555305'!$F$39 | H62: =IFERROR(B62/$B$62*100,"") | I62: =IFERROR(C62/$B$62*100,"") | J62: =IFERROR(D62/$B$62*100,"") | K62: =IFERROR(E62/$B$62*100,"") | L62: =IFERROR(F62/$B$62*100,"")
A63: Ansvarlig lånekapital (kortfristet) | B63: ='balance_raw_19555305'!$B$40 | C63: ='balance_raw_19555305'!$C$40 | D63: ='balance_raw_19555305'!$D$40 | E63: ='balance_raw_19555305'!$E$40 | F63: ='balance_raw_19555305'!$F$40 | H63: =IFERROR(B63/$B$63*100,"") | I63: =IFERROR(C63/$B$63*100,"") | J63: =IFERROR(D63/$B$63*100,"") | K63: =IFERROR(E63/$B$63*100,"") | L63: =IFERROR(F63/$B$63*100,"")
A64: Kortfristet del af langfristede gældsforpligtelser | B64: ='balance_raw_19555305'!$B$41 | C64: ='balance_raw_19555305'!$C$41 | D64: ='balance_raw_19555305'!$D$41 | E64: ='balance_raw_19555305'!$E$41 | F64: ='balance_raw_19555305'!$F$41 | H64: =IFERROR(B64/$B$64*100,"") | I64: =IFERROR(C64/$B$64*100,"") | J64: =IFERROR(D64/$B$64*100,"") | K64: =IFERROR(E64/$B$64*100,"") | L64: =IFERROR(F64/$B$64*100,"")
A65: Kreditinstitutter | B65: ='balance_raw_19555305'!$B$42 | C65: ='balance_raw_19555305'!$C$42 | D65: ='balance_raw_19555305'!$D$42 | E65: ='balance_raw_19555305'!$E$42 | F65: ='balance_raw_19555305'!$F$42 | H65: =IFERROR(B65/$B$65*100,"") | I65: =IFERROR(C65/$B$65*100,"") | J65: =IFERROR(D65/$B$65*100,"") | K65: =IFERROR(E65/$B$65*100,"") | L65: =IFERROR(F65/$B$65*100,"")
A66: Leasingforpligtelser (kortfristet) | B66: ='balance_raw_19555305'!$B$43 | C66: ='balance_raw_19555305'!$C$43 | D66: ='balance_raw_19555305'!$D$43 | E66: ='balance_raw_19555305'!$E$43 | F66: ='balance_raw_19555305'!$F$43 | H66: =IFERROR(B66/$B$66*100,"") | I66: =IFERROR(C66/$B$66*100,"") | J66: =IFERROR(D66/$B$66*100,"") | K66: =IFERROR(E66/$B$66*100,"") | L66: =IFERROR(F66/$B$66*100,"")
A67: Leverandører af varer og tjenesteydelser | B67: ='balance_raw_19555305'!$B$44 | C67: ='balance_raw_19555305'!$C$44 | D67: ='balance_raw_19555305'!$D$44 | E67: ='balance_raw_19555305'!$E$44 | F67: ='balance_raw_19555305'!$F$44 | H67: =IFERROR(B67/$B$67*100,"") | I67: =IFERROR(C67/$B$67*100,"") | J67: =IFERROR(D67/$B$67*100,"") | K67: =IFERROR(E67/$B$67*100,"") | L67: =IFERROR(F67/$B$67*100,"")
A68: Gæld til tilknyttede virksomheder | B68: ='balance_raw_19555305'!$B$45 | C68: ='balance_raw_19555305'!$C$45 | D68: ='balance_raw_19555305'!$D$45 | E68: ='balance_raw_19555305'!$E$45 | F68: ='balance_raw_19555305'!$F$45 | H68: =IFERROR(B68/$B$68*100,"") | I68: =IFERROR(C68/$B$68*100,"") | J68: =IFERROR(D68/$B$68*100,"") | K68: =IFERROR(E68/$B$68*100,"") | L68: =IFERROR(F68/$B$68*100,"")
A69: Gæld til selskabsdeltagere og ledelse | B69: ='balance_raw_19555305'!$B$46 | C69: ='balance_raw_19555305'!$C$46 | D69: ='balance_raw_19555305'!$D$46 | E69: ='balance_raw_19555305'!$E$46 | F69: ='balance_raw_19555305'!$F$46 | H69: =IFERROR(B69/$B$69*100,"") | I69: =IFERROR(C69/$B$69*100,"") | J69: =IFERROR(D69/$B$69*100,"") | K69: =IFERROR(E69/$B$69*100,"") | L69: =IFERROR(F69/$B$69*100,"")
A70: Selskabsskat | B70: ='balance_raw_19555305'!$B$47 | C70: ='balance_raw_19555305'!$C$47 | D70: ='balance_raw_19555305'!$D$47 | E70: ='balance_raw_19555305'!$E$47 | F70: ='balance_raw_19555305'!$F$47 | H70: =IFERROR(B70/$B$70*100,"") | I70: =IFERROR(C70/$B$70*100,"") | J70: =IFERROR(D70/$B$70*100,"") | K70: =IFERROR(E70/$B$70*100,"") | L70: =IFERROR(F70/$B$70*100,"")
A71: Gæld til tilknyttede virksomheder vedr. selskabsskat | B71: ='balance_raw_19555305'!$B$48 | C71: ='balance_raw_19555305'!$C$48 | D71: ='balance_raw_19555305'!$D$48 | E71: ='balance_raw_19555305'!$E$48 | F71: ='balance_raw_19555305'!$F$48 | H71: =IFERROR(B71/$B$71*100,"") | I71: =IFERROR(C71/$B$71*100,"") | J71: =IFERROR(D71/$B$71*100,"") | K71: =IFERROR(E71/$B$71*100,"") | L71: =IFERROR(F71/$B$71*100,"")
A72: Anden gæld (kortfristet) | B72: ='balance_raw_19555305'!$B$49 | C72: ='balance_raw_19555305'!$C$49 | D72: ='balance_raw_19555305'!$D$49 | E72: ='balance_raw_19555305'!$E$49 | F72: ='balance_raw_19555305'!$F$49 | H72: =IFERROR(B72/$B$72*100,"") | I72: =IFERROR(C72/$B$72*100,"") | J72: =IFERROR(D72/$B$72*100,"") | K72: =IFERROR(E72/$B$72*100,"") | L72: =IFERROR(F72/$B$72*100,"")
A73: Periodeafgrænsningsposter (passiver) | B73: ='balance_raw_19555305'!$B$50 | C73: ='balance_raw_19555305'!$C$50 | D73: ='balance_raw_19555305'!$D$50 | E73: ='balance_raw_19555305'!$E$50 | F73: ='balance_raw_19555305'!$F$50 | H73: =IFERROR(B73/$B$73*100,"") | I73: =IFERROR(C73/$B$73*100,"") | J73: =IFERROR(D73/$B$73*100,"") | K73: =IFERROR(E73/$B$73*100,"") | L73: =IFERROR(F73/$B$73*100,"")
A74: Kortfristede gældsforpligtelser | B74: ='balance_raw_19555305'!$B$51 | C74: ='balance_raw_19555305'!$C$51 | D74: ='balance_raw_19555305'!$D$51 | E74: ='balance_raw_19555305'!$E$51 | F74: ='balance_raw_19555305'!$F$51 | H74: =IFERROR(B74/$B$74*100,"") | I74: =IFERROR(C74/$B$74*100,"") | J74: =IFERROR(D74/$B$74*100,"") | K74: =IFERROR(E74/$B$74*100,"") | L74: =IFERROR(F74/$B$74*100,"")
A75: Gældsforpligtelser | B75: ='balance_raw_19555305'!$B$52 | C75: ='balance_raw_19555305'!$C$52 | D75: ='balance_raw_19555305'!$D$52 | E75: ='balance_raw_19555305'!$E$52 | F75: ='balance_raw_19555305'!$F$52 | H75: =IFERROR(B75/$B$75*100,"") | I75: =IFERROR(C75/$B$75*100,"") | J75: =IFERROR(D75/$B$75*100,"") | K75: =IFERROR(E75/$B$75*100,"") | L75: =IFERROR(F75/$B$75*100,"")
A76: Passiver | B76: ='balance_raw_19555305'!$B$53 | C76: ='balance_raw_19555305'!$C$53 | D76: ='balance_raw_19555305'!$D$53 | E76: ='balance_raw_19555305'!$E$53 | F76: ='balance_raw_19555305'!$F$53 | H76: =IFERROR(B76/$B$76*100,"") | I76: =IFERROR(C76/$B$76*100,"") | J76: =IFERROR(D76/$B$76*100,"") | K76: =IFERROR(E76/$B$76*100,"") | L76: =IFERROR(F76/$B$76*100,"")
A78: NØGLEOPLYSNINGER | B78: 2021 | C78: 2022 | D78: 2023 | E78: 2024 | F78: 2025
A79: Gns. antal medarbejdere | B79: ='res_raw_19555305'!$B$19 | C79: ='res_raw_19555305'!$C$19 | D79: ='res_raw_19555305'!$D$19 | E79: ='res_raw_19555305'!$E$19 | F79: ='res_raw_19555305'!$F$19 | H79: =IFERROR(B79/$B$79*100,"") | I79: =IFERROR(C79/$B$79*100,"") | J79: =IFERROR(D79/$B$79*100,"") | K79: =IFERROR(E79/$B$79*100,"") | L79: =IFERROR(F79/$B$79*100,"")
A80: Investering i materielle anlægsaktiver | B80: ='res_raw_19555305'!$B$20 | C80: ='res_raw_19555305'!$C$20 | D80: ='res_raw_19555305'!$D$20 | E80: ='res_raw_19555305'!$E$20 | F80: ='res_raw_19555305'!$F$20 | H80: =IFERROR(B80/$B$80*100,"") | I80: =IFERROR(C80/$B$80*100,"") | J80: =IFERROR(D80/$B$80*100,"") | K80: =IFERROR(E80/$B$80*100,"") | L80: =IFERROR(F80/$B$80*100,"")
A82: NØGLETAL | B82: 2021 | C82: 2022 | D82: 2023 | E82: 2024 | F82: 2025
A83: Afkastningsgrad, % | B83: =IFERROR(($B$13+$B$15+$B$14)/$B$46*100,"") | C83: =IFERROR(($C$13+$C$15+$C$14)/$C$46*100,"") | D83: =IFERROR(($D$13+$D$15+$D$14)/$D$46*100,"") | E83: =IFERROR(($E$13+$E$15+$E$14)/$E$46*100,"") | F83: =IFERROR(($F$13+$F$15+$F$14)/$F$46*100,"")
A84: Overskudsgrad, % | B84: =IFERROR(($B$13+$B$15+$B$14)/$B$4*100,"") | C84: =IFERROR(($C$13+$C$15+$C$14)/$C$4*100,"") | D84: =IFERROR(($D$13+$D$15+$D$14)/$D$4*100,"") | E84: =IFERROR(($E$13+$E$15+$E$14)/$E$4*100,"") | F84: =IFERROR(($F$13+$F$15+$F$14)/$F$4*100,"")
A85: Aktivernes omsætningshastighed, gange | B85: =IFERROR($B$4/$B$46,"") | C85: =IFERROR($C$4/$C$46,"") | D85: =IFERROR($D$4/$D$46,"") | E85: =IFERROR($E$4/$E$46,"") | F85: =IFERROR($F$4/$F$46,"")
A86: Egenkapitalens forrentning, % | B86: =IFERROR($B$18/$B$55*100,"") | C86: =IFERROR($C$18/$C$55*100,"") | D86: =IFERROR($D$18/$D$55*100,"") | E86: =IFERROR($E$18/$E$55*100,"") | F86: =IFERROR($F$18/$F$55*100,"")
A87: Gældsrente, % | B87: =IFERROR($B$16/($B$76-$B$55)*100,"") | C87: =IFERROR($C$16/($C$76-$C$55)*100,"") | D87: =IFERROR($D$16/($D$76-$D$55)*100,"") | E87: =IFERROR($E$16/($E$76-$E$55)*100,"") | F87: =IFERROR($F$16/($F$76-$F$55)*100,"")
A88: Soliditetsgrad, % | B88: =IFERROR($B$55/$B$46*100,"") | C88: =IFERROR($C$55/$C$46*100,"") | D88: =IFERROR($D$55/$D$46*100,"") | E88: =IFERROR($E$55/$E$46*100,"") | F88: =IFERROR($F$55/$F$46*100,"")
A89: Gearing | B89: =IFERROR(($B$76-$B$55)/$B$55,"") | C89: =IFERROR(($C$76-$C$55)/$C$55,"") | D89: =IFERROR(($D$76-$D$55)/$D$55,"") | E89: =IFERROR(($E$76-$E$55)/$E$55,"") | F89: =IFERROR(($F$76-$F$55)/$F$55,"")
A90: Likviditetsgrad, % | B90: =IFERROR($B$45/$B$74*100,"") | C90: =IFERROR($C$45/$C$74*100,"") | D90: =IFERROR($D$45/$D$74*100,"") | E90: =IFERROR($E$45/$E$74*100,"") | F90: =IFERROR($F$45/$F$74*100,"")
A91: Rentemarginal, % | B91: =IFERROR(B83-B87,"") | C91: =IFERROR(C83-C87,"") | D91: =IFERROR(D83-D87,"") | E91: =IFERROR(E83-E87,"") | F91: =IFERROR(F83-F87,"")
A92: Gældsandel, % | B92: =IFERROR(($B$76-$B$55)/$B$46*100,"") | C92: =IFERROR(($C$76-$C$55)/$C$46*100,"") | D92: =IFERROR(($D$76-$D$55)/$D$46*100,"") | E92: =IFERROR(($E$76-$E$55)/$E$46*100,"") | F92: =IFERROR(($F$76-$F$55)/$F$46*100,"")
A93: Kapitalbindingsgrad, % | B93: =IFERROR($B$30/($B$55+$B$62)*100,"") | C93: =IFERROR($C$30/($C$55+$C$62)*100,"") | D93: =IFERROR($D$30/($D$55+$D$62)*100,"") | E93: =IFERROR($E$30/($E$55+$E$62)*100,"") | F93: =IFERROR($F$30/($F$55+$F$62)*100,"")
A95: PENGESTRØMSOPGØRELSE t.kr.
A96: Pengestrømme fra driftsaktivitet | B96: ='pengestrom_raw_19555305'!$B$2 | C96: ='pengestrom_raw_19555305'!$C$2 | D96: ='pengestrom_raw_19555305'!$D$2 | E96: ='pengestrom_raw_19555305'!$E$2 | F96: ='pengestrom_raw_19555305'!$F$2
A97: Pengestrømme fra investeringsaktivitet | B97: ='pengestrom_raw_19555305'!$B$3 | C97: ='pengestrom_raw_19555305'!$C$3 | D97: ='pengestrom_raw_19555305'!$D$3 | E97: ='pengestrom_raw_19555305'!$E$3 | F97: ='pengestrom_raw_19555305'!$F$3
A98: Pengestrømme fra finansieringsaktivitet | B98: ='pengestrom_raw_19555305'!$B$4 | C98: ='pengestrom_raw_19555305'!$C$4 | D98: ='pengestrom_raw_19555305'!$D$4 | E98: ='pengestrom_raw_19555305'!$E$4 | F98: ='pengestrom_raw_19555305'!$F$4
A99: Årets pengestrøm (rapporteret) | B99: ='pengestrom_raw_19555305'!$B$5 | C99: ='pengestrom_raw_19555305'!$C$5 | D99: ='pengestrom_raw_19555305'!$D$5 | E99: ='pengestrom_raw_19555305'!$E$5 | F99: ='pengestrom_raw_19555305'!$F$5
A100: Krydstjek: drift + inv. + fin. = årets pengestrøm | B100: =IF(ABS(('pengestrom_raw_19555305'!$B$2+'pengestrom_raw_19555305'!$B$3+'pengestrom_raw_19555305'!$B$4)-'pengestrom_raw_19555305'!$B$5)<=2,"✓","⚠ "&TEXT(('pengestrom_raw_19555305'!$B$2+'pengestrom_raw_19555305'!$B$3+'pengestrom_raw_19555305'!$B$4)-'pengestrom_raw_19555305'!$B$5,"+#,##0;-#,##0")) | C100: =IF(ABS(('pengestrom_raw_19555305'!$C$2+'pengestrom_raw_19555305'!$C$3+'pengestrom_raw_19555305'!$C$4)-'pengestrom_raw_19555305'!$C$5)<=2,"✓","⚠ "&TEXT(('pengestrom_raw_19555305'!$C$2+'pengestrom_raw_19555305'!$C$3+'pengestrom_raw_19555305'!$C$4)-'pengestrom_raw_19555305'!$C$5,"+#,##0;-#,##0")) | D100: =IF(ABS(('pengestrom_raw_19555305'!$D$2+'pengestrom_raw_19555305'!$D$3+'pengestrom_raw_19555305'!$D$4)-'pengestrom_raw_19555305'!$D$5)<=2,"✓","⚠ "&TEXT(('pengestrom_raw_19555305'!$D$2+'pengestrom_raw_19555305'!$D$3+'pengestrom_raw_19555305'!$D$4)-'pengestrom_raw_19555305'!$D$5,"+#,##0;-#,##0")) | E100: =IF(ABS(('pengestrom_raw_19555305'!$E$2+'pengestrom_raw_19555305'!$E$3+'pengestrom_raw_19555305'!$E$4)-'pengestrom_raw_19555305'!$E$5)<=2,"✓","⚠ "&TEXT(('pengestrom_raw_19555305'!$E$2+'pengestrom_raw_19555305'!$E$3+'pengestrom_raw_19555305'!$E$4)-'pengestrom_raw_19555305'!$E$5,"+#,##0;-#,##0")) | F100: =IF(ABS(('pengestrom_raw_19555305'!$F$2+'pengestrom_raw_19555305'!$F$3+'pengestrom_raw_19555305'!$F$4)-'pengestrom_raw_19555305'!$F$5)<=2,"✓","⚠ "&TEXT(('pengestrom_raw_19555305'!$F$2+'pengestrom_raw_19555305'!$F$3+'pengestrom_raw_19555305'!$F$4)-'pengestrom_raw_19555305'!$F$5,"+#,##0;-#,##0"))

Sheet res_raw_19555305
A1: Resultatopgørelse & nøgleoplysninger (t.kr.) | B1: 2021 | C1: 2022 | D1: 2023 | E1: 2024 | F1: 2025
A2: Nettoomsætning | B2: 3066793 | C2: 3003311 | D2: 2796892 | E2: 2844360 | F2: 2959613
A3: Andre driftsindtægter | B3: 3503 | C3: 4846 | D3: 4105 | E3: 2819 | F3: 2847
A4: Vareforbrug | B4: 1869021 | C4: 1886147 | D4: 1778980 | E4: 1804016 | F4: 1814362
A5: Andre eksterne omkostninger | B5: 470806 | C5: 479214 | D5: 479086 | E5: 500025 | F5: 505728
A6: Bruttoresultat | B6: 730469 | C6: 642796 | D6: 542931 | E6: 543138 | F6: 642370
A7: Personaleomkostninger | B7: 440132 | C7: 451591 | D7: 435193 | E7: 439563 | F7: 463171
A8: Resultat før afskrivninger
A9: Af- og nedskrivninger | B9: 65506 | C9: 68741 | D9: 76967 | E9: 68385 | F9: 59134
A10: Andre driftsomkostninger | C10: 2664 | D10: 465 | E10: 787 | F10: 708
A11: Resultat af primær drift | B11: 224831 | C11: 119800 | D11: 30306 | E11: 34403 | F11: 119357
A12: Indtægter af kapitalandele, dattervirksomheder
A13: Finansielle indtægter | B13: 5 | C13: 328 | D13: 3229 | E13: 6085 | F13: 5993
A14: Finansielle omkostninger
A15: Finansielle poster, netto
A16: Resultat før skat | B16: 220032 | C16: 116623 | D16: 31717 | E16: 38892 | F16: 124233
A17: Skat af årets resultat | B17: 48492 | C17: 25969 | D17: 6995 | E17: 8704 | F17: 27451
A18: Årets resultat | B18: 171540 | C18: 90654 | D18: 24722 | E18: 30188 | F18: 96782
A19: Gns. antal medarbejdere | B19: 1113 | C19: 1134 | D19: 1095 | E19: 1001 | F19: 1003
A20: Investering i materielle anlægsaktiver

Sheet balance_raw_19555305
A1: Balance (t.kr.) | B1: 2021 | C1: 2022 | D1: 2023 | E1: 2024 | F1: 2025
A2: Immaterielle anlægsaktiver | B2: 22007 | C2: 42220 | D2: 23305 | E2: 8649 | F2: 9541
A3: Grunde og bygninger
A4: Produktionsanlæg og maskiner
A5: Driftsmateriel og inventar | B5: 189059 | C5: 217810 | D5: 211478 | E5: 204868 | F5: 194529
A6: Indretning af lejede lokaler | B6: 14260 | C6: 11178 | D6: 19221 | E6: 17615 | F6: 16838
A7: Forudbetaling og anlægsaktiver under opførelse
A8: Materielle anlægsaktiver | B8: 203319 | C8: 228988 | D8: 230699 | E8: 222483 | F8: 211367
A9: Anlægsaktiver | B9: 225326 | C9: 271208 | D9: 254004 | E9: 231132 | F9: 220908
A10: Råvarer og hjælpematerialer
A11: Varer under fremstilling
A12: Færdigvarer og handelsvarer | B12: 672250 | C12: 793657 | D12: 769481 | E12: 722739 | F12: 791746
A13: Varebeholdninger | B13: 672250 | C13: 793657 | D13: 769481 | E13: 722739 | F13: 791746
A14: Tilgodehavender fra salg og tjenesteydelser | B14: 57797 | C14: 37192 | D14: 83608 | E14: 74415 | F14: 47743
A15: Tilgodehavender hos tilknyttede virksomheder | B15: 47314 | C15: 65559 | D15: 32939 | E15: 3195 | F15: 29943
A16: Andre tilgodehavender | B16: 120 | C16: 808 | D16: 14365 | E16: 4254 | F16: 6725
A17: Periodeafgrænsningsposter (aktiver) | B17: 5032 | C17: 8775 | D17: 435 | E17: 6336 | F17: 9642
A18: Udskudt skatteaktiv
A19: Tilgodehavende skat hos tilknyttede virksomheder | B19: 32288 | C19: 64042 | D19: 62603 | E19: 25631 | F19: 18211
A20: Kortfristede skattetilgodehavender
A21: Tilgodehavender | B21: 142551 | C21: 176376 | D21: 193950 | E21: 113831 | F21: 112264
A22: Værdipapirer
A23: Likvide beholdninger | B23: 127204 | C23: 60423 | D23: 77537 | E23: 216020 | F23: 288703
A24: Omsætningsaktiver | B24: 942005 | C24: 1030456 | D24: 1040968 | E24: 1052590 | F24: 1192713
A25: Aktiver | B25: 1167331 | C25: 1301664 | D25: 1294972 | E25: 1283722 | F25: 1413621
A26: Selskabskapital | B26: 32000 | C26: 32000 | D26: 32000 | E26: 32000 | F26: 32000
A27: Reserve for nettoopskrivning (indre værdis metode)
A28: Reserve for udviklingsomkostninger
A29: Reserve for sikringstransaktioner
A30: Andre reserver
A31: Overført resultat | B31: 719688 | C31: 810342 | D31: 835064 | E31: 865252 | F31: 962034
A32: Egenkapital i alt | B32: 751688 | C32: 842342 | D32: 867064 | E32: 897252 | F32: 994034
A33: Hensættelse til udskudt skat | B33: 9926 | C33: 16993 | D33: 13055 | E33: 10128 | F33: 8707
A34: Hensatte forpligtelser | B34: 9926 | C34: 16993 | D34: 13055 | E34: 10128 | F34: 8707
A35: Ansvarlig lånekapital (langfristet)
A36: Langfristede lån
A37: Leasingforpligtelser (langfristet) | B37: 3576 | C37: 3298 | D37: 3443 | E37: 4221 | F37: 6100
A38: Anden gæld (langfristet) | B38: 100000 | C38: 0
A39: Langfristede gældsforpligtelser | B39: 103576 | C39: 3298 | D39: 3443 | E39: 4221 | F39: 6100
A40: Ansvarlig lånekapital (kortfristet)
A41: Kortfristet del af langfristede gældsforpligtelser | B41: 2769 | C41: 3068 | D41: 4881 | E41: 3723 | F41: 3677
A42: Kreditinstitutter | B42: 2903 | C42: 1443 | D42: 0
A43: Leasingforpligtelser (kortfristet)
A44: Leverandører af varer og tjenesteydelser | B44: 163970 | C44: 179229 | D44: 257164 | E44: 245732 | F44: 273688
A45: Gæld til tilknyttede virksomheder | B45: 3584 | C45: 139336 | D45: 17821 | E45: 7807 | F45: 9867
A46: Gæld til selskabsdeltagere og ledelse
A47: Selskabsskat
A48: Gæld til tilknyttede virksomheder vedr. selskabsskat
A49: Anden gæld (kortfristet) | B49: 125298 | C49: 111577 | D49: 129594 | E49: 112173 | F49: 116338
A50: Periodeafgrænsningsposter (passiver) | B50: 3617 | C50: 4378 | D50: 1950 | E50: 2686 | F50: 1210
A51: Kortfristede gældsforpligtelser | B51: 302141 | C51: 439031 | D51: 411410 | E51: 372121 | F51: 404780
A52: Gældsforpligtelser | B52: 405717 | C52: 442329 | D52: 414853 | E52: 376342 | F52: 410880
A53: Passiver | B53: 1167331 | C53: 1301664 | D53: 1294972 | E53: 1283722 | F53: 1413621

Sheet pengestrom_raw_19555305
A1: Pengestrømsopgørelse (t.kr.) | B1: 2021 | C1: 2022 | D1: 2023 | E1: 2024 | F1: 2025
A2: Pengestrømme fra driftsaktivitet | B2: 184758 | C2: 156672 | D2: 74039 | E2: 184376 | F2: 118646
A3: Pengestrømme fra investeringsaktivitet | B3: -72168 | C3: -119465 | D3: -59535 | E3: -45468 | F3: -47796
A4: Pengestrømme fra finansieringsaktivitet | B4: -1113 | C4: -102528 | D4: 4053 | E4: -425 | F4: 1833
A5: Årets pengestrøm

Sheet Simpel_arts
A1: Regnskabs- og nøgletal (CVR: 19555305) — artsopdelt
A3: Beløb i 1.000 kr. | B3: 2025 | C3: 2024 | D3: 2023 | F3: Note / XBRL-felt
A4: Uddrag af resultatopgørelse
A5: Nettoomsætning | B5: ='res_raw_19555305'!$F$2 | C5: ='res_raw_19555305'!$E$2 | D5: ='res_raw_19555305'!$D$2 | F5: fsa:Revenue
A6: Andre driftsindtægter | B6: ='res_raw_19555305'!$F$3 | C6: ='res_raw_19555305'!$E$3 | D6: ='res_raw_19555305'!$D$3 | F6: fsa:OtherOperatingIncome. Indtægter fra sekundære aktiviteter (huslejeindtægter, avance ved salg af anlæg mv.).
A7: Vareforbrug | B7: =-'res_raw_19555305'!$F$4 | C7: =-'res_raw_19555305'!$E$4 | D7: =-'res_raw_19555305'!$D$4 | F7: fsa:CostOfSales (vises negativt for korrekt SUM-formel).
A8: Andre eksterne omk. mv. | B8: =-'res_raw_19555305'!$F$5 | C8: =-'res_raw_19555305'!$E$5 | D8: =-'res_raw_19555305'!$D$5 | F8: fsa:OtherExternalExpenses (vises negativt). Husleje, energi, kontorhold mv.
A9: Bruttofortjeneste | B9: =SUM(B5:B8) | C9: =SUM(C5:C8) | D9: =SUM(D5:D8) | F9: Beregnet: Nettoomsætning + Andre driftsindt. − Vareforbrug − Andre ext. omk.
A10: Personaleomkostninger | B10: =-'res_raw_19555305'!$F$7 | C10: =-'res_raw_19555305'!$E$7 | D10: =-'res_raw_19555305'!$D$7 | F10: fsa:EmployeeBenefitsExpense (vises negativt). Lønninger, pension, sociale ydelser.
A11: Af- og nedskrivninger | B11: =-'res_raw_19555305'!$F$9 | C11: =-'res_raw_19555305'!$E$9 | D11: =-'res_raw_19555305'!$D$9 | F11: fsa:Depreciation (vises negativt). Af- og nedskrivninger på materielle og immaterielle anlægsaktiver.
A12: Andre driftsomkostninger | B12: =-'res_raw_19555305'!$F$10 | C12: =-'res_raw_19555305'!$E$10 | D12: =-'res_raw_19555305'!$D$10 | F12: fsa:OtherOperatingExpenses (vises negativt). Typisk 0 eller meget lille post.
A13: Resultat af primær drift | B13: =SUM(B9:B12) | C13: =SUM(C9:C12) | D13: =SUM(D9:D12) | F13: Beregnet: Bruttofortjeneste − Personaleomk. − Af- og nedskrivninger − Andre driftsomk. EBIT.
A14: Finansielle indtægter mv. | B14: =N('res_raw_19555305'!$F$12)+N('res_raw_19555305'!$F$13) | C14: =N('res_raw_19555305'!$E$12)+N('res_raw_19555305'!$E$13) | D14: =N('res_raw_19555305'!$D$12)+N('res_raw_19555305'!$D$13) | F14: fsa:IncomeFromSubsidiaries + fsa:OtherFinanceIncome.
A15: Finansielle omkostninger mv. | B15: =-'res_raw_19555305'!$F$14 | C15: =-'res_raw_19555305'!$E$14 | D15: =-'res_raw_19555305'!$D$14 | F15: fsa:OtherFinanceExpenses (vises negativt). Renteomkostninger, kurstab mv.
A16: Resultat før skat | B16: =SUM(B13:B15) | C16: =SUM(C13:C15) | D16: =SUM(D13:D15) | F16: Beregnet: EBIT + Fin. indtægter + Fin. omk. EBT.
A18: Uddrag af balance
A19: Anlægsaktiver | B19: ='balance_raw_19555305'!$F$9 | C19: ='balance_raw_19555305'!$E$9 | D19: ='balance_raw_19555305'!$D$9 | F19: fsa:NoncurrentAssets. Materielle, immaterielle og finansielle anlægsaktiver.
A20: Omsætningsaktiver | B20: ='balance_raw_19555305'!$F$24 | C20: ='balance_raw_19555305'!$E$24 | D20: ='balance_raw_19555305'!$D$24 | F20: fsa:CurrentAssets. Varebeholdninger, tilgodehavender, likvider.
A21: Aktiver i alt | B21: =SUM(B19:B20) | C21: =SUM(C19:C20) | D21: =SUM(D19:D20) | F21: Beregnet: Anlægsaktiver + Omsætningsaktiver. Bør matche fsa:Assets.
A23: Egenkapital | B23: ='balance_raw_19555305'!$F$32 | C23: ='balance_raw_19555305'!$E$32 | D23: ='balance_raw_19555305'!$D$32 | F23: fsa:Equity. Selskabskapital, overført resultat, reserver.
A24: Forpligtelser | B24: ='balance_raw_19555305'!$F$53-'balance_raw_19555305'!$F$32 | C24: ='balance_raw_19555305'!$E$53-'balance_raw_19555305'!$E$32 | D24: ='balance_raw_19555305'!$D$53-'balance_raw_19555305'!$D$32 | F24: Beregnet: Passiver (fsa:LiabilitiesAndEquity) − Egenkapital. Hensættelser + kort- og langfristet gæld.
A25: Passiver i alt | B25: =SUM(B23:B24) | C25: =SUM(C23:C24) | D25: =SUM(D23:D24) | F25: Beregnet: Egenkapital + Forpligtelser. Bør matche Aktiver i alt.
A27: Udvalgte balanceposter
A28: Varebeholdninger | B28: ='balance_raw_19555305'!$F$13 | C28: ='balance_raw_19555305'!$E$13 | D28: ='balance_raw_19555305'!$D$13 | F28: fsa:Inventories (eller fsa:ManufacturedGoodsAndGoodsForResale hvis total mangler).
A29: Tilgodehavender fra salg | B29: ='balance_raw_19555305'!$F$14 | C29: ='balance_raw_19555305'!$E$14 | D29: ='balance_raw_19555305'!$D$14 | F29: fsa:ShorttermTradeReceivables. Kortfristede tilgodehavender fra kunder.
A30: Kortfristede gældsforpligtelser | B30: ='balance_raw_19555305'!$F$51 | C30: ='balance_raw_19555305'!$E$51 | D30: ='balance_raw_19555305'!$D$51 | F30: fsa:ShorttermLiabilitiesOtherThanProvisions. Gæld der forfalder inden for 1 år.
A32: Rentabilitet
A33: Afkastningsgrad, % | B33: =IFERROR((B13+B14)/B21*100,"") | C33: =IFERROR((C13+C14)/C21*100,"") | D33: =IFERROR((D13+D14)/D21*100,"")
A34: Overskudsgrad, % | B34: =IFERROR((B13+B14)/B5*100,"") | C34: =IFERROR((C13+C14)/C5*100,"") | D34: =IFERROR((D13+D14)/D5*100,"")
A35: Aktivernes omsætningshastighed, gange | B35: =IFERROR(B5/B21,"") | C35: =IFERROR(C5/C21,"") | D35: =IFERROR(D5/D21,"")
A36: Gældsrente, % | B36: =IFERROR(-B15*100/B24,"") | C36: =IFERROR(-C15*100/C24,"") | D36: =IFERROR(-D15*100/D24,"")
A37: Egenkapitalens forrentning, % | B37: =IFERROR(B16/B23*100,"") | C37: =IFERROR(C16/C23*100,"") | D37: =IFERROR(D16/D23*100,"")
A38: Gearing, gange | B38: =IFERROR(B24/B23,"") | C38: =IFERROR(C24/C23,"") | D38: =IFERROR(D24/D23,"")
A40: Indekstal for indtjeningsevne (2023=100)
A41: Nettoomsætning | B41: =IFERROR(B5/$D5*100,"") | C41: =IFERROR(C5/$D5*100,"") | D41: =IFERROR(D5/$D5*100,"")
A42: Vareforbrug | B42: =IFERROR(B7/$D7*100,"") | C42: =IFERROR(C7/$D7*100,"") | D42: =IFERROR(D7/$D7*100,"")
A43: Andre eksterne omk. | B43: =IFERROR(B8/$D8*100,"") | C43: =IFERROR(C8/$D8*100,"") | D43: =IFERROR(D8/$D8*100,"")
A44: Personaleomkostninger | B44: =IFERROR(B10/$D10*100,"") | C44: =IFERROR(C10/$D10*100,"") | D44: =IFERROR(D10/$D10*100,"")
A45: Af- og nedskrivninger | B45: =IFERROR(B11/$D11*100,"") | C45: =IFERROR(C11/$D11*100,"") | D45: =IFERROR(D11/$D11*100,"")
A47: Indekstal for kapitaltilpasningsevne (2023=100)
A48: Nettoomsætning | B48: =IFERROR(B5*100/$D5,"") | C48: =IFERROR(C5*100/$D5,"") | D48: =IFERROR(D5*100/$D5,"")
A49: Anlægsaktiver | B49: =IFERROR(B19*100/$D19,"") | C49: =IFERROR(C19*100/$D19,"") | D49: =IFERROR(D19*100/$D19,"")
A50: Varebeholdninger | B50: =IFERROR(B28*100/$D28,"") | C50: =IFERROR(C28*100/$D28,"") | D50: =IFERROR(D28*100/$D28,"")
A51: Tilgodehavender fra salg | B51: =IFERROR(B29*100/$D29,"") | C51: =IFERROR(C29*100/$D29,"") | D51: =IFERROR(D29*100/$D29,"")
A53: Soliditet og likviditet
A54: Soliditetsgrad, % | B54: =IFERROR(B23*100/B21,"") | C54: =IFERROR(C23*100/C21,"") | D54: =IFERROR(D23*100/D21,"")
A55: Gældsandel, % | B55: =IFERROR(B24*100/B21,"") | C55: =IFERROR(C24*100/C21,"") | D55: =IFERROR(D24*100/D21,"")
A56: Likviditetsgrad, % | B56: =IFERROR(B20*100/B30,"") | C56: =IFERROR(C20*100/C30,"") | D56: =IFERROR(D20*100/D30,"")
A58: Kilde: Bearbejdet uddrag af årsrapporter for 2023-2025. Alle dataceller er live formler der peger på res_raw / balance_raw.
A60: Krydstjek mod rådata (tolerance: 1 t.kr.)
A61: Aktiver i alt = fsa:Assets | B61: =IF('balance_raw_19555305'!$F$25="","—",IF(ABS(B21-'balance_raw_19555305'!$F$25)<=1,"✓ OK","❌ "&TEXT(B21-'balance_raw_19555305'!$F$25,"+#,##0;-#,##0")&" t.kr.")) | C61: =IF('balance_raw_19555305'!$E$25="","—",IF(ABS(C21-'balance_raw_19555305'!$E$25)<=1,"✓ OK","❌ "&TEXT(C21-'balance_raw_19555305'!$E$25,"+#,##0;-#,##0")&" t.kr.")) | D61: =IF('balance_raw_19555305'!$D$25="","—",IF(ABS(D21-'balance_raw_19555305'!$D$25)<=1,"✓ OK","❌ "&TEXT(D21-'balance_raw_19555305'!$D$25,"+#,##0;-#,##0")&" t.kr.")) | F61: Verificerer at sum(Anlæg+Omsætning) matcher Assets-totalen.
A62: Passiver i alt = fsa:LiabilitiesAndEquity | B62: =IF('balance_raw_19555305'!$F$53="","—",IF(ABS(B25-'balance_raw_19555305'!$F$53)<=1,"✓ OK","❌ "&TEXT(B25-'balance_raw_19555305'!$F$53,"+#,##0;-#,##0")&" t.kr.")) | C62: =IF('balance_raw_19555305'!$E$53="","—",IF(ABS(C25-'balance_raw_19555305'!$E$53)<=1,"✓ OK","❌ "&TEXT(C25-'balance_raw_19555305'!$E$53,"+#,##0;-#,##0")&" t.kr.")) | D62: =IF('balance_raw_19555305'!$D$53="","—",IF(ABS(D25-'balance_raw_19555305'!$D$53)<=1,"✓ OK","❌ "&TEXT(D25-'balance_raw_19555305'!$D$53,"+#,##0;-#,##0")&" t.kr.")) | F62: Verificerer at sum(EK+Forpligtelser) matcher Passiver-totalen.
A63: Aktiver i alt = Passiver i alt | B63: =IF(ABS(B21-B25)<=1,"✓ OK","❌ "&TEXT(B21-B25,"+#,##0;-#,##0")&" t.kr.") | C63: =IF(ABS(C21-C25)<=1,"✓ OK","❌ "&TEXT(C21-C25,"+#,##0;-#,##0")&" t.kr.") | D63: =IF(ABS(D21-D25)<=1,"✓ OK","❌ "&TEXT(D21-D25,"+#,##0;-#,##0")&" t.kr.") | F63: Balance-identitet på arket selv. Skal altid være 0 differance.
A64: Bruttoresultat (beregnet) = fsa:GrossResult | B64: =IF('res_raw_19555305'!$F$6="","—",IF(ABS(B9-'res_raw_19555305'!$F$6)<=1,"✓ OK","❌ "&TEXT(B9-'res_raw_19555305'!$F$6,"+#,##0;-#,##0")&" t.kr.")) | C64: =IF('res_raw_19555305'!$E$6="","—",IF(ABS(C9-'res_raw_19555305'!$E$6)<=1,"✓ OK","❌ "&TEXT(C9-'res_raw_19555305'!$E$6,"+#,##0;-#,##0")&" t.kr.")) | D64: =IF('res_raw_19555305'!$D$6="","—",IF(ABS(D9-'res_raw_19555305'!$D$6)<=1,"✓ OK","❌ "&TEXT(D9-'res_raw_19555305'!$D$6,"+#,##0;-#,##0")&" t.kr.")) | F64: Hvis Nettoomsætning eller omkostninger mangler, vil sumberegnet bruttoresultat afvige.
A65: EBIT (beregnet) = fsa:ProfitLossFromOrdinaryOperatingActivities | B65: =IF('res_raw_19555305'!$F$11="","—",IF(ABS(B13-'res_raw_19555305'!$F$11)<=1,"✓ OK","❌ "&TEXT(B13-'res_raw_19555305'!$F$11,"+#,##0;-#,##0")&" t.kr.")) | C65: =IF('res_raw_19555305'!$E$11="","—",IF(ABS(C13-'res_raw_19555305'!$E$11)<=1,"✓ OK","❌ "&TEXT(C13-'res_raw_19555305'!$E$11,"+#,##0;-#,##0")&" t.kr.")) | D65: =IF('res_raw_19555305'!$D$11="","—",IF(ABS(D13-'res_raw_19555305'!$D$11)<=1,"✓ OK","❌ "&TEXT(D13-'res_raw_19555305'!$D$11,"+#,##0;-#,##0")&" t.kr.")) | F65: Verificerer at sumberegnet EBIT matcher det rapporterede.
A66: EBT (beregnet) = fsa:ProfitLossFromOrdinaryActivitiesBeforeTax | B66: =IF('res_raw_19555305'!$F$16="","—",IF(ABS(B16-'res_raw_19555305'!$F$16)<=1,"✓ OK","❌ "&TEXT(B16-'res_raw_19555305'!$F$16,"+#,##0;-#,##0")&" t.kr.")) | C66: =IF('res_raw_19555305'!$E$16="","—",IF(ABS(C16-'res_raw_19555305'!$E$16)<=1,"✓ OK","❌ "&TEXT(C16-'res_raw_19555305'!$E$16,"+#,##0;-#,##0")&" t.kr.")) | D66: =IF('res_raw_19555305'!$D$16="","—",IF(ABS(D16-'res_raw_19555305'!$D$16)<=1,"✓ OK","❌ "&TEXT(D16-'res_raw_19555305'!$D$16,"+#,##0;-#,##0")&" t.kr.")) | F66: Verificerer at sumberegnet resultat før skat matcher det rapporterede.
