Workbook

Sheet Overblik_25313763
A1: Regnskabsanalyse – Resultatopgørelse & Balance (t.EUR) · Klasse C-stor · Revision
H2: Indekstal (2021=100)
A3: Resultatopgørelse t.EUR | B3: 2021 | C3: 2022 | D3: 2023 | E3: 2024 | F3: 2025 | H3: 2021 | I3: 2022 | J3: 2023 | K3: 2024 | L3: 2025
A4: Nettoomsætning | B4: ='res_raw_25313763'!$B$2 | C4: ='res_raw_25313763'!$C$2 | D4: ='res_raw_25313763'!$D$2 | E4: ='res_raw_25313763'!$E$2 | F4: ='res_raw_25313763'!$F$2 | H4: =IFERROR(B4/$B$4*100,"") | I4: =IFERROR(C4/$B$4*100,"") | J4: =IFERROR(D4/$B$4*100,"") | K4: =IFERROR(E4/$B$4*100,"") | L4: =IFERROR(F4/$B$4*100,"")
A5: Produktionsomkostninger | B5: ='res_raw_25313763'!$B$3 | C5: ='res_raw_25313763'!$C$3 | D5: ='res_raw_25313763'!$D$3 | E5: ='res_raw_25313763'!$E$3 | F5: ='res_raw_25313763'!$F$3 | H5: =IFERROR(B5/$B$5*100,"") | I5: =IFERROR(C5/$B$5*100,"") | J5: =IFERROR(D5/$B$5*100,"") | K5: =IFERROR(E5/$B$5*100,"") | L5: =IFERROR(F5/$B$5*100,"")
A6: Bruttoresultat | B6: ='res_raw_25313763'!$B$4 | C6: ='res_raw_25313763'!$C$4 | D6: ='res_raw_25313763'!$D$4 | E6: ='res_raw_25313763'!$E$4 | F6: ='res_raw_25313763'!$F$4 | H6: =IFERROR(B6/$B$6*100,"") | I6: =IFERROR(C6/$B$6*100,"") | J6: =IFERROR(D6/$B$6*100,"") | K6: =IFERROR(E6/$B$6*100,"") | L6: =IFERROR(F6/$B$6*100,"")
A7: Salgs- og distributionsomkostninger | B7: ='res_raw_25313763'!$B$5 | C7: ='res_raw_25313763'!$C$5 | D7: ='res_raw_25313763'!$D$5 | E7: ='res_raw_25313763'!$E$5 | F7: ='res_raw_25313763'!$F$5 | H7: =IFERROR(B7/$B$7*100,"") | I7: =IFERROR(C7/$B$7*100,"") | J7: =IFERROR(D7/$B$7*100,"") | K7: =IFERROR(E7/$B$7*100,"") | L7: =IFERROR(F7/$B$7*100,"")
A8: Administrationsomkostninger | B8: ='res_raw_25313763'!$B$6 | C8: ='res_raw_25313763'!$C$6 | D8: ='res_raw_25313763'!$D$6 | E8: ='res_raw_25313763'!$E$6 | F8: ='res_raw_25313763'!$F$6 | H8: =IFERROR(B8/$B$8*100,"") | I8: =IFERROR(C8/$B$8*100,"") | J8: =IFERROR(D8/$B$8*100,"") | K8: =IFERROR(E8/$B$8*100,"") | L8: =IFERROR(F8/$B$8*100,"")
A9: Andre driftsindtægter | B9: ='res_raw_25313763'!$B$7 | C9: ='res_raw_25313763'!$C$7 | D9: ='res_raw_25313763'!$D$7 | E9: ='res_raw_25313763'!$E$7 | F9: ='res_raw_25313763'!$F$7 | H9: =IFERROR(B9/$B$9*100,"") | I9: =IFERROR(C9/$B$9*100,"") | J9: =IFERROR(D9/$B$9*100,"") | K9: =IFERROR(E9/$B$9*100,"") | L9: =IFERROR(F9/$B$9*100,"")
A10: Andre driftsomkostninger | B10: ='res_raw_25313763'!$B$8 | C10: ='res_raw_25313763'!$C$8 | D10: ='res_raw_25313763'!$D$8 | E10: ='res_raw_25313763'!$E$8 | F10: ='res_raw_25313763'!$F$8 | H10: =IFERROR(B10/$B$10*100,"") | I10: =IFERROR(C10/$B$10*100,"") | J10: =IFERROR(D10/$B$10*100,"") | K10: =IFERROR(E10/$B$10*100,"") | L10: =IFERROR(F10/$B$10*100,"")
A11: Resultat af primær drift | B11: ='res_raw_25313763'!$B$9 | C11: ='res_raw_25313763'!$C$9 | D11: ='res_raw_25313763'!$D$9 | E11: ='res_raw_25313763'!$E$9 | F11: ='res_raw_25313763'!$F$9 | H11: =IFERROR(B11/$B$11*100,"") | I11: =IFERROR(C11/$B$11*100,"") | J11: =IFERROR(D11/$B$11*100,"") | K11: =IFERROR(E11/$B$11*100,"") | L11: =IFERROR(F11/$B$11*100,"")
A12: Indtægter af kapitalandele, dattervirksomheder | B12: ='res_raw_25313763'!$B$10 | C12: ='res_raw_25313763'!$C$10 | D12: ='res_raw_25313763'!$D$10 | E12: ='res_raw_25313763'!$E$10 | F12: ='res_raw_25313763'!$F$10 | H12: =IFERROR(B12/$B$12*100,"") | I12: =IFERROR(C12/$B$12*100,"") | J12: =IFERROR(D12/$B$12*100,"") | K12: =IFERROR(E12/$B$12*100,"") | L12: =IFERROR(F12/$B$12*100,"")
A13: Finansielle indtægter | B13: ='res_raw_25313763'!$B$11 | C13: ='res_raw_25313763'!$C$11 | D13: ='res_raw_25313763'!$D$11 | E13: ='res_raw_25313763'!$E$11 | F13: ='res_raw_25313763'!$F$11 | H13: =IFERROR(B13/$B$13*100,"") | I13: =IFERROR(C13/$B$13*100,"") | J13: =IFERROR(D13/$B$13*100,"") | K13: =IFERROR(E13/$B$13*100,"") | L13: =IFERROR(F13/$B$13*100,"")
A14: Finansielle omkostninger | B14: ='res_raw_25313763'!$B$12 | C14: ='res_raw_25313763'!$C$12 | D14: ='res_raw_25313763'!$D$12 | E14: ='res_raw_25313763'!$E$12 | F14: ='res_raw_25313763'!$F$12 | H14: =IFERROR(B14/$B$14*100,"") | I14: =IFERROR(C14/$B$14*100,"") | J14: =IFERROR(D14/$B$14*100,"") | K14: =IFERROR(E14/$B$14*100,"") | L14: =IFERROR(F14/$B$14*100,"")
A15: Finansielle poster, netto | B15: ='res_raw_25313763'!$B$13 | C15: ='res_raw_25313763'!$C$13 | D15: ='res_raw_25313763'!$D$13 | E15: ='res_raw_25313763'!$E$13 | F15: ='res_raw_25313763'!$F$13 | H15: =IFERROR(B15/$B$15*100,"") | I15: =IFERROR(C15/$B$15*100,"") | J15: =IFERROR(D15/$B$15*100,"") | K15: =IFERROR(E15/$B$15*100,"") | L15: =IFERROR(F15/$B$15*100,"")
A16: Resultat før skat | B16: ='res_raw_25313763'!$B$14 | C16: ='res_raw_25313763'!$C$14 | D16: ='res_raw_25313763'!$D$14 | E16: ='res_raw_25313763'!$E$14 | F16: ='res_raw_25313763'!$F$14 | H16: =IFERROR(B16/$B$16*100,"") | I16: =IFERROR(C16/$B$16*100,"") | J16: =IFERROR(D16/$B$16*100,"") | K16: =IFERROR(E16/$B$16*100,"") | L16: =IFERROR(F16/$B$16*100,"")
A17: Skat af årets resultat | B17: ='res_raw_25313763'!$B$15 | C17: ='res_raw_25313763'!$C$15 | D17: ='res_raw_25313763'!$D$15 | E17: ='res_raw_25313763'!$E$15 | F17: ='res_raw_25313763'!$F$15 | H17: =IFERROR(B17/$B$17*100,"") | I17: =IFERROR(C17/$B$17*100,"") | J17: =IFERROR(D17/$B$17*100,"") | K17: =IFERROR(E17/$B$17*100,"") | L17: =IFERROR(F17/$B$17*100,"")
A18: Årets resultat | B18: ='res_raw_25313763'!$B$16 | C18: ='res_raw_25313763'!$C$16 | D18: ='res_raw_25313763'!$D$16 | E18: ='res_raw_25313763'!$E$16 | F18: ='res_raw_25313763'!$F$16 | H18: =IFERROR(B18/$B$18*100,"") | I18: =IFERROR(C18/$B$18*100,"") | J18: =IFERROR(D18/$B$18*100,"") | K18: =IFERROR(E18/$B$18*100,"") | L18: =IFERROR(F18/$B$18*100,"")
A20: AKTIVER t.EUR | B20: 2021 | C20: 2022 | D20: 2023 | E20: 2024 | F20: 2025 | H20: 2021 | I20: 2022 | J20: 2023 | K20: 2024 | L20: 2025
A21: Udviklingsprojekter | B21: ='balance_raw_25313763'!$B$2 | C21: ='balance_raw_25313763'!$C$2 | D21: ='balance_raw_25313763'!$D$2 | E21: ='balance_raw_25313763'!$E$2 | F21: ='balance_raw_25313763'!$F$2 | H21: =IFERROR(B21/$B$21*100,"") | I21: =IFERROR(C21/$B$21*100,"") | J21: =IFERROR(D21/$B$21*100,"") | K21: =IFERROR(E21/$B$21*100,"") | L21: =IFERROR(F21/$B$21*100,"")
A22: Patenter, varemærker mv. | B22: ='balance_raw_25313763'!$B$3 | C22: ='balance_raw_25313763'!$C$3 | D22: ='balance_raw_25313763'!$D$3 | E22: ='balance_raw_25313763'!$E$3 | F22: ='balance_raw_25313763'!$F$3 | H22: =IFERROR(B22/$B$22*100,"") | I22: =IFERROR(C22/$B$22*100,"") | J22: =IFERROR(D22/$B$22*100,"") | K22: =IFERROR(E22/$B$22*100,"") | L22: =IFERROR(F22/$B$22*100,"")
A23: Goodwill | B23: ='balance_raw_25313763'!$B$4 | C23: ='balance_raw_25313763'!$C$4 | D23: ='balance_raw_25313763'!$D$4 | E23: ='balance_raw_25313763'!$E$4 | F23: ='balance_raw_25313763'!$F$4 | H23: =IFERROR(B23/$B$23*100,"") | I23: =IFERROR(C23/$B$23*100,"") | J23: =IFERROR(D23/$B$23*100,"") | K23: =IFERROR(E23/$B$23*100,"") | L23: =IFERROR(F23/$B$23*100,"")
A24: Immaterielle anlægsaktiver | B24: ='balance_raw_25313763'!$B$5 | C24: ='balance_raw_25313763'!$C$5 | D24: ='balance_raw_25313763'!$D$5 | E24: ='balance_raw_25313763'!$E$5 | F24: ='balance_raw_25313763'!$F$5 | H24: =IFERROR(B24/$B$24*100,"") | I24: =IFERROR(C24/$B$24*100,"") | J24: =IFERROR(D24/$B$24*100,"") | K24: =IFERROR(E24/$B$24*100,"") | L24: =IFERROR(F24/$B$24*100,"")
A25: Materielle anlægsaktiver | B25: ='balance_raw_25313763'!$B$6 | C25: ='balance_raw_25313763'!$C$6 | D25: ='balance_raw_25313763'!$D$6 | E25: ='balance_raw_25313763'!$E$6 | F25: ='balance_raw_25313763'!$F$6 | H25: =IFERROR(B25/$B$25*100,"") | I25: =IFERROR(C25/$B$25*100,"") | J25: =IFERROR(D25/$B$25*100,"") | K25: =IFERROR(E25/$B$25*100,"") | L25: =IFERROR(F25/$B$25*100,"")
A26: Kapitalandele, dattervirksomheder | B26: ='balance_raw_25313763'!$B$7 | C26: ='balance_raw_25313763'!$C$7 | D26: ='balance_raw_25313763'!$D$7 | E26: ='balance_raw_25313763'!$E$7 | F26: ='balance_raw_25313763'!$F$7 | H26: =IFERROR(B26/$B$26*100,"") | I26: =IFERROR(C26/$B$26*100,"") | J26: =IFERROR(D26/$B$26*100,"") | K26: =IFERROR(E26/$B$26*100,"") | L26: =IFERROR(F26/$B$26*100,"")
A27: Deposita | B27: ='balance_raw_25313763'!$B$8 | C27: ='balance_raw_25313763'!$C$8 | D27: ='balance_raw_25313763'!$D$8 | E27: ='balance_raw_25313763'!$E$8 | F27: ='balance_raw_25313763'!$F$8 | H27: =IFERROR(B27/$B$27*100,"") | I27: =IFERROR(C27/$B$27*100,"") | J27: =IFERROR(D27/$B$27*100,"") | K27: =IFERROR(E27/$B$27*100,"") | L27: =IFERROR(F27/$B$27*100,"")
A28: Finansielle anlægsaktiver | B28: ='balance_raw_25313763'!$B$9 | C28: ='balance_raw_25313763'!$C$9 | D28: ='balance_raw_25313763'!$D$9 | E28: ='balance_raw_25313763'!$E$9 | F28: ='balance_raw_25313763'!$F$9 | H28: =IFERROR(B28/$B$28*100,"") | I28: =IFERROR(C28/$B$28*100,"") | J28: =IFERROR(D28/$B$28*100,"") | K28: =IFERROR(E28/$B$28*100,"") | L28: =IFERROR(F28/$B$28*100,"")
A29: Anlægsaktiver | B29: ='balance_raw_25313763'!$B$10 | C29: ='balance_raw_25313763'!$C$10 | D29: ='balance_raw_25313763'!$D$10 | E29: ='balance_raw_25313763'!$E$10 | F29: ='balance_raw_25313763'!$F$10 | H29: =IFERROR(B29/$B$29*100,"") | I29: =IFERROR(C29/$B$29*100,"") | J29: =IFERROR(D29/$B$29*100,"") | K29: =IFERROR(E29/$B$29*100,"") | L29: =IFERROR(F29/$B$29*100,"")
A30: Varebeholdninger | B30: ='balance_raw_25313763'!$B$11 | C30: ='balance_raw_25313763'!$C$11 | D30: ='balance_raw_25313763'!$D$11 | E30: ='balance_raw_25313763'!$E$11 | F30: ='balance_raw_25313763'!$F$11 | H30: =IFERROR(B30/$B$30*100,"") | I30: =IFERROR(C30/$B$30*100,"") | J30: =IFERROR(D30/$B$30*100,"") | K30: =IFERROR(E30/$B$30*100,"") | L30: =IFERROR(F30/$B$30*100,"")
A31: Tilgodehavender fra salg og tjenesteydelser | B31: ='balance_raw_25313763'!$B$12 | C31: ='balance_raw_25313763'!$C$12 | D31: ='balance_raw_25313763'!$D$12 | E31: ='balance_raw_25313763'!$E$12 | F31: ='balance_raw_25313763'!$F$12 | H31: =IFERROR(B31/$B$31*100,"") | I31: =IFERROR(C31/$B$31*100,"") | J31: =IFERROR(D31/$B$31*100,"") | K31: =IFERROR(E31/$B$31*100,"") | L31: =IFERROR(F31/$B$31*100,"")
A32: Tilgodehavender hos tilknyttede virksomheder | B32: ='balance_raw_25313763'!$B$13 | C32: ='balance_raw_25313763'!$C$13 | D32: ='balance_raw_25313763'!$D$13 | E32: ='balance_raw_25313763'!$E$13 | F32: ='balance_raw_25313763'!$F$13 | H32: =IFERROR(B32/$B$32*100,"") | I32: =IFERROR(C32/$B$32*100,"") | J32: =IFERROR(D32/$B$32*100,"") | K32: =IFERROR(E32/$B$32*100,"") | L32: =IFERROR(F32/$B$32*100,"")
A33: Andre tilgodehavender | B33: ='balance_raw_25313763'!$B$14 | C33: ='balance_raw_25313763'!$C$14 | D33: ='balance_raw_25313763'!$D$14 | E33: ='balance_raw_25313763'!$E$14 | F33: ='balance_raw_25313763'!$F$14 | H33: =IFERROR(B33/$B$33*100,"") | I33: =IFERROR(C33/$B$33*100,"") | J33: =IFERROR(D33/$B$33*100,"") | K33: =IFERROR(E33/$B$33*100,"") | L33: =IFERROR(F33/$B$33*100,"")
A34: Periodeafgrænsningsposter (aktiver) | B34: ='balance_raw_25313763'!$B$15 | C34: ='balance_raw_25313763'!$C$15 | D34: ='balance_raw_25313763'!$D$15 | E34: ='balance_raw_25313763'!$E$15 | F34: ='balance_raw_25313763'!$F$15 | H34: =IFERROR(B34/$B$34*100,"") | I34: =IFERROR(C34/$B$34*100,"") | J34: =IFERROR(D34/$B$34*100,"") | K34: =IFERROR(E34/$B$34*100,"") | L34: =IFERROR(F34/$B$34*100,"")
A35: Udskudt skatteaktiv | B35: ='balance_raw_25313763'!$B$16 | C35: ='balance_raw_25313763'!$C$16 | D35: ='balance_raw_25313763'!$D$16 | E35: ='balance_raw_25313763'!$E$16 | F35: ='balance_raw_25313763'!$F$16 | H35: =IFERROR(B35/$B$35*100,"") | I35: =IFERROR(C35/$B$35*100,"") | J35: =IFERROR(D35/$B$35*100,"") | K35: =IFERROR(E35/$B$35*100,"") | L35: =IFERROR(F35/$B$35*100,"")
A36: Tilgodehavende skat hos tilknyttede virksomheder | B36: ='balance_raw_25313763'!$B$17 | C36: ='balance_raw_25313763'!$C$17 | D36: ='balance_raw_25313763'!$D$17 | E36: ='balance_raw_25313763'!$E$17 | F36: ='balance_raw_25313763'!$F$17 | H36: =IFERROR(B36/$B$36*100,"") | I36: =IFERROR(C36/$B$36*100,"") | J36: =IFERROR(D36/$B$36*100,"") | K36: =IFERROR(E36/$B$36*100,"") | L36: =IFERROR(F36/$B$36*100,"")
A37: Kortfristede skattetilgodehavender | B37: ='balance_raw_25313763'!$B$18 | C37: ='balance_raw_25313763'!$C$18 | D37: ='balance_raw_25313763'!$D$18 | E37: ='balance_raw_25313763'!$E$18 | F37: ='balance_raw_25313763'!$F$18 | H37: =IFERROR(B37/$B$37*100,"") | I37: =IFERROR(C37/$B$37*100,"") | J37: =IFERROR(D37/$B$37*100,"") | K37: =IFERROR(E37/$B$37*100,"") | L37: =IFERROR(F37/$B$37*100,"")
A38: Tilgodehavender | B38: ='balance_raw_25313763'!$B$19 | C38: ='balance_raw_25313763'!$C$19 | D38: ='balance_raw_25313763'!$D$19 | E38: ='balance_raw_25313763'!$E$19 | F38: ='balance_raw_25313763'!$F$19 | H38: =IFERROR(B38/$B$38*100,"") | I38: =IFERROR(C38/$B$38*100,"") | J38: =IFERROR(D38/$B$38*100,"") | K38: =IFERROR(E38/$B$38*100,"") | L38: =IFERROR(F38/$B$38*100,"")
A39: Værdipapirer | B39: ='balance_raw_25313763'!$B$20 | C39: ='balance_raw_25313763'!$C$20 | D39: ='balance_raw_25313763'!$D$20 | E39: ='balance_raw_25313763'!$E$20 | F39: ='balance_raw_25313763'!$F$20 | H39: =IFERROR(B39/$B$39*100,"") | I39: =IFERROR(C39/$B$39*100,"") | J39: =IFERROR(D39/$B$39*100,"") | K39: =IFERROR(E39/$B$39*100,"") | L39: =IFERROR(F39/$B$39*100,"")
A40: Likvide beholdninger | B40: ='balance_raw_25313763'!$B$21 | C40: ='balance_raw_25313763'!$C$21 | D40: ='balance_raw_25313763'!$D$21 | E40: ='balance_raw_25313763'!$E$21 | F40: ='balance_raw_25313763'!$F$21 | H40: =IFERROR(B40/$B$40*100,"") | I40: =IFERROR(C40/$B$40*100,"") | J40: =IFERROR(D40/$B$40*100,"") | K40: =IFERROR(E40/$B$40*100,"") | L40: =IFERROR(F40/$B$40*100,"")
A41: Omsætningsaktiver | B41: ='balance_raw_25313763'!$B$22 | C41: ='balance_raw_25313763'!$C$22 | D41: ='balance_raw_25313763'!$D$22 | E41: ='balance_raw_25313763'!$E$22 | F41: ='balance_raw_25313763'!$F$22 | H41: =IFERROR(B41/$B$41*100,"") | I41: =IFERROR(C41/$B$41*100,"") | J41: =IFERROR(D41/$B$41*100,"") | K41: =IFERROR(E41/$B$41*100,"") | L41: =IFERROR(F41/$B$41*100,"")
A42: Aktiver | B42: ='balance_raw_25313763'!$B$23 | C42: ='balance_raw_25313763'!$C$23 | D42: ='balance_raw_25313763'!$D$23 | E42: ='balance_raw_25313763'!$E$23 | F42: ='balance_raw_25313763'!$F$23 | H42: =IFERROR(B42/$B$42*100,"") | I42: =IFERROR(C42/$B$42*100,"") | J42: =IFERROR(D42/$B$42*100,"") | K42: =IFERROR(E42/$B$42*100,"") | L42: =IFERROR(F42/$B$42*100,"")
A44: PASSIVER t.EUR | B44: 2021 | C44: 2022 | D44: 2023 | E44: 2024 | F44: 2025 | H44: 2021 | I44: 2022 | J44: 2023 | K44: 2024 | L44: 2025
A45: Selskabskapital | B45: ='balance_raw_25313763'!$B$24 | C45: ='balance_raw_25313763'!$C$24 | D45: ='balance_raw_25313763'!$D$24 | E45: ='balance_raw_25313763'!$E$24 | F45: ='balance_raw_25313763'!$F$24 | H45: =IFERROR(B45/$B$45*100,"") | I45: =IFERROR(C45/$B$45*100,"") | J45: =IFERROR(D45/$B$45*100,"") | K45: =IFERROR(E45/$B$45*100,"") | L45: =IFERROR(F45/$B$45*100,"")
A46: Reserve for nettoopskrivning (indre værdis metode) | B46: ='balance_raw_25313763'!$B$25 | C46: ='balance_raw_25313763'!$C$25 | D46: ='balance_raw_25313763'!$D$25 | E46: ='balance_raw_25313763'!$E$25 | F46: ='balance_raw_25313763'!$F$25 | H46: =IFERROR(B46/$B$46*100,"") | I46: =IFERROR(C46/$B$46*100,"") | J46: =IFERROR(D46/$B$46*100,"") | K46: =IFERROR(E46/$B$46*100,"") | L46: =IFERROR(F46/$B$46*100,"")
A47: Reserve for udviklingsomkostninger | B47: ='balance_raw_25313763'!$B$26 | C47: ='balance_raw_25313763'!$C$26 | D47: ='balance_raw_25313763'!$D$26 | E47: ='balance_raw_25313763'!$E$26 | F47: ='balance_raw_25313763'!$F$26 | H47: =IFERROR(B47/$B$47*100,"") | I47: =IFERROR(C47/$B$47*100,"") | J47: =IFERROR(D47/$B$47*100,"") | K47: =IFERROR(E47/$B$47*100,"") | L47: =IFERROR(F47/$B$47*100,"")
A48: Reserve for sikringstransaktioner | B48: ='balance_raw_25313763'!$B$27 | C48: ='balance_raw_25313763'!$C$27 | D48: ='balance_raw_25313763'!$D$27 | E48: ='balance_raw_25313763'!$E$27 | F48: ='balance_raw_25313763'!$F$27 | H48: =IFERROR(B48/$B$48*100,"") | I48: =IFERROR(C48/$B$48*100,"") | J48: =IFERROR(D48/$B$48*100,"") | K48: =IFERROR(E48/$B$48*100,"") | L48: =IFERROR(F48/$B$48*100,"")
A49: Andre reserver | B49: ='balance_raw_25313763'!$B$28 | C49: ='balance_raw_25313763'!$C$28 | D49: ='balance_raw_25313763'!$D$28 | E49: ='balance_raw_25313763'!$E$28 | F49: ='balance_raw_25313763'!$F$28 | H49: =IFERROR(B49/$B$49*100,"") | I49: =IFERROR(C49/$B$49*100,"") | J49: =IFERROR(D49/$B$49*100,"") | K49: =IFERROR(E49/$B$49*100,"") | L49: =IFERROR(F49/$B$49*100,"")
A50: Overført resultat | B50: ='balance_raw_25313763'!$B$29 | C50: ='balance_raw_25313763'!$C$29 | D50: ='balance_raw_25313763'!$D$29 | E50: ='balance_raw_25313763'!$E$29 | F50: ='balance_raw_25313763'!$F$29 | H50: =IFERROR(B50/$B$50*100,"") | I50: =IFERROR(C50/$B$50*100,"") | J50: =IFERROR(D50/$B$50*100,"") | K50: =IFERROR(E50/$B$50*100,"") | L50: =IFERROR(F50/$B$50*100,"")
A51: Egenkapital i alt | B51: ='balance_raw_25313763'!$B$30 | C51: ='balance_raw_25313763'!$C$30 | D51: ='balance_raw_25313763'!$D$30 | E51: ='balance_raw_25313763'!$E$30 | F51: ='balance_raw_25313763'!$F$30 | H51: =IFERROR(B51/$B$51*100,"") | I51: =IFERROR(C51/$B$51*100,"") | J51: =IFERROR(D51/$B$51*100,"") | K51: =IFERROR(E51/$B$51*100,"") | L51: =IFERROR(F51/$B$51*100,"")
A52: Hensættelse til udskudt skat | B52: ='balance_raw_25313763'!$B$31 | C52: ='balance_raw_25313763'!$C$31 | D52: ='balance_raw_25313763'!$D$31 | E52: ='balance_raw_25313763'!$E$31 | F52: ='balance_raw_25313763'!$F$31 | H52: =IFERROR(B52/$B$52*100,"") | I52: =IFERROR(C52/$B$52*100,"") | J52: =IFERROR(D52/$B$52*100,"") | K52: =IFERROR(E52/$B$52*100,"") | L52: =IFERROR(F52/$B$52*100,"")
A53: Hensatte forpligtelser | B53: ='balance_raw_25313763'!$B$32 | C53: ='balance_raw_25313763'!$C$32 | D53: ='balance_raw_25313763'!$D$32 | E53: ='balance_raw_25313763'!$E$32 | F53: ='balance_raw_25313763'!$F$32 | H53: =IFERROR(B53/$B$53*100,"") | I53: =IFERROR(C53/$B$53*100,"") | J53: =IFERROR(D53/$B$53*100,"") | K53: =IFERROR(E53/$B$53*100,"") | L53: =IFERROR(F53/$B$53*100,"")
A54: Langfristede gældsforpligtelser | B54: ='balance_raw_25313763'!$B$33 | C54: ='balance_raw_25313763'!$C$33 | D54: ='balance_raw_25313763'!$D$33 | E54: ='balance_raw_25313763'!$E$33 | F54: ='balance_raw_25313763'!$F$33 | H54: =IFERROR(B54/$B$54*100,"") | I54: =IFERROR(C54/$B$54*100,"") | J54: =IFERROR(D54/$B$54*100,"") | K54: =IFERROR(E54/$B$54*100,"") | L54: =IFERROR(F54/$B$54*100,"")
A55: Ansvarlig lånekapital (kortfristet) | B55: ='balance_raw_25313763'!$B$34 | C55: ='balance_raw_25313763'!$C$34 | D55: ='balance_raw_25313763'!$D$34 | E55: ='balance_raw_25313763'!$E$34 | F55: ='balance_raw_25313763'!$F$34 | H55: =IFERROR(B55/$B$55*100,"") | I55: =IFERROR(C55/$B$55*100,"") | J55: =IFERROR(D55/$B$55*100,"") | K55: =IFERROR(E55/$B$55*100,"") | L55: =IFERROR(F55/$B$55*100,"")
A56: Kortfristet del af langfristede gældsforpligtelser | B56: ='balance_raw_25313763'!$B$35 | C56: ='balance_raw_25313763'!$C$35 | D56: ='balance_raw_25313763'!$D$35 | E56: ='balance_raw_25313763'!$E$35 | F56: ='balance_raw_25313763'!$F$35 | H56: =IFERROR(B56/$B$56*100,"") | I56: =IFERROR(C56/$B$56*100,"") | J56: =IFERROR(D56/$B$56*100,"") | K56: =IFERROR(E56/$B$56*100,"") | L56: =IFERROR(F56/$B$56*100,"")
A57: Kreditinstitutter | B57: ='balance_raw_25313763'!$B$36 | C57: ='balance_raw_25313763'!$C$36 | D57: ='balance_raw_25313763'!$D$36 | E57: ='balance_raw_25313763'!$E$36 | F57: ='balance_raw_25313763'!$F$36 | H57: =IFERROR(B57/$B$57*100,"") | I57: =IFERROR(C57/$B$57*100,"") | J57: =IFERROR(D57/$B$57*100,"") | K57: =IFERROR(E57/$B$57*100,"") | L57: =IFERROR(F57/$B$57*100,"")
A58: Leasingforpligtelser (kortfristet) | B58: ='balance_raw_25313763'!$B$37 | C58: ='balance_raw_25313763'!$C$37 | D58: ='balance_raw_25313763'!$D$37 | E58: ='balance_raw_25313763'!$E$37 | F58: ='balance_raw_25313763'!$F$37 | H58: =IFERROR(B58/$B$58*100,"") | I58: =IFERROR(C58/$B$58*100,"") | J58: =IFERROR(D58/$B$58*100,"") | K58: =IFERROR(E58/$B$58*100,"") | L58: =IFERROR(F58/$B$58*100,"")
A59: Leverandører af varer og tjenesteydelser | B59: ='balance_raw_25313763'!$B$38 | C59: ='balance_raw_25313763'!$C$38 | D59: ='balance_raw_25313763'!$D$38 | E59: ='balance_raw_25313763'!$E$38 | F59: ='balance_raw_25313763'!$F$38 | H59: =IFERROR(B59/$B$59*100,"") | I59: =IFERROR(C59/$B$59*100,"") | J59: =IFERROR(D59/$B$59*100,"") | K59: =IFERROR(E59/$B$59*100,"") | L59: =IFERROR(F59/$B$59*100,"")
A60: Gæld til tilknyttede virksomheder | B60: ='balance_raw_25313763'!$B$39 | C60: ='balance_raw_25313763'!$C$39 | D60: ='balance_raw_25313763'!$D$39 | E60: ='balance_raw_25313763'!$E$39 | F60: ='balance_raw_25313763'!$F$39 | H60: =IFERROR(B60/$B$60*100,"") | I60: =IFERROR(C60/$B$60*100,"") | J60: =IFERROR(D60/$B$60*100,"") | K60: =IFERROR(E60/$B$60*100,"") | L60: =IFERROR(F60/$B$60*100,"")
A61: Gæld til selskabsdeltagere og ledelse | B61: ='balance_raw_25313763'!$B$40 | C61: ='balance_raw_25313763'!$C$40 | D61: ='balance_raw_25313763'!$D$40 | E61: ='balance_raw_25313763'!$E$40 | F61: ='balance_raw_25313763'!$F$40 | H61: =IFERROR(B61/$B$61*100,"") | I61: =IFERROR(C61/$B$61*100,"") | J61: =IFERROR(D61/$B$61*100,"") | K61: =IFERROR(E61/$B$61*100,"") | L61: =IFERROR(F61/$B$61*100,"")
A62: Selskabsskat | B62: ='balance_raw_25313763'!$B$41 | C62: ='balance_raw_25313763'!$C$41 | D62: ='balance_raw_25313763'!$D$41 | E62: ='balance_raw_25313763'!$E$41 | F62: ='balance_raw_25313763'!$F$41 | H62: =IFERROR(B62/$B$62*100,"") | I62: =IFERROR(C62/$B$62*100,"") | J62: =IFERROR(D62/$B$62*100,"") | K62: =IFERROR(E62/$B$62*100,"") | L62: =IFERROR(F62/$B$62*100,"")
A63: Gæld til tilknyttede virksomheder vedr. selskabsskat | B63: ='balance_raw_25313763'!$B$42 | C63: ='balance_raw_25313763'!$C$42 | D63: ='balance_raw_25313763'!$D$42 | E63: ='balance_raw_25313763'!$E$42 | F63: ='balance_raw_25313763'!$F$42 | H63: =IFERROR(B63/$B$63*100,"") | I63: =IFERROR(C63/$B$63*100,"") | J63: =IFERROR(D63/$B$63*100,"") | K63: =IFERROR(E63/$B$63*100,"") | L63: =IFERROR(F63/$B$63*100,"")
A64: Anden gæld (kortfristet) | B64: ='balance_raw_25313763'!$B$43 | C64: ='balance_raw_25313763'!$C$43 | D64: ='balance_raw_25313763'!$D$43 | E64: ='balance_raw_25313763'!$E$43 | F64: ='balance_raw_25313763'!$F$43 | H64: =IFERROR(B64/$B$64*100,"") | I64: =IFERROR(C64/$B$64*100,"") | J64: =IFERROR(D64/$B$64*100,"") | K64: =IFERROR(E64/$B$64*100,"") | L64: =IFERROR(F64/$B$64*100,"")
A65: Periodeafgrænsningsposter (passiver) | B65: ='balance_raw_25313763'!$B$44 | C65: ='balance_raw_25313763'!$C$44 | D65: ='balance_raw_25313763'!$D$44 | E65: ='balance_raw_25313763'!$E$44 | F65: ='balance_raw_25313763'!$F$44 | H65: =IFERROR(B65/$B$65*100,"") | I65: =IFERROR(C65/$B$65*100,"") | J65: =IFERROR(D65/$B$65*100,"") | K65: =IFERROR(E65/$B$65*100,"") | L65: =IFERROR(F65/$B$65*100,"")
A66: Kortfristede gældsforpligtelser | B66: ='balance_raw_25313763'!$B$45 | C66: ='balance_raw_25313763'!$C$45 | D66: ='balance_raw_25313763'!$D$45 | E66: ='balance_raw_25313763'!$E$45 | F66: ='balance_raw_25313763'!$F$45 | H66: =IFERROR(B66/$B$66*100,"") | I66: =IFERROR(C66/$B$66*100,"") | J66: =IFERROR(D66/$B$66*100,"") | K66: =IFERROR(E66/$B$66*100,"") | L66: =IFERROR(F66/$B$66*100,"")
A67: Gældsforpligtelser | B67: ='balance_raw_25313763'!$B$46 | C67: ='balance_raw_25313763'!$C$46 | D67: ='balance_raw_25313763'!$D$46 | E67: ='balance_raw_25313763'!$E$46 | F67: ='balance_raw_25313763'!$F$46 | H67: =IFERROR(B67/$B$67*100,"") | I67: =IFERROR(C67/$B$67*100,"") | J67: =IFERROR(D67/$B$67*100,"") | K67: =IFERROR(E67/$B$67*100,"") | L67: =IFERROR(F67/$B$67*100,"")
A68: Passiver | B68: ='balance_raw_25313763'!$B$47 | C68: ='balance_raw_25313763'!$C$47 | D68: ='balance_raw_25313763'!$D$47 | E68: ='balance_raw_25313763'!$E$47 | F68: ='balance_raw_25313763'!$F$47 | H68: =IFERROR(B68/$B$68*100,"") | I68: =IFERROR(C68/$B$68*100,"") | J68: =IFERROR(D68/$B$68*100,"") | K68: =IFERROR(E68/$B$68*100,"") | L68: =IFERROR(F68/$B$68*100,"")
A70: NØGLEOPLYSNINGER | B70: 2021 | C70: 2022 | D70: 2023 | E70: 2024 | F70: 2025
A71: Gns. antal medarbejdere | B71: ='res_raw_25313763'!$B$17 | C71: ='res_raw_25313763'!$C$17 | D71: ='res_raw_25313763'!$D$17 | E71: ='res_raw_25313763'!$E$17 | F71: ='res_raw_25313763'!$F$17 | H71: =IFERROR(B71/$B$71*100,"") | I71: =IFERROR(C71/$B$71*100,"") | J71: =IFERROR(D71/$B$71*100,"") | K71: =IFERROR(E71/$B$71*100,"") | L71: =IFERROR(F71/$B$71*100,"")
A72: Investering i materielle anlægsaktiver | B72: ='res_raw_25313763'!$B$18 | C72: ='res_raw_25313763'!$C$18 | D72: ='res_raw_25313763'!$D$18 | E72: ='res_raw_25313763'!$E$18 | F72: ='res_raw_25313763'!$F$18 | H72: =IFERROR(B72/$B$72*100,"") | I72: =IFERROR(C72/$B$72*100,"") | J72: =IFERROR(D72/$B$72*100,"") | K72: =IFERROR(E72/$B$72*100,"") | L72: =IFERROR(F72/$B$72*100,"")
A74: NØGLETAL | B74: 2021 | C74: 2022 | D74: 2023 | E74: 2024 | F74: 2025
A75: Afkastningsgrad, % | B75: =IFERROR(($B$11+$B$13+$B$12)/$B$42*100,"") | C75: =IFERROR(($C$11+$C$13+$C$12)/$C$42*100,"") | D75: =IFERROR(($D$11+$D$13+$D$12)/$D$42*100,"") | E75: =IFERROR(($E$11+$E$13+$E$12)/$E$42*100,"") | F75: =IFERROR(($F$11+$F$13+$F$12)/$F$42*100,"")
A76: Overskudsgrad, % | B76: =IFERROR(($B$11+$B$13+$B$12)/$B$4*100,"") | C76: =IFERROR(($C$11+$C$13+$C$12)/$C$4*100,"") | D76: =IFERROR(($D$11+$D$13+$D$12)/$D$4*100,"") | E76: =IFERROR(($E$11+$E$13+$E$12)/$E$4*100,"") | F76: =IFERROR(($F$11+$F$13+$F$12)/$F$4*100,"")
A77: Aktivernes omsætningshastighed, gange | B77: =IFERROR($B$4/$B$42,"") | C77: =IFERROR($C$4/$C$42,"") | D77: =IFERROR($D$4/$D$42,"") | E77: =IFERROR($E$4/$E$42,"") | F77: =IFERROR($F$4/$F$42,"")
A78: Egenkapitalens forrentning, % | B78: =IFERROR($B$16/$B$51*100,"") | C78: =IFERROR($C$16/$C$51*100,"") | D78: =IFERROR($D$16/$D$51*100,"") | E78: =IFERROR($E$16/$E$51*100,"") | F78: =IFERROR($F$16/$F$51*100,"")
A79: Gældsrente, % | B79: =IFERROR($B$14/($B$68-$B$51)*100,"") | C79: =IFERROR($C$14/($C$68-$C$51)*100,"") | D79: =IFERROR($D$14/($D$68-$D$51)*100,"") | E79: =IFERROR($E$14/($E$68-$E$51)*100,"") | F79: =IFERROR($F$14/($F$68-$F$51)*100,"")
A80: Soliditetsgrad, % | B80: =IFERROR($B$51/$B$42*100,"") | C80: =IFERROR($C$51/$C$42*100,"") | D80: =IFERROR($D$51/$D$42*100,"") | E80: =IFERROR($E$51/$E$42*100,"") | F80: =IFERROR($F$51/$F$42*100,"")
A81: Gearing | B81: =IFERROR(($B$68-$B$51)/$B$51,"") | C81: =IFERROR(($C$68-$C$51)/$C$51,"") | D81: =IFERROR(($D$68-$D$51)/$D$51,"") | E81: =IFERROR(($E$68-$E$51)/$E$51,"") | F81: =IFERROR(($F$68-$F$51)/$F$51,"")
A82: Likviditetsgrad, % | B82: =IFERROR($B$41/$B$66*100,"") | C82: =IFERROR($C$41/$C$66*100,"") | D82: =IFERROR($D$41/$D$66*100,"") | E82: =IFERROR($E$41/$E$66*100,"") | F82: =IFERROR($F$41/$F$66*100,"")
A83: Rentemarginal, % | B83: =IFERROR(B75-B79,"") | C83: =IFERROR(C75-C79,"") | D83: =IFERROR(D75-D79,"") | E83: =IFERROR(E75-E79,"") | F83: =IFERROR(F75-F79,"")
A84: Gældsandel, % | B84: =IFERROR(($B$68-$B$51)/$B$42*100,"") | C84: =IFERROR(($C$68-$C$51)/$C$42*100,"") | D84: =IFERROR(($D$68-$D$51)/$D$42*100,"") | E84: =IFERROR(($E$68-$E$51)/$E$42*100,"") | F84: =IFERROR(($F$68-$F$51)/$F$42*100,"")
A85: Kapitalbindingsgrad, % | B85: =IFERROR($B$29/($B$51+$B$54)*100,"") | C85: =IFERROR($C$29/($C$51+$C$54)*100,"") | D85: =IFERROR($D$29/($D$51+$D$54)*100,"") | E85: =IFERROR($E$29/($E$51+$E$54)*100,"") | F85: =IFERROR($F$29/($F$51+$F$54)*100,"")

Sheet res_raw_25313763
A1: Resultatopgørelse & nøgleoplysninger (t.EUR) | B1: 2021 | C1: 2022 | D1: 2023 | E1: 2024 | F1: 2025
A2: Nettoomsætning | B2: 11202000 | C2: 13793000 | D2: 13674000 | E2: 13770000 | F2: 15066000
A3: Produktionsomkostninger | E3: 10803000 | F3: 12068000
A4: Bruttoresultat | B4: 2380000 | C4: 2648000 | D4: 2780000 | E4: 2967000 | F4: 2998000
A5: Salgs- og distributionsomkostninger | E5: 1824000 | F5: 1913000
A6: Administrationsomkostninger | E6: 508000 | F6: 535000
A7: Andre driftsindtægter | B7: 110000 | C7: 162000 | D7: 113000 | E7: 48000 | F7: 135000
A8: Andre driftsomkostninger | E8: 118000 | F8: 68000
A9: Resultat af primær drift | E9: 598000 | F9: 647000
A10: Indtægter af kapitalandele, dattervirksomheder
A11: Finansielle indtægter | B11: 14000 | C11: 37000 | D11: 135000 | E11: 183000 | F11: 175000
A12: Finansielle omkostninger | B12: 75000 | C12: 117000 | D12: 280000 | E12: 318000 | F12: 308000
A13: Finansielle poster, netto
A14: Resultat før skat | B14: 407000 | C14: 449000 | D14: 455000 | E14: 463000 | F14: 514000
A15: Skat af årets resultat | B15: 61000 | C15: 49000 | D15: 56000 | E15: 46000 | F15: 81000
A16: Årets resultat | B16: 346000 | C16: 400000 | D16: 399000 | E16: 417000 | F16: 433000
A17: Gns. antal medarbejdere | C17: 0 | D17: 21307 | E17: 21895
A18: Investering i materielle anlægsaktiver | B18: 452000 | C18: 373000 | D18: 445000 | E18: 557000 | F18: 570000

Sheet balance_raw_25313763
A1: Balance (t.EUR) | B1: 2021 | C1: 2022 | D1: 2023 | E1: 2024 | F1: 2025
A2: Udviklingsprojekter
A3: Patenter, varemærker mv.
A4: Goodwill | E4: 938000 | F4: 897000
A5: Immaterielle anlægsaktiver | B5: 946000 | C5: 954000 | D5: 1010000 | E5: 269000 | F5: 287000
A6: Materielle anlægsaktiver | D6: 3149000
A7: Kapitalandele, dattervirksomheder | E7: 560000 | F7: 462000
A8: Deposita | B8: 247000 | C8: 247000 | D8: 246000 | E8: 24000 | F8: 28000
A9: Finansielle anlægsaktiver
A10: Anlægsaktiver | B10: 4668000 | C10: 4611000 | D10: 4788000 | E10: 5354000 | F10: 5366000
A11: Varebeholdninger | B11: 1248000 | C11: 1772000 | D11: 1384000 | E11: 1635000 | F11: 1743000
A12: Tilgodehavender fra salg og tjenesteydelser | B12: 1007000 | C12: 1267000 | D12: 1145000 | E12: 1317000 | F12: 1247000
A13: Tilgodehavender hos tilknyttede virksomheder
A14: Andre tilgodehavender | E14: 90000 | F14: 117000
A15: Periodeafgrænsningsposter (aktiver)
A16: Udskudt skatteaktiv | B16: 21000 | C16: 22000 | D16: 23000 | E16: 31000 | F16: 23000
A17: Tilgodehavende skat hos tilknyttede virksomheder
A18: Kortfristede skattetilgodehavender
A19: Tilgodehavender | E19: 266000 | F19: 327000
A20: Værdipapirer
A21: Likvide beholdninger | B21: 97000 | C21: 106000 | D21: 138000 | E21: 91000 | F21: 76000
A22: Omsætningsaktiver | B22: 3145000 | C22: 4135000 | D22: 3511000 | E22: 3976000 | F22: 4061000
A23: Aktiver | B23: 7813000 | C23: 8746000 | D23: 8299000 | E23: 9330000 | F23: 9427000
A24: Selskabskapital
A25: Reserve for nettoopskrivning (indre værdis metode)
A26: Reserve for udviklingsomkostninger
A27: Reserve for sikringstransaktioner
A28: Andre reserver | E28: 44000 | F28: -161000
A29: Overført resultat
A30: Egenkapital i alt | B30: 2910000 | C30: 3168000 | D30: 3052000 | E30: 3072000 | F30: 2950000
A31: Hensættelse til udskudt skat | E31: 101000 | F31: 106000
A32: Hensatte forpligtelser | B32: 269000 | C32: 189000 | D32: 198000 | E32: 166000 | F32: 159000
A33: Langfristede gældsforpligtelser | B33: 2113000 | C33: 2640000 | D33: 2650000 | E33: 2808000 | F33: 2990000
A34: Ansvarlig lånekapital (kortfristet)
A35: Kortfristet del af langfristede gældsforpligtelser
A36: Kreditinstitutter | E36: 1194000 | F36: 1221000
A37: Leasingforpligtelser (kortfristet)
A38: Leverandører af varer og tjenesteydelser | B38: 1445000 | C38: 1597000 | D38: 1425000 | E38: 1433000 | F38: 1469000
A39: Gæld til tilknyttede virksomheder
A40: Gæld til selskabsdeltagere og ledelse
A41: Selskabsskat
A42: Gæld til tilknyttede virksomheder vedr. selskabsskat
A43: Anden gæld (kortfristet) | B43: 280000 | C43: 301000 | D43: 306000 | E43: 365000 | F43: 370000
A44: Periodeafgrænsningsposter (passiver)
A45: Kortfristede gældsforpligtelser | B45: 2457000 | C45: 2663000 | D45: 2597000 | E45: 3087000 | F45: 3102000
A46: Gældsforpligtelser | B46: 4903000 | C46: 5578000 | D46: 5247000 | E46: 6192000 | F46: 6411000
A47: Passiver | B47: 7813000 | C47: 8746000 | D47: 8299000 | E47: 9330000 | F47: 9427000

Sheet Simpel_funktion
A1: Regnskabs- og nøgletal (CVR: 25313763) — funktionsopdelt
A3: Beløb i 1.000 kr. | B3: 2025 | C3: 2024 | D3: 2023 | F3: Note / XBRL-felt
A4: Uddrag af resultatopgørelse
A5: Nettoomsætning | B5: ='res_raw_25313763'!$F$2 | C5: ='res_raw_25313763'!$E$2 | D5: ='res_raw_25313763'!$D$2 | F5: fsa:Revenue
A6: Produktionsomkostninger | B6: =-'res_raw_25313763'!$F$3 | C6: =-'res_raw_25313763'!$E$3 | D6: =-'res_raw_25313763'!$D$3 | F6: fsa:CostOfProduction (vises negativt). Materialer, lønninger, produktionsoverhead.
A7: Bruttoresultat | B7: =SUM(B5:B6) | C7: =SUM(C5:C6) | D7: =SUM(D5:D6) | F7: Beregnet: Nettoomsætning − Produktionsomkostninger. Matcher fsa:GrossResult.
A8: Salgs- og distributionsomk. | B8: =-'res_raw_25313763'!$F$5 | C8: =-'res_raw_25313763'!$E$5 | D8: =-'res_raw_25313763'!$D$5 | F8: fsa:DistributionCosts (vises negativt). Marketing, salg, distribution.
A9: Administrationsomkostninger mv. | B9: =-'res_raw_25313763'!$F$6 | C9: =-'res_raw_25313763'!$E$6 | D9: =-'res_raw_25313763'!$D$6 | F9: fsa:AdministrativeExpenses (vises negativt). Generel administration.
A10: Andre driftsindtægter | B10: ='res_raw_25313763'!$F$7 | C10: ='res_raw_25313763'!$E$7 | D10: ='res_raw_25313763'!$D$7 | F10: fsa:OtherOperatingIncome. Sekundære driftsindtægter (huslejeindtægter, off. tilskud, avancer mv.).
A11: Andre driftsomkostninger | B11: =-'res_raw_25313763'!$F$8 | C11: =-'res_raw_25313763'!$E$8 | D11: =-'res_raw_25313763'!$D$8 | F11: fsa:OtherOperatingExpenses (vises negativt). Sekundære driftsomkostninger.
A12: Resultat af primær drift | B12: =SUM(B7:B11) | C12: =SUM(C7:C11) | D12: =SUM(D7:D11) | F12: Beregnet: Bruttoresultat − Salgs/dist. − Administration + Andre driftsindt. − Andre driftsomk. EBIT.
A13: Finansielle indtægter mv. | B13: =N('res_raw_25313763'!$F$10)+N('res_raw_25313763'!$F$11) | C13: =N('res_raw_25313763'!$E$10)+N('res_raw_25313763'!$E$11) | D13: =N('res_raw_25313763'!$D$10)+N('res_raw_25313763'!$D$11) | F13: fsa:IncomeFromSubsidiaries + fsa:OtherFinanceIncome.
A14: Finansielle omkostninger mv. | B14: =-'res_raw_25313763'!$F$12 | C14: =-'res_raw_25313763'!$E$12 | D14: =-'res_raw_25313763'!$D$12 | F14: fsa:OtherFinanceExpenses (vises negativt). Renteomkostninger, kurstab.
A15: Resultat før skat | B15: =SUM(B12:B14) | C15: =SUM(C12:C14) | D15: =SUM(D12:D14) | F15: Beregnet: EBIT + Fin. indtægter + Fin. omk. EBT.
A17: Uddrag af balance
A18: Anlægsaktiver | B18: ='balance_raw_25313763'!$F$10 | C18: ='balance_raw_25313763'!$E$10 | D18: ='balance_raw_25313763'!$D$10 | F18: fsa:NoncurrentAssets. Materielle, immaterielle og finansielle anlægsaktiver.
A19: Omsætningsaktiver | B19: ='balance_raw_25313763'!$F$22 | C19: ='balance_raw_25313763'!$E$22 | D19: ='balance_raw_25313763'!$D$22 | F19: fsa:CurrentAssets. Varebeholdninger, tilgodehavender, likvider.
A20: Aktiver i alt | B20: =SUM(B18:B19) | C20: =SUM(C18:C19) | D20: =SUM(D18:D19) | F20: Beregnet: Anlægsaktiver + Omsætningsaktiver. Bør matche fsa:Assets.
A22: Egenkapital | B22: ='balance_raw_25313763'!$F$30 | C22: ='balance_raw_25313763'!$E$30 | D22: ='balance_raw_25313763'!$D$30 | F22: fsa:Equity. Selskabskapital, overført resultat, reserver.
A23: Forpligtelser | B23: ='balance_raw_25313763'!$F$47-'balance_raw_25313763'!$F$30 | C23: ='balance_raw_25313763'!$E$47-'balance_raw_25313763'!$E$30 | D23: ='balance_raw_25313763'!$D$47-'balance_raw_25313763'!$D$30 | F23: Beregnet: Passiver (fsa:LiabilitiesAndEquity) − Egenkapital. Hensættelser + kort- og langfristet gæld.
A24: Passiver i alt | B24: =SUM(B22:B23) | C24: =SUM(C22:C23) | D24: =SUM(D22:D23) | F24: Beregnet: Egenkapital + Forpligtelser. Bør matche Aktiver i alt.
A26: Udvalgte balanceposter
A27: Varebeholdninger | B27: ='balance_raw_25313763'!$F$11 | C27: ='balance_raw_25313763'!$E$11 | D27: ='balance_raw_25313763'!$D$11 | F27: fsa:Inventories (eller fsa:ManufacturedGoodsAndGoodsForResale hvis total mangler).
A28: Tilgodehavender fra salg | B28: ='balance_raw_25313763'!$F$12 | C28: ='balance_raw_25313763'!$E$12 | D28: ='balance_raw_25313763'!$D$12 | F28: fsa:ShorttermTradeReceivables. Kortfristede tilgodehavender fra kunder.
A29: Kortfristede gældsforpligtelser | B29: ='balance_raw_25313763'!$F$45 | C29: ='balance_raw_25313763'!$E$45 | D29: ='balance_raw_25313763'!$D$45 | F29: fsa:ShorttermLiabilitiesOtherThanProvisions. Gæld der forfalder inden for 1 år.
A31: Rentabilitet
A32: Afkastningsgrad, % | B32: =IFERROR((B12+B13)/B20*100,"") | C32: =IFERROR((C12+C13)/C20*100,"") | D32: =IFERROR((D12+D13)/D20*100,"")
A33: Overskudsgrad, % | B33: =IFERROR((B12+B13)/B5*100,"") | C33: =IFERROR((C12+C13)/C5*100,"") | D33: =IFERROR((D12+D13)/D5*100,"")
A34: Aktivernes omsætningshastighed, gange | B34: =IFERROR(B5/B20,"") | C34: =IFERROR(C5/C20,"") | D34: =IFERROR(D5/D20,"")
A35: Gældsrente, % | B35: =IFERROR(-B14*100/B23,"") | C35: =IFERROR(-C14*100/C23,"") | D35: =IFERROR(-D14*100/D23,"")
A36: Egenkapitalens forrentning, % | B36: =IFERROR(B15/B22*100,"") | C36: =IFERROR(C15/C22*100,"") | D36: =IFERROR(D15/D22*100,"")
A37: Gearing, gange | B37: =IFERROR(B23/B22,"") | C37: =IFERROR(C23/C22,"") | D37: =IFERROR(D23/D22,"")
A39: Indekstal for indtjeningsevne (2023=100)
A40: Nettoomsætning | B40: =IFERROR(B5/$D5*100,"") | C40: =IFERROR(C5/$D5*100,"") | D40: =IFERROR(D5/$D5*100,"")
A41: Produktionsomkostninger | B41: =IFERROR(B6/$D6*100,"") | C41: =IFERROR(C6/$D6*100,"") | D41: =IFERROR(D6/$D6*100,"")
A42: Salgs- og distributionsomk. | B42: =IFERROR(B8/$D8*100,"") | C42: =IFERROR(C8/$D8*100,"") | D42: =IFERROR(D8/$D8*100,"")
A43: Administrationsomk. | B43: =IFERROR(B9/$D9*100,"") | C43: =IFERROR(C9/$D9*100,"") | D43: =IFERROR(D9/$D9*100,"")
A44: Andre driftsomkostninger | B44: =IFERROR(B11/$D11*100,"") | C44: =IFERROR(C11/$D11*100,"") | D44: =IFERROR(D11/$D11*100,"")
A46: Indekstal for kapitaltilpasningsevne (2023=100)
A47: Nettoomsætning | B47: =IFERROR(B5*100/$D5,"") | C47: =IFERROR(C5*100/$D5,"") | D47: =IFERROR(D5*100/$D5,"")
A48: Anlægsaktiver | B48: =IFERROR(B18*100/$D18,"") | C48: =IFERROR(C18*100/$D18,"") | D48: =IFERROR(D18*100/$D18,"")
A49: Varebeholdninger | B49: =IFERROR(B27*100/$D27,"") | C49: =IFERROR(C27*100/$D27,"") | D49: =IFERROR(D27*100/$D27,"")
A50: Tilgodehavender fra salg | B50: =IFERROR(B28*100/$D28,"") | C50: =IFERROR(C28*100/$D28,"") | D50: =IFERROR(D28*100/$D28,"")
A52: Soliditet og likviditet
A53: Soliditetsgrad, % | B53: =IFERROR(B22*100/B20,"") | C53: =IFERROR(C22*100/C20,"") | D53: =IFERROR(D22*100/D20,"")
A54: Gældsandel, % | B54: =IFERROR(B23*100/B20,"") | C54: =IFERROR(C23*100/C20,"") | D54: =IFERROR(D23*100/D20,"")
A55: Likviditetsgrad, % | B55: =IFERROR(B19*100/B29,"") | C55: =IFERROR(C19*100/C29,"") | D55: =IFERROR(D19*100/D29,"")
A57: Kilde: Bearbejdet uddrag af årsrapporter for 2023-2025. Alle dataceller er live formler der peger på res_raw / balance_raw.
A59: Krydstjek mod rådata (tolerance: 1 t.kr.)
A60: Aktiver i alt = fsa:Assets | B60: =IF('balance_raw_25313763'!$F$23="","—",IF(ABS(B20-'balance_raw_25313763'!$F$23)<=1,"✓ OK","❌ "&TEXT(B20-'balance_raw_25313763'!$F$23,"+#,##0;-#,##0")&" t.EUR")) | C60: =IF('balance_raw_25313763'!$E$23="","—",IF(ABS(C20-'balance_raw_25313763'!$E$23)<=1,"✓ OK","❌ "&TEXT(C20-'balance_raw_25313763'!$E$23,"+#,##0;-#,##0")&" t.EUR")) | D60: =IF('balance_raw_25313763'!$D$23="","—",IF(ABS(D20-'balance_raw_25313763'!$D$23)<=1,"✓ OK","❌ "&TEXT(D20-'balance_raw_25313763'!$D$23,"+#,##0;-#,##0")&" t.EUR")) | F60: Verificerer at sum(Anlæg+Omsætning) matcher Assets-totalen.
A61: Passiver i alt = fsa:LiabilitiesAndEquity | B61: =IF('balance_raw_25313763'!$F$47="","—",IF(ABS(B24-'balance_raw_25313763'!$F$47)<=1,"✓ OK","❌ "&TEXT(B24-'balance_raw_25313763'!$F$47,"+#,##0;-#,##0")&" t.EUR")) | C61: =IF('balance_raw_25313763'!$E$47="","—",IF(ABS(C24-'balance_raw_25313763'!$E$47)<=1,"✓ OK","❌ "&TEXT(C24-'balance_raw_25313763'!$E$47,"+#,##0;-#,##0")&" t.EUR")) | D61: =IF('balance_raw_25313763'!$D$47="","—",IF(ABS(D24-'balance_raw_25313763'!$D$47)<=1,"✓ OK","❌ "&TEXT(D24-'balance_raw_25313763'!$D$47,"+#,##0;-#,##0")&" t.EUR")) | F61: Verificerer at sum(EK+Forpligtelser) matcher Passiver-totalen.
A62: Aktiver i alt = Passiver i alt | B62: =IF(ABS(B20-B24)<=1,"✓ OK","❌ "&TEXT(B20-B24,"+#,##0;-#,##0")&" t.EUR") | C62: =IF(ABS(C20-C24)<=1,"✓ OK","❌ "&TEXT(C20-C24,"+#,##0;-#,##0")&" t.EUR") | D62: =IF(ABS(D20-D24)<=1,"✓ OK","❌ "&TEXT(D20-D24,"+#,##0;-#,##0")&" t.EUR") | F62: Balance-identitet på arket selv. Skal altid være 0 differance.
A63: Bruttoresultat (beregnet) = fsa:GrossResult | B63: =IF('res_raw_25313763'!$F$4="","—",IF(ABS(B7-'res_raw_25313763'!$F$4)<=1,"✓ OK","❌ "&TEXT(B7-'res_raw_25313763'!$F$4,"+#,##0;-#,##0")&" t.EUR")) | C63: =IF('res_raw_25313763'!$E$4="","—",IF(ABS(C7-'res_raw_25313763'!$E$4)<=1,"✓ OK","❌ "&TEXT(C7-'res_raw_25313763'!$E$4,"+#,##0;-#,##0")&" t.EUR")) | D63: =IF('res_raw_25313763'!$D$4="","—",IF(ABS(D7-'res_raw_25313763'!$D$4)<=1,"✓ OK","❌ "&TEXT(D7-'res_raw_25313763'!$D$4,"+#,##0;-#,##0")&" t.EUR")) | F63: Hvis Nettoomsætning eller omkostninger mangler, vil sumberegnet bruttoresultat afvige.
A64: EBIT (beregnet) = fsa:ProfitLossFromOrdinaryOperatingActivities | B64: =IF('res_raw_25313763'!$F$9="","—",IF(ABS(B12-'res_raw_25313763'!$F$9)<=1,"✓ OK","❌ "&TEXT(B12-'res_raw_25313763'!$F$9,"+#,##0;-#,##0")&" t.EUR")) | C64: =IF('res_raw_25313763'!$E$9="","—",IF(ABS(C12-'res_raw_25313763'!$E$9)<=1,"✓ OK","❌ "&TEXT(C12-'res_raw_25313763'!$E$9,"+#,##0;-#,##0")&" t.EUR")) | D64: =IF('res_raw_25313763'!$D$9="","—",IF(ABS(D12-'res_raw_25313763'!$D$9)<=1,"✓ OK","❌ "&TEXT(D12-'res_raw_25313763'!$D$9,"+#,##0;-#,##0")&" t.EUR")) | F64: Verificerer at sumberegnet EBIT matcher det rapporterede.
A65: EBT (beregnet) = fsa:ProfitLossFromOrdinaryActivitiesBeforeTax | B65: =IF('res_raw_25313763'!$F$14="","—",IF(ABS(B15-'res_raw_25313763'!$F$14)<=1,"✓ OK","❌ "&TEXT(B15-'res_raw_25313763'!$F$14,"+#,##0;-#,##0")&" t.EUR")) | C65: =IF('res_raw_25313763'!$E$14="","—",IF(ABS(C15-'res_raw_25313763'!$E$14)<=1,"✓ OK","❌ "&TEXT(C15-'res_raw_25313763'!$E$14,"+#,##0;-#,##0")&" t.EUR")) | D65: =IF('res_raw_25313763'!$D$14="","—",IF(ABS(D15-'res_raw_25313763'!$D$14)<=1,"✓ OK","❌ "&TEXT(D15-'res_raw_25313763'!$D$14,"+#,##0;-#,##0")&" t.EUR")) | F65: Verificerer at sumberegnet resultat før skat matcher det rapporterede.

Sheet Noter_info
A1: Ukendte XBRL-felter — disse er noter og ikke en del af hoved-regnskabet
A2: Kategori | B2: Dansk navn | C2: XBRL feltnavn | D2: 2021 t.kr. | E2: 2022 t.kr. | F2: 2023 t.kr. | G2: 2024 t.kr. | H2: 2025 t.kr. | I2: Forklaring
A3: Øvrige (ukendt) | B3: ifrs-full:AdjustmentsForUndistributedProfitsOfAssociates | C3: ifrs-full:AdjustmentsForUndistributedProfitsOfAssociates | G3: 33000 | H3: 30000 | I3: Ingen forklaring tilgængelig.
A4: Øvrige (ukendt) | B4: ifrs-full:AmountRemovedFromReserveOfChangeInValueOfForeignCurrencyBasisSpreadsAndIncludedInInitialCostOrOtherCarryingAmountOfNonfinancialAssetLiabilityOrFirmCommitmentForWhichFairValueHedgeAccountingIsApplied | C4: ifrs-full:AmountRemovedFromReserveOfChangeInValueOfForeignCurrencyBasisSpreadsAndIncludedInInitialCostOrOtherCarryingAmountOfNonfinancialAssetLiabilityOrFirmCommitmentForWhichFairValueHedgeAccountingIsApplied | G4: -4000 | H4: 0 | I4: Ingen forklaring tilgængelig.
A5: Øvrige (ukendt) | B5: ifrs-full:DividendsReceivedClassifiedAsOperatingActivities | C5: ifrs-full:DividendsReceivedClassifiedAsOperatingActivities | D5: 24000 | E5: 15000 | F5: 18000 | G5: 24000 | H5: 21000 | I5: Ingen forklaring tilgængelig.
A6: Øvrige (ukendt) | B6: ifrs-full:InvestmentsInSubsidiariesJointVenturesAndAssociates | C6: ifrs-full:InvestmentsInSubsidiariesJointVenturesAndAssociates | D6: 530000 | E6: 565000 | F6: 560000 | I6: Ingen forklaring tilgængelig.
A7: Øvrige (ukendt) | B7: ifrs-full:IssuedCapitalOrdinaryShares | C7: ifrs-full:IssuedCapitalOrdinaryShares | G7: 2230000 | H7: 2049000 | I7: Ingen forklaring tilgængelig.
A8: Øvrige (ukendt) | B8: ifrs-full:IssuedCapitalPreferenceShares | C8: ifrs-full:IssuedCapitalPreferenceShares | G8: 570000 | H8: 834000 | I8: Ingen forklaring tilgængelig.
A9: Øvrige (ukendt) | B9: ifrs-full:ProceedsFromSalesOrMaturityOfFinancialInstrumentsClassifiedAsInvestingActivities | C9: ifrs-full:ProceedsFromSalesOrMaturityOfFinancialInstrumentsClassifiedAsInvestingActivities | G9: 56000 | H9: 36000 | I9: Ingen forklaring tilgængelig.
