Workbook

Sheet Overblik_25652991
A1: Regnskabsanalyse – Resultatopgørelse & Balance (t.kr.)
H2: Indekstal (2020=100)
A3: Resultatopgørelse t.kr. | B3: 2020 | C3: 2021 | D3: 2022 | E3: 2023 | F3: 2024 | H3: 2020 | I3: 2021 | J3: 2022 | K3: 2023 | L3: 2024
A4: Nettoomsætning | B4: ='res_raw_25652991'!$B$2 | C4: ='res_raw_25652991'!$C$2 | D4: ='res_raw_25652991'!$D$2 | E4: ='res_raw_25652991'!$E$2 | F4: ='res_raw_25652991'!$F$2 | H4: =IFERROR(B4/$B$4*100,"") | I4: =IFERROR(C4/$B$4*100,"") | J4: =IFERROR(D4/$B$4*100,"") | K4: =IFERROR(E4/$B$4*100,"") | L4: =IFERROR(F4/$B$4*100,"")
A5: Andre driftsindtægter | B5: ='res_raw_25652991'!$B$3 | C5: ='res_raw_25652991'!$C$3 | D5: ='res_raw_25652991'!$D$3 | E5: ='res_raw_25652991'!$E$3 | F5: ='res_raw_25652991'!$F$3 | H5: =IFERROR(B5/$B$5*100,"") | I5: =IFERROR(C5/$B$5*100,"") | J5: =IFERROR(D5/$B$5*100,"") | K5: =IFERROR(E5/$B$5*100,"") | L5: =IFERROR(F5/$B$5*100,"")
A6: Vareforbrug | B6: ='res_raw_25652991'!$B$4 | C6: ='res_raw_25652991'!$C$4 | D6: ='res_raw_25652991'!$D$4 | E6: ='res_raw_25652991'!$E$4 | F6: ='res_raw_25652991'!$F$4 | H6: =IFERROR(B6/$B$6*100,"") | I6: =IFERROR(C6/$B$6*100,"") | J6: =IFERROR(D6/$B$6*100,"") | K6: =IFERROR(E6/$B$6*100,"") | L6: =IFERROR(F6/$B$6*100,"")
A7: Andre eksterne omkostninger | B7: ='res_raw_25652991'!$B$5 | C7: ='res_raw_25652991'!$C$5 | D7: ='res_raw_25652991'!$D$5 | E7: ='res_raw_25652991'!$E$5 | F7: ='res_raw_25652991'!$F$5 | H7: =IFERROR(B7/$B$7*100,"") | I7: =IFERROR(C7/$B$7*100,"") | J7: =IFERROR(D7/$B$7*100,"") | K7: =IFERROR(E7/$B$7*100,"") | L7: =IFERROR(F7/$B$7*100,"")
A8: Bruttoresultat | B8: ='res_raw_25652991'!$B$6 | C8: ='res_raw_25652991'!$C$6 | D8: ='res_raw_25652991'!$D$6 | E8: ='res_raw_25652991'!$E$6 | F8: ='res_raw_25652991'!$F$6 | H8: =IFERROR(B8/$B$8*100,"") | I8: =IFERROR(C8/$B$8*100,"") | J8: =IFERROR(D8/$B$8*100,"") | K8: =IFERROR(E8/$B$8*100,"") | L8: =IFERROR(F8/$B$8*100,"")
A9: Personaleomkostninger | B9: ='res_raw_25652991'!$B$7 | C9: ='res_raw_25652991'!$C$7 | D9: ='res_raw_25652991'!$D$7 | E9: ='res_raw_25652991'!$E$7 | F9: ='res_raw_25652991'!$F$7 | H9: =IFERROR(B9/$B$9*100,"") | I9: =IFERROR(C9/$B$9*100,"") | J9: =IFERROR(D9/$B$9*100,"") | K9: =IFERROR(E9/$B$9*100,"") | L9: =IFERROR(F9/$B$9*100,"")
A10: Resultat før afskrivninger | B10: =IFERROR($B$8-ABS($B$9),"") | C10: =IFERROR($C$8-ABS($C$9),"") | D10: =IFERROR($D$8-ABS($D$9),"") | E10: =IFERROR($E$8-ABS($E$9),"") | F10: =IFERROR($F$8-ABS($F$9),"") | H10: =IFERROR(B10/$B$10*100,"") | I10: =IFERROR(C10/$B$10*100,"") | J10: =IFERROR(D10/$B$10*100,"") | K10: =IFERROR(E10/$B$10*100,"") | L10: =IFERROR(F10/$B$10*100,"")
A11: Af- og nedskrivninger | B11: ='res_raw_25652991'!$B$9 | C11: ='res_raw_25652991'!$C$9 | D11: ='res_raw_25652991'!$D$9 | E11: ='res_raw_25652991'!$E$9 | F11: ='res_raw_25652991'!$F$9 | H11: =IFERROR(B11/$B$11*100,"") | I11: =IFERROR(C11/$B$11*100,"") | J11: =IFERROR(D11/$B$11*100,"") | K11: =IFERROR(E11/$B$11*100,"") | L11: =IFERROR(F11/$B$11*100,"")
A12: Andre driftsomkostninger | B12: ='res_raw_25652991'!$B$10 | C12: ='res_raw_25652991'!$C$10 | D12: ='res_raw_25652991'!$D$10 | E12: ='res_raw_25652991'!$E$10 | F12: ='res_raw_25652991'!$F$10 | H12: =IFERROR(B12/$B$12*100,"") | I12: =IFERROR(C12/$B$12*100,"") | J12: =IFERROR(D12/$B$12*100,"") | K12: =IFERROR(E12/$B$12*100,"") | L12: =IFERROR(F12/$B$12*100,"")
A13: Resultat af primær drift | B13: ='res_raw_25652991'!$B$11 | C13: ='res_raw_25652991'!$C$11 | D13: ='res_raw_25652991'!$D$11 | E13: ='res_raw_25652991'!$E$11 | F13: ='res_raw_25652991'!$F$11 | H13: =IFERROR(B13/$B$13*100,"") | I13: =IFERROR(C13/$B$13*100,"") | J13: =IFERROR(D13/$B$13*100,"") | K13: =IFERROR(E13/$B$13*100,"") | L13: =IFERROR(F13/$B$13*100,"")
A14: Indtægter af kapitalandele, dattervirksomheder | B14: ='res_raw_25652991'!$B$12 | C14: ='res_raw_25652991'!$C$12 | D14: ='res_raw_25652991'!$D$12 | E14: ='res_raw_25652991'!$E$12 | F14: ='res_raw_25652991'!$F$12 | H14: =IFERROR(B14/$B$14*100,"") | I14: =IFERROR(C14/$B$14*100,"") | J14: =IFERROR(D14/$B$14*100,"") | K14: =IFERROR(E14/$B$14*100,"") | L14: =IFERROR(F14/$B$14*100,"")
A15: Finansielle indtægter | B15: ='res_raw_25652991'!$B$13 | C15: ='res_raw_25652991'!$C$13 | D15: ='res_raw_25652991'!$D$13 | E15: ='res_raw_25652991'!$E$13 | F15: ='res_raw_25652991'!$F$13 | H15: =IFERROR(B15/$B$15*100,"") | I15: =IFERROR(C15/$B$15*100,"") | J15: =IFERROR(D15/$B$15*100,"") | K15: =IFERROR(E15/$B$15*100,"") | L15: =IFERROR(F15/$B$15*100,"")
A16: Finansielle omkostninger | B16: ='res_raw_25652991'!$B$14 | C16: ='res_raw_25652991'!$C$14 | D16: ='res_raw_25652991'!$D$14 | E16: ='res_raw_25652991'!$E$14 | F16: ='res_raw_25652991'!$F$14 | H16: =IFERROR(B16/$B$16*100,"") | I16: =IFERROR(C16/$B$16*100,"") | J16: =IFERROR(D16/$B$16*100,"") | K16: =IFERROR(E16/$B$16*100,"") | L16: =IFERROR(F16/$B$16*100,"")
A17: Finansielle poster, netto | B17: ='res_raw_25652991'!$B$15 | C17: ='res_raw_25652991'!$C$15 | D17: ='res_raw_25652991'!$D$15 | E17: ='res_raw_25652991'!$E$15 | F17: ='res_raw_25652991'!$F$15 | H17: =IFERROR(B17/$B$17*100,"") | I17: =IFERROR(C17/$B$17*100,"") | J17: =IFERROR(D17/$B$17*100,"") | K17: =IFERROR(E17/$B$17*100,"") | L17: =IFERROR(F17/$B$17*100,"")
A18: Resultat før skat | B18: ='res_raw_25652991'!$B$16 | C18: ='res_raw_25652991'!$C$16 | D18: ='res_raw_25652991'!$D$16 | E18: ='res_raw_25652991'!$E$16 | F18: ='res_raw_25652991'!$F$16 | H18: =IFERROR(B18/$B$18*100,"") | I18: =IFERROR(C18/$B$18*100,"") | J18: =IFERROR(D18/$B$18*100,"") | K18: =IFERROR(E18/$B$18*100,"") | L18: =IFERROR(F18/$B$18*100,"")
A19: Skat af årets resultat | B19: ='res_raw_25652991'!$B$17 | C19: ='res_raw_25652991'!$C$17 | D19: ='res_raw_25652991'!$D$17 | E19: ='res_raw_25652991'!$E$17 | F19: ='res_raw_25652991'!$F$17 | H19: =IFERROR(B19/$B$19*100,"") | I19: =IFERROR(C19/$B$19*100,"") | J19: =IFERROR(D19/$B$19*100,"") | K19: =IFERROR(E19/$B$19*100,"") | L19: =IFERROR(F19/$B$19*100,"")
A20: Årets resultat | B20: ='res_raw_25652991'!$B$18 | C20: ='res_raw_25652991'!$C$18 | D20: ='res_raw_25652991'!$D$18 | E20: ='res_raw_25652991'!$E$18 | F20: ='res_raw_25652991'!$F$18 | H20: =IFERROR(B20/$B$20*100,"") | I20: =IFERROR(C20/$B$20*100,"") | J20: =IFERROR(D20/$B$20*100,"") | K20: =IFERROR(E20/$B$20*100,"") | L20: =IFERROR(F20/$B$20*100,"")
A22: AKTIVER t.kr. | B22: 2020 | C22: 2021 | D22: 2022 | E22: 2023 | F22: 2024 | H22: 2020 | I22: 2021 | J22: 2022 | K22: 2023 | L22: 2024
A23: Udviklingsprojekter | B23: ='balance_raw_25652991'!$B$2 | C23: ='balance_raw_25652991'!$C$2 | D23: ='balance_raw_25652991'!$D$2 | E23: ='balance_raw_25652991'!$E$2 | F23: ='balance_raw_25652991'!$F$2 | H23: =IFERROR(B23/$B$23*100,"") | I23: =IFERROR(C23/$B$23*100,"") | J23: =IFERROR(D23/$B$23*100,"") | K23: =IFERROR(E23/$B$23*100,"") | L23: =IFERROR(F23/$B$23*100,"")
A24: Patenter, varemærker mv. | B24: ='balance_raw_25652991'!$B$3 | C24: ='balance_raw_25652991'!$C$3 | D24: ='balance_raw_25652991'!$D$3 | E24: ='balance_raw_25652991'!$E$3 | F24: ='balance_raw_25652991'!$F$3 | H24: =IFERROR(B24/$B$24*100,"") | I24: =IFERROR(C24/$B$24*100,"") | J24: =IFERROR(D24/$B$24*100,"") | K24: =IFERROR(E24/$B$24*100,"") | L24: =IFERROR(F24/$B$24*100,"")
A25: Goodwill | B25: ='balance_raw_25652991'!$B$4 | C25: ='balance_raw_25652991'!$C$4 | D25: ='balance_raw_25652991'!$D$4 | E25: ='balance_raw_25652991'!$E$4 | F25: ='balance_raw_25652991'!$F$4 | H25: =IFERROR(B25/$B$25*100,"") | I25: =IFERROR(C25/$B$25*100,"") | J25: =IFERROR(D25/$B$25*100,"") | K25: =IFERROR(E25/$B$25*100,"") | L25: =IFERROR(F25/$B$25*100,"")
A26: Immaterielle anlægsaktiver | B26: ='balance_raw_25652991'!$B$5 | C26: ='balance_raw_25652991'!$C$5 | D26: ='balance_raw_25652991'!$D$5 | E26: ='balance_raw_25652991'!$E$5 | F26: ='balance_raw_25652991'!$F$5 | H26: =IFERROR(B26/$B$26*100,"") | I26: =IFERROR(C26/$B$26*100,"") | J26: =IFERROR(D26/$B$26*100,"") | K26: =IFERROR(E26/$B$26*100,"") | L26: =IFERROR(F26/$B$26*100,"")
A27: Grunde og bygninger | B27: ='balance_raw_25652991'!$B$6 | C27: ='balance_raw_25652991'!$C$6 | D27: ='balance_raw_25652991'!$D$6 | E27: ='balance_raw_25652991'!$E$6 | F27: ='balance_raw_25652991'!$F$6 | H27: =IFERROR(B27/$B$27*100,"") | I27: =IFERROR(C27/$B$27*100,"") | J27: =IFERROR(D27/$B$27*100,"") | K27: =IFERROR(E27/$B$27*100,"") | L27: =IFERROR(F27/$B$27*100,"")
A28: Produktionsanlæg og maskiner | B28: ='balance_raw_25652991'!$B$7 | C28: ='balance_raw_25652991'!$C$7 | D28: ='balance_raw_25652991'!$D$7 | E28: ='balance_raw_25652991'!$E$7 | F28: ='balance_raw_25652991'!$F$7 | H28: =IFERROR(B28/$B$28*100,"") | I28: =IFERROR(C28/$B$28*100,"") | J28: =IFERROR(D28/$B$28*100,"") | K28: =IFERROR(E28/$B$28*100,"") | L28: =IFERROR(F28/$B$28*100,"")
A29: Driftsmateriel og inventar | B29: ='balance_raw_25652991'!$B$8 | C29: ='balance_raw_25652991'!$C$8 | D29: ='balance_raw_25652991'!$D$8 | E29: ='balance_raw_25652991'!$E$8 | F29: ='balance_raw_25652991'!$F$8 | H29: =IFERROR(B29/$B$29*100,"") | I29: =IFERROR(C29/$B$29*100,"") | J29: =IFERROR(D29/$B$29*100,"") | K29: =IFERROR(E29/$B$29*100,"") | L29: =IFERROR(F29/$B$29*100,"")
A30: Indretning af lejede lokaler | B30: ='balance_raw_25652991'!$B$9 | C30: ='balance_raw_25652991'!$C$9 | D30: ='balance_raw_25652991'!$D$9 | E30: ='balance_raw_25652991'!$E$9 | F30: ='balance_raw_25652991'!$F$9 | H30: =IFERROR(B30/$B$30*100,"") | I30: =IFERROR(C30/$B$30*100,"") | J30: =IFERROR(D30/$B$30*100,"") | K30: =IFERROR(E30/$B$30*100,"") | L30: =IFERROR(F30/$B$30*100,"")
A31: Forudbetaling og anlægsaktiver under opførelse | B31: ='balance_raw_25652991'!$B$10 | C31: ='balance_raw_25652991'!$C$10 | D31: ='balance_raw_25652991'!$D$10 | E31: ='balance_raw_25652991'!$E$10 | F31: ='balance_raw_25652991'!$F$10 | H31: =IFERROR(B31/$B$31*100,"") | I31: =IFERROR(C31/$B$31*100,"") | J31: =IFERROR(D31/$B$31*100,"") | K31: =IFERROR(E31/$B$31*100,"") | L31: =IFERROR(F31/$B$31*100,"")
A32: Materielle anlægsaktiver | B32: ='balance_raw_25652991'!$B$11 | C32: ='balance_raw_25652991'!$C$11 | D32: ='balance_raw_25652991'!$D$11 | E32: ='balance_raw_25652991'!$E$11 | F32: ='balance_raw_25652991'!$F$11 | H32: =IFERROR(B32/$B$32*100,"") | I32: =IFERROR(C32/$B$32*100,"") | J32: =IFERROR(D32/$B$32*100,"") | K32: =IFERROR(E32/$B$32*100,"") | L32: =IFERROR(F32/$B$32*100,"")
A33: Kapitalandele, dattervirksomheder | B33: ='balance_raw_25652991'!$B$12 | C33: ='balance_raw_25652991'!$C$12 | D33: ='balance_raw_25652991'!$D$12 | E33: ='balance_raw_25652991'!$E$12 | F33: ='balance_raw_25652991'!$F$12 | H33: =IFERROR(B33/$B$33*100,"") | I33: =IFERROR(C33/$B$33*100,"") | J33: =IFERROR(D33/$B$33*100,"") | K33: =IFERROR(E33/$B$33*100,"") | L33: =IFERROR(F33/$B$33*100,"")
A34: Deposita | B34: ='balance_raw_25652991'!$B$13 | C34: ='balance_raw_25652991'!$C$13 | D34: ='balance_raw_25652991'!$D$13 | E34: ='balance_raw_25652991'!$E$13 | F34: ='balance_raw_25652991'!$F$13 | H34: =IFERROR(B34/$B$34*100,"") | I34: =IFERROR(C34/$B$34*100,"") | J34: =IFERROR(D34/$B$34*100,"") | K34: =IFERROR(E34/$B$34*100,"") | L34: =IFERROR(F34/$B$34*100,"")
A35: Finansielle anlægsaktiver | B35: ='balance_raw_25652991'!$B$14 | C35: ='balance_raw_25652991'!$C$14 | D35: ='balance_raw_25652991'!$D$14 | E35: ='balance_raw_25652991'!$E$14 | F35: ='balance_raw_25652991'!$F$14 | H35: =IFERROR(B35/$B$35*100,"") | I35: =IFERROR(C35/$B$35*100,"") | J35: =IFERROR(D35/$B$35*100,"") | K35: =IFERROR(E35/$B$35*100,"") | L35: =IFERROR(F35/$B$35*100,"")
A36: Anlægsaktiver | B36: ='balance_raw_25652991'!$B$15 | C36: ='balance_raw_25652991'!$C$15 | D36: ='balance_raw_25652991'!$D$15 | E36: ='balance_raw_25652991'!$E$15 | F36: ='balance_raw_25652991'!$F$15 | H36: =IFERROR(B36/$B$36*100,"") | I36: =IFERROR(C36/$B$36*100,"") | J36: =IFERROR(D36/$B$36*100,"") | K36: =IFERROR(E36/$B$36*100,"") | L36: =IFERROR(F36/$B$36*100,"")
A37: Råvarer og hjælpematerialer | B37: ='balance_raw_25652991'!$B$16 | C37: ='balance_raw_25652991'!$C$16 | D37: ='balance_raw_25652991'!$D$16 | E37: ='balance_raw_25652991'!$E$16 | F37: ='balance_raw_25652991'!$F$16 | H37: =IFERROR(B37/$B$37*100,"") | I37: =IFERROR(C37/$B$37*100,"") | J37: =IFERROR(D37/$B$37*100,"") | K37: =IFERROR(E37/$B$37*100,"") | L37: =IFERROR(F37/$B$37*100,"")
A38: Varer under fremstilling | B38: ='balance_raw_25652991'!$B$17 | C38: ='balance_raw_25652991'!$C$17 | D38: ='balance_raw_25652991'!$D$17 | E38: ='balance_raw_25652991'!$E$17 | F38: ='balance_raw_25652991'!$F$17 | H38: =IFERROR(B38/$B$38*100,"") | I38: =IFERROR(C38/$B$38*100,"") | J38: =IFERROR(D38/$B$38*100,"") | K38: =IFERROR(E38/$B$38*100,"") | L38: =IFERROR(F38/$B$38*100,"")
A39: Færdigvarer og handelsvarer | B39: ='balance_raw_25652991'!$B$18 | C39: ='balance_raw_25652991'!$C$18 | D39: ='balance_raw_25652991'!$D$18 | E39: ='balance_raw_25652991'!$E$18 | F39: ='balance_raw_25652991'!$F$18 | H39: =IFERROR(B39/$B$39*100,"") | I39: =IFERROR(C39/$B$39*100,"") | J39: =IFERROR(D39/$B$39*100,"") | K39: =IFERROR(E39/$B$39*100,"") | L39: =IFERROR(F39/$B$39*100,"")
A40: Varebeholdninger | B40: ='balance_raw_25652991'!$B$19 | C40: ='balance_raw_25652991'!$C$19 | D40: ='balance_raw_25652991'!$D$19 | E40: ='balance_raw_25652991'!$E$19 | F40: ='balance_raw_25652991'!$F$19 | H40: =IFERROR(B40/$B$40*100,"") | I40: =IFERROR(C40/$B$40*100,"") | J40: =IFERROR(D40/$B$40*100,"") | K40: =IFERROR(E40/$B$40*100,"") | L40: =IFERROR(F40/$B$40*100,"")
A41: Tilgodehavender fra salg og tjenesteydelser | B41: ='balance_raw_25652991'!$B$20 | C41: ='balance_raw_25652991'!$C$20 | D41: ='balance_raw_25652991'!$D$20 | E41: ='balance_raw_25652991'!$E$20 | F41: ='balance_raw_25652991'!$F$20 | H41: =IFERROR(B41/$B$41*100,"") | I41: =IFERROR(C41/$B$41*100,"") | J41: =IFERROR(D41/$B$41*100,"") | K41: =IFERROR(E41/$B$41*100,"") | L41: =IFERROR(F41/$B$41*100,"")
A42: Tilgodehavender hos tilknyttede virksomheder | B42: ='balance_raw_25652991'!$B$21 | C42: ='balance_raw_25652991'!$C$21 | D42: ='balance_raw_25652991'!$D$21 | E42: ='balance_raw_25652991'!$E$21 | F42: ='balance_raw_25652991'!$F$21 | H42: =IFERROR(B42/$B$42*100,"") | I42: =IFERROR(C42/$B$42*100,"") | J42: =IFERROR(D42/$B$42*100,"") | K42: =IFERROR(E42/$B$42*100,"") | L42: =IFERROR(F42/$B$42*100,"")
A43: Andre tilgodehavender | B43: ='balance_raw_25652991'!$B$22 | C43: ='balance_raw_25652991'!$C$22 | D43: ='balance_raw_25652991'!$D$22 | E43: ='balance_raw_25652991'!$E$22 | F43: ='balance_raw_25652991'!$F$22 | H43: =IFERROR(B43/$B$43*100,"") | I43: =IFERROR(C43/$B$43*100,"") | J43: =IFERROR(D43/$B$43*100,"") | K43: =IFERROR(E43/$B$43*100,"") | L43: =IFERROR(F43/$B$43*100,"")
A44: Periodeafgrænsningsposter (aktiver) | B44: ='balance_raw_25652991'!$B$23 | C44: ='balance_raw_25652991'!$C$23 | D44: ='balance_raw_25652991'!$D$23 | E44: ='balance_raw_25652991'!$E$23 | F44: ='balance_raw_25652991'!$F$23 | H44: =IFERROR(B44/$B$44*100,"") | I44: =IFERROR(C44/$B$44*100,"") | J44: =IFERROR(D44/$B$44*100,"") | K44: =IFERROR(E44/$B$44*100,"") | L44: =IFERROR(F44/$B$44*100,"")
A45: Udskudt skatteaktiv | B45: ='balance_raw_25652991'!$B$24 | C45: ='balance_raw_25652991'!$C$24 | D45: ='balance_raw_25652991'!$D$24 | E45: ='balance_raw_25652991'!$E$24 | F45: ='balance_raw_25652991'!$F$24 | H45: =IFERROR(B45/$B$45*100,"") | I45: =IFERROR(C45/$B$45*100,"") | J45: =IFERROR(D45/$B$45*100,"") | K45: =IFERROR(E45/$B$45*100,"") | L45: =IFERROR(F45/$B$45*100,"")
A46: Tilgodehavende skat hos tilknyttede virksomheder | B46: ='balance_raw_25652991'!$B$25 | C46: ='balance_raw_25652991'!$C$25 | D46: ='balance_raw_25652991'!$D$25 | E46: ='balance_raw_25652991'!$E$25 | F46: ='balance_raw_25652991'!$F$25 | H46: =IFERROR(B46/$B$46*100,"") | I46: =IFERROR(C46/$B$46*100,"") | J46: =IFERROR(D46/$B$46*100,"") | K46: =IFERROR(E46/$B$46*100,"") | L46: =IFERROR(F46/$B$46*100,"")
A47: Kortfristede skattetilgodehavender | B47: ='balance_raw_25652991'!$B$26 | C47: ='balance_raw_25652991'!$C$26 | D47: ='balance_raw_25652991'!$D$26 | E47: ='balance_raw_25652991'!$E$26 | F47: ='balance_raw_25652991'!$F$26 | H47: =IFERROR(B47/$B$47*100,"") | I47: =IFERROR(C47/$B$47*100,"") | J47: =IFERROR(D47/$B$47*100,"") | K47: =IFERROR(E47/$B$47*100,"") | L47: =IFERROR(F47/$B$47*100,"")
A48: Tilgodehavender | B48: ='balance_raw_25652991'!$B$27 | C48: ='balance_raw_25652991'!$C$27 | D48: ='balance_raw_25652991'!$D$27 | E48: ='balance_raw_25652991'!$E$27 | F48: ='balance_raw_25652991'!$F$27 | H48: =IFERROR(B48/$B$48*100,"") | I48: =IFERROR(C48/$B$48*100,"") | J48: =IFERROR(D48/$B$48*100,"") | K48: =IFERROR(E48/$B$48*100,"") | L48: =IFERROR(F48/$B$48*100,"")
A49: Værdipapirer | B49: ='balance_raw_25652991'!$B$28 | C49: ='balance_raw_25652991'!$C$28 | D49: ='balance_raw_25652991'!$D$28 | E49: ='balance_raw_25652991'!$E$28 | F49: ='balance_raw_25652991'!$F$28 | H49: =IFERROR(B49/$B$49*100,"") | I49: =IFERROR(C49/$B$49*100,"") | J49: =IFERROR(D49/$B$49*100,"") | K49: =IFERROR(E49/$B$49*100,"") | L49: =IFERROR(F49/$B$49*100,"")
A50: Likvide beholdninger | B50: ='balance_raw_25652991'!$B$29 | C50: ='balance_raw_25652991'!$C$29 | D50: ='balance_raw_25652991'!$D$29 | E50: ='balance_raw_25652991'!$E$29 | F50: ='balance_raw_25652991'!$F$29 | H50: =IFERROR(B50/$B$50*100,"") | I50: =IFERROR(C50/$B$50*100,"") | J50: =IFERROR(D50/$B$50*100,"") | K50: =IFERROR(E50/$B$50*100,"") | L50: =IFERROR(F50/$B$50*100,"")
A51: Omsætningsaktiver | B51: ='balance_raw_25652991'!$B$30 | C51: ='balance_raw_25652991'!$C$30 | D51: ='balance_raw_25652991'!$D$30 | E51: ='balance_raw_25652991'!$E$30 | F51: ='balance_raw_25652991'!$F$30 | H51: =IFERROR(B51/$B$51*100,"") | I51: =IFERROR(C51/$B$51*100,"") | J51: =IFERROR(D51/$B$51*100,"") | K51: =IFERROR(E51/$B$51*100,"") | L51: =IFERROR(F51/$B$51*100,"")
A52: Aktiver | B52: ='balance_raw_25652991'!$B$31 | C52: ='balance_raw_25652991'!$C$31 | D52: ='balance_raw_25652991'!$D$31 | E52: ='balance_raw_25652991'!$E$31 | F52: ='balance_raw_25652991'!$F$31 | H52: =IFERROR(B52/$B$52*100,"") | I52: =IFERROR(C52/$B$52*100,"") | J52: =IFERROR(D52/$B$52*100,"") | K52: =IFERROR(E52/$B$52*100,"") | L52: =IFERROR(F52/$B$52*100,"")
A54: PASSIVER t.kr. | B54: 2020 | C54: 2021 | D54: 2022 | E54: 2023 | F54: 2024 | H54: 2020 | I54: 2021 | J54: 2022 | K54: 2023 | L54: 2024
A55: Selskabskapital | B55: ='balance_raw_25652991'!$B$32 | C55: ='balance_raw_25652991'!$C$32 | D55: ='balance_raw_25652991'!$D$32 | E55: ='balance_raw_25652991'!$E$32 | F55: ='balance_raw_25652991'!$F$32 | H55: =IFERROR(B55/$B$55*100,"") | I55: =IFERROR(C55/$B$55*100,"") | J55: =IFERROR(D55/$B$55*100,"") | K55: =IFERROR(E55/$B$55*100,"") | L55: =IFERROR(F55/$B$55*100,"")
A56: Reserve for nettoopskrivning (indre værdis metode) | B56: ='balance_raw_25652991'!$B$33 | C56: ='balance_raw_25652991'!$C$33 | D56: ='balance_raw_25652991'!$D$33 | E56: ='balance_raw_25652991'!$E$33 | F56: ='balance_raw_25652991'!$F$33 | H56: =IFERROR(B56/$B$56*100,"") | I56: =IFERROR(C56/$B$56*100,"") | J56: =IFERROR(D56/$B$56*100,"") | K56: =IFERROR(E56/$B$56*100,"") | L56: =IFERROR(F56/$B$56*100,"")
A57: Reserve for udviklingsomkostninger | B57: ='balance_raw_25652991'!$B$34 | C57: ='balance_raw_25652991'!$C$34 | D57: ='balance_raw_25652991'!$D$34 | E57: ='balance_raw_25652991'!$E$34 | F57: ='balance_raw_25652991'!$F$34 | H57: =IFERROR(B57/$B$57*100,"") | I57: =IFERROR(C57/$B$57*100,"") | J57: =IFERROR(D57/$B$57*100,"") | K57: =IFERROR(E57/$B$57*100,"") | L57: =IFERROR(F57/$B$57*100,"")
A58: Reserve for sikringstransaktioner | B58: ='balance_raw_25652991'!$B$35 | C58: ='balance_raw_25652991'!$C$35 | D58: ='balance_raw_25652991'!$D$35 | E58: ='balance_raw_25652991'!$E$35 | F58: ='balance_raw_25652991'!$F$35 | H58: =IFERROR(B58/$B$58*100,"") | I58: =IFERROR(C58/$B$58*100,"") | J58: =IFERROR(D58/$B$58*100,"") | K58: =IFERROR(E58/$B$58*100,"") | L58: =IFERROR(F58/$B$58*100,"")
A59: Andre reserver | B59: ='balance_raw_25652991'!$B$36 | C59: ='balance_raw_25652991'!$C$36 | D59: ='balance_raw_25652991'!$D$36 | E59: ='balance_raw_25652991'!$E$36 | F59: ='balance_raw_25652991'!$F$36 | H59: =IFERROR(B59/$B$59*100,"") | I59: =IFERROR(C59/$B$59*100,"") | J59: =IFERROR(D59/$B$59*100,"") | K59: =IFERROR(E59/$B$59*100,"") | L59: =IFERROR(F59/$B$59*100,"")
A60: Overført resultat | B60: ='balance_raw_25652991'!$B$37 | C60: ='balance_raw_25652991'!$C$37 | D60: ='balance_raw_25652991'!$D$37 | E60: ='balance_raw_25652991'!$E$37 | F60: ='balance_raw_25652991'!$F$37 | H60: =IFERROR(B60/$B$60*100,"") | I60: =IFERROR(C60/$B$60*100,"") | J60: =IFERROR(D60/$B$60*100,"") | K60: =IFERROR(E60/$B$60*100,"") | L60: =IFERROR(F60/$B$60*100,"")
A61: Egenkapital i alt | B61: ='balance_raw_25652991'!$B$38 | C61: ='balance_raw_25652991'!$C$38 | D61: ='balance_raw_25652991'!$D$38 | E61: ='balance_raw_25652991'!$E$38 | F61: ='balance_raw_25652991'!$F$38 | H61: =IFERROR(B61/$B$61*100,"") | I61: =IFERROR(C61/$B$61*100,"") | J61: =IFERROR(D61/$B$61*100,"") | K61: =IFERROR(E61/$B$61*100,"") | L61: =IFERROR(F61/$B$61*100,"")
A62: Hensatte forpligtelser | B62: ='balance_raw_25652991'!$B$39 | C62: ='balance_raw_25652991'!$C$39 | D62: ='balance_raw_25652991'!$D$39 | E62: ='balance_raw_25652991'!$E$39 | F62: ='balance_raw_25652991'!$F$39 | H62: =IFERROR(B62/$B$62*100,"") | I62: =IFERROR(C62/$B$62*100,"") | J62: =IFERROR(D62/$B$62*100,"") | K62: =IFERROR(E62/$B$62*100,"") | L62: =IFERROR(F62/$B$62*100,"")
A63: Ansvarlig lånekapital (langfristet) | B63: ='balance_raw_25652991'!$B$40 | C63: ='balance_raw_25652991'!$C$40 | D63: ='balance_raw_25652991'!$D$40 | E63: ='balance_raw_25652991'!$E$40 | F63: ='balance_raw_25652991'!$F$40 | H63: =IFERROR(B63/$B$63*100,"") | I63: =IFERROR(C63/$B$63*100,"") | J63: =IFERROR(D63/$B$63*100,"") | K63: =IFERROR(E63/$B$63*100,"") | L63: =IFERROR(F63/$B$63*100,"")
A64: Langfristede lån | B64: ='balance_raw_25652991'!$B$41 | C64: ='balance_raw_25652991'!$C$41 | D64: ='balance_raw_25652991'!$D$41 | E64: ='balance_raw_25652991'!$E$41 | F64: ='balance_raw_25652991'!$F$41 | H64: =IFERROR(B64/$B$64*100,"") | I64: =IFERROR(C64/$B$64*100,"") | J64: =IFERROR(D64/$B$64*100,"") | K64: =IFERROR(E64/$B$64*100,"") | L64: =IFERROR(F64/$B$64*100,"")
A65: Leasingforpligtelser (langfristet) | B65: ='balance_raw_25652991'!$B$42 | C65: ='balance_raw_25652991'!$C$42 | D65: ='balance_raw_25652991'!$D$42 | E65: ='balance_raw_25652991'!$E$42 | F65: ='balance_raw_25652991'!$F$42 | H65: =IFERROR(B65/$B$65*100,"") | I65: =IFERROR(C65/$B$65*100,"") | J65: =IFERROR(D65/$B$65*100,"") | K65: =IFERROR(E65/$B$65*100,"") | L65: =IFERROR(F65/$B$65*100,"")
A66: Anden gæld (langfristet) | B66: ='balance_raw_25652991'!$B$43 | C66: ='balance_raw_25652991'!$C$43 | D66: ='balance_raw_25652991'!$D$43 | E66: ='balance_raw_25652991'!$E$43 | F66: ='balance_raw_25652991'!$F$43 | H66: =IFERROR(B66/$B$66*100,"") | I66: =IFERROR(C66/$B$66*100,"") | J66: =IFERROR(D66/$B$66*100,"") | K66: =IFERROR(E66/$B$66*100,"") | L66: =IFERROR(F66/$B$66*100,"")
A67: Langfristede gældsforpligtelser | B67: ='balance_raw_25652991'!$B$44 | C67: ='balance_raw_25652991'!$C$44 | D67: ='balance_raw_25652991'!$D$44 | E67: ='balance_raw_25652991'!$E$44 | F67: ='balance_raw_25652991'!$F$44 | H67: =IFERROR(B67/$B$67*100,"") | I67: =IFERROR(C67/$B$67*100,"") | J67: =IFERROR(D67/$B$67*100,"") | K67: =IFERROR(E67/$B$67*100,"") | L67: =IFERROR(F67/$B$67*100,"")
A68: Ansvarlig lånekapital (kortfristet) | B68: ='balance_raw_25652991'!$B$45 | C68: ='balance_raw_25652991'!$C$45 | D68: ='balance_raw_25652991'!$D$45 | E68: ='balance_raw_25652991'!$E$45 | F68: ='balance_raw_25652991'!$F$45 | H68: =IFERROR(B68/$B$68*100,"") | I68: =IFERROR(C68/$B$68*100,"") | J68: =IFERROR(D68/$B$68*100,"") | K68: =IFERROR(E68/$B$68*100,"") | L68: =IFERROR(F68/$B$68*100,"")
A69: Kortfristet del af langfristede gældsforpligtelser | B69: ='balance_raw_25652991'!$B$46 | C69: ='balance_raw_25652991'!$C$46 | D69: ='balance_raw_25652991'!$D$46 | E69: ='balance_raw_25652991'!$E$46 | F69: ='balance_raw_25652991'!$F$46 | H69: =IFERROR(B69/$B$69*100,"") | I69: =IFERROR(C69/$B$69*100,"") | J69: =IFERROR(D69/$B$69*100,"") | K69: =IFERROR(E69/$B$69*100,"") | L69: =IFERROR(F69/$B$69*100,"")
A70: Kreditinstitutter | B70: ='balance_raw_25652991'!$B$47 | C70: ='balance_raw_25652991'!$C$47 | D70: ='balance_raw_25652991'!$D$47 | E70: ='balance_raw_25652991'!$E$47 | F70: ='balance_raw_25652991'!$F$47 | H70: =IFERROR(B70/$B$70*100,"") | I70: =IFERROR(C70/$B$70*100,"") | J70: =IFERROR(D70/$B$70*100,"") | K70: =IFERROR(E70/$B$70*100,"") | L70: =IFERROR(F70/$B$70*100,"")
A71: Leasingforpligtelser (kortfristet) | B71: ='balance_raw_25652991'!$B$48 | C71: ='balance_raw_25652991'!$C$48 | D71: ='balance_raw_25652991'!$D$48 | E71: ='balance_raw_25652991'!$E$48 | F71: ='balance_raw_25652991'!$F$48 | H71: =IFERROR(B71/$B$71*100,"") | I71: =IFERROR(C71/$B$71*100,"") | J71: =IFERROR(D71/$B$71*100,"") | K71: =IFERROR(E71/$B$71*100,"") | L71: =IFERROR(F71/$B$71*100,"")
A72: Leverandører af varer og tjenesteydelser | B72: ='balance_raw_25652991'!$B$49 | C72: ='balance_raw_25652991'!$C$49 | D72: ='balance_raw_25652991'!$D$49 | E72: ='balance_raw_25652991'!$E$49 | F72: ='balance_raw_25652991'!$F$49 | H72: =IFERROR(B72/$B$72*100,"") | I72: =IFERROR(C72/$B$72*100,"") | J72: =IFERROR(D72/$B$72*100,"") | K72: =IFERROR(E72/$B$72*100,"") | L72: =IFERROR(F72/$B$72*100,"")
A73: Gæld til tilknyttede virksomheder | B73: ='balance_raw_25652991'!$B$50 | C73: ='balance_raw_25652991'!$C$50 | D73: ='balance_raw_25652991'!$D$50 | E73: ='balance_raw_25652991'!$E$50 | F73: ='balance_raw_25652991'!$F$50 | H73: =IFERROR(B73/$B$73*100,"") | I73: =IFERROR(C73/$B$73*100,"") | J73: =IFERROR(D73/$B$73*100,"") | K73: =IFERROR(E73/$B$73*100,"") | L73: =IFERROR(F73/$B$73*100,"")
A74: Gæld til selskabsdeltagere og ledelse | B74: ='balance_raw_25652991'!$B$51 | C74: ='balance_raw_25652991'!$C$51 | D74: ='balance_raw_25652991'!$D$51 | E74: ='balance_raw_25652991'!$E$51 | F74: ='balance_raw_25652991'!$F$51 | H74: =IFERROR(B74/$B$74*100,"") | I74: =IFERROR(C74/$B$74*100,"") | J74: =IFERROR(D74/$B$74*100,"") | K74: =IFERROR(E74/$B$74*100,"") | L74: =IFERROR(F74/$B$74*100,"")
A75: Selskabsskat | B75: ='balance_raw_25652991'!$B$52 | C75: ='balance_raw_25652991'!$C$52 | D75: ='balance_raw_25652991'!$D$52 | E75: ='balance_raw_25652991'!$E$52 | F75: ='balance_raw_25652991'!$F$52 | H75: =IFERROR(B75/$B$75*100,"") | I75: =IFERROR(C75/$B$75*100,"") | J75: =IFERROR(D75/$B$75*100,"") | K75: =IFERROR(E75/$B$75*100,"") | L75: =IFERROR(F75/$B$75*100,"")
A76: Gæld til tilknyttede virksomheder vedr. selskabsskat | B76: ='balance_raw_25652991'!$B$53 | C76: ='balance_raw_25652991'!$C$53 | D76: ='balance_raw_25652991'!$D$53 | E76: ='balance_raw_25652991'!$E$53 | F76: ='balance_raw_25652991'!$F$53 | H76: =IFERROR(B76/$B$76*100,"") | I76: =IFERROR(C76/$B$76*100,"") | J76: =IFERROR(D76/$B$76*100,"") | K76: =IFERROR(E76/$B$76*100,"") | L76: =IFERROR(F76/$B$76*100,"")
A77: Anden gæld (kortfristet) | B77: ='balance_raw_25652991'!$B$54 | C77: ='balance_raw_25652991'!$C$54 | D77: ='balance_raw_25652991'!$D$54 | E77: ='balance_raw_25652991'!$E$54 | F77: ='balance_raw_25652991'!$F$54 | H77: =IFERROR(B77/$B$77*100,"") | I77: =IFERROR(C77/$B$77*100,"") | J77: =IFERROR(D77/$B$77*100,"") | K77: =IFERROR(E77/$B$77*100,"") | L77: =IFERROR(F77/$B$77*100,"")
A78: Periodeafgrænsningsposter (passiver) | B78: ='balance_raw_25652991'!$B$55 | C78: ='balance_raw_25652991'!$C$55 | D78: ='balance_raw_25652991'!$D$55 | E78: ='balance_raw_25652991'!$E$55 | F78: ='balance_raw_25652991'!$F$55 | H78: =IFERROR(B78/$B$78*100,"") | I78: =IFERROR(C78/$B$78*100,"") | J78: =IFERROR(D78/$B$78*100,"") | K78: =IFERROR(E78/$B$78*100,"") | L78: =IFERROR(F78/$B$78*100,"")
A79: Kortfristede gældsforpligtelser | B79: ='balance_raw_25652991'!$B$56 | C79: ='balance_raw_25652991'!$C$56 | D79: ='balance_raw_25652991'!$D$56 | E79: ='balance_raw_25652991'!$E$56 | F79: ='balance_raw_25652991'!$F$56 | H79: =IFERROR(B79/$B$79*100,"") | I79: =IFERROR(C79/$B$79*100,"") | J79: =IFERROR(D79/$B$79*100,"") | K79: =IFERROR(E79/$B$79*100,"") | L79: =IFERROR(F79/$B$79*100,"")
A80: Gældsforpligtelser | B80: ='balance_raw_25652991'!$B$57 | C80: ='balance_raw_25652991'!$C$57 | D80: ='balance_raw_25652991'!$D$57 | E80: ='balance_raw_25652991'!$E$57 | F80: ='balance_raw_25652991'!$F$57 | H80: =IFERROR(B80/$B$80*100,"") | I80: =IFERROR(C80/$B$80*100,"") | J80: =IFERROR(D80/$B$80*100,"") | K80: =IFERROR(E80/$B$80*100,"") | L80: =IFERROR(F80/$B$80*100,"")
A81: Passiver | B81: ='balance_raw_25652991'!$B$58 | C81: ='balance_raw_25652991'!$C$58 | D81: ='balance_raw_25652991'!$D$58 | E81: ='balance_raw_25652991'!$E$58 | F81: ='balance_raw_25652991'!$F$58 | H81: =IFERROR(B81/$B$81*100,"") | I81: =IFERROR(C81/$B$81*100,"") | J81: =IFERROR(D81/$B$81*100,"") | K81: =IFERROR(E81/$B$81*100,"") | L81: =IFERROR(F81/$B$81*100,"")
A83: NØGLEOPLYSNINGER | B83: 2020 | C83: 2021 | D83: 2022 | E83: 2023 | F83: 2024
A84: Gns. antal medarbejdere | B84: ='res_raw_25652991'!$B$19 | C84: ='res_raw_25652991'!$C$19 | D84: ='res_raw_25652991'!$D$19 | E84: ='res_raw_25652991'!$E$19 | F84: ='res_raw_25652991'!$F$19 | H84: =IFERROR(B84/$B$84*100,"") | I84: =IFERROR(C84/$B$84*100,"") | J84: =IFERROR(D84/$B$84*100,"") | K84: =IFERROR(E84/$B$84*100,"") | L84: =IFERROR(F84/$B$84*100,"")
A85: Investering i materielle anlægsaktiver | B85: ='res_raw_25652991'!$B$20 | C85: ='res_raw_25652991'!$C$20 | D85: ='res_raw_25652991'!$D$20 | E85: ='res_raw_25652991'!$E$20 | F85: ='res_raw_25652991'!$F$20 | H85: =IFERROR(B85/$B$85*100,"") | I85: =IFERROR(C85/$B$85*100,"") | J85: =IFERROR(D85/$B$85*100,"") | K85: =IFERROR(E85/$B$85*100,"") | L85: =IFERROR(F85/$B$85*100,"")
A87: NØGLETAL | B87: 2020 | C87: 2021 | D87: 2022 | E87: 2023 | F87: 2024
A88: Afkastningsgrad, % | B88: =IFERROR(($B$13+$B$15+$B$14)/$B$52*100,"") | C88: =IFERROR(($C$13+$C$15+$C$14)/$C$52*100,"") | D88: =IFERROR(($D$13+$D$15+$D$14)/$D$52*100,"") | E88: =IFERROR(($E$13+$E$15+$E$14)/$E$52*100,"") | F88: =IFERROR(($F$13+$F$15+$F$14)/$F$52*100,"")
A89: Overskudsgrad, % | B89: =IFERROR(($B$13+$B$15+$B$14)/$B$4*100,"") | C89: =IFERROR(($C$13+$C$15+$C$14)/$C$4*100,"") | D89: =IFERROR(($D$13+$D$15+$D$14)/$D$4*100,"") | E89: =IFERROR(($E$13+$E$15+$E$14)/$E$4*100,"") | F89: =IFERROR(($F$13+$F$15+$F$14)/$F$4*100,"")
A90: Aktivernes omsætningshastighed, gange | B90: =IFERROR($B$4/$B$52,"") | C90: =IFERROR($C$4/$C$52,"") | D90: =IFERROR($D$4/$D$52,"") | E90: =IFERROR($E$4/$E$52,"") | F90: =IFERROR($F$4/$F$52,"")
A91: Egenkapitalens forrentning, % | B91: =IFERROR($B$18/$B$61*100,"") | C91: =IFERROR($C$18/$C$61*100,"") | D91: =IFERROR($D$18/$D$61*100,"") | E91: =IFERROR($E$18/$E$61*100,"") | F91: =IFERROR($F$18/$F$61*100,"")
A92: Gældsrente, % | B92: =IFERROR($B$16/($B$81-$B$61)*100,"") | C92: =IFERROR($C$16/($C$81-$C$61)*100,"") | D92: =IFERROR($D$16/($D$81-$D$61)*100,"") | E92: =IFERROR($E$16/($E$81-$E$61)*100,"") | F92: =IFERROR($F$16/($F$81-$F$61)*100,"")
A93: Soliditetsgrad, % | B93: =IFERROR($B$61/$B$52*100,"") | C93: =IFERROR($C$61/$C$52*100,"") | D93: =IFERROR($D$61/$D$52*100,"") | E93: =IFERROR($E$61/$E$52*100,"") | F93: =IFERROR($F$61/$F$52*100,"")
A94: Gearing | B94: =IFERROR(($B$81-$B$61)/$B$61,"") | C94: =IFERROR(($C$81-$C$61)/$C$61,"") | D94: =IFERROR(($D$81-$D$61)/$D$61,"") | E94: =IFERROR(($E$81-$E$61)/$E$61,"") | F94: =IFERROR(($F$81-$F$61)/$F$61,"")
A95: Likviditetsgrad, % | B95: =IFERROR($B$51/$B$79*100,"") | C95: =IFERROR($C$51/$C$79*100,"") | D95: =IFERROR($D$51/$D$79*100,"") | E95: =IFERROR($E$51/$E$79*100,"") | F95: =IFERROR($F$51/$F$79*100,"")
A96: Rentemarginal, % | B96: =IFERROR(B88-B92,"") | C96: =IFERROR(C88-C92,"") | D96: =IFERROR(D88-D92,"") | E96: =IFERROR(E88-E92,"") | F96: =IFERROR(F88-F92,"")
A97: Gældsandel, % | B97: =IFERROR(($B$81-$B$61)/$B$52*100,"") | C97: =IFERROR(($C$81-$C$61)/$C$52*100,"") | D97: =IFERROR(($D$81-$D$61)/$D$52*100,"") | E97: =IFERROR(($E$81-$E$61)/$E$52*100,"") | F97: =IFERROR(($F$81-$F$61)/$F$52*100,"")
A98: Kapitalbindingsgrad, % | B98: =IFERROR($B$36/($B$61+$B$67)*100,"") | C98: =IFERROR($C$36/($C$61+$C$67)*100,"") | D98: =IFERROR($D$36/($D$61+$D$67)*100,"") | E98: =IFERROR($E$36/($E$61+$E$67)*100,"") | F98: =IFERROR($F$36/($F$61+$F$67)*100,"")

Sheet res_raw_25652991
A1: Resultatopgørelse & nøgleoplysninger (t.kr.) | B1: 2020 | C1: 2021 | D1: 2022 | E1: 2023 | F1: 2024
A2: Nettoomsætning | B2: 914953 | C2: 768149 | D2: 1189258 | E2: 1195178 | F2: 1187681
A3: Andre driftsindtægter | B3: 184186 | C3: 206076 | D3: 485 | E3: 997 | F3: 13484
A4: Vareforbrug | B4: 75647 | C4: 50576 | D4: 77900 | E4: 80912 | F4: 70230
A5: Andre eksterne omkostninger | B5: 706838 | C5: 630891 | D5: 677139 | E5: 693318 | F5: 655035
A6: Bruttoresultat | B6: 316654 | C6: 292758 | D6: 434704 | E6: 421945 | F6: 475900
A7: Personaleomkostninger | B7: 388570 | C7: 394008 | D7: 318034 | E7: 313685 | F7: 285536
A8: Resultat før afskrivninger
A9: Af- og nedskrivninger | B9: 271012 | C9: 158360 | D9: 177726 | E9: 145299 | F9: 156670
A10: Andre driftsomkostninger | C10: 11035 | D10: 6158 | E10: 10389 | F10: 5550
A11: Resultat af primær drift | B11: -342928 | C11: -270645 | D11: -67214 | E11: -47428 | F11: 28144
A12: Indtægter af kapitalandele, dattervirksomheder | B12: -33194 | C12: 0
A13: Finansielle indtægter | B13: 159 | C13: 1501 | D13: 5103 | E13: 2472 | F13: 3132
A14: Finansielle omkostninger | B14: 9051 | C14: 9571 | D14: 9819 | E14: 9055 | F14: 17594
A15: Finansielle poster, netto | B15: -8892 | C15: -8070 | D15: -4716 | E15: -6583 | F15: -14462
A16: Resultat før skat | B16: -385014 | C16: -278715 | D16: -71930 | E16: -54011 | F16: 13682
A17: Skat af årets resultat | B17: -55478 | C17: -57262 | D17: -48866 | E17: -4649 | F17: 4690
A18: Årets resultat | B18: -329536 | C18: -221453 | D18: -23064 | E18: -49362 | F18: 8992
A19: Gns. antal medarbejdere | B19: 1 | C19: 1036 | D19: 678 | E19: 630 | F19: 597
A20: Investering i materielle anlægsaktiver | B20: 47800 | C20: 17014 | D20: 158086 | E20: 105166 | F20: 311010

Sheet balance_raw_25652991
A1: Balance (t.kr.) | B1: 2020 | C1: 2021 | D1: 2022 | E1: 2023 | F1: 2024
A2: Udviklingsprojekter | B2: 30256 | C2: 4315 | D2: 2556 | E2: 4583 | F2: 1742
A3: Patenter, varemærker mv. | B3: 480 | C3: 18654 | D3: 8775 | E3: 1215 | F3: 0
A4: Goodwill | B4: 84692 | C4: 59734 | D4: 39641 | E4: 23151 | F4: 7297
A5: Immaterielle anlægsaktiver | B5: 145720 | C5: 83063 | D5: 51212 | E5: 29069 | F5: 22825
A6: Grunde og bygninger
A7: Produktionsanlæg og maskiner
A8: Driftsmateriel og inventar | B8: 216896 | C8: 161850 | D8: 119267 | E8: 112490 | F8: 250770
A9: Indretning af lejede lokaler | B9: 144420 | C9: 133150 | D9: 170396 | E9: 149834 | F9: 179935
A10: Forudbetaling og anlægsaktiver under opførelse | B10: 27762 | C10: 2884 | D10: 7592 | E10: 8336 | F10: 3604
A11: Materielle anlægsaktiver | B11: 389078 | C11: 297884 | D11: 297255 | E11: 270660 | F11: 434309
A12: Kapitalandele, dattervirksomheder | B12: 0 | C12: 0 | D12: 0 | E12: 0 | F12: 0
A13: Deposita | B13: 48476 | C13: 52140 | D13: 48692 | E13: 51771 | F13: 51728
A14: Finansielle anlægsaktiver | B14: 48476 | C14: 52140 | D14: 48692 | E14: 51771 | F14: 51728
A15: Anlægsaktiver | B15: 583274 | C15: 433087 | D15: 397159 | E15: 351500 | F15: 508862
A16: Råvarer og hjælpematerialer
A17: Varer under fremstilling
A18: Færdigvarer og handelsvarer | C18: 10734 | D18: 15332 | E18: 9392 | F18: 9023
A19: Varebeholdninger | B19: 12123 | C19: 10734 | D19: 15332 | E19: 9392 | F19: 9023
A20: Tilgodehavender fra salg og tjenesteydelser | B20: 12452 | C20: 21590 | D20: 19296 | E20: 11127 | F20: 8465
A21: Tilgodehavender hos tilknyttede virksomheder | B21: 15145 | C21: 9392 | D21: 8678 | E21: 17499 | F21: 1812
A22: Andre tilgodehavender | B22: 28465 | C22: 4231 | D22: 4876 | E22: 6106 | F22: 4320
A23: Periodeafgrænsningsposter (aktiver) | B23: 8763 | C23: 9056 | D23: 11315 | E23: 19506 | F23: 23352
A24: Udskudt skatteaktiv | B24: 26558 | C24: 76371 | D24: 122460 | E24: 129869 | F24: 124991
A25: Tilgodehavende skat hos tilknyttede virksomheder | C25: 751 | D25: 508 | E25: 0
A26: Kortfristede skattetilgodehavender
A27: Tilgodehavender | B27: 91383 | C27: 121391 | D27: 167133 | E27: 184107 | F27: 162940
A28: Værdipapirer
A29: Likvide beholdninger | B29: 11577 | C29: 95597 | D29: 13668 | E29: 94904 | F29: 74359
A30: Omsætningsaktiver | B30: 115083 | C30: 227722 | D30: 196133 | E30: 288403 | F30: 246322
A31: Aktiver | B31: 698357 | C31: 660809 | D31: 593292 | E31: 639903 | F31: 755184
A32: Selskabskapital | B32: 891 | C32: 891 | D32: 891 | E32: 891 | F32: 891
A33: Reserve for nettoopskrivning (indre værdis metode)
A34: Reserve for udviklingsomkostninger | B34: 18751 | C34: 3749 | D34: 773 | E34: 0 | F34: 10382
A35: Reserve for sikringstransaktioner
A36: Andre reserver
A37: Overført resultat | B37: 57 | C37: -206393 | D37: 23519 | E37: 74930 | F37: 49695
A38: Egenkapital i alt | B38: 19699 | C38: -201753 | D38: 25183 | E38: 75821 | F38: 60968
A39: Hensatte forpligtelser | B39: 82851 | C39: 60073 | D39: 103961 | E39: 131334 | F39: 124804
A40: Ansvarlig lånekapital (langfristet)
A41: Langfristede lån
A42: Leasingforpligtelser (langfristet) | B42: 70578 | C42: 35994 | D42: 17227 | E42: 6270 | F42: 916
A43: Anden gæld (langfristet) | B43: 27153 | C43: 44983 | D43: 19942 | E43: 144813 | F43: 151278
A44: Langfristede gældsforpligtelser | B44: 179662 | C44: 166565 | D44: 126578 | E44: 169387 | F44: 187443
A45: Ansvarlig lånekapital (kortfristet)
A46: Kortfristet del af langfristede gældsforpligtelser | C46: 35447 | D46: 18769 | E46: 10957 | F46: 8131
A47: Kreditinstitutter | B47: 0
A48: Leasingforpligtelser (kortfristet) | B48: 36658
A49: Leverandører af varer og tjenesteydelser | B49: 108306 | C49: 81355 | D49: 80173 | E49: 84865 | F49: 209725
A50: Gæld til tilknyttede virksomheder | B50: 59543 | C50: 379266 | D50: 208768 | E50: 116050 | F50: 110127
A51: Gæld til selskabsdeltagere og ledelse
A52: Selskabsskat
A53: Gæld til tilknyttede virksomheder vedr. selskabsskat | B53: 7850 | C53: 0 | E53: 163 | F53: 0
A54: Anden gæld (kortfristet) | B54: 60919 | C54: 67816 | D54: 17252 | E54: 40026 | F54: 44128
A55: Periodeafgrænsningsposter (passiver) | B55: 142869 | C55: 72040 | D55: 12608 | E55: 11300 | F55: 9858
A56: Kortfristede gældsforpligtelser | B56: 416145 | C56: 635924 | D56: 337570 | E56: 263361 | F56: 381969
A57: Gældsforpligtelser | B57: 595807 | C57: 802489 | D57: 464148 | E57: 432748 | F57: 569412
A58: Passiver | B58: 698357 | C58: 660809 | D58: 593292 | E58: 639903 | F58: 755184

Sheet Simpel_arts
A1: Regnskabs- og nøgletal (CVR: 25652991) — artsopdelt
A3: Beløb i 1.000 kr. | B3: 2024 | C3: 2023 | D3: 2022 | F3: Note / XBRL-felt
A4: Uddrag af resultatopgørelse
A5: Nettoomsætning | B5: ='res_raw_25652991'!$F$2 | C5: ='res_raw_25652991'!$E$2 | D5: ='res_raw_25652991'!$D$2 | F5: fsa:Revenue
A6: Andre driftsindtægter | B6: ='res_raw_25652991'!$F$3 | C6: ='res_raw_25652991'!$E$3 | D6: ='res_raw_25652991'!$D$3 | F6: fsa:OtherOperatingIncome. Indtægter fra sekundære aktiviteter (huslejeindtægter, avance ved salg af anlæg mv.).
A7: Vareforbrug | B7: =-'res_raw_25652991'!$F$4 | C7: =-'res_raw_25652991'!$E$4 | D7: =-'res_raw_25652991'!$D$4 | F7: fsa:CostOfSales (vises negativt for korrekt SUM-formel).
A8: Andre eksterne omk. mv. | B8: =-'res_raw_25652991'!$F$5 | C8: =-'res_raw_25652991'!$E$5 | D8: =-'res_raw_25652991'!$D$5 | F8: fsa:OtherExternalExpenses (vises negativt). Husleje, energi, kontorhold mv.
A9: Bruttofortjeneste | B9: =SUM(B5:B8) | C9: =SUM(C5:C8) | D9: =SUM(D5:D8) | F9: Beregnet: Nettoomsætning + Andre driftsindt. − Vareforbrug − Andre ext. omk.
A10: Personaleomkostninger | B10: =-'res_raw_25652991'!$F$7 | C10: =-'res_raw_25652991'!$E$7 | D10: =-'res_raw_25652991'!$D$7 | F10: fsa:EmployeeBenefitsExpense (vises negativt). Lønninger, pension, sociale ydelser.
A11: Af- og nedskrivninger | B11: =-'res_raw_25652991'!$F$9 | C11: =-'res_raw_25652991'!$E$9 | D11: =-'res_raw_25652991'!$D$9 | F11: fsa:Depreciation (vises negativt). Af- og nedskrivninger på materielle og immaterielle anlægsaktiver.
A12: Andre driftsomkostninger | B12: =-'res_raw_25652991'!$F$10 | C12: =-'res_raw_25652991'!$E$10 | D12: =-'res_raw_25652991'!$D$10 | F12: fsa:OtherOperatingExpenses (vises negativt). Typisk 0 eller meget lille post.
A13: Resultat af primær drift | B13: =SUM(B9:B12) | C13: =SUM(C9:C12) | D13: =SUM(D9:D12) | F13: Beregnet: Bruttofortjeneste − Personaleomk. − Af- og nedskrivninger − Andre driftsomk. EBIT.
A14: Finansielle indtægter mv. | B14: =N('res_raw_25652991'!$F$12)+N('res_raw_25652991'!$F$13) | C14: =N('res_raw_25652991'!$E$12)+N('res_raw_25652991'!$E$13) | D14: =N('res_raw_25652991'!$D$12)+N('res_raw_25652991'!$D$13) | F14: fsa:IncomeFromSubsidiaries + fsa:OtherFinanceIncome.
A15: Finansielle omkostninger mv. | B15: =-'res_raw_25652991'!$F$14 | C15: =-'res_raw_25652991'!$E$14 | D15: =-'res_raw_25652991'!$D$14 | F15: fsa:OtherFinanceExpenses (vises negativt). Renteomkostninger, kurstab mv.
A16: Resultat før skat | B16: =SUM(B13:B15) | C16: =SUM(C13:C15) | D16: =SUM(D13:D15) | F16: Beregnet: EBIT + Fin. indtægter + Fin. omk. EBT.
A18: Uddrag af balance
A19: Anlægsaktiver | B19: ='balance_raw_25652991'!$F$15 | C19: ='balance_raw_25652991'!$E$15 | D19: ='balance_raw_25652991'!$D$15 | F19: fsa:NoncurrentAssets. Materielle, immaterielle og finansielle anlægsaktiver.
A20: Omsætningsaktiver | B20: ='balance_raw_25652991'!$F$30 | C20: ='balance_raw_25652991'!$E$30 | D20: ='balance_raw_25652991'!$D$30 | F20: fsa:CurrentAssets. Varebeholdninger, tilgodehavender, likvider.
A21: Aktiver i alt | B21: =SUM(B19:B20) | C21: =SUM(C19:C20) | D21: =SUM(D19:D20) | F21: Beregnet: Anlægsaktiver + Omsætningsaktiver. Bør matche fsa:Assets.
A23: Egenkapital | B23: ='balance_raw_25652991'!$F$38 | C23: ='balance_raw_25652991'!$E$38 | D23: ='balance_raw_25652991'!$D$38 | F23: fsa:Equity. Selskabskapital, overført resultat, reserver.
A24: Forpligtelser | B24: ='balance_raw_25652991'!$F$58-'balance_raw_25652991'!$F$38 | C24: ='balance_raw_25652991'!$E$58-'balance_raw_25652991'!$E$38 | D24: ='balance_raw_25652991'!$D$58-'balance_raw_25652991'!$D$38 | F24: Beregnet: Passiver (fsa:LiabilitiesAndEquity) − Egenkapital. Hensættelser + kort- og langfristet gæld.
A25: Passiver i alt | B25: =SUM(B23:B24) | C25: =SUM(C23:C24) | D25: =SUM(D23:D24) | F25: Beregnet: Egenkapital + Forpligtelser. Bør matche Aktiver i alt.
A27: Udvalgte balanceposter
A28: Varebeholdninger | B28: ='balance_raw_25652991'!$F$19 | C28: ='balance_raw_25652991'!$E$19 | D28: ='balance_raw_25652991'!$D$19 | F28: fsa:Inventories (eller fsa:ManufacturedGoodsAndGoodsForResale hvis total mangler).
A29: Tilgodehavender fra salg | B29: ='balance_raw_25652991'!$F$20 | C29: ='balance_raw_25652991'!$E$20 | D29: ='balance_raw_25652991'!$D$20 | F29: fsa:ShorttermTradeReceivables. Kortfristede tilgodehavender fra kunder.
A30: Kortfristede gældsforpligtelser | B30: ='balance_raw_25652991'!$F$56 | C30: ='balance_raw_25652991'!$E$56 | D30: ='balance_raw_25652991'!$D$56 | F30: fsa:ShorttermLiabilitiesOtherThanProvisions. Gæld der forfalder inden for 1 år.
A32: Rentabilitet
A33: Afkastningsgrad, % | B33: =IFERROR((B13+B14)/B21*100,"") | C33: =IFERROR((C13+C14)/C21*100,"") | D33: =IFERROR((D13+D14)/D21*100,"")
A34: Overskudsgrad, % | B34: =IFERROR((B13+B14)/B5*100,"") | C34: =IFERROR((C13+C14)/C5*100,"") | D34: =IFERROR((D13+D14)/D5*100,"")
A35: Aktivernes omsætningshastighed, gange | B35: =IFERROR(B5/B21,"") | C35: =IFERROR(C5/C21,"") | D35: =IFERROR(D5/D21,"")
A36: Gældsrente, % | B36: =IFERROR(-B15*100/B24,"") | C36: =IFERROR(-C15*100/C24,"") | D36: =IFERROR(-D15*100/D24,"")
A37: Egenkapitalens forrentning, % | B37: =IFERROR(B16/B23*100,"") | C37: =IFERROR(C16/C23*100,"") | D37: =IFERROR(D16/D23*100,"")
A38: Gearing, gange | B38: =IFERROR(B24/B23,"") | C38: =IFERROR(C24/C23,"") | D38: =IFERROR(D24/D23,"")
A40: Indekstal for indtjeningsevne (2022=100)
A41: Nettoomsætning | B41: =IFERROR(B5/$D5*100,"") | C41: =IFERROR(C5/$D5*100,"") | D41: =IFERROR(D5/$D5*100,"")
A42: Vareforbrug | B42: =IFERROR(B7/$D7*100,"") | C42: =IFERROR(C7/$D7*100,"") | D42: =IFERROR(D7/$D7*100,"")
A43: Andre eksterne omk. | B43: =IFERROR(B8/$D8*100,"") | C43: =IFERROR(C8/$D8*100,"") | D43: =IFERROR(D8/$D8*100,"")
A44: Personaleomkostninger | B44: =IFERROR(B10/$D10*100,"") | C44: =IFERROR(C10/$D10*100,"") | D44: =IFERROR(D10/$D10*100,"")
A45: Af- og nedskrivninger | B45: =IFERROR(B11/$D11*100,"") | C45: =IFERROR(C11/$D11*100,"") | D45: =IFERROR(D11/$D11*100,"")
A47: Indekstal for kapitaltilpasningsevne (2022=100)
A48: Nettoomsætning | B48: =IFERROR(B5*100/$D5,"") | C48: =IFERROR(C5*100/$D5,"") | D48: =IFERROR(D5*100/$D5,"")
A49: Anlægsaktiver | B49: =IFERROR(B19*100/$D19,"") | C49: =IFERROR(C19*100/$D19,"") | D49: =IFERROR(D19*100/$D19,"")
A50: Varebeholdninger | B50: =IFERROR(B28*100/$D28,"") | C50: =IFERROR(C28*100/$D28,"") | D50: =IFERROR(D28*100/$D28,"")
A51: Tilgodehavender fra salg | B51: =IFERROR(B29*100/$D29,"") | C51: =IFERROR(C29*100/$D29,"") | D51: =IFERROR(D29*100/$D29,"")
A53: Soliditet og likviditet
A54: Soliditetsgrad, % | B54: =IFERROR(B23*100/B21,"") | C54: =IFERROR(C23*100/C21,"") | D54: =IFERROR(D23*100/D21,"")
A55: Gældsandel, % | B55: =IFERROR(B24*100/B21,"") | C55: =IFERROR(C24*100/C21,"") | D55: =IFERROR(D24*100/D21,"")
A56: Likviditetsgrad, % | B56: =IFERROR(B20*100/B30,"") | C56: =IFERROR(C20*100/C30,"") | D56: =IFERROR(D20*100/D30,"")
A58: Kilde: Bearbejdet uddrag af årsrapporter for 2022-2024. Alle dataceller er live formler der peger på res_raw / balance_raw.
A60: Krydstjek mod rådata (tolerance: 1 t.kr.)
A61: Aktiver i alt = fsa:Assets | B61: =IF('balance_raw_25652991'!$F$31="","—",IF(ABS(B21-'balance_raw_25652991'!$F$31)<=1,"✓ OK","❌ "&TEXT(B21-'balance_raw_25652991'!$F$31,"+#,##0;-#,##0")&" t.kr.")) | C61: =IF('balance_raw_25652991'!$E$31="","—",IF(ABS(C21-'balance_raw_25652991'!$E$31)<=1,"✓ OK","❌ "&TEXT(C21-'balance_raw_25652991'!$E$31,"+#,##0;-#,##0")&" t.kr.")) | D61: =IF('balance_raw_25652991'!$D$31="","—",IF(ABS(D21-'balance_raw_25652991'!$D$31)<=1,"✓ OK","❌ "&TEXT(D21-'balance_raw_25652991'!$D$31,"+#,##0;-#,##0")&" t.kr.")) | F61: Verificerer at sum(Anlæg+Omsætning) matcher Assets-totalen.
A62: Passiver i alt = fsa:LiabilitiesAndEquity | B62: =IF('balance_raw_25652991'!$F$58="","—",IF(ABS(B25-'balance_raw_25652991'!$F$58)<=1,"✓ OK","❌ "&TEXT(B25-'balance_raw_25652991'!$F$58,"+#,##0;-#,##0")&" t.kr.")) | C62: =IF('balance_raw_25652991'!$E$58="","—",IF(ABS(C25-'balance_raw_25652991'!$E$58)<=1,"✓ OK","❌ "&TEXT(C25-'balance_raw_25652991'!$E$58,"+#,##0;-#,##0")&" t.kr.")) | D62: =IF('balance_raw_25652991'!$D$58="","—",IF(ABS(D25-'balance_raw_25652991'!$D$58)<=1,"✓ OK","❌ "&TEXT(D25-'balance_raw_25652991'!$D$58,"+#,##0;-#,##0")&" t.kr.")) | F62: Verificerer at sum(EK+Forpligtelser) matcher Passiver-totalen.
A63: Aktiver i alt = Passiver i alt | B63: =IF(ABS(B21-B25)<=1,"✓ OK","❌ "&TEXT(B21-B25,"+#,##0;-#,##0")&" t.kr.") | C63: =IF(ABS(C21-C25)<=1,"✓ OK","❌ "&TEXT(C21-C25,"+#,##0;-#,##0")&" t.kr.") | D63: =IF(ABS(D21-D25)<=1,"✓ OK","❌ "&TEXT(D21-D25,"+#,##0;-#,##0")&" t.kr.") | F63: Balance-identitet på arket selv. Skal altid være 0 differance.
A64: Bruttoresultat (beregnet) = fsa:GrossResult | B64: =IF('res_raw_25652991'!$F$6="","—",IF(ABS(B9-'res_raw_25652991'!$F$6)<=1,"✓ OK","❌ "&TEXT(B9-'res_raw_25652991'!$F$6,"+#,##0;-#,##0")&" t.kr.")) | C64: =IF('res_raw_25652991'!$E$6="","—",IF(ABS(C9-'res_raw_25652991'!$E$6)<=1,"✓ OK","❌ "&TEXT(C9-'res_raw_25652991'!$E$6,"+#,##0;-#,##0")&" t.kr.")) | D64: =IF('res_raw_25652991'!$D$6="","—",IF(ABS(D9-'res_raw_25652991'!$D$6)<=1,"✓ OK","❌ "&TEXT(D9-'res_raw_25652991'!$D$6,"+#,##0;-#,##0")&" t.kr.")) | F64: Hvis Nettoomsætning eller omkostninger mangler, vil sumberegnet bruttoresultat afvige.
A65: EBIT (beregnet) = fsa:ProfitLossFromOrdinaryOperatingActivities | B65: =IF('res_raw_25652991'!$F$11="","—",IF(ABS(B13-'res_raw_25652991'!$F$11)<=1,"✓ OK","❌ "&TEXT(B13-'res_raw_25652991'!$F$11,"+#,##0;-#,##0")&" t.kr.")) | C65: =IF('res_raw_25652991'!$E$11="","—",IF(ABS(C13-'res_raw_25652991'!$E$11)<=1,"✓ OK","❌ "&TEXT(C13-'res_raw_25652991'!$E$11,"+#,##0;-#,##0")&" t.kr.")) | D65: =IF('res_raw_25652991'!$D$11="","—",IF(ABS(D13-'res_raw_25652991'!$D$11)<=1,"✓ OK","❌ "&TEXT(D13-'res_raw_25652991'!$D$11,"+#,##0;-#,##0")&" t.kr.")) | F65: Verificerer at sumberegnet EBIT matcher det rapporterede.
A66: EBT (beregnet) = fsa:ProfitLossFromOrdinaryActivitiesBeforeTax | B66: =IF('res_raw_25652991'!$F$16="","—",IF(ABS(B16-'res_raw_25652991'!$F$16)<=1,"✓ OK","❌ "&TEXT(B16-'res_raw_25652991'!$F$16,"+#,##0;-#,##0")&" t.kr.")) | C66: =IF('res_raw_25652991'!$E$16="","—",IF(ABS(C16-'res_raw_25652991'!$E$16)<=1,"✓ OK","❌ "&TEXT(C16-'res_raw_25652991'!$E$16,"+#,##0;-#,##0")&" t.kr.")) | D66: =IF('res_raw_25652991'!$D$16="","—",IF(ABS(D16-'res_raw_25652991'!$D$16)<=1,"✓ OK","❌ "&TEXT(D16-'res_raw_25652991'!$D$16,"+#,##0;-#,##0")&" t.kr.")) | F66: Verificerer at sumberegnet resultat før skat matcher det rapporterede.

Sheet Noter_info
A1: Ukendte XBRL-felter — disse er noter og ikke en del af hoved-regnskabet
A2: Kategori | B2: Dansk navn | C2: XBRL feltnavn | D2: 2020 t.kr. | E2: 2021 t.kr. | F2: 2022 t.kr. | G2: 2023 t.kr. | H2: 2024 t.kr. | I2: Forklaring
A3: Øvrige (ukendt) | B3: fsa:AmountOfIncomeCostItemsWhichAreSpecialDueToSizeAndNature | C3: fsa:AmountOfIncomeCostItemsWhichAreSpecialDueToSizeAndNature | E3: 120500 | F3: 0 | G3: -16766 | H3: 0 | I3: Ingen forklaring tilgængelig.
A4: Øvrige (ukendt) | B4: fsa:InterestExpenseToParticipatingInterests | C4: fsa:InterestExpenseToParticipatingInterests | E4: 3657 | F4: 3820 | G4: 5405 | H4: 7384 | I4: Ingen forklaring tilgængelig.
A5: Øvrige (ukendt) | B5: fsa:LongtermTradePayables | C5: fsa:LongtermTradePayables | H5: 16946 | I5: Ingen forklaring tilgængelig.
A6: Øvrige (ukendt) | B6: fsa:RefundInJointAssessment | C6: fsa:RefundInJointAssessment | F6: -508 | G6: 163 | H6: 0 | I6: Ingen forklaring tilgængelig.
