Workbook

Sheet Overblik_27908470
A1: Refsvindinge Bryggeri ApS (CVR 27908470) — Regnskabsanalyse – Resultatopgørelse & Balance (t.kr.) · Klasse B · Udvidet gennemgang · Regnskabsår 1/7–30/6 (forskudt)
H2: Indekstal (2021=100)
A3: Resultatopgørelse t.kr. | B3: 2021 | C3: 2022 | D3: 2023 | E3: 2024 | F3: 2025 | H3: 2021 | I3: 2022 | J3: 2023 | K3: 2024 | L3: 2025
A4: Nettoomsætning | B4: ='res_raw_27908470'!$B$2 | C4: ='res_raw_27908470'!$C$2 | D4: ='res_raw_27908470'!$D$2 | E4: ='res_raw_27908470'!$E$2 | F4: ='res_raw_27908470'!$F$2 | H4: =IFERROR(B4/$B$4*100,"") | I4: =IFERROR(C4/$B$4*100,"") | J4: =IFERROR(D4/$B$4*100,"") | K4: =IFERROR(E4/$B$4*100,"") | L4: =IFERROR(F4/$B$4*100,"")
A5: Andre driftsindtægter | B5: ='res_raw_27908470'!$B$3 | C5: ='res_raw_27908470'!$C$3 | D5: ='res_raw_27908470'!$D$3 | E5: ='res_raw_27908470'!$E$3 | F5: ='res_raw_27908470'!$F$3 | H5: =IFERROR(B5/$B$5*100,"") | I5: =IFERROR(C5/$B$5*100,"") | J5: =IFERROR(D5/$B$5*100,"") | K5: =IFERROR(E5/$B$5*100,"") | L5: =IFERROR(F5/$B$5*100,"")
A6: Vareforbrug | B6: ='res_raw_27908470'!$B$4 | C6: ='res_raw_27908470'!$C$4 | D6: ='res_raw_27908470'!$D$4 | E6: ='res_raw_27908470'!$E$4 | F6: ='res_raw_27908470'!$F$4 | H6: =IFERROR(B6/$B$6*100,"") | I6: =IFERROR(C6/$B$6*100,"") | J6: =IFERROR(D6/$B$6*100,"") | K6: =IFERROR(E6/$B$6*100,"") | L6: =IFERROR(F6/$B$6*100,"")
A7: Andre eksterne omkostninger | B7: ='res_raw_27908470'!$B$5 | C7: ='res_raw_27908470'!$C$5 | D7: ='res_raw_27908470'!$D$5 | E7: ='res_raw_27908470'!$E$5 | F7: ='res_raw_27908470'!$F$5 | H7: =IFERROR(B7/$B$7*100,"") | I7: =IFERROR(C7/$B$7*100,"") | J7: =IFERROR(D7/$B$7*100,"") | K7: =IFERROR(E7/$B$7*100,"") | L7: =IFERROR(F7/$B$7*100,"")
A8: Bruttoresultat | B8: ='res_raw_27908470'!$B$6 | C8: ='res_raw_27908470'!$C$6 | D8: ='res_raw_27908470'!$D$6 | E8: ='res_raw_27908470'!$E$6 | F8: ='res_raw_27908470'!$F$6 | H8: =IFERROR(B8/$B$8*100,"") | I8: =IFERROR(C8/$B$8*100,"") | J8: =IFERROR(D8/$B$8*100,"") | K8: =IFERROR(E8/$B$8*100,"") | L8: =IFERROR(F8/$B$8*100,"")
A9: Personaleomkostninger | B9: ='res_raw_27908470'!$B$7 | C9: ='res_raw_27908470'!$C$7 | D9: ='res_raw_27908470'!$D$7 | E9: ='res_raw_27908470'!$E$7 | F9: ='res_raw_27908470'!$F$7 | H9: =IFERROR(B9/$B$9*100,"") | I9: =IFERROR(C9/$B$9*100,"") | J9: =IFERROR(D9/$B$9*100,"") | K9: =IFERROR(E9/$B$9*100,"") | L9: =IFERROR(F9/$B$9*100,"")
A10: Resultat før afskrivninger | B10: =IFERROR($B$8-ABS($B$9),"") | C10: =IFERROR($C$8-ABS($C$9),"") | D10: =IFERROR($D$8-ABS($D$9),"") | E10: =IFERROR($E$8-ABS($E$9),"") | F10: =IFERROR($F$8-ABS($F$9),"") | H10: =IFERROR(B10/$B$10*100,"") | I10: =IFERROR(C10/$B$10*100,"") | J10: =IFERROR(D10/$B$10*100,"") | K10: =IFERROR(E10/$B$10*100,"") | L10: =IFERROR(F10/$B$10*100,"")
A11: Af- og nedskrivninger | B11: ='res_raw_27908470'!$B$9 | C11: ='res_raw_27908470'!$C$9 | D11: ='res_raw_27908470'!$D$9 | E11: ='res_raw_27908470'!$E$9 | F11: ='res_raw_27908470'!$F$9 | H11: =IFERROR(B11/$B$11*100,"") | I11: =IFERROR(C11/$B$11*100,"") | J11: =IFERROR(D11/$B$11*100,"") | K11: =IFERROR(E11/$B$11*100,"") | L11: =IFERROR(F11/$B$11*100,"")
A12: Andre driftsomkostninger | B12: ='res_raw_27908470'!$B$10 | C12: ='res_raw_27908470'!$C$10 | D12: ='res_raw_27908470'!$D$10 | E12: ='res_raw_27908470'!$E$10 | F12: ='res_raw_27908470'!$F$10 | H12: =IFERROR(B12/$B$12*100,"") | I12: =IFERROR(C12/$B$12*100,"") | J12: =IFERROR(D12/$B$12*100,"") | K12: =IFERROR(E12/$B$12*100,"") | L12: =IFERROR(F12/$B$12*100,"")
A13: Resultat af primær drift | B13: ='res_raw_27908470'!$B$11 | C13: ='res_raw_27908470'!$C$11 | D13: ='res_raw_27908470'!$D$11 | E13: ='res_raw_27908470'!$E$11 | F13: ='res_raw_27908470'!$F$11 | H13: =IFERROR(B13/$B$13*100,"") | I13: =IFERROR(C13/$B$13*100,"") | J13: =IFERROR(D13/$B$13*100,"") | K13: =IFERROR(E13/$B$13*100,"") | L13: =IFERROR(F13/$B$13*100,"")
A14: Indtægter af kapitalandele, dattervirksomheder | B14: ='res_raw_27908470'!$B$12 | C14: ='res_raw_27908470'!$C$12 | D14: ='res_raw_27908470'!$D$12 | E14: ='res_raw_27908470'!$E$12 | F14: ='res_raw_27908470'!$F$12 | H14: =IFERROR(B14/$B$14*100,"") | I14: =IFERROR(C14/$B$14*100,"") | J14: =IFERROR(D14/$B$14*100,"") | K14: =IFERROR(E14/$B$14*100,"") | L14: =IFERROR(F14/$B$14*100,"")
A15: Finansielle indtægter | B15: ='res_raw_27908470'!$B$13 | C15: ='res_raw_27908470'!$C$13 | D15: ='res_raw_27908470'!$D$13 | E15: ='res_raw_27908470'!$E$13 | F15: ='res_raw_27908470'!$F$13 | H15: =IFERROR(B15/$B$15*100,"") | I15: =IFERROR(C15/$B$15*100,"") | J15: =IFERROR(D15/$B$15*100,"") | K15: =IFERROR(E15/$B$15*100,"") | L15: =IFERROR(F15/$B$15*100,"")
A16: Finansielle omkostninger | B16: ='res_raw_27908470'!$B$14 | C16: ='res_raw_27908470'!$C$14 | D16: ='res_raw_27908470'!$D$14 | E16: ='res_raw_27908470'!$E$14 | F16: ='res_raw_27908470'!$F$14 | H16: =IFERROR(B16/$B$16*100,"") | I16: =IFERROR(C16/$B$16*100,"") | J16: =IFERROR(D16/$B$16*100,"") | K16: =IFERROR(E16/$B$16*100,"") | L16: =IFERROR(F16/$B$16*100,"")
A17: Finansielle poster, netto | B17: ='res_raw_27908470'!$B$15 | C17: ='res_raw_27908470'!$C$15 | D17: ='res_raw_27908470'!$D$15 | E17: ='res_raw_27908470'!$E$15 | F17: ='res_raw_27908470'!$F$15 | H17: =IFERROR(B17/$B$17*100,"") | I17: =IFERROR(C17/$B$17*100,"") | J17: =IFERROR(D17/$B$17*100,"") | K17: =IFERROR(E17/$B$17*100,"") | L17: =IFERROR(F17/$B$17*100,"")
A18: Resultat før skat | B18: ='res_raw_27908470'!$B$16 | C18: ='res_raw_27908470'!$C$16 | D18: ='res_raw_27908470'!$D$16 | E18: ='res_raw_27908470'!$E$16 | F18: ='res_raw_27908470'!$F$16 | H18: =IFERROR(B18/$B$18*100,"") | I18: =IFERROR(C18/$B$18*100,"") | J18: =IFERROR(D18/$B$18*100,"") | K18: =IFERROR(E18/$B$18*100,"") | L18: =IFERROR(F18/$B$18*100,"")
A19: Skat af årets resultat | B19: ='res_raw_27908470'!$B$17 | C19: ='res_raw_27908470'!$C$17 | D19: ='res_raw_27908470'!$D$17 | E19: ='res_raw_27908470'!$E$17 | F19: ='res_raw_27908470'!$F$17 | H19: =IFERROR(B19/$B$19*100,"") | I19: =IFERROR(C19/$B$19*100,"") | J19: =IFERROR(D19/$B$19*100,"") | K19: =IFERROR(E19/$B$19*100,"") | L19: =IFERROR(F19/$B$19*100,"")
A20: Årets resultat | B20: ='res_raw_27908470'!$B$18 | C20: ='res_raw_27908470'!$C$18 | D20: ='res_raw_27908470'!$D$18 | E20: ='res_raw_27908470'!$E$18 | F20: ='res_raw_27908470'!$F$18 | H20: =IFERROR(B20/$B$20*100,"") | I20: =IFERROR(C20/$B$20*100,"") | J20: =IFERROR(D20/$B$20*100,"") | K20: =IFERROR(E20/$B$20*100,"") | L20: =IFERROR(F20/$B$20*100,"")
A22: AKTIVER t.kr. | B22: 2021 | C22: 2022 | D22: 2023 | E22: 2024 | F22: 2025 | H22: 2021 | I22: 2022 | J22: 2023 | K22: 2024 | L22: 2025
A23: Grunde og bygninger | B23: ='balance_raw_27908470'!$B$2 | C23: ='balance_raw_27908470'!$C$2 | D23: ='balance_raw_27908470'!$D$2 | E23: ='balance_raw_27908470'!$E$2 | F23: ='balance_raw_27908470'!$F$2 | H23: =IFERROR(B23/$B$23*100,"") | I23: =IFERROR(C23/$B$23*100,"") | J23: =IFERROR(D23/$B$23*100,"") | K23: =IFERROR(E23/$B$23*100,"") | L23: =IFERROR(F23/$B$23*100,"")
A24: Produktionsanlæg og maskiner | B24: ='balance_raw_27908470'!$B$3 | C24: ='balance_raw_27908470'!$C$3 | D24: ='balance_raw_27908470'!$D$3 | E24: ='balance_raw_27908470'!$E$3 | F24: ='balance_raw_27908470'!$F$3 | H24: =IFERROR(B24/$B$24*100,"") | I24: =IFERROR(C24/$B$24*100,"") | J24: =IFERROR(D24/$B$24*100,"") | K24: =IFERROR(E24/$B$24*100,"") | L24: =IFERROR(F24/$B$24*100,"")
A25: Driftsmateriel og inventar | B25: ='balance_raw_27908470'!$B$4 | C25: ='balance_raw_27908470'!$C$4 | D25: ='balance_raw_27908470'!$D$4 | E25: ='balance_raw_27908470'!$E$4 | F25: ='balance_raw_27908470'!$F$4 | H25: =IFERROR(B25/$B$25*100,"") | I25: =IFERROR(C25/$B$25*100,"") | J25: =IFERROR(D25/$B$25*100,"") | K25: =IFERROR(E25/$B$25*100,"") | L25: =IFERROR(F25/$B$25*100,"")
A26: Indretning af lejede lokaler | B26: ='balance_raw_27908470'!$B$5 | C26: ='balance_raw_27908470'!$C$5 | D26: ='balance_raw_27908470'!$D$5 | E26: ='balance_raw_27908470'!$E$5 | F26: ='balance_raw_27908470'!$F$5 | H26: =IFERROR(B26/$B$26*100,"") | I26: =IFERROR(C26/$B$26*100,"") | J26: =IFERROR(D26/$B$26*100,"") | K26: =IFERROR(E26/$B$26*100,"") | L26: =IFERROR(F26/$B$26*100,"")
A27: Forudbetaling og anlægsaktiver under opførelse | B27: ='balance_raw_27908470'!$B$6 | C27: ='balance_raw_27908470'!$C$6 | D27: ='balance_raw_27908470'!$D$6 | E27: ='balance_raw_27908470'!$E$6 | F27: ='balance_raw_27908470'!$F$6 | H27: =IFERROR(B27/$B$27*100,"") | I27: =IFERROR(C27/$B$27*100,"") | J27: =IFERROR(D27/$B$27*100,"") | K27: =IFERROR(E27/$B$27*100,"") | L27: =IFERROR(F27/$B$27*100,"")
A28: Materielle anlægsaktiver | B28: ='balance_raw_27908470'!$B$7 | C28: ='balance_raw_27908470'!$C$7 | D28: ='balance_raw_27908470'!$D$7 | E28: ='balance_raw_27908470'!$E$7 | F28: ='balance_raw_27908470'!$F$7 | H28: =IFERROR(B28/$B$28*100,"") | I28: =IFERROR(C28/$B$28*100,"") | J28: =IFERROR(D28/$B$28*100,"") | K28: =IFERROR(E28/$B$28*100,"") | L28: =IFERROR(F28/$B$28*100,"")
A29: Kapitalandele, dattervirksomheder | B29: ='balance_raw_27908470'!$B$8 | C29: ='balance_raw_27908470'!$C$8 | D29: ='balance_raw_27908470'!$D$8 | E29: ='balance_raw_27908470'!$E$8 | F29: ='balance_raw_27908470'!$F$8 | H29: =IFERROR(B29/$B$29*100,"") | I29: =IFERROR(C29/$B$29*100,"") | J29: =IFERROR(D29/$B$29*100,"") | K29: =IFERROR(E29/$B$29*100,"") | L29: =IFERROR(F29/$B$29*100,"")
A30: Deposita | B30: ='balance_raw_27908470'!$B$9 | C30: ='balance_raw_27908470'!$C$9 | D30: ='balance_raw_27908470'!$D$9 | E30: ='balance_raw_27908470'!$E$9 | F30: ='balance_raw_27908470'!$F$9 | H30: =IFERROR(B30/$B$30*100,"") | I30: =IFERROR(C30/$B$30*100,"") | J30: =IFERROR(D30/$B$30*100,"") | K30: =IFERROR(E30/$B$30*100,"") | L30: =IFERROR(F30/$B$30*100,"")
A31: Finansielle anlægsaktiver | B31: ='balance_raw_27908470'!$B$10 | C31: ='balance_raw_27908470'!$C$10 | D31: ='balance_raw_27908470'!$D$10 | E31: ='balance_raw_27908470'!$E$10 | F31: ='balance_raw_27908470'!$F$10 | H31: =IFERROR(B31/$B$31*100,"") | I31: =IFERROR(C31/$B$31*100,"") | J31: =IFERROR(D31/$B$31*100,"") | K31: =IFERROR(E31/$B$31*100,"") | L31: =IFERROR(F31/$B$31*100,"")
A32: Anlægsaktiver | B32: ='balance_raw_27908470'!$B$11 | C32: ='balance_raw_27908470'!$C$11 | D32: ='balance_raw_27908470'!$D$11 | E32: ='balance_raw_27908470'!$E$11 | F32: ='balance_raw_27908470'!$F$11 | H32: =IFERROR(B32/$B$32*100,"") | I32: =IFERROR(C32/$B$32*100,"") | J32: =IFERROR(D32/$B$32*100,"") | K32: =IFERROR(E32/$B$32*100,"") | L32: =IFERROR(F32/$B$32*100,"")
A33: Råvarer og hjælpematerialer | B33: ='balance_raw_27908470'!$B$12 | C33: ='balance_raw_27908470'!$C$12 | D33: ='balance_raw_27908470'!$D$12 | E33: ='balance_raw_27908470'!$E$12 | F33: ='balance_raw_27908470'!$F$12 | H33: =IFERROR(B33/$B$33*100,"") | I33: =IFERROR(C33/$B$33*100,"") | J33: =IFERROR(D33/$B$33*100,"") | K33: =IFERROR(E33/$B$33*100,"") | L33: =IFERROR(F33/$B$33*100,"")
A34: Varer under fremstilling | B34: ='balance_raw_27908470'!$B$13 | C34: ='balance_raw_27908470'!$C$13 | D34: ='balance_raw_27908470'!$D$13 | E34: ='balance_raw_27908470'!$E$13 | F34: ='balance_raw_27908470'!$F$13 | H34: =IFERROR(B34/$B$34*100,"") | I34: =IFERROR(C34/$B$34*100,"") | J34: =IFERROR(D34/$B$34*100,"") | K34: =IFERROR(E34/$B$34*100,"") | L34: =IFERROR(F34/$B$34*100,"")
A35: Færdigvarer og handelsvarer | B35: ='balance_raw_27908470'!$B$14 | C35: ='balance_raw_27908470'!$C$14 | D35: ='balance_raw_27908470'!$D$14 | E35: ='balance_raw_27908470'!$E$14 | F35: ='balance_raw_27908470'!$F$14 | H35: =IFERROR(B35/$B$35*100,"") | I35: =IFERROR(C35/$B$35*100,"") | J35: =IFERROR(D35/$B$35*100,"") | K35: =IFERROR(E35/$B$35*100,"") | L35: =IFERROR(F35/$B$35*100,"")
A36: Varebeholdninger | B36: ='balance_raw_27908470'!$B$15 | C36: ='balance_raw_27908470'!$C$15 | D36: ='balance_raw_27908470'!$D$15 | E36: ='balance_raw_27908470'!$E$15 | F36: ='balance_raw_27908470'!$F$15 | H36: =IFERROR(B36/$B$36*100,"") | I36: =IFERROR(C36/$B$36*100,"") | J36: =IFERROR(D36/$B$36*100,"") | K36: =IFERROR(E36/$B$36*100,"") | L36: =IFERROR(F36/$B$36*100,"")
A37: Tilgodehavender fra salg og tjenesteydelser | B37: ='balance_raw_27908470'!$B$16 | C37: ='balance_raw_27908470'!$C$16 | D37: ='balance_raw_27908470'!$D$16 | E37: ='balance_raw_27908470'!$E$16 | F37: ='balance_raw_27908470'!$F$16 | H37: =IFERROR(B37/$B$37*100,"") | I37: =IFERROR(C37/$B$37*100,"") | J37: =IFERROR(D37/$B$37*100,"") | K37: =IFERROR(E37/$B$37*100,"") | L37: =IFERROR(F37/$B$37*100,"")
A38: Tilgodehavender hos tilknyttede virksomheder | B38: ='balance_raw_27908470'!$B$17 | C38: ='balance_raw_27908470'!$C$17 | D38: ='balance_raw_27908470'!$D$17 | E38: ='balance_raw_27908470'!$E$17 | F38: ='balance_raw_27908470'!$F$17 | H38: =IFERROR(B38/$B$38*100,"") | I38: =IFERROR(C38/$B$38*100,"") | J38: =IFERROR(D38/$B$38*100,"") | K38: =IFERROR(E38/$B$38*100,"") | L38: =IFERROR(F38/$B$38*100,"")
A39: Andre tilgodehavender | B39: ='balance_raw_27908470'!$B$18 | C39: ='balance_raw_27908470'!$C$18 | D39: ='balance_raw_27908470'!$D$18 | E39: ='balance_raw_27908470'!$E$18 | F39: ='balance_raw_27908470'!$F$18 | H39: =IFERROR(B39/$B$39*100,"") | I39: =IFERROR(C39/$B$39*100,"") | J39: =IFERROR(D39/$B$39*100,"") | K39: =IFERROR(E39/$B$39*100,"") | L39: =IFERROR(F39/$B$39*100,"")
A40: Periodeafgrænsningsposter (aktiver) | B40: ='balance_raw_27908470'!$B$19 | C40: ='balance_raw_27908470'!$C$19 | D40: ='balance_raw_27908470'!$D$19 | E40: ='balance_raw_27908470'!$E$19 | F40: ='balance_raw_27908470'!$F$19 | H40: =IFERROR(B40/$B$40*100,"") | I40: =IFERROR(C40/$B$40*100,"") | J40: =IFERROR(D40/$B$40*100,"") | K40: =IFERROR(E40/$B$40*100,"") | L40: =IFERROR(F40/$B$40*100,"")
A41: Udskudt skatteaktiv | B41: ='balance_raw_27908470'!$B$20 | C41: ='balance_raw_27908470'!$C$20 | D41: ='balance_raw_27908470'!$D$20 | E41: ='balance_raw_27908470'!$E$20 | F41: ='balance_raw_27908470'!$F$20 | H41: =IFERROR(B41/$B$41*100,"") | I41: =IFERROR(C41/$B$41*100,"") | J41: =IFERROR(D41/$B$41*100,"") | K41: =IFERROR(E41/$B$41*100,"") | L41: =IFERROR(F41/$B$41*100,"")
A42: Tilgodehavende skat hos tilknyttede virksomheder | B42: ='balance_raw_27908470'!$B$21 | C42: ='balance_raw_27908470'!$C$21 | D42: ='balance_raw_27908470'!$D$21 | E42: ='balance_raw_27908470'!$E$21 | F42: ='balance_raw_27908470'!$F$21 | H42: =IFERROR(B42/$B$42*100,"") | I42: =IFERROR(C42/$B$42*100,"") | J42: =IFERROR(D42/$B$42*100,"") | K42: =IFERROR(E42/$B$42*100,"") | L42: =IFERROR(F42/$B$42*100,"")
A43: Kortfristede skattetilgodehavender | B43: ='balance_raw_27908470'!$B$22 | C43: ='balance_raw_27908470'!$C$22 | D43: ='balance_raw_27908470'!$D$22 | E43: ='balance_raw_27908470'!$E$22 | F43: ='balance_raw_27908470'!$F$22 | H43: =IFERROR(B43/$B$43*100,"") | I43: =IFERROR(C43/$B$43*100,"") | J43: =IFERROR(D43/$B$43*100,"") | K43: =IFERROR(E43/$B$43*100,"") | L43: =IFERROR(F43/$B$43*100,"")
A44: Tilgodehavender | B44: ='balance_raw_27908470'!$B$23 | C44: ='balance_raw_27908470'!$C$23 | D44: ='balance_raw_27908470'!$D$23 | E44: ='balance_raw_27908470'!$E$23 | F44: ='balance_raw_27908470'!$F$23 | H44: =IFERROR(B44/$B$44*100,"") | I44: =IFERROR(C44/$B$44*100,"") | J44: =IFERROR(D44/$B$44*100,"") | K44: =IFERROR(E44/$B$44*100,"") | L44: =IFERROR(F44/$B$44*100,"")
A45: Værdipapirer | B45: ='balance_raw_27908470'!$B$24 | C45: ='balance_raw_27908470'!$C$24 | D45: ='balance_raw_27908470'!$D$24 | E45: ='balance_raw_27908470'!$E$24 | F45: ='balance_raw_27908470'!$F$24 | H45: =IFERROR(B45/$B$45*100,"") | I45: =IFERROR(C45/$B$45*100,"") | J45: =IFERROR(D45/$B$45*100,"") | K45: =IFERROR(E45/$B$45*100,"") | L45: =IFERROR(F45/$B$45*100,"")
A46: Likvide beholdninger | B46: ='balance_raw_27908470'!$B$25 | C46: ='balance_raw_27908470'!$C$25 | D46: ='balance_raw_27908470'!$D$25 | E46: ='balance_raw_27908470'!$E$25 | F46: ='balance_raw_27908470'!$F$25 | H46: =IFERROR(B46/$B$46*100,"") | I46: =IFERROR(C46/$B$46*100,"") | J46: =IFERROR(D46/$B$46*100,"") | K46: =IFERROR(E46/$B$46*100,"") | L46: =IFERROR(F46/$B$46*100,"")
A47: Omsætningsaktiver | B47: ='balance_raw_27908470'!$B$26 | C47: ='balance_raw_27908470'!$C$26 | D47: ='balance_raw_27908470'!$D$26 | E47: ='balance_raw_27908470'!$E$26 | F47: ='balance_raw_27908470'!$F$26 | H47: =IFERROR(B47/$B$47*100,"") | I47: =IFERROR(C47/$B$47*100,"") | J47: =IFERROR(D47/$B$47*100,"") | K47: =IFERROR(E47/$B$47*100,"") | L47: =IFERROR(F47/$B$47*100,"")
A48: Aktiver | B48: ='balance_raw_27908470'!$B$27 | C48: ='balance_raw_27908470'!$C$27 | D48: ='balance_raw_27908470'!$D$27 | E48: ='balance_raw_27908470'!$E$27 | F48: ='balance_raw_27908470'!$F$27 | H48: =IFERROR(B48/$B$48*100,"") | I48: =IFERROR(C48/$B$48*100,"") | J48: =IFERROR(D48/$B$48*100,"") | K48: =IFERROR(E48/$B$48*100,"") | L48: =IFERROR(F48/$B$48*100,"")
A50: PASSIVER t.kr. | B50: 2021 | C50: 2022 | D50: 2023 | E50: 2024 | F50: 2025 | H50: 2021 | I50: 2022 | J50: 2023 | K50: 2024 | L50: 2025
A51: Selskabskapital | B51: ='balance_raw_27908470'!$B$28 | C51: ='balance_raw_27908470'!$C$28 | D51: ='balance_raw_27908470'!$D$28 | E51: ='balance_raw_27908470'!$E$28 | F51: ='balance_raw_27908470'!$F$28 | H51: =IFERROR(B51/$B$51*100,"") | I51: =IFERROR(C51/$B$51*100,"") | J51: =IFERROR(D51/$B$51*100,"") | K51: =IFERROR(E51/$B$51*100,"") | L51: =IFERROR(F51/$B$51*100,"")
A52: Reserve for nettoopskrivning (indre værdis metode) | B52: ='balance_raw_27908470'!$B$29 | C52: ='balance_raw_27908470'!$C$29 | D52: ='balance_raw_27908470'!$D$29 | E52: ='balance_raw_27908470'!$E$29 | F52: ='balance_raw_27908470'!$F$29 | H52: =IFERROR(B52/$B$52*100,"") | I52: =IFERROR(C52/$B$52*100,"") | J52: =IFERROR(D52/$B$52*100,"") | K52: =IFERROR(E52/$B$52*100,"") | L52: =IFERROR(F52/$B$52*100,"")
A53: Reserve for udviklingsomkostninger | B53: ='balance_raw_27908470'!$B$30 | C53: ='balance_raw_27908470'!$C$30 | D53: ='balance_raw_27908470'!$D$30 | E53: ='balance_raw_27908470'!$E$30 | F53: ='balance_raw_27908470'!$F$30 | H53: =IFERROR(B53/$B$53*100,"") | I53: =IFERROR(C53/$B$53*100,"") | J53: =IFERROR(D53/$B$53*100,"") | K53: =IFERROR(E53/$B$53*100,"") | L53: =IFERROR(F53/$B$53*100,"")
A54: Reserve for sikringstransaktioner | B54: ='balance_raw_27908470'!$B$31 | C54: ='balance_raw_27908470'!$C$31 | D54: ='balance_raw_27908470'!$D$31 | E54: ='balance_raw_27908470'!$E$31 | F54: ='balance_raw_27908470'!$F$31 | H54: =IFERROR(B54/$B$54*100,"") | I54: =IFERROR(C54/$B$54*100,"") | J54: =IFERROR(D54/$B$54*100,"") | K54: =IFERROR(E54/$B$54*100,"") | L54: =IFERROR(F54/$B$54*100,"")
A55: Andre reserver | B55: ='balance_raw_27908470'!$B$32 | C55: ='balance_raw_27908470'!$C$32 | D55: ='balance_raw_27908470'!$D$32 | E55: ='balance_raw_27908470'!$E$32 | F55: ='balance_raw_27908470'!$F$32 | H55: =IFERROR(B55/$B$55*100,"") | I55: =IFERROR(C55/$B$55*100,"") | J55: =IFERROR(D55/$B$55*100,"") | K55: =IFERROR(E55/$B$55*100,"") | L55: =IFERROR(F55/$B$55*100,"")
A56: Overført resultat | B56: ='balance_raw_27908470'!$B$33 | C56: ='balance_raw_27908470'!$C$33 | D56: ='balance_raw_27908470'!$D$33 | E56: ='balance_raw_27908470'!$E$33 | F56: ='balance_raw_27908470'!$F$33 | H56: =IFERROR(B56/$B$56*100,"") | I56: =IFERROR(C56/$B$56*100,"") | J56: =IFERROR(D56/$B$56*100,"") | K56: =IFERROR(E56/$B$56*100,"") | L56: =IFERROR(F56/$B$56*100,"")
A57: Egenkapital i alt | B57: ='balance_raw_27908470'!$B$34 | C57: ='balance_raw_27908470'!$C$34 | D57: ='balance_raw_27908470'!$D$34 | E57: ='balance_raw_27908470'!$E$34 | F57: ='balance_raw_27908470'!$F$34 | H57: =IFERROR(B57/$B$57*100,"") | I57: =IFERROR(C57/$B$57*100,"") | J57: =IFERROR(D57/$B$57*100,"") | K57: =IFERROR(E57/$B$57*100,"") | L57: =IFERROR(F57/$B$57*100,"")
A58: Langfristede gældsforpligtelser | B58: ='balance_raw_27908470'!$B$35 | C58: ='balance_raw_27908470'!$C$35 | D58: ='balance_raw_27908470'!$D$35 | E58: ='balance_raw_27908470'!$E$35 | F58: ='balance_raw_27908470'!$F$35 | H58: =IFERROR(B58/$B$58*100,"") | I58: =IFERROR(C58/$B$58*100,"") | J58: =IFERROR(D58/$B$58*100,"") | K58: =IFERROR(E58/$B$58*100,"") | L58: =IFERROR(F58/$B$58*100,"")
A59: Ansvarlig lånekapital (kortfristet) | B59: ='balance_raw_27908470'!$B$36 | C59: ='balance_raw_27908470'!$C$36 | D59: ='balance_raw_27908470'!$D$36 | E59: ='balance_raw_27908470'!$E$36 | F59: ='balance_raw_27908470'!$F$36 | H59: =IFERROR(B59/$B$59*100,"") | I59: =IFERROR(C59/$B$59*100,"") | J59: =IFERROR(D59/$B$59*100,"") | K59: =IFERROR(E59/$B$59*100,"") | L59: =IFERROR(F59/$B$59*100,"")
A60: Kortfristet del af langfristede gældsforpligtelser | B60: ='balance_raw_27908470'!$B$37 | C60: ='balance_raw_27908470'!$C$37 | D60: ='balance_raw_27908470'!$D$37 | E60: ='balance_raw_27908470'!$E$37 | F60: ='balance_raw_27908470'!$F$37 | H60: =IFERROR(B60/$B$60*100,"") | I60: =IFERROR(C60/$B$60*100,"") | J60: =IFERROR(D60/$B$60*100,"") | K60: =IFERROR(E60/$B$60*100,"") | L60: =IFERROR(F60/$B$60*100,"")
A61: Kreditinstitutter | B61: ='balance_raw_27908470'!$B$38 | C61: ='balance_raw_27908470'!$C$38 | D61: ='balance_raw_27908470'!$D$38 | E61: ='balance_raw_27908470'!$E$38 | F61: ='balance_raw_27908470'!$F$38 | H61: =IFERROR(B61/$B$61*100,"") | I61: =IFERROR(C61/$B$61*100,"") | J61: =IFERROR(D61/$B$61*100,"") | K61: =IFERROR(E61/$B$61*100,"") | L61: =IFERROR(F61/$B$61*100,"")
A62: Leasingforpligtelser (kortfristet) | B62: ='balance_raw_27908470'!$B$39 | C62: ='balance_raw_27908470'!$C$39 | D62: ='balance_raw_27908470'!$D$39 | E62: ='balance_raw_27908470'!$E$39 | F62: ='balance_raw_27908470'!$F$39 | H62: =IFERROR(B62/$B$62*100,"") | I62: =IFERROR(C62/$B$62*100,"") | J62: =IFERROR(D62/$B$62*100,"") | K62: =IFERROR(E62/$B$62*100,"") | L62: =IFERROR(F62/$B$62*100,"")
A63: Leverandører af varer og tjenesteydelser | B63: ='balance_raw_27908470'!$B$40 | C63: ='balance_raw_27908470'!$C$40 | D63: ='balance_raw_27908470'!$D$40 | E63: ='balance_raw_27908470'!$E$40 | F63: ='balance_raw_27908470'!$F$40 | H63: =IFERROR(B63/$B$63*100,"") | I63: =IFERROR(C63/$B$63*100,"") | J63: =IFERROR(D63/$B$63*100,"") | K63: =IFERROR(E63/$B$63*100,"") | L63: =IFERROR(F63/$B$63*100,"")
A64: Gæld til tilknyttede virksomheder | B64: ='balance_raw_27908470'!$B$41 | C64: ='balance_raw_27908470'!$C$41 | D64: ='balance_raw_27908470'!$D$41 | E64: ='balance_raw_27908470'!$E$41 | F64: ='balance_raw_27908470'!$F$41 | H64: =IFERROR(B64/$B$64*100,"") | I64: =IFERROR(C64/$B$64*100,"") | J64: =IFERROR(D64/$B$64*100,"") | K64: =IFERROR(E64/$B$64*100,"") | L64: =IFERROR(F64/$B$64*100,"")
A65: Gæld til selskabsdeltagere og ledelse | B65: ='balance_raw_27908470'!$B$42 | C65: ='balance_raw_27908470'!$C$42 | D65: ='balance_raw_27908470'!$D$42 | E65: ='balance_raw_27908470'!$E$42 | F65: ='balance_raw_27908470'!$F$42 | H65: =IFERROR(B65/$B$65*100,"") | I65: =IFERROR(C65/$B$65*100,"") | J65: =IFERROR(D65/$B$65*100,"") | K65: =IFERROR(E65/$B$65*100,"") | L65: =IFERROR(F65/$B$65*100,"")
A66: Selskabsskat | B66: ='balance_raw_27908470'!$B$43 | C66: ='balance_raw_27908470'!$C$43 | D66: ='balance_raw_27908470'!$D$43 | E66: ='balance_raw_27908470'!$E$43 | F66: ='balance_raw_27908470'!$F$43 | H66: =IFERROR(B66/$B$66*100,"") | I66: =IFERROR(C66/$B$66*100,"") | J66: =IFERROR(D66/$B$66*100,"") | K66: =IFERROR(E66/$B$66*100,"") | L66: =IFERROR(F66/$B$66*100,"")
A67: Gæld til tilknyttede virksomheder vedr. selskabsskat | B67: ='balance_raw_27908470'!$B$44 | C67: ='balance_raw_27908470'!$C$44 | D67: ='balance_raw_27908470'!$D$44 | E67: ='balance_raw_27908470'!$E$44 | F67: ='balance_raw_27908470'!$F$44 | H67: =IFERROR(B67/$B$67*100,"") | I67: =IFERROR(C67/$B$67*100,"") | J67: =IFERROR(D67/$B$67*100,"") | K67: =IFERROR(E67/$B$67*100,"") | L67: =IFERROR(F67/$B$67*100,"")
A68: Anden gæld (kortfristet) | B68: ='balance_raw_27908470'!$B$45 | C68: ='balance_raw_27908470'!$C$45 | D68: ='balance_raw_27908470'!$D$45 | E68: ='balance_raw_27908470'!$E$45 | F68: ='balance_raw_27908470'!$F$45 | H68: =IFERROR(B68/$B$68*100,"") | I68: =IFERROR(C68/$B$68*100,"") | J68: =IFERROR(D68/$B$68*100,"") | K68: =IFERROR(E68/$B$68*100,"") | L68: =IFERROR(F68/$B$68*100,"")
A69: Periodeafgrænsningsposter (passiver) | B69: ='balance_raw_27908470'!$B$46 | C69: ='balance_raw_27908470'!$C$46 | D69: ='balance_raw_27908470'!$D$46 | E69: ='balance_raw_27908470'!$E$46 | F69: ='balance_raw_27908470'!$F$46 | H69: =IFERROR(B69/$B$69*100,"") | I69: =IFERROR(C69/$B$69*100,"") | J69: =IFERROR(D69/$B$69*100,"") | K69: =IFERROR(E69/$B$69*100,"") | L69: =IFERROR(F69/$B$69*100,"")
A70: Kortfristede gældsforpligtelser | B70: ='balance_raw_27908470'!$B$47 | C70: ='balance_raw_27908470'!$C$47 | D70: ='balance_raw_27908470'!$D$47 | E70: ='balance_raw_27908470'!$E$47 | F70: ='balance_raw_27908470'!$F$47 | H70: =IFERROR(B70/$B$70*100,"") | I70: =IFERROR(C70/$B$70*100,"") | J70: =IFERROR(D70/$B$70*100,"") | K70: =IFERROR(E70/$B$70*100,"") | L70: =IFERROR(F70/$B$70*100,"")
A71: Gældsforpligtelser | B71: ='balance_raw_27908470'!$B$48 | C71: ='balance_raw_27908470'!$C$48 | D71: ='balance_raw_27908470'!$D$48 | E71: ='balance_raw_27908470'!$E$48 | F71: ='balance_raw_27908470'!$F$48 | H71: =IFERROR(B71/$B$71*100,"") | I71: =IFERROR(C71/$B$71*100,"") | J71: =IFERROR(D71/$B$71*100,"") | K71: =IFERROR(E71/$B$71*100,"") | L71: =IFERROR(F71/$B$71*100,"")
A72: Passiver | B72: ='balance_raw_27908470'!$B$49 | C72: ='balance_raw_27908470'!$C$49 | D72: ='balance_raw_27908470'!$D$49 | E72: ='balance_raw_27908470'!$E$49 | F72: ='balance_raw_27908470'!$F$49 | H72: =IFERROR(B72/$B$72*100,"") | I72: =IFERROR(C72/$B$72*100,"") | J72: =IFERROR(D72/$B$72*100,"") | K72: =IFERROR(E72/$B$72*100,"") | L72: =IFERROR(F72/$B$72*100,"")
A74: NØGLEOPLYSNINGER | B74: 2021 | C74: 2022 | D74: 2023 | E74: 2024 | F74: 2025
A75: Gns. antal medarbejdere | B75: ='res_raw_27908470'!$B$19 | C75: ='res_raw_27908470'!$C$19 | D75: ='res_raw_27908470'!$D$19 | E75: ='res_raw_27908470'!$E$19 | F75: ='res_raw_27908470'!$F$19 | H75: =IFERROR(B75/$B$75*100,"") | I75: =IFERROR(C75/$B$75*100,"") | J75: =IFERROR(D75/$B$75*100,"") | K75: =IFERROR(E75/$B$75*100,"") | L75: =IFERROR(F75/$B$75*100,"")
A76: Investering i materielle anlægsaktiver | B76: ='res_raw_27908470'!$B$20 | C76: ='res_raw_27908470'!$C$20 | D76: ='res_raw_27908470'!$D$20 | E76: ='res_raw_27908470'!$E$20 | F76: ='res_raw_27908470'!$F$20 | H76: =IFERROR(B76/$B$76*100,"") | I76: =IFERROR(C76/$B$76*100,"") | J76: =IFERROR(D76/$B$76*100,"") | K76: =IFERROR(E76/$B$76*100,"") | L76: =IFERROR(F76/$B$76*100,"")
A78: NØGLETAL | B78: 2021 | C78: 2022 | D78: 2023 | E78: 2024 | F78: 2025
A79: Afkastningsgrad, % | B79: =IFERROR(($B$13+$B$15+$B$14)/$B$48*100,"") | C79: =IFERROR(($C$13+$C$15+$C$14)/$C$48*100,"") | D79: =IFERROR(($D$13+$D$15+$D$14)/$D$48*100,"") | E79: =IFERROR(($E$13+$E$15+$E$14)/$E$48*100,"") | F79: =IFERROR(($F$13+$F$15+$F$14)/$F$48*100,"")
A80: Overskudsgrad, % | B80: =IFERROR(($B$13+$B$15+$B$14)/$B$4*100,"") | C80: =IFERROR(($C$13+$C$15+$C$14)/$C$4*100,"") | D80: =IFERROR(($D$13+$D$15+$D$14)/$D$4*100,"") | E80: =IFERROR(($E$13+$E$15+$E$14)/$E$4*100,"") | F80: =IFERROR(($F$13+$F$15+$F$14)/$F$4*100,"")
A81: Aktivernes omsætningshastighed, gange | B81: =IFERROR($B$4/$B$48,"") | C81: =IFERROR($C$4/$C$48,"") | D81: =IFERROR($D$4/$D$48,"") | E81: =IFERROR($E$4/$E$48,"") | F81: =IFERROR($F$4/$F$48,"")
A82: Egenkapitalens forrentning, % | B82: =IFERROR($B$18/$B$57*100,"") | C82: =IFERROR($C$18/$C$57*100,"") | D82: =IFERROR($D$18/$D$57*100,"") | E82: =IFERROR($E$18/$E$57*100,"") | F82: =IFERROR($F$18/$F$57*100,"")
A83: Gældsrente, % | B83: =IFERROR($B$16/($B$72-$B$57)*100,"") | C83: =IFERROR($C$16/($C$72-$C$57)*100,"") | D83: =IFERROR($D$16/($D$72-$D$57)*100,"") | E83: =IFERROR($E$16/($E$72-$E$57)*100,"") | F83: =IFERROR($F$16/($F$72-$F$57)*100,"")
A84: Soliditetsgrad, % | B84: =IFERROR($B$57/$B$48*100,"") | C84: =IFERROR($C$57/$C$48*100,"") | D84: =IFERROR($D$57/$D$48*100,"") | E84: =IFERROR($E$57/$E$48*100,"") | F84: =IFERROR($F$57/$F$48*100,"")
A85: Gearing | B85: =IFERROR(($B$72-$B$57)/$B$57,"") | C85: =IFERROR(($C$72-$C$57)/$C$57,"") | D85: =IFERROR(($D$72-$D$57)/$D$57,"") | E85: =IFERROR(($E$72-$E$57)/$E$57,"") | F85: =IFERROR(($F$72-$F$57)/$F$57,"")
A86: Likviditetsgrad, % | B86: =IFERROR($B$47/$B$70*100,"") | C86: =IFERROR($C$47/$C$70*100,"") | D86: =IFERROR($D$47/$D$70*100,"") | E86: =IFERROR($E$47/$E$70*100,"") | F86: =IFERROR($F$47/$F$70*100,"")
A87: Rentemarginal, % | B87: =IFERROR(B79-B83,"") | C87: =IFERROR(C79-C83,"") | D87: =IFERROR(D79-D83,"") | E87: =IFERROR(E79-E83,"") | F87: =IFERROR(F79-F83,"")
A88: Gældsandel, % | B88: =IFERROR(($B$72-$B$57)/$B$48*100,"") | C88: =IFERROR(($C$72-$C$57)/$C$48*100,"") | D88: =IFERROR(($D$72-$D$57)/$D$48*100,"") | E88: =IFERROR(($E$72-$E$57)/$E$48*100,"") | F88: =IFERROR(($F$72-$F$57)/$F$48*100,"")
A89: Kapitalbindingsgrad, % | B89: =IFERROR($B$32/($B$57+$B$58)*100,"") | C89: =IFERROR($C$32/($C$57+$C$58)*100,"") | D89: =IFERROR($D$32/($D$57+$D$58)*100,"") | E89: =IFERROR($E$32/($E$57+$E$58)*100,"") | F89: =IFERROR($F$32/($F$57+$F$58)*100,"")
A91: Pengestrømsopgørelse ikke offentliggjort (jf. koncernfritagelse, ÅRL §86, stk. 4)

Sheet res_raw_27908470
A1: Refsvindinge Bryggeri ApS (CVR 27908470) — Resultatopgørelse & nøgleoplysninger (t.kr.) | B1: 2021 | C1: 2022 | D1: 2023 | E1: 2024 | F1: 2025
A2: Nettoomsætning
A3: Andre driftsindtægter
A4: Vareforbrug
A5: Andre eksterne omkostninger
A6: Bruttoresultat | B6: 3365 | C6: 3181 | D6: 2103 | E6: 2505 | F6: 2127
A7: Personaleomkostninger | B7: 1707 | C7: 1808 | D7: 2039 | E7: 1984 | F7: 1954
A8: Resultat før afskrivninger
A9: Af- og nedskrivninger | B9: 334 | C9: 310 | D9: 179 | E9: 170 | F9: 106
A10: Andre driftsomkostninger | E10: 322 | F10: 0
A11: Resultat af primær drift | B11: 1324 | C11: 1063 | D11: -115 | E11: 28 | F11: 67
A12: Indtægter af kapitalandele, dattervirksomheder
A13: Finansielle indtægter | B13: 0 | C13: 0 | F13: 18
A14: Finansielle omkostninger | B14: 88 | C14: 91 | D14: 109 | E14: 81 | F14: 56
A15: Finansielle poster, netto
A16: Resultat før skat | B16: 1236 | C16: 973 | D16: -224 | E16: -53 | F16: 30
A17: Skat af årets resultat | B17: 274 | C17: 218 | D17: -49 | E17: 168 | F17: 8
A18: Årets resultat | B18: 961 | C18: 755 | D18: -175 | E18: -221 | F18: 22
A19: Gns. antal medarbejdere | B19: 5 | C19: 6 | D19: 5 | E19: 5 | F19: 5
A20: Investering i materielle anlægsaktiver

Sheet balance_raw_27908470
A1: Refsvindinge Bryggeri ApS (CVR 27908470) — Balance (t.kr.) | B1: 2021 | C1: 2022 | D1: 2023 | E1: 2024 | F1: 2025
A2: Grunde og bygninger | B2: 2287 | C2: 2484 | D2: 2415 | E2: 0
A3: Produktionsanlæg og maskiner | B3: 538 | C3: 291 | D3: 231 | E3: 132 | F3: 55
A4: Driftsmateriel og inventar
A5: Indretning af lejede lokaler | E5: 232 | F5: 223
A6: Forudbetaling og anlægsaktiver under opførelse
A7: Materielle anlægsaktiver | B7: 2825 | C7: 2775 | D7: 2646 | E7: 364 | F7: 279
A8: Kapitalandele, dattervirksomheder
A9: Deposita | B9: 259 | C9: 259 | D9: 259 | E9: 259 | F9: 259
A10: Finansielle anlægsaktiver | B10: 259 | C10: 259 | D10: 259 | E10: 259 | F10: 259
A11: Anlægsaktiver | B11: 3084 | C11: 3034 | D11: 2905 | E11: 624 | F11: 538
A12: Råvarer og hjælpematerialer
A13: Varer under fremstilling
A14: Færdigvarer og handelsvarer | B14: 1050 | C14: 1160 | D14: 1049 | E14: 1128 | F14: 1183
A15: Varebeholdninger | B15: 1050 | C15: 1160 | D15: 1049 | E15: 1128 | F15: 1183
A16: Tilgodehavender fra salg og tjenesteydelser | B16: 391 | C16: 633 | D16: 489 | E16: 618 | F16: 240
A17: Tilgodehavender hos tilknyttede virksomheder
A18: Andre tilgodehavender | B18: 120 | C18: 208 | D18: 140 | E18: 2049 | F18: 170
A19: Periodeafgrænsningsposter (aktiver) | B19: 0 | C19: 14 | D19: 31 | E19: 30 | F19: 34
A20: Udskudt skatteaktiv | B20: 113 | C20: 141 | D20: 170 | E20: 46 | F20: 46
A21: Tilgodehavende skat hos tilknyttede virksomheder
A22: Kortfristede skattetilgodehavender | D22: 20 | E22: 20 | F22: 0
A23: Tilgodehavender | B23: 624 | C23: 996 | D23: 849 | E23: 2763 | F23: 490
A24: Værdipapirer
A25: Likvide beholdninger | B25: 973 | C25: 980 | D25: 949 | E25: 1179 | F25: 832
A26: Omsætningsaktiver | B26: 2647 | C26: 3136 | D26: 2847 | E26: 5070 | F26: 2505
A27: Aktiver | B27: 5730 | C27: 6170 | D27: 5752 | E27: 5693 | F27: 3043
A28: Selskabskapital | B28: 125 | C28: 125 | D28: 125 | E28: 125 | F28: 125
A29: Reserve for nettoopskrivning (indre værdis metode)
A30: Reserve for udviklingsomkostninger
A31: Reserve for sikringstransaktioner
A32: Andre reserver
A33: Overført resultat | B33: 2417 | C33: 2672 | D33: 2497 | E33: 1276 | F33: 1298
A34: Egenkapital i alt | B34: 3542 | C34: 3297 | D34: 2622 | E34: 2401 | F34: 1423
A35: Langfristede gældsforpligtelser | B35: 163 | C35: 245 | D35: 0 | E35: 45 | F35: 8
A36: Ansvarlig lånekapital (kortfristet)
A37: Kortfristet del af langfristede gældsforpligtelser
A38: Kreditinstitutter
A39: Leasingforpligtelser (kortfristet)
A40: Leverandører af varer og tjenesteydelser | B40: 499 | C40: 639 | D40: 767 | E40: 890 | F40: 297
A41: Gæld til tilknyttede virksomheder | B41: 977 | C41: 1544 | D41: 1833 | E41: 1907 | F41: 981
A42: Gæld til selskabsdeltagere og ledelse | E42: 222 | F42: 57
A43: Selskabsskat | B43: 63 | C43: 0 | F43: 45
A44: Gæld til tilknyttede virksomheder vedr. selskabsskat
A45: Anden gæld (kortfristet) | B45: 487 | C45: 444
A46: Periodeafgrænsningsposter (passiver)
A47: Kortfristede gældsforpligtelser | B47: 2026 | C47: 2628 | D47: 3130 | E47: 3248 | F47: 1612
A48: Gældsforpligtelser | B48: 2189 | C48: 2873 | D48: 3130 | E48: 3293 | F48: 1620
A49: Passiver | B49: 5730 | C49: 6170 | D49: 5752 | E49: 5693 | F49: 3043

Sheet Simpel_arts
A1: Refsvindinge Bryggeri ApS (CVR 27908470) — Regnskabs- og nøgletal (CVR: 27908470) — artsopdelt
A3: Beløb i 1.000 kr. | B3: 2025 | C3: 2024 | D3: 2023 | F3: Note / XBRL-felt
A4: Uddrag af resultatopgørelse
A5: Nettoomsætning | B5: ='res_raw_27908470'!$F$2 | C5: ='res_raw_27908470'!$E$2 | D5: ='res_raw_27908470'!$D$2 | F5: fsa:Revenue
A6: Andre driftsindtægter | B6: ='res_raw_27908470'!$F$3 | C6: ='res_raw_27908470'!$E$3 | D6: ='res_raw_27908470'!$D$3 | F6: fsa:OtherOperatingIncome. Indtægter fra sekundære aktiviteter (huslejeindtægter, avance ved salg af anlæg mv.).
A7: Vareforbrug | B7: =-'res_raw_27908470'!$F$4 | C7: =-'res_raw_27908470'!$E$4 | D7: =-'res_raw_27908470'!$D$4 | F7: fsa:CostOfSales (vises negativt for korrekt SUM-formel).
A8: Andre eksterne omk. mv. | B8: =-'res_raw_27908470'!$F$5 | C8: =-'res_raw_27908470'!$E$5 | D8: =-'res_raw_27908470'!$D$5 | F8: fsa:OtherExternalExpenses (vises negativt). Husleje, energi, kontorhold mv.
A9: Bruttofortjeneste | B9: =SUM(B5:B8) | C9: =SUM(C5:C8) | D9: =SUM(D5:D8) | F9: Beregnet: Nettoomsætning + Andre driftsindt. − Vareforbrug − Andre ext. omk.
A10: Personaleomkostninger | B10: =-'res_raw_27908470'!$F$7 | C10: =-'res_raw_27908470'!$E$7 | D10: =-'res_raw_27908470'!$D$7 | F10: fsa:EmployeeBenefitsExpense (vises negativt). Lønninger, pension, sociale ydelser.
A11: Af- og nedskrivninger | B11: =-'res_raw_27908470'!$F$9 | C11: =-'res_raw_27908470'!$E$9 | D11: =-'res_raw_27908470'!$D$9 | F11: fsa:Depreciation (vises negativt). Af- og nedskrivninger på materielle og immaterielle anlægsaktiver.
A12: Andre driftsomkostninger | B12: =-'res_raw_27908470'!$F$10 | C12: =-'res_raw_27908470'!$E$10 | D12: =-'res_raw_27908470'!$D$10 | F12: fsa:OtherOperatingExpenses (vises negativt). Typisk 0 eller meget lille post.
A13: Resultat af primær drift | B13: =SUM(B9:B12) | C13: =SUM(C9:C12) | D13: =SUM(D9:D12) | F13: Beregnet: Bruttofortjeneste − Personaleomk. − Af- og nedskrivninger − Andre driftsomk. EBIT.
A14: Finansielle indtægter mv. | B14: =N('res_raw_27908470'!$F$12)+N('res_raw_27908470'!$F$13) | C14: =N('res_raw_27908470'!$E$12)+N('res_raw_27908470'!$E$13) | D14: =N('res_raw_27908470'!$D$12)+N('res_raw_27908470'!$D$13) | F14: fsa:IncomeFromSubsidiaries + fsa:OtherFinanceIncome.
A15: Finansielle omkostninger mv. | B15: =-'res_raw_27908470'!$F$14 | C15: =-'res_raw_27908470'!$E$14 | D15: =-'res_raw_27908470'!$D$14 | F15: fsa:OtherFinanceExpenses (vises negativt). Renteomkostninger, kurstab mv.
A16: Resultat før skat | B16: =SUM(B13:B15) | C16: =SUM(C13:C15) | D16: =SUM(D13:D15) | F16: Beregnet: EBIT + Fin. indtægter + Fin. omk. EBT.
A18: Uddrag af balance
A19: Anlægsaktiver | B19: ='balance_raw_27908470'!$F$11 | C19: ='balance_raw_27908470'!$E$11 | D19: ='balance_raw_27908470'!$D$11 | F19: fsa:NoncurrentAssets. Materielle, immaterielle og finansielle anlægsaktiver.
A20: Omsætningsaktiver | B20: ='balance_raw_27908470'!$F$26 | C20: ='balance_raw_27908470'!$E$26 | D20: ='balance_raw_27908470'!$D$26 | F20: fsa:CurrentAssets. Varebeholdninger, tilgodehavender, likvider.
A21: Aktiver i alt | B21: =SUM(B19:B20) | C21: =SUM(C19:C20) | D21: =SUM(D19:D20) | F21: Beregnet: Anlægsaktiver + Omsætningsaktiver. Bør matche fsa:Assets.
A23: Egenkapital | B23: ='balance_raw_27908470'!$F$34 | C23: ='balance_raw_27908470'!$E$34 | D23: ='balance_raw_27908470'!$D$34 | F23: fsa:Equity. Selskabskapital, overført resultat, reserver.
A24: Forpligtelser | B24: ='balance_raw_27908470'!$F$49-'balance_raw_27908470'!$F$34 | C24: ='balance_raw_27908470'!$E$49-'balance_raw_27908470'!$E$34 | D24: ='balance_raw_27908470'!$D$49-'balance_raw_27908470'!$D$34 | F24: Beregnet: Passiver (fsa:LiabilitiesAndEquity) − Egenkapital. Hensættelser + kort- og langfristet gæld.
A25: Passiver i alt | B25: =SUM(B23:B24) | C25: =SUM(C23:C24) | D25: =SUM(D23:D24) | F25: Beregnet: Egenkapital + Forpligtelser. Bør matche Aktiver i alt.
A27: Udvalgte balanceposter
A28: Varebeholdninger | B28: ='balance_raw_27908470'!$F$15 | C28: ='balance_raw_27908470'!$E$15 | D28: ='balance_raw_27908470'!$D$15 | F28: fsa:Inventories (eller fsa:ManufacturedGoodsAndGoodsForResale hvis total mangler).
A29: Tilgodehavender fra salg | B29: ='balance_raw_27908470'!$F$16 | C29: ='balance_raw_27908470'!$E$16 | D29: ='balance_raw_27908470'!$D$16 | F29: fsa:ShorttermTradeReceivables. Kortfristede tilgodehavender fra kunder.
A30: Kortfristede gældsforpligtelser | B30: ='balance_raw_27908470'!$F$47 | C30: ='balance_raw_27908470'!$E$47 | D30: ='balance_raw_27908470'!$D$47 | F30: fsa:ShorttermLiabilitiesOtherThanProvisions. Gæld der forfalder inden for 1 år.
A32: Rentabilitet
A33: Afkastningsgrad, % | B33: =IFERROR((B13+B14)/B21*100,"") | C33: =IFERROR((C13+C14)/C21*100,"") | D33: =IFERROR((D13+D14)/D21*100,"")
A34: Overskudsgrad, % | B34: =IFERROR((B13+B14)/B5*100,"") | C34: =IFERROR((C13+C14)/C5*100,"") | D34: =IFERROR((D13+D14)/D5*100,"")
A35: Aktivernes omsætningshastighed, gange | B35: =IFERROR(B5/B21,"") | C35: =IFERROR(C5/C21,"") | D35: =IFERROR(D5/D21,"")
A36: Gældsrente, % | B36: =IFERROR(-B15*100/B24,"") | C36: =IFERROR(-C15*100/C24,"") | D36: =IFERROR(-D15*100/D24,"")
A37: Egenkapitalens forrentning, % | B37: =IFERROR(B16/B23*100,"") | C37: =IFERROR(C16/C23*100,"") | D37: =IFERROR(D16/D23*100,"")
A38: Gearing, gange | B38: =IFERROR(B24/B23,"") | C38: =IFERROR(C24/C23,"") | D38: =IFERROR(D24/D23,"")
A40: Indekstal for indtjeningsevne (2023=100)
A41: Nettoomsætning | B41: =IFERROR(B5/$D5*100,"") | C41: =IFERROR(C5/$D5*100,"") | D41: =IFERROR(D5/$D5*100,"")
A42: Vareforbrug | B42: =IFERROR(B7/$D7*100,"") | C42: =IFERROR(C7/$D7*100,"") | D42: =IFERROR(D7/$D7*100,"")
A43: Andre eksterne omk. | B43: =IFERROR(B8/$D8*100,"") | C43: =IFERROR(C8/$D8*100,"") | D43: =IFERROR(D8/$D8*100,"")
A44: Personaleomkostninger | B44: =IFERROR(B10/$D10*100,"") | C44: =IFERROR(C10/$D10*100,"") | D44: =IFERROR(D10/$D10*100,"")
A45: Af- og nedskrivninger | B45: =IFERROR(B11/$D11*100,"") | C45: =IFERROR(C11/$D11*100,"") | D45: =IFERROR(D11/$D11*100,"")
A47: Indekstal for kapitaltilpasningsevne (2023=100)
A48: Nettoomsætning | B48: =IFERROR(B5*100/$D5,"") | C48: =IFERROR(C5*100/$D5,"") | D48: =IFERROR(D5*100/$D5,"")
A49: Anlægsaktiver | B49: =IFERROR(B19*100/$D19,"") | C49: =IFERROR(C19*100/$D19,"") | D49: =IFERROR(D19*100/$D19,"")
A50: Varebeholdninger | B50: =IFERROR(B28*100/$D28,"") | C50: =IFERROR(C28*100/$D28,"") | D50: =IFERROR(D28*100/$D28,"")
A51: Tilgodehavender fra salg | B51: =IFERROR(B29*100/$D29,"") | C51: =IFERROR(C29*100/$D29,"") | D51: =IFERROR(D29*100/$D29,"")
A53: Soliditet og likviditet
A54: Soliditetsgrad, % | B54: =IFERROR(B23*100/B21,"") | C54: =IFERROR(C23*100/C21,"") | D54: =IFERROR(D23*100/D21,"")
A55: Gældsandel, % | B55: =IFERROR(B24*100/B21,"") | C55: =IFERROR(C24*100/C21,"") | D55: =IFERROR(D24*100/D21,"")
A56: Likviditetsgrad, % | B56: =IFERROR(B20*100/B30,"") | C56: =IFERROR(C20*100/C30,"") | D56: =IFERROR(D20*100/D30,"")
A58: Kilde: Bearbejdet uddrag af årsrapporter for 2023-2025. Alle dataceller er live formler der peger på res_raw / balance_raw.
A60: Krydstjek mod rådata (tolerance: 1 t.kr.)
A61: Aktiver i alt = fsa:Assets | B61: =IF('balance_raw_27908470'!$F$27="","—",IF(ABS(B21-'balance_raw_27908470'!$F$27)<=1,"✓ OK","❌ "&TEXT(B21-'balance_raw_27908470'!$F$27,"+#,##0;-#,##0")&" t.kr.")) | C61: =IF('balance_raw_27908470'!$E$27="","—",IF(ABS(C21-'balance_raw_27908470'!$E$27)<=1,"✓ OK","❌ "&TEXT(C21-'balance_raw_27908470'!$E$27,"+#,##0;-#,##0")&" t.kr.")) | D61: =IF('balance_raw_27908470'!$D$27="","—",IF(ABS(D21-'balance_raw_27908470'!$D$27)<=1,"✓ OK","❌ "&TEXT(D21-'balance_raw_27908470'!$D$27,"+#,##0;-#,##0")&" t.kr.")) | F61: Verificerer at sum(Anlæg+Omsætning) matcher Assets-totalen.
A62: Passiver i alt = fsa:LiabilitiesAndEquity | B62: =IF('balance_raw_27908470'!$F$49="","—",IF(ABS(B25-'balance_raw_27908470'!$F$49)<=1,"✓ OK","❌ "&TEXT(B25-'balance_raw_27908470'!$F$49,"+#,##0;-#,##0")&" t.kr.")) | C62: =IF('balance_raw_27908470'!$E$49="","—",IF(ABS(C25-'balance_raw_27908470'!$E$49)<=1,"✓ OK","❌ "&TEXT(C25-'balance_raw_27908470'!$E$49,"+#,##0;-#,##0")&" t.kr.")) | D62: =IF('balance_raw_27908470'!$D$49="","—",IF(ABS(D25-'balance_raw_27908470'!$D$49)<=1,"✓ OK","❌ "&TEXT(D25-'balance_raw_27908470'!$D$49,"+#,##0;-#,##0")&" t.kr.")) | F62: Verificerer at sum(EK+Forpligtelser) matcher Passiver-totalen.
A63: Aktiver i alt = Passiver i alt | B63: =IF(ABS(B21-B25)<=1,"✓ OK","❌ "&TEXT(B21-B25,"+#,##0;-#,##0")&" t.kr.") | C63: =IF(ABS(C21-C25)<=1,"✓ OK","❌ "&TEXT(C21-C25,"+#,##0;-#,##0")&" t.kr.") | D63: =IF(ABS(D21-D25)<=1,"✓ OK","❌ "&TEXT(D21-D25,"+#,##0;-#,##0")&" t.kr.") | F63: Balance-identitet på arket selv. Skal altid være 0 differance.
A64: Bruttoresultat (beregnet) = fsa:GrossResult | B64: =IF('res_raw_27908470'!$F$6="","—",IF(ABS(B9-'res_raw_27908470'!$F$6)<=1,"✓ OK","❌ "&TEXT(B9-'res_raw_27908470'!$F$6,"+#,##0;-#,##0")&" t.kr.")) | C64: =IF('res_raw_27908470'!$E$6="","—",IF(ABS(C9-'res_raw_27908470'!$E$6)<=1,"✓ OK","❌ "&TEXT(C9-'res_raw_27908470'!$E$6,"+#,##0;-#,##0")&" t.kr.")) | D64: =IF('res_raw_27908470'!$D$6="","—",IF(ABS(D9-'res_raw_27908470'!$D$6)<=1,"✓ OK","❌ "&TEXT(D9-'res_raw_27908470'!$D$6,"+#,##0;-#,##0")&" t.kr.")) | F64: Hvis Nettoomsætning eller omkostninger mangler, vil sumberegnet bruttoresultat afvige.
A65: EBIT (beregnet) = fsa:ProfitLossFromOrdinaryOperatingActivities | B65: =IF('res_raw_27908470'!$F$11="","—",IF(ABS(B13-'res_raw_27908470'!$F$11)<=1,"✓ OK","❌ "&TEXT(B13-'res_raw_27908470'!$F$11,"+#,##0;-#,##0")&" t.kr.")) | C65: =IF('res_raw_27908470'!$E$11="","—",IF(ABS(C13-'res_raw_27908470'!$E$11)<=1,"✓ OK","❌ "&TEXT(C13-'res_raw_27908470'!$E$11,"+#,##0;-#,##0")&" t.kr.")) | D65: =IF('res_raw_27908470'!$D$11="","—",IF(ABS(D13-'res_raw_27908470'!$D$11)<=1,"✓ OK","❌ "&TEXT(D13-'res_raw_27908470'!$D$11,"+#,##0;-#,##0")&" t.kr.")) | F65: Verificerer at sumberegnet EBIT matcher det rapporterede.
A66: EBT (beregnet) = fsa:ProfitLossFromOrdinaryActivitiesBeforeTax | B66: =IF('res_raw_27908470'!$F$16="","—",IF(ABS(B16-'res_raw_27908470'!$F$16)<=1,"✓ OK","❌ "&TEXT(B16-'res_raw_27908470'!$F$16,"+#,##0;-#,##0")&" t.kr.")) | C66: =IF('res_raw_27908470'!$E$16="","—",IF(ABS(C16-'res_raw_27908470'!$E$16)<=1,"✓ OK","❌ "&TEXT(C16-'res_raw_27908470'!$E$16,"+#,##0;-#,##0")&" t.kr.")) | D66: =IF('res_raw_27908470'!$D$16="","—",IF(ABS(D16-'res_raw_27908470'!$D$16)<=1,"✓ OK","❌ "&TEXT(D16-'res_raw_27908470'!$D$16,"+#,##0;-#,##0")&" t.kr.")) | F66: Verificerer at sumberegnet resultat før skat matcher det rapporterede.

Sheet Noter_info
A1: Refsvindinge Bryggeri ApS (CVR 27908470) — Ukendte XBRL-felter — disse er noter og ikke en del af hoved-regnskabet
A2: Kategori | B2: Dansk navn | C2: XBRL feltnavn | D2: 2021 t.kr. | E2: 2022 t.kr. | F2: 2023 t.kr. | G2: 2024 t.kr. | H2: 2025 t.kr. | I2: Forklaring
A3: Øvrige (ukendt) | B3: fsa:LongtermTaxPayables | C3: fsa:LongtermTaxPayables | D3: 163 | E3: 245 | F3: 0 | G3: 45 | H3: 8 | I3: Ingen forklaring tilgængelig.
