Workbook

Sheet Overblik_32931499
A1: Sunweb Group Scandinavia A/S (CVR 32931499) — Regnskabsanalyse – Resultatopgørelse & Balance (t.kr.) · Klasse B · Udvidet gennemgang · Regnskabsår 1/11–31/10 (forskudt)
H2: Indekstal (2021=100)
A3: Resultatopgørelse t.kr. | B3: 2021 | C3: 2022 | D3: 2023 | E3: 2024 | F3: 2025 | H3: 2021 | I3: 2022 | J3: 2023 | K3: 2024 | L3: 2025
A4: Nettoomsætning | B4: ='res_raw_32931499'!$B$2 | C4: ='res_raw_32931499'!$C$2 | D4: ='res_raw_32931499'!$D$2 | E4: ='res_raw_32931499'!$E$2 | F4: ='res_raw_32931499'!$F$2 | H4: =IFERROR(B4/$B$4*100,"") | I4: =IFERROR(C4/$B$4*100,"") | J4: =IFERROR(D4/$B$4*100,"") | K4: =IFERROR(E4/$B$4*100,"") | L4: =IFERROR(F4/$B$4*100,"")
A5: Andre driftsindtægter | B5: ='res_raw_32931499'!$B$3 | C5: ='res_raw_32931499'!$C$3 | D5: ='res_raw_32931499'!$D$3 | E5: ='res_raw_32931499'!$E$3 | F5: ='res_raw_32931499'!$F$3 | H5: =IFERROR(B5/$B$5*100,"") | I5: =IFERROR(C5/$B$5*100,"") | J5: =IFERROR(D5/$B$5*100,"") | K5: =IFERROR(E5/$B$5*100,"") | L5: =IFERROR(F5/$B$5*100,"")
A6: Vareforbrug | B6: ='res_raw_32931499'!$B$4 | C6: ='res_raw_32931499'!$C$4 | D6: ='res_raw_32931499'!$D$4 | E6: ='res_raw_32931499'!$E$4 | F6: ='res_raw_32931499'!$F$4 | H6: =IFERROR(B6/$B$6*100,"") | I6: =IFERROR(C6/$B$6*100,"") | J6: =IFERROR(D6/$B$6*100,"") | K6: =IFERROR(E6/$B$6*100,"") | L6: =IFERROR(F6/$B$6*100,"")
A7: Andre eksterne omkostninger | B7: ='res_raw_32931499'!$B$5 | C7: ='res_raw_32931499'!$C$5 | D7: ='res_raw_32931499'!$D$5 | E7: ='res_raw_32931499'!$E$5 | F7: ='res_raw_32931499'!$F$5 | H7: =IFERROR(B7/$B$7*100,"") | I7: =IFERROR(C7/$B$7*100,"") | J7: =IFERROR(D7/$B$7*100,"") | K7: =IFERROR(E7/$B$7*100,"") | L7: =IFERROR(F7/$B$7*100,"")
A8: Bruttoresultat | B8: ='res_raw_32931499'!$B$6 | C8: ='res_raw_32931499'!$C$6 | D8: ='res_raw_32931499'!$D$6 | E8: ='res_raw_32931499'!$E$6 | F8: ='res_raw_32931499'!$F$6 | H8: =IFERROR(B8/$B$8*100,"") | I8: =IFERROR(C8/$B$8*100,"") | J8: =IFERROR(D8/$B$8*100,"") | K8: =IFERROR(E8/$B$8*100,"") | L8: =IFERROR(F8/$B$8*100,"")
A9: Personaleomkostninger | B9: ='res_raw_32931499'!$B$7 | C9: ='res_raw_32931499'!$C$7 | D9: ='res_raw_32931499'!$D$7 | E9: ='res_raw_32931499'!$E$7 | F9: ='res_raw_32931499'!$F$7 | H9: =IFERROR(B9/$B$9*100,"") | I9: =IFERROR(C9/$B$9*100,"") | J9: =IFERROR(D9/$B$9*100,"") | K9: =IFERROR(E9/$B$9*100,"") | L9: =IFERROR(F9/$B$9*100,"")
A10: Resultat før afskrivninger | B10: =IFERROR($B$8-ABS($B$9),"") | C10: =IFERROR($C$8-ABS($C$9),"") | D10: =IFERROR($D$8-ABS($D$9),"") | E10: =IFERROR($E$8-ABS($E$9),"") | F10: =IFERROR($F$8-ABS($F$9),"") | H10: =IFERROR(B10/$B$10*100,"") | I10: =IFERROR(C10/$B$10*100,"") | J10: =IFERROR(D10/$B$10*100,"") | K10: =IFERROR(E10/$B$10*100,"") | L10: =IFERROR(F10/$B$10*100,"")
A11: Af- og nedskrivninger | B11: ='res_raw_32931499'!$B$9 | C11: ='res_raw_32931499'!$C$9 | D11: ='res_raw_32931499'!$D$9 | E11: ='res_raw_32931499'!$E$9 | F11: ='res_raw_32931499'!$F$9 | H11: =IFERROR(B11/$B$11*100,"") | I11: =IFERROR(C11/$B$11*100,"") | J11: =IFERROR(D11/$B$11*100,"") | K11: =IFERROR(E11/$B$11*100,"") | L11: =IFERROR(F11/$B$11*100,"")
A12: Andre driftsomkostninger | B12: ='res_raw_32931499'!$B$10 | C12: ='res_raw_32931499'!$C$10 | D12: ='res_raw_32931499'!$D$10 | E12: ='res_raw_32931499'!$E$10 | F12: ='res_raw_32931499'!$F$10 | H12: =IFERROR(B12/$B$12*100,"") | I12: =IFERROR(C12/$B$12*100,"") | J12: =IFERROR(D12/$B$12*100,"") | K12: =IFERROR(E12/$B$12*100,"") | L12: =IFERROR(F12/$B$12*100,"")
A13: Resultat af primær drift | B13: ='res_raw_32931499'!$B$11 | C13: ='res_raw_32931499'!$C$11 | D13: ='res_raw_32931499'!$D$11 | E13: ='res_raw_32931499'!$E$11 | F13: ='res_raw_32931499'!$F$11 | H13: =IFERROR(B13/$B$13*100,"") | I13: =IFERROR(C13/$B$13*100,"") | J13: =IFERROR(D13/$B$13*100,"") | K13: =IFERROR(E13/$B$13*100,"") | L13: =IFERROR(F13/$B$13*100,"")
A14: Indtægter af kapitalandele, dattervirksomheder | B14: ='res_raw_32931499'!$B$12 | C14: ='res_raw_32931499'!$C$12 | D14: ='res_raw_32931499'!$D$12 | E14: ='res_raw_32931499'!$E$12 | F14: ='res_raw_32931499'!$F$12 | H14: =IFERROR(B14/$B$14*100,"") | I14: =IFERROR(C14/$B$14*100,"") | J14: =IFERROR(D14/$B$14*100,"") | K14: =IFERROR(E14/$B$14*100,"") | L14: =IFERROR(F14/$B$14*100,"")
A15: Finansielle indtægter | B15: ='res_raw_32931499'!$B$13 | C15: ='res_raw_32931499'!$C$13 | D15: ='res_raw_32931499'!$D$13 | E15: ='res_raw_32931499'!$E$13 | F15: ='res_raw_32931499'!$F$13 | H15: =IFERROR(B15/$B$15*100,"") | I15: =IFERROR(C15/$B$15*100,"") | J15: =IFERROR(D15/$B$15*100,"") | K15: =IFERROR(E15/$B$15*100,"") | L15: =IFERROR(F15/$B$15*100,"")
A16: Finansielle omkostninger | B16: ='res_raw_32931499'!$B$14 | C16: ='res_raw_32931499'!$C$14 | D16: ='res_raw_32931499'!$D$14 | E16: ='res_raw_32931499'!$E$14 | F16: ='res_raw_32931499'!$F$14 | H16: =IFERROR(B16/$B$16*100,"") | I16: =IFERROR(C16/$B$16*100,"") | J16: =IFERROR(D16/$B$16*100,"") | K16: =IFERROR(E16/$B$16*100,"") | L16: =IFERROR(F16/$B$16*100,"")
A17: Finansielle poster, netto | B17: ='res_raw_32931499'!$B$15 | C17: ='res_raw_32931499'!$C$15 | D17: ='res_raw_32931499'!$D$15 | E17: ='res_raw_32931499'!$E$15 | F17: ='res_raw_32931499'!$F$15 | H17: =IFERROR(B17/$B$17*100,"") | I17: =IFERROR(C17/$B$17*100,"") | J17: =IFERROR(D17/$B$17*100,"") | K17: =IFERROR(E17/$B$17*100,"") | L17: =IFERROR(F17/$B$17*100,"")
A18: Resultat før skat | B18: ='res_raw_32931499'!$B$16 | C18: ='res_raw_32931499'!$C$16 | D18: ='res_raw_32931499'!$D$16 | E18: ='res_raw_32931499'!$E$16 | F18: ='res_raw_32931499'!$F$16 | H18: =IFERROR(B18/$B$18*100,"") | I18: =IFERROR(C18/$B$18*100,"") | J18: =IFERROR(D18/$B$18*100,"") | K18: =IFERROR(E18/$B$18*100,"") | L18: =IFERROR(F18/$B$18*100,"")
A19: Skat af årets resultat | B19: ='res_raw_32931499'!$B$17 | C19: ='res_raw_32931499'!$C$17 | D19: ='res_raw_32931499'!$D$17 | E19: ='res_raw_32931499'!$E$17 | F19: ='res_raw_32931499'!$F$17 | H19: =IFERROR(B19/$B$19*100,"") | I19: =IFERROR(C19/$B$19*100,"") | J19: =IFERROR(D19/$B$19*100,"") | K19: =IFERROR(E19/$B$19*100,"") | L19: =IFERROR(F19/$B$19*100,"")
A20: Årets resultat | B20: ='res_raw_32931499'!$B$18 | C20: ='res_raw_32931499'!$C$18 | D20: ='res_raw_32931499'!$D$18 | E20: ='res_raw_32931499'!$E$18 | F20: ='res_raw_32931499'!$F$18 | H20: =IFERROR(B20/$B$20*100,"") | I20: =IFERROR(C20/$B$20*100,"") | J20: =IFERROR(D20/$B$20*100,"") | K20: =IFERROR(E20/$B$20*100,"") | L20: =IFERROR(F20/$B$20*100,"")
A22: AKTIVER t.kr. | B22: 2021 | C22: 2022 | D22: 2023 | E22: 2024 | F22: 2025 | H22: 2021 | I22: 2022 | J22: 2023 | K22: 2024 | L22: 2025
A23: Grunde og bygninger | B23: ='balance_raw_32931499'!$B$2 | C23: ='balance_raw_32931499'!$C$2 | D23: ='balance_raw_32931499'!$D$2 | E23: ='balance_raw_32931499'!$E$2 | F23: ='balance_raw_32931499'!$F$2 | H23: =IFERROR(B23/$B$23*100,"") | I23: =IFERROR(C23/$B$23*100,"") | J23: =IFERROR(D23/$B$23*100,"") | K23: =IFERROR(E23/$B$23*100,"") | L23: =IFERROR(F23/$B$23*100,"")
A24: Produktionsanlæg og maskiner | B24: ='balance_raw_32931499'!$B$3 | C24: ='balance_raw_32931499'!$C$3 | D24: ='balance_raw_32931499'!$D$3 | E24: ='balance_raw_32931499'!$E$3 | F24: ='balance_raw_32931499'!$F$3 | H24: =IFERROR(B24/$B$24*100,"") | I24: =IFERROR(C24/$B$24*100,"") | J24: =IFERROR(D24/$B$24*100,"") | K24: =IFERROR(E24/$B$24*100,"") | L24: =IFERROR(F24/$B$24*100,"")
A25: Driftsmateriel og inventar | B25: ='balance_raw_32931499'!$B$4 | C25: ='balance_raw_32931499'!$C$4 | D25: ='balance_raw_32931499'!$D$4 | E25: ='balance_raw_32931499'!$E$4 | F25: ='balance_raw_32931499'!$F$4 | H25: =IFERROR(B25/$B$25*100,"") | I25: =IFERROR(C25/$B$25*100,"") | J25: =IFERROR(D25/$B$25*100,"") | K25: =IFERROR(E25/$B$25*100,"") | L25: =IFERROR(F25/$B$25*100,"")
A26: Indretning af lejede lokaler | B26: ='balance_raw_32931499'!$B$5 | C26: ='balance_raw_32931499'!$C$5 | D26: ='balance_raw_32931499'!$D$5 | E26: ='balance_raw_32931499'!$E$5 | F26: ='balance_raw_32931499'!$F$5 | H26: =IFERROR(B26/$B$26*100,"") | I26: =IFERROR(C26/$B$26*100,"") | J26: =IFERROR(D26/$B$26*100,"") | K26: =IFERROR(E26/$B$26*100,"") | L26: =IFERROR(F26/$B$26*100,"")
A27: Forudbetaling og anlægsaktiver under opførelse | B27: ='balance_raw_32931499'!$B$6 | C27: ='balance_raw_32931499'!$C$6 | D27: ='balance_raw_32931499'!$D$6 | E27: ='balance_raw_32931499'!$E$6 | F27: ='balance_raw_32931499'!$F$6 | H27: =IFERROR(B27/$B$27*100,"") | I27: =IFERROR(C27/$B$27*100,"") | J27: =IFERROR(D27/$B$27*100,"") | K27: =IFERROR(E27/$B$27*100,"") | L27: =IFERROR(F27/$B$27*100,"")
A28: Materielle anlægsaktiver | B28: ='balance_raw_32931499'!$B$7 | C28: ='balance_raw_32931499'!$C$7 | D28: ='balance_raw_32931499'!$D$7 | E28: ='balance_raw_32931499'!$E$7 | F28: ='balance_raw_32931499'!$F$7 | H28: =IFERROR(B28/$B$28*100,"") | I28: =IFERROR(C28/$B$28*100,"") | J28: =IFERROR(D28/$B$28*100,"") | K28: =IFERROR(E28/$B$28*100,"") | L28: =IFERROR(F28/$B$28*100,"")
A29: Anlægsaktiver | B29: ='balance_raw_32931499'!$B$8 | C29: ='balance_raw_32931499'!$C$8 | D29: ='balance_raw_32931499'!$D$8 | E29: ='balance_raw_32931499'!$E$8 | F29: ='balance_raw_32931499'!$F$8 | H29: =IFERROR(B29/$B$29*100,"") | I29: =IFERROR(C29/$B$29*100,"") | J29: =IFERROR(D29/$B$29*100,"") | K29: =IFERROR(E29/$B$29*100,"") | L29: =IFERROR(F29/$B$29*100,"")
A30: Tilgodehavender fra salg og tjenesteydelser | B30: ='balance_raw_32931499'!$B$9 | C30: ='balance_raw_32931499'!$C$9 | D30: ='balance_raw_32931499'!$D$9 | E30: ='balance_raw_32931499'!$E$9 | F30: ='balance_raw_32931499'!$F$9 | H30: =IFERROR(B30/$B$30*100,"") | I30: =IFERROR(C30/$B$30*100,"") | J30: =IFERROR(D30/$B$30*100,"") | K30: =IFERROR(E30/$B$30*100,"") | L30: =IFERROR(F30/$B$30*100,"")
A31: Tilgodehavender hos tilknyttede virksomheder | B31: ='balance_raw_32931499'!$B$10 | C31: ='balance_raw_32931499'!$C$10 | D31: ='balance_raw_32931499'!$D$10 | E31: ='balance_raw_32931499'!$E$10 | F31: ='balance_raw_32931499'!$F$10 | H31: =IFERROR(B31/$B$31*100,"") | I31: =IFERROR(C31/$B$31*100,"") | J31: =IFERROR(D31/$B$31*100,"") | K31: =IFERROR(E31/$B$31*100,"") | L31: =IFERROR(F31/$B$31*100,"")
A32: Andre tilgodehavender | B32: ='balance_raw_32931499'!$B$11 | C32: ='balance_raw_32931499'!$C$11 | D32: ='balance_raw_32931499'!$D$11 | E32: ='balance_raw_32931499'!$E$11 | F32: ='balance_raw_32931499'!$F$11 | H32: =IFERROR(B32/$B$32*100,"") | I32: =IFERROR(C32/$B$32*100,"") | J32: =IFERROR(D32/$B$32*100,"") | K32: =IFERROR(E32/$B$32*100,"") | L32: =IFERROR(F32/$B$32*100,"")
A33: Periodeafgrænsningsposter (aktiver) | B33: ='balance_raw_32931499'!$B$12 | C33: ='balance_raw_32931499'!$C$12 | D33: ='balance_raw_32931499'!$D$12 | E33: ='balance_raw_32931499'!$E$12 | F33: ='balance_raw_32931499'!$F$12 | H33: =IFERROR(B33/$B$33*100,"") | I33: =IFERROR(C33/$B$33*100,"") | J33: =IFERROR(D33/$B$33*100,"") | K33: =IFERROR(E33/$B$33*100,"") | L33: =IFERROR(F33/$B$33*100,"")
A34: Udskudt skatteaktiv | B34: ='balance_raw_32931499'!$B$13 | C34: ='balance_raw_32931499'!$C$13 | D34: ='balance_raw_32931499'!$D$13 | E34: ='balance_raw_32931499'!$E$13 | F34: ='balance_raw_32931499'!$F$13 | H34: =IFERROR(B34/$B$34*100,"") | I34: =IFERROR(C34/$B$34*100,"") | J34: =IFERROR(D34/$B$34*100,"") | K34: =IFERROR(E34/$B$34*100,"") | L34: =IFERROR(F34/$B$34*100,"")
A35: Tilgodehavende skat hos tilknyttede virksomheder | B35: ='balance_raw_32931499'!$B$14 | C35: ='balance_raw_32931499'!$C$14 | D35: ='balance_raw_32931499'!$D$14 | E35: ='balance_raw_32931499'!$E$14 | F35: ='balance_raw_32931499'!$F$14 | H35: =IFERROR(B35/$B$35*100,"") | I35: =IFERROR(C35/$B$35*100,"") | J35: =IFERROR(D35/$B$35*100,"") | K35: =IFERROR(E35/$B$35*100,"") | L35: =IFERROR(F35/$B$35*100,"")
A36: Kortfristede skattetilgodehavender | B36: ='balance_raw_32931499'!$B$15 | C36: ='balance_raw_32931499'!$C$15 | D36: ='balance_raw_32931499'!$D$15 | E36: ='balance_raw_32931499'!$E$15 | F36: ='balance_raw_32931499'!$F$15 | H36: =IFERROR(B36/$B$36*100,"") | I36: =IFERROR(C36/$B$36*100,"") | J36: =IFERROR(D36/$B$36*100,"") | K36: =IFERROR(E36/$B$36*100,"") | L36: =IFERROR(F36/$B$36*100,"")
A37: Tilgodehavender | B37: ='balance_raw_32931499'!$B$16 | C37: ='balance_raw_32931499'!$C$16 | D37: ='balance_raw_32931499'!$D$16 | E37: ='balance_raw_32931499'!$E$16 | F37: ='balance_raw_32931499'!$F$16 | H37: =IFERROR(B37/$B$37*100,"") | I37: =IFERROR(C37/$B$37*100,"") | J37: =IFERROR(D37/$B$37*100,"") | K37: =IFERROR(E37/$B$37*100,"") | L37: =IFERROR(F37/$B$37*100,"")
A38: Værdipapirer | B38: ='balance_raw_32931499'!$B$17 | C38: ='balance_raw_32931499'!$C$17 | D38: ='balance_raw_32931499'!$D$17 | E38: ='balance_raw_32931499'!$E$17 | F38: ='balance_raw_32931499'!$F$17 | H38: =IFERROR(B38/$B$38*100,"") | I38: =IFERROR(C38/$B$38*100,"") | J38: =IFERROR(D38/$B$38*100,"") | K38: =IFERROR(E38/$B$38*100,"") | L38: =IFERROR(F38/$B$38*100,"")
A39: Likvide beholdninger | B39: ='balance_raw_32931499'!$B$18 | C39: ='balance_raw_32931499'!$C$18 | D39: ='balance_raw_32931499'!$D$18 | E39: ='balance_raw_32931499'!$E$18 | F39: ='balance_raw_32931499'!$F$18 | H39: =IFERROR(B39/$B$39*100,"") | I39: =IFERROR(C39/$B$39*100,"") | J39: =IFERROR(D39/$B$39*100,"") | K39: =IFERROR(E39/$B$39*100,"") | L39: =IFERROR(F39/$B$39*100,"")
A40: Omsætningsaktiver | B40: ='balance_raw_32931499'!$B$19 | C40: ='balance_raw_32931499'!$C$19 | D40: ='balance_raw_32931499'!$D$19 | E40: ='balance_raw_32931499'!$E$19 | F40: ='balance_raw_32931499'!$F$19 | H40: =IFERROR(B40/$B$40*100,"") | I40: =IFERROR(C40/$B$40*100,"") | J40: =IFERROR(D40/$B$40*100,"") | K40: =IFERROR(E40/$B$40*100,"") | L40: =IFERROR(F40/$B$40*100,"")
A41: Aktiver | B41: ='balance_raw_32931499'!$B$20 | C41: ='balance_raw_32931499'!$C$20 | D41: ='balance_raw_32931499'!$D$20 | E41: ='balance_raw_32931499'!$E$20 | F41: ='balance_raw_32931499'!$F$20 | H41: =IFERROR(B41/$B$41*100,"") | I41: =IFERROR(C41/$B$41*100,"") | J41: =IFERROR(D41/$B$41*100,"") | K41: =IFERROR(E41/$B$41*100,"") | L41: =IFERROR(F41/$B$41*100,"")
A43: PASSIVER t.kr. | B43: 2021 | C43: 2022 | D43: 2023 | E43: 2024 | F43: 2025 | H43: 2021 | I43: 2022 | J43: 2023 | K43: 2024 | L43: 2025
A44: Selskabskapital | B44: ='balance_raw_32931499'!$B$21 | C44: ='balance_raw_32931499'!$C$21 | D44: ='balance_raw_32931499'!$D$21 | E44: ='balance_raw_32931499'!$E$21 | F44: ='balance_raw_32931499'!$F$21 | H44: =IFERROR(B44/$B$44*100,"") | I44: =IFERROR(C44/$B$44*100,"") | J44: =IFERROR(D44/$B$44*100,"") | K44: =IFERROR(E44/$B$44*100,"") | L44: =IFERROR(F44/$B$44*100,"")
A45: Reserve for nettoopskrivning (indre værdis metode) | B45: ='balance_raw_32931499'!$B$22 | C45: ='balance_raw_32931499'!$C$22 | D45: ='balance_raw_32931499'!$D$22 | E45: ='balance_raw_32931499'!$E$22 | F45: ='balance_raw_32931499'!$F$22 | H45: =IFERROR(B45/$B$45*100,"") | I45: =IFERROR(C45/$B$45*100,"") | J45: =IFERROR(D45/$B$45*100,"") | K45: =IFERROR(E45/$B$45*100,"") | L45: =IFERROR(F45/$B$45*100,"")
A46: Reserve for udviklingsomkostninger | B46: ='balance_raw_32931499'!$B$23 | C46: ='balance_raw_32931499'!$C$23 | D46: ='balance_raw_32931499'!$D$23 | E46: ='balance_raw_32931499'!$E$23 | F46: ='balance_raw_32931499'!$F$23 | H46: =IFERROR(B46/$B$46*100,"") | I46: =IFERROR(C46/$B$46*100,"") | J46: =IFERROR(D46/$B$46*100,"") | K46: =IFERROR(E46/$B$46*100,"") | L46: =IFERROR(F46/$B$46*100,"")
A47: Reserve for sikringstransaktioner | B47: ='balance_raw_32931499'!$B$24 | C47: ='balance_raw_32931499'!$C$24 | D47: ='balance_raw_32931499'!$D$24 | E47: ='balance_raw_32931499'!$E$24 | F47: ='balance_raw_32931499'!$F$24 | H47: =IFERROR(B47/$B$47*100,"") | I47: =IFERROR(C47/$B$47*100,"") | J47: =IFERROR(D47/$B$47*100,"") | K47: =IFERROR(E47/$B$47*100,"") | L47: =IFERROR(F47/$B$47*100,"")
A48: Andre reserver | B48: ='balance_raw_32931499'!$B$25 | C48: ='balance_raw_32931499'!$C$25 | D48: ='balance_raw_32931499'!$D$25 | E48: ='balance_raw_32931499'!$E$25 | F48: ='balance_raw_32931499'!$F$25 | H48: =IFERROR(B48/$B$48*100,"") | I48: =IFERROR(C48/$B$48*100,"") | J48: =IFERROR(D48/$B$48*100,"") | K48: =IFERROR(E48/$B$48*100,"") | L48: =IFERROR(F48/$B$48*100,"")
A49: Overført resultat | B49: ='balance_raw_32931499'!$B$26 | C49: ='balance_raw_32931499'!$C$26 | D49: ='balance_raw_32931499'!$D$26 | E49: ='balance_raw_32931499'!$E$26 | F49: ='balance_raw_32931499'!$F$26 | H49: =IFERROR(B49/$B$49*100,"") | I49: =IFERROR(C49/$B$49*100,"") | J49: =IFERROR(D49/$B$49*100,"") | K49: =IFERROR(E49/$B$49*100,"") | L49: =IFERROR(F49/$B$49*100,"")
A50: Egenkapital i alt | B50: ='balance_raw_32931499'!$B$27 | C50: ='balance_raw_32931499'!$C$27 | D50: ='balance_raw_32931499'!$D$27 | E50: ='balance_raw_32931499'!$E$27 | F50: ='balance_raw_32931499'!$F$27 | H50: =IFERROR(B50/$B$50*100,"") | I50: =IFERROR(C50/$B$50*100,"") | J50: =IFERROR(D50/$B$50*100,"") | K50: =IFERROR(E50/$B$50*100,"") | L50: =IFERROR(F50/$B$50*100,"")
A51: Hensættelse til udskudt skat | B51: ='balance_raw_32931499'!$B$28 | C51: ='balance_raw_32931499'!$C$28 | D51: ='balance_raw_32931499'!$D$28 | E51: ='balance_raw_32931499'!$E$28 | F51: ='balance_raw_32931499'!$F$28 | H51: =IFERROR(B51/$B$51*100,"") | I51: =IFERROR(C51/$B$51*100,"") | J51: =IFERROR(D51/$B$51*100,"") | K51: =IFERROR(E51/$B$51*100,"") | L51: =IFERROR(F51/$B$51*100,"")
A52: Hensatte forpligtelser | B52: ='balance_raw_32931499'!$B$29 | C52: ='balance_raw_32931499'!$C$29 | D52: ='balance_raw_32931499'!$D$29 | E52: ='balance_raw_32931499'!$E$29 | F52: ='balance_raw_32931499'!$F$29 | H52: =IFERROR(B52/$B$52*100,"") | I52: =IFERROR(C52/$B$52*100,"") | J52: =IFERROR(D52/$B$52*100,"") | K52: =IFERROR(E52/$B$52*100,"") | L52: =IFERROR(F52/$B$52*100,"")
A53: Langfristede gældsforpligtelser | B53: ='balance_raw_32931499'!$B$30 | C53: ='balance_raw_32931499'!$C$30 | D53: ='balance_raw_32931499'!$D$30 | E53: ='balance_raw_32931499'!$E$30 | F53: ='balance_raw_32931499'!$F$30 | H53: =IFERROR(B53/$B$53*100,"") | I53: =IFERROR(C53/$B$53*100,"") | J53: =IFERROR(D53/$B$53*100,"") | K53: =IFERROR(E53/$B$53*100,"") | L53: =IFERROR(F53/$B$53*100,"")
A54: Ansvarlig lånekapital (kortfristet) | B54: ='balance_raw_32931499'!$B$31 | C54: ='balance_raw_32931499'!$C$31 | D54: ='balance_raw_32931499'!$D$31 | E54: ='balance_raw_32931499'!$E$31 | F54: ='balance_raw_32931499'!$F$31 | H54: =IFERROR(B54/$B$54*100,"") | I54: =IFERROR(C54/$B$54*100,"") | J54: =IFERROR(D54/$B$54*100,"") | K54: =IFERROR(E54/$B$54*100,"") | L54: =IFERROR(F54/$B$54*100,"")
A55: Kortfristet del af langfristede gældsforpligtelser | B55: ='balance_raw_32931499'!$B$32 | C55: ='balance_raw_32931499'!$C$32 | D55: ='balance_raw_32931499'!$D$32 | E55: ='balance_raw_32931499'!$E$32 | F55: ='balance_raw_32931499'!$F$32 | H55: =IFERROR(B55/$B$55*100,"") | I55: =IFERROR(C55/$B$55*100,"") | J55: =IFERROR(D55/$B$55*100,"") | K55: =IFERROR(E55/$B$55*100,"") | L55: =IFERROR(F55/$B$55*100,"")
A56: Kreditinstitutter | B56: ='balance_raw_32931499'!$B$33 | C56: ='balance_raw_32931499'!$C$33 | D56: ='balance_raw_32931499'!$D$33 | E56: ='balance_raw_32931499'!$E$33 | F56: ='balance_raw_32931499'!$F$33 | H56: =IFERROR(B56/$B$56*100,"") | I56: =IFERROR(C56/$B$56*100,"") | J56: =IFERROR(D56/$B$56*100,"") | K56: =IFERROR(E56/$B$56*100,"") | L56: =IFERROR(F56/$B$56*100,"")
A57: Leasingforpligtelser (kortfristet) | B57: ='balance_raw_32931499'!$B$34 | C57: ='balance_raw_32931499'!$C$34 | D57: ='balance_raw_32931499'!$D$34 | E57: ='balance_raw_32931499'!$E$34 | F57: ='balance_raw_32931499'!$F$34 | H57: =IFERROR(B57/$B$57*100,"") | I57: =IFERROR(C57/$B$57*100,"") | J57: =IFERROR(D57/$B$57*100,"") | K57: =IFERROR(E57/$B$57*100,"") | L57: =IFERROR(F57/$B$57*100,"")
A58: Leverandører af varer og tjenesteydelser | B58: ='balance_raw_32931499'!$B$35 | C58: ='balance_raw_32931499'!$C$35 | D58: ='balance_raw_32931499'!$D$35 | E58: ='balance_raw_32931499'!$E$35 | F58: ='balance_raw_32931499'!$F$35 | H58: =IFERROR(B58/$B$58*100,"") | I58: =IFERROR(C58/$B$58*100,"") | J58: =IFERROR(D58/$B$58*100,"") | K58: =IFERROR(E58/$B$58*100,"") | L58: =IFERROR(F58/$B$58*100,"")
A59: Gæld til tilknyttede virksomheder | B59: ='balance_raw_32931499'!$B$36 | C59: ='balance_raw_32931499'!$C$36 | D59: ='balance_raw_32931499'!$D$36 | E59: ='balance_raw_32931499'!$E$36 | F59: ='balance_raw_32931499'!$F$36 | H59: =IFERROR(B59/$B$59*100,"") | I59: =IFERROR(C59/$B$59*100,"") | J59: =IFERROR(D59/$B$59*100,"") | K59: =IFERROR(E59/$B$59*100,"") | L59: =IFERROR(F59/$B$59*100,"")
A60: Gæld til selskabsdeltagere og ledelse | B60: ='balance_raw_32931499'!$B$37 | C60: ='balance_raw_32931499'!$C$37 | D60: ='balance_raw_32931499'!$D$37 | E60: ='balance_raw_32931499'!$E$37 | F60: ='balance_raw_32931499'!$F$37 | H60: =IFERROR(B60/$B$60*100,"") | I60: =IFERROR(C60/$B$60*100,"") | J60: =IFERROR(D60/$B$60*100,"") | K60: =IFERROR(E60/$B$60*100,"") | L60: =IFERROR(F60/$B$60*100,"")
A61: Selskabsskat | B61: ='balance_raw_32931499'!$B$38 | C61: ='balance_raw_32931499'!$C$38 | D61: ='balance_raw_32931499'!$D$38 | E61: ='balance_raw_32931499'!$E$38 | F61: ='balance_raw_32931499'!$F$38 | H61: =IFERROR(B61/$B$61*100,"") | I61: =IFERROR(C61/$B$61*100,"") | J61: =IFERROR(D61/$B$61*100,"") | K61: =IFERROR(E61/$B$61*100,"") | L61: =IFERROR(F61/$B$61*100,"")
A62: Gæld til tilknyttede virksomheder vedr. selskabsskat | B62: ='balance_raw_32931499'!$B$39 | C62: ='balance_raw_32931499'!$C$39 | D62: ='balance_raw_32931499'!$D$39 | E62: ='balance_raw_32931499'!$E$39 | F62: ='balance_raw_32931499'!$F$39 | H62: =IFERROR(B62/$B$62*100,"") | I62: =IFERROR(C62/$B$62*100,"") | J62: =IFERROR(D62/$B$62*100,"") | K62: =IFERROR(E62/$B$62*100,"") | L62: =IFERROR(F62/$B$62*100,"")
A63: Anden gæld (kortfristet) | B63: ='balance_raw_32931499'!$B$40 | C63: ='balance_raw_32931499'!$C$40 | D63: ='balance_raw_32931499'!$D$40 | E63: ='balance_raw_32931499'!$E$40 | F63: ='balance_raw_32931499'!$F$40 | H63: =IFERROR(B63/$B$63*100,"") | I63: =IFERROR(C63/$B$63*100,"") | J63: =IFERROR(D63/$B$63*100,"") | K63: =IFERROR(E63/$B$63*100,"") | L63: =IFERROR(F63/$B$63*100,"")
A64: Periodeafgrænsningsposter (passiver) | B64: ='balance_raw_32931499'!$B$41 | C64: ='balance_raw_32931499'!$C$41 | D64: ='balance_raw_32931499'!$D$41 | E64: ='balance_raw_32931499'!$E$41 | F64: ='balance_raw_32931499'!$F$41 | H64: =IFERROR(B64/$B$64*100,"") | I64: =IFERROR(C64/$B$64*100,"") | J64: =IFERROR(D64/$B$64*100,"") | K64: =IFERROR(E64/$B$64*100,"") | L64: =IFERROR(F64/$B$64*100,"")
A65: Kortfristede gældsforpligtelser | B65: ='balance_raw_32931499'!$B$42 | C65: ='balance_raw_32931499'!$C$42 | D65: ='balance_raw_32931499'!$D$42 | E65: ='balance_raw_32931499'!$E$42 | F65: ='balance_raw_32931499'!$F$42 | H65: =IFERROR(B65/$B$65*100,"") | I65: =IFERROR(C65/$B$65*100,"") | J65: =IFERROR(D65/$B$65*100,"") | K65: =IFERROR(E65/$B$65*100,"") | L65: =IFERROR(F65/$B$65*100,"")
A66: Gældsforpligtelser | B66: ='balance_raw_32931499'!$B$43 | C66: ='balance_raw_32931499'!$C$43 | D66: ='balance_raw_32931499'!$D$43 | E66: ='balance_raw_32931499'!$E$43 | F66: ='balance_raw_32931499'!$F$43 | H66: =IFERROR(B66/$B$66*100,"") | I66: =IFERROR(C66/$B$66*100,"") | J66: =IFERROR(D66/$B$66*100,"") | K66: =IFERROR(E66/$B$66*100,"") | L66: =IFERROR(F66/$B$66*100,"")
A67: Passiver | B67: ='balance_raw_32931499'!$B$44 | C67: ='balance_raw_32931499'!$C$44 | D67: ='balance_raw_32931499'!$D$44 | E67: ='balance_raw_32931499'!$E$44 | F67: ='balance_raw_32931499'!$F$44 | H67: =IFERROR(B67/$B$67*100,"") | I67: =IFERROR(C67/$B$67*100,"") | J67: =IFERROR(D67/$B$67*100,"") | K67: =IFERROR(E67/$B$67*100,"") | L67: =IFERROR(F67/$B$67*100,"")
A69: NØGLEOPLYSNINGER | B69: 2021 | C69: 2022 | D69: 2023 | E69: 2024 | F69: 2025
A70: Gns. antal medarbejdere | B70: ='res_raw_32931499'!$B$19 | C70: ='res_raw_32931499'!$C$19 | D70: ='res_raw_32931499'!$D$19 | E70: ='res_raw_32931499'!$E$19 | F70: ='res_raw_32931499'!$F$19 | H70: =IFERROR(B70/$B$70*100,"") | I70: =IFERROR(C70/$B$70*100,"") | J70: =IFERROR(D70/$B$70*100,"") | K70: =IFERROR(E70/$B$70*100,"") | L70: =IFERROR(F70/$B$70*100,"")
A71: Investering i materielle anlægsaktiver | B71: ='res_raw_32931499'!$B$20 | C71: ='res_raw_32931499'!$C$20 | D71: ='res_raw_32931499'!$D$20 | E71: ='res_raw_32931499'!$E$20 | F71: ='res_raw_32931499'!$F$20 | H71: =IFERROR(B71/$B$71*100,"") | I71: =IFERROR(C71/$B$71*100,"") | J71: =IFERROR(D71/$B$71*100,"") | K71: =IFERROR(E71/$B$71*100,"") | L71: =IFERROR(F71/$B$71*100,"")
A73: NØGLETAL | B73: 2021 | C73: 2022 | D73: 2023 | E73: 2024 | F73: 2025
A74: Afkastningsgrad, % | B74: =IFERROR(($B$13+$B$15+$B$14)/$B$41*100,"") | C74: =IFERROR(($C$13+$C$15+$C$14)/$C$41*100,"") | D74: =IFERROR(($D$13+$D$15+$D$14)/$D$41*100,"") | E74: =IFERROR(($E$13+$E$15+$E$14)/$E$41*100,"") | F74: =IFERROR(($F$13+$F$15+$F$14)/$F$41*100,"")
A75: Overskudsgrad, % | B75: =IFERROR(($B$13+$B$15+$B$14)/$B$4*100,"") | C75: =IFERROR(($C$13+$C$15+$C$14)/$C$4*100,"") | D75: =IFERROR(($D$13+$D$15+$D$14)/$D$4*100,"") | E75: =IFERROR(($E$13+$E$15+$E$14)/$E$4*100,"") | F75: =IFERROR(($F$13+$F$15+$F$14)/$F$4*100,"")
A76: Aktivernes omsætningshastighed, gange | B76: =IFERROR($B$4/$B$41,"") | C76: =IFERROR($C$4/$C$41,"") | D76: =IFERROR($D$4/$D$41,"") | E76: =IFERROR($E$4/$E$41,"") | F76: =IFERROR($F$4/$F$41,"")
A77: Egenkapitalens forrentning, % | B77: =IFERROR($B$18/$B$50*100,"") | C77: =IFERROR($C$18/$C$50*100,"") | D77: =IFERROR($D$18/$D$50*100,"") | E77: =IFERROR($E$18/$E$50*100,"") | F77: =IFERROR($F$18/$F$50*100,"")
A78: Gældsrente, % | B78: =IFERROR($B$16/($B$67-$B$50)*100,"") | C78: =IFERROR($C$16/($C$67-$C$50)*100,"") | D78: =IFERROR($D$16/($D$67-$D$50)*100,"") | E78: =IFERROR($E$16/($E$67-$E$50)*100,"") | F78: =IFERROR($F$16/($F$67-$F$50)*100,"")
A79: Soliditetsgrad, % | B79: =IFERROR($B$50/$B$41*100,"") | C79: =IFERROR($C$50/$C$41*100,"") | D79: =IFERROR($D$50/$D$41*100,"") | E79: =IFERROR($E$50/$E$41*100,"") | F79: =IFERROR($F$50/$F$41*100,"")
A80: Gearing | B80: =IFERROR(($B$67-$B$50)/$B$50,"") | C80: =IFERROR(($C$67-$C$50)/$C$50,"") | D80: =IFERROR(($D$67-$D$50)/$D$50,"") | E80: =IFERROR(($E$67-$E$50)/$E$50,"") | F80: =IFERROR(($F$67-$F$50)/$F$50,"")
A81: Likviditetsgrad, % | B81: =IFERROR($B$40/$B$65*100,"") | C81: =IFERROR($C$40/$C$65*100,"") | D81: =IFERROR($D$40/$D$65*100,"") | E81: =IFERROR($E$40/$E$65*100,"") | F81: =IFERROR($F$40/$F$65*100,"")
A82: Rentemarginal, % | B82: =IFERROR(B74-B78,"") | C82: =IFERROR(C74-C78,"") | D82: =IFERROR(D74-D78,"") | E82: =IFERROR(E74-E78,"") | F82: =IFERROR(F74-F78,"")
A83: Gældsandel, % | B83: =IFERROR(($B$67-$B$50)/$B$41*100,"") | C83: =IFERROR(($C$67-$C$50)/$C$41*100,"") | D83: =IFERROR(($D$67-$D$50)/$D$41*100,"") | E83: =IFERROR(($E$67-$E$50)/$E$41*100,"") | F83: =IFERROR(($F$67-$F$50)/$F$41*100,"")
A84: Kapitalbindingsgrad, % | B84: =IFERROR($B$29/($B$50+$B$53)*100,"") | C84: =IFERROR($C$29/($C$50+$C$53)*100,"") | D84: =IFERROR($D$29/($D$50+$D$53)*100,"") | E84: =IFERROR($E$29/($E$50+$E$53)*100,"") | F84: =IFERROR($F$29/($F$50+$F$53)*100,"")
A86: Pengestrømsopgørelse ikke offentliggjort (jf. koncernfritagelse, ÅRL §86, stk. 4)

Sheet res_raw_32931499
A1: Sunweb Group Scandinavia A/S (CVR 32931499) — Resultatopgørelse & nøgleoplysninger (t.kr.) | B1: 2021 | C1: 2022 | D1: 2023 | E1: 2024 | F1: 2025
A2: Nettoomsætning
A3: Andre driftsindtægter
A4: Vareforbrug
A5: Andre eksterne omkostninger
A6: Bruttoresultat | B6: 12322 | C6: 19587 | D6: 24223 | E6: 30278 | F6: 22885
A7: Personaleomkostninger | B7: 7044 | C7: 8383 | D7: 10904 | E7: 11593 | F7: 15782
A8: Resultat før afskrivninger
A9: Af- og nedskrivninger | B9: 0 | C9: 0 | D9: 12 | E9: 32 | F9: 35
A10: Andre driftsomkostninger | C10: 0 | D10: 15 | E10: 0
A11: Resultat af primær drift | B11: 5279 | C11: 11204 | D11: 13292 | E11: 18653 | F11: 7067
A12: Indtægter af kapitalandele, dattervirksomheder
A13: Finansielle indtægter | B13: 145 | C13: 601 | D13: 3158 | E13: 6033 | F13: 1418
A14: Finansielle omkostninger | B14: 2806 | C14: 3471 | D14: 3778 | E14: 5803 | F14: 5619
A15: Finansielle poster, netto
A16: Resultat før skat | B16: 2600 | C16: 8334 | D16: 12583 | E16: 18877 | F16: 2866
A17: Skat af årets resultat | B17: 103 | C17: 1883 | D17: 2757 | E17: 4177 | F17: 650
A18: Årets resultat | B18: 2497 | C18: 6451 | D18: 9826 | E18: 14699 | F18: 2216
A19: Gns. antal medarbejdere | B19: 18 | C19: 23 | D19: 30 | E19: 35 | F19: 36
A20: Investering i materielle anlægsaktiver

Sheet balance_raw_32931499
A1: Sunweb Group Scandinavia A/S (CVR 32931499) — Balance (t.kr.) | B1: 2021 | C1: 2022 | D1: 2023 | E1: 2024 | F1: 2025
A2: Grunde og bygninger
A3: Produktionsanlæg og maskiner
A4: Driftsmateriel og inventar | B4: 0 | C4: 0 | D4: 139 | E4: 116 | F4: 81
A5: Indretning af lejede lokaler
A6: Forudbetaling og anlægsaktiver under opførelse
A7: Materielle anlægsaktiver | B7: 0 | C7: 0 | D7: 139 | E7: 116 | F7: 81
A8: Anlægsaktiver | B8: 0 | C8: 0 | D8: 139 | E8: 116 | F8: 81
A9: Tilgodehavender fra salg og tjenesteydelser | B9: 0 | D9: 0 | E9: 0
A10: Tilgodehavender hos tilknyttede virksomheder | B10: 55552 | C10: 55804 | D10: 62007 | E10: 64981 | F10: 29399
A11: Andre tilgodehavender | B11: 1046 | C11: 1346 | D11: 1195 | E11: 2419 | F11: 3109
A12: Periodeafgrænsningsposter (aktiver) | B12: 39 | C12: 118 | D12: 70 | E12: 35 | F12: 6597
A13: Udskudt skatteaktiv | B13: 6 | C13: 0 | D13: 6 | E13: 0
A14: Tilgodehavende skat hos tilknyttede virksomheder
A15: Kortfristede skattetilgodehavender
A16: Tilgodehavender | B16: 56643 | C16: 57268 | D16: 63278 | E16: 67435 | F16: 39105
A17: Værdipapirer
A18: Likvide beholdninger | B18: 8284 | C18: 6280 | D18: 4989 | E18: 2677 | F18: 1352
A19: Omsætningsaktiver | B19: 64927 | C19: 63548 | D19: 68267 | E19: 70111 | F19: 40457
A20: Aktiver | B20: 64927 | C20: 63548 | D20: 68406 | E20: 70228 | F20: 40538
A21: Selskabskapital | B21: 500 | C21: 500 | D21: 500 | E21: 500 | F21: 500
A22: Reserve for nettoopskrivning (indre værdis metode)
A23: Reserve for udviklingsomkostninger
A24: Reserve for sikringstransaktioner
A25: Andre reserver
A26: Overført resultat | B26: 30770 | C26: 37221 | D26: 47047 | E26: 1746 | F26: 3962
A27: Egenkapital i alt | B27: 31270 | C27: 37721 | D27: 47547 | E27: 62246 | F27: 4462
A28: Hensættelse til udskudt skat | D28: 0 | E28: 5 | F28: 3
A29: Hensatte forpligtelser | B29: 0 | D29: 0 | E29: 5 | F29: 231
A30: Langfristede gældsforpligtelser | B30: 0 | C30: 1473 | D30: 2467 | E30: 3856 | F30: 259
A31: Ansvarlig lånekapital (kortfristet)
A32: Kortfristet del af langfristede gældsforpligtelser
A33: Kreditinstitutter | B33: 274 | C33: 18620 | F33: 16
A34: Leasingforpligtelser (kortfristet)
A35: Leverandører af varer og tjenesteydelser | B35: 49 | C35: 535 | D35: 1155 | E35: 140 | F35: 139
A36: Gæld til tilknyttede virksomheder | B36: 30338 | C36: 4223 | D36: 12530 | E36: 2541 | F36: 34678
A37: Gæld til selskabsdeltagere og ledelse
A38: Selskabsskat | B38: 1284 | C38: 0 | D38: 1069 | E38: 0 | F38: 38
A39: Gæld til tilknyttede virksomheder vedr. selskabsskat
A40: Anden gæld (kortfristet) | B40: 1631 | C40: 900 | D40: 3566 | E40: 1240 | F40: 715
A41: Periodeafgrænsningsposter (passiver) | B41: 81 | C41: 76 | D41: 0 | E41: 170 | F41: 0
A42: Kortfristede gældsforpligtelser | B42: 33656 | C42: 24354 | D42: 18392 | E42: 4120 | F42: 35586
A43: Gældsforpligtelser | B43: 33656 | C43: 25827 | D43: 20859 | E43: 7976 | F43: 35845
A44: Passiver | B44: 64927 | C44: 63548 | D44: 68406 | E44: 70228 | F44: 40538

Sheet Simpel_arts
A1: Sunweb Group Scandinavia A/S (CVR 32931499) — Regnskabs- og nøgletal (CVR: 32931499) — artsopdelt
A3: Beløb i 1.000 kr. | B3: 2025 | C3: 2024 | D3: 2023 | F3: Note / XBRL-felt
A4: Uddrag af resultatopgørelse
A5: Nettoomsætning | B5: ='res_raw_32931499'!$F$2 | C5: ='res_raw_32931499'!$E$2 | D5: ='res_raw_32931499'!$D$2 | F5: fsa:Revenue
A6: Andre driftsindtægter | B6: ='res_raw_32931499'!$F$3 | C6: ='res_raw_32931499'!$E$3 | D6: ='res_raw_32931499'!$D$3 | F6: fsa:OtherOperatingIncome. Indtægter fra sekundære aktiviteter (huslejeindtægter, avance ved salg af anlæg mv.).
A7: Vareforbrug | B7: =-'res_raw_32931499'!$F$4 | C7: =-'res_raw_32931499'!$E$4 | D7: =-'res_raw_32931499'!$D$4 | F7: fsa:CostOfSales (vises negativt for korrekt SUM-formel).
A8: Andre eksterne omk. mv. | B8: =-'res_raw_32931499'!$F$5 | C8: =-'res_raw_32931499'!$E$5 | D8: =-'res_raw_32931499'!$D$5 | F8: fsa:OtherExternalExpenses (vises negativt). Husleje, energi, kontorhold mv.
A9: Bruttofortjeneste | B9: =SUM(B5:B8) | C9: =SUM(C5:C8) | D9: =SUM(D5:D8) | F9: Beregnet: Nettoomsætning + Andre driftsindt. − Vareforbrug − Andre ext. omk.
A10: Personaleomkostninger | B10: =-'res_raw_32931499'!$F$7 | C10: =-'res_raw_32931499'!$E$7 | D10: =-'res_raw_32931499'!$D$7 | F10: fsa:EmployeeBenefitsExpense (vises negativt). Lønninger, pension, sociale ydelser.
A11: Af- og nedskrivninger | B11: =-'res_raw_32931499'!$F$9 | C11: =-'res_raw_32931499'!$E$9 | D11: =-'res_raw_32931499'!$D$9 | F11: fsa:Depreciation (vises negativt). Af- og nedskrivninger på materielle og immaterielle anlægsaktiver.
A12: Andre driftsomkostninger | B12: =-'res_raw_32931499'!$F$10 | C12: =-'res_raw_32931499'!$E$10 | D12: =-'res_raw_32931499'!$D$10 | F12: fsa:OtherOperatingExpenses (vises negativt). Typisk 0 eller meget lille post.
A13: Resultat af primær drift | B13: =SUM(B9:B12) | C13: =SUM(C9:C12) | D13: =SUM(D9:D12) | F13: Beregnet: Bruttofortjeneste − Personaleomk. − Af- og nedskrivninger − Andre driftsomk. EBIT.
A14: Finansielle indtægter mv. | B14: =N('res_raw_32931499'!$F$12)+N('res_raw_32931499'!$F$13) | C14: =N('res_raw_32931499'!$E$12)+N('res_raw_32931499'!$E$13) | D14: =N('res_raw_32931499'!$D$12)+N('res_raw_32931499'!$D$13) | F14: fsa:IncomeFromSubsidiaries + fsa:OtherFinanceIncome.
A15: Finansielle omkostninger mv. | B15: =-'res_raw_32931499'!$F$14 | C15: =-'res_raw_32931499'!$E$14 | D15: =-'res_raw_32931499'!$D$14 | F15: fsa:OtherFinanceExpenses (vises negativt). Renteomkostninger, kurstab mv.
A16: Resultat før skat | B16: =SUM(B13:B15) | C16: =SUM(C13:C15) | D16: =SUM(D13:D15) | F16: Beregnet: EBIT + Fin. indtægter + Fin. omk. EBT.
A18: Uddrag af balance
A19: Anlægsaktiver | B19: ='balance_raw_32931499'!$F$8 | C19: ='balance_raw_32931499'!$E$8 | D19: ='balance_raw_32931499'!$D$8 | F19: fsa:NoncurrentAssets. Materielle, immaterielle og finansielle anlægsaktiver.
A20: Omsætningsaktiver | B20: ='balance_raw_32931499'!$F$19 | C20: ='balance_raw_32931499'!$E$19 | D20: ='balance_raw_32931499'!$D$19 | F20: fsa:CurrentAssets. Varebeholdninger, tilgodehavender, likvider.
A21: Aktiver i alt | B21: =SUM(B19:B20) | C21: =SUM(C19:C20) | D21: =SUM(D19:D20) | F21: Beregnet: Anlægsaktiver + Omsætningsaktiver. Bør matche fsa:Assets.
A23: Egenkapital | B23: ='balance_raw_32931499'!$F$27 | C23: ='balance_raw_32931499'!$E$27 | D23: ='balance_raw_32931499'!$D$27 | F23: fsa:Equity. Selskabskapital, overført resultat, reserver.
A24: Forpligtelser | B24: ='balance_raw_32931499'!$F$44-'balance_raw_32931499'!$F$27 | C24: ='balance_raw_32931499'!$E$44-'balance_raw_32931499'!$E$27 | D24: ='balance_raw_32931499'!$D$44-'balance_raw_32931499'!$D$27 | F24: Beregnet: Passiver (fsa:LiabilitiesAndEquity) − Egenkapital. Hensættelser + kort- og langfristet gæld.
A25: Passiver i alt | B25: =SUM(B23:B24) | C25: =SUM(C23:C24) | D25: =SUM(D23:D24) | F25: Beregnet: Egenkapital + Forpligtelser. Bør matche Aktiver i alt.
A27: Udvalgte balanceposter
A28: Varebeholdninger | F28: fsa:Inventories (eller fsa:ManufacturedGoodsAndGoodsForResale hvis total mangler).
A29: Tilgodehavender fra salg | B29: ='balance_raw_32931499'!$F$9 | C29: ='balance_raw_32931499'!$E$9 | D29: ='balance_raw_32931499'!$D$9 | F29: fsa:ShorttermTradeReceivables. Kortfristede tilgodehavender fra kunder.
A30: Kortfristede gældsforpligtelser | B30: ='balance_raw_32931499'!$F$42 | C30: ='balance_raw_32931499'!$E$42 | D30: ='balance_raw_32931499'!$D$42 | F30: fsa:ShorttermLiabilitiesOtherThanProvisions. Gæld der forfalder inden for 1 år.
A32: Rentabilitet
A33: Afkastningsgrad, % | B33: =IFERROR((B13+B14)/B21*100,"") | C33: =IFERROR((C13+C14)/C21*100,"") | D33: =IFERROR((D13+D14)/D21*100,"")
A34: Overskudsgrad, % | B34: =IFERROR((B13+B14)/B5*100,"") | C34: =IFERROR((C13+C14)/C5*100,"") | D34: =IFERROR((D13+D14)/D5*100,"")
A35: Aktivernes omsætningshastighed, gange | B35: =IFERROR(B5/B21,"") | C35: =IFERROR(C5/C21,"") | D35: =IFERROR(D5/D21,"")
A36: Gældsrente, % | B36: =IFERROR(-B15*100/B24,"") | C36: =IFERROR(-C15*100/C24,"") | D36: =IFERROR(-D15*100/D24,"")
A37: Egenkapitalens forrentning, % | B37: =IFERROR(B16/B23*100,"") | C37: =IFERROR(C16/C23*100,"") | D37: =IFERROR(D16/D23*100,"")
A38: Gearing, gange | B38: =IFERROR(B24/B23,"") | C38: =IFERROR(C24/C23,"") | D38: =IFERROR(D24/D23,"")
A40: Indekstal for indtjeningsevne (2023=100)
A41: Nettoomsætning | B41: =IFERROR(B5/$D5*100,"") | C41: =IFERROR(C5/$D5*100,"") | D41: =IFERROR(D5/$D5*100,"")
A42: Vareforbrug | B42: =IFERROR(B7/$D7*100,"") | C42: =IFERROR(C7/$D7*100,"") | D42: =IFERROR(D7/$D7*100,"")
A43: Andre eksterne omk. | B43: =IFERROR(B8/$D8*100,"") | C43: =IFERROR(C8/$D8*100,"") | D43: =IFERROR(D8/$D8*100,"")
A44: Personaleomkostninger | B44: =IFERROR(B10/$D10*100,"") | C44: =IFERROR(C10/$D10*100,"") | D44: =IFERROR(D10/$D10*100,"")
A45: Af- og nedskrivninger | B45: =IFERROR(B11/$D11*100,"") | C45: =IFERROR(C11/$D11*100,"") | D45: =IFERROR(D11/$D11*100,"")
A47: Indekstal for kapitaltilpasningsevne (2023=100)
A48: Nettoomsætning | B48: =IFERROR(B5*100/$D5,"") | C48: =IFERROR(C5*100/$D5,"") | D48: =IFERROR(D5*100/$D5,"")
A49: Anlægsaktiver | B49: =IFERROR(B19*100/$D19,"") | C49: =IFERROR(C19*100/$D19,"") | D49: =IFERROR(D19*100/$D19,"")
A50: Varebeholdninger | B50: =IFERROR(B28*100/$D28,"") | C50: =IFERROR(C28*100/$D28,"") | D50: =IFERROR(D28*100/$D28,"")
A51: Tilgodehavender fra salg | B51: =IFERROR(B29*100/$D29,"") | C51: =IFERROR(C29*100/$D29,"") | D51: =IFERROR(D29*100/$D29,"")
A53: Soliditet og likviditet
A54: Soliditetsgrad, % | B54: =IFERROR(B23*100/B21,"") | C54: =IFERROR(C23*100/C21,"") | D54: =IFERROR(D23*100/D21,"")
A55: Gældsandel, % | B55: =IFERROR(B24*100/B21,"") | C55: =IFERROR(C24*100/C21,"") | D55: =IFERROR(D24*100/D21,"")
A56: Likviditetsgrad, % | B56: =IFERROR(B20*100/B30,"") | C56: =IFERROR(C20*100/C30,"") | D56: =IFERROR(D20*100/D30,"")
A58: Kilde: Bearbejdet uddrag af årsrapporter for 2023-2025. Alle dataceller er live formler der peger på res_raw / balance_raw.
A60: Krydstjek mod rådata (tolerance: 1 t.kr.)
A61: Aktiver i alt = fsa:Assets | B61: =IF('balance_raw_32931499'!$F$20="","—",IF(ABS(B21-'balance_raw_32931499'!$F$20)<=1,"✓ OK","❌ "&TEXT(B21-'balance_raw_32931499'!$F$20,"+#,##0;-#,##0")&" t.kr.")) | C61: =IF('balance_raw_32931499'!$E$20="","—",IF(ABS(C21-'balance_raw_32931499'!$E$20)<=1,"✓ OK","❌ "&TEXT(C21-'balance_raw_32931499'!$E$20,"+#,##0;-#,##0")&" t.kr.")) | D61: =IF('balance_raw_32931499'!$D$20="","—",IF(ABS(D21-'balance_raw_32931499'!$D$20)<=1,"✓ OK","❌ "&TEXT(D21-'balance_raw_32931499'!$D$20,"+#,##0;-#,##0")&" t.kr.")) | F61: Verificerer at sum(Anlæg+Omsætning) matcher Assets-totalen.
A62: Passiver i alt = fsa:LiabilitiesAndEquity | B62: =IF('balance_raw_32931499'!$F$44="","—",IF(ABS(B25-'balance_raw_32931499'!$F$44)<=1,"✓ OK","❌ "&TEXT(B25-'balance_raw_32931499'!$F$44,"+#,##0;-#,##0")&" t.kr.")) | C62: =IF('balance_raw_32931499'!$E$44="","—",IF(ABS(C25-'balance_raw_32931499'!$E$44)<=1,"✓ OK","❌ "&TEXT(C25-'balance_raw_32931499'!$E$44,"+#,##0;-#,##0")&" t.kr.")) | D62: =IF('balance_raw_32931499'!$D$44="","—",IF(ABS(D25-'balance_raw_32931499'!$D$44)<=1,"✓ OK","❌ "&TEXT(D25-'balance_raw_32931499'!$D$44,"+#,##0;-#,##0")&" t.kr.")) | F62: Verificerer at sum(EK+Forpligtelser) matcher Passiver-totalen.
A63: Aktiver i alt = Passiver i alt | B63: =IF(ABS(B21-B25)<=1,"✓ OK","❌ "&TEXT(B21-B25,"+#,##0;-#,##0")&" t.kr.") | C63: =IF(ABS(C21-C25)<=1,"✓ OK","❌ "&TEXT(C21-C25,"+#,##0;-#,##0")&" t.kr.") | D63: =IF(ABS(D21-D25)<=1,"✓ OK","❌ "&TEXT(D21-D25,"+#,##0;-#,##0")&" t.kr.") | F63: Balance-identitet på arket selv. Skal altid være 0 differance.
A64: Bruttoresultat (beregnet) = fsa:GrossResult | B64: =IF('res_raw_32931499'!$F$6="","—",IF(ABS(B9-'res_raw_32931499'!$F$6)<=1,"✓ OK","❌ "&TEXT(B9-'res_raw_32931499'!$F$6,"+#,##0;-#,##0")&" t.kr.")) | C64: =IF('res_raw_32931499'!$E$6="","—",IF(ABS(C9-'res_raw_32931499'!$E$6)<=1,"✓ OK","❌ "&TEXT(C9-'res_raw_32931499'!$E$6,"+#,##0;-#,##0")&" t.kr.")) | D64: =IF('res_raw_32931499'!$D$6="","—",IF(ABS(D9-'res_raw_32931499'!$D$6)<=1,"✓ OK","❌ "&TEXT(D9-'res_raw_32931499'!$D$6,"+#,##0;-#,##0")&" t.kr.")) | F64: Hvis Nettoomsætning eller omkostninger mangler, vil sumberegnet bruttoresultat afvige.
A65: EBIT (beregnet) = fsa:ProfitLossFromOrdinaryOperatingActivities | B65: =IF('res_raw_32931499'!$F$11="","—",IF(ABS(B13-'res_raw_32931499'!$F$11)<=1,"✓ OK","❌ "&TEXT(B13-'res_raw_32931499'!$F$11,"+#,##0;-#,##0")&" t.kr.")) | C65: =IF('res_raw_32931499'!$E$11="","—",IF(ABS(C13-'res_raw_32931499'!$E$11)<=1,"✓ OK","❌ "&TEXT(C13-'res_raw_32931499'!$E$11,"+#,##0;-#,##0")&" t.kr.")) | D65: =IF('res_raw_32931499'!$D$11="","—",IF(ABS(D13-'res_raw_32931499'!$D$11)<=1,"✓ OK","❌ "&TEXT(D13-'res_raw_32931499'!$D$11,"+#,##0;-#,##0")&" t.kr.")) | F65: Verificerer at sumberegnet EBIT matcher det rapporterede.
A66: EBT (beregnet) = fsa:ProfitLossFromOrdinaryActivitiesBeforeTax | B66: =IF('res_raw_32931499'!$F$16="","—",IF(ABS(B16-'res_raw_32931499'!$F$16)<=1,"✓ OK","❌ "&TEXT(B16-'res_raw_32931499'!$F$16,"+#,##0;-#,##0")&" t.kr.")) | C66: =IF('res_raw_32931499'!$E$16="","—",IF(ABS(C16-'res_raw_32931499'!$E$16)<=1,"✓ OK","❌ "&TEXT(C16-'res_raw_32931499'!$E$16,"+#,##0;-#,##0")&" t.kr.")) | D66: =IF('res_raw_32931499'!$D$16="","—",IF(ABS(D16-'res_raw_32931499'!$D$16)<=1,"✓ OK","❌ "&TEXT(D16-'res_raw_32931499'!$D$16,"+#,##0;-#,##0")&" t.kr.")) | F66: Verificerer at sumberegnet resultat før skat matcher det rapporterede.

Sheet Noter_info
A1: Sunweb Group Scandinavia A/S (CVR 32931499) — Ukendte XBRL-felter — disse er noter og ikke en del af hoved-regnskabet
A2: Kategori | B2: Dansk navn | C2: XBRL feltnavn | D2: 2021 t.kr. | E2: 2022 t.kr. | F2: 2023 t.kr. | G2: 2024 t.kr. | H2: 2025 t.kr. | I2: Forklaring
A3: Øvrige (ukendt) | B3: fsa:FinanceExpensesArisingFromGroupEnterprises | C3: fsa:FinanceExpensesArisingFromGroupEnterprises | D3: 17 | E3: 0 | F3: 89 | G3: 6 | I3: Ingen forklaring tilgængelig.
A4: Øvrige (ukendt) | B4: fsa:LongtermTaxPayables | C4: fsa:LongtermTaxPayables | D4: 0 | E4: 1473 | F4: 2467 | G4: 3856 | H4: 259 | I4: Ingen forklaring tilgængelig.
