Workbook

Sheet Overblik_47458714
A1: LEGO System A/S (CVR 47458714) — Regnskabsanalyse – Resultatopgørelse & Balance (t.kr.) · Klasse C-stor · Revision
H2: Indekstal (2021=100)
A3: Resultatopgørelse t.kr. | B3: 2021 | C3: 2022 | D3: 2023 | E3: 2024 | F3: 2025 | H3: 2021 | I3: 2022 | J3: 2023 | K3: 2024 | L3: 2025
A4: Nettoomsætning | B4: ='res_raw_47458714'!$B$2 | C4: ='res_raw_47458714'!$C$2 | D4: ='res_raw_47458714'!$D$2 | E4: ='res_raw_47458714'!$E$2 | F4: ='res_raw_47458714'!$F$2 | H4: =IFERROR(B4/$B$4*100,"") | I4: =IFERROR(C4/$B$4*100,"") | J4: =IFERROR(D4/$B$4*100,"") | K4: =IFERROR(E4/$B$4*100,"") | L4: =IFERROR(F4/$B$4*100,"")
A5: Produktionsomkostninger | B5: ='res_raw_47458714'!$B$3 | C5: ='res_raw_47458714'!$C$3 | D5: ='res_raw_47458714'!$D$3 | E5: ='res_raw_47458714'!$E$3 | F5: ='res_raw_47458714'!$F$3 | H5: =IFERROR(B5/$B$5*100,"") | I5: =IFERROR(C5/$B$5*100,"") | J5: =IFERROR(D5/$B$5*100,"") | K5: =IFERROR(E5/$B$5*100,"") | L5: =IFERROR(F5/$B$5*100,"")
A6: Bruttoresultat | B6: ='res_raw_47458714'!$B$4 | C6: ='res_raw_47458714'!$C$4 | D6: ='res_raw_47458714'!$D$4 | E6: ='res_raw_47458714'!$E$4 | F6: ='res_raw_47458714'!$F$4 | H6: =IFERROR(B6/$B$6*100,"") | I6: =IFERROR(C6/$B$6*100,"") | J6: =IFERROR(D6/$B$6*100,"") | K6: =IFERROR(E6/$B$6*100,"") | L6: =IFERROR(F6/$B$6*100,"")
A7: Salgs- og distributionsomkostninger | B7: ='res_raw_47458714'!$B$5 | C7: ='res_raw_47458714'!$C$5 | D7: ='res_raw_47458714'!$D$5 | E7: ='res_raw_47458714'!$E$5 | F7: ='res_raw_47458714'!$F$5 | H7: =IFERROR(B7/$B$7*100,"") | I7: =IFERROR(C7/$B$7*100,"") | J7: =IFERROR(D7/$B$7*100,"") | K7: =IFERROR(E7/$B$7*100,"") | L7: =IFERROR(F7/$B$7*100,"")
A8: Administrationsomkostninger | B8: ='res_raw_47458714'!$B$6 | C8: ='res_raw_47458714'!$C$6 | D8: ='res_raw_47458714'!$D$6 | E8: ='res_raw_47458714'!$E$6 | F8: ='res_raw_47458714'!$F$6 | H8: =IFERROR(B8/$B$8*100,"") | I8: =IFERROR(C8/$B$8*100,"") | J8: =IFERROR(D8/$B$8*100,"") | K8: =IFERROR(E8/$B$8*100,"") | L8: =IFERROR(F8/$B$8*100,"")
A9: Andre driftsindtægter | B9: ='res_raw_47458714'!$B$7 | C9: ='res_raw_47458714'!$C$7 | D9: ='res_raw_47458714'!$D$7 | E9: ='res_raw_47458714'!$E$7 | F9: ='res_raw_47458714'!$F$7 | H9: =IFERROR(B9/$B$9*100,"") | I9: =IFERROR(C9/$B$9*100,"") | J9: =IFERROR(D9/$B$9*100,"") | K9: =IFERROR(E9/$B$9*100,"") | L9: =IFERROR(F9/$B$9*100,"")
A10: Andre driftsomkostninger | B10: ='res_raw_47458714'!$B$8 | C10: ='res_raw_47458714'!$C$8 | D10: ='res_raw_47458714'!$D$8 | E10: ='res_raw_47458714'!$E$8 | F10: ='res_raw_47458714'!$F$8 | H10: =IFERROR(B10/$B$10*100,"") | I10: =IFERROR(C10/$B$10*100,"") | J10: =IFERROR(D10/$B$10*100,"") | K10: =IFERROR(E10/$B$10*100,"") | L10: =IFERROR(F10/$B$10*100,"")
A11: Resultat af primær drift | B11: ='res_raw_47458714'!$B$9 | C11: ='res_raw_47458714'!$C$9 | D11: ='res_raw_47458714'!$D$9 | E11: ='res_raw_47458714'!$E$9 | F11: ='res_raw_47458714'!$F$9 | H11: =IFERROR(B11/$B$11*100,"") | I11: =IFERROR(C11/$B$11*100,"") | J11: =IFERROR(D11/$B$11*100,"") | K11: =IFERROR(E11/$B$11*100,"") | L11: =IFERROR(F11/$B$11*100,"")
A12: Indtægter af kapitalandele, dattervirksomheder | B12: ='res_raw_47458714'!$B$10 | C12: ='res_raw_47458714'!$C$10 | D12: ='res_raw_47458714'!$D$10 | E12: ='res_raw_47458714'!$E$10 | F12: ='res_raw_47458714'!$F$10 | H12: =IFERROR(B12/$B$12*100,"") | I12: =IFERROR(C12/$B$12*100,"") | J12: =IFERROR(D12/$B$12*100,"") | K12: =IFERROR(E12/$B$12*100,"") | L12: =IFERROR(F12/$B$12*100,"")
A13: Finansielle indtægter | B13: ='res_raw_47458714'!$B$11 | C13: ='res_raw_47458714'!$C$11 | D13: ='res_raw_47458714'!$D$11 | E13: ='res_raw_47458714'!$E$11 | F13: ='res_raw_47458714'!$F$11 | H13: =IFERROR(B13/$B$13*100,"") | I13: =IFERROR(C13/$B$13*100,"") | J13: =IFERROR(D13/$B$13*100,"") | K13: =IFERROR(E13/$B$13*100,"") | L13: =IFERROR(F13/$B$13*100,"")
A14: Finansielle omkostninger | B14: ='res_raw_47458714'!$B$12 | C14: ='res_raw_47458714'!$C$12 | D14: ='res_raw_47458714'!$D$12 | E14: ='res_raw_47458714'!$E$12 | F14: ='res_raw_47458714'!$F$12 | H14: =IFERROR(B14/$B$14*100,"") | I14: =IFERROR(C14/$B$14*100,"") | J14: =IFERROR(D14/$B$14*100,"") | K14: =IFERROR(E14/$B$14*100,"") | L14: =IFERROR(F14/$B$14*100,"")
A15: Finansielle poster, netto | B15: ='res_raw_47458714'!$B$13 | C15: ='res_raw_47458714'!$C$13 | D15: ='res_raw_47458714'!$D$13 | E15: ='res_raw_47458714'!$E$13 | F15: ='res_raw_47458714'!$F$13 | H15: =IFERROR(B15/$B$15*100,"") | I15: =IFERROR(C15/$B$15*100,"") | J15: =IFERROR(D15/$B$15*100,"") | K15: =IFERROR(E15/$B$15*100,"") | L15: =IFERROR(F15/$B$15*100,"")
A16: Resultat før skat | B16: ='res_raw_47458714'!$B$14 | C16: ='res_raw_47458714'!$C$14 | D16: ='res_raw_47458714'!$D$14 | E16: ='res_raw_47458714'!$E$14 | F16: ='res_raw_47458714'!$F$14 | H16: =IFERROR(B16/$B$16*100,"") | I16: =IFERROR(C16/$B$16*100,"") | J16: =IFERROR(D16/$B$16*100,"") | K16: =IFERROR(E16/$B$16*100,"") | L16: =IFERROR(F16/$B$16*100,"")
A17: Skat af årets resultat | B17: ='res_raw_47458714'!$B$15 | C17: ='res_raw_47458714'!$C$15 | D17: ='res_raw_47458714'!$D$15 | E17: ='res_raw_47458714'!$E$15 | F17: ='res_raw_47458714'!$F$15 | H17: =IFERROR(B17/$B$17*100,"") | I17: =IFERROR(C17/$B$17*100,"") | J17: =IFERROR(D17/$B$17*100,"") | K17: =IFERROR(E17/$B$17*100,"") | L17: =IFERROR(F17/$B$17*100,"")
A18: Årets resultat | B18: ='res_raw_47458714'!$B$16 | C18: ='res_raw_47458714'!$C$16 | D18: ='res_raw_47458714'!$D$16 | E18: ='res_raw_47458714'!$E$16 | F18: ='res_raw_47458714'!$F$16 | H18: =IFERROR(B18/$B$18*100,"") | I18: =IFERROR(C18/$B$18*100,"") | J18: =IFERROR(D18/$B$18*100,"") | K18: =IFERROR(E18/$B$18*100,"") | L18: =IFERROR(F18/$B$18*100,"")
A20: AKTIVER t.kr. | B20: 2021 | C20: 2022 | D20: 2023 | E20: 2024 | F20: 2025 | H20: 2021 | I20: 2022 | J20: 2023 | K20: 2024 | L20: 2025
A21: Udviklingsprojekter | B21: ='balance_raw_47458714'!$B$2 | C21: ='balance_raw_47458714'!$C$2 | D21: ='balance_raw_47458714'!$D$2 | E21: ='balance_raw_47458714'!$E$2 | F21: ='balance_raw_47458714'!$F$2 | H21: =IFERROR(B21/$B$21*100,"") | I21: =IFERROR(C21/$B$21*100,"") | J21: =IFERROR(D21/$B$21*100,"") | K21: =IFERROR(E21/$B$21*100,"") | L21: =IFERROR(F21/$B$21*100,"")
A22: Patenter, varemærker mv. | B22: ='balance_raw_47458714'!$B$3 | C22: ='balance_raw_47458714'!$C$3 | D22: ='balance_raw_47458714'!$D$3 | E22: ='balance_raw_47458714'!$E$3 | F22: ='balance_raw_47458714'!$F$3 | H22: =IFERROR(B22/$B$22*100,"") | I22: =IFERROR(C22/$B$22*100,"") | J22: =IFERROR(D22/$B$22*100,"") | K22: =IFERROR(E22/$B$22*100,"") | L22: =IFERROR(F22/$B$22*100,"")
A23: Goodwill | B23: ='balance_raw_47458714'!$B$4 | C23: ='balance_raw_47458714'!$C$4 | D23: ='balance_raw_47458714'!$D$4 | E23: ='balance_raw_47458714'!$E$4 | F23: ='balance_raw_47458714'!$F$4 | H23: =IFERROR(B23/$B$23*100,"") | I23: =IFERROR(C23/$B$23*100,"") | J23: =IFERROR(D23/$B$23*100,"") | K23: =IFERROR(E23/$B$23*100,"") | L23: =IFERROR(F23/$B$23*100,"")
A24: Immaterielle anlægsaktiver | B24: ='balance_raw_47458714'!$B$5 | C24: ='balance_raw_47458714'!$C$5 | D24: ='balance_raw_47458714'!$D$5 | E24: ='balance_raw_47458714'!$E$5 | F24: ='balance_raw_47458714'!$F$5 | H24: =IFERROR(B24/$B$24*100,"") | I24: =IFERROR(C24/$B$24*100,"") | J24: =IFERROR(D24/$B$24*100,"") | K24: =IFERROR(E24/$B$24*100,"") | L24: =IFERROR(F24/$B$24*100,"")
A25: Grunde og bygninger | B25: ='balance_raw_47458714'!$B$6 | C25: ='balance_raw_47458714'!$C$6 | D25: ='balance_raw_47458714'!$D$6 | E25: ='balance_raw_47458714'!$E$6 | F25: ='balance_raw_47458714'!$F$6 | H25: =IFERROR(B25/$B$25*100,"") | I25: =IFERROR(C25/$B$25*100,"") | J25: =IFERROR(D25/$B$25*100,"") | K25: =IFERROR(E25/$B$25*100,"") | L25: =IFERROR(F25/$B$25*100,"")
A26: Produktionsanlæg og maskiner | B26: ='balance_raw_47458714'!$B$7 | C26: ='balance_raw_47458714'!$C$7 | D26: ='balance_raw_47458714'!$D$7 | E26: ='balance_raw_47458714'!$E$7 | F26: ='balance_raw_47458714'!$F$7 | H26: =IFERROR(B26/$B$26*100,"") | I26: =IFERROR(C26/$B$26*100,"") | J26: =IFERROR(D26/$B$26*100,"") | K26: =IFERROR(E26/$B$26*100,"") | L26: =IFERROR(F26/$B$26*100,"")
A27: Driftsmateriel og inventar | B27: ='balance_raw_47458714'!$B$8 | C27: ='balance_raw_47458714'!$C$8 | D27: ='balance_raw_47458714'!$D$8 | E27: ='balance_raw_47458714'!$E$8 | F27: ='balance_raw_47458714'!$F$8 | H27: =IFERROR(B27/$B$27*100,"") | I27: =IFERROR(C27/$B$27*100,"") | J27: =IFERROR(D27/$B$27*100,"") | K27: =IFERROR(E27/$B$27*100,"") | L27: =IFERROR(F27/$B$27*100,"")
A28: Indretning af lejede lokaler | B28: ='balance_raw_47458714'!$B$9 | C28: ='balance_raw_47458714'!$C$9 | D28: ='balance_raw_47458714'!$D$9 | E28: ='balance_raw_47458714'!$E$9 | F28: ='balance_raw_47458714'!$F$9 | H28: =IFERROR(B28/$B$28*100,"") | I28: =IFERROR(C28/$B$28*100,"") | J28: =IFERROR(D28/$B$28*100,"") | K28: =IFERROR(E28/$B$28*100,"") | L28: =IFERROR(F28/$B$28*100,"")
A29: Forudbetaling og anlægsaktiver under opførelse | B29: ='balance_raw_47458714'!$B$10 | C29: ='balance_raw_47458714'!$C$10 | D29: ='balance_raw_47458714'!$D$10 | E29: ='balance_raw_47458714'!$E$10 | F29: ='balance_raw_47458714'!$F$10 | H29: =IFERROR(B29/$B$29*100,"") | I29: =IFERROR(C29/$B$29*100,"") | J29: =IFERROR(D29/$B$29*100,"") | K29: =IFERROR(E29/$B$29*100,"") | L29: =IFERROR(F29/$B$29*100,"")
A30: Materielle anlægsaktiver | B30: ='balance_raw_47458714'!$B$11 | C30: ='balance_raw_47458714'!$C$11 | D30: ='balance_raw_47458714'!$D$11 | E30: ='balance_raw_47458714'!$E$11 | F30: ='balance_raw_47458714'!$F$11 | H30: =IFERROR(B30/$B$30*100,"") | I30: =IFERROR(C30/$B$30*100,"") | J30: =IFERROR(D30/$B$30*100,"") | K30: =IFERROR(E30/$B$30*100,"") | L30: =IFERROR(F30/$B$30*100,"")
A31: Kapitalandele, dattervirksomheder | B31: ='balance_raw_47458714'!$B$12 | C31: ='balance_raw_47458714'!$C$12 | D31: ='balance_raw_47458714'!$D$12 | E31: ='balance_raw_47458714'!$E$12 | F31: ='balance_raw_47458714'!$F$12 | H31: =IFERROR(B31/$B$31*100,"") | I31: =IFERROR(C31/$B$31*100,"") | J31: =IFERROR(D31/$B$31*100,"") | K31: =IFERROR(E31/$B$31*100,"") | L31: =IFERROR(F31/$B$31*100,"")
A32: Deposita | B32: ='balance_raw_47458714'!$B$13 | C32: ='balance_raw_47458714'!$C$13 | D32: ='balance_raw_47458714'!$D$13 | E32: ='balance_raw_47458714'!$E$13 | F32: ='balance_raw_47458714'!$F$13 | H32: =IFERROR(B32/$B$32*100,"") | I32: =IFERROR(C32/$B$32*100,"") | J32: =IFERROR(D32/$B$32*100,"") | K32: =IFERROR(E32/$B$32*100,"") | L32: =IFERROR(F32/$B$32*100,"")
A33: Finansielle anlægsaktiver | B33: ='balance_raw_47458714'!$B$14 | C33: ='balance_raw_47458714'!$C$14 | D33: ='balance_raw_47458714'!$D$14 | E33: ='balance_raw_47458714'!$E$14 | F33: ='balance_raw_47458714'!$F$14 | H33: =IFERROR(B33/$B$33*100,"") | I33: =IFERROR(C33/$B$33*100,"") | J33: =IFERROR(D33/$B$33*100,"") | K33: =IFERROR(E33/$B$33*100,"") | L33: =IFERROR(F33/$B$33*100,"")
A34: Anlægsaktiver | B34: ='balance_raw_47458714'!$B$15 | C34: ='balance_raw_47458714'!$C$15 | D34: ='balance_raw_47458714'!$D$15 | E34: ='balance_raw_47458714'!$E$15 | F34: ='balance_raw_47458714'!$F$15 | H34: =IFERROR(B34/$B$34*100,"") | I34: =IFERROR(C34/$B$34*100,"") | J34: =IFERROR(D34/$B$34*100,"") | K34: =IFERROR(E34/$B$34*100,"") | L34: =IFERROR(F34/$B$34*100,"")
A35: Varebeholdninger | B35: ='balance_raw_47458714'!$B$16 | C35: ='balance_raw_47458714'!$C$16 | D35: ='balance_raw_47458714'!$D$16 | E35: ='balance_raw_47458714'!$E$16 | F35: ='balance_raw_47458714'!$F$16 | H35: =IFERROR(B35/$B$35*100,"") | I35: =IFERROR(C35/$B$35*100,"") | J35: =IFERROR(D35/$B$35*100,"") | K35: =IFERROR(E35/$B$35*100,"") | L35: =IFERROR(F35/$B$35*100,"")
A36: Tilgodehavender fra salg og tjenesteydelser | B36: ='balance_raw_47458714'!$B$17 | C36: ='balance_raw_47458714'!$C$17 | D36: ='balance_raw_47458714'!$D$17 | E36: ='balance_raw_47458714'!$E$17 | F36: ='balance_raw_47458714'!$F$17 | H36: =IFERROR(B36/$B$36*100,"") | I36: =IFERROR(C36/$B$36*100,"") | J36: =IFERROR(D36/$B$36*100,"") | K36: =IFERROR(E36/$B$36*100,"") | L36: =IFERROR(F36/$B$36*100,"")
A37: Tilgodehavender hos tilknyttede virksomheder | B37: ='balance_raw_47458714'!$B$18 | C37: ='balance_raw_47458714'!$C$18 | D37: ='balance_raw_47458714'!$D$18 | E37: ='balance_raw_47458714'!$E$18 | F37: ='balance_raw_47458714'!$F$18 | H37: =IFERROR(B37/$B$37*100,"") | I37: =IFERROR(C37/$B$37*100,"") | J37: =IFERROR(D37/$B$37*100,"") | K37: =IFERROR(E37/$B$37*100,"") | L37: =IFERROR(F37/$B$37*100,"")
A38: Andre tilgodehavender | B38: ='balance_raw_47458714'!$B$19 | C38: ='balance_raw_47458714'!$C$19 | D38: ='balance_raw_47458714'!$D$19 | E38: ='balance_raw_47458714'!$E$19 | F38: ='balance_raw_47458714'!$F$19 | H38: =IFERROR(B38/$B$38*100,"") | I38: =IFERROR(C38/$B$38*100,"") | J38: =IFERROR(D38/$B$38*100,"") | K38: =IFERROR(E38/$B$38*100,"") | L38: =IFERROR(F38/$B$38*100,"")
A39: Periodeafgrænsningsposter (aktiver) | B39: ='balance_raw_47458714'!$B$20 | C39: ='balance_raw_47458714'!$C$20 | D39: ='balance_raw_47458714'!$D$20 | E39: ='balance_raw_47458714'!$E$20 | F39: ='balance_raw_47458714'!$F$20 | H39: =IFERROR(B39/$B$39*100,"") | I39: =IFERROR(C39/$B$39*100,"") | J39: =IFERROR(D39/$B$39*100,"") | K39: =IFERROR(E39/$B$39*100,"") | L39: =IFERROR(F39/$B$39*100,"")
A40: Udskudt skatteaktiv | B40: ='balance_raw_47458714'!$B$21 | C40: ='balance_raw_47458714'!$C$21 | D40: ='balance_raw_47458714'!$D$21 | E40: ='balance_raw_47458714'!$E$21 | F40: ='balance_raw_47458714'!$F$21 | H40: =IFERROR(B40/$B$40*100,"") | I40: =IFERROR(C40/$B$40*100,"") | J40: =IFERROR(D40/$B$40*100,"") | K40: =IFERROR(E40/$B$40*100,"") | L40: =IFERROR(F40/$B$40*100,"")
A41: Tilgodehavende skat hos tilknyttede virksomheder | B41: ='balance_raw_47458714'!$B$22 | C41: ='balance_raw_47458714'!$C$22 | D41: ='balance_raw_47458714'!$D$22 | E41: ='balance_raw_47458714'!$E$22 | F41: ='balance_raw_47458714'!$F$22 | H41: =IFERROR(B41/$B$41*100,"") | I41: =IFERROR(C41/$B$41*100,"") | J41: =IFERROR(D41/$B$41*100,"") | K41: =IFERROR(E41/$B$41*100,"") | L41: =IFERROR(F41/$B$41*100,"")
A42: Kortfristede skattetilgodehavender | B42: ='balance_raw_47458714'!$B$23 | C42: ='balance_raw_47458714'!$C$23 | D42: ='balance_raw_47458714'!$D$23 | E42: ='balance_raw_47458714'!$E$23 | F42: ='balance_raw_47458714'!$F$23 | H42: =IFERROR(B42/$B$42*100,"") | I42: =IFERROR(C42/$B$42*100,"") | J42: =IFERROR(D42/$B$42*100,"") | K42: =IFERROR(E42/$B$42*100,"") | L42: =IFERROR(F42/$B$42*100,"")
A43: Tilgodehavender | B43: ='balance_raw_47458714'!$B$24 | C43: ='balance_raw_47458714'!$C$24 | D43: ='balance_raw_47458714'!$D$24 | E43: ='balance_raw_47458714'!$E$24 | F43: ='balance_raw_47458714'!$F$24 | H43: =IFERROR(B43/$B$43*100,"") | I43: =IFERROR(C43/$B$43*100,"") | J43: =IFERROR(D43/$B$43*100,"") | K43: =IFERROR(E43/$B$43*100,"") | L43: =IFERROR(F43/$B$43*100,"")
A44: Værdipapirer | B44: ='balance_raw_47458714'!$B$25 | C44: ='balance_raw_47458714'!$C$25 | D44: ='balance_raw_47458714'!$D$25 | E44: ='balance_raw_47458714'!$E$25 | F44: ='balance_raw_47458714'!$F$25 | H44: =IFERROR(B44/$B$44*100,"") | I44: =IFERROR(C44/$B$44*100,"") | J44: =IFERROR(D44/$B$44*100,"") | K44: =IFERROR(E44/$B$44*100,"") | L44: =IFERROR(F44/$B$44*100,"")
A45: Likvide beholdninger | B45: ='balance_raw_47458714'!$B$26 | C45: ='balance_raw_47458714'!$C$26 | D45: ='balance_raw_47458714'!$D$26 | E45: ='balance_raw_47458714'!$E$26 | F45: ='balance_raw_47458714'!$F$26 | H45: =IFERROR(B45/$B$45*100,"") | I45: =IFERROR(C45/$B$45*100,"") | J45: =IFERROR(D45/$B$45*100,"") | K45: =IFERROR(E45/$B$45*100,"") | L45: =IFERROR(F45/$B$45*100,"")
A46: Omsætningsaktiver | B46: ='balance_raw_47458714'!$B$27 | C46: ='balance_raw_47458714'!$C$27 | D46: ='balance_raw_47458714'!$D$27 | E46: ='balance_raw_47458714'!$E$27 | F46: ='balance_raw_47458714'!$F$27 | H46: =IFERROR(B46/$B$46*100,"") | I46: =IFERROR(C46/$B$46*100,"") | J46: =IFERROR(D46/$B$46*100,"") | K46: =IFERROR(E46/$B$46*100,"") | L46: =IFERROR(F46/$B$46*100,"")
A47: Aktiver | B47: ='balance_raw_47458714'!$B$28 | C47: ='balance_raw_47458714'!$C$28 | D47: ='balance_raw_47458714'!$D$28 | E47: ='balance_raw_47458714'!$E$28 | F47: ='balance_raw_47458714'!$F$28 | H47: =IFERROR(B47/$B$47*100,"") | I47: =IFERROR(C47/$B$47*100,"") | J47: =IFERROR(D47/$B$47*100,"") | K47: =IFERROR(E47/$B$47*100,"") | L47: =IFERROR(F47/$B$47*100,"")
A49: PASSIVER t.kr. | B49: 2021 | C49: 2022 | D49: 2023 | E49: 2024 | F49: 2025 | H49: 2021 | I49: 2022 | J49: 2023 | K49: 2024 | L49: 2025
A50: Selskabskapital | B50: ='balance_raw_47458714'!$B$29 | C50: ='balance_raw_47458714'!$C$29 | D50: ='balance_raw_47458714'!$D$29 | E50: ='balance_raw_47458714'!$E$29 | F50: ='balance_raw_47458714'!$F$29 | H50: =IFERROR(B50/$B$50*100,"") | I50: =IFERROR(C50/$B$50*100,"") | J50: =IFERROR(D50/$B$50*100,"") | K50: =IFERROR(E50/$B$50*100,"") | L50: =IFERROR(F50/$B$50*100,"")
A51: Reserve for nettoopskrivning (indre værdis metode) | B51: ='balance_raw_47458714'!$B$30 | C51: ='balance_raw_47458714'!$C$30 | D51: ='balance_raw_47458714'!$D$30 | E51: ='balance_raw_47458714'!$E$30 | F51: ='balance_raw_47458714'!$F$30 | H51: =IFERROR(B51/$B$51*100,"") | I51: =IFERROR(C51/$B$51*100,"") | J51: =IFERROR(D51/$B$51*100,"") | K51: =IFERROR(E51/$B$51*100,"") | L51: =IFERROR(F51/$B$51*100,"")
A52: Reserve for udviklingsomkostninger | B52: ='balance_raw_47458714'!$B$31 | C52: ='balance_raw_47458714'!$C$31 | D52: ='balance_raw_47458714'!$D$31 | E52: ='balance_raw_47458714'!$E$31 | F52: ='balance_raw_47458714'!$F$31 | H52: =IFERROR(B52/$B$52*100,"") | I52: =IFERROR(C52/$B$52*100,"") | J52: =IFERROR(D52/$B$52*100,"") | K52: =IFERROR(E52/$B$52*100,"") | L52: =IFERROR(F52/$B$52*100,"")
A53: Reserve for sikringstransaktioner | B53: ='balance_raw_47458714'!$B$32 | C53: ='balance_raw_47458714'!$C$32 | D53: ='balance_raw_47458714'!$D$32 | E53: ='balance_raw_47458714'!$E$32 | F53: ='balance_raw_47458714'!$F$32 | H53: =IFERROR(B53/$B$53*100,"") | I53: =IFERROR(C53/$B$53*100,"") | J53: =IFERROR(D53/$B$53*100,"") | K53: =IFERROR(E53/$B$53*100,"") | L53: =IFERROR(F53/$B$53*100,"")
A54: Andre reserver | B54: ='balance_raw_47458714'!$B$33 | C54: ='balance_raw_47458714'!$C$33 | D54: ='balance_raw_47458714'!$D$33 | E54: ='balance_raw_47458714'!$E$33 | F54: ='balance_raw_47458714'!$F$33 | H54: =IFERROR(B54/$B$54*100,"") | I54: =IFERROR(C54/$B$54*100,"") | J54: =IFERROR(D54/$B$54*100,"") | K54: =IFERROR(E54/$B$54*100,"") | L54: =IFERROR(F54/$B$54*100,"")
A55: Overført resultat | B55: ='balance_raw_47458714'!$B$34 | C55: ='balance_raw_47458714'!$C$34 | D55: ='balance_raw_47458714'!$D$34 | E55: ='balance_raw_47458714'!$E$34 | F55: ='balance_raw_47458714'!$F$34 | H55: =IFERROR(B55/$B$55*100,"") | I55: =IFERROR(C55/$B$55*100,"") | J55: =IFERROR(D55/$B$55*100,"") | K55: =IFERROR(E55/$B$55*100,"") | L55: =IFERROR(F55/$B$55*100,"")
A56: Egenkapital i alt | B56: ='balance_raw_47458714'!$B$35 | C56: ='balance_raw_47458714'!$C$35 | D56: ='balance_raw_47458714'!$D$35 | E56: ='balance_raw_47458714'!$E$35 | F56: ='balance_raw_47458714'!$F$35 | H56: =IFERROR(B56/$B$56*100,"") | I56: =IFERROR(C56/$B$56*100,"") | J56: =IFERROR(D56/$B$56*100,"") | K56: =IFERROR(E56/$B$56*100,"") | L56: =IFERROR(F56/$B$56*100,"")
A57: Hensættelse til udskudt skat | B57: ='balance_raw_47458714'!$B$36 | C57: ='balance_raw_47458714'!$C$36 | D57: ='balance_raw_47458714'!$D$36 | E57: ='balance_raw_47458714'!$E$36 | F57: ='balance_raw_47458714'!$F$36 | H57: =IFERROR(B57/$B$57*100,"") | I57: =IFERROR(C57/$B$57*100,"") | J57: =IFERROR(D57/$B$57*100,"") | K57: =IFERROR(E57/$B$57*100,"") | L57: =IFERROR(F57/$B$57*100,"")
A58: Hensatte forpligtelser | B58: ='balance_raw_47458714'!$B$37 | C58: ='balance_raw_47458714'!$C$37 | D58: ='balance_raw_47458714'!$D$37 | E58: ='balance_raw_47458714'!$E$37 | F58: ='balance_raw_47458714'!$F$37 | H58: =IFERROR(B58/$B$58*100,"") | I58: =IFERROR(C58/$B$58*100,"") | J58: =IFERROR(D58/$B$58*100,"") | K58: =IFERROR(E58/$B$58*100,"") | L58: =IFERROR(F58/$B$58*100,"")
A59: Ansvarlig lånekapital (langfristet) | B59: ='balance_raw_47458714'!$B$38 | C59: ='balance_raw_47458714'!$C$38 | D59: ='balance_raw_47458714'!$D$38 | E59: ='balance_raw_47458714'!$E$38 | F59: ='balance_raw_47458714'!$F$38 | H59: =IFERROR(B59/$B$59*100,"") | I59: =IFERROR(C59/$B$59*100,"") | J59: =IFERROR(D59/$B$59*100,"") | K59: =IFERROR(E59/$B$59*100,"") | L59: =IFERROR(F59/$B$59*100,"")
A60: Langfristede lån | B60: ='balance_raw_47458714'!$B$39 | C60: ='balance_raw_47458714'!$C$39 | D60: ='balance_raw_47458714'!$D$39 | E60: ='balance_raw_47458714'!$E$39 | F60: ='balance_raw_47458714'!$F$39 | H60: =IFERROR(B60/$B$60*100,"") | I60: =IFERROR(C60/$B$60*100,"") | J60: =IFERROR(D60/$B$60*100,"") | K60: =IFERROR(E60/$B$60*100,"") | L60: =IFERROR(F60/$B$60*100,"")
A61: Leasingforpligtelser (langfristet) | B61: ='balance_raw_47458714'!$B$40 | C61: ='balance_raw_47458714'!$C$40 | D61: ='balance_raw_47458714'!$D$40 | E61: ='balance_raw_47458714'!$E$40 | F61: ='balance_raw_47458714'!$F$40 | H61: =IFERROR(B61/$B$61*100,"") | I61: =IFERROR(C61/$B$61*100,"") | J61: =IFERROR(D61/$B$61*100,"") | K61: =IFERROR(E61/$B$61*100,"") | L61: =IFERROR(F61/$B$61*100,"")
A62: Anden gæld (langfristet) | B62: ='balance_raw_47458714'!$B$41 | C62: ='balance_raw_47458714'!$C$41 | D62: ='balance_raw_47458714'!$D$41 | E62: ='balance_raw_47458714'!$E$41 | F62: ='balance_raw_47458714'!$F$41 | H62: =IFERROR(B62/$B$62*100,"") | I62: =IFERROR(C62/$B$62*100,"") | J62: =IFERROR(D62/$B$62*100,"") | K62: =IFERROR(E62/$B$62*100,"") | L62: =IFERROR(F62/$B$62*100,"")
A63: Langfristede gældsforpligtelser | B63: ='balance_raw_47458714'!$B$42 | C63: ='balance_raw_47458714'!$C$42 | D63: ='balance_raw_47458714'!$D$42 | E63: ='balance_raw_47458714'!$E$42 | F63: ='balance_raw_47458714'!$F$42 | H63: =IFERROR(B63/$B$63*100,"") | I63: =IFERROR(C63/$B$63*100,"") | J63: =IFERROR(D63/$B$63*100,"") | K63: =IFERROR(E63/$B$63*100,"") | L63: =IFERROR(F63/$B$63*100,"")
A64: Ansvarlig lånekapital (kortfristet) | B64: ='balance_raw_47458714'!$B$43 | C64: ='balance_raw_47458714'!$C$43 | D64: ='balance_raw_47458714'!$D$43 | E64: ='balance_raw_47458714'!$E$43 | F64: ='balance_raw_47458714'!$F$43 | H64: =IFERROR(B64/$B$64*100,"") | I64: =IFERROR(C64/$B$64*100,"") | J64: =IFERROR(D64/$B$64*100,"") | K64: =IFERROR(E64/$B$64*100,"") | L64: =IFERROR(F64/$B$64*100,"")
A65: Kortfristet del af langfristede gældsforpligtelser | B65: ='balance_raw_47458714'!$B$44 | C65: ='balance_raw_47458714'!$C$44 | D65: ='balance_raw_47458714'!$D$44 | E65: ='balance_raw_47458714'!$E$44 | F65: ='balance_raw_47458714'!$F$44 | H65: =IFERROR(B65/$B$65*100,"") | I65: =IFERROR(C65/$B$65*100,"") | J65: =IFERROR(D65/$B$65*100,"") | K65: =IFERROR(E65/$B$65*100,"") | L65: =IFERROR(F65/$B$65*100,"")
A66: Kreditinstitutter | B66: ='balance_raw_47458714'!$B$45 | C66: ='balance_raw_47458714'!$C$45 | D66: ='balance_raw_47458714'!$D$45 | E66: ='balance_raw_47458714'!$E$45 | F66: ='balance_raw_47458714'!$F$45 | H66: =IFERROR(B66/$B$66*100,"") | I66: =IFERROR(C66/$B$66*100,"") | J66: =IFERROR(D66/$B$66*100,"") | K66: =IFERROR(E66/$B$66*100,"") | L66: =IFERROR(F66/$B$66*100,"")
A67: Leasingforpligtelser (kortfristet) | B67: ='balance_raw_47458714'!$B$46 | C67: ='balance_raw_47458714'!$C$46 | D67: ='balance_raw_47458714'!$D$46 | E67: ='balance_raw_47458714'!$E$46 | F67: ='balance_raw_47458714'!$F$46 | H67: =IFERROR(B67/$B$67*100,"") | I67: =IFERROR(C67/$B$67*100,"") | J67: =IFERROR(D67/$B$67*100,"") | K67: =IFERROR(E67/$B$67*100,"") | L67: =IFERROR(F67/$B$67*100,"")
A68: Leverandører af varer og tjenesteydelser | B68: ='balance_raw_47458714'!$B$47 | C68: ='balance_raw_47458714'!$C$47 | D68: ='balance_raw_47458714'!$D$47 | E68: ='balance_raw_47458714'!$E$47 | F68: ='balance_raw_47458714'!$F$47 | H68: =IFERROR(B68/$B$68*100,"") | I68: =IFERROR(C68/$B$68*100,"") | J68: =IFERROR(D68/$B$68*100,"") | K68: =IFERROR(E68/$B$68*100,"") | L68: =IFERROR(F68/$B$68*100,"")
A69: Gæld til tilknyttede virksomheder | B69: ='balance_raw_47458714'!$B$48 | C69: ='balance_raw_47458714'!$C$48 | D69: ='balance_raw_47458714'!$D$48 | E69: ='balance_raw_47458714'!$E$48 | F69: ='balance_raw_47458714'!$F$48 | H69: =IFERROR(B69/$B$69*100,"") | I69: =IFERROR(C69/$B$69*100,"") | J69: =IFERROR(D69/$B$69*100,"") | K69: =IFERROR(E69/$B$69*100,"") | L69: =IFERROR(F69/$B$69*100,"")
A70: Gæld til selskabsdeltagere og ledelse | B70: ='balance_raw_47458714'!$B$49 | C70: ='balance_raw_47458714'!$C$49 | D70: ='balance_raw_47458714'!$D$49 | E70: ='balance_raw_47458714'!$E$49 | F70: ='balance_raw_47458714'!$F$49 | H70: =IFERROR(B70/$B$70*100,"") | I70: =IFERROR(C70/$B$70*100,"") | J70: =IFERROR(D70/$B$70*100,"") | K70: =IFERROR(E70/$B$70*100,"") | L70: =IFERROR(F70/$B$70*100,"")
A71: Selskabsskat | B71: ='balance_raw_47458714'!$B$50 | C71: ='balance_raw_47458714'!$C$50 | D71: ='balance_raw_47458714'!$D$50 | E71: ='balance_raw_47458714'!$E$50 | F71: ='balance_raw_47458714'!$F$50 | H71: =IFERROR(B71/$B$71*100,"") | I71: =IFERROR(C71/$B$71*100,"") | J71: =IFERROR(D71/$B$71*100,"") | K71: =IFERROR(E71/$B$71*100,"") | L71: =IFERROR(F71/$B$71*100,"")
A72: Gæld til tilknyttede virksomheder vedr. selskabsskat | B72: ='balance_raw_47458714'!$B$51 | C72: ='balance_raw_47458714'!$C$51 | D72: ='balance_raw_47458714'!$D$51 | E72: ='balance_raw_47458714'!$E$51 | F72: ='balance_raw_47458714'!$F$51 | H72: =IFERROR(B72/$B$72*100,"") | I72: =IFERROR(C72/$B$72*100,"") | J72: =IFERROR(D72/$B$72*100,"") | K72: =IFERROR(E72/$B$72*100,"") | L72: =IFERROR(F72/$B$72*100,"")
A73: Anden gæld (kortfristet) | B73: ='balance_raw_47458714'!$B$52 | C73: ='balance_raw_47458714'!$C$52 | D73: ='balance_raw_47458714'!$D$52 | E73: ='balance_raw_47458714'!$E$52 | F73: ='balance_raw_47458714'!$F$52 | H73: =IFERROR(B73/$B$73*100,"") | I73: =IFERROR(C73/$B$73*100,"") | J73: =IFERROR(D73/$B$73*100,"") | K73: =IFERROR(E73/$B$73*100,"") | L73: =IFERROR(F73/$B$73*100,"")
A74: Periodeafgrænsningsposter (passiver) | B74: ='balance_raw_47458714'!$B$53 | C74: ='balance_raw_47458714'!$C$53 | D74: ='balance_raw_47458714'!$D$53 | E74: ='balance_raw_47458714'!$E$53 | F74: ='balance_raw_47458714'!$F$53 | H74: =IFERROR(B74/$B$74*100,"") | I74: =IFERROR(C74/$B$74*100,"") | J74: =IFERROR(D74/$B$74*100,"") | K74: =IFERROR(E74/$B$74*100,"") | L74: =IFERROR(F74/$B$74*100,"")
A75: Kortfristede gældsforpligtelser | B75: ='balance_raw_47458714'!$B$54 | C75: ='balance_raw_47458714'!$C$54 | D75: ='balance_raw_47458714'!$D$54 | E75: ='balance_raw_47458714'!$E$54 | F75: ='balance_raw_47458714'!$F$54 | H75: =IFERROR(B75/$B$75*100,"") | I75: =IFERROR(C75/$B$75*100,"") | J75: =IFERROR(D75/$B$75*100,"") | K75: =IFERROR(E75/$B$75*100,"") | L75: =IFERROR(F75/$B$75*100,"")
A76: Gældsforpligtelser | B76: ='balance_raw_47458714'!$B$55 | C76: ='balance_raw_47458714'!$C$55 | D76: ='balance_raw_47458714'!$D$55 | E76: ='balance_raw_47458714'!$E$55 | F76: ='balance_raw_47458714'!$F$55 | H76: =IFERROR(B76/$B$76*100,"") | I76: =IFERROR(C76/$B$76*100,"") | J76: =IFERROR(D76/$B$76*100,"") | K76: =IFERROR(E76/$B$76*100,"") | L76: =IFERROR(F76/$B$76*100,"")
A77: Passiver | B77: ='balance_raw_47458714'!$B$56 | C77: ='balance_raw_47458714'!$C$56 | D77: ='balance_raw_47458714'!$D$56 | E77: ='balance_raw_47458714'!$E$56 | F77: ='balance_raw_47458714'!$F$56 | H77: =IFERROR(B77/$B$77*100,"") | I77: =IFERROR(C77/$B$77*100,"") | J77: =IFERROR(D77/$B$77*100,"") | K77: =IFERROR(E77/$B$77*100,"") | L77: =IFERROR(F77/$B$77*100,"")
A79: NØGLEOPLYSNINGER | B79: 2021 | C79: 2022 | D79: 2023 | E79: 2024 | F79: 2025
A80: Gns. antal medarbejdere | B80: ='res_raw_47458714'!$B$17 | C80: ='res_raw_47458714'!$C$17 | D80: ='res_raw_47458714'!$D$17 | E80: ='res_raw_47458714'!$E$17 | F80: ='res_raw_47458714'!$F$17 | H80: =IFERROR(B80/$B$80*100,"") | I80: =IFERROR(C80/$B$80*100,"") | J80: =IFERROR(D80/$B$80*100,"") | K80: =IFERROR(E80/$B$80*100,"") | L80: =IFERROR(F80/$B$80*100,"")
A81: Investering i materielle anlægsaktiver | B81: ='res_raw_47458714'!$B$18 | C81: ='res_raw_47458714'!$C$18 | D81: ='res_raw_47458714'!$D$18 | E81: ='res_raw_47458714'!$E$18 | F81: ='res_raw_47458714'!$F$18 | H81: =IFERROR(B81/$B$81*100,"") | I81: =IFERROR(C81/$B$81*100,"") | J81: =IFERROR(D81/$B$81*100,"") | K81: =IFERROR(E81/$B$81*100,"") | L81: =IFERROR(F81/$B$81*100,"")
A83: NØGLETAL | B83: 2021 | C83: 2022 | D83: 2023 | E83: 2024 | F83: 2025
A84: Afkastningsgrad, % | B84: =IFERROR(($B$11+$B$13+$B$12)/$B$47*100,"") | C84: =IFERROR(($C$11+$C$13+$C$12)/$C$47*100,"") | D84: =IFERROR(($D$11+$D$13+$D$12)/$D$47*100,"") | E84: =IFERROR(($E$11+$E$13+$E$12)/$E$47*100,"") | F84: =IFERROR(($F$11+$F$13+$F$12)/$F$47*100,"")
A85: Overskudsgrad, % | B85: =IFERROR(($B$11+$B$13+$B$12)/$B$4*100,"") | C85: =IFERROR(($C$11+$C$13+$C$12)/$C$4*100,"") | D85: =IFERROR(($D$11+$D$13+$D$12)/$D$4*100,"") | E85: =IFERROR(($E$11+$E$13+$E$12)/$E$4*100,"") | F85: =IFERROR(($F$11+$F$13+$F$12)/$F$4*100,"")
A86: Aktivernes omsætningshastighed, gange | B86: =IFERROR($B$4/$B$47,"") | C86: =IFERROR($C$4/$C$47,"") | D86: =IFERROR($D$4/$D$47,"") | E86: =IFERROR($E$4/$E$47,"") | F86: =IFERROR($F$4/$F$47,"")
A87: Egenkapitalens forrentning, % | B87: =IFERROR($B$16/$B$56*100,"") | C87: =IFERROR($C$16/$C$56*100,"") | D87: =IFERROR($D$16/$D$56*100,"") | E87: =IFERROR($E$16/$E$56*100,"") | F87: =IFERROR($F$16/$F$56*100,"")
A88: Gældsrente, % | B88: =IFERROR($B$14/($B$77-$B$56)*100,"") | C88: =IFERROR($C$14/($C$77-$C$56)*100,"") | D88: =IFERROR($D$14/($D$77-$D$56)*100,"") | E88: =IFERROR($E$14/($E$77-$E$56)*100,"") | F88: =IFERROR($F$14/($F$77-$F$56)*100,"")
A89: Soliditetsgrad, % | B89: =IFERROR($B$56/$B$47*100,"") | C89: =IFERROR($C$56/$C$47*100,"") | D89: =IFERROR($D$56/$D$47*100,"") | E89: =IFERROR($E$56/$E$47*100,"") | F89: =IFERROR($F$56/$F$47*100,"")
A90: Gearing | B90: =IFERROR(($B$77-$B$56)/$B$56,"") | C90: =IFERROR(($C$77-$C$56)/$C$56,"") | D90: =IFERROR(($D$77-$D$56)/$D$56,"") | E90: =IFERROR(($E$77-$E$56)/$E$56,"") | F90: =IFERROR(($F$77-$F$56)/$F$56,"")
A91: Likviditetsgrad, % | B91: =IFERROR($B$46/$B$75*100,"") | C91: =IFERROR($C$46/$C$75*100,"") | D91: =IFERROR($D$46/$D$75*100,"") | E91: =IFERROR($E$46/$E$75*100,"") | F91: =IFERROR($F$46/$F$75*100,"")
A92: Rentemarginal, % | B92: =IFERROR(B84-B88,"") | C92: =IFERROR(C84-C88,"") | D92: =IFERROR(D84-D88,"") | E92: =IFERROR(E84-E88,"") | F92: =IFERROR(F84-F88,"")
A93: Gældsandel, % | B93: =IFERROR(($B$77-$B$56)/$B$47*100,"") | C93: =IFERROR(($C$77-$C$56)/$C$47*100,"") | D93: =IFERROR(($D$77-$D$56)/$D$47*100,"") | E93: =IFERROR(($E$77-$E$56)/$E$47*100,"") | F93: =IFERROR(($F$77-$F$56)/$F$47*100,"")
A94: Kapitalbindingsgrad, % | B94: =IFERROR($B$34/($B$56+$B$63)*100,"") | C94: =IFERROR($C$34/($C$56+$C$63)*100,"") | D94: =IFERROR($D$34/($D$56+$D$63)*100,"") | E94: =IFERROR($E$34/($E$56+$E$63)*100,"") | F94: =IFERROR($F$34/($F$56+$F$63)*100,"")
A96: Pengestrømsopgørelse ikke offentliggjort (jf. koncernfritagelse, ÅRL §86, stk. 4)

Sheet res_raw_47458714
A1: LEGO System A/S (CVR 47458714) — Resultatopgørelse & nøgleoplysninger (t.kr.) | B1: 2021 | C1: 2022 | D1: 2023 | E1: 2024 | F1: 2025
A2: Nettoomsætning | B2: 40925000 | C2: 48295000 | D2: 47957000 | E2: 55590000 | F2: 61963000
A3: Produktionsomkostninger | B3: 17545000 | C3: 21641000 | D3: 22828000 | E3: 26075000 | F3: 29937000
A4: Bruttoresultat | B4: 23380000 | C4: 26654000 | D4: 25129000 | E4: 29515000 | F4: 32026000
A5: Salgs- og distributionsomkostninger | B5: 6266000 | C5: 7592000 | D5: 7616000 | E5: 8884000 | F5: 9544000
A6: Administrationsomkostninger | B6: 2657000 | C6: 2746000 | D6: 3187000 | E6: 3884000 | F6: 4157000
A7: Andre driftsindtægter
A8: Andre driftsomkostninger | B8: 999000 | C8: 1594000 | D8: 1876000 | E8: 2447000 | F8: 2544000
A9: Resultat af primær drift | B9: 14457000 | C9: 16316000 | D9: 14326000 | E9: 16747000 | F9: 18325000
A10: Indtægter af kapitalandele, dattervirksomheder
A11: Finansielle indtægter | B11: 382000 | C11: 587000 | D11: 1690000 | E11: 1296000 | F11: 1410000
A12: Finansielle omkostninger | B12: 186000 | C12: 990000 | D12: 377000 | E12: 948000 | F12: 242000
A13: Finansielle poster, netto | B13: 196000 | C13: -403000 | D13: 1313000 | E13: 348000 | F13: 1168000
A14: Resultat før skat | B14: 13654000 | C14: 14319000 | D14: 13763000 | E14: 14648000 | F14: 16949000
A15: Skat af årets resultat | B15: 2981000 | C15: 2949000 | D15: 2851000 | E15: 3243000 | F15: 3691000
A16: Årets resultat | B16: 10673000 | C16: 11370000 | D16: 10912000 | E16: 11405000 | F16: 13258000
A17: Gns. antal medarbejdere | B17: 4409 | C17: 4958 | D17: 5587 | E17: 5950 | F17: 6257
A18: Investering i materielle anlægsaktiver | B18: 1313000 | C18: 1822000 | D18: 1707000 | E18: 1900000 | F18: 2528000

Sheet balance_raw_47458714
A1: LEGO System A/S (CVR 47458714) — Balance (t.kr.) | B1: 2021 | C1: 2022 | D1: 2023 | E1: 2024 | F1: 2025
A2: Udviklingsprojekter | B2: 51000 | C2: 126000 | D2: 306000 | E2: 442000 | F2: 629000
A3: Patenter, varemærker mv.
A4: Goodwill
A5: Immaterielle anlægsaktiver | B5: 81000 | C5: 143000 | D5: 310000 | E5: 445000 | F5: 631000
A6: Grunde og bygninger | B6: 563000 | C6: 589000 | D6: 573000 | E6: 556000 | F6: 672000
A7: Produktionsanlæg og maskiner | B7: 2061000 | C7: 2283000 | D7: 2419000 | E7: 2307000 | F7: 3357000
A8: Driftsmateriel og inventar | B8: 209000 | C8: 293000 | D8: 306000 | E8: 336000 | F8: 286000
A9: Indretning af lejede lokaler
A10: Forudbetaling og anlægsaktiver under opførelse | B10: 645000 | C10: 1246000 | D10: 1782000 | E10: 2849000 | F10: 3431000
A11: Materielle anlægsaktiver | B11: 3478000 | C11: 4411000 | D11: 5080000 | E11: 6048000 | F11: 7746000
A12: Kapitalandele, dattervirksomheder
A13: Deposita | D13: 5098000 | E13: 10077000 | F13: 9475000
A14: Finansielle anlægsaktiver | D14: 175000 | E14: 10187000 | F14: 9703000
A15: Anlægsaktiver | B15: 5552000 | C15: 6556000 | D15: 12503000 | E15: 18893000 | F15: 20827000
A16: Varebeholdninger | B16: 2126000 | C16: 3522000 | D16: 3378000 | E16: 4034000 | F16: 4505000
A17: Tilgodehavender fra salg og tjenesteydelser | B17: 622000 | C17: 399000 | D17: 421000 | E17: 517000 | F17: 537000
A18: Tilgodehavender hos tilknyttede virksomheder | B18: 27394000 | C18: 28959000 | D18: 23782000 | E18: 21833000 | F18: 23125000
A19: Andre tilgodehavender | B19: 818000 | C19: 1391000 | D19: 1438000 | E19: 771000 | F19: 1130000
A20: Periodeafgrænsningsposter (aktiver) | C20: 0
A21: Udskudt skatteaktiv | B21: 66000 | D21: 39000 | E21: 79000 | F21: 0
A22: Tilgodehavende skat hos tilknyttede virksomheder
A23: Kortfristede skattetilgodehavender | B23: 0 | D23: 531000 | E23: 501000 | F23: 501000
A24: Tilgodehavender | B24: 28900000 | C24: 30749000 | D24: 26211000 | E24: 24085000 | F24: 25720000
A25: Værdipapirer
A26: Likvide beholdninger | B26: 427000 | C26: 509000 | D26: 102000 | E26: 0 | F26: 185000
A27: Omsætningsaktiver | B27: 31453000 | C27: 34780000 | D27: 29691000 | E27: 28119000 | F27: 30410000
A28: Aktiver | B28: 37005000 | C28: 41336000 | D28: 42194000 | E28: 47012000 | F28: 51237000
A29: Selskabskapital | B29: 50000 | C29: 50000 | D29: 50000 | E29: 50000 | F29: 50000
A30: Reserve for nettoopskrivning (indre værdis metode)
A31: Reserve for udviklingsomkostninger | B31: 63000 | C31: 112000 | D31: 242000 | E31: 347000 | F31: 493000
A32: Reserve for sikringstransaktioner | B32: -161000 | C32: 157000 | D32: 54000 | E32: -216000 | F32: 147000
A33: Andre reserver
A34: Overført resultat | B34: 6670000 | C34: 8991000 | D34: 10773000 | E34: 13073000 | F34: 12185000
A35: Egenkapital i alt | B35: 16622000 | C35: 18310000 | D35: 20119000 | E35: 22254000 | F35: 24875000
A36: Hensættelse til udskudt skat | B36: 0 | C36: 26000 | D36: 0 | F36: 81000
A37: Hensatte forpligtelser | B37: 46000 | C37: 100000 | D37: 24000 | E37: 9000 | F37: 89000
A38: Ansvarlig lånekapital (langfristet)
A39: Langfristede lån | B39: 127000 | C39: 118000 | D39: 0
A40: Leasingforpligtelser (langfristet) | B40: 1838000 | C40: 1827000 | D40: 1860000 | E40: 1982000 | F40: 2558000
A41: Anden gæld (langfristet) | C41: 95000 | D41: 0 | F41: 97000
A42: Langfristede gældsforpligtelser | B42: 1965000 | C42: 2040000 | D42: 1860000 | E42: 1982000 | F42: 2655000
A43: Ansvarlig lånekapital (kortfristet)
A44: Kortfristet del af langfristede gældsforpligtelser
A45: Kreditinstitutter | B45: 10000 | C45: 9000 | D45: 0 | E45: 68000 | F45: 0
A46: Leasingforpligtelser (kortfristet) | B46: 181000 | C46: 210000 | D46: 202000 | E46: 289000 | F46: 249000
A47: Leverandører af varer og tjenesteydelser | B47: 2200000 | C47: 2408000 | D47: 2193000 | E47: 2366000 | F47: 2938000
A48: Gæld til tilknyttede virksomheder | B48: 12693000 | C48: 14665000 | D48: 13495000 | E48: 14038000 | F48: 13986000
A49: Gæld til selskabsdeltagere og ledelse
A50: Selskabsskat | B50: 18000 | C50: 232000 | D50: 690000 | E50: 561000 | F50: 837000
A51: Gæld til tilknyttede virksomheder vedr. selskabsskat
A52: Anden gæld (kortfristet) | B52: 2875000 | C52: 2747000 | D52: 2803000 | E52: 4497000 | F52: 4595000
A53: Periodeafgrænsningsposter (passiver) | B53: 395000 | C53: 615000 | D53: 808000 | E53: 948000 | F53: 1013000
A54: Kortfristede gældsforpligtelser | B54: 18372000 | C54: 20886000 | D54: 20191000 | E54: 22767000 | F54: 23618000
A55: Gældsforpligtelser | B55: 20337000 | C55: 22926000 | D55: 22051000 | E55: 24749000 | F55: 26273000
A56: Passiver | B56: 37005000 | C56: 41336000 | D56: 42194000 | E56: 47012000 | F56: 51237000

Sheet Simpel_funktion
A1: LEGO System A/S (CVR 47458714) — Regnskabs- og nøgletal (CVR: 47458714) — funktionsopdelt
A3: Beløb i 1.000 kr. | B3: 2025 | C3: 2024 | D3: 2023 | F3: Note / XBRL-felt
A4: Uddrag af resultatopgørelse
A5: Nettoomsætning | B5: ='res_raw_47458714'!$F$2 | C5: ='res_raw_47458714'!$E$2 | D5: ='res_raw_47458714'!$D$2 | F5: fsa:Revenue
A6: Produktionsomkostninger | B6: =-'res_raw_47458714'!$F$3 | C6: =-'res_raw_47458714'!$E$3 | D6: =-'res_raw_47458714'!$D$3 | F6: fsa:CostOfProduction (vises negativt). Materialer, lønninger, produktionsoverhead.
A7: Bruttoresultat | B7: =SUM(B5:B6) | C7: =SUM(C5:C6) | D7: =SUM(D5:D6) | F7: Beregnet: Nettoomsætning − Produktionsomkostninger. Matcher fsa:GrossResult.
A8: Salgs- og distributionsomk. | B8: =-'res_raw_47458714'!$F$5 | C8: =-'res_raw_47458714'!$E$5 | D8: =-'res_raw_47458714'!$D$5 | F8: fsa:DistributionCosts (vises negativt). Marketing, salg, distribution.
A9: Administrationsomkostninger mv. | B9: =-'res_raw_47458714'!$F$6 | C9: =-'res_raw_47458714'!$E$6 | D9: =-'res_raw_47458714'!$D$6 | F9: fsa:AdministrativeExpenses (vises negativt). Generel administration.
A10: Andre driftsindtægter | B10: ='res_raw_47458714'!$F$7 | C10: ='res_raw_47458714'!$E$7 | D10: ='res_raw_47458714'!$D$7 | F10: fsa:OtherOperatingIncome. Sekundære driftsindtægter (huslejeindtægter, off. tilskud, avancer mv.).
A11: Andre driftsomkostninger | B11: =-'res_raw_47458714'!$F$8 | C11: =-'res_raw_47458714'!$E$8 | D11: =-'res_raw_47458714'!$D$8 | F11: fsa:OtherOperatingExpenses (vises negativt). Sekundære driftsomkostninger.
A12: Resultat af primær drift | B12: =SUM(B7:B11) | C12: =SUM(C7:C11) | D12: =SUM(D7:D11) | F12: Beregnet: Bruttoresultat − Salgs/dist. − Administration + Andre driftsindt. − Andre driftsomk. EBIT.
A13: Finansielle indtægter mv. | B13: =N('res_raw_47458714'!$F$10)+N('res_raw_47458714'!$F$11) | C13: =N('res_raw_47458714'!$E$10)+N('res_raw_47458714'!$E$11) | D13: =N('res_raw_47458714'!$D$10)+N('res_raw_47458714'!$D$11) | F13: fsa:IncomeFromSubsidiaries + fsa:OtherFinanceIncome.
A14: Finansielle omkostninger mv. | B14: =-'res_raw_47458714'!$F$12 | C14: =-'res_raw_47458714'!$E$12 | D14: =-'res_raw_47458714'!$D$12 | F14: fsa:OtherFinanceExpenses (vises negativt). Renteomkostninger, kurstab.
A15: Resultat før skat | B15: =SUM(B12:B14) | C15: =SUM(C12:C14) | D15: =SUM(D12:D14) | F15: Beregnet: EBIT + Fin. indtægter + Fin. omk. EBT.
A17: Uddrag af balance
A18: Anlægsaktiver | B18: ='balance_raw_47458714'!$F$15 | C18: ='balance_raw_47458714'!$E$15 | D18: ='balance_raw_47458714'!$D$15 | F18: fsa:NoncurrentAssets. Materielle, immaterielle og finansielle anlægsaktiver.
A19: Omsætningsaktiver | B19: ='balance_raw_47458714'!$F$27 | C19: ='balance_raw_47458714'!$E$27 | D19: ='balance_raw_47458714'!$D$27 | F19: fsa:CurrentAssets. Varebeholdninger, tilgodehavender, likvider.
A20: Aktiver i alt | B20: =SUM(B18:B19) | C20: =SUM(C18:C19) | D20: =SUM(D18:D19) | F20: Beregnet: Anlægsaktiver + Omsætningsaktiver. Bør matche fsa:Assets.
A22: Egenkapital | B22: ='balance_raw_47458714'!$F$35 | C22: ='balance_raw_47458714'!$E$35 | D22: ='balance_raw_47458714'!$D$35 | F22: fsa:Equity. Selskabskapital, overført resultat, reserver.
A23: Forpligtelser | B23: ='balance_raw_47458714'!$F$56-'balance_raw_47458714'!$F$35 | C23: ='balance_raw_47458714'!$E$56-'balance_raw_47458714'!$E$35 | D23: ='balance_raw_47458714'!$D$56-'balance_raw_47458714'!$D$35 | F23: Beregnet: Passiver (fsa:LiabilitiesAndEquity) − Egenkapital. Hensættelser + kort- og langfristet gæld.
A24: Passiver i alt | B24: =SUM(B22:B23) | C24: =SUM(C22:C23) | D24: =SUM(D22:D23) | F24: Beregnet: Egenkapital + Forpligtelser. Bør matche Aktiver i alt.
A26: Udvalgte balanceposter
A27: Varebeholdninger | B27: ='balance_raw_47458714'!$F$16 | C27: ='balance_raw_47458714'!$E$16 | D27: ='balance_raw_47458714'!$D$16 | F27: fsa:Inventories (eller fsa:ManufacturedGoodsAndGoodsForResale hvis total mangler).
A28: Tilgodehavender fra salg | B28: ='balance_raw_47458714'!$F$17 | C28: ='balance_raw_47458714'!$E$17 | D28: ='balance_raw_47458714'!$D$17 | F28: fsa:ShorttermTradeReceivables. Kortfristede tilgodehavender fra kunder.
A29: Kortfristede gældsforpligtelser | B29: ='balance_raw_47458714'!$F$54 | C29: ='balance_raw_47458714'!$E$54 | D29: ='balance_raw_47458714'!$D$54 | F29: fsa:ShorttermLiabilitiesOtherThanProvisions. Gæld der forfalder inden for 1 år.
A31: Rentabilitet
A32: Afkastningsgrad, % | B32: =IFERROR((B12+B13)/B20*100,"") | C32: =IFERROR((C12+C13)/C20*100,"") | D32: =IFERROR((D12+D13)/D20*100,"")
A33: Overskudsgrad, % | B33: =IFERROR((B12+B13)/B5*100,"") | C33: =IFERROR((C12+C13)/C5*100,"") | D33: =IFERROR((D12+D13)/D5*100,"")
A34: Aktivernes omsætningshastighed, gange | B34: =IFERROR(B5/B20,"") | C34: =IFERROR(C5/C20,"") | D34: =IFERROR(D5/D20,"")
A35: Gældsrente, % | B35: =IFERROR(-B14*100/B23,"") | C35: =IFERROR(-C14*100/C23,"") | D35: =IFERROR(-D14*100/D23,"")
A36: Egenkapitalens forrentning, % | B36: =IFERROR(B15/B22*100,"") | C36: =IFERROR(C15/C22*100,"") | D36: =IFERROR(D15/D22*100,"")
A37: Gearing, gange | B37: =IFERROR(B23/B22,"") | C37: =IFERROR(C23/C22,"") | D37: =IFERROR(D23/D22,"")
A39: Indekstal for indtjeningsevne (2023=100)
A40: Nettoomsætning | B40: =IFERROR(B5/$D5*100,"") | C40: =IFERROR(C5/$D5*100,"") | D40: =IFERROR(D5/$D5*100,"")
A41: Produktionsomkostninger | B41: =IFERROR(B6/$D6*100,"") | C41: =IFERROR(C6/$D6*100,"") | D41: =IFERROR(D6/$D6*100,"")
A42: Salgs- og distributionsomk. | B42: =IFERROR(B8/$D8*100,"") | C42: =IFERROR(C8/$D8*100,"") | D42: =IFERROR(D8/$D8*100,"")
A43: Administrationsomk. | B43: =IFERROR(B9/$D9*100,"") | C43: =IFERROR(C9/$D9*100,"") | D43: =IFERROR(D9/$D9*100,"")
A44: Andre driftsomkostninger | B44: =IFERROR(B11/$D11*100,"") | C44: =IFERROR(C11/$D11*100,"") | D44: =IFERROR(D11/$D11*100,"")
A46: Indekstal for kapitaltilpasningsevne (2023=100)
A47: Nettoomsætning | B47: =IFERROR(B5*100/$D5,"") | C47: =IFERROR(C5*100/$D5,"") | D47: =IFERROR(D5*100/$D5,"")
A48: Anlægsaktiver | B48: =IFERROR(B18*100/$D18,"") | C48: =IFERROR(C18*100/$D18,"") | D48: =IFERROR(D18*100/$D18,"")
A49: Varebeholdninger | B49: =IFERROR(B27*100/$D27,"") | C49: =IFERROR(C27*100/$D27,"") | D49: =IFERROR(D27*100/$D27,"")
A50: Tilgodehavender fra salg | B50: =IFERROR(B28*100/$D28,"") | C50: =IFERROR(C28*100/$D28,"") | D50: =IFERROR(D28*100/$D28,"")
A52: Soliditet og likviditet
A53: Soliditetsgrad, % | B53: =IFERROR(B22*100/B20,"") | C53: =IFERROR(C22*100/C20,"") | D53: =IFERROR(D22*100/D20,"")
A54: Gældsandel, % | B54: =IFERROR(B23*100/B20,"") | C54: =IFERROR(C23*100/C20,"") | D54: =IFERROR(D23*100/D20,"")
A55: Likviditetsgrad, % | B55: =IFERROR(B19*100/B29,"") | C55: =IFERROR(C19*100/C29,"") | D55: =IFERROR(D19*100/D29,"")
A57: Kilde: Bearbejdet uddrag af årsrapporter for 2023-2025. Alle dataceller er live formler der peger på res_raw / balance_raw.
A59: Krydstjek mod rådata (tolerance: 1 t.kr.)
A60: Aktiver i alt = fsa:Assets | B60: =IF('balance_raw_47458714'!$F$28="","—",IF(ABS(B20-'balance_raw_47458714'!$F$28)<=1,"✓ OK","❌ "&TEXT(B20-'balance_raw_47458714'!$F$28,"+#,##0;-#,##0")&" t.kr.")) | C60: =IF('balance_raw_47458714'!$E$28="","—",IF(ABS(C20-'balance_raw_47458714'!$E$28)<=1,"✓ OK","❌ "&TEXT(C20-'balance_raw_47458714'!$E$28,"+#,##0;-#,##0")&" t.kr.")) | D60: =IF('balance_raw_47458714'!$D$28="","—",IF(ABS(D20-'balance_raw_47458714'!$D$28)<=1,"✓ OK","❌ "&TEXT(D20-'balance_raw_47458714'!$D$28,"+#,##0;-#,##0")&" t.kr.")) | F60: Verificerer at sum(Anlæg+Omsætning) matcher Assets-totalen.
A61: Passiver i alt = fsa:LiabilitiesAndEquity | B61: =IF('balance_raw_47458714'!$F$56="","—",IF(ABS(B24-'balance_raw_47458714'!$F$56)<=1,"✓ OK","❌ "&TEXT(B24-'balance_raw_47458714'!$F$56,"+#,##0;-#,##0")&" t.kr.")) | C61: =IF('balance_raw_47458714'!$E$56="","—",IF(ABS(C24-'balance_raw_47458714'!$E$56)<=1,"✓ OK","❌ "&TEXT(C24-'balance_raw_47458714'!$E$56,"+#,##0;-#,##0")&" t.kr.")) | D61: =IF('balance_raw_47458714'!$D$56="","—",IF(ABS(D24-'balance_raw_47458714'!$D$56)<=1,"✓ OK","❌ "&TEXT(D24-'balance_raw_47458714'!$D$56,"+#,##0;-#,##0")&" t.kr.")) | F61: Verificerer at sum(EK+Forpligtelser) matcher Passiver-totalen.
A62: Aktiver i alt = Passiver i alt | B62: =IF(ABS(B20-B24)<=1,"✓ OK","❌ "&TEXT(B20-B24,"+#,##0;-#,##0")&" t.kr.") | C62: =IF(ABS(C20-C24)<=1,"✓ OK","❌ "&TEXT(C20-C24,"+#,##0;-#,##0")&" t.kr.") | D62: =IF(ABS(D20-D24)<=1,"✓ OK","❌ "&TEXT(D20-D24,"+#,##0;-#,##0")&" t.kr.") | F62: Balance-identitet på arket selv. Skal altid være 0 differance.
A63: Bruttoresultat (beregnet) = fsa:GrossResult | B63: =IF('res_raw_47458714'!$F$4="","—",IF(ABS(B7-'res_raw_47458714'!$F$4)<=1,"✓ OK","❌ "&TEXT(B7-'res_raw_47458714'!$F$4,"+#,##0;-#,##0")&" t.kr.")) | C63: =IF('res_raw_47458714'!$E$4="","—",IF(ABS(C7-'res_raw_47458714'!$E$4)<=1,"✓ OK","❌ "&TEXT(C7-'res_raw_47458714'!$E$4,"+#,##0;-#,##0")&" t.kr.")) | D63: =IF('res_raw_47458714'!$D$4="","—",IF(ABS(D7-'res_raw_47458714'!$D$4)<=1,"✓ OK","❌ "&TEXT(D7-'res_raw_47458714'!$D$4,"+#,##0;-#,##0")&" t.kr.")) | F63: Hvis Nettoomsætning eller omkostninger mangler, vil sumberegnet bruttoresultat afvige.
A64: EBIT (beregnet) = fsa:ProfitLossFromOrdinaryOperatingActivities | B64: =IF('res_raw_47458714'!$F$9="","—",IF(ABS(B12-'res_raw_47458714'!$F$9)<=1,"✓ OK","❌ "&TEXT(B12-'res_raw_47458714'!$F$9,"+#,##0;-#,##0")&" t.kr.")) | C64: =IF('res_raw_47458714'!$E$9="","—",IF(ABS(C12-'res_raw_47458714'!$E$9)<=1,"✓ OK","❌ "&TEXT(C12-'res_raw_47458714'!$E$9,"+#,##0;-#,##0")&" t.kr.")) | D64: =IF('res_raw_47458714'!$D$9="","—",IF(ABS(D12-'res_raw_47458714'!$D$9)<=1,"✓ OK","❌ "&TEXT(D12-'res_raw_47458714'!$D$9,"+#,##0;-#,##0")&" t.kr.")) | F64: Verificerer at sumberegnet EBIT matcher det rapporterede.
A65: EBT (beregnet) = fsa:ProfitLossFromOrdinaryActivitiesBeforeTax | B65: =IF('res_raw_47458714'!$F$14="","—",IF(ABS(B15-'res_raw_47458714'!$F$14)<=1,"✓ OK","❌ "&TEXT(B15-'res_raw_47458714'!$F$14,"+#,##0;-#,##0")&" t.kr.")) | C65: =IF('res_raw_47458714'!$E$14="","—",IF(ABS(C15-'res_raw_47458714'!$E$14)<=1,"✓ OK","❌ "&TEXT(C15-'res_raw_47458714'!$E$14,"+#,##0;-#,##0")&" t.kr.")) | D65: =IF('res_raw_47458714'!$D$14="","—",IF(ABS(D15-'res_raw_47458714'!$D$14)<=1,"✓ OK","❌ "&TEXT(D15-'res_raw_47458714'!$D$14,"+#,##0;-#,##0")&" t.kr.")) | F65: Verificerer at sumberegnet resultat før skat matcher det rapporterede.

Sheet Noter_info
A1: LEGO System A/S (CVR 47458714) — Ukendte XBRL-felter — disse er noter og ikke en del af hoved-regnskabet
A2: Kategori | B2: Dansk navn | C2: XBRL feltnavn | D2: 2021 t.kr. | E2: 2022 t.kr. | F2: 2023 t.kr. | G2: 2024 t.kr. | H2: 2025 t.kr. | I2: Forklaring
A3: Øvrige (ukendt) | B3: fsa:LongtermDeferredIncome | C3: fsa:LongtermDeferredIncome | I3: Ingen forklaring tilgængelig.
